Workbook

Sheet 总表
A1: 2024年08月份LOS毛利表（海运）-68
A2: JOB | B2: 集装编号 | C2: 利润
A4: JOB080389 | B4: COLL004124 | C4: =SUM('JOB080389'!AF10) -> 36938.519
A9: JOB080353 | B9: COLL004085 | C9: =SUM('JOB080353'!AF17) -> 19429.606
A21: JOB080361 | B21: COLL004096 | C21: =SUM('JOB080361'!AF25) -> 19357.961
A42: JOB080362 | B42: COLL004097 | C42: =SUM('JOB080362'!AF9) -> 228.98845
A46: JOB080363 | B46: COLL004098 | C46: =SUM('JOB080363'!AF15) -> 12540.769
A56: JOB080364 | B56: COLL004100 | C56: =SUM('JOB080364'!AF17) -> 11502.074
A68: JOB080373 | B68: COLL004107 | C68: =SUM('JOB080373'!AF21) -> 8082.2163
A84: JOB080374 | B84: COLL004108 | C84: =SUM('JOB080374'!AF15) -> -11.172348
A94: JOB080371 | B94: COLL004105整柜 | C94: =SUM('JOB080371'!AF6) -> 96367.997
A95: JOB080387 | B95: COLL004121 | C95: =SUM('JOB080387'!AF24) -> 15283.59
A114: JOB100326 | B114: COLL004189 | C114: =SUM('JOB100326'!AF30) -> 8491.9024
A139: 合计 | C139: =SUM(C3:C138) -> 228212.45

Sheet 总表 (2)
A1: 2024年08月份LOS毛利表（海运）
A2: JOB | B2: 集装编号 | C2: 运单编号 | D2: 日期 | E2: 业务 | F2: 发货人 | G2: 收货人 | H2: 计费体积 | I2: 计费重量 | J2: 应 收 | Q2: 总应收 | R2: 起 运 港 成 本 | W2: 代垫运费 | X2: 起运港成本 合计 | Y2: 目的港成本 | AE2: 总支出 | AF2: 利润
J3: 应收RMB | K3: LOS Income(NGN)收到(奈拉) | L3: LOS 收到USD | M3: 美元汇率 dollar currency rate | N3: 应收 到付款USD | O3: 汇率 | P3: 人民币 | R3: 代理商 | S3: 运费+出口报关费 | T3: 提货费 | U3: 装卸费 | V3: 包装费 | Y3: 进口报关费 | Z3: 到门配送费 | AA3: 转运费 | AB3: 目的港支出 | AC3: 汇率 | AD3: 人民币 | AE3: 起运港+目的港
A4: JOB080389 | B4: COLL004124 | C4: 240708000003 | D4: 45491 | E4: 罗伟健 | F4: MailMail速运-演员 | G4: zeng hai | H4: 2.2272 | I4: 11222 | K4: 8906452 | M4: =SUM(K4/N4) -> 1620.0015 | N4: 5497.8047 | O4: 7.12 | P4: =SUM(N4*O4) -> 39144.369 | Q4: =SUM(P4:P8) -> 58091.472 | R4: 赛捷 | S4: =SUM(19204/9.8671)*H4 -> 4334.7234 | T4: =SUM(40.68/9.8671)*H4 -> 9.1822821 | V4: 350 | X4: =SUM(S4:W4) -> 4693.9056 | AA4: 100.29 | AB4: =SUM(Y4:AA4) -> 100.29 | AC4: 7.15 | AD4: =SUM(AB4*AC4) -> 717.0735 | AE4: =SUM(X4+AD4) -> 5410.9791 | AF4: =SUM(P4-AE4) -> 33733.39
C5: 240715000049 | D5: 45490 | E5: Sam.Pao | F5: Sam.Pao | G5: Yusky | H5: 0.4043 | I5: 55 | J5: 923.29 | P5: =SUBTOTAL(9,J5) -> 923.29 | S5: =SUM(19204/9.8671)*H5 -> 786.87529 | T5: =SUM(40.68/9.8671)*H5 -> 1.6668448 | X5: =SUM(S5:W5) -> 788.54214 | AB5: =SUM(Y5:AA5) -> 0 | AC5: 7.15 | AD5: =SUM(AB5*AC5) -> 0 | AE5: =SUM(X5+AD5) -> 788.54214 | AF5: =SUM(P5-AE5) -> 134.74786
C6: 240709000025 | D6: 45491 | E6: 黄颖 | F6: ying | G6: Huangpu | H6: 0.1112 | I6: 57 | J6: 556 | P6: =SUBTOTAL(9,J6) -> 556 | S6: =SUM(19204/9.8671)*H6 -> 216.42477 | T6: =SUM(40.68/9.8671)*H6 -> 0.45845446 | X6: =SUM(S6:W6) -> 216.88322 | Z6: 37.06 | AB6: =SUM(Y6:AA6) -> 37.06 | AC6: 7.15 | AD6: =SUM(AB6*AC6) -> 264.979 | AE6: =SUM(X6+AD6) -> 481.86222 | AF6: =SUM(P6-AE6) -> 74.13778
C7: 240713000006 | D7: 45491 | E7: 朱小飞 | F7: Isabel Zhu | G7: Anthonia | H7: 1.7306 | I7: 346 | J7: 5462 | P7: =SUM(J7) -> 5462 | S7: =SUM(19204/9.8671)*H7 -> 3368.2077 | T7: =SUM(40.68/9.8671)*H7 -> 7.1349037 | X7: =SUM(S7:W7) -> 3375.3426 | Z7: 70.8 | AB7: =SUM(Y7:AA7) -> 70.8 | AC7: 7.15 | AD7: =SUM(AB7*AC7) -> 506.22 | AE7: =SUM(X7+AD7) -> 3881.5626 | AF7: =SUM(P7-AE7) -> 1580.4374
C8: 240718000002 | D8: 45491 | E8: 罗伟健 | F8: MailMail速运-演员 | G8: zeng hai | H8: 5.3938 | I8: 1414 | K8: 2909624 | M8: =SUM(K8/N8) -> 1711 | N8: 1700.54 | O8: 7.06 | P8: =SUM(N8*O8) -> 12005.812 | S8: =SUM(19204/9.8671)*H8 -> 10497.769 | T8: =SUM(40.68/9.8671)*H8 -> 22.237515 | V8: 70 | X8: =SUM(S8:W8) -> 10590.006 | AB8: =SUM(Y8:AA8) -> 0 | AC8: 7.15 | AD8: =SUM(AB8*AC8) -> 0 | AE8: =SUM(X8+AD8) -> 10590.006 | AF8: =SUM(P8-AE8) -> 1415.806
A9: JOB080353 | B9: COLL004085 | C9: 240719000024 | D9: 45505 | E9: 吕沛霖 | F9: Paul | G9: Paul | H9: 0.0423 | I9: 12.5 | J9: 356 | P9: =SUBTOTAL(9,J9) -> 356 | Q9: =SUM(P9:P20) -> 156015.34 | R9: 华茂青松=56567 赛捷=1280 | S9: =SUM(57847/67.0927)*H9 -> 36.470855 | U9: =SUM(1400/67.0927)*H9 -> 0.88265937 | X9: =SUM(S9:W9) -> 37.353514 | Y9: =SUM(10235.99/67.0927)*H9 -> 6.4534946 | Z9: 9.09 | AB9: =SUM(Y9:AA9) -> 15.543495 | AC9: 7.08 | AD9: =SUM(AB9*AC9) -> 110.04794 | AE9: =SUM(X9+AD9) -> 147.40146 | AF9: =SUM(P9-AE9) -> 208.59854
C10: 240717000037 | D10: 45498 | E10: 朱小飞 | F10: Isabel Zhu | G10: Mr Michael | H10: 6.1861 | I10: 1004.71 | J10: 14822 | P10: =SUBTOTAL(9,J10) -> 14822 | S10: =SUM(57847/67.0927)*H10 -> 5333.6254 | U10: =SUM(1400/67.0927)*H10 -> 129.08319 | X10: =SUM(S10:W10) -> 5462.7086 | Y10: =SUM(10235.99/67.0927)*H10 -> 943.78163 | AB10: =SUM(Y10:AA10) -> 943.78163 | AC10: 7.08 | AD10: =SUM(AB10*AC10) -> 6681.9739 | AE10: =SUM(X10+AD10) -> 12144.682 | AF10: =SUM(P10-AE10) -> 2677.3175
C11: 240724000023 | D11: 45505 | E11: Sam.Pao | F11: Sam.Pao | G11: Yusky | H11: 0.158 | I11: 156 | J11: 337.92 | P11: =SUBTOTAL(9,J11) -> 337.92 | S11: =SUM(57847/67.0927)*H11 -> 136.22683 | U11: =SUM(1400/67.0927)*H11 -> 3.296931 | X11: =SUM(S11:W11) -> 139.52376 | Y11: =SUM(10235.99/67.0927)*H11 -> 24.105252 | AB11: =SUM(Y11:AA11) -> 24.105252 | AC11: 7.08 | AD11: =SUM(AB11*AC11) -> 170.66518 | AE11: =SUM(X11+AD11) -> 310.18895 | AF11: =SUM(P11-AE11) -> 27.731055
C12: 240718000039 | D12: 45511 | E12: 黄颖 | F12: ying | G12: Idris | H12: 0.5054 | I12: 412 | J12: 2582 | P12: =SUBTOTAL(9,J12) -> 2582 | S12: =SUM(57847/67.0927)*H12 -> 435.75342 | U12: =SUM(1400/67.0927)*H12 -> 10.546006 | X12: =SUM(S12:W12) -> 446.29943 | Y12: =SUM(10235.99/67.0927)*H12 -> 77.106292 | AB12: =SUM(Y12:AA12) -> 77.106292 | AC12: 7.08 | AD12: =SUM(AB12*AC12) -> 545.91255 | AE12: =SUM(X12+AD12) -> 992.21198 | AF12: =SUM(P12-AE12) -> 1589.788
C13: 240726000053 | D13: 45505 | E13: 朱小飞 | F13: Isabel Zhu | G13: Halifa Success | H13: 0.2452 | I13: 41 | J13: 611.38 | P13: =SUBTOTAL(9,J13) -> 611.38 | S13: =SUM(57847/67.0927)*H13 -> 211.41025 | U13: =SUM(1400/67.0927)*H13 -> 5.116503 | X13: =SUM(S13:W13) -> 216.52675 | Y13: =SUM(10235.99/67.0927)*H13 -> 37.40891 | AB13: =SUM(Y13:AA13) -> 37.40891 | AC13: 7.08 | AD13: =SUM(AB13*AC13) -> 264.85508 | AE13: =SUM(X13+AD13) -> 481.38183 | AF13: =SUM(P13-AE13) -> 129.99817
C14: 240727000003 | D14: 45505 | E14: Sam.Pao | F14: Sam.Pao | G14: Nick Wang | H14: 4.7589 | I14: 760 | J14: 17244.43 | P14: =SUBTOTAL(9,J14) -> 17244.43 | S14: =SUM(57847/67.0927)*H14 -> 4103.1005 | U14: =SUM(1400/67.0927)*H14 -> 99.302309 | X14: =SUM(S14:W14) -> 4202.4028 | Y14: =SUM(10235.99/67.0927)*H14 -> 726.04103 | Z14: 678.47 | AB14: =SUM(Y14:AA14) -> 1404.511 | AC14: 7.08 | AD14: =SUM(AB14*AC14) -> 9943.9381 | AE14: =SUM(X14+AD14) -> 14146.341 | AF14: =SUM(P14-AE14) -> 3098.0892
C15: 240729000009 | D15: 45505 | E15: 朱小飞 | F15: Isabel Zhu | G15: Joy | H15: 2.2224 | I15: 3202 | K15: 2787617 | M15: =SUM(K15/N15) -> 1741.2595 | N15: 1600.9199 | O15: 7.12 | P15: =SUM(N15*O15) -> 11398.55 | S15: =SUM(57847/67.0927)*H15 -> 1916.1425 | U15: =SUM(1400/67.0927)*H15 -> 46.374047 | X15: =SUM(S15:W15) -> 1962.5165 | Y15: =SUM(10235.99/67.0927)*H15 -> 339.0602 | AB15: =SUM(Y15:AA15) -> 339.0602 | AC15: 7.08 | AD15: =SUM(AB15*AC15) -> 2400.5462 | AE15: =SUM(X15+AD15) -> 4363.0627 | AF15: =SUM(P15-AE15) -> 7035.487
C16: 240729000055 | D16: 45505 | E16: 陆总 | F16: 喵喵速运-江 | G16: LUZHILONG | H16: 22.022 | I16: 12675 | J16: 54288.61 | P16: =SUBTOTAL(9,J16) -> 54288.61 | S16: =SUM(57847/67.0927)*H16 -> 18987.261 | U16: =SUM(1400/67.0927)*H16 -> 459.5254 | X16: =SUM(S16:W16) -> 19446.787 | Y16: =SUM(10235.99/67.0927)*H16 -> 3359.7839 | AB16: =SUM(Y16:AA16) -> 3359.7839 | AC16: 7.08 | AD16: =SUM(AB16*AC16) -> 23787.27 | AE16: =SUM(X16+AD16) -> 43234.057 | AF16: =SUM(P16-AE16) -> 11054.553
C17: 240730000017 | D17: 45505 | E17: Sam.Pao | F17: Sam.Pao | G17: MaiKaiNian | H17: 0.2622 | I17: 392 | J17: 1290.24 | P17: =SUBTOTAL(9,J17) -> 1290.24 | S17: =SUM(57847/67.0927)*H17 -> 226.06757 | U17: =SUM(1400/67.0927)*H17 -> 5.4712361 | X17: =SUM(S17:W17) -> 231.5388 | Y17: =SUM(10235.99/67.0927)*H17 -> 40.002513 | AB17: =SUM(Y17:AA17) -> 40.002513 | AC17: 7.08 | AD17: =SUM(AB17*AC17) -> 283.21779 | AE17: =SUM(X17+AD17) -> 514.75659 | AF17: =SUM(P17-AE17) -> 775.48341
C18: 240801000003 | D18: 45505 | E18: Sam.Pao | F18: Sam.Pao | G18: Yusky | H18: 2.1 | I18: 352 | J18: 4491.38 | P18: =SUBTOTAL(9,J18) -> 4491.38 | S18: =SUM(57847/67.0927)*H18 -> 1810.6098 | U18: =SUM(1400/67.0927)*H18 -> 43.819968 | X18: =SUM(S18:W18) -> 1854.4298 | Y18: =SUM(10235.99/67.0927)*H18 -> 320.38626 | AB18: =SUM(Y18:AA18) -> 320.38626 | AC18: 7.08 | AD18: =SUM(AB18*AC18) -> 2268.3347 | AE18: =SUM(X18+AD18) -> 4122.7645 | AF18: =SUM(P18-AE18) -> 368.61554
C19: 240801000001 | D19: 45506 | E19: Sam.Pao | F19: Sam.Pao | G19: SKY JET | H19: 28.4144 | I19: 2700 | J19: 48216.84 | P19: =SUBTOTAL(9,J19) -> 48216.84 | S19: =SUM(57847/67.0927)*H19 -> 24498.758 | U19: =SUM(1400/67.0927)*H19 -> 592.91339 | X19: =SUM(S19:W19) -> 25091.671 | Y19: =SUM(10235.99/67.0927)*H19 -> 4335.0396 | AB19: =SUM(Y19:AA19) -> 4335.0396 | AC19: 7.08 | AD19: =SUM(AB19*AC19) -> 30692.081 | AE19: =SUM(X19+AD19) -> 55783.752 | AF19: =SUM(P19-AE19) -> -7566.9117
C20: 240801000004 | D20: 45505 | E20: Sam.Pao | F20: Sam.Pao | G20: Yusky | H20: 0.1758 | I20: 34 | J20: 375.99 | P20: =SUBTOTAL(9,J20) -> 375.99 | S20: =SUM(57847/67.0927)*H20 -> 151.57391 | U20: =SUM(1400/67.0927)*H20 -> 3.6683574 | X20: =SUM(S20:W20) -> 155.24226 | Y20: =SUM(10235.99/67.0927)*H20 -> 26.820907 | AB20: =SUM(Y20:AA20) -> 26.820907 | AC20: 7.08 | AD20: =SUM(AB20*AC20) -> 189.89202 | AE20: =SUM(X20+AD20) -> 345.13428 | AF20: =SUM(P20-AE20) -> 30.855718
A21: JOB080361 | B21: COLL004096 | C21: 240707000004 | D21: 45506 | E21: Sam.Pao | F21: Sam.Pao | G21: ShanShan | H21: 9.3447 | I21: 5042.5 | J21: 28642.1 | P21: =SUBTOTAL(9,J21) -> 28642.1 | Q21: =SUM(P21:P40) -> 165882.73 | R21: 华茂青松=56567 赛捷=2300 | S21: =SUM(58867/68)*H21 -> 8089.6243 | U21: =SUM(2000/68)*H21 -> 274.84412 | X21: =SUM(S21:W21) -> 8364.4685 | Y21: =SUM(10117.99/68)*H21 -> 1390.435 | Z21: 88.5 | AA21: =SUM(91.45/68)*H21 -> 12.567247 | AB21: =SUM(Y21:AA21) -> 1491.5023 | AC21: 7.15 | AD21: =SUM(AB21*AC21) -> 10664.241 | AE21: =SUM(X21+AD21) -> 19028.71 | AF21: =SUM(P21-AE21) -> 9613.3904
C22: 240719000020 | D22: 45506 | E22: Sam.Pao | F22: Sam.Pao | G22: Wendy | H22: 0.645 | I22: 148 | J22: 2922.21 | P22: =SUBTOTAL(9,J22) -> 2922.21 | S22: =SUM(58867/68)*H22 -> 558.37081 | U22: =SUM(2000/68)*H22 -> 18.970588 | X22: =SUM(S22:W22) -> 577.3414 | Y22: =SUM(10117.99/68)*H22 -> 95.972111 | Z22: 160.91 | AA22: =SUM(91.45/68)*H22 -> 0.86743015 | AB22: =SUM(Y22:AA22) -> 257.74954 | AC22: 7.15 | AD22: =SUM(AB22*AC22) -> 1842.9092 | AE22: =SUM(X22+AD22) -> 2420.2506 | AF22: =SUM(P22-AE22) -> 501.95938
C23: 240719000037 | D23: 45506 | E23: 吕沛霖 | F23: 喵喵速运-Layne | G23: Hu Hai Liang | H23: 0.9193 | I23: 430 | K23: 579841.5 | M23: =SUM(K23/N23) -> 1744.5663 | N23: 332.37 | O23: 7.12 | P23: =SUM(N23*O23) -> 2366.4744 | S23: =SUM(58867/68)*H23 -> 795.8299 | U23: =SUM(2000/68)*H23 -> 27.038235 | X23: =SUM(S23:W23) -> 822.86813 | Y23: =SUM(10117.99/68)*H23 -> 136.7863 | AA23: =SUM(91.45/68)*H23 -> 1.2363233 | AB23: =SUM(Y23:AA23) -> 138.02262 | AC23: 7.15 | AD23: =SUM(AB23*AC23) -> 986.86174 | AE23: =SUM(X23+AD23) -> 1809.7299 | AF23: =SUM(P23-AE23) -> 556.74453
C24: 240723000028 | D24: 45506 | E24: 朱小飞 | F24: Isabel Zhu | G24: Musa Garuba | H24: 0.4159 | I24: 53.8 | K24: 286650 | M24: =SUM(K24/N24) -> 1750 | N24: 163.8 | O24: 7.12 | P24: =SUM(N24*O24) -> 1166.256 | S24: =SUM(58867/68)*H24 -> 360.04096 | U24: =SUM(2000/68)*H24 -> 12.232353 | X24: =SUM(S24:W24) -> 372.27331 | Y24: =SUM(10117.99/68)*H24 -> 61.883412 | AA24: =SUM(91.45/68)*H24 -> 0.55932434 | AB24: =SUM(Y24:AA24) -> 62.442737 | AC24: 7.15 | AD24: =SUM(AB24*AC24) -> 446.46557 | AE24: =SUM(X24+AD24) -> 818.73888 | AF24: =SUM(P24-AE24) -> 347.51712
C25: 240717000037 | D25: 45498 | E25: 朱小飞 | F25: Isabel Zhu | G25: Mr Michael | H25: 8.2 | I25: 882 | J25: 19661.07 | P25: =SUBTOTAL(9,J25) -> 19661.07 | S25: =SUM(58867/68)*H25 -> 7098.6676 | U25: =SUM(2000/68)*H25 -> 241.17647 | X25: =SUM(S25:W25) -> 7339.8441 | Y25: =SUM(10117.99/68)*H25 -> 1220.1106 | AA25: =SUM(91.45/68)*H25 -> 11.027794 | AB25: =SUM(Y25:AA25) -> 1231.1384 | AC25: 7.15 | AD25: =SUM(AB25*AC25) -> 8802.6392 | AE25: =SUM(X25+AD25) -> 16142.483 | AF25: =SUM(P25-AE25) -> 3518.5867
C26: 240718000039 | D26: 45511 | E26: 黄颖 | F26: ying | G26: Idris | H26: 2.7869 | I26: 2167 | J26: 14238 | P26: =SUBTOTAL(9,J26) -> 14238 | S26: =SUM(58867/68)*H26 -> 2412.5947 | U26: =SUM(2000/68)*H26 -> 81.967647 | X26: =SUM(S26:W26) -> 2494.5624 | Y26: =SUM(10117.99/68)*H26 -> 414.67392 | AA26: =SUM(91.45/68)*H26 -> 3.7479707 | AB26: =SUM(Y26:AA26) -> 418.42189 | AC26: 7.15 | AD26: =SUM(AB26*AC26) -> 2991.7165 | AE26: =SUM(X26+AD26) -> 5486.2789 | AF26: =SUM(P26-AE26) -> 8751.7211
C27: 240630000010 | D27: 45511 | E27: 吕沛霖 | F27: 喵喵速运-Layne | G27: WEI PING | H27: 1.6128 | I27: 637 | J27: 3432 | P27: =SUM(J27) -> 3432 | S27: =SUM(58867/68)*H27 -> 1396.1867 | U27: =SUM(2000/68)*H27 -> 47.435294 | X27: =SUM(S27:W27) -> 1443.622 | Y27: =SUM(10117.99/68)*H27 -> 239.97492 | AA27: =SUM(91.45/68)*H27 -> 2.1689788 | AB27: =SUM(Y27:AA27) -> 242.14389 | AC27: 7.15 | AD27: =SUM(AB27*AC27) -> 1731.3288 | AE27: =SUM(X27+AD27) -> 3174.9509 | AF27: =SUM(P27-AE27) -> 257.04913
C28: 240726000008 | D28: 45506 | E28: Bella | F28: Bella Chan | G28: zhong zi xin | H28: 0.835 | I28: 1254 | K28: 1830068.5 | M28: =SUM(K28/N28) -> 1711 | N28: 1069.59 | O28: 7.12 | P28: =SUM(N28*O28) -> 7615.4808 | S28: =SUM(58867/68)*H28 -> 722.85213 | U28: =SUM(2000/68)*H28 -> 24.558824 | X28: =SUM(S28:W28) -> 747.41096 | Y28: =SUM(10117.99/68)*H28 -> 124.24297 | Z28: 284.87 | AA28: =SUM(91.45/68)*H28 -> 1.1229522 | AB28: =SUM(Y28:AA28) -> 410.23592 | AC28: 7.15 | AD28: =SUM(AB28*AC28) -> 2933.1868 | AE28: =SUM(X28+AD28) -> 3680.5978 | AF28: =SUM(P28-AE28) -> 3934.883
C29: 240729000013 | D29: 45506 | E29: 朱小飞 | F29: Isabel Zhu | G29: Halifa Success | H29: 0.3557 | I29: 50 | J29: 801.54 | P29: =SUBTOTAL(9,J29) -> 801.54 | S29: =SUM(58867/68)*H29 -> 307.92635 | U29: =SUM(2000/68)*H29 -> 10.461765 | X29: =SUM(S29:W29) -> 318.38812 | Y29: =SUM(10117.99/68)*H29 -> 52.926015 | AA29: =SUM(91.45/68)*H29 -> 0.47836419 | AB29: =SUM(Y29:AA29) -> 53.40438 | AC29: 7.15 | AD29: =SUM(AB29*AC29) -> 381.84131 | AE29: =SUM(X29+AD29) -> 700.22943 | AF29: =SUM(P29-AE29) -> 101.31057
C30: 240724000026 | D30: 45506 | E30: Bella | F30: Bella Chan | G30: zhong zi xin | H30: 3.0722 | I30: 4949 | K30: 1723658 | M30: =SUM(K30/N30) -> 1711.0136 | N30: 1007.39 | O30: 7.12 | P30: =SUM(N30*O30) -> 7172.6168 | S30: =SUM(58867/68)*H30 -> 2659.5764 | U30: =SUM(2000/68)*H30 -> 90.358824 | X30: =SUM(S30:W30) -> 2749.9353 | Y30: =SUM(10117.99/68)*H30 -> 457.12484 | AA30: =SUM(91.45/68)*H30 -> 4.1316572 | AB30: =SUM(Y30:AA30) -> 461.25649 | AC30: 7.15 | AD30: =SUM(AB30*AC30) -> 3297.9839 | AE30: =SUM(X30+AD30) -> 6047.9192 | AF30: =SUM(P30-AE30) -> 1124.6976
C31: 240729000017 | D31: 45506 | E31: Bella | F31: Bella Chan | G31: zhang jian fei | H31: 1.1178 | I31: 1055 | K31: 776250 | M31: =SUM(K31/N31) -> 1725 | N31: 450 | O31: 7.12 | P31: =SUM(N31*O31) -> 3204 | S31: =SUM(58867/68)*H31 -> 967.6696 | U31: =SUM(2000/68)*H31 -> 32.876471 | X31: =SUM(S31:W31) -> 1000.5461 | Y31: =SUM(10117.99/68)*H31 -> 166.3219 | AA31: =SUM(91.45/68)*H31 -> 1.5032766 | AB31: =SUM(Y31:AA31) -> 167.82518 | AC31: 7.15 | AD31: =SUM(AB31*AC31) -> 1199.95 | AE31: =SUM(X31+AD31) -> 2200.4961 | AF31: =SUM(P31-AE31) -> 1003.5039
C32: 240729000020 | D32: 45506 | E32: 黄颖 | F32: ying | G32: zhounengquan | H32: 0.0032 | I32: 2.7 | J32: 235.2 | P32: =SUBTOTAL(9,J32) -> 235.2 | S32: =SUM(58867/68)*H32 -> 2.7702118 | U32: =SUM(2000/68)*H32 -> 0.094117647 | X32: =SUM(S32:W32) -> 2.8643294 | Y32: =SUM(10117.99/68)*H32 -> 0.47614071 | AA32: =SUM(91.45/68)*H32 -> 0.0043035294 | AB32: =SUM(Y32:AA32) -> 0.48044424 | AC32: 7.15 | AD32: =SUM(AB32*AC32) -> 3.4351763 | AE32: =SUM(X32+AD32) -> 6.2995057 | AF32: =SUM(P32-AE32) -> 228.90049
C33: 240730000010 | D33: 45506 | E33: 朱小飞 | F33: Isabel Zhu | G33: Halifa Success | H33: 3.0014 | I33: 502 | J33: 6679.5 | P33: =SUBTOTAL(9,J33) -> 6679.5 | S33: =SUM(58867/68)*H33 -> 2598.2855 | U33: =SUM(2000/68)*H33 -> 88.276471 | X33: =SUM(S33:W33) -> 2686.562 | Y33: =SUM(10117.99/68)*H33 -> 446.59022 | AA33: =SUM(91.45/68)*H33 -> 4.0364416 | AB33: =SUM(Y33:AA33) -> 450.62666 | AC33: 7.15 | AD33: =SUM(AB33*AC33) -> 3221.9807 | AE33: =SUM(X33+AD33) -> 5908.5426 | AF33: =SUM(P33-AE33) -> 770.95738
C34: 240731000038 | D34: 45506 | E34: 陆总 | F34: 喵喵速运-江 | G34: LUZHILONG | H34: 3.6015 | I34: 1074 | J34: 8038.58 | P34: =SUBTOTAL(9,J34) -> 8038.58 | S34: =SUM(58867/68)*H34 -> 3117.7868 | U34: =SUM(2000/68)*H34 -> 105.92647 | X34: =SUM(S34:W34) -> 3223.7132 | Y34: =SUM(10117.99/68)*H34 -> 535.88149 | AA34: =SUM(91.45/68)*H34 -> 4.8434879 | AB34: =SUM(Y34:AA34) -> 540.72497 | AC34: 7.15 | AD34: =SUM(AB34*AC34) -> 3866.1836 | AE34: =SUM(X34+AD34) -> 7089.8968 | AF34: =SUM(P34-AE34) -> 948.6832
C35: 240801000001 | D35: 45506 | E35: Sam.Pao | F35: Sam.Pao | G35: SKY JET | H35: 32.88 | I35: 4188 | J35: 51584.98 | P35: =SUBTOTAL(9,J35) -> 51584.98 | S35: =SUM(58867/68)*H35 -> 28463.926 | U35: =SUM(2000/68)*H35 -> 967.05882 | X35: =SUM(S35:W35) -> 29430.985 | Y35: =SUM(10117.99/68)*H35 -> 4892.3458 | AA35: =SUM(91.45/68)*H35 -> 44.218765 | AB35: =SUM(Y35:AA35) -> 4936.5645 | AC35: 7.15 | AD35: =SUM(AB35*AC35) -> 35296.436 | AE35: =SUM(X35+AD35) -> 64727.421 | AF35: =SUM(P35-AE35) -> -13142.441
C36: 240728000003 | D36: 45506 | E36: Sam.Pao | F36: Sam.Pao | G36: Nick Wang | H36: 0.2595 | I36: 100 | J36: 699 | P36: =SUBTOTAL(9,J36) -> 699 | S36: =SUM(58867/68)*H36 -> 224.64686 | U36: =SUM(2000/68)*H36 -> 7.6323529 | X36: =SUM(S36:W36) -> 232.27921 | Y36: =SUM(10117.99/68)*H36 -> 38.612035 | AA36: =SUM(91.45/68)*H36 -> 0.34898934 | AB36: =SUM(Y36:AA36) -> 38.961025 | AC36: 7.15 | AD36: =SUM(AB36*AC36) -> 278.57133 | AE36: =SUM(X36+AD36) -> 510.85054 | AF36: =SUM(P36-AE36) -> 188.14946
C37: 240801000022 | D37: 45506 | E37: Bella | F37: Bella Chan | G37: new hope 边鹏飞 | H37: 1.8732 | I37: 1420 | K37: 1129654.4 | M37: =SUM(K37/N37) -> 1739 | N37: 649.6 | O37: 7.06 | P37: =SUM(N37*O37) -> 4586.176 | S37: =SUM(58867/68)*H37 -> 1621.6127 | U37: =SUM(2000/68)*H37 -> 55.094118 | X37: =SUM(S37:W37) -> 1676.7068 | Y37: =SUM(10117.99/68)*H37 -> 278.72087 | AA37: =SUM(91.45/68)*H37 -> 2.5191785 | AB37: =SUM(Y37:AA37) -> 281.24004 | AC37: 7.15 | AD37: =SUM(AB37*AC37) -> 2010.8663 | AE37: =SUM(X37+AD37) -> 3687.5731 | AF37: =SUM(P37-AE37) -> 898.60285
C38: 240802000022 | D38: 45506 | E38: Sam.Pao | F38: Sam.Pao | G38: ShanShan | H38: 0.02 | I38: 5.5 | J38: 61.48 | P38: =SUBTOTAL(9,J38) -> 61.48 | S38: =SUM(58867/68)*H38 -> 17.313824 | U38: =SUM(2000/68)*H38 -> 0.58823529 | X38: =SUM(S38:W38) -> 17.902059 | Y38: =SUM(10117.99/68)*H38 -> 2.9758794 | AA38: =SUM(91.45/68)*H38 -> 0.026897059 | AB38: =SUM(Y38:AA38) -> 3.0027765 | AC38: 7.15 | AD38: =SUM(AB38*AC38) -> 21.469852 | AE38: =SUM(X38+AD38) -> 39.371911 | AF38: =SUM(P38-AE38) -> 22.108089
C39: 240802000026 | D39: 45506 | E39: 陆总 | F39: 喵喵速运-江 | G39: LUZHILONG | H39: 0.0391 | I39: 42.5 | J39: 98.57 | P39: =SUBTOTAL(9,J39) -> 98.57 | S39: =SUM(58867/68)*H39 -> 33.848525 | U39: =SUM(2000/68)*H39 -> 1.15 | X39: =SUM(S39:W39) -> 34.998525 | Y39: =SUM(10117.99/68)*H39 -> 5.8178443 | AA39: =SUM(91.45/68)*H39 -> 0.05258375 | AB39: =SUM(Y39:AA39) -> 5.870428 | AC39: 7.15 | AD39: =SUM(AB39*AC39) -> 41.97356 | AE39: =SUM(X39+AD39) -> 76.972085 | AF39: =SUM(P39-AE39) -> 21.597915
C40: 240802000029 | D40: 45506 | E40: Sam.Pao | F40: Sam.Pao | G40: Yusky | H40: 1.5074 | I40: 207 | J40: 2677.5 | P40: =SUBTOTAL(9,J40) -> 2677.5 | S40: =SUM(58867/68)*H40 -> 1304.9429 | U40: =SUM(2000/68)*H40 -> 44.335294 | X40: =SUM(S40:W40) -> 1349.2782 | Y40: =SUM(10117.99/68)*H40 -> 224.29203 | AA40: =SUM(91.45/68)*H40 -> 2.0272313 | AB40: =SUM(Y40:AA40) -> 226.31926 | AC40: 7.15 | AD40: =SUM(AB40*AC40) -> 1618.1827 | AE40: =SUM(X40+AD40) -> 2967.4609 | AF40: =SUM(P40-AE40) -> -289.9609
A41: JOB080362 | B41: COLL004097 | C41: 240804000005 | D41: 45511 | E41: 黄颖 | F41: ying | G41: Sunday Adelena | H41: 34.5199 | I41: 9224 | J41: 77059.62 | P41: =SUBTOTAL(9,J41) -> 77059.62 | Q41: =SUM(P41:P44) -> 141684.32 | R41: 赛捷=56732.25 赛捷=800 | S41: =SUM(57532.25/68)*H41 -> 29205.993 | U41: =SUM(1450/68)*H41 -> 736.0861 | X41: =SUM(S41:W41) -> 29942.079 | Y41: =SUM(10529/68)*H41 -> 5345.0004 | AA41: =SUM(206.48/68)*H41 -> 104.81866 | AB41: =SUM(Y41:AA41) -> 5449.8191 | AC41: 7.09 | AD41: =SUM(AB41*AC41) -> 38639.217 | AE41: =SUM(X41+AD41) -> 68581.296 | AF41: =SUM(P41-AE41) -> 8478.3239
C42: 240630000010 | D42: 45511 | E42: 吕沛霖 | F42: 喵喵速运-Layne | G42: WEI PING | H42: 1.5552 | I42: 912 | J42: 3309 | P42: =SUM(J42) -> 3309 | S42: =SUM(57532.25/68)*H42 -> 1315.7964 | U42: =SUM(1450/68)*H42 -> 33.162353 | X42: =SUM(S42:W42) -> 1348.9588 | Y42: =SUM(10529/68)*H42 -> 240.80442 | AA42: =SUM(206.48/68)*H42 -> 4.7223191 | AB42: =SUM(Y42:AA42) -> 245.52674 | AC42: 7.09 | AD42: =SUM(AB42*AC42) -> 1740.7846 | AE42: =SUM(X42+AD42) -> 3089.7434 | AF42: =SUM(P42-AE42) -> 219.25664
C43: 240806000035 | D43: 45511 | E43: Sam.Pao | F43: Sam.Pao | G43: SKY JET | H43: 34.38 | I43: 4304 | J43: 59321.31 | P43: =SUBTOTAL(9,J43) -> 59321.31 | S43: =SUM(57532.25/68)*H43 -> 29087.629 | U43: =SUM(1450/68)*H43 -> 733.10294 | X43: =SUM(S43:W43) -> 29820.732 | Y43: =SUM(10529/68)*H43 -> 5323.3385 | AA43: =SUM(206.48/68)*H43 -> 104.39386 | AB43: =SUM(Y43:AA43) -> 5427.7324 | AC43: 7.09 | AD43: =SUM(AB43*AC43) -> 38482.623 | AE43: =SUM(X43+AD43) -> 68303.354 | AF43: =SUM(P43-AE43) -> -8982.0443
C44: 240805000030 | D44: 45511 | E44: 朱小飞 | F44: Isabel Zhu | G44: Abdul Aziz | H44: 0.4717 | I44: 63 | J44: 1994.39 | P44: =SUBTOTAL(9,J44) -> 1994.39 | S44: =SUM(57532.25/68)*H44 -> 399.08768 | U44: =SUM(1450/68)*H44 -> 10.058309 | X44: =SUM(S44:W44) -> 409.14599 | Y44: =SUM(10529/68)*H44 -> 73.037196 | Z44: 76.7 | AA44: =SUM(206.48/68)*H44 -> 1.4323032 | AB44: =SUM(Y44:AA44) -> 151.1695 | AC44: 7.09 | AD44: =SUM(AB44*AC44) -> 1071.7917 | AE44: =SUM(X44+AD44) -> 1480.9377 | AF44: =SUM(P44-AE44) -> 513.45226
A45: JOB080363 | B45: COLL004098 | C45: 240718000039 | D45: 45511 | E45: 黄颖 | F45: ying | G45: Idris | H45: 9.29 | I45: 13260 | J45: 47474 | P45: =SUBTOTAL(9,J45) -> 47474 | Q45: =SUM(P45:P54) -> 179665.7 | R45: 赛捷=56837.25 赛捷=2300 | S45: =SUM(59137.25/68)*H45 -> 8079.1919 | U45: =SUM(1450/68)*H45 -> 198.09559 | V45: 960 | X45: =SUM(S45:W45) -> 9237.2875 | Y45: =SUM(10529/68)*H45 -> 1438.4472 | Z45: 1823.01 | AA45: =SUM(259.58/68)*H45 -> 35.463209 | AB45: =SUM(Y45:AA45) -> 3296.9204 | AC45: 7.09 | AD45: =SUM(AB45*AC45) -> 23375.166 | AE45: =SUM(X45+AD45) -> 32612.453 | AF45: =SUM(P45-AE45) -> 14861.547
C46: 240724000012 | D46: 45511 | E46: Bella | F46: Bella Chan | G46: zhang yong chong | H46: 5.7046 | I46: 942 | J46: 14778 | P46: =SUBTOTAL(9,J46) -> 14778 | S46: =SUM(59137.25/68)*H46 -> 4961.0935 | U46: =SUM(1450/68)*H46 -> 121.64221 | V46: 1400 | X46: =SUM(S46:W46) -> 6482.7357 | Y46: =SUM(10529/68)*H46 -> 883.2902 | AA46: =SUM(259.58/68)*H46 -> 21.776472 | AB46: =SUM(Y46:AA46) -> 905.06667 | AC46: 7.09 | AD46: =SUM(AB46*AC46) -> 6416.9227 | AE46: =SUM(X46+AD46) -> 12899.658 | AF46: =SUM(P46-AE46) -> 1878.3416
C47: 240730000015 | D47: 45511 | E47: 黄颖 | F47: ying | G47: Huangpu | H47: 0.159 | I47: 26.5 | J47: 376.32 | P47: =SUBTOTAL(9,J47) -> 376.32 | S47: =SUM(59137.25/68)*H47 -> 138.27681 | U47: =SUM(1450/68)*H47 -> 3.3904412 | X47: =SUM(S47:W47) -> 141.66725 | Y47: =SUM(10529/68)*H47 -> 24.619279 | AA47: =SUM(259.58/68)*H47 -> 0.60695912 | AB47: =SUM(Y47:AA47) -> 25.226239 | AC47: 7.09 | AD47: =SUM(AB47*AC47) -> 178.85403 | AE47: =SUM(X47+AD47) -> 320.52128 | AF47: =SUM(P47-AE47) -> 55.798723
C48: 240801000020 | D48: 45512 | E48: 朱小飞 | F48: Isabel Zhu | G48: Mr Michael | H48: 5.1796 | I48: 572 | J48: 12648 | P48: =SUBTOTAL(9,J48) -> 12648 | S48: =SUM(59137.25/68)*H48 -> 4504.5191 | U48: =SUM(1450/68)*H48 -> 110.44735 | X48: =SUM(S48:W48) -> 4614.9665 | Y48: =SUM(10529/68)*H48 -> 802.00012 | AA48: =SUM(259.58/68)*H48 -> 19.772361 | AB48: =SUM(Y48:AA48) -> 821.77248 | AC48: 7.09 | AD48: =SUM(AB48*AC48) -> 5826.3669 | AE48: =SUM(X48+AD48) -> 10441.333 | AF48: =SUM(P48-AE48) -> 2206.6666
C49: 240630000010 | D49: 45534 | E49: 吕沛霖 | F49: 喵喵速运-Layne | G49: WEI PING | H49: 4.6083 | I49: 761.3 | J49: 9806 | P49: =SUM(J49) -> 9806 | S49: =SUM(59137.25/68)*H49 -> 4007.6793 | U49: =SUM(1450/68)*H49 -> 98.265221 | X49: =SUM(S49:W49) -> 4105.9445 | Y49: =SUM(10529/68)*H49 -> 713.54104 | AA49: =SUM(259.58/68)*H49 -> 17.591508 | AB49: =SUM(Y49:AA49) -> 731.13255 | AC49: 7.09 | AD49: =SUM(AB49*AC49) -> 5183.7298 | AE49: =SUM(X49+AD49) -> 9289.6742 | AF49: =SUM(P49-AE49) -> 516.32577
C50: 240728000003 | D50: 45506 | E50: Sam.Pao | F50: Sam.Pao | G50: Nick Wang | H50: 0.29 | I50: 135 | J50: 782 | P50: =SUBTOTAL(9,J50) -> 782 | S50: =SUM(59137.25/68)*H50 -> 252.20298 | U50: =SUM(1450/68)*H50 -> 6.1838235 | X50: =SUM(S50:W50) -> 258.3868 | Y50: =SUM(10529/68)*H50 -> 44.903088 | AA50: =SUM(259.58/68)*H50 -> 1.1070324 | AB50: =SUM(Y50:AA50) -> 46.010121 | AC50: 7.09 | AD50: =SUM(AB50*AC50) -> 326.21175 | AE50: =SUM(X50+AD50) -> 584.59856 | AF50: =SUM(P50-AE50) -> 197.40144
C51: 240730000035 | D51: 45511 | E51: 吕沛霖 | F51: 喵喵速运-Layne | G51: MR MANBO | H51: 1.0597 | I51: 336 | J51: 3645.46 | P51: =SUBTOTAL(9,J51) -> 3645.46 | S51: =SUM(59137.25/68)*H51 -> 921.58447 | U51: =SUM(1450/68)*H51 -> 22.596544 | X51: =SUM(S51:W51) -> 944.18101 | Y51: =SUM(10529/68)*H51 -> 164.08208 | Z51: 50.15 | AA51: =SUM(259.58/68)*H51 -> 4.0452489 | AB51: =SUM(Y51:AA51) -> 218.27733 | AC51: 7.09 | AD51: =SUM(AB51*AC51) -> 1547.5862 | AE51: =SUM(X51+AD51) -> 2491.7673 | AF51: =SUM(P51-AE51) -> 1153.6927
C52: 240802000009 | D52: 45511 | E52: Bella | F52: Bella Chan | G52: zhang long ting | H52: 0.1283 | I52: 12.76 | J52: 327.6 | P52: =SUBTOTAL(9,J52) -> 327.6 | S52: =SUM(59137.25/68)*H52 -> 111.57808 | U52: =SUM(1450/68)*H52 -> 2.7358088 | X52: =SUM(S52:W52) -> 114.31388 | Y52: =SUM(10529/68)*H52 -> 19.865746 | AA52: =SUM(259.58/68)*H52 -> 0.48976638 | AB52: =SUM(Y52:AA52) -> 20.355512 | AC52: 7.09 | AD52: =SUM(AB52*AC52) -> 144.32058 | AE52: =SUM(X52+AD52) -> 258.63446 | AF52: =SUM(P52-AE52) -> 68.965535
C53: 240804000004 | D53: 45511 | E53: 罗伟健 | F53: MailMail速运-演员 | G53: zeng hai | H53: 10.2324 | I53: 1319 | K53: 5637625 | M53: =SUM(K53/N53) -> 1710.9999 | N53: 3294.93 | O53: 7.06 | P53: =SUM(N53*O53) -> 23262.206 | S53: =SUM(59137.25/68)*H53 -> 8898.7647 | U53: =SUM(1450/68)*H53 -> 218.19088 | V53: 150 | X53: =SUM(S53:W53) -> 9266.9555 | Y53: =SUM(10529/68)*H53 -> 1584.3668 | AA53: =SUM(259.58/68)*H53 -> 39.060682 | AB53: =SUM(Y53:AA53) -> 1623.4274 | AC53: 7.09 | AD53: =SUM(AB53*AC53) -> 11510.101 | AE53: =SUM(X53+AD53) -> 20777.056 | AF53: =SUM(P53-AE53) -> 2485.1497
C54: 240806000035 | D54: 45511 | E54: Sam.Pao | F54: Sam.Pao | G54: SKY JET | H54: 38.42 | I54: 4700 | J54: 66566.11 | P54: =SUBTOTAL(9,J54) -> 66566.11 | S54: =SUM(59137.25/68)*H54 -> 33412.546 | U54: =SUM(1450/68)*H54 -> 819.25 | X54: =SUM(S54:W54) -> 34231.796 | Y54: =SUM(10529/68)*H54 -> 5948.885 | AA54: =SUM(259.58/68)*H54 -> 146.6627 | AB54: =SUM(Y54:AA54) -> 6095.5477 | AC54: 7.09 | AD54: =SUM(AB54*AC54) -> 43217.433 | AE54: =SUM(X54+AD54) -> 77449.229 | AF54: =SUM(P54-AE54) -> -10883.119
A55: JOB080364 | B55: COLL004100 | C55: 240801000020 | D55: 45512 | E55: 朱小飞 | F55: Isabel Zhu | G55: Mr Michael | H55: 5.7204 | I55: 603 | J55: 13956 | P55: =SUBTOTAL(9,J55) -> 13956 | Q55: =SUM(P55:P66) -> 154255.39 | R55: 赛捷=57732.25 赛捷=800 | S55: =SUM(58532.25/68)*H55 -> 4923.9395 | T55: =SUM(54.99/68)*H55 -> 4.6259529 | U55: =SUM(1000/68)*H55 -> 84.123529 | X55: =SUM(S55:W55) -> 5012.6889 | Y55: =SUM(10435/68)*H55 -> 877.82903 | AB55: =SUM(Y55:AA55) -> 877.82903 | AC55: 7.12 | AD55: =SUM(AB55*AC55) -> 6250.1427 | AE55: =SUM(X55+AD55) -> 11262.832 | AF55: =SUM(P55-AE55) -> 2693.1684
C56: 240802000002 | D56: 45512 | E56: 黄颖 | F56: ying | G56: huangzhaoyong | H56: 1.848 | I56: 1035 | J56: 4482.5 | P56: =SUBTOTAL(9,J56) -> 4482.5 | S56: =SUM(58532.25/68)*H56 -> 1590.7 | T56: =SUM(54.99/68)*H56 -> 1.4944341 | U56: =SUM(1000/68)*H56 -> 27.176471 | X56: =SUM(S56:W56) -> 1619.3709 | Y56: =SUM(10435/68)*H56 -> 283.58647 | AB56: =SUM(Y56:AA56) -> 283.58647 | AC56: 7.12 | AD56: =SUM(AB56*AC56) -> 2019.1357 | AE56: =SUM(X56+AD56) -> 3638.5065 | AF56: =SUM(P56-AE56) -> 843.99345
C57: 240803000005 | D57: 45512 | E57: Sam.Pao | F57: Sam.Pao | G57: Cherry | H57: 2.6248 | I57: 630 | J57: 6236.5 | P57: =SUBTOTAL(9,J57) -> 6236.5 | S57: =SUM(58532.25/68)*H57 -> 2259.3448 | T57: =SUM(54.99/68)*H57 -> 2.122614 | U57: =SUM(1000/68)*H57 -> 38.6 | X57: =SUM(S57:W57) -> 2300.0675 | Y57: =SUM(10435/68)*H57 -> 402.791 | AB57: =SUM(Y57:AA57) -> 402.791 | AC57: 7.12 | AD57: =SUM(AB57*AC57) -> 2867.8719 | AE57: =SUM(X57+AD57) -> 5167.9394 | AF57: =SUM(P57-AE57) -> 1068.5606
C58: 240803000017 | D58: 45512 | E58: 黄颖 | F58: ying | G58: Sunday Adelena | H58: 17.17 | I58: 12298 | J58: 38477.75 | P58: =SUBTOTAL(9,J58) -> 38477.75 | S58: =SUM(58532.25/68)*H58 -> 14779.393 | T58: =SUM(54.99/68)*H58 -> 13.884975 | U58: =SUM(1000/68)*H58 -> 252.5 | X58: =SUM(S58:W58) -> 15045.778 | Y58: =SUM(10435/68)*H58 -> 2634.8375 | AB58: =SUM(Y58:AA58) -> 2634.8375 | AC58: 7.12 | AD58: =SUM(AB58*AC58) -> 18760.043 | AE58: =SUM(X58+AD58) -> 33805.821 | AF58: =SUM(P58-AE58) -> 4671.9289
C59: 240807000012 | D59: 45512 | E59: Sam.Pao | F59: Sam.Pao | G59: Yusky | H59: 3.79 | I59: 780 | J59: 7638.75 | P59: =SUBTOTAL(9,J59) -> 7638.75 | S59: =SUM(58532.25/68)*H59 -> 3262.3122 | T59: =SUM(54.99/68)*H59 -> 3.0648838 | U59: =SUM(1000/68)*H59 -> 55.735294 | X59: =SUM(S59:W59) -> 3321.1123 | Y59: =SUM(10435/68)*H59 -> 581.59779 | AB59: =SUM(Y59:AA59) -> 581.59779 | AC59: 7.12 | AD59: =SUM(AB59*AC59) -> 4140.9763 | AE59: =SUM(X59+AD59) -> 7462.0886 | AF59: =SUM(P59-AE59) -> 176.66136
C60: 240808000010 | D60: 45512 | E60: Sam.Pao | F60: Sam.Pao | G60: SKY JET | H60: 9.8 | I60: 1059 | J60: 15645.79 | P60: =SUBTOTAL(9,J60) -> 15645.79 | S60: =SUM(58532.25/68)*H60 -> 8435.5301 | T60: =SUM(54.99/68)*H60 -> 7.9250294 | U60: =SUM(1000/68)*H60 -> 144.11765 | X60: =SUM(S60:W60) -> 8587.5728 | Y60: =SUM(10435/68)*H60 -> 1503.8676 | AB60: =SUM(Y60:AA60) -> 1503.8676 | AC60: 7.12 | AD60: =SUM(AB60*AC60) -> 10707.538 | AE60: =SUM(X60+AD60) -> 19295.11 | AF60: =SUM(P60-AE60) -> -3649.3205
C61: 240728000003 | D61: 45506 | E61: Sam.Pao | F61: Sam.Pao | G61: Nick Wang | H61: 0.632 | I61: 166 | J61: 1705 | P61: =SUBTOTAL(9,J61) -> 1705 | S61: =SUM(58532.25/68)*H61 -> 544.00562 | T61: =SUM(54.99/68)*H61 -> 0.51108353 | U61: =SUM(1000/68)*H61 -> 9.2941176 | X61: =SUM(S61:W61) -> 553.81082 | Y61: =SUM(10435/68)*H61 -> 96.984118 | AB61: =SUM(Y61:AA61) -> 96.984118 | AC61: 7.12 | AD61: =SUM(AB61*AC61) -> 690.52692 | AE61: =SUM(X61+AD61) -> 1244.3377 | AF61: =SUM(P61-AE61) -> 460.66226
C62: 240613000018 | D62: 45506 | E62: Sam.Pao | F62: Sam.Pao | G62: ChenGaoHong | H62: 1.6564 | I62: 313 | J62: 3117 | P62: =SUBTOTAL(9,J62) -> 3117 | S62: =SUM(58532.25/68)*H62 -> 1425.7767 | T62: =SUM(54.99/68)*H62 -> 1.3394917 | U62: =SUM(1000/68)*H62 -> 24.358824 | X62: =SUM(S62:W62) -> 1451.4751 | Y62: =SUM(10435/68)*H62 -> 254.18432 | AB62: =SUM(Y62:AA62) -> 254.18432 | AC62: 7.12 | AD62: =SUM(AB62*AC62) -> 1809.7924 | AE62: =SUM(X62+AD62) -> 3261.2674 | AF62: =SUM(P62-AE62) -> -144.26745
C63: 240808000011 | D63: 45534 | E63: Sam.Pao | F63: Sam.Pao | G63: Yusky | H63: 0.6332 | I63: 114 | J63: 1276.22 | P63: =SUBTOTAL(9,J63) -> 1276.22 | S63: =SUM(58532.25/68)*H63 -> 545.03854 | T63: =SUM(54.99/68)*H63 -> 0.51205394 | U63: =SUM(1000/68)*H63 -> 9.3117647 | X63: =SUM(S63:W63) -> 554.86236 | Y63: =SUM(10435/68)*H63 -> 97.168265 | AB63: =SUM(Y63:AA63) -> 97.168265 | AC63: 7.12 | AD63: =SUM(AB63*AC63) -> 691.83804 | AE63: =SUM(X63+AD63) -> 1246.7004 | AF63: =SUM(P63-AE63) -> 29.519597
C64: 240808000012 | D64: 45512 | E64: 吕沛霖 | F64: 喵喵速运-Layne | G64: YA | H64: 0.2465 | I64: 35.5 | J64: 821 | P64: =SUM(J64) -> 821 | S64: =SUM(58532.25/68)*H64 -> 212.17941 | T64: =SUM(54.99/68)*H64 -> 0.19933875 | U64: =SUM(1000/68)*H64 -> 3.625 | X64: =SUM(S64:W64) -> 216.00375 | Y64: =SUM(10435/68)*H64 -> 37.826875 | AA64: 22.18 | AB64: =SUM(Y64:AA64) -> 60.006875 | AC64: 7.12 | AD64: =SUM(AB64*AC64) -> 427.24895 | AE64: =SUM(X64+AD64) -> 643.2527 | AF64: =SUM(P64-AE64) -> 177.74731
C65: 240630000010 | D65: 45534 | E65: 吕沛霖 | F65: 喵喵速运-Layne | G65: WEI PING | H65: 20.8295 | I65: 1472 | J65: 44333.83 | P65: =SUM(J65) -> 44333.83 | S65: =SUM(58532.25/68)*H65 -> 17929.375 | T65: =SUM(54.99/68)*H65 -> 16.844327 | U65: =SUM(1000/68)*H65 -> 306.31618 | X65: =SUM(S65:W65) -> 18252.536 | Y65: =SUM(10435/68)*H65 -> 3196.4093 | AB65: =SUM(Y65:AA65) -> 3196.4093 | AC65: 7.12 | AD65: =SUM(AB65*AC65) -> 22758.434 | AE65: =SUM(X65+AD65) -> 41010.97 | AF65: =SUM(P65-AE65) -> 3322.8603
C66: 240808000019 | D66: 45512 | E66: 陆总 | F66: Sam.Pao | G66: LuZhiLong | H66: 7.4735 | I66: 1000 | J66: 16565.05 | P66: =SUBTOTAL(9,J66) -> 16565.05 | S66: =SUM(58532.25/68)*H66 -> 6432.9525 | T66: =SUM(54.99/68)*H66 -> 6.0436436 | U66: =SUM(1000/68)*H66 -> 109.90441 | X66: =SUM(S66:W66) -> 6548.9006 | Y66: =SUM(10435/68)*H66 -> 1146.8525 | AB66: =SUM(Y66:AA66) -> 1146.8525 | AC66: 7.12 | AD66: =SUM(AB66*AC66) -> 8165.5901 | AE66: =SUM(X66+AD66) -> 14714.491 | AF66: =SUM(P66-AE66) -> 1850.5594
A67: JOB080373 | B67: COLL004107 | C67: 240630000010 | D67: 45534 | E67: 吕沛霖 | F67: 喵喵速运-Layne | G67: WEI PING | H67: 4.5207 | I67: 744 | J67: 9620 | P67: =SUM(J67) -> 9620 | Q67: =SUM(P67:P82) -> 160773.2 | R67: 赛捷=56265.25 赛捷=1280 | S67: =SUM(57545.25/68)*H67 -> 3825.659 | U67: =SUM(2100/68)*H67 -> 139.60985 | V67: 900 | X67: =SUM(S67:W67) -> 4865.2688 | Y67: =SUM(10417/68)*H67 -> 692.53135 | Z67: 70.8 | AB67: =SUM(Y67:AA67) -> 763.33135 | AC67: 7.07 | AD67: =SUM(AB67*AC67) -> 5396.7527 | AE67: =SUM(X67+AD67) -> 10262.022 | AF67: =SUM(P67-AE67) -> -642.0215
C68: 240725000027 | D68: 45534 | E68: 黄颖 | F68: ying | G68: Huangpu | H68: 0.0213 | I68: 3.7 | K68: 85293 | M68: =SUM(K68/N68) -> 1730.4321 | N68: 49.29 | O68: 7.12 | P68: =SUM(N68*O68) -> 350.9448 | S68: =SUM(57545.25/68)*H68 -> 18.025203 | U68: =SUM(2100/68)*H68 -> 0.65779412 | X68: =SUM(S68:W68) -> 18.682997 | Y68: =SUM(10417/68)*H68 -> 3.2629721 | Z68: 7.25 | AB68: =SUM(Y68:AA68) -> 10.512972 | AC68: 7.07 | AD68: =SUM(AB68*AC68) -> 74.326712 | AE68: =SUM(X68+AD68) -> 93.00971 | AF68: =SUM(P68-AE68) -> 257.93509
C69: 240806000025 | D69: 45534 | E69: 吕沛霖 | F69: 喵喵速运-Layne | G69: FRANK | H69: 4.665 | I69: 886 | J69: 10755.219 | P69: =SUM(J69) -> 10755.219 | S69: =SUM(57545.25/68)*H69 -> 3947.7734 | U69: =SUM(2100/68)*H69 -> 144.06618 | X69: =SUM(S69:W69) -> 4091.8396 | Y69: =SUM(10417/68)*H69 -> 714.63684 | AB69: =SUM(Y69:AA69) -> 714.63684 | AC69: 7.07 | AD69: =SUM(AB69*AC69) -> 5052.4824 | AE69: =SUM(X69+AD69) -> 9144.322 | AF69: =SUM(P69-AE69) -> 1610.897
C70: 240807000004 | D70: 45534 | E70: 朱小飞 | F70: Isabel Zhu | G70: Inemesit udoh | H70: 2.4662 | I70: 160 | K70: 1842570 | M70: =SUM(K70/N70) -> 1735 | N70: 1062 | O70: 7.12 | P70: =SUM(N70*O70) -> 7561.44 | S70: =SUM(57545.25/68)*H70 -> 2087.0308 | U70: =SUM(2100/68)*H70 -> 76.162059 | X70: =SUM(S70:W70) -> 2163.1929 | Y70: =SUM(10417/68)*H70 -> 377.80008 | AB70: =SUM(Y70:AA70) -> 377.80008 | AC70: 7.07 | AD70: =SUM(AB70*AC70) -> 2671.0466 | AE70: =SUM(X70+AD70) -> 4834.2394 | AF70: =SUM(P70-AE70) -> 2727.2006
C71: 240807000010 | D71: 45534 | E71: 黄颖 | F71: ying | G71: Huangpu | H71: 0.0207 | I71: 4.2 | K71: 59049 | M71: =SUM(K71/N71) -> 1786.1162 | N71: 33.06 | O71: 7.12 | P71: =SUM(N71*O71) -> 235.3872 | S71: =SUM(57545.25/68)*H71 -> 17.517451 | U71: =SUM(2100/68)*H71 -> 0.63926471 | X71: =SUM(S71:W71) -> 18.156716 | Y71: =SUM(10417/68)*H71 -> 3.1710574 | Z71: 7.5 | AB71: =SUM(Y71:AA71) -> 10.671057 | AC71: 7.07 | AD71: =SUM(AB71*AC71) -> 75.444375 | AE71: =SUM(X71+AD71) -> 93.601091 | AF71: =SUM(P71-AE71) -> 141.78611
C72: 240808000002 | D72: 45534 | E72: 吕沛霖 | F72: 喵喵速运-Layne | G72: FRANK | H72: 2.1795 | I72: 785 | K72: 1256000 | M72: =SUM(K72/N72) -> 1751.89 | N72: 716.94 | O72: 7.15 | P72: =SUM(N72*O72) -> 5126.121 | S72: =SUM(57545.25/68)*H72 -> 1844.4099 | U72: =SUM(2100/68)*H72 -> 67.308088 | X72: =SUM(S72:W72) -> 1911.718 | Y72: =SUM(10417/68)*H72 -> 333.88017 | AB72: =SUM(Y72:AA72) -> 333.88017 | AC72: 7.07 | AD72: =SUM(AB72*AC72) -> 2360.5328 | AE72: =SUM(X72+AD72) -> 4272.2508 | AF72: =SUM(P72-AE72) -> 853.87023
C73: 240808000011 | D73: 45534 | E73: Sam.Pao | F73: Sam.Pao | G73: Yusky | H73: 1.8652 | I73: 420 | J73: 3624.06 | P73: =SUBTOTAL(9,J73) -> 3624.06 | S73: =SUM(57545.25/68)*H73 -> 1578.4324 | U73: =SUM(2100/68)*H73 -> 57.601765 | X73: =SUM(S73:W73) -> 1636.0341 | Y73: =SUM(10417/68)*H73 -> 285.73218 | AB73: =SUM(Y73:AA73) -> 285.73218 | AC73: 7.07 | AD73: =SUM(AB73*AC73) -> 2020.1265 | AE73: =SUM(X73+AD73) -> 3656.1607 | AF73: =SUM(P73-AE73) -> -32.100651
C74: 240728000003 | D74: 45506 | E74: Sam.Pao | F74: Sam.Pao | G74: Nick Wang | H74: 0.354 | I74: 131 | J74: 954 | P74: =SUBTOTAL(9,J74) -> 954 | S74: =SUM(57545.25/68)*H74 -> 299.5738 | U74: =SUM(2100/68)*H74 -> 10.932353 | X74: =SUM(S74:W74) -> 310.50615 | Y74: =SUM(10417/68)*H74 -> 54.229676 | AB74: =SUM(Y74:AA74) -> 54.229676 | AC74: 7.07 | AD74: =SUM(AB74*AC74) -> 383.40381 | AE74: =SUM(X74+AD74) -> 693.90997 | AF74: =SUM(P74-AE74) -> 260.09003
C75: 240808000024 | D75: 45534 | E75: 黄颖 | F75: ying | G75: Emma | H75: 2.295 | I75: 107 | L75: 827 | M75: =SUM(K75/N75) -> 0 | N75: 827 | O75: 7.12 | P75: =SUM(N75*O75) -> 5888.24 | S75: =SUM(57545.25/68)*H75 -> 1942.1522 | U75: =SUM(2100/68)*H75 -> 70.875 | X75: =SUM(S75:W75) -> 2013.0272 | Y75: =SUM(10417/68)*H75 -> 351.57375 | Z75: 70.8 | AB75: =SUM(Y75:AA75) -> 422.37375 | AC75: 7.07 | AD75: =SUM(AB75*AC75) -> 2986.1824 | AE75: =SUM(X75+AD75) -> 4999.2096 | AF75: =SUM(P75-AE75) -> 889.0304
C76: 240809000022 | D76: 45534 | E76: Sam.Pao | F76: Sam.Pao | G76: Oladunni Eludire | H76: 8.119 | I76: 5120 | J76: 22858.98 | P76: =SUBTOTAL(9,J76) -> 22858.98 | S76: =SUM(57545.25/68)*H76 -> 6870.7336 | U76: =SUM(2100/68)*H76 -> 250.73382 | W76: =SUM(700+300) -> 1000 | X76: =SUM(S76:W76) -> 8121.4674 | Y76: =SUM(10417/68)*H76 -> 1243.7592 | AB76: =SUM(Y76:AA76) -> 1243.7592 | AC76: 7.07 | AD76: =SUM(AB76*AC76) -> 8793.3773 | AE76: =SUM(X76+AD76) -> 16914.845 | AF76: =SUM(P76-AE76) -> 5944.1353
C77: 240809000034 | D77: 45534 | E77: 朱小飞 | F77: Isabel Zhu | G77: Victor Nnamdi | H77: 0.9292 | I77: 144 | K77: 548260 | M77: =SUM(K77/N77) -> 1735 | N77: 316 | O77: 7.12 | P77: =SUM(N77*O77) -> 2249.92 | S77: =SUM(57545.25/68)*H77 -> 786.33892 | U77: =SUM(2100/68)*H77 -> 28.695882 | X77: =SUM(S77:W77) -> 815.0348 | Y77: =SUM(10417/68)*H77 -> 142.34524 | AB77: =SUM(Y77:AA77) -> 142.34524 | AC77: 7.07 | AD77: =SUM(AB77*AC77) -> 1006.3809 | AE77: =SUM(X77+AD77) -> 1821.4157 | AF77: =SUM(P77-AE77) -> 428.50435
C78: 240813000001 | D78: 45534 | E78: Sam.Pao | F78: Sam.Pao | G78: SKY JET | H78: 33.04 | I78: 4133 | J78: 53646.12 | P78: =SUBTOTAL(9,J78) -> 53646.12 | S78: =SUM(57545.25/68)*H78 -> 27960.221 | U78: =SUM(2100/68)*H78 -> 1020.3529 | X78: =SUM(S78:W78) -> 28980.574 | Y78: =SUM(10417/68)*H78 -> 5061.4365 | AB78: =SUM(Y78:AA78) -> 5061.4365 | AC78: 7.07 | AD78: =SUM(AB78*AC78) -> 35784.356 | AE78: =SUM(X78+AD78) -> 64764.93 | AF78: =SUM(P78-AE78) -> -11118.81
C79: 240809000038 | D79: 45534 | E79: Bella | F79: Bella Chan | G79: FENG | H79: 2.0316 | I79: 173 | J79: 4667 | P79: =SUBTOTAL(9,J79) -> 4667 | S79: =SUM(57545.25/68)*H79 -> 1719.249 | U79: =SUM(2100/68)*H79 -> 62.740588 | X79: =SUM(S79:W79) -> 1781.9896 | Y79: =SUM(10417/68)*H79 -> 311.22319 | AB79: =SUM(Y79:AA79) -> 311.22319 | AC79: 7.07 | AD79: =SUM(AB79*AC79) -> 2200.348 | AE79: =SUM(X79+AD79) -> 3982.3375 | AF79: =SUM(P79-AE79) -> 684.66246
C80: 240810000008 | D80: 45534 | E80: 罗伟健 | F80: MailMail速运-演员 | G80: Mr.Joseph Ezekiel | H80: 7.4021 | I80: 2808 | K80: 4341273 | M80: =SUM(K80/N80) -> 1725 | N80: 2516.68 | O80: 7.12 | P80: =SUM(N80*O80) -> 17918.762 | S80: =SUM(57545.25/68)*H80 -> 6264.0543 | U80: =SUM(2100/68)*H80 -> 228.59426 | X80: =SUM(S80:W80) -> 6492.6486 | Y80: =SUM(10417/68)*H80 -> 1133.9364 | AB80: =SUM(Y80:AA80) -> 1133.9364 | AC80: 7.07 | AD80: =SUM(AB80*AC80) -> 8016.9304 | AE80: =SUM(X80+AD80) -> 14509.579 | AF80: =SUM(P80-AE80) -> 3409.1826
C81: 240813000002 | D81: 45534 | E81: Sam.Pao | F81: Sam.Pao | G81: SKY JET | H81: 1.14 | I81: 155 | J81: 1853.23 | P81: =SUBTOTAL(9,J81) -> 1853.23 | S81: =SUM(57545.25/68)*H81 -> 964.72919 | U81: =SUM(2100/68)*H81 -> 35.205882 | X81: =SUM(S81:W81) -> 999.93507 | Y81: =SUM(10417/68)*H81 -> 174.63794 | AB81: =SUM(Y81:AA81) -> 174.63794 | AC81: 7.07 | AD81: =SUM(AB81*AC81) -> 1234.6902 | AE81: =SUM(X81+AD81) -> 2234.6253 | AF81: =SUM(P81-AE81) -> -381.39532
C82: 240812000043 | D82: 45534 | E82: 陆总 | F82: Sam.Pao | G82: LuZhiLong | H82: 5.313 | I82: 2925 | J82: 13463.78 | P82: =SUBTOTAL(9,J82) -> 13463.78 | S82: =SUM(57545.25/68)*H82 -> 4496.1458 | U82: =SUM(2100/68)*H82 -> 164.07794 | X82: =SUM(S82:W82) -> 4660.2237 | Y82: =SUM(10417/68)*H82 -> 813.90472 | AB82: =SUM(Y82:AA82) -> 813.90472 | AC82: 7.07 | AD82: =SUM(AB82*AC82) -> 5754.3064 | AE82: =SUM(X82+AD82) -> 10414.53 | AF82: =SUM(P82-AE82) -> 3049.2499
A83: JOB080374 | B83: COLL004108 | C83: 240729000025 | D83: 45534 | E83: 黄颖 | F83: ying | G83: leoyang | H83: 0.3136 | I83: 10 | J83: 753 | P83: =SUM(J83) -> 753 | Q83: =SUM(P83:P92) -> 139455.48 | R83: 赛捷=56265.25 赛捷=1000 | S83: =SUM(57265.25/68)*H83 -> 264.09386 | U83: =SUM(1400/68)*H83 -> 6.4564706 | X83: =SUM(S83:W83) -> 270.55033 | Y83: =SUM(10328/68)*H83 -> 47.630306 | AA83: =SUM(277.12/68)*H83 -> 1.2780122 | AB83: =SUM(Y83:AA83) -> 48.908318 | AC83: 7.06 | AD83: =SUM(AB83*AC83) -> 345.29273 | AE83: =SUM(X83+AD83) -> 615.84306 | AF83: =SUM(P83-AE83) -> 137.15694
C84: 240804000005 | D84: 45534 | E84: 黄颖 | F84: ying | G84: Sunday Adelena | H84: 31.7366 | I84: 8596 | J84: 70573.12 | P84: =SUBTOTAL(9,J84) -> 70573.12 | S84: =SUM(57265.25/68)*H84 -> 26726.534 | U84: =SUM(1400/68)*H84 -> 653.40059 | X84: =SUM(S84:W84) -> 27379.935 | Y84: =SUM(10328/68)*H84 -> 4820.2295 | AA84: =SUM(277.12/68)*H84 -> 129.33598 | AB84: =SUM(Y84:AA84) -> 4949.5655 | AC84: 7.06 | AD84: =SUM(AB84*AC84) -> 34943.932 | AE84: =SUM(X84+AD84) -> 62323.867 | AF84: =SUM(P84-AE84) -> 8249.2529
C85: 240812000053 | D85: 45534 | E85: Sam.Pao | F85: Sam.Pao | G85: Yusky | H85: 1.748 | I85: 203 | J85: 3548.44 | P85: =SUBTOTAL(9,J85) -> 3548.44 | S85: =SUM(57265.25/68)*H85 -> 1472.0538 | U85: =SUM(1400/68)*H85 -> 35.988235 | X85: =SUM(S85:W85) -> 1508.042 | Y85: =SUM(10328/68)*H85 -> 265.49035 | AA85: =SUM(277.12/68)*H85 -> 7.1236141 | AB85: =SUM(Y85:AA85) -> 272.61397 | AC85: 7.06 | AD85: =SUM(AB85*AC85) -> 1924.6546 | AE85: =SUM(X85+AD85) -> 3432.6966 | AF85: =SUM(P85-AE85) -> 115.74338
C86: 240811000002 | D86: 45534 | E86: 黄颖 | F86: ying | G86: yanjiafu | H86: 0.293 | I86: 65.5 | K86: 295731 | M86: =SUM(K86/N86) -> 1737.5499 | N86: 170.2 | O86: 7.15 | P86: =SUM(N86*O86) -> 1216.93 | S86: =SUM(57265.25/68)*H86 -> 246.74586 | T86: 355.58 | U86: =SUM(1400/68)*H86 -> 6.0323529 | W86: 54.56 | X86: =SUM(S86:W86) -> 662.91821 | Y86: =SUM(10328/68)*H86 -> 44.501529 | Z86: 27.05 | AA86: =SUM(277.12/68)*H86 -> 1.1940612 | AB86: =SUM(Y86:AA86) -> 72.745591 | AC86: 7.06 | AD86: =SUM(AB86*AC86) -> 513.58387 | AE86: =SUM(X86+AD86) -> 1176.5021 | AF86: =SUM(P86-AE86) -> 40.427921
C87: 240812000054 | D87: 45534 | E87: Sam.Pao | F87: Sam.Pao | G87: Yusky | H87: 0.2239 | I87: 43 | J87: 454.5 | P87: =SUBTOTAL(9,J87) -> 454.5 | S87: =SUM(57265.25/68)*H87 -> 188.55426 | U87: =SUM(1400/68)*H87 -> 4.6097059 | X87: =SUM(S87:W87) -> 193.16396 | Y87: =SUM(10328/68)*H87 -> 34.006459 | AA87: =SUM(277.12/68)*H87 -> 0.91245835 | AB87: =SUM(Y87:AA87) -> 34.918917 | AC87: 7.06 | AD87: =SUM(AB87*AC87) -> 246.52756 | AE87: =SUM(X87+AD87) -> 439.69152 | AF87: =SUM(P87-AE87) -> 14.808482
C88: 240812000055 | D88: 45534 | E88: Sam.Pao | F88: Sam.Pao | G88: Yusky | H88: 0.1922 | I88: 29 | J88: 390.2 | P88: =SUBTOTAL(9,J88) -> 390.2 | S88: =SUM(57265.25/68)*H88 -> 161.85854 | U88: =SUM(1400/68)*H88 -> 3.9570588 | X88: =SUM(S88:W88) -> 165.8156 | Y88: =SUM(10328/68)*H88 -> 29.191788 | AA88: =SUM(277.12/68)*H88 -> 0.78327153 | AB88: =SUM(Y88:AA88) -> 29.97506 | AC88: 7.06 | AD88: =SUM(AB88*AC88) -> 211.62392 | AE88: =SUM(X88+AD88) -> 377.43953 | AF88: =SUM(P88-AE88) -> 12.760474
C89: 240812000056 | D89: 45534 | E89: Sam.Pao | F89: Sam.Pao | G89: Yusky | H89: 0.1689 | I89: 34 | J89: 342.85 | P89: =SUBTOTAL(9,J89) -> 342.85 | S89: =SUM(57265.25/68)*H89 -> 142.23678 | U89: =SUM(1400/68)*H89 -> 3.4773529 | X89: =SUM(S89:W89) -> 145.71413 | Y89: =SUM(10328/68)*H89 -> 25.652929 | AA89: =SUM(277.12/68)*H89 -> 0.68831718 | AB89: =SUM(Y89:AA89) -> 26.341247 | AC89: 7.06 | AD89: =SUM(AB89*AC89) -> 185.9692 | AE89: =SUM(X89+AD89) -> 331.68333 | AF89: =SUM(P89-AE89) -> 11.166671
C90: 240813000001 | D90: 45534 | E90: Sam.Pao | F90: Sam.Pao | G90: SKY JET | H90: 1.98 | I90: 736 | J90: 3388.18 | P90: =SUBTOTAL(9,J90) -> 3388.18 | S90: =SUM(57265.25/68)*H90 -> 1667.4293 | U90: =SUM(1400/68)*H90 -> 40.764706 | X90: =SUM(S90:W90) -> 1708.194 | Y90: =SUM(10328/68)*H90 -> 300.72706 | AA90: =SUM(277.12/68)*H90 -> 8.0690824 | AB90: =SUM(Y90:AA90) -> 308.79614 | AC90: 7.06 | AD90: =SUM(AB90*AC90) -> 2180.1008 | AE90: =SUM(X90+AD90) -> 3888.2948 | AF90: =SUM(P90-AE90) -> -500.1148
C91: 240613000018 | D91: 45506 | E91: Sam.Pao | F91: Sam.Pao | G91: ChenGaoHong | H91: 1.087 | I91: 234 | J91: 2370 | P91: =SUBTOTAL(9,J91) -> 2370 | S91: =SUM(57265.25/68)*H91 -> 915.40186 | U91: =SUM(1400/68)*H91 -> 22.379412 | X91: =SUM(S91:W91) -> 937.78128 | Y91: =SUM(10328/68)*H91 -> 165.09612 | AA91: =SUM(277.12/68)*H91 -> 4.4298447 | AB91: =SUM(Y91:AA91) -> 169.52596 | AC91: 7.06 | AD91: =SUM(AB91*AC91) -> 1196.8533 | AE91: =SUM(X91+AD91) -> 2134.6346 | AF91: =SUM(P91-AE91) -> 235.36543
C92: 240813000002 | D92: 45534 | E92: Sam.Pao | F92: Sam.Pao | G92: SKY JET | H92: 32.97 | I92: 3574 | J92: 56418.26 | P92: =SUBTOTAL(9,J92) -> 56418.26 | S92: =SUM(57265.25/68)*H92 -> 27765.225 | U92: =SUM(1400/68)*H92 -> 678.79412 | X92: =SUM(S92:W92) -> 28444.019 | Y92: =SUM(10328/68)*H92 -> 5007.5612 | AA92: =SUM(277.12/68)*H92 -> 134.36245 | AB92: =SUM(Y92:AA92) -> 5141.9236 | AC92: 7.06 | AD92: =SUM(AB92*AC92) -> 36301.981 | AE92: =SUM(X92+AD92) -> 64746 | AF92: =SUM(P92-AE92) -> -8327.7398
A93: JOB080371 | B93: COLL004105整柜 | C93: 240812000027 | D93: 45498 | E93: Sam.Pao | F93: Sam.Pao | G93: JunYue hotel | H93: 68 | I93: 21890 | J93: 68172 | K93: 21300000 | M93: =SUM(K93/N93) -> 1694.5579 | N93: 12569.65 | O93: 7.15 | P93: =SUM(N93*O93+J93) -> 158045 | Q93: =SUM(P93) -> 158045 | R93: 华茂青松 | S93: 61677 | X93: =SUM(S93:W93) -> 61677 | Y93: 0 | AB93: =SUM(Y93:AA93) -> 0 | AC93: 7.15 | AD93: =SUM(AB93*AC93) -> 0 | AE93: =SUM(X93+AD93) -> 61677 | AF93: =SUM(P93-AE93) -> 96367.997
A94: JOB080387 | B94: COLL004121 | C94: 240807000029 | D94: 45516 | E94: 吕沛霖 | F94: 喵喵速运-Layne | G94: Candice Ding | H94: 0.55 | I94: 148 | J94: 1768.88 | P94: =SUM(J94) -> 1768.88 | Q94: =SUM(P94:P112) -> 161460.15 | R94: 登凯=50475 赛捷=1000 拖车费=1670 杂费=61 过磅费=53 | S94: =SUM(53259/68)*H94 -> 430.77132 | U94: =SUM(1300/68)*H94 -> 10.514706 | X94: =SUM(S94:W94) -> 441.28603 | Y94: =SUM(10737.46/68)*H94 -> 86.847103 | Z94: 47.2 | AB94: =SUM(Y94:AA94) -> 134.0471 | AC94: 7.06 | AD94: =SUM(AB94*AC94) -> 946.37255 | AE94: =SUM(X94+AD94) -> 1387.6586 | AF94: =SUM(P94-AE94) -> 381.22142
C95: 240810000003 | D95: 45516 | E95: 黄颖 | F95: ying | G95: Sunday Adelena | H95: 0.693 | I95: 463 | J95: 1600 | P95: =SUBTOTAL(9,J95) -> 1600 | S95: =SUM(53259/68)*H95 -> 542.77187 | U95: =SUM(1300/68)*H95 -> 13.248529 | X95: =SUM(S95:W95) -> 556.0204 | Y95: =SUM(10737.46/68)*H95 -> 109.42735 | AB95: =SUM(Y95:AA95) -> 109.42735 | AC95: 7.06 | AD95: =SUM(AB95*AC95) -> 772.55709 | AE95: =SUM(X95+AD95) -> 1328.5775 | AF95: =SUM(P95-AE95) -> 271.42251
C96: 240613000018 | D96: 45506 | E96: Sam.Pao | F96: Sam.Pao | G96: ChenGaoHong | H96: 0.044 | I96: 28 | J96: 96 | P96: =SUBTOTAL(9,J96) -> 96 | S96: =SUM(53259/68)*H96 -> 34.461706 | U96: =SUM(1300/68)*H96 -> 0.84117647 | X96: =SUM(S96:W96) -> 35.302882 | Y96: =SUM(10737.46/68)*H96 -> 6.9477682 | AB96: =SUM(Y96:AA96) -> 6.9477682 | AC96: 7.06 | AD96: =SUM(AB96*AC96) -> 49.051244 | AE96: =SUM(X96+AD96) -> 84.354126 | AF96: =SUM(P96-AE96) -> 11.645874
C97: 240811000001 | D97: 45516 | E97: 吕沛霖 | F97: 喵喵速运-Layne | G97: FRANK | H97: 8.3155 | I97: 4780 | K97: 4494672 | M97: =SUM(K97/N97) -> 1773.8649 | N97: 2533.83 | O97: 7.24 | P97: =SUM(N97*O97) -> 18344.929 | S97: =SUM(53259/68)*H97 -> 6512.8708 | U97: =SUM(1300/68)*H97 -> 158.97279 | X97: =SUM(S97:W97) -> 6671.8436 | Y97: =SUM(10737.46/68)*H97 -> 1313.0492 | AB97: =SUM(Y97:AA97) -> 1313.0492 | AC97: 7.06 | AD97: =SUM(AB97*AC97) -> 9270.1277 | AE97: =SUM(X97+AD97) -> 15941.971 | AF97: =SUM(P97-AE97) -> 2402.9579
C98: 240728000003 | D98: 45506 | E98: Sam.Pao | F98: Sam.Pao | G98: Nick Wang | H98: 0.236 | I98: 94 | J98: 636 | P98: =SUBTOTAL(9,J98) -> 636 | S98: =SUM(53259/68)*H98 -> 184.84006 | U98: =SUM(1300/68)*H98 -> 4.5117647 | X98: =SUM(S98:W98) -> 189.35182 | Y98: =SUM(10737.46/68)*H98 -> 37.265302 | AB98: =SUM(Y98:AA98) -> 37.265302 | AC98: 7.06 | AD98: =SUM(AB98*AC98) -> 263.09303 | AE98: =SUM(X98+AD98) -> 452.44486 | AF98: =SUM(P98-AE98) -> 183.55514
C99: 240811000012 | D99: 45516 | E99: Sam.Pao | F99: Sam.Pao | G99: Maxim | H99: 1.4797 | I99: 153.4 | J99: 3842.88 | P99: =SUBTOTAL(9,J99) -> 3842.88 | S99: =SUM(53259/68)*H99 -> 1158.9315 | U99: =SUM(1300/68)*H99 -> 28.288382 | X99: =SUM(S99:W99) -> 1187.2199 | Y99: =SUM(10737.46/68)*H99 -> 233.65029 | Z99: 8.85 | AB99: =SUM(Y99:AA99) -> 242.50029 | AC99: 7.06 | AD99: =SUM(AB99*AC99) -> 1712.052 | AE99: =SUM(X99+AD99) -> 2899.2719 | AF99: =SUM(P99-AE99) -> 943.60808
C100: 240812000069 | D100: 45516 | E100: 黄颖 | F100: ying | G100: zhounengquan | H100: 0.045 | I100: 52.5 | J100: 565.2 | P100: =SUBTOTAL(9,J100) -> 565.2 | S100: =SUM(53259/68)*H100 -> 35.244926 | U100: =SUM(1300/68)*H100 -> 0.86029412 | X100: =SUM(S100:W100) -> 36.105221 | Y100: =SUM(10737.46/68)*H100 -> 7.1056721 | Z100: 50.15 | AB100: =SUM(Y100:AA100) -> 57.255672 | AC100: 7.06 | AD100: =SUM(AB100*AC100) -> 404.22504 | AE100: =SUM(X100+AD100) -> 440.33027 | AF100: =SUM(P100-AE100) -> 124.86973
...

Sheet JOB080389
A1: 2024年08月份LOS毛利表（海运）
A2: PSL表 | B2: 体积cbm | C2: 9.8671
A3: JOB | B3: 集装编号 | C3: 运单编号 | D3: 日期 | E3: 业务 | F3: 发货人 | G3: 收货人 | H3: 计费体积 | I3: 计费重量 | J3: 应 收 | Q3: 总应收 | R3: 起 运 港 成 本 | W3: 代垫运费 | X3: 起运港成本 合计 | Y3: 目的港成本 | AE3: 总支出 | AF3: 利润
J4: 应收RMB | K4: LOS Income(NGN)收到(奈拉) | L4: LOS 收到USD | M4: 美元汇率 dollar currency rate | N4: 应收 到付款USD | O4: 汇率 | P4: 人民币 | R4: 代理商 | S4: 运费+出口报关费 | T4: 提货费 | U4: 装卸费 | V4: 包装费 | Y4: 进口报关费 | Z4: 到门配送费 | AA4: 转运费 | AB4: 目的港支出 | AC4: 汇率 | AD4: 人民币 | AE4: 起运港+目的港
A5: JOB080389 | B5: COLL004124 | C5: 240708000003 | D5: 45491 | E5: 罗伟健 | F5: MailMail速运-演员 | G5: zeng hai | H5: 2.2272 | I5: 11222 | K5: 8906452 | M5: =SUM(K5/N5) -> 1620.0015 | N5: 5497.8047 | O5: 7.12 | P5: =SUM(N5*O5) -> 39144.369 | Q5: =SUM(P5:P9) -> 58091.472 | R5: 赛捷 | S5: =SUM(19204/9.8671)*H5 -> 4334.7234 | T5: =SUM(40.68/9.8671)*H5 -> 9.1822821 | V5: 350 | X5: =SUM(S5:W5) -> 4693.9056 | AA5: 100.29 | AB5: =SUM(Y5:AA5) -> 100.29 | AC5: 7.15 | AD5: =SUM(AB5*AC5) -> 717.0735 | AE5: =SUM(X5+AD5) -> 5410.9791 | AF5: =SUM(P5-AE5) -> 33733.39
C6: 240715000049 | D6: 45490 | E6: Sam.Pao | F6: Sam.Pao | G6: Yusky | H6: 0.4043 | I6: 55 | J6: 923.29 | P6: =SUBTOTAL(9,J6) -> 923.29 | S6: =SUM(19204/9.8671)*H6 -> 786.87529 | T6: =SUM(40.68/9.8671)*H6 -> 1.6668448 | X6: =SUM(S6:W6) -> 788.54214 | AB6: =SUM(Y6:AA6) -> 0 | AC6: 7.15 | AD6: =SUM(AB6*AC6) -> 0 | AE6: =SUM(X6+AD6) -> 788.54214 | AF6: =SUM(P6-AE6) -> 134.74786
C7: 240709000025 | D7: 45491 | E7: 黄颖 | F7: ying | G7: Huangpu | H7: 0.1112 | I7: 57 | J7: 556 | P7: =SUBTOTAL(9,J7) -> 556 | S7: =SUM(19204/9.8671)*H7 -> 216.42477 | T7: =SUM(40.68/9.8671)*H7 -> 0.45845446 | X7: =SUM(S7:W7) -> 216.88322 | Z7: 37.06 | AB7: =SUM(Y7:AA7) -> 37.06 | AC7: 7.15 | AD7: =SUM(AB7*AC7) -> 264.979 | AE7: =SUM(X7+AD7) -> 481.86222 | AF7: =SUM(P7-AE7) -> 74.13778
C8: 240713000006 | D8: 45491 | E8: 朱小飞 | F8: Isabel Zhu | G8: Anthonia | H8: 1.7306 | I8: 346 | J8: 5462 | P8: =SUM(J8) -> 5462 | S8: =SUM(19204/9.8671)*H8 -> 3368.2077 | T8: =SUM(40.68/9.8671)*H8 -> 7.1349037 | X8: =SUM(S8:W8) -> 3375.3426 | Z8: 70.8 | AB8: =SUM(Y8:AA8) -> 70.8 | AC8: 7.15 | AD8: =SUM(AB8*AC8) -> 506.22 | AE8: =SUM(X8+AD8) -> 3881.5626 | AF8: =SUM(P8-AE8) -> 1580.4374
C9: 240718000002 | D9: 45491 | E9: 罗伟健 | F9: MailMail速运-演员 | G9: zeng hai | H9: 5.3938 | I9: 1414 | K9: 2909624 | M9: =SUM(K9/N9) -> 1711 | N9: 1700.54 | O9: 7.06 | P9: =SUM(N9*O9) -> 12005.812 | S9: =SUM(19204/9.8671)*H9 -> 10497.769 | T9: =SUM(40.68/9.8671)*H9 -> 22.237515 | V9: 70 | X9: =SUM(S9:W9) -> 10590.006 | AB9: =SUM(Y9:AA9) -> 0 | AC9: 7.15 | AD9: =SUM(AB9*AC9) -> 0 | AE9: =SUM(X9+AD9) -> 10590.006 | AF9: =SUM(P9-AE9) -> 1415.806
A10: 合计 | J10: =SUM(J4:J4) -> 0 | N10: =SUM(N4:N4) -> 0 | P10: =SUM(P4:P4) -> 0 | Q10: =SUM(Q4:Q4) -> 0 | X10: =SUM(X4:X4) -> 0 | AD10: =SUM(AD4:AD4) -> 0 | AF10: =SUM(AF4:AF9) -> 36938.519

Sheet JOB080353
A1: 2024年08月份LOS毛利表（海运）
A2: PSL表 | B2: 体积cbm | C2: 67.0927
A3: JOB | B3: 集装编号 | C3: 运单编号 | D3: 日期 | E3: 业务 | F3: 发货人 | G3: 收货人 | H3: 计费体积 | I3: 计费重量 | J3: 应 收 | Q3: 总应收 | R3: 起 运 港 成 本 | W3: 代垫运费 | X3: 起运港成本 合计 | Y3: 目的港成本 | AE3: 总支出 | AF3: 利润
J4: 应收RMB | K4: LOS Income(NGN)收到(奈拉) | L4: LOS 收到USD | M4: 美元汇率 dollar currency rate | N4: 应收 到付款USD | O4: 汇率 | P4: 人民币 | R4: 代理商 | S4: 运费+出口报关费 | T4: 提货费 | U4: 装卸费 | V4: 包装费 | Y4: 进口报关费 | Z4: 到门配送费 | AA4: 转运费 | AB4: 目的港支出 | AC4: 汇率 | AD4: 人民币 | AE4: 起运港+目的港
A5: JOB080353 | B5: COLL004085 | C5: 240719000024 | D5: 45505 | E5: 吕沛霖 | F5: Paul | G5: Paul | H5: 0.0423 | I5: 12.5 | J5: 356 | P5: =SUBTOTAL(9,J5) -> 356 | Q5: =SUM(P5:P16) -> 156015.34 | R5: 华茂青松=56567 赛捷=1280 | S5: =SUM(57847/67.0927)*H5 -> 36.470855 | U5: =SUM(1400/67.0927)*H5 -> 0.88265937 | X5: =SUM(S5:W5) -> 37.353514 | Y5: =SUM(10235.99/67.0927)*H5 -> 6.4534946 | Z5: 9.09 | AB5: =SUM(Y5:AA5) -> 15.543495 | AC5: 7.08 | AD5: =SUM(AB5*AC5) -> 110.04794 | AE5: =SUM(X5+AD5) -> 147.40146 | AF5: =SUM(P5-AE5) -> 208.59854
C6: 240717000037 | D6: 45498 | E6: 朱小飞 | F6: Isabel Zhu | G6: Mr Michael | H6: 6.1861 | I6: 1004.71 | J6: 14822 | P6: =SUBTOTAL(9,J6) -> 14822 | S6: =SUM(57847/67.0927)*H6 -> 5333.6254 | U6: =SUM(1400/67.0927)*H6 -> 129.08319 | X6: =SUM(S6:W6) -> 5462.7086 | Y6: =SUM(10235.99/67.0927)*H6 -> 943.78163 | AB6: =SUM(Y6:AA6) -> 943.78163 | AC6: 7.08 | AD6: =SUM(AB6*AC6) -> 6681.9739 | AE6: =SUM(X6+AD6) -> 12144.682 | AF6: =SUM(P6-AE6) -> 2677.3175
C7: 240724000023 | D7: 45505 | E7: Sam.Pao | F7: Sam.Pao | G7: Yusky | H7: 0.158 | I7: 156 | J7: 337.92 | P7: =SUBTOTAL(9,J7) -> 337.92 | S7: =SUM(57847/67.0927)*H7 -> 136.22683 | U7: =SUM(1400/67.0927)*H7 -> 3.296931 | X7: =SUM(S7:W7) -> 139.52376 | Y7: =SUM(10235.99/67.0927)*H7 -> 24.105252 | AB7: =SUM(Y7:AA7) -> 24.105252 | AC7: 7.08 | AD7: =SUM(AB7*AC7) -> 170.66518 | AE7: =SUM(X7+AD7) -> 310.18895 | AF7: =SUM(P7-AE7) -> 27.731055
C8: 240718000039 | D8: 45511 | E8: 黄颖 | F8: ying | G8: Idris | H8: 0.5054 | I8: 412 | J8: 2582 | P8: =SUBTOTAL(9,J8) -> 2582 | S8: =SUM(57847/67.0927)*H8 -> 435.75342 | U8: =SUM(1400/67.0927)*H8 -> 10.546006 | X8: =SUM(S8:W8) -> 446.29943 | Y8: =SUM(10235.99/67.0927)*H8 -> 77.106292 | AB8: =SUM(Y8:AA8) -> 77.106292 | AC8: 7.08 | AD8: =SUM(AB8*AC8) -> 545.91255 | AE8: =SUM(X8+AD8) -> 992.21198 | AF8: =SUM(P8-AE8) -> 1589.788
C9: 240726000053 | D9: 45505 | E9: 朱小飞 | F9: Isabel Zhu | G9: Halifa Success | H9: 0.2452 | I9: 41 | J9: 611.38 | P9: =SUBTOTAL(9,J9) -> 611.38 | S9: =SUM(57847/67.0927)*H9 -> 211.41025 | U9: =SUM(1400/67.0927)*H9 -> 5.116503 | X9: =SUM(S9:W9) -> 216.52675 | Y9: =SUM(10235.99/67.0927)*H9 -> 37.40891 | AB9: =SUM(Y9:AA9) -> 37.40891 | AC9: 7.08 | AD9: =SUM(AB9*AC9) -> 264.85508 | AE9: =SUM(X9+AD9) -> 481.38183 | AF9: =SUM(P9-AE9) -> 129.99817
C10: 240727000003 | D10: 45505 | E10: Sam.Pao | F10: Sam.Pao | G10: Nick Wang | H10: 4.7589 | I10: 760 | J10: 17244.43 | P10: =SUBTOTAL(9,J10) -> 17244.43 | S10: =SUM(57847/67.0927)*H10 -> 4103.1005 | U10: =SUM(1400/67.0927)*H10 -> 99.302309 | X10: =SUM(S10:W10) -> 4202.4028 | Y10: =SUM(10235.99/67.0927)*H10 -> 726.04103 | Z10: 678.47 | AB10: =SUM(Y10:AA10) -> 1404.511 | AC10: 7.08 | AD10: =SUM(AB10*AC10) -> 9943.9381 | AE10: =SUM(X10+AD10) -> 14146.341 | AF10: =SUM(P10-AE10) -> 3098.0892
C11: 240729000009 | D11: 45505 | E11: 朱小飞 | F11: Isabel Zhu | G11: Joy | H11: 2.2224 | I11: 3202 | K11: 2787617 | M11: =SUM(K11/N11) -> 1741.2595 | N11: 1600.9199 | O11: 7.12 | P11: =SUM(N11*O11) -> 11398.55 | S11: =SUM(57847/67.0927)*H11 -> 1916.1425 | U11: =SUM(1400/67.0927)*H11 -> 46.374047 | X11: =SUM(S11:W11) -> 1962.5165 | Y11: =SUM(10235.99/67.0927)*H11 -> 339.0602 | AB11: =SUM(Y11:AA11) -> 339.0602 | AC11: 7.08 | AD11: =SUM(AB11*AC11) -> 2400.5462 | AE11: =SUM(X11+AD11) -> 4363.0627 | AF11: =SUM(P11-AE11) -> 7035.487
C12: 240729000055 | D12: 45505 | E12: 陆总 | F12: 喵喵速运-江 | G12: LUZHILONG | H12: 22.022 | I12: 12675 | J12: 54288.61 | P12: =SUBTOTAL(9,J12) -> 54288.61 | S12: =SUM(57847/67.0927)*H12 -> 18987.261 | U12: =SUM(1400/67.0927)*H12 -> 459.5254 | X12: =SUM(S12:W12) -> 19446.787 | Y12: =SUM(10235.99/67.0927)*H12 -> 3359.7839 | AB12: =SUM(Y12:AA12) -> 3359.7839 | AC12: 7.08 | AD12: =SUM(AB12*AC12) -> 23787.27 | AE12: =SUM(X12+AD12) -> 43234.057 | AF12: =SUM(P12-AE12) -> 11054.553
C13: 240730000017 | D13: 45505 | E13: Sam.Pao | F13: Sam.Pao | G13: MaiKaiNian | H13: 0.2622 | I13: 392 | J13: 1290.24 | P13: =SUBTOTAL(9,J13) -> 1290.24 | S13: =SUM(57847/67.0927)*H13 -> 226.06757 | U13: =SUM(1400/67.0927)*H13 -> 5.4712361 | X13: =SUM(S13:W13) -> 231.5388 | Y13: =SUM(10235.99/67.0927)*H13 -> 40.002513 | AB13: =SUM(Y13:AA13) -> 40.002513 | AC13: 7.08 | AD13: =SUM(AB13*AC13) -> 283.21779 | AE13: =SUM(X13+AD13) -> 514.75659 | AF13: =SUM(P13-AE13) -> 775.48341
C14: 240801000003 | D14: 45505 | E14: Sam.Pao | F14: Sam.Pao | G14: Yusky | H14: 2.1 | I14: 352 | J14: 4491.38 | P14: =SUBTOTAL(9,J14) -> 4491.38 | S14: =SUM(57847/67.0927)*H14 -> 1810.6098 | U14: =SUM(1400/67.0927)*H14 -> 43.819968 | X14: =SUM(S14:W14) -> 1854.4298 | Y14: =SUM(10235.99/67.0927)*H14 -> 320.38626 | AB14: =SUM(Y14:AA14) -> 320.38626 | AC14: 7.08 | AD14: =SUM(AB14*AC14) -> 2268.3347 | AE14: =SUM(X14+AD14) -> 4122.7645 | AF14: =SUM(P14-AE14) -> 368.61554
C15: 240801000001 | D15: 45506 | E15: Sam.Pao | F15: Sam.Pao | G15: SKY JET | H15: 28.4144 | I15: 2700 | J15: 48216.84 | P15: =SUBTOTAL(9,J15) -> 48216.84 | S15: =SUM(57847/67.0927)*H15 -> 24498.758 | U15: =SUM(1400/67.0927)*H15 -> 592.91339 | X15: =SUM(S15:W15) -> 25091.671 | Y15: =SUM(10235.99/67.0927)*H15 -> 4335.0396 | AB15: =SUM(Y15:AA15) -> 4335.0396 | AC15: 7.08 | AD15: =SUM(AB15*AC15) -> 30692.081 | AE15: =SUM(X15+AD15) -> 55783.752 | AF15: =SUM(P15-AE15) -> -7566.9117
C16: 240801000004 | D16: 45505 | E16: Sam.Pao | F16: Sam.Pao | G16: Yusky | H16: 0.1758 | I16: 34 | J16: 375.99 | P16: =SUBTOTAL(9,J16) -> 375.99 | S16: =SUM(57847/67.0927)*H16 -> 151.57391 | U16: =SUM(1400/67.0927)*H16 -> 3.6683574 | X16: =SUM(S16:W16) -> 155.24226 | Y16: =SUM(10235.99/67.0927)*H16 -> 26.820907 | AB16: =SUM(Y16:AA16) -> 26.820907 | AC16: 7.08 | AD16: =SUM(AB16*AC16) -> 189.89202 | AE16: =SUM(X16+AD16) -> 345.13428 | AF16: =SUM(P16-AE16) -> 30.855718
A17: 合计 | J17: =SUM(J4:J4) -> 0 | N17: =SUM(N4:N4) -> 0 | P17: =SUM(P4:P4) -> 0 | Q17: =SUM(Q4:Q4) -> 0 | X17: =SUM(X4:X4) -> 0 | AD17: =SUM(AD4:AD4) -> 0 | AF17: =SUM(AF4:AF16) -> 19429.606

Sheet JOB080361
A1: 2024年08月份LOS毛利表（海运）
A2: PSL表 | B2: 体积cbm | C2: 72.4906
A3: JOB | B3: 集装编号 | C3: 运单编号 | D3: 日期 | E3: 业务 | F3: 发货人 | G3: 收货人 | H3: 计费体积 | I3: 计费重量 | J3: 应 收 | Q3: 总应收 | R3: 起 运 港 成 本 | W3: 代垫运费 | X3: 起运港成本 合计 | Y3: 目的港成本 | AE3: 总支出 | AF3: 利润
J4: 应收RMB | K4: LOS Income(NGN)收到(奈拉) | L4: LOS 收到USD | M4: 美元汇率 dollar currency rate | N4: 应收 到付款USD | O4: 汇率 | P4: 人民币 | R4: 代理商 | S4: 运费+出口报关费 | T4: 提货费 | U4: 装卸费 | V4: 包装费 | Y4: 进口报关费 | Z4: 到门配送费 | AA4: 转运费 | AB4: 目的港支出 | AC4: 汇率 | AD4: 人民币 | AE4: 起运港+目的港
A5: JOB080361 | B5: COLL004096 | C5: 240707000004 | D5: 45506 | E5: Sam.Pao | F5: Sam.Pao | G5: ShanShan | H5: 9.3447 | I5: 5042.5 | J5: 28642.1 | P5: =SUBTOTAL(9,J5) -> 28642.1 | Q5: =SUM(P5:P24) -> 165882.73 | R5: 华茂青松=56567 赛捷=2300 | S5: =SUM(58867/68)*H5 -> 8089.6243 | U5: =SUM(2000/68)*H5 -> 274.84412 | X5: =SUM(S5:W5) -> 8364.4685 | Y5: =SUM(10117.99/68)*H5 -> 1390.435 | Z5: 88.5 | AA5: =SUM(91.45/68)*H5 -> 12.567247 | AB5: =SUM(Y5:AA5) -> 1491.5023 | AC5: 7.15 | AD5: =SUM(AB5*AC5) -> 10664.241 | AE5: =SUM(X5+AD5) -> 19028.71 | AF5: =SUM(P5-AE5) -> 9613.3904
C6: 240719000020 | D6: 45506 | E6: Sam.Pao | F6: Sam.Pao | G6: Wendy | H6: 0.645 | I6: 148 | J6: 2922.21 | P6: =SUBTOTAL(9,J6) -> 2922.21 | S6: =SUM(58867/68)*H6 -> 558.37081 | U6: =SUM(2000/68)*H6 -> 18.970588 | X6: =SUM(S6:W6) -> 577.3414 | Y6: =SUM(10117.99/68)*H6 -> 95.972111 | Z6: 160.91 | AA6: =SUM(91.45/68)*H6 -> 0.86743015 | AB6: =SUM(Y6:AA6) -> 257.74954 | AC6: 7.15 | AD6: =SUM(AB6*AC6) -> 1842.9092 | AE6: =SUM(X6+AD6) -> 2420.2506 | AF6: =SUM(P6-AE6) -> 501.95938
C7: 240719000037 | D7: 45506 | E7: 吕沛霖 | F7: 喵喵速运-Layne | G7: Hu Hai Liang | H7: 0.9193 | I7: 430 | K7: 579841.5 | M7: =SUM(K7/N7) -> 1744.5663 | N7: 332.37 | O7: 7.12 | P7: =SUM(N7*O7) -> 2366.4744 | S7: =SUM(58867/68)*H7 -> 795.8299 | U7: =SUM(2000/68)*H7 -> 27.038235 | X7: =SUM(S7:W7) -> 822.86813 | Y7: =SUM(10117.99/68)*H7 -> 136.7863 | AA7: =SUM(91.45/68)*H7 -> 1.2363233 | AB7: =SUM(Y7:AA7) -> 138.02262 | AC7: 7.15 | AD7: =SUM(AB7*AC7) -> 986.86174 | AE7: =SUM(X7+AD7) -> 1809.7299 | AF7: =SUM(P7-AE7) -> 556.74453
C8: 240723000028 | D8: 45506 | E8: 朱小飞 | F8: Isabel Zhu | G8: Musa Garuba | H8: 0.4159 | I8: 53.8 | K8: 286650 | M8: =SUM(K8/N8) -> 1750 | N8: 163.8 | O8: 7.12 | P8: =SUM(N8*O8) -> 1166.256 | S8: =SUM(58867/68)*H8 -> 360.04096 | U8: =SUM(2000/68)*H8 -> 12.232353 | X8: =SUM(S8:W8) -> 372.27331 | Y8: =SUM(10117.99/68)*H8 -> 61.883412 | AA8: =SUM(91.45/68)*H8 -> 0.55932434 | AB8: =SUM(Y8:AA8) -> 62.442737 | AC8: 7.15 | AD8: =SUM(AB8*AC8) -> 446.46557 | AE8: =SUM(X8+AD8) -> 818.73888 | AF8: =SUM(P8-AE8) -> 347.51712
C9: 240717000037 | D9: 45498 | E9: 朱小飞 | F9: Isabel Zhu | G9: Mr Michael | H9: 8.2 | I9: 882 | J9: 19661.07 | P9: =SUBTOTAL(9,J9) -> 19661.07 | S9: =SUM(58867/68)*H9 -> 7098.6676 | U9: =SUM(2000/68)*H9 -> 241.17647 | X9: =SUM(S9:W9) -> 7339.8441 | Y9: =SUM(10117.99/68)*H9 -> 1220.1106 | AA9: =SUM(91.45/68)*H9 -> 11.027794 | AB9: =SUM(Y9:AA9) -> 1231.1384 | AC9: 7.15 | AD9: =SUM(AB9*AC9) -> 8802.6392 | AE9: =SUM(X9+AD9) -> 16142.483 | AF9: =SUM(P9-AE9) -> 3518.5867
C10: 240718000039 | D10: 45511 | E10: 黄颖 | F10: ying | G10: Idris | H10: 2.7869 | I10: 2167 | J10: 14238 | P10: =SUBTOTAL(9,J10) -> 14238 | S10: =SUM(58867/68)*H10 -> 2412.5947 | U10: =SUM(2000/68)*H10 -> 81.967647 | X10: =SUM(S10:W10) -> 2494.5624 | Y10: =SUM(10117.99/68)*H10 -> 414.67392 | AA10: =SUM(91.45/68)*H10 -> 3.7479707 | AB10: =SUM(Y10:AA10) -> 418.42189 | AC10: 7.15 | AD10: =SUM(AB10*AC10) -> 2991.7165 | AE10: =SUM(X10+AD10) -> 5486.2789 | AF10: =SUM(P10-AE10) -> 8751.7211
C11: 240630000010 | D11: 45511 | E11: 吕沛霖 | F11: 喵喵速运-Layne | G11: WEI PING | H11: 1.6128 | I11: 637 | J11: 3432 | P11: =SUM(J11) -> 3432 | S11: =SUM(58867/68)*H11 -> 1396.1867 | U11: =SUM(2000/68)*H11 -> 47.435294 | X11: =SUM(S11:W11) -> 1443.622 | Y11: =SUM(10117.99/68)*H11 -> 239.97492 | AA11: =SUM(91.45/68)*H11 -> 2.1689788 | AB11: =SUM(Y11:AA11) -> 242.14389 | AC11: 7.15 | AD11: =SUM(AB11*AC11) -> 1731.3288 | AE11: =SUM(X11+AD11) -> 3174.9509 | AF11: =SUM(P11-AE11) -> 257.04913
C12: 240726000008 | D12: 45506 | E12: Bella | F12: Bella Chan | G12: zhong zi xin | H12: 0.835 | I12: 1254 | K12: 1830068.5 | M12: =SUM(K12/N12) -> 1711 | N12: 1069.59 | O12: 7.12 | P12: =SUM(N12*O12) -> 7615.4808 | S12: =SUM(58867/68)*H12 -> 722.85213 | U12: =SUM(2000/68)*H12 -> 24.558824 | X12: =SUM(S12:W12) -> 747.41096 | Y12: =SUM(10117.99/68)*H12 -> 124.24297 | Z12: 284.87 | AA12: =SUM(91.45/68)*H12 -> 1.1229522 | AB12: =SUM(Y12:AA12) -> 410.23592 | AC12: 7.15 | AD12: =SUM(AB12*AC12) -> 2933.1868 | AE12: =SUM(X12+AD12) -> 3680.5978 | AF12: =SUM(P12-AE12) -> 3934.883
C13: 240729000013 | D13: 45506 | E13: 朱小飞 | F13: Isabel Zhu | G13: Halifa Success | H13: 0.3557 | I13: 50 | J13: 801.54 | P13: =SUBTOTAL(9,J13) -> 801.54 | S13: =SUM(58867/68)*H13 -> 307.92635 | U13: =SUM(2000/68)*H13 -> 10.461765 | X13: =SUM(S13:W13) -> 318.38812 | Y13: =SUM(10117.99/68)*H13 -> 52.926015 | AA13: =SUM(91.45/68)*H13 -> 0.47836419 | AB13: =SUM(Y13:AA13) -> 53.40438 | AC13: 7.15 | AD13: =SUM(AB13*AC13) -> 381.84131 | AE13: =SUM(X13+AD13) -> 700.22943 | AF13: =SUM(P13-AE13) -> 101.31057
C14: 240724000026 | D14: 45506 | E14: Bella | F14: Bella Chan | G14: zhong zi xin | H14: 3.0722 | I14: 4949 | K14: 1723658 | M14: =SUM(K14/N14) -> 1711.0136 | N14: 1007.39 | O14: 7.12 | P14: =SUM(N14*O14) -> 7172.6168 | S14: =SUM(58867/68)*H14 -> 2659.5764 | U14: =SUM(2000/68)*H14 -> 90.358824 | X14: =SUM(S14:W14) -> 2749.9353 | Y14: =SUM(10117.99/68)*H14 -> 457.12484 | AA14: =SUM(91.45/68)*H14 -> 4.1316572 | AB14: =SUM(Y14:AA14) -> 461.25649 | AC14: 7.15 | AD14: =SUM(AB14*AC14) -> 3297.9839 | AE14: =SUM(X14+AD14) -> 6047.9192 | AF14: =SUM(P14-AE14) -> 1124.6976
C15: 240729000017 | D15: 45506 | E15: Bella | F15: Bella Chan | G15: zhang jian fei | H15: 1.1178 | I15: 1055 | K15: 776250 | M15: =SUM(K15/N15) -> 1725 | N15: 450 | O15: 7.12 | P15: =SUM(N15*O15) -> 3204 | S15: =SUM(58867/68)*H15 -> 967.6696 | U15: =SUM(2000/68)*H15 -> 32.876471 | X15: =SUM(S15:W15) -> 1000.5461 | Y15: =SUM(10117.99/68)*H15 -> 166.3219 | AA15: =SUM(91.45/68)*H15 -> 1.5032766 | AB15: =SUM(Y15:AA15) -> 167.82518 | AC15: 7.15 | AD15: =SUM(AB15*AC15) -> 1199.95 | AE15: =SUM(X15+AD15) -> 2200.4961 | AF15: =SUM(P15-AE15) -> 1003.5039
C16: 240729000020 | D16: 45506 | E16: 黄颖 | F16: ying | G16: zhounengquan | H16: 0.0032 | I16: 2.7 | J16: 235.2 | P16: =SUBTOTAL(9,J16) -> 235.2 | S16: =SUM(58867/68)*H16 -> 2.7702118 | U16: =SUM(2000/68)*H16 -> 0.094117647 | X16: =SUM(S16:W16) -> 2.8643294 | Y16: =SUM(10117.99/68)*H16 -> 0.47614071 | AA16: =SUM(91.45/68)*H16 -> 0.0043035294 | AB16: =SUM(Y16:AA16) -> 0.48044424 | AC16: 7.15 | AD16: =SUM(AB16*AC16) -> 3.4351763 | AE16: =SUM(X16+AD16) -> 6.2995057 | AF16: =SUM(P16-AE16) -> 228.90049
C17: 240730000010 | D17: 45506 | E17: 朱小飞 | F17: Isabel Zhu | G17: Halifa Success | H17: 3.0014 | I17: 502 | J17: 6679.5 | P17: =SUBTOTAL(9,J17) -> 6679.5 | S17: =SUM(58867/68)*H17 -> 2598.2855 | U17: =SUM(2000/68)*H17 -> 88.276471 | X17: =SUM(S17:W17) -> 2686.562 | Y17: =SUM(10117.99/68)*H17 -> 446.59022 | AA17: =SUM(91.45/68)*H17 -> 4.0364416 | AB17: =SUM(Y17:AA17) -> 450.62666 | AC17: 7.15 | AD17: =SUM(AB17*AC17) -> 3221.9807 | AE17: =SUM(X17+AD17) -> 5908.5426 | AF17: =SUM(P17-AE17) -> 770.95738
C18: 240731000038 | D18: 45506 | E18: 陆总 | F18: 喵喵速运-江 | G18: LUZHILONG | H18: 3.6015 | I18: 1074 | J18: 8038.58 | P18: =SUBTOTAL(9,J18) -> 8038.58 | S18: =SUM(58867/68)*H18 -> 3117.7868 | U18: =SUM(2000/68)*H18 -> 105.92647 | X18: =SUM(S18:W18) -> 3223.7132 | Y18: =SUM(10117.99/68)*H18 -> 535.88149 | AA18: =SUM(91.45/68)*H18 -> 4.8434879 | AB18: =SUM(Y18:AA18) -> 540.72497 | AC18: 7.15 | AD18: =SUM(AB18*AC18) -> 3866.1836 | AE18: =SUM(X18+AD18) -> 7089.8968 | AF18: =SUM(P18-AE18) -> 948.6832
C19: 240801000001 | D19: 45506 | E19: Sam.Pao | F19: Sam.Pao | G19: SKY JET | H19: 32.88 | I19: 4188 | J19: 51584.98 | P19: =SUBTOTAL(9,J19) -> 51584.98 | S19: =SUM(58867/68)*H19 -> 28463.926 | U19: =SUM(2000/68)*H19 -> 967.05882 | X19: =SUM(S19:W19) -> 29430.985 | Y19: =SUM(10117.99/68)*H19 -> 4892.3458 | AA19: =SUM(91.45/68)*H19 -> 44.218765 | AB19: =SUM(Y19:AA19) -> 4936.5645 | AC19: 7.15 | AD19: =SUM(AB19*AC19) -> 35296.436 | AE19: =SUM(X19+AD19) -> 64727.421 | AF19: =SUM(P19-AE19) -> -13142.441
C20: 240728000003 | D20: 45506 | E20: Sam.Pao | F20: Sam.Pao | G20: Nick Wang | H20: 0.2595 | I20: 100 | J20: 699 | P20: =SUBTOTAL(9,J20) -> 699 | S20: =SUM(58867/68)*H20 -> 224.64686 | U20: =SUM(2000/68)*H20 -> 7.6323529 | X20: =SUM(S20:W20) -> 232.27921 | Y20: =SUM(10117.99/68)*H20 -> 38.612035 | AA20: =SUM(91.45/68)*H20 -> 0.34898934 | AB20: =SUM(Y20:AA20) -> 38.961025 | AC20: 7.15 | AD20: =SUM(AB20*AC20) -> 278.57133 | AE20: =SUM(X20+AD20) -> 510.85054 | AF20: =SUM(P20-AE20) -> 188.14946
C21: 240801000022 | D21: 45506 | E21: Bella | F21: Bella Chan | G21: new hope 边鹏飞 | H21: 1.8732 | I21: 1420 | K21: 1129654.4 | M21: =SUM(K21/N21) -> 1739 | N21: 649.6 | O21: 7.06 | P21: =SUM(N21*O21) -> 4586.176 | S21: =SUM(58867/68)*H21 -> 1621.6127 | U21: =SUM(2000/68)*H21 -> 55.094118 | X21: =SUM(S21:W21) -> 1676.7068 | Y21: =SUM(10117.99/68)*H21 -> 278.72087 | AA21: =SUM(91.45/68)*H21 -> 2.5191785 | AB21: =SUM(Y21:AA21) -> 281.24004 | AC21: 7.15 | AD21: =SUM(AB21*AC21) -> 2010.8663 | AE21: =SUM(X21+AD21) -> 3687.5731 | AF21: =SUM(P21-AE21) -> 898.60285
C22: 240802000022 | D22: 45506 | E22: Sam.Pao | F22: Sam.Pao | G22: ShanShan | H22: 0.02 | I22: 5.5 | J22: 61.48 | P22: =SUBTOTAL(9,J22) -> 61.48 | S22: =SUM(58867/68)*H22 -> 17.313824 | U22: =SUM(2000/68)*H22 -> 0.58823529 | X22: =SUM(S22:W22) -> 17.902059 | Y22: =SUM(10117.99/68)*H22 -> 2.9758794 | AA22: =SUM(91.45/68)*H22 -> 0.026897059 | AB22: =SUM(Y22:AA22) -> 3.0027765 | AC22: 7.15 | AD22: =SUM(AB22*AC22) -> 21.469852 | AE22: =SUM(X22+AD22) -> 39.371911 | AF22: =SUM(P22-AE22) -> 22.108089
C23: 240802000026 | D23: 45506 | E23: 陆总 | F23: 喵喵速运-江 | G23: LUZHILONG | H23: 0.0391 | I23: 42.5 | J23: 98.57 | P23: =SUBTOTAL(9,J23) -> 98.57 | S23: =SUM(58867/68)*H23 -> 33.848525 | U23: =SUM(2000/68)*H23 -> 1.15 | X23: =SUM(S23:W23) -> 34.998525 | Y23: =SUM(10117.99/68)*H23 -> 5.8178443 | AA23: =SUM(91.45/68)*H23 -> 0.05258375 | AB23: =SUM(Y23:AA23) -> 5.870428 | AC23: 7.15 | AD23: =SUM(AB23*AC23) -> 41.97356 | AE23: =SUM(X23+AD23) -> 76.972085 | AF23: =SUM(P23-AE23) -> 21.597915
C24: 240802000029 | D24: 45506 | E24: Sam.Pao | F24: Sam.Pao | G24: Yusky | H24: 1.5074 | I24: 207 | J24: 2677.5 | P24: =SUBTOTAL(9,J24) -> 2677.5 | S24: =SUM(58867/68)*H24 -> 1304.9429 | U24: =SUM(2000/68)*H24 -> 44.335294 | X24: =SUM(S24:W24) -> 1349.2782 | Y24: =SUM(10117.99/68)*H24 -> 224.29203 | AA24: =SUM(91.45/68)*H24 -> 2.0272313 | AB24: =SUM(Y24:AA24) -> 226.31926 | AC24: 7.15 | AD24: =SUM(AB24*AC24) -> 1618.1827 | AE24: =SUM(X24+AD24) -> 2967.4609 | AF24: =SUM(P24-AE24) -> -289.9609
A25: 合计 | J25: =SUM(J4:J4) -> 0 | N25: =SUM(N4:N4) -> 0 | P25: =SUM(P4:P4) -> 0 | Q25: =SUM(Q4:Q4) -> 0 | X25: =SUM(X4:X4) -> 0 | AD25: =SUM(AD4:AD4) -> 0 | AF25: =SUM(AF4:AF24) -> 19357.961

Sheet JOB080362
A1: 2024年08月份LOS毛利表（海运）
A2: PSL表 | B2: 体积cbm | C2: 70.927
A3: JOB | B3: 集装编号 | C3: 运单编号 | D3: 日期 | E3: 业务 | F3: 发货人 | G3: 收货人 | H3: 计费体积 | I3: 计费重量 | J3: 应 收 | Q3: 总应收 | R3: 起 运 港 成 本 | W3: 代垫运费 | X3: 起运港成本 合计 | Y3: 目的港成本 | AE3: 总支出 | AF3: 利润
J4: 应收RMB | K4: LOS Income(NGN)收到(奈拉) | L4: LOS 收到USD | M4: 美元汇率 dollar currency rate | N4: 应收 到付款USD | O4: 汇率 | P4: 人民币 | R4: 代理商 | S4: 运费+出口报关费 | T4: 提货费 | U4: 装卸费 | V4: 包装费 | Y4: 进口报关费 | Z4: 到门配送费 | AA4: 转运费 | AB4: 目的港支出 | AC4: 汇率 | AD4: 人民币 | AE4: 起运港+目的港
A5: JOB080362 | B5: COLL004097 | C5: 240804000005 | D5: 45511 | E5: 黄颖 | F5: ying | G5: Sunday Adelena | H5: 34.5199 | I5: 9224 | J5: 77059.62 | P5: =SUBTOTAL(9,J5) -> 77059.62 | Q5: =SUM(P5:P8) -> 141684.32 | R5: 赛捷=56732.25 赛捷=800 | S5: =SUM(57532.25/68)*H5 -> 29205.993 | U5: =SUM(1450/68)*H5 -> 736.0861 | X5: =SUM(S5:W5) -> 29942.079 | Y5: =SUM(10529/68)*H5 -> 5345.0004 | AA5: =SUM(206.48/68)*H5 -> 104.81866 | AB5: =SUM(Y5:AA5) -> 5449.8191 | AC5: 7.09 | AD5: =SUM(AB5*AC5) -> 38639.217 | AE5: =SUM(X5+AD5) -> 68581.296 | AF5: =SUM(P5-AE5) -> 8478.3239
C6: 240630000010 | D6: 45511 | E6: 吕沛霖 | F6: 喵喵速运-Layne | G6: WEI PING | H6: 1.5552 | I6: 912 | J6: 3309 | P6: =SUM(J6) -> 3309 | S6: =SUM(57532.25/68)*H6 -> 1315.7964 | U6: =SUM(1450/68)*H6 -> 33.162353 | X6: =SUM(S6:W6) -> 1348.9588 | Y6: =SUM(10529/68)*H6 -> 240.80442 | AA6: =SUM(206.48/68)*H6 -> 4.7223191 | AB6: =SUM(Y6:AA6) -> 245.52674 | AC6: 7.09 | AD6: =SUM(AB6*AC6) -> 1740.7846 | AE6: =SUM(X6+AD6) -> 3089.7434 | AF6: =SUM(P6-AE6) -> 219.25664
C7: 240806000035 | D7: 45511 | E7: Sam.Pao | F7: Sam.Pao | G7: SKY JET | H7: 34.38 | I7: 4304 | J7: 59321.31 | P7: =SUBTOTAL(9,J7) -> 59321.31 | S7: =SUM(57532.25/68)*H7 -> 29087.629 | U7: =SUM(1450/68)*H7 -> 733.10294 | X7: =SUM(S7:W7) -> 29820.732 | Y7: =SUM(10529/68)*H7 -> 5323.3385 | AA7: =SUM(206.48/68)*H7 -> 104.39386 | AB7: =SUM(Y7:AA7) -> 5427.7324 | AC7: 7.09 | AD7: =SUM(AB7*AC7) -> 38482.623 | AE7: =SUM(X7+AD7) -> 68303.354 | AF7: =SUM(P7-AE7) -> -8982.0443
C8: 240805000030 | D8: 45511 | E8: 朱小飞 | F8: Isabel Zhu | G8: Abdul Aziz | H8: 0.4717 | I8: 63 | J8: 1994.39 | P8: =SUBTOTAL(9,J8) -> 1994.39 | S8: =SUM(57532.25/68)*H8 -> 399.08768 | U8: =SUM(1450/68)*H8 -> 10.058309 | X8: =SUM(S8:W8) -> 409.14599 | Y8: =SUM(10529/68)*H8 -> 73.037196 | Z8: 76.7 | AA8: =SUM(206.48/68)*H8 -> 1.4323032 | AB8: =SUM(Y8:AA8) -> 151.1695 | AC8: 7.09 | AD8: =SUM(AB8*AC8) -> 1071.7917 | AE8: =SUM(X8+AD8) -> 1480.9377 | AF8: =SUM(P8-AE8) -> 513.45226
A9: 合计 | J9: =SUM(J4:J4) -> 0 | N9: =SUM(N4:N4) -> 0 | P9: =SUM(P4:P4) -> 0 | Q9: =SUM(Q4:Q4) -> 0 | X9: =SUM(X4:X4) -> 0 | AD9: =SUM(AD4:AD4) -> 0 | AF9: =SUM(AF4:AF8) -> 228.98845

Sheet JOB080363
A1: 2024年08月份LOS毛利表（海运）
A2: PSL表 | B2: 体积cbm | C2: 75.072
A3: JOB | B3: 集装编号 | C3: 运单编号 | D3: 日期 | E3: 业务 | F3: 发货人 | G3: 收货人 | H3: 计费体积 | I3: 计费重量 | J3: 应 收 | Q3: 总应收 | R3: 起 运 港 成 本 | W3: 代垫运费 | X3: 起运港成本 合计 | Y3: 目的港成本 | AE3: 总支出 | AF3: 利润
J4: 应收RMB | K4: LOS Income(NGN)收到(奈拉) | L4: LOS 收到USD | M4: 美元汇率 dollar currency rate | N4: 应收 到付款USD | O4: 汇率 | P4: 人民币 | R4: 代理商 | S4: 运费+出口报关费 | T4: 提货费 | U4: 装卸费 | V4: 包装费 | Y4: 进口报关费 | Z4: 到门配送费 | AA4: 转运费 | AB4: 目的港支出 | AC4: 汇率 | AD4: 人民币 | AE4: 起运港+目的港
A5: JOB080363 | B5: COLL004098 | C5: 240718000039 | D5: 45511 | E5: 黄颖 | F5: ying | G5: Idris | H5: 9.29 | I5: 13260 | J5: 47474 | P5: =SUBTOTAL(9,J5) -> 47474 | Q5: =SUM(P5:P14) -> 179665.7 | R5: 赛捷=56837.25 赛捷=2300 | S5: =SUM(59137.25/68)*H5 -> 8079.1919 | U5: =SUM(1450/68)*H5 -> 198.09559 | V5: 960 | X5: =SUM(S5:W5) -> 9237.2875 | Y5: =SUM(10529/68)*H5 -> 1438.4472 | Z5: 1823.01 | AA5: =SUM(259.58/68)*H5 -> 35.463209 | AB5: =SUM(Y5:AA5) -> 3296.9204 | AC5: 7.09 | AD5: =SUM(AB5*AC5) -> 23375.166 | AE5: =SUM(X5+AD5) -> 32612.453 | AF5: =SUM(P5-AE5) -> 14861.547
C6: 240724000012 | D6: 45511 | E6: Bella | F6: Bella Chan | G6: zhang yong chong | H6: 5.7046 | I6: 942 | J6: 14778 | P6: =SUBTOTAL(9,J6) -> 14778 | S6: =SUM(59137.25/68)*H6 -> 4961.0935 | U6: =SUM(1450/68)*H6 -> 121.64221 | V6: 1400 | X6: =SUM(S6:W6) -> 6482.7357 | Y6: =SUM(10529/68)*H6 -> 883.2902 | AA6: =SUM(259.58/68)*H6 -> 21.776472 | AB6: =SUM(Y6:AA6) -> 905.06667 | AC6: 7.09 | AD6: =SUM(AB6*AC6) -> 6416.9227 | AE6: =SUM(X6+AD6) -> 12899.658 | AF6: =SUM(P6-AE6) -> 1878.3416
C7: 240730000015 | D7: 45511 | E7: 黄颖 | F7: ying | G7: Huangpu | H7: 0.159 | I7: 26.5 | J7: 376.32 | P7: =SUBTOTAL(9,J7) -> 376.32 | S7: =SUM(59137.25/68)*H7 -> 138.27681 | U7: =SUM(1450/68)*H7 -> 3.3904412 | X7: =SUM(S7:W7) -> 141.66725 | Y7: =SUM(10529/68)*H7 -> 24.619279 | AA7: =SUM(259.58/68)*H7 -> 0.60695912 | AB7: =SUM(Y7:AA7) -> 25.226239 | AC7: 7.09 | AD7: =SUM(AB7*AC7) -> 178.85403 | AE7: =SUM(X7+AD7) -> 320.52128 | AF7: =SUM(P7-AE7) -> 55.798723
C8: 240801000020 | D8: 45512 | E8: 朱小飞 | F8: Isabel Zhu | G8: Mr Michael | H8: 5.1796 | I8: 572 | J8: 12648 | P8: =SUBTOTAL(9,J8) -> 12648 | S8: =SUM(59137.25/68)*H8 -> 4504.5191 | U8: =SUM(1450/68)*H8 -> 110.44735 | X8: =SUM(S8:W8) -> 4614.9665 | Y8: =SUM(10529/68)*H8 -> 802.00012 | AA8: =SUM(259.58/68)*H8 -> 19.772361 | AB8: =SUM(Y8:AA8) -> 821.77248 | AC8: 7.09 | AD8: =SUM(AB8*AC8) -> 5826.3669 | AE8: =SUM(X8+AD8) -> 10441.333 | AF8: =SUM(P8-AE8) -> 2206.6666
C9: 240630000010 | D9: 45534 | E9: 吕沛霖 | F9: 喵喵速运-Layne | G9: WEI PING | H9: 4.6083 | I9: 761.3 | J9: 9806 | P9: =SUM(J9) -> 9806 | S9: =SUM(59137.25/68)*H9 -> 4007.6793 | U9: =SUM(1450/68)*H9 -> 98.265221 | X9: =SUM(S9:W9) -> 4105.9445 | Y9: =SUM(10529/68)*H9 -> 713.54104 | AA9: =SUM(259.58/68)*H9 -> 17.591508 | AB9: =SUM(Y9:AA9) -> 731.13255 | AC9: 7.09 | AD9: =SUM(AB9*AC9) -> 5183.7298 | AE9: =SUM(X9+AD9) -> 9289.6742 | AF9: =SUM(P9-AE9) -> 516.32577
C10: 240728000003 | D10: 45506 | E10: Sam.Pao | F10: Sam.Pao | G10: Nick Wang | H10: 0.29 | I10: 135 | J10: 782 | P10: =SUBTOTAL(9,J10) -> 782 | S10: =SUM(59137.25/68)*H10 -> 252.20298 | U10: =SUM(1450/68)*H10 -> 6.1838235 | X10: =SUM(S10:W10) -> 258.3868 | Y10: =SUM(10529/68)*H10 -> 44.903088 | AA10: =SUM(259.58/68)*H10 -> 1.1070324 | AB10: =SUM(Y10:AA10) -> 46.010121 | AC10: 7.09 | AD10: =SUM(AB10*AC10) -> 326.21175 | AE10: =SUM(X10+AD10) -> 584.59856 | AF10: =SUM(P10-AE10) -> 197.40144
C11: 240730000035 | D11: 45511 | E11: 吕沛霖 | F11: 喵喵速运-Layne | G11: MR MANBO | H11: 1.0597 | I11: 336 | J11: 3645.46 | P11: =SUBTOTAL(9,J11) -> 3645.46 | S11: =SUM(59137.25/68)*H11 -> 921.58447 | U11: =SUM(1450/68)*H11 -> 22.596544 | X11: =SUM(S11:W11) -> 944.18101 | Y11: =SUM(10529/68)*H11 -> 164.08208 | Z11: 50.15 | AA11: =SUM(259.58/68)*H11 -> 4.0452489 | AB11: =SUM(Y11:AA11) -> 218.27733 | AC11: 7.09 | AD11: =SUM(AB11*AC11) -> 1547.5862 | AE11: =SUM(X11+AD11) -> 2491.7673 | AF11: =SUM(P11-AE11) -> 1153.6927
C12: 240802000009 | D12: 45511 | E12: Bella | F12: Bella Chan | G12: zhang long ting | H12: 0.1283 | I12: 12.76 | J12: 327.6 | P12: =SUBTOTAL(9,J12) -> 327.6 | S12: =SUM(59137.25/68)*H12 -> 111.57808 | U12: =SUM(1450/68)*H12 -> 2.7358088 | X12: =SUM(S12:W12) -> 114.31388 | Y12: =SUM(10529/68)*H12 -> 19.865746 | AA12: =SUM(259.58/68)*H12 -> 0.48976638 | AB12: =SUM(Y12:AA12) -> 20.355512 | AC12: 7.09 | AD12: =SUM(AB12*AC12) -> 144.32058 | AE12: =SUM(X12+AD12) -> 258.63446 | AF12: =SUM(P12-AE12) -> 68.965535
C13: 240804000004 | D13: 45511 | E13: 罗伟健 | F13: MailMail速运-演员 | G13: zeng hai | H13: 10.2324 | I13: 1319 | K13: 5637625 | M13: =SUM(K13/N13) -> 1710.9999 | N13: 3294.93 | O13: 7.06 | P13: =SUM(N13*O13) -> 23262.206 | S13: =SUM(59137.25/68)*H13 -> 8898.7647 | U13: =SUM(1450/68)*H13 -> 218.19088 | V13: 150 | X13: =SUM(S13:W13) -> 9266.9555 | Y13: =SUM(10529/68)*H13 -> 1584.3668 | AA13: =SUM(259.58/68)*H13 -> 39.060682 | AB13: =SUM(Y13:AA13) -> 1623.4274 | AC13: 7.09 | AD13: =SUM(AB13*AC13) -> 11510.101 | AE13: =SUM(X13+AD13) -> 20777.056 | AF13: =SUM(P13-AE13) -> 2485.1497
C14: 240806000035 | D14: 45511 | E14: Sam.Pao | F14: Sam.Pao | G14: SKY JET | H14: 38.42 | I14: 4700 | J14: 66566.11 | P14: =SUBTOTAL(9,J14) -> 66566.11 | S14: =SUM(59137.25/68)*H14 -> 33412.546 | U14: =SUM(1450/68)*H14 -> 819.25 | X14: =SUM(S14:W14) -> 34231.796 | Y14: =SUM(10529/68)*H14 -> 5948.885 | AA14: =SUM(259.58/68)*H14 -> 146.6627 | AB14: =SUM(Y14:AA14) -> 6095.5477 | AC14: 7.09 | AD14: =SUM(AB14*AC14) -> 43217.433 | AE14: =SUM(X14+AD14) -> 77449.229 | AF14: =SUM(P14-AE14) -> -10883.119
A15: 合计 | J15: =SUM(J4:J4) -> 0 | N15: =SUM(N4:N4) -> 0 | P15: =SUM(P4:P4) -> 0 | Q15: =SUM(Q4:Q4) -> 0 | X15: =SUM(X4:X4) -> 0 | AD15: =SUM(AD4:AD4) -> 0 | AF15: =SUM(AF4:AF14) -> 12540.769

Sheet JOB080364
A1: 2024年08月份LOS毛利表（海运）
A2: PSL表 | B2: 体积cbm | C2: 72.4244
A3: JOB | B3: 集装编号 | C3: 运单编号 | D3: 日期 | E3: 业务 | F3: 发货人 | G3: 收货人 | H3: 计费体积 | I3: 计费重量 | J3: 应 收 | Q3: 总应收 | R3: 起 运 港 成 本 | W3: 代垫运费 | X3: 起运港成本 合计 | Y3: 目的港成本 | AE3: 总支出 | AF3: 利润
J4: 应收RMB | K4: LOS Income(NGN)收到(奈拉) | L4: LOS 收到USD | M4: 美元汇率 dollar currency rate | N4: 应收 到付款USD | O4: 汇率 | P4: 人民币 | R4: 代理商 | S4: 运费+出口报关费 | T4: 提货费 | U4: 装卸费 | V4: 包装费 | Y4: 进口报关费 | Z4: 到门配送费 | AA4: 转运费 | AB4: 目的港支出 | AC4: 汇率 | AD4: 人民币 | AE4: 起运港+目的港
A5: JOB080364 | B5: COLL004100 | C5: 240801000020 | D5: 45512 | E5: 朱小飞 | F5: Isabel Zhu | G5: Mr Michael | H5: 5.7204 | I5: 603 | J5: 13956 | P5: =SUBTOTAL(9,J5) -> 13956 | Q5: =SUM(P5:P16) -> 154255.39 | R5: 赛捷=57732.25 赛捷=800 | S5: =SUM(58532.25/68)*H5 -> 4923.9395 | T5: =SUM(54.99/68)*H5 -> 4.6259529 | U5: =SUM(1000/68)*H5 -> 84.123529 | X5: =SUM(S5:W5) -> 5012.6889 | Y5: =SUM(10435/68)*H5 -> 877.82903 | AB5: =SUM(Y5:AA5) -> 877.82903 | AC5: 7.12 | AD5: =SUM(AB5*AC5) -> 6250.1427 | AE5: =SUM(X5+AD5) -> 11262.832 | AF5: =SUM(P5-AE5) -> 2693.1684
C6: 240802000002 | D6: 45512 | E6: 黄颖 | F6: ying | G6: huangzhaoyong | H6: 1.848 | I6: 1035 | J6: 4482.5 | P6: =SUBTOTAL(9,J6) -> 4482.5 | S6: =SUM(58532.25/68)*H6 -> 1590.7 | T6: =SUM(54.99/68)*H6 -> 1.4944341 | U6: =SUM(1000/68)*H6 -> 27.176471 | X6: =SUM(S6:W6) -> 1619.3709 | Y6: =SUM(10435/68)*H6 -> 283.58647 | AB6: =SUM(Y6:AA6) -> 283.58647 | AC6: 7.12 | AD6: =SUM(AB6*AC6) -> 2019.1357 | AE6: =SUM(X6+AD6) -> 3638.5065 | AF6: =SUM(P6-AE6) -> 843.99345
C7: 240803000005 | D7: 45512 | E7: Sam.Pao | F7: Sam.Pao | G7: Cherry | H7: 2.6248 | I7: 630 | J7: 6236.5 | P7: =SUBTOTAL(9,J7) -> 6236.5 | S7: =SUM(58532.25/68)*H7 -> 2259.3448 | T7: =SUM(54.99/68)*H7 -> 2.122614 | U7: =SUM(1000/68)*H7 -> 38.6 | X7: =SUM(S7:W7) -> 2300.0675 | Y7: =SUM(10435/68)*H7 -> 402.791 | AB7: =SUM(Y7:AA7) -> 402.791 | AC7: 7.12 | AD7: =SUM(AB7*AC7) -> 2867.8719 | AE7: =SUM(X7+AD7) -> 5167.9394 | AF7: =SUM(P7-AE7) -> 1068.5606
C8: 240803000017 | D8: 45512 | E8: 黄颖 | F8: ying | G8: Sunday Adelena | H8: 17.17 | I8: 12298 | J8: 38477.75 | P8: =SUBTOTAL(9,J8) -> 38477.75 | S8: =SUM(58532.25/68)*H8 -> 14779.393 | T8: =SUM(54.99/68)*H8 -> 13.884975 | U8: =SUM(1000/68)*H8 -> 252.5 | X8: =SUM(S8:W8) -> 15045.778 | Y8: =SUM(10435/68)*H8 -> 2634.8375 | AB8: =SUM(Y8:AA8) -> 2634.8375 | AC8: 7.12 | AD8: =SUM(AB8*AC8) -> 18760.043 | AE8: =SUM(X8+AD8) -> 33805.821 | AF8: =SUM(P8-AE8) -> 4671.9289
C9: 240807000012 | D9: 45512 | E9: Sam.Pao | F9: Sam.Pao | G9: Yusky | H9: 3.79 | I9: 780 | J9: 7638.75 | P9: =SUBTOTAL(9,J9) -> 7638.75 | S9: =SUM(58532.25/68)*H9 -> 3262.3122 | T9: =SUM(54.99/68)*H9 -> 3.0648838 | U9: =SUM(1000/68)*H9 -> 55.735294 | X9: =SUM(S9:W9) -> 3321.1123 | Y9: =SUM(10435/68)*H9 -> 581.59779 | AB9: =SUM(Y9:AA9) -> 581.59779 | AC9: 7.12 | AD9: =SUM(AB9*AC9) -> 4140.9763 | AE9: =SUM(X9+AD9) -> 7462.0886 | AF9: =SUM(P9-AE9) -> 176.66136
C10: 240808000010 | D10: 45512 | E10: Sam.Pao | F10: Sam.Pao | G10: SKY JET | H10: 9.8 | I10: 1059 | J10: 15645.79 | P10: =SUBTOTAL(9,J10) -> 15645.79 | S10: =SUM(58532.25/68)*H10 -> 8435.5301 | T10: =SUM(54.99/68)*H10 -> 7.9250294 | U10: =SUM(1000/68)*H10 -> 144.11765 | X10: =SUM(S10:W10) -> 8587.5728 | Y10: =SUM(10435/68)*H10 -> 1503.8676 | AB10: =SUM(Y10:AA10) -> 1503.8676 | AC10: 7.12 | AD10: =SUM(AB10*AC10) -> 10707.538 | AE10: =SUM(X10+AD10) -> 19295.11 | AF10: =SUM(P10-AE10) -> -3649.3205
C11: 240728000003 | D11: 45506 | E11: Sam.Pao | F11: Sam.Pao | G11: Nick Wang | H11: 0.632 | I11: 166 | J11: 1705 | P11: =SUBTOTAL(9,J11) -> 1705 | S11: =SUM(58532.25/68)*H11 -> 544.00562 | T11: =SUM(54.99/68)*H11 -> 0.51108353 | U11: =SUM(1000/68)*H11 -> 9.2941176 | X11: =SUM(S11:W11) -> 553.81082 | Y11: =SUM(10435/68)*H11 -> 96.984118 | AB11: =SUM(Y11:AA11) -> 96.984118 | AC11: 7.12 | AD11: =SUM(AB11*AC11) -> 690.52692 | AE11: =SUM(X11+AD11) -> 1244.3377 | AF11: =SUM(P11-AE11) -> 460.66226
C12: 240613000018 | D12: 45506 | E12: Sam.Pao | F12: Sam.Pao | G12: ChenGaoHong | H12: 1.6564 | I12: 313 | J12: 3117 | P12: =SUBTOTAL(9,J12) -> 3117 | S12: =SUM(58532.25/68)*H12 -> 1425.7767 | T12: =SUM(54.99/68)*H12 -> 1.3394917 | U12: =SUM(1000/68)*H12 -> 24.358824 | X12: =SUM(S12:W12) -> 1451.4751 | Y12: =SUM(10435/68)*H12 -> 254.18432 | AB12: =SUM(Y12:AA12) -> 254.18432 | AC12: 7.12 | AD12: =SUM(AB12*AC12) -> 1809.7924 | AE12: =SUM(X12+AD12) -> 3261.2674 | AF12: =SUM(P12-AE12) -> -144.26745
C13: 240808000011 | D13: 45534 | E13: Sam.Pao | F13: Sam.Pao | G13: Yusky | H13: 0.6332 | I13: 114 | J13: 1276.22 | P13: =SUBTOTAL(9,J13) -> 1276.22 | S13: =SUM(58532.25/68)*H13 -> 545.03854 | T13: =SUM(54.99/68)*H13 -> 0.51205394 | U13: =SUM(1000/68)*H13 -> 9.3117647 | X13: =SUM(S13:W13) -> 554.86236 | Y13: =SUM(10435/68)*H13 -> 97.168265 | AB13: =SUM(Y13:AA13) -> 97.168265 | AC13: 7.12 | AD13: =SUM(AB13*AC13) -> 691.83804 | AE13: =SUM(X13+AD13) -> 1246.7004 | AF13: =SUM(P13-AE13) -> 29.519597
C14: 240808000012 | D14: 45512 | E14: 吕沛霖 | F14: 喵喵速运-Layne | G14: YA | H14: 0.2465 | I14: 35.5 | J14: 821 | P14: =SUM(J14) -> 821 | S14: =SUM(58532.25/68)*H14 -> 212.17941 | T14: =SUM(54.99/68)*H14 -> 0.19933875 | U14: =SUM(1000/68)*H14 -> 3.625 | X14: =SUM(S14:W14) -> 216.00375 | Y14: =SUM(10435/68)*H14 -> 37.826875 | AA14: 22.18 | AB14: =SUM(Y14:AA14) -> 60.006875 | AC14: 7.12 | AD14: =SUM(AB14*AC14) -> 427.24895 | AE14: =SUM(X14+AD14) -> 643.2527 | AF14: =SUM(P14-AE14) -> 177.74731
C15: 240630000010 | D15: 45534 | E15: 吕沛霖 | F15: 喵喵速运-Layne | G15: WEI PING | H15: 20.8295 | I15: 1472 | J15: 44333.83 | P15: =SUM(J15) -> 44333.83 | S15: =SUM(58532.25/68)*H15 -> 17929.375 | T15: =SUM(54.99/68)*H15 -> 16.844327 | U15: =SUM(1000/68)*H15 -> 306.31618 | X15: =SUM(S15:W15) -> 18252.536 | Y15: =SUM(10435/68)*H15 -> 3196.4093 | AB15: =SUM(Y15:AA15) -> 3196.4093 | AC15: 7.12 | AD15: =SUM(AB15*AC15) -> 22758.434 | AE15: =SUM(X15+AD15) -> 41010.97 | AF15: =SUM(P15-AE15) -> 3322.8603
C16: 240808000019 | D16: 45512 | E16: 陆总 | F16: Sam.Pao | G16: LuZhiLong | H16: 7.4735 | I16: 1000 | J16: 16565.05 | P16: =SUBTOTAL(9,J16) -> 16565.05 | S16: =SUM(58532.25/68)*H16 -> 6432.9525 | T16: =SUM(54.99/68)*H16 -> 6.0436436 | U16: =SUM(1000/68)*H16 -> 109.90441 | X16: =SUM(S16:W16) -> 6548.9006 | Y16: =SUM(10435/68)*H16 -> 1146.8525 | AB16: =SUM(Y16:AA16) -> 1146.8525 | AC16: 7.12 | AD16: =SUM(AB16*AC16) -> 8165.5901 | AE16: =SUM(X16+AD16) -> 14714.491 | AF16: =SUM(P16-AE16) -> 1850.5594
A17: 合计 | J17: =SUM(J4:J4) -> 0 | N17: =SUM(N4:N4) -> 0 | P17: =SUM(P4:P4) -> 0 | Q17: =SUM(Q4:Q4) -> 0 | X17: =SUM(X4:X4) -> 0 | AD17: =SUM(AD4:AD4) -> 0 | AF17: =SUM(AF4:AF16) -> 11502.074

Sheet JOB080373
A1: 2024年08月份LOS毛利表（海运）
A2: PSL表 | B2: 体积cbm | C2: 76.3591
A3: JOB | B3: 集装编号 | C3: 运单编号 | D3: 日期 | E3: 业务 | F3: 发货人 | G3: 收货人 | H3: 计费体积 | I3: 计费重量 | J3: 应 收 | Q3: 总应收 | R3: 起 运 港 成 本 | W3: 代垫运费 | X3: 起运港成本 合计 | Y3: 目的港成本 | AE3: 总支出 | AF3: 利润
J4: 应收RMB | K4: LOS Income(NGN)收到(奈拉) | L4: LOS 收到USD | M4: 美元汇率 dollar currency rate | N4: 应收 到付款USD | O4: 汇率 | P4: 人民币 | R4: 代理商 | S4: 运费+出口报关费 | T4: 提货费 | U4: 装卸费 | V4: 包装费 | Y4: 进口报关费 | Z4: 到门配送费 | AA4: 转运费 | AB4: 目的港支出 | AC4: 汇率 | AD4: 人民币 | AE4: 起运港+目的港
A5: JOB080373 | B5: COLL004107 | C5: 240630000010 | D5: 45534 | E5: 吕沛霖 | F5: 喵喵速运-Layne | G5: WEI PING | H5: 4.5207 | I5: 744 | J5: 9620 | P5: =SUM(J5) -> 9620 | Q5: =SUM(P5:P20) -> 160773.2 | R5: 赛捷=56265.25 赛捷=1280 | S5: =SUM(57545.25/68)*H5 -> 3825.659 | U5: =SUM(2100/68)*H5 -> 139.60985 | V5: 900 | X5: =SUM(S5:W5) -> 4865.2688 | Y5: =SUM(10417/68)*H5 -> 692.53135 | Z5: 70.8 | AB5: =SUM(Y5:AA5) -> 763.33135 | AC5: 7.07 | AD5: =SUM(AB5*AC5) -> 5396.7527 | AE5: =SUM(X5+AD5) -> 10262.022 | AF5: =SUM(P5-AE5) -> -642.0215
C6: 240725000027 | D6: 45534 | E6: 黄颖 | F6: ying | G6: Huangpu | H6: 0.0213 | I6: 3.7 | K6: 85293 | M6: =SUM(K6/N6) -> 1730.4321 | N6: 49.29 | O6: 7.12 | P6: =SUM(N6*O6) -> 350.9448 | S6: =SUM(57545.25/68)*H6 -> 18.025203 | U6: =SUM(2100/68)*H6 -> 0.65779412 | X6: =SUM(S6:W6) -> 18.682997 | Y6: =SUM(10417/68)*H6 -> 3.2629721 | Z6: 7.25 | AB6: =SUM(Y6:AA6) -> 10.512972 | AC6: 7.07 | AD6: =SUM(AB6*AC6) -> 74.326712 | AE6: =SUM(X6+AD6) -> 93.00971 | AF6: =SUM(P6-AE6) -> 257.93509
C7: 240806000025 | D7: 45534 | E7: 吕沛霖 | F7: 喵喵速运-Layne | G7: FRANK | H7: 4.665 | I7: 886 | J7: 10755.219 | P7: =SUM(J7) -> 10755.219 | S7: =SUM(57545.25/68)*H7 -> 3947.7734 | U7: =SUM(2100/68)*H7 -> 144.06618 | X7: =SUM(S7:W7) -> 4091.8396 | Y7: =SUM(10417/68)*H7 -> 714.63684 | AB7: =SUM(Y7:AA7) -> 714.63684 | AC7: 7.07 | AD7: =SUM(AB7*AC7) -> 5052.4824 | AE7: =SUM(X7+AD7) -> 9144.322 | AF7: =SUM(P7-AE7) -> 1610.897
C8: 240807000004 | D8: 45534 | E8: 朱小飞 | F8: Isabel Zhu | G8: Inemesit udoh | H8: 2.4662 | I8: 160 | K8: 1842570 | M8: =SUM(K8/N8) -> 1735 | N8: 1062 | O8: 7.12 | P8: =SUM(N8*O8) -> 7561.44 | S8: =SUM(57545.25/68)*H8 -> 2087.0308 | U8: =SUM(2100/68)*H8 -> 76.162059 | X8: =SUM(S8:W8) -> 2163.1929 | Y8: =SUM(10417/68)*H8 -> 377.80008 | AB8: =SUM(Y8:AA8) -> 377.80008 | AC8: 7.07 | AD8: =SUM(AB8*AC8) -> 2671.0466 | AE8: =SUM(X8+AD8) -> 4834.2394 | AF8: =SUM(P8-AE8) -> 2727.2006
C9: 240807000010 | D9: 45534 | E9: 黄颖 | F9: ying | G9: Huangpu | H9: 0.0207 | I9: 4.2 | K9: 59049 | M9: =SUM(K9/N9) -> 1786.1162 | N9: 33.06 | O9: 7.12 | P9: =SUM(N9*O9) -> 235.3872 | S9: =SUM(57545.25/68)*H9 -> 17.517451 | U9: =SUM(2100/68)*H9 -> 0.63926471 | X9: =SUM(S9:W9) -> 18.156716 | Y9: =SUM(10417/68)*H9 -> 3.1710574 | Z9: 7.5 | AB9: =SUM(Y9:AA9) -> 10.671057 | AC9: 7.07 | AD9: =SUM(AB9*AC9) -> 75.444375 | AE9: =SUM(X9+AD9) -> 93.601091 | AF9: =SUM(P9-AE9) -> 141.78611
C10: 240808000002 | D10: 45534 | E10: 吕沛霖 | F10: 喵喵速运-Layne | G10: FRANK | H10: 2.1795 | I10: 785 | K10: 1256000 | M10: =SUM(K10/N10) -> 1751.89 | N10: 716.94 | O10: 7.15 | P10: =SUM(N10*O10) -> 5126.121 | S10: =SUM(57545.25/68)*H10 -> 1844.4099 | U10: =SUM(2100/68)*H10 -> 67.308088 | X10: =SUM(S10:W10) -> 1911.718 | Y10: =SUM(10417/68)*H10 -> 333.88017 | AB10: =SUM(Y10:AA10) -> 333.88017 | AC10: 7.07 | AD10: =SUM(AB10*AC10) -> 2360.5328 | AE10: =SUM(X10+AD10) -> 4272.2508 | AF10: =SUM(P10-AE10) -> 853.87023
C11: 240808000011 | D11: 45534 | E11: Sam.Pao | F11: Sam.Pao | G11: Yusky | H11: 1.8652 | I11: 420 | J11: 3624.06 | P11: =SUBTOTAL(9,J11) -> 3624.06 | S11: =SUM(57545.25/68)*H11 -> 1578.4324 | U11: =SUM(2100/68)*H11 -> 57.601765 | X11: =SUM(S11:W11) -> 1636.0341 | Y11: =SUM(10417/68)*H11 -> 285.73218 | AB11: =SUM(Y11:AA11) -> 285.73218 | AC11: 7.07 | AD11: =SUM(AB11*AC11) -> 2020.1265 | AE11: =SUM(X11+AD11) -> 3656.1607 | AF11: =SUM(P11-AE11) -> -32.100651
C12: 240728000003 | D12: 45506 | E12: Sam.Pao | F12: Sam.Pao | G12: Nick Wang | H12: 0.354 | I12: 131 | J12: 954 | P12: =SUBTOTAL(9,J12) -> 954 | S12: =SUM(57545.25/68)*H12 -> 299.5738 | U12: =SUM(2100/68)*H12 -> 10.932353 | X12: =SUM(S12:W12) -> 310.50615 | Y12: =SUM(10417/68)*H12 -> 54.229676 | AB12: =SUM(Y12:AA12) -> 54.229676 | AC12: 7.07 | AD12: =SUM(AB12*AC12) -> 383.40381 | AE12: =SUM(X12+AD12) -> 693.90997 | AF12: =SUM(P12-AE12) -> 260.09003
C13: 240808000024 | D13: 45534 | E13: 黄颖 | F13: ying | G13: Emma | H13: 2.295 | I13: 107 | L13: 827 | M13: =SUM(K13/N13) -> 0 | N13: 827 | O13: 7.12 | P13: =SUM(N13*O13) -> 5888.24 | S13: =SUM(57545.25/68)*H13 -> 1942.1522 | U13: =SUM(2100/68)*H13 -> 70.875 | X13: =SUM(S13:W13) -> 2013.0272 | Y13: =SUM(10417/68)*H13 -> 351.57375 | Z13: 70.8 | AB13: =SUM(Y13:AA13) -> 422.37375 | AC13: 7.07 | AD13: =SUM(AB13*AC13) -> 2986.1824 | AE13: =SUM(X13+AD13) -> 4999.2096 | AF13: =SUM(P13-AE13) -> 889.0304
C14: 240809000022 | D14: 45534 | E14: Sam.Pao | F14: Sam.Pao | G14: Oladunni Eludire | H14: 8.119 | I14: 5120 | J14: 22858.98 | P14: =SUBTOTAL(9,J14) -> 22858.98 | S14: =SUM(57545.25/68)*H14 -> 6870.7336 | U14: =SUM(2100/68)*H14 -> 250.73382 | W14: =SUM(700+300) -> 1000 | X14: =SUM(S14:W14) -> 8121.4674 | Y14: =SUM(10417/68)*H14 -> 1243.7592 | AB14: =SUM(Y14:AA14) -> 1243.7592 | AC14: 7.07 | AD14: =SUM(AB14*AC14) -> 8793.3773 | AE14: =SUM(X14+AD14) -> 16914.845 | AF14: =SUM(P14-AE14) -> 5944.1353
C15: 240809000034 | D15: 45534 | E15: 朱小飞 | F15: Isabel Zhu | G15: Victor Nnamdi | H15: 0.9292 | I15: 144 | K15: 548260 | M15: =SUM(K15/N15) -> 1735 | N15: 316 | O15: 7.12 | P15: =SUM(N15*O15) -> 2249.92 | S15: =SUM(57545.25/68)*H15 -> 786.33892 | U15: =SUM(2100/68)*H15 -> 28.695882 | X15: =SUM(S15:W15) -> 815.0348 | Y15: =SUM(10417/68)*H15 -> 142.34524 | AB15: =SUM(Y15:AA15) -> 142.34524 | AC15: 7.07 | AD15: =SUM(AB15*AC15) -> 1006.3809 | AE15: =SUM(X15+AD15) -> 1821.4157 | AF15: =SUM(P15-AE15) -> 428.50435
C16: 240813000001 | D16: 45534 | E16: Sam.Pao | F16: Sam.Pao | G16: SKY JET | H16: 33.04 | I16: 4133 | J16: 53646.12 | P16: =SUBTOTAL(9,J16) -> 53646.12 | S16: =SUM(57545.25/68)*H16 -> 27960.221 | U16: =SUM(2100/68)*H16 -> 1020.3529 | X16: =SUM(S16:W16) -> 28980.574 | Y16: =SUM(10417/68)*H16 -> 5061.4365 | AB16: =SUM(Y16:AA16) -> 5061.4365 | AC16: 7.07 | AD16: =SUM(AB16*AC16) -> 35784.356 | AE16: =SUM(X16+AD16) -> 64764.93 | AF16: =SUM(P16-AE16) -> -11118.81
C17: 240809000038 | D17: 45534 | E17: Bella | F17: Bella Chan | G17: FENG | H17: 2.0316 | I17: 173 | J17: 4667 | P17: =SUBTOTAL(9,J17) -> 4667 | S17: =SUM(57545.25/68)*H17 -> 1719.249 | U17: =SUM(2100/68)*H17 -> 62.740588 | X17: =SUM(S17:W17) -> 1781.9896 | Y17: =SUM(10417/68)*H17 -> 311.22319 | AB17: =SUM(Y17:AA17) -> 311.22319 | AC17: 7.07 | AD17: =SUM(AB17*AC17) -> 2200.348 | AE17: =SUM(X17+AD17) -> 3982.3375 | AF17: =SUM(P17-AE17) -> 684.66246
C18: 240810000008 | D18: 45534 | E18: 罗伟健 | F18: MailMail速运-演员 | G18: Mr.Joseph Ezekiel | H18: 7.4021 | I18: 2808 | K18: 4341273 | M18: =SUM(K18/N18) -> 1725 | N18: 2516.68 | O18: 7.12 | P18: =SUM(N18*O18) -> 17918.762 | S18: =SUM(57545.25/68)*H18 -> 6264.0543 | U18: =SUM(2100/68)*H18 -> 228.59426 | X18: =SUM(S18:W18) -> 6492.6486 | Y18: =SUM(10417/68)*H18 -> 1133.9364 | AB18: =SUM(Y18:AA18) -> 1133.9364 | AC18: 7.07 | AD18: =SUM(AB18*AC18) -> 8016.9304 | AE18: =SUM(X18+AD18) -> 14509.579 | AF18: =SUM(P18-AE18) -> 3409.1826
C19: 240813000002 | D19: 45534 | E19: Sam.Pao | F19: Sam.Pao | G19: SKY JET | H19: 1.14 | I19: 155 | J19: 1853.23 | P19: =SUBTOTAL(9,J19) -> 1853.23 | S19: =SUM(57545.25/68)*H19 -> 964.72919 | U19: =SUM(2100/68)*H19 -> 35.205882 | X19: =SUM(S19:W19) -> 999.93507 | Y19: =SUM(10417/68)*H19 -> 174.63794 | AB19: =SUM(Y19:AA19) -> 174.63794 | AC19: 7.07 | AD19: =SUM(AB19*AC19) -> 1234.6902 | AE19: =SUM(X19+AD19) -> 2234.6253 | AF19: =SUM(P19-AE19) -> -381.39532
C20: 240812000043 | D20: 45534 | E20: 陆总 | F20: Sam.Pao | G20: LuZhiLong | H20: 5.313 | I20: 2925 | J20: 13463.78 | P20: =SUBTOTAL(9,J20) -> 13463.78 | S20: =SUM(57545.25/68)*H20 -> 4496.1458 | U20: =SUM(2100/68)*H20 -> 164.07794 | X20: =SUM(S20:W20) -> 4660.2237 | Y20: =SUM(10417/68)*H20 -> 813.90472 | AB20: =SUM(Y20:AA20) -> 813.90472 | AC20: 7.07 | AD20: =SUM(AB20*AC20) -> 5754.3064 | AE20: =SUM(X20+AD20) -> 10414.53 | AF20: =SUM(P20-AE20) -> 3049.2499
A21: 合计 | J21: =SUM(J4:J4) -> 0 | N21: =SUM(N4:N4) -> 0 | P21: =SUM(P4:P4) -> 0 | Q21: =SUM(Q4:Q4) -> 0 | X21: =SUM(X4:X4) -> 0 | AD21: =SUM(AD4:AD4) -> 0 | AF21: =SUM(AF4:AF20) -> 8082.2163

Sheet JOB080374
A1: 2024年08月份LOS毛利表（海运）
A2: PSL表 | B2: 体积cbm | C2: 70.7131
A3: JOB | B3: 集装编号 | C3: 运单编号 | D3: 日期 | E3: 业务 | F3: 发货人 | G3: 收货人 | H3: 计费体积 | I3: 计费重量 | J3: 应 收 | Q3: 总应收 | R3: 起 运 港 成 本 | W3: 代垫运费 | X3: 起运港成本 合计 | Y3: 目的港成本 | AE3: 总支出 | AF3: 利润
J4: 应收RMB | K4: LOS Income(NGN)收到(奈拉) | L4: LOS 收到USD | M4: 美元汇率 dollar currency rate | N4: 应收 到付款USD | O4: 汇率 | P4: 人民币 | R4: 代理商 | S4: 运费+出口报关费 | T4: 提货费 | U4: 装卸费 | V4: 包装费 | Y4: 进口报关费 | Z4: 到门配送费 | AA4: 转运费 | AB4: 目的港支出 | AC4: 汇率 | AD4: 人民币 | AE4: 起运港+目的港
A5: JOB080374 | B5: COLL004108 | C5: 240729000025 | D5: 45534 | E5: 黄颖 | F5: ying | G5: leoyang | H5: 0.3136 | I5: 10 | J5: 753 | P5: =SUM(J5) -> 753 | Q5: =SUM(P5:P14) -> 139455.48 | R5: 赛捷=56265.25 赛捷=1000 | S5: =SUM(57265.25/68)*H5 -> 264.09386 | U5: =SUM(1400/68)*H5 -> 6.4564706 | X5: =SUM(S5:W5) -> 270.55033 | Y5: =SUM(10328/68)*H5 -> 47.630306 | AA5: =SUM(277.12/68)*H5 -> 1.2780122 | AB5: =SUM(Y5:AA5) -> 48.908318 | AC5: 7.06 | AD5: =SUM(AB5*AC5) -> 345.29273 | AE5: =SUM(X5+AD5) -> 615.84306 | AF5: =SUM(P5-AE5) -> 137.15694
C6: 240804000005 | D6: 45534 | E6: 黄颖 | F6: ying | G6: Sunday Adelena | H6: 31.7366 | I6: 8596 | J6: 70573.12 | P6: =SUBTOTAL(9,J6) -> 70573.12 | S6: =SUM(57265.25/68)*H6 -> 26726.534 | U6: =SUM(1400/68)*H6 -> 653.40059 | X6: =SUM(S6:W6) -> 27379.935 | Y6: =SUM(10328/68)*H6 -> 4820.2295 | AA6: =SUM(277.12/68)*H6 -> 129.33598 | AB6: =SUM(Y6:AA6) -> 4949.5655 | AC6: 7.06 | AD6: =SUM(AB6*AC6) -> 34943.932 | AE6: =SUM(X6+AD6) -> 62323.867 | AF6: =SUM(P6-AE6) -> 8249.2529
C7: 240812000053 | D7: 45534 | E7: Sam.Pao | F7: Sam.Pao | G7: Yusky | H7: 1.748 | I7: 203 | J7: 3548.44 | P7: =SUBTOTAL(9,J7) -> 3548.44 | S7: =SUM(57265.25/68)*H7 -> 1472.0538 | U7: =SUM(1400/68)*H7 -> 35.988235 | X7: =SUM(S7:W7) -> 1508.042 | Y7: =SUM(10328/68)*H7 -> 265.49035 | AA7: =SUM(277.12/68)*H7 -> 7.1236141 | AB7: =SUM(Y7:AA7) -> 272.61397 | AC7: 7.06 | AD7: =SUM(AB7*AC7) -> 1924.6546 | AE7: =SUM(X7+AD7) -> 3432.6966 | AF7: =SUM(P7-AE7) -> 115.74338
C8: 240811000002 | D8: 45534 | E8: 黄颖 | F8: ying | G8: yanjiafu | H8: 0.293 | I8: 65.5 | K8: 295731 | M8: =SUM(K8/N8) -> 1737.5499 | N8: 170.2 | O8: 7.15 | P8: =SUM(N8*O8) -> 1216.93 | S8: =SUM(57265.25/68)*H8 -> 246.74586 | T8: 355.58 | U8: =SUM(1400/68)*H8 -> 6.0323529 | W8: 54.56 | X8: =SUM(S8:W8) -> 662.91821 | Y8: =SUM(10328/68)*H8 -> 44.501529 | Z8: 27.05 | AA8: =SUM(277.12/68)*H8 -> 1.1940612 | AB8: =SUM(Y8:AA8) -> 72.745591 | AC8: 7.06 | AD8: =SUM(AB8*AC8) -> 513.58387 | AE8: =SUM(X8+AD8) -> 1176.5021 | AF8: =SUM(P8-AE8) -> 40.427921
C9: 240812000054 | D9: 45534 | E9: Sam.Pao | F9: Sam.Pao | G9: Yusky | H9: 0.2239 | I9: 43 | J9: 454.5 | P9: =SUBTOTAL(9,J9) -> 454.5 | S9: =SUM(57265.25/68)*H9 -> 188.55426 | U9: =SUM(1400/68)*H9 -> 4.6097059 | X9: =SUM(S9:W9) -> 193.16396 | Y9: =SUM(10328/68)*H9 -> 34.006459 | AA9: =SUM(277.12/68)*H9 -> 0.91245835 | AB9: =SUM(Y9:AA9) -> 34.918917 | AC9: 7.06 | AD9: =SUM(AB9*AC9) -> 246.52756 | AE9: =SUM(X9+AD9) -> 439.69152 | AF9: =SUM(P9-AE9) -> 14.808482
C10: 240812000055 | D10: 45534 | E10: Sam.Pao | F10: Sam.Pao | G10: Yusky | H10: 0.1922 | I10: 29 | J10: 390.2 | P10: =SUBTOTAL(9,J10) -> 390.2 | S10: =SUM(57265.25/68)*H10 -> 161.85854 | U10: =SUM(1400/68)*H10 -> 3.9570588 | X10: =SUM(S10:W10) -> 165.8156 | Y10: =SUM(10328/68)*H10 -> 29.191788 | AA10: =SUM(277.12/68)*H10 -> 0.78327153 | AB10: =SUM(Y10:AA10) -> 29.97506 | AC10: 7.06 | AD10: =SUM(AB10*AC10) -> 211.62392 | AE10: =SUM(X10+AD10) -> 377.43953 | AF10: =SUM(P10-AE10) -> 12.760474
C11: 240812000056 | D11: 45534 | E11: Sam.Pao | F11: Sam.Pao | G11: Yusky | H11: 0.1689 | I11: 34 | J11: 342.85 | P11: =SUBTOTAL(9,J11) -> 342.85 | S11: =SUM(57265.25/68)*H11 -> 142.23678 | U11: =SUM(1400/68)*H11 -> 3.4773529 | X11: =SUM(S11:W11) -> 145.71413 | Y11: =SUM(10328/68)*H11 -> 25.652929 | AA11: =SUM(277.12/68)*H11 -> 0.68831718 | AB11: =SUM(Y11:AA11) -> 26.341247 | AC11: 7.06 | AD11: =SUM(AB11*AC11) -> 185.9692 | AE11: =SUM(X11+AD11) -> 331.68333 | AF11: =SUM(P11-AE11) -> 11.166671
C12: 240813000001 | D12: 45534 | E12: Sam.Pao | F12: Sam.Pao | G12: SKY JET | H12: 1.98 | I12: 736 | J12: 3388.18 | P12: =SUBTOTAL(9,J12) -> 3388.18 | S12: =SUM(57265.25/68)*H12 -> 1667.4293 | U12: =SUM(1400/68)*H12 -> 40.764706 | X12: =SUM(S12:W12) -> 1708.194 | Y12: =SUM(10328/68)*H12 -> 300.72706 | AA12: =SUM(277.12/68)*H12 -> 8.0690824 | AB12: =SUM(Y12:AA12) -> 308.79614 | AC12: 7.06 | AD12: =SUM(AB12*AC12) -> 2180.1008 | AE12: =SUM(X12+AD12) -> 3888.2948 | AF12: =SUM(P12-AE12) -> -500.1148
C13: 240613000018 | D13: 45506 | E13: Sam.Pao | F13: Sam.Pao | G13: ChenGaoHong | H13: 1.087 | I13: 234 | J13: 2370 | P13: =SUBTOTAL(9,J13) -> 2370 | S13: =SUM(57265.25/68)*H13 -> 915.40186 | U13: =SUM(1400/68)*H13 -> 22.379412 | X13: =SUM(S13:W13) -> 937.78128 | Y13: =SUM(10328/68)*H13 -> 165.09612 | AA13: =SUM(277.12/68)*H13 -> 4.4298447 | AB13: =SUM(Y13:AA13) -> 169.52596 | AC13: 7.06 | AD13: =SUM(AB13*AC13) -> 1196.8533 | AE13: =SUM(X13+AD13) -> 2134.6346 | AF13: =SUM(P13-AE13) -> 235.36543
C14: 240813000002 | D14: 45534 | E14: Sam.Pao | F14: Sam.Pao | G14: SKY JET | H14: 32.97 | I14: 3574 | J14: 56418.26 | P14: =SUBTOTAL(9,J14) -> 56418.26 | S14: =SUM(57265.25/68)*H14 -> 27765.225 | U14: =SUM(1400/68)*H14 -> 678.79412 | X14: =SUM(S14:W14) -> 28444.019 | Y14: =SUM(10328/68)*H14 -> 5007.5612 | AA14: =SUM(277.12/68)*H14 -> 134.36245 | AB14: =SUM(Y14:AA14) -> 5141.9236 | AC14: 7.06 | AD14: =SUM(AB14*AC14) -> 36301.981 | AE14: =SUM(X14+AD14) -> 64746 | AF14: =SUM(P14-AE14) -> -8327.7398
A15: 合计 | J15: =SUM(J4:J4) -> 0 | N15: =SUM(N4:N4) -> 0 | P15: =SUM(P4:P4) -> 0 | Q15: =SUM(Q4:Q4) -> 0 | X15: =SUM(X4:X4) -> 0 | AD15: =SUM(AD4:AD4) -> 0 | AF15: =SUM(AF4:AF14) -> -11.172348

Sheet JOB080371
A1: 2024年08月份LOS毛利表（海运）
A2: PSL表 | B2: 体积cbm | C2: 68
A3: JOB | B3: 集装编号 | C3: 运单编号 | D3: 日期 | E3: 业务 | F3: 发货人 | G3: 收货人 | H3: 计费体积 | I3: 计费重量 | J3: 应 收 | Q3: 总应收 | R3: 起 运 港 成 本 | W3: 代垫运费 | X3: 起运港成本 合计 | Y3: 目的港成本 | AE3: 总支出 | AF3: 利润
J4: 应收RMB | K4: LOS Income(NGN)收到(奈拉) | L4: LOS 收到USD | M4: 美元汇率 dollar currency rate | N4: 应收 到付款USD | O4: 汇率 | P4: 人民币 | R4: 代理商 | S4: 运费+出口报关费 | T4: 提货费 | U4: 装卸费 | V4: 包装费 | Y4: 进口报关费 | Z4: 到门配送费 | AA4: 转运费 | AB4: 目的港支出 | AC4: 汇率 | AD4: 人民币 | AE4: 起运港+目的港
A5: JOB080371 | B5: COLL004105整柜 | C5: 240812000027 | D5: 45498 | E5: Sam.Pao | F5: Sam.Pao | G5: JunYue hotel | H5: 68 | I5: 21890 | J5: 68172 | K5: 21300000 | M5: =SUM(K5/N5) -> 1694.5579 | N5: 12569.65 | O5: 7.15 | P5: =SUM(N5*O5+J5) -> 158045 | Q5: =SUM(P5) -> 158045 | R5: 华茂青松 | S5: 61677 | X5: =SUM(S5:W5) -> 61677 | Y5: 0 | AB5: =SUM(Y5:AA5) -> 0 | AC5: 7.15 | AD5: =SUM(AB5*AC5) -> 0 | AE5: =SUM(X5+AD5) -> 61677 | AF5: =SUM(P5-AE5) -> 96367.997
A6: 合计 | J6: =SUM(J4:J4) -> 0 | N6: =SUM(N4:N4) -> 0 | P6: =SUM(P4:P4) -> 0 | Q6: =SUM(Q4:Q4) -> 0 | X6: =SUM(X4:X4) -> 0 | AD6: =SUM(AD4:AD4) -> 0 | AF6: =SUM(AF4:AF5) -> 96367.997

Sheet JOB080387
A1: 2024年08月份LOS毛利表（海运）
A2: PSL表 | B2: 体积cbm | C2: 73.374
A3: JOB | B3: 集装编号 | C3: 运单编号 | D3: 日期 | E3: 业务 | F3: 发货人 | G3: 收货人 | H3: 计费体积 | I3: 计费重量 | J3: 应 收 | Q3: 总应收 | R3: 起 运 港 成 本 | W3: 代垫运费 | X3: 起运港成本 合计 | Y3: 目的港成本 | AE3: 总支出 | AF3: 利润
J4: 应收RMB | K4: LOS Income(NGN)收到(奈拉) | L4: LOS 收到USD | M4: 美元汇率 dollar currency rate | N4: 应收 到付款USD | O4: 汇率 | P4: 人民币 | R4: 代理商 | S4: 运费+出口报关费 | T4: 提货费 | U4: 装卸费 | V4: 包装费 | Y4: 进口报关费 | Z4: 到门配送费 | AA4: 转运费 | AB4: 目的港支出 | AC4: 汇率 | AD4: 人民币 | AE4: 起运港+目的港
A5: JOB080387 | B5: COLL004121 | C5: 240807000029 | D5: 45516 | E5: 吕沛霖 | F5: 喵喵速运-Layne | G5: Candice Ding | H5: 0.55 | I5: 148 | J5: 1768.88 | P5: =SUM(J5) -> 1768.88 | Q5: =SUM(P5:P23) -> 161460.15 | R5: 登凯=50475 赛捷=1000 拖车费=1670 杂费=61 过磅费=53 | S5: =SUM(53259/68)*H5 -> 430.77132 | U5: =SUM(1300/68)*H5 -> 10.514706 | X5: =SUM(S5:W5) -> 441.28603 | Y5: =SUM(10737.46/68)*H5 -> 86.847103 | Z5: 47.2 | AB5: =SUM(Y5:AA5) -> 134.0471 | AC5: 7.06 | AD5: =SUM(AB5*AC5) -> 946.37255 | AE5: =SUM(X5+AD5) -> 1387.6586 | AF5: =SUM(P5-AE5) -> 381.22142
C6: 240810000003 | D6: 45516 | E6: 黄颖 | F6: ying | G6: Sunday Adelena | H6: 0.693 | I6: 463 | J6: 1600 | P6: =SUBTOTAL(9,J6) -> 1600 | S6: =SUM(53259/68)*H6 -> 542.77187 | U6: =SUM(1300/68)*H6 -> 13.248529 | X6: =SUM(S6:W6) -> 556.0204 | Y6: =SUM(10737.46/68)*H6 -> 109.42735 | AB6: =SUM(Y6:AA6) -> 109.42735 | AC6: 7.06 | AD6: =SUM(AB6*AC6) -> 772.55709 | AE6: =SUM(X6+AD6) -> 1328.5775 | AF6: =SUM(P6-AE6) -> 271.42251
C7: 240613000018 | D7: 45506 | E7: Sam.Pao | F7: Sam.Pao | G7: ChenGaoHong | H7: 0.044 | I7: 28 | J7: 96 | P7: =SUBTOTAL(9,J7) -> 96 | S7: =SUM(53259/68)*H7 -> 34.461706 | U7: =SUM(1300/68)*H7 -> 0.84117647 | X7: =SUM(S7:W7) -> 35.302882 | Y7: =SUM(10737.46/68)*H7 -> 6.9477682 | AB7: =SUM(Y7:AA7) -> 6.9477682 | AC7: 7.06 | AD7: =SUM(AB7*AC7) -> 49.051244 | AE7: =SUM(X7+AD7) -> 84.354126 | AF7: =SUM(P7-AE7) -> 11.645874
C8: 240811000001 | D8: 45516 | E8: 吕沛霖 | F8: 喵喵速运-Layne | G8: FRANK | H8: 8.3155 | I8: 4780 | K8: 4494672 | M8: =SUM(K8/N8) -> 1773.8649 | N8: 2533.83 | O8: 7.24 | P8: =SUM(N8*O8) -> 18344.929 | S8: =SUM(53259/68)*H8 -> 6512.8708 | U8: =SUM(1300/68)*H8 -> 158.97279 | X8: =SUM(S8:W8) -> 6671.8436 | Y8: =SUM(10737.46/68)*H8 -> 1313.0492 | AB8: =SUM(Y8:AA8) -> 1313.0492 | AC8: 7.06 | AD8: =SUM(AB8*AC8) -> 9270.1277 | AE8: =SUM(X8+AD8) -> 15941.971 | AF8: =SUM(P8-AE8) -> 2402.9579
C9: 240728000003 | D9: 45506 | E9: Sam.Pao | F9: Sam.Pao | G9: Nick Wang | H9: 0.236 | I9: 94 | J9: 636 | P9: =SUBTOTAL(9,J9) -> 636 | S9: =SUM(53259/68)*H9 -> 184.84006 | U9: =SUM(1300/68)*H9 -> 4.5117647 | X9: =SUM(S9:W9) -> 189.35182 | Y9: =SUM(10737.46/68)*H9 -> 37.265302 | AB9: =SUM(Y9:AA9) -> 37.265302 | AC9: 7.06 | AD9: =SUM(AB9*AC9) -> 263.09303 | AE9: =SUM(X9+AD9) -> 452.44486 | AF9: =SUM(P9-AE9) -> 183.55514
C10: 240811000012 | D10: 45516 | E10: Sam.Pao | F10: Sam.Pao | G10: Maxim | H10: 1.4797 | I10: 153.4 | J10: 3842.88 | P10: =SUBTOTAL(9,J10) -> 3842.88 | S10: =SUM(53259/68)*H10 -> 1158.9315 | U10: =SUM(1300/68)*H10 -> 28.288382 | X10: =SUM(S10:W10) -> 1187.2199 | Y10: =SUM(10737.46/68)*H10 -> 233.65029 | Z10: 8.85 | AB10: =SUM(Y10:AA10) -> 242.50029 | AC10: 7.06 | AD10: =SUM(AB10*AC10) -> 1712.052 | AE10: =SUM(X10+AD10) -> 2899.2719 | AF10: =SUM(P10-AE10) -> 943.60808
C11: 240812000069 | D11: 45516 | E11: 黄颖 | F11: ying | G11: zhounengquan | H11: 0.045 | I11: 52.5 | J11: 565.2 | P11: =SUBTOTAL(9,J11) -> 565.2 | S11: =SUM(53259/68)*H11 -> 35.244926 | U11: =SUM(1300/68)*H11 -> 0.86029412 | X11: =SUM(S11:W11) -> 36.105221 | Y11: =SUM(10737.46/68)*H11 -> 7.1056721 | Z11: 50.15 | AB11: =SUM(Y11:AA11) -> 57.255672 | AC11: 7.06 | AD11: =SUM(AB11*AC11) -> 404.22504 | AE11: =SUM(X11+AD11) -> 440.33027 | AF11: =SUM(P11-AE11) -> 124.86973
C12: 240813000034 | D12: 45516 | E12: 吕沛霖 | F12: 喵喵速运-Layne | G12: Hu Hai Liang | H12: 4.253 | I12: 1141 | K12: 2383535 | M12: =SUM(K12/N12) -> 1751.2714 | N12: 1361.0312 | O12: 7.12 | P12: =SUM(N12*O12) -> 9690.5421 | S12: =SUM(53259/68)*H12 -> 3331.0372 | U12: =SUM(1300/68)*H12 -> 81.307353 | X12: =SUM(S12:W12) -> 3412.3445 | Y12: =SUM(10737.46/68)*H12 -> 671.56496 | AB12: =SUM(Y12:AA12) -> 671.56496 | AC12: 7.06 | AD12: =SUM(AB12*AC12) -> 4741.2486 | AE12: =SUM(X12+AD12) -> 8153.5931 | AF12: =SUM(P12-AE12) -> 1536.949
C13: 240814000018 | D13: 45516 | E13: 黄颖 | F13: ying | G13: baikaibo | H13: 0.414 | I13: 225 | J13: 1588 | P13: =SUBTOTAL(9,J13) -> 1588 | S13: =SUM(53259/68)*H13 -> 324.25332 | U13: =SUM(1300/68)*H13 -> 7.9147059 | X13: =SUM(S13:W13) -> 332.16803 | Y13: =SUM(10737.46/68)*H13 -> 65.372183 | Z13: 81.63 | AB13: =SUM(Y13:AA13) -> 147.00218 | AC13: 7.06 | AD13: =SUM(AB13*AC13) -> 1037.8354 | AE13: =SUM(X13+AD13) -> 1370.0034 | AF13: =SUM(P13-AE13) -> 217.99656
C14: 240814000019 | D14: 45516 | E14: 黄颖 | F14: ying | G14: Nura | H14: 1.0206 | I14: 428 | J14: 2389.6 | P14: =SUBTOTAL(9,J14) -> 2389.6 | S14: =SUM(53259/68)*H14 -> 799.35493 | U14: =SUM(1300/68)*H14 -> 19.511471 | X14: =SUM(S14:W14) -> 818.8664 | Y14: =SUM(10737.46/68)*H14 -> 161.15664 | AB14: =SUM(Y14:AA14) -> 161.15664 | AC14: 7.06 | AD14: =SUM(AB14*AC14) -> 1137.7659 | AE14: =SUM(X14+AD14) -> 1956.6323 | AF14: =SUM(P14-AE14) -> 432.9677
C15: 240814000024 | D15: 45516 | E15: 黄颖 | F15: ying | G15: baikaibo | H15: 0.0407 | I15: 2 | J15: 835.2 | P15: =SUBTOTAL(9,J15) -> 835.2 | S15: =SUM(53259/68)*H15 -> 31.877078 | U15: =SUM(1300/68)*H15 -> 0.77808824 | X15: =SUM(S15:W15) -> 32.655166 | Y15: =SUM(10737.46/68)*H15 -> 6.4266856 | Z15: 81.63 | AB15: =SUM(Y15:AA15) -> 88.056686 | AC15: 7.06 | AD15: =SUM(AB15*AC15) -> 621.6802 | AE15: =SUM(X15+AD15) -> 654.33537 | AF15: =SUM(P15-AE15) -> 180.86463
C16: 240815000013 | D16: 45516 | E16: 黄颖 | F16: ying | G16: liangyu | H16: 0.2945 | I16: 235 | J16: 1105 | P16: =SUBTOTAL(9,J16) -> 1105 | S16: =SUM(53259/68)*H16 -> 230.65846 | U16: =SUM(1300/68)*H16 -> 5.6301471 | W16: 316 | X16: =SUM(S16:W16) -> 552.28861 | Y16: =SUM(10737.46/68)*H16 -> 46.502676 | AB16: =SUM(Y16:AA16) -> 46.502676 | AC16: 7.06 | AD16: =SUM(AB16*AC16) -> 328.30889 | AE16: =SUM(X16+AD16) -> 880.5975 | AF16: =SUM(P16-AE16) -> 224.4025
C17: 240815000041 | D17: 45516 | E17: Bella | F17: Bella Chan | G17: Shuaibu musa | H17: 6.6096 | I17: 2430 | J17: 20266.26 | P17: =SUBTOTAL(9,J17) -> 20266.26 | S17: =SUM(53259/68)*H17 -> 5176.7748 | U17: =SUM(1300/68)*H17 -> 126.36 | X17: =SUM(S17:W17) -> 5303.1348 | Y17: =SUM(10737.46/68)*H17 -> 1043.6811 | AB17: =SUM(Y17:AA17) -> 1043.6811 | AC17: 7.06 | AD17: =SUM(AB17*AC17) -> 7368.3887 | AE17: =SUM(X17+AD17) -> 12671.523 | AF17: =SUM(P17-AE17) -> 7594.7365
C18: 240816000023 | D18: 45516 | E18: 黄颖 | F18: ying | G18: libiao | H18: 1.9876 | I18: 92 | J18: 4277.5 | P18: =SUBTOTAL(9,J18) -> 4277.5 | S18: =SUM(53259/68)*H18 -> 1556.7292 | U18: =SUM(1300/68)*H18 -> 37.998235 | W18: 99 | X18: =SUM(S18:W18) -> 1693.7275 | Y18: =SUM(10737.46/68)*H18 -> 313.84964 | Z18: 47.2 | AB18: =SUM(Y18:AA18) -> 361.04964 | AC18: 7.06 | AD18: =SUM(AB18*AC18) -> 2549.0105 | AE18: =SUM(X18+AD18) -> 4242.7379 | AF18: =SUM(P18-AE18) -> 34.762068
C19: 240818000009 | D19: 45516 | E19: 朱小飞 | F19: Isabel Zhu | G19: Wu Jiao Xing | H19: 0.1955 | I19: 39 | J19: 468 | P19: =SUBTOTAL(9,J19) -> 468 | S19: =SUM(53259/68)*H19 -> 153.11963 | U19: =SUM(1300/68)*H19 -> 3.7375 | X19: =SUM(S19:W19) -> 156.85712 | Y19: =SUM(10737.46/68)*H19 -> 30.870197 | AB19: =SUM(Y19:AA19) -> 30.870197 | AC19: 7.06 | AD19: =SUM(AB19*AC19) -> 217.94359 | AE19: =SUM(X19+AD19) -> 374.80072 | AF19: =SUM(P19-AE19) -> 93.199281
C20: 240818000013 | D20: 45516 | E20: 朱小飞 | F20: Isabel Zhu | G20: Lin Bao Zhen | H20: 1.5335 | I20: 305 | K20: 1228413.6 | M20: =SUM(K20/N20) -> 1744.98 | N20: 703.97 | O20: 7.15 | P20: =SUM(N20*O20) -> 5033.3855 | S20: =SUM(53259/68)*H20 -> 1201.0688 | U20: =SUM(1300/68)*H20 -> 29.316912 | X20: =SUM(S20:W20) -> 1230.3857 | Y20: =SUM(10737.46/68)*H20 -> 242.14551 | Z20: 248 | AB20: =SUM(Y20:AA20) -> 490.14551 | AC20: 7.06 | AD20: =SUM(AB20*AC20) -> 3460.4273 | AE20: =SUM(X20+AD20) -> 4690.813 | AF20: =SUM(P20-AE20) -> 342.57249
C21: 240819000004 | D21: 45532 | E21: Bella | F21: Bella Chan | G21: FENG | H21: 4.6 | I21: 2063 | J21: 9940 | P21: =SUBTOTAL(9,J21) -> 9940 | S21: =SUM(53259/68)*H21 -> 3602.8147 | U21: =SUM(1300/68)*H21 -> 87.941176 | X21: =SUM(S21:W21) -> 3690.7559 | Y21: =SUM(10737.46/68)*H21 -> 726.35759 | AB21: =SUM(Y21:AA21) -> 726.35759 | AC21: 7.06 | AD21: =SUM(AB21*AC21) -> 5128.0846 | AE21: =SUM(X21+AD21) -> 8818.8405 | AF21: =SUM(P21-AE21) -> 1121.1595
C22: 240819000017 | D22: 45516 | E22: 吕沛霖 | F22: 喵喵速运-Layne | G22: WEI PING | H22: 23.494 | I22: 2608 | J22: 50190.17 | P22: =SUBTOTAL(9,J22) -> 50190.17 | S22: =SUM(53259/68)*H22 -> 18400.984 | U22: =SUM(1300/68)*H22 -> 449.15 | V22: 960 | W22: 146.5 | X22: =SUM(S22:W22) -> 19956.635 | Y22: =SUM(10737.46/68)*H22 -> 3709.7924 | AB22: =SUM(Y22:AA22) -> 3709.7924 | AC22: 7.06 | AD22: =SUM(AB22*AC22) -> 26191.135 | AE22: =SUM(X22+AD22) -> 46147.769 | AF22: =SUM(P22-AE22) -> 4042.4009
C23: 240821000040 | D23: 45516 | E23: Sam.Pao | F23: Sam.Pao | G23: SKY JET | H23: 17.568 | I23: 2034 | J23: 28822.6 | P23: =SUBTOTAL(9,J23) -> 28822.6 | S23: =SUM(53259/68)*H23 -> 13759.619 | U23: =SUM(1300/68)*H23 -> 335.85882 | X23: =SUM(S23:W23) -> 14095.478 | Y23: =SUM(10737.46/68)*H23 -> 2774.0544 | AB23: =SUM(Y23:AA23) -> 2774.0544 | AC23: 7.06 | AD23: =SUM(AB23*AC23) -> 19584.824 | AE23: =SUM(X23+AD23) -> 33680.302 | AF23: =SUM(P23-AE23) -> -4857.702
A24: 合计 | J24: =SUM(J4:J4) -> 0 | N24: =SUM(N4:N4) -> 0 | P24: =SUM(P4:P4) -> 0 | Q24: =SUM(Q4:Q4) -> 0 | X24: =SUM(X4:X4) -> 0 | AD24: =SUM(AD4:AD4) -> 0 | AF24: =SUM(AF4:AF23) -> 15283.59

Sheet JOB100326
A1: 2024年08月份LOS毛利表（海运）
A2: PSL表 | B2: 体积cbm | C2: 88.6579
A3: JOB | B3: 集装编号 | C3: 运单编号 | D3: 日期 | E3: 业务 | F3: 发货人 | G3: 收货人 | H3: 计费体积 | I3: 计费重量 | J3: 应 收 | Q3: 总应收 | R3: 起 运 港 成 本 | W3: 代垫运费 | X3: 起运港成本 合计 | Y3: 目的港成本 | AE3: 总支出 | AF3: 利润
J4: 应收RMB | K4: LOS Income(NGN)收到(奈拉) | L4: LOS 收到USD | M4: 美元汇率 dollar currency rate | N4: 应收 到付款USD | O4: 汇率 | P4: 人民币 | R4: 代理商 | S4: 运费+出口报关费 | T4: 提货费 | U4: 装卸费 | V4: 包装费 | Y4: 进口报关费 | Z4: 到门配送费 | AA4: 转运费 | AB4: 目的港支出 | AC4: 汇率 | AD4: 人民币 | AE4: 起运港+目的港
A5: JOB100326 | B5: COLL004189 | C5: 240613000018 | D5: 45532 | E5: Sam.Pao | F5: Sam.Pao | G5: ChenGaoHong | H5: 21.6755 | I5: 6691 | J5: 46755 | P5: =SUBTOTAL(9,J5) -> 46755 | Q5: =SUM(P5:P29) -> 179091.83 | R5: 登凯=48262.5 赛捷=2800 拖车费=1670 杂费=61 过磅费=63 | S5: =SUM(52856.5/68)*H5 -> 16848.398 | U5: =SUM(1500/68)*H5 -> 478.13603 | V5: 420 | X5: =SUM(S5:W5) -> 17746.534 | Y5: =SUM(10737.46/68)*H5 -> 3422.6443 | AA5: =SUM(247.79/68)*H5 -> 78.984884 | AB5: =SUM(Y5:AA5) -> 3501.6292 | AC5: 7.12 | AD5: =SUM(AB5*AC5) -> 24931.6 | AE5: =SUM(X5+AD5) -> 42678.134 | AF5: =SUM(P5-AE5) -> 4076.866
C6: 240816000038 | D6: 45532 | E6: 朱小飞 | F6: Isabel Zhu | G6: Nicolas | H6: 0.1557 | I6: 40.2 | J6: 602 | P6: =SUM(J6) -> 602 | S6: =SUM(52856.5/68)*H6 -> 121.02584 | U6: =SUM(1500/68)*H6 -> 3.4345588 | X6: =SUM(S6:W6) -> 124.4604 | Y6: =SUM(10737.46/68)*H6 -> 24.585625 | Z6: 21.12 | AA6: =SUM(247.79/68)*H6 -> 0.56736622 | AB6: =SUM(Y6:AA6) -> 46.272992 | AC6: 7.12 | AD6: =SUM(AB6*AC6) -> 329.4637 | AE6: =SUM(X6+AD6) -> 453.9241 | AF6: =SUM(P6-AE6) -> 148.0759
C7: 240818000042 | D7: 45532 | E7: 黄颖 | F7: ying | G7: zhounengquan | H7: 0.0276 | I7: 60 | K7: 120050 | M7: =SUM(K7/N7) -> 1800.66 | N7: 66.67 | O7: 7.12 | P7: =SUM(N7*O7) -> 474.6904 | S7: =SUM(52856.5/68)*H7 -> 21.453521 | U7: =SUM(1500/68)*H7 -> 0.60882353 | X7: =SUM(S7:W7) -> 22.062344 | Y7: =SUM(10737.46/68)*H7 -> 4.3581455 | Z7: 35.4 | AA7: =SUM(247.79/68)*H7 -> 0.10057359 | AB7: =SUM(Y7:AA7) -> 39.858719 | AC7: 7.12 | AD7: =SUM(AB7*AC7) -> 283.79408 | AE7: =SUM(X7+AD7) -> 305.85642 | AF7: =SUM(P7-AE7) -> 168.83398
C8: 240819000004 | D8: 45532 | E8: Bella | F8: Bella Chan | G8: FENG | H8: 0.0982 | I8: 59 | J8: 212 | P8: =SUBTOTAL(9,J8) -> 212 | S8: =SUM(52856.5/68)*H8 -> 76.331004 | U8: =SUM(1500/68)*H8 -> 2.1661765 | X8: =SUM(S8:W8) -> 78.497181 | Y8: =SUM(10737.46/68)*H8 -> 15.506155 | AA8: =SUM(247.79/68)*H8 -> 0.35783791 | AB8: =SUM(Y8:AA8) -> 15.863993 | AC8: 7.12 | AD8: =SUM(AB8*AC8) -> 112.95163 | AE8: =SUM(X8+AD8) -> 191.44881 | AF8: =SUM(P8-AE8) -> 20.551186
C9: 240819000033 | D9: 45532 | E9: 吕沛霖 | F9: 喵喵速运-Layne | G9: Candice Ding | H9: 0.2086 | I9: 344 | K9: 383195 | M9: =SUM(K9/N9) -> 1811.7967 | N9: 211.5 | O9: 7.3 | P9: =SUM(N9*O9) -> 1543.95 | S9: =SUM(52856.5/68)*H9 -> 162.14509 | U9: =SUM(1500/68)*H9 -> 4.6014706 | X9: =SUM(S9:W9) -> 166.74656 | Y9: =SUM(10737.46/68)*H9 -> 32.938738 | Z9: 46.5 | AA9: =SUM(247.79/68)*H9 -> 0.76013226 | AB9: =SUM(Y9:AA9) -> 80.19887 | AC9: 7.12 | AD9: =SUM(AB9*AC9) -> 571.01595 | AE9: =SUM(X9+AD9) -> 737.76251 | AF9: =SUM(P9-AE9) -> 806.18749
C10: 240820000001 | D10: 45532 | E10: 朱小飞 | F10: Isabel Zhu | G10: Mr Michael | H10: 7.0865 | I10: 599 | J10: 17258.7 | P10: =SUBTOTAL(9,J10) -> 17258.7 | S10: =SUM(52856.5/68)*H10 -> 5508.3469 | U10: =SUM(1500/68)*H10 -> 156.31985 | V10: 300 | X10: =SUM(S10:W10) -> 5964.6667 | Y10: =SUM(10737.46/68)*H10 -> 1118.9854 | AA10: =SUM(247.79/68)*H10 -> 25.822998 | AB10: =SUM(Y10:AA10) -> 1144.8084 | AC10: 7.12 | AD10: =SUM(AB10*AC10) -> 8151.0361 | AE10: =SUM(X10+AD10) -> 14115.703 | AF10: =SUM(P10-AE10) -> 3142.9972
C11: 240823000021 | D11: 45532 | E11: 吕沛霖 | F11: 喵喵速运-Layne | G11: FRANK | H11: 7.4589 | I11: 3300 | K11: 3229875 | M11: =SUM(K11/N11) -> 1650 | N11: 1957.5 | O11: 7.12 | P11: =SUM(N11*O11) -> 13937.4 | S11: =SUM(52856.5/68)*H11 -> 5797.8139 | U11: =SUM(1500/68)*H11 -> 164.53456 | X11: =SUM(S11:W11) -> 5962.3485 | Y11: =SUM(10737.46/68)*H11 -> 1177.7888 | AA11: =SUM(247.79/68)*H11 -> 27.180012 | AB11: =SUM(Y11:AA11) -> 1204.9688 | AC11: 7.12 | AD11: =SUM(AB11*AC11) -> 8579.3782 | AE11: =SUM(X11+AD11) -> 14541.727 | AF11: =SUM(P11-AE11) -> -604.32665
C12: 240826000011 | D12: 45532 | E12: 罗珮文 | F12: Shirley | G12: Yusky | H12: 6.3305 | I12: 880 | J12: 10555.28 | P12: =SUBTOTAL(9,J12) -> 10555.28 | S12: =SUM(52856.5/68)*H12 -> 4920.707 | U12: =SUM(1500/68)*H12 -> 139.64338 | X12: =SUM(S12:W12) -> 5060.3503 | Y12: =SUM(10737.46/68)*H12 -> 999.61015 | AA12: =SUM(247.79/68)*H12 -> 23.068156 | AB12: =SUM(Y12:AA12) -> 1022.6783 | AC12: 7.12 | AD12: =SUM(AB12*AC12) -> 7281.4696 | AE12: =SUM(X12+AD12) -> 12341.82 | AF12: =SUM(P12-AE12) -> -1786.5399
C13: 240826000013 | D13: 45532 | E13: 罗珮文 | F13: Shirley | G13: Yusky | H13: 0.699 | I13: 105 | J13: 1165.58 | P13: =SUBTOTAL(9,J13) -> 1165.58 | S13: =SUM(52856.5/68)*H13 -> 543.33373 | U13: =SUM(1500/68)*H13 -> 15.419118 | X13: =SUM(S13:W13) -> 558.75285 | Y13: =SUM(10737.46/68)*H13 -> 110.37477 | AA13: =SUM(247.79/68)*H13 -> 2.5471354 | AB13: =SUM(Y13:AA13) -> 112.92191 | AC13: 7.12 | AD13: =SUM(AB13*AC13) -> 804.00399 | AE13: =SUM(X13+AD13) -> 1362.7568 | AF13: =SUM(P13-AE13) -> -197.17683
C14: 240826000015 | D14: 45532 | E14: 罗珮文 | F14: Shirley | G14: Yusky | H14: 0.2907 | I14: 36 | J14: 483.58 | P14: =SUBTOTAL(9,J14) -> 483.58 | S14: =SUM(52856.5/68)*H14 -> 225.96154 | U14: =SUM(1500/68)*H14 -> 6.4125 | X14: =SUM(S14:W14) -> 232.37404 | Y14: =SUM(10737.46/68)*H14 -> 45.902642 | AA14: =SUM(247.79/68)*H14 -> 1.0593023 | AB14: =SUM(Y14:AA14) -> 46.961944 | AC14: 7.12 | AD14: =SUM(AB14*AC14) -> 334.36904 | AE14: =SUM(X14+AD14) -> 566.74308 | AF14: =SUM(P14-AE14) -> -83.163077
C15: 240826000016 | D15: 45532 | E15: 罗珮文 | F15: Shirley | G15: Yusky | H15: 0.5572 | I15: 42 | J15: 928.8 | P15: =SUBTOTAL(9,J15) -> 928.8 | S15: =SUM(52856.5/68)*H15 -> 433.11238 | U15: =SUM(1500/68)*H15 -> 12.291176 | X15: =SUM(S15:W15) -> 445.40356 | Y15: =SUM(10737.46/68)*H15 -> 87.98401 | AA15: =SUM(247.79/68)*H15 -> 2.0304204 | AB15: =SUM(Y15:AA15) -> 90.014431 | AC15: 7.12 | AD15: =SUM(AB15*AC15) -> 640.90275 | AE15: =SUM(X15+AD15) -> 1086.3063 | AF15: =SUM(P15-AE15) -> -157.5063
C16: 240826000017 | D16: 45532 | E16: 罗珮文 | F16: Shirley | G16: Yusky | H16: 0.1598 | I16: 78 | J16: 266.44 | P16: =SUBTOTAL(9,J16) -> 266.44 | S16: =SUM(52856.5/68)*H16 -> 124.21277 | U16: =SUM(1500/68)*H16 -> 3.525 | X16: =SUM(S16:W16) -> 127.73777 | Y16: =SUM(10737.46/68)*H16 -> 25.233031 | AA16: =SUM(247.79/68)*H16 -> 0.5823065 | AB16: =SUM(Y16:AA16) -> 25.815337 | AC16: 7.12 | AD16: =SUM(AB16*AC16) -> 183.8052 | AE16: =SUM(X16+AD16) -> 311.54298 | AF16: =SUM(P16-AE16) -> -45.102978
C17: 240826000018 | D17: 45532 | E17: 罗珮文 | F17: Shirley | G17: Yusky | H17: 0.141 | I17: 37 | J17: 235.26 | P17: =SUBTOTAL(9,J17) -> 235.26 | S17: =SUM(52856.5/68)*H17 -> 109.59951 | U17: =SUM(1500/68)*H17 -> 3.1102941 | X17: =SUM(S17:W17) -> 112.7098 | Y17: =SUM(10737.46/68)*H17 -> 22.264439 | AA17: =SUM(247.79/68)*H17 -> 0.51379985 | AB17: =SUM(Y17:AA17) -> 22.778239 | AC17: 7.12 | AD17: =SUM(AB17*AC17) -> 162.18106 | AE17: =SUM(X17+AD17) -> 274.89086 | AF17: =SUM(P17-AE17) -> -39.630863
C18: 240826000019 | D18: 45532 | E18: 罗珮文 | F18: Shirley | G18: Yusky | H18: 1.4354 | I18: 186 | J18: 2392.86 | P18: =SUBTOTAL(9,J18) -> 2392.86 | S18: =SUM(52856.5/68)*H18 -> 1115.7385 | U18: =SUM(1500/68)*H18 -> 31.663235 | X18: =SUM(S18:W18) -> 1147.4018 | Y18: =SUM(10737.46/68)*H18 -> 226.65515 | AA18: =SUM(247.79/68)*H18 -> 5.2305554 | AB18: =SUM(Y18:AA18) -> 231.8857 | AC18: 7.12 | AD18: =SUM(AB18*AC18) -> 1651.0262 | AE18: =SUM(X18+AD18) -> 2798.428 | AF18: =SUM(P18-AE18) -> -405.56798
C19: 240826000039 | D19: 45532 | E19: 朱小飞 | F19: Isabel Zhu | G19: Lin Bao Zhen | H19: 1.823 | I19: 321 | K19: 964731.6 | M19: =SUM(K19/N19) -> 1764.005 | N19: 546.89844 | O19: 7.23 | P19: =SUM(N19*O19) -> 3954.0757 | S19: =SUM(52856.5/68)*H19 -> 1417.0206 | U19: =SUM(1500/68)*H19 -> 40.213235 | X19: =SUM(S19:W19) -> 1457.2338 | Y19: =SUM(10737.46/68)*H19 -> 287.85867 | AA19: =SUM(247.79/68)*H19 -> 6.6429584 | AB19: =SUM(Y19:AA19) -> 294.50163 | AC19: 7.12 | AD19: =SUM(AB19*AC19) -> 2096.8516 | AE19: =SUM(X19+AD19) -> 3554.0854 | AF19: =SUM(P19-AE19) -> 399.99031
C20: 240826000045 | D20: 45532 | E20: 黄颖 | F20: ying | G20: Nura | H20: 0.4085 | I20: 179 | J20: 904 | P20: =SUBTOTAL(9,J20) -> 904 | S20: =SUM(52856.5/68)*H20 -> 317.52765 | U20: =SUM(1500/68)*H20 -> 9.0110294 | X20: =SUM(S20:W20) -> 326.53868 | Y20: =SUM(10737.46/68)*H20 -> 64.503712 | AA20: =SUM(247.79/68)*H20 -> 1.488562 | AB20: =SUM(Y20:AA20) -> 65.992274 | AC20: 7.12 | AD20: =SUM(AB20*AC20) -> 469.86499 | AE20: =SUM(X20+AD20) -> 796.40367 | AF20: =SUM(P20-AE20) -> 107.59633
C21: 240827000034 | D21: 45532 | E21: 陆总 | F21: 陆梓龙 | G21: jizong | H21: 9.2 | I21: 7350 | J21: 24057.26 | P21: =SUBTOTAL(9,J21) -> 24057.26 | S21: =SUM(52856.5/68)*H21 -> 7151.1735 | U21: =SUM(1500/68)*H21 -> 202.94118 | X21: =SUM(S21:W21) -> 7354.1147 | Y21: =SUM(10737.46/68)*H21 -> 1452.7152 | AA21: =SUM(247.79/68)*H21 -> 33.524529 | AB21: =SUM(Y21:AA21) -> 1486.2397 | AC21: 7.12 | AD21: =SUM(AB21*AC21) -> 10582.027 | AE21: =SUM(X21+AD21) -> 17936.141 | AF21: =SUM(P21-AE21) -> 6121.1186
C22: 240807000019 | D22: 45506 | E22: Sam.Pao | F22: Sam.Pao | G22: Nick Wang | H22: 7.5437 | I22: 1504 | J22: 17283 | P22: =SUBTOTAL(9,J22) -> 17283 | S22: =SUM(52856.5/68)*H22 -> 5863.7291 | U22: =SUM(1500/68)*H22 -> 166.40515 | X22: =SUM(S22:W22) -> 6030.1343 | Y22: =SUM(10737.46/68)*H22 -> 1191.1791 | AA22: =SUM(247.79/68)*H22 -> 27.489021 | AB22: =SUM(Y22:AA22) -> 1218.6681 | AC22: 7.12 | AD22: =SUM(AB22*AC22) -> 8676.9168 | AE22: =SUM(X22+AD22) -> 14707.051 | AF22: =SUM(P22-AE22) -> 2575.9489
C23: 240728000003 | D23: 45506 | E23: Sam.Pao | F23: Sam.Pao | G23: Nick Wang | H23: 0.193 | I23: 47 | J23: 520 | P23: =SUBTOTAL(9,J23) -> 520 | S23: =SUM(52856.5/68)*H23 -> 150.01918 | U23: =SUM(1500/68)*H23 -> 4.2573529 | X23: =SUM(S23:W23) -> 154.27654 | Y23: =SUM(10737.46/68)*H23 -> 30.475438 | AA23: =SUM(247.79/68)*H23 -> 0.70328632 | AB23: =SUM(Y23:AA23) -> 31.178724 | AC23: 7.12 | AD23: =SUM(AB23*AC23) -> 221.99252 | AE23: =SUM(X23+AD23) -> 376.26905 | AF23: =SUM(P23-AE23) -> 143.73095
C24: 240828000002 | D24: 45532 | E24: Sam.Pao | F24: Sam.Pao | G24: SKY JET | H24: 17.63 | I24: 2193 | J24: 25894.59 | P24: =SUBTOTAL(9,J24) -> 25894.59 | S24: =SUM(52856.5/68)*H24 -> 13703.825 | U24: =SUM(1500/68)*H24 -> 388.89706 | X24: =SUM(S24:W24) -> 14092.722 | Y24: =SUM(10737.46/68)*H24 -> 2783.8444 | AA24: =SUM(247.79/68)*H24 -> 64.243201 | AB24: =SUM(Y24:AA24) -> 2848.0876 | AC24: 7.12 | AD24: =SUM(AB24*AC24) -> 20278.384 | AE24: =SUM(X24+AD24) -> 34371.106 | AF24: =SUM(P24-AE24) -> -8476.5158
C25: 240828000003 | D25: 45532 | E25: 罗珮文 | F25: Shirley | G25: Yusky | H25: 0.807 | I25: 46 | J25: 1345.67 | P25: =SUBTOTAL(9,J25) -> 1345.67 | S25: =SUM(52856.5/68)*H25 -> 627.28229 | U25: =SUM(1500/68)*H25 -> 17.801471 | X25: =SUM(S25:W25) -> 645.08376 | Y25: =SUM(10737.46/68)*H25 -> 127.42839 | AA25: =SUM(247.79/68)*H25 -> 2.9406843 | AB25: =SUM(Y25:AA25) -> 130.36907 | AC25: 7.12 | AD25: =SUM(AB25*AC25) -> 928.22778 | AE25: =SUM(X25+AD25) -> 1573.3115 | AF25: =SUM(P25-AE25) -> -227.64153
C26: 240828000005 | D26: 45532 | E26: 罗珮文 | F26: Shirley | G26: Yusky | H26: 0.6964 | I26: 42 | J26: 1161.45 | P26: =SUBTOTAL(9,J26) -> 1161.45 | S26: =SUM(52856.5/68)*H26 -> 541.31274 | U26: =SUM(1500/68)*H26 -> 15.361765 | X26: =SUM(S26:W26) -> 556.67451 | Y26: =SUM(10737.46/68)*H26 -> 109.96422 | AA26: =SUM(247.79/68)*H26 -> 2.5376611 | AB26: =SUM(Y26:AA26) -> 112.50188 | AC26: 7.12 | AD26: =SUM(AB26*AC26) -> 801.01341 | AE26: =SUM(X26+AD26) -> 1357.6879 | AF26: =SUM(P26-AE26) -> -196.23792
C27: 240828000008 | D27: 45532 | E27: 罗珮文 | F27: Shirley | G27: Yusky | H27: 0.0844 | I27: 25 | J27: 140.94 | P27: =SUBTOTAL(9,J27) -> 140.94 | S27: =SUM(52856.5/68)*H27 -> 65.604244 | U27: =SUM(1500/68)*H27 -> 1.8617647 | X27: =SUM(S27:W27) -> 67.466009 | Y27: =SUM(10737.46/68)*H27 -> 13.327083 | AA27: =SUM(247.79/68)*H27 -> 0.30755112 | AB27: =SUM(Y27:AA27) -> 13.634634 | AC27: 7.12 | AD27: =SUM(AB27*AC27) -> 97.078593 | AE27: =SUM(X27+AD27) -> 164.5446 | AF27: =SUM(P27-AE27) -> -23.604602
C28: 240828000017 | D28: 45532 | E28: 吕沛霖 | F28: 喵喵速运-Layne | G28: Sule Adekunle | H28: 0.1138 | I28: 45 | J28: 421 | P28: =SUM(J28) -> 421 | S28: =SUM(52856.5/68)*H28 -> 88.456907 | U28: =SUM(1500/68)*H28 -> 2.5102941 | X28: =SUM(S28:W28) -> 90.967201 | Y28: =SUM(10737.46/68)*H28 -> 17.969455 | Z28: 20.65 | AA28: =SUM(247.79/68)*H28 -> 0.41468385 | AB28: =SUM(Y28:AA28) -> 39.034139 | AC28: 7.12 | AD28: =SUM(AB28*AC28) -> 277.92307 | AE28: =SUM(X28+AD28) -> 368.89027 | AF28: =SUM(P28-AE28) -> 52.109729
C29: 240828000062 | D29: 45532 | E29: 罗珮文 | F29: Shirley | G29: Yusky | H29: 1.8606 | I29: 279 | J29: 6598.3 | P29: =SUBTOTAL(9,J29) -> 6598.3 | S29: =SUM(52856.5/68)*H29 -> 1446.2471 | U29: =SUM(1500/68)*H29 -> 41.042647 | X29: =SUM(S29:W29) -> 1487.2898 | Y29: =SUM(10737.46/68)*H29 -> 293.79585 | AA29: =SUM(247.79/68)*H29 -> 6.7799717 | AB29: =SUM(Y29:AA29) -> 300.57583 | AC29: 7.12 | AD29: =SUM(AB29*AC29) -> 2140.0999 | AE29: =SUM(X29+AD29) -> 3627.3896 | AF29: =SUM(P29-AE29) -> 2970.9104
A30: 合计 | J30: =SUM(J4:J4) -> 0 | N30: =SUM(N4:N4) -> 0 | P30: =SUM(P4:P4) -> 0 | Q30: =SUM(Q4:Q4) -> 0 | X30: =SUM(X4:X4) -> 0 | AD30: =SUM(AD4:AD4) -> 0 | AF30: =SUM(AF4:AF29) -> 8491.9024
