Workbook

Sheet 黄颖
A1: LOS毛利表
A3: JOB | B3: 集装编号 | C3: 运单编号 | D3: 日期 | E3: 业务 | F3: 发货人 | G3: 收货人 | H3: 计费体积 | I3: 计费重量 | J3: 应 收 | Q3: 总应收 | R3: 起 运 港 成 本 | W3: 代垫运费 | X3: 起运港成本 合计 | Y3: 目的港成本 | AE3: 总支出 | AF3: 利润
J4: 应收RMB | K4: LOS Income(NGN)收到(奈拉) | L4: LOS 收到USD | M4: 美元汇率 dollar currency rate | N4: 应收 到付款USD | O4: 汇率 | P4: 人民币 | R4: 代理商 | S4: 运费+出口报关费 | T4: 提货费 | U4: 装卸费 | V4: 包装费 | Y4: 进口报关费 | Z4: 到门配送费 | AA4: 转运费 | AB4: 目的港支出 | AC4: 汇率 | AD4: 人民币 | AE4: 起运港+目的港
A5: JOB070344 | B5: COLL004043 | C5: 240624000034 | D5: 45477 | E5: 黄颖 | F5: ying | G5: baikaibo | H5: 3.024 | I5: 2000 | K5: 2320436 | M5: 1651.8616 | N5: 1404.74 | O5: 7.12 | P5: 10001.749 | Q5: 63897.482 | R5: 华茂青松=60177 赛捷=1300 | S5: 2733.9184 | U5: 55.588235 | X5: 2789.5066 | Y5: 473.17818 | Z5: 5.49 | AB5: 478.66818 | AC5: 7.1 | AD5: 3398.5441 | AE5: 6188.0506 | AF5: 3813.6982
C6: 240624000036 | D6: 45478 | E6: 黄颖 | F6: ying | G6: Sunday Adelena | H6: 10.2263 | I6: 7008 | J6: 26828 | P6: 26828 | S6: 9245.3271 | U6: 187.98346 | V6: 120 | X6: 9553.3106 | Y6: 1600.1528 | AB6: 1600.1528 | AC6: 7.1 | AD6: 11361.085 | AE6: 20914.395 | AF6: 5913.6047
C7: 240628000020 | D7: 45477 | E7: 黄颖 | F7: ying | G7: baikaibo | H7: 0.472 | I7: 420 | K7: 439900 | M7: 1705.0388 | N7: 258 | O7: 7.12 | P7: 1836.96 | S7: 426.72271 | U7: 8.6764706 | X7: 435.39918 | Y7: 73.855853 | AB7: 73.855853 | AC7: 7.1 | AD7: 524.37656 | AE7: 959.77573 | AF7: 877.18427
C8: 240617000035 | D8: 45490 | E8: 黄颖 | F8: ying | G8: Huangpu | H8: 0.0887 | I8: 106 | J8: 332 | P8: 332 | S8: 80.191322 | U8: 1.6305147 | X8: 81.821837 | Y8: 13.879267 | AB8: 13.879267 | AC8: 7.1 | AD8: 98.542798 | AE8: 180.36463 | AF8: 151.63537
C9: 240624000036 | D9: 45478 | E9: 黄颖 | F9: ying | G9: Sunday Adelena | H9: 1.1026 | I9: 1089 | J9: 2892 | P9: 2892 | S9: 988.72412 | T9: 2.0368914 | U9: 18.646912 | V9: 120 | X9: 1129.4079 | Y9: 171.53975 | AA9: 0.93931791 | AB9: 172.47907 | AC9: 7.1 | AD9: 1224.6014 | AE9: 2354.0093 | AF9: 537.99068
C10: 240624000037 | D10: 45478 | E10: 黄颖 | F10: ying | G10: Sunday Adelena | H10: 14.6754 | I10: 11776.5 | J10: 43280 | P10: 43280 | S10: 13159.733 | T10: 27.110643 | U10: 248.18691 | X10: 13435.031 | Y10: 2283.162 | AA10: 12.502146 | AB10: 2295.6642 | AC10: 7.1 | AD10: 16299.216 | AE10: 29734.247 | AF10: 13545.753
C11: 240617000035 | D11: 45490 | E11: 黄颖 | F11: ying | G11: Huangpu | H11: 1.6952 | I11: 322.7 | J11: 6330 | P11: 6330 | S11: 1520.1207 | T11: 3.1316327 | U11: 28.668824 | X11: 1551.9212 | Y11: 263.73498 | AA11: 1.4441608 | AB11: 265.17914 | AC11: 7.1 | AD11: 1882.7719 | AE11: 3434.6931 | AF11: 2895.3069
C12: 240617000035 | D12: 45490 | E12: 黄颖 | F12: ying | G12: Huangpu | H12: 12.8123 | I12: 5331.1 | J12: 47840 | P12: 47840 | S12: 11620.945 | U12: 414.51559 | X12: 12035.46 | Y12: 1928.6261 | AA12: 14.673852 | AB12: 1943.3 | AC12: 7.12 | AD12: 13836.296 | AE12: 25871.756 | AF12: 21968.244
A13: JOB070370 | B13: COLL004070 | C13: 240617000035 | D13: 45490 | E13: 黄颖 | F13: ying | G13: Huangpu | H13: 4.9371 | I13: 11872 | J13: 18452 | P13: 18452 | Q13: 36956.95 | R13: 华茂青松=60177 赛捷=2300 | S13: 4536.1058 | T13: 770 | U13: 174.25059 | W13: 2630 | X13: 8110.3564 | Y13: 743.17803 | Z13: 471.98 | AA13: 2.5701962 | AB13: 1217.7282 | AC13: 7.26 | AD13: 8840.7069 | AE13: 16951.063 | AF13: 1500.9366
C14: 240702000004 | D14: 45490 | E14: 黄颖 | F14: ying | G14: liangyu | H14: 1.9054 | I14: 586.7 | J14: 7303 | P14: 7303 | S14: 1750.6423 | U14: 67.249412 | X14: 1817.8917 | Y14: 286.81846 | AA14: 0.99192882 | AB14: 287.81039 | AC14: 7.26 | AD14: 2089.5034 | AE14: 3907.3951 | AF14: 3395.6049
C15: 240716000022 | D15: 45498 | E15: 黄颖 | F15: ying | G15: Huangpu | H15: 0.0648 | I15: 67.5 | J15: 630 | P15: 630 | S15: 58.583965 | T15: 0.57176471 | U15: 1.0958824 | X15: 60.251612 | Y15: 10.015726 | Z15: 30.54 | AA15: 0.033734118 | AB15: 40.58946 | AC15: 7.06 | AD15: 286.56159 | AE15: 346.8132 | AF15: 283.1868
C16: 240717000017 | D16: 45498 | E16: 黄颖 | F16: ying | G16: Nura | H16: 0.6221 | I16: 294 | J16: 1390 | P16: 1390 | S16: 562.42414 | T16: 5.4891176 | U16: 10.520809 | X16: 578.43407 | Y16: 96.154063 | AA16: 0.32385794 | AB16: 96.477921 | AC16: 7.06 | AD16: 681.13412 | AE16: 1259.5682 | AF16: 130.43181
C17: 240718000030 | D17: 45498 | E17: 黄颖 | F17: ying | G17: liangyu | H17: 0.2438 | I17: 26.5 | J17: 606.5 | P17: 606.5 | S17: 220.41313 | T17: 2.1511765 | U17: 4.1230882 | X17: 226.68739 | Y17: 37.682624 | AA17: 0.12691941 | AB17: 37.809544 | AC17: 7.06 | AD17: 266.93538 | AE17: 493.62277 | AF17: 112.87723
C18: 240719000002 | D18: 45498 | E18: 黄颖 | F18: ying | G18: chuks | H18: 0.8911 | I18: 332 | J18: 2500 | P18: 2500 | S18: 805.61992 | T18: 7.8626471 | U18: 15.070074 | X18: 828.55264 | Y18: 137.73169 | Z18: 41.3 | AA18: 0.46389618 | AB18: 179.49559 | AC18: 7.06 | AD18: 1267.2389 | AE18: 2095.7915 | AF18: 404.2085
C19: 240724000014 | D19: 45498 | E19: 黄颖 | F19: ying | G19: Huangpu | H19: 0.2732 | I19: 264 | J19: 894 | P19: 894 | S19: 246.99289 | T19: 2.4105882 | U19: 4.6202941 | X19: 254.02377 | Y19: 42.226796 | AA19: 0.14222471 | AB19: 42.369021 | AC19: 7.06 | AD19: 299.12529 | AE19: 553.14906 | AF19: 340.85094
A20: 合 计 | AF20: =SUM(AF5:AF19) -> 55871.515
C22: 基本任务：小于6千 | F22: 不够基本任务6千， 公司将根据空运提成里抽出补足基数 | K22: 黄颖 提成
K23: 名称 | L23: 计费体积 | M23: 毛利
C24: 基本任务：6千-3.5万 | F24: 按40%提成 | K24: LOS | L24: =SUM(H5:H19) -> 53.034 | M24: =SUM(AF20) -> 55871.515
K25: 任务 | M25: 6000
C26: 基本任务：3.5万以上 | F26: 按50%提成 | K26: 提成计数 | M26: =SUM(M24-M25) -> 49871.515
K27: 基数 | M27: 35000
K28: 提成计数40% | M28: 0.4
K29: 提成金额 | M29: =SUM(M27*M28) -> 14000
K30: 实提成计数 | M30: =SUM(M26-M27) -> 14871.515
K31: 提成点数50% | M31: 0.5
K32: 提成金额 | M32: =SUM(M30*M31) -> 7435.7573
K33: 合计提成金额 | M33: =SUM(M29+M32) -> 21435.757

Sheet 三凤
A1: LOS毛利表
A2: JOB | B2: 集装编号 | C2: 运单编号 | D2: 日期 | E2: 业务 | F2: 发货人 | G2: 收货人 | H2: 计费体积 | I2: 计费重量 | J2: 应 收 | Q2: 总应收 | R2: 起 运 港 成 本 | W2: 代垫运费 | X2: 起运港成本 合计 | Y2: 目的港成本 | AE2: 总支出 | AF2: 利润
J3: 应收RMB | K3: LOS Income(NGN)收到(奈拉) | L3: LOS 收到USD | M3: 美元汇率 dollar currency rate | N3: 应收 到付款USD | O3: 汇率 | P3: 人民币 | R3: 代理商 | S3: 运费+出口报关费 | T3: 提货费 | U3: 装卸费 | V3: 包装费 | Y3: 进口报关费 | Z3: 到门配送费 | AA3: 转运费 | AB3: 目的港支出 | AC3: 汇率 | AD3: 人民币 | AE3: 起运港+目的港
C4: 240711000027 | D4: 45490 | E4: Bella | F4: Bella Chan | G4: James | H4: 0.8466 | I4: 370 | L4: 296.31 | M4: 0 | N4: 296.31006 | O4: 7.12 | P4: 2109.7276 | S4: 777.83865 | U4: 29.88 | X4: 807.71865 | Y4: 127.43808 | AA4: 0.44073 | AB4: 127.87881 | AC4: 7.26 | AD4: 928.40013 | AE4: 1736.1188 | AF4: 373.60885
C5: 240724000026 | D5: 45498 | E5: Bella | F5: Bella Chan | G5: zhong zi xin | H5: 15.7603 | I5: 8373 | K5: 8696280.7 | M5: 1710.9973 | N5: 5082.58 | O5: 7.12 | P5: 36187.97 | S5: 14248.47 | T5: 139.06147 | U5: 266.53449 | X5: 14654.066 | Y5: 2435.9699 | Z5: 217.7 | AA5: 8.2046268 | AB5: 2661.8745 | AC5: 7.06 | AD5: 18792.834 | AE5: 33446.9 | AF5: 2741.0694
A6: 合 计 | AF6: =SUM(AF4:AF5) -> 3114.6782
AF7: =SUM(AF4/2) -> 186.80442
C8: 基本任务：小于6千 | F8: 不够基本任务6千， 公司将根据空运提成里抽出补足基数 | K8: 三凤 提成 | AF8: =SUM(AF6-AF7) -> 2927.8738
K9: 名称 | L9: 计费体积 | M9: 毛利 | N9: 备注
C10: 基本任务：6千-3.5万 | F10: 按40%提成 | K10: LOS | L10: =SUM(H2:H5) -> 16.6069 | M10: 2927.8738 | N10: 总利润减james 利润的 一半186.8
K11: 基数
C12: 基本任务：3.5万以上 | F12: 按50%提成 | K12: 提成计数
K13: 提成点数 | M13: 0.1
K14: 提成金额 | M14: =SUM(M10*M13) -> 292.78738

Sheet 朱小飞
A1: LOS毛利表
A3: JOB | B3: 集装编号 | C3: 运单编号 | D3: 日期 | E3: 业务 | F3: 发货人 | G3: 收货人 | H3: 计费体积 | I3: 计费重量 | J3: 应 收 | Q3: 总应收 | R3: 起 运 港 成 本 | W3: 代垫运费 | X3: 起运港成本 合计 | Y3: 目的港成本 | AE3: 总支出 | AF3: 利润
J4: 应收RMB | K4: LOS Income(NGN)收到(奈拉) | L4: LOS 收到USD | M4: 美元汇率 dollar currency rate | N4: 应收 到付款USD | O4: 汇率 | P4: 人民币 | R4: 代理商 | S4: 运费+出口报关费 | T4: 提货费 | U4: 装卸费 | V4: 包装费 | Y4: 进口报关费 | Z4: 到门配送费 | AA4: 转运费 | AB4: 目的港支出 | AC4: 汇率 | AD4: 人民币 | AE4: 起运港+目的港
C5: 240628000036 | D5: 45477 | E5: 朱小飞 | F5: Isabel Zhu | G5: Halifa Success | H5: 0.6693 | I5: 116.5 | J5: 1662.94 | P5: 1662.94 | S5: 605.09641 | U5: 12.303309 | X5: 617.39972 | Y5: 104.72823 | AB5: 104.72823 | AC5: 7.1 | AD5: 743.5704 | AE5: 1360.9701 | AF5: 301.96988
C6: 240702000007 | D6: 45477 | E6: 朱小飞 | F6: Isabel Zhu | G6: Halifa Success | H6: 0.8928 | I6: 218 | J6: 2361.55 | P6: 2361.55 | S6: 807.15685 | U6: 16.411765 | W6: 292 | X6: 1115.5686 | Y6: 139.70022 | AB6: 139.70022 | AC6: 7.1 | AD6: 991.87159 | AE6: 2107.4402 | AF6: 254.1098
C7: 240702000008 | D7: 45477 | E7: 朱小飞 | F7: Isabel Zhu | G7: Halifa Success | H7: 2.232 | I7: 1028 | J7: 6070.88 | P7: 6070.88 | S7: 2017.8921 | T7: 215 | U7: 41.029412 | W7: 420 | X7: 2693.9215 | Y7: 349.25056 | AB7: 349.25056 | AC7: 7.1 | AD7: 2479.679 | AE7: 5173.6005 | AF7: 897.2795
C8: 240702000009 | D8: 45477 | E8: 朱小飞 | F8: Isabel Zhu | G8: Halifa Success | H8: 5.8065 | I8: 650 | J8: 13360.1 | P8: 13360.1 | S8: 5249.5029 | U8: 106.73713 | X8: 5356.2401 | Y8: 908.56782 | AB8: 908.56782 | AC8: 7.1 | AD8: 6450.8315 | AE8: 11807.072 | AF8: 1553.0284
C9: 240719000036 | D9: 45498 | E9: 朱小飞 | F9: Isabel Zhu | G9: Halifa Success | H9: 1.8646 | I9: 213 | J9: 4300.07 | P9: 4300.07 | S9: 1685.7355 | T9: 16.452353 | U9: 31.533676 | X9: 1733.7215 | Y9: 288.19943 | AA9: 0.97068882 | AB9: 289.17012 | AC9: 7.06 | AD9: 2041.541 | AE9: 3775.2626 | AF9: 524.80742
C10: 240720000015 | D10: 45498 | E10: 朱小飞 | F10: Isabel Zhu | G10: Halifa Success | H10: 0.3673 | I10: 57 | J10: 880.38 | P10: 880.38 | S10: 332.06621 | T10: 3.2408824 | U10: 6.2116912 | X10: 341.51878 | Y10: 56.771238 | AA10: 0.19121206 | AB10: 56.96245 | AC10: 7.06 | AD10: 402.1549 | AE10: 743.67368 | AF10: 136.70632
C11: 240715000001 | D11: 45490 | E11: 朱小飞 | F11: Isabel Zhu | G11: Halifa Success | H11: 0.269 | I11: 184 | J11: 660.29 | P11: 660.29 | S11: 247.15166 | U11: 9.4941176 | X11: 256.64578 | Y11: 40.492372 | AA11: 0.14003824 | AB11: 40.63241 | AC11: 7.26 | AD11: 294.9913 | AE11: 551.63708 | AF11: 108.65292 | AG11: =SUM(AF5:AF11) -> 3776.5543 | AH11: =SUM(AG11/2) -> 1888.2771
C12: 240628000031 | D12: 45477 | E12: 朱小飞 | F12: Isabel Zhu | G12: Wang Hui Feng | H12: 1.7537 | I12: 2930 | K12: 2405060 | M12: 1640 | N12: 1466.5 | O12: 7.12 | P12: 10441.48 | S12: 1585.4737 | U12: 32.237132 | X12: 1617.7109 | Y12: 274.40892 | AB12: 274.40892 | AC12: 7.1 | AD12: 1948.3033 | AE12: 3566.0142 | AF12: 6875.4658
C13: 240703000022 | D13: 45477 | E13: 朱小飞 | F13: Isabel Zhu | G13: Lilon | H13: 2.6714 | I13: 1555 | J13: 7525.12 | P13: 7525.12 | S13: 2415.142 | U13: 49.106618 | X13: 2464.2486 | Y13: 418.00535 | AB13: 418.00535 | AC13: 7.1 | AD13: 2967.838 | AE13: 5432.0866 | AF13: 2093.0334
C14: 240716000001 | D14: 45490 | E14: 朱小飞 | F14: Isabel Zhu | G14: Victor Nnamdi | H14: 0.9605 | I14: 145 | K14: 591555 | M14: 1710.7842 | N14: 345.78003 | O14: 7.06 | P14: 2441.207 | S14: 882.48762 | U14: 33.9 | X14: 916.38762 | Y14: 144.58336 | AA14: 0.500025 | AB14: 145.08338 | AC14: 7.26 | AD14: 1053.3054 | AE14: 1969.693 | AF14: 471.51402
C15: 240717000037 | D15: 45498 | E15: 朱小飞 | F15: Isabel Zhu | G15: Mr Michael | H15: 0.9774 | I15: 169.65 | J15: 2342 | P15: 2342 | S15: 883.64147 | T15: 8.6241176 | U15: 16.529559 | W15: 52 | X15: 960.79514 | Y15: 151.07054 | AA15: 0.50882294 | AB15: 151.57936 | AC15: 7.06 | AD15: 1070.1503 | AE15: 2030.9454 | AF15: 311.05457
A16: 合计 | AF16: =SUM(AF5:AF15) -> 13527.622
AF17: 1888.2771
C18: 基本任务：小于6千 | F18: 不够基本任务6千， 公司将根据空运提成里抽出补足基数 | K18: 朱小飞 提成 | AF18: =SUM(AF16-AF17) -> 11639.345
K19: 名称 | L19: 计费体积 | M19: 毛利 | N19: 备注
C20: 基本任务：6千-3.5万 | F20: 按40%提成 | K20: LOS | L20: =SUM(H5:H10) -> 11.8325 | M20: 11639.345 | N20: 总利润减Halifa 利润的 一半1888.28
K21: 基数
C22: 基本任务：3.5万以上 | F22: 按50%提成 | K22: 提成计数
K23: 提成点数 | M23: 0.1
K24: 提成金额 | M24: =SUM(M20*M23) -> 1163.9345

Sheet 吕沛霖
A1: LOS毛利表
A2: JOB | B2: 集装编号 | C2: 运单编号 | D2: 日期 | E2: 业务 | F2: 发货人 | G2: 收货人 | H2: 计费体积 | I2: 计费重量 | J2: 应 收 | Q2: 总应收 | R2: 起 运 港 成 本 | W2: 代垫运费 | X2: 起运港成本 合计 | Y2: 目的港成本 | AE2: 总支出 | AF2: 利润
J3: 应收RMB | K3: LOS Income(NGN)收到(奈拉) | L3: LOS 收到USD | M3: 美元汇率 dollar currency rate | N3: 应收 到付款USD | O3: 汇率 | P3: 人民币 | R3: 代理商 | S3: 运费+出口报关费 | T3: 提货费 | U3: 装卸费 | V3: 包装费 | Y3: 进口报关费 | Z3: 到门配送费 | AA3: 转运费 | AB3: 目的港支出 | AC3: 汇率 | AD3: 人民币 | AE3: 起运港+目的港
C4: 240701000015 | D4: 45477 | E4: 吕沛霖 | F4: 喵喵速运-Layne | G4: YA | H4: 0.3978 | I4: 49.5 | J4: 1385.08 | P4: 1385.08 | S4: 359.64045 | U4: 7.3125 | X4: 366.95295 | Y4: 62.245463 | Z4: 41.46 | AB4: 103.70546 | AC4: 7.1 | AD4: 736.30878 | AE4: 1103.2617 | AF4: 281.81827
C5: 240701000020 | D5: 45477 | E5: 吕沛霖 | F5: 喵喵速运-Layne | G5: Jinggang Pan | H5: 0.5519 | I5: 82 | J5: 1460.33 | P5: 1460.33 | S5: 498.95818 | U5: 10.145221 | X5: 509.1034 | Y5: 86.358147 | AB5: 86.358147 | AC5: 7.1 | AD5: 613.14284 | AE5: 1122.2462 | AF5: 338.08376
C6: 240607000053 | D6: 45478 | E6: 吕沛霖 | F6: 喵喵速运-Layne | G6: KE ZONG | H6: 1.3088 | I6: 352 | J6: 3425 | P6: 3425 | S6: 1183.2514 | U6: 24.058824 | X6: 1207.3103 | Y6: 204.79352 | AB6: 204.79352 | AC6: 7.1 | AD6: 1454.034 | AE6: 2661.3442 | AF6: 763.65577
A7: JOB070349 | B7: COLL004049 | C7: 240607000053 | D7: 45478 | E7: 吕沛霖 | F7: 喵喵速运-Layne | G7: KE ZONG | H7: 1.3459 | I7: 622 | J7: 3524.24 | P7: 3524.24 | Q7: 9854.24 | R7: 华茂青松=60177 赛捷=800 | S7: 1206.8962 | T7: 2.4863523 | U7: 22.761544 | V7: 120 | X7: 1352.1441 | Y7: 209.39176 | AA7: 1.146588 | AB7: 210.53835 | AC7: 7.1 | AD7: 1494.8223 | AE7: 2846.9664 | AF7: 677.27361
C8: 240708000040 | D8: 45490 | E8: 吕沛霖 | F8: 喵喵速运-Layne | G8: Candice Ding | H8: 0.6334 | I8: 1195 | K8: 1077245.4 | M8: 1744.414 | N8: 617.54 | O8: 7.12 | P8: 4396.8848 | S8: 581.95488 | U8: 22.355294 | X8: 604.31017 | Y8: 95.345236 | Z8: 59 | AA8: 0.32974059 | AB8: 154.67498 | AC8: 7.26 | AD8: 1122.9403 | AE8: 1727.2505 | AF8: 2669.6343
A9: 合计 | AF9: =SUM(AF4:AF8) -> 4730.4657
C12: 基本任务：小于6千 | F12: 不够基本任务6千， 公司将根据空运提成里抽出补足基数 | K12: 吕沛霖 提成
K13: 名称 | L13: 计费体积 | M13: 毛利
C14: 基本任务：6千-3.5万 | F14: 按40%提成 | K14: LOS | L14: =SUM(H4:H8) -> 4.2378 | M14: =SUM(AF9) -> 4730.4657
K15: 基数 | M15: 6663.1356
C16: 基本任务：3.5万以上 | F16: 按50%提成 | K16: 提成计数 | M16: =SUM(M14-M15) -> -1932.6699
K17: 提成点数
K18: 提成金额 | L18: 下个月基数为 | M18: =SUM(M15-M16) -> 8595.8056

Sheet 罗伟健
A1: LOS毛利表
A3: JOB | B3: 集装编号 | C3: 运单编号 | D3: 日期 | E3: 业务 | F3: 发货人 | G3: 收货人 | H3: 计费体积 | I3: 计费重量 | J3: 应 收 | Q3: 总应收 | R3: 起 运 港 成 本 | W3: 代垫运费 | X3: 起运港成本 合计 | Y3: 目的港成本 | AE3: 总支出 | AF3: 利润
J4: 应收RMB | K4: LOS Income(NGN)收到(奈拉) | L4: LOS 收到USD | M4: 美元汇率 dollar currency rate | N4: 应收 到付款USD | O4: 汇率 | P4: 人民币 | R4: 代理商 | S4: 运费+出口报关费 | T4: 提货费 | U4: 装卸费 | V4: 包装费 | Y4: 进口报关费 | Z4: 到门配送费 | AA4: 转运费 | AB4: 目的港支出 | AC4: 汇率 | AD4: 人民币 | AE4: 起运港+目的港
C5: 240724000017 | D5: 45498 | E5: 罗伟健 | F5: MailMail速运-演员 | G5: zeng hai | H5: 0.2991 | I5: 1311 | K5: 1137000 | M5: =SUM(K5/N5) -> 1689.7013 | N5: 672.9 | O5: 7.06 | P5: =SUM(N5*O5) -> 4750.674 | S5: =SUM(61477/68)*H5 -> 270.40839 | T5: =SUM(600/68)*H5 -> 2.6391176 | U5: =SUM(1150/68)*H5 -> 5.0583088 | V5: 210 | W5: 330 | X5: =SUM(S5:W5) -> 818.10582 | Y5: =SUM(10510.33/68)*H5 -> 46.229996 | AA5: =SUM(35.4/68)*H5 -> 0.15570794 | AB5: =SUM(Y5:AA5) -> 46.385704 | AC5: 7.06 | AD5: =SUM(AB5*AC5) -> 327.48307 | AE5: =SUM(X5+AD5) -> 1145.5889 | AF5: =SUM(P5-AE5) -> 3605.0851
A6: 合计 | AF6: =SUM(AF5:AF5) -> 3605.0851
C8: 基本任务：小于6千 | F8: 不够基本任务6千， 公司将根据空运提成里抽出补足基数 | K8: 罗伟健 提成
K9: 名称 | L9: 计费体积 | M9: 毛利
C10: 基本任务：6千-3.5万 | F10: 按40%提成 | K10: LOS | L10: =SUM(H5) -> 0.2991 | M10: =SUM(AF5) -> 3605.0851
K11: 基数 | M11: 6000
C12: 基本任务：3.5万以上 | F12: 按50%提成 | K12: 提成计数 | M12: =SUM(M10-M11) -> -2394.9149
K13: 提成点数
K14: 提成金额

Sheet 苏慧琪
A1: LOS毛利表
A3: JOB | B3: 集装编号 | C3: 运单编号 | D3: 日期 | E3: 业务 | F3: 发货人 | G3: 收货人 | H3: 计费体积 | I3: 计费重量 | J3: 应 收 | Q3: 总应收 | R3: 起 运 港 成 本 | W3: 代垫运费 | X3: 起运港成本 合计 | Y3: 目的港成本 | AE3: 总支出 | AF3: 利润
J4: 应收RMB | K4: LOS Income(NGN)收到(奈拉) | L4: LOS 收到USD | M4: 美元汇率 dollar currency rate | N4: 应收 到付款USD | O4: 汇率 | P4: 人民币 | R4: 代理商 | S4: 运费+出口报关费 | T4: 提货费 | U4: 装卸费 | V4: 包装费 | Y4: 进口报关费 | Z4: 到门配送费 | AA4: 转运费 | AB4: 目的港支出 | AC4: 汇率 | AD4: 人民币 | AE4: 起运港+目的港
A5: JOB070375 | B5: COLL004074 | C5: 240715000042 | D5: 45498 | E5: 苏慧琪 | F5: Danny | G5: Austin Efe | H5: 0.3636 | I5: 253.4 | J5: 1117.2 | P5: 1117.2 | Q5: 44075.844 | R5: 华茂青松=60177 赛捷=1300 | S5: 328.72114 | T5: 3.2082353 | U5: 6.1491176 | X5: 338.07849 | Y5: 56.199353 | AA5: 0.18928588 | AB5: 56.388639 | AC5: 7.06 | AD5: 398.10379 | AE5: 736.18228 | AF5: 381.01772
A6: 合计 | AF6: =SUM(AF5:AF5) -> 381.01772
C8: 基本任务：小于6千 | F8: 不够基本任务6千， 公司将根据空运提成里抽出补足基数 | K8: 苏慧琪 提成
K9: 名称 | L9: 计费体积 | M9: 毛利
C10: 基本任务：6千-3.5万 | F10: 按40%提成 | K10: LOS | L10: =SUM(H5) -> 0.3636 | M10: =SUM(AF5) -> 381.01772
K11: 基数 | M11: 6000
C12: 基本任务：3.5万以上 | F12: 按50%提成 | K12: 提成计数 | M12: =SUM(M10-M11) -> -5618.9823
K13: 提成点数
K14: 提成金额

Sheet 陆总
A1: LOS毛利表
A3: JOB | B3: 集装编号 | C3: 运单编号 | D3: 日期 | E3: 业务 | F3: 发货人 | G3: 收货人 | H3: 计费体积 | I3: 计费重量 | J3: 应 收 | Q3: 总应收 | R3: 起 运 港 成 本 | W3: 代垫运费 | X3: 起运港成本 合计 | Y3: 目的港成本 | AE3: 总支出 | AF3: 利润
J4: 应收RMB | K4: LOS Income(NGN)收到(奈拉) | L4: LOS 收到USD | M4: 美元汇率 dollar currency rate | N4: 应收 到付款USD | O4: 汇率 | P4: 人民币 | R4: 代理商 | S4: 运费+出口报关费 | T4: 提货费 | U4: 装卸费 | V4: 包装费 | Y4: 进口报关费 | Z4: 到门配送费 | AA4: 转运费 | AB4: 目的港支出 | AC4: 汇率 | AD4: 人民币 | AE4: 起运港+目的港
C5: 240708000038 | D5: 45482 | E5: 陆总 | F5: 喵喵速运-江 | G5: LUZHILONG | H5: 1.6 | I5: 1009 | J5: 3916.8 | P5: 3916.8 | S5: 1451.2235 | U5: 51.764706 | X5: 1502.9882 | Y5: 240.84682 | AA5: 1.8324706 | AB5: 242.67929 | AC5: 7.12 | AD5: 1727.8766 | AE5: 3230.8648 | AF5: 685.93519
C6: 240715000029 | D6: 45490 | E6: 陆总 | F6: 喵喵速运-江 | G6: LUZHILONG | H6: 7.56 | I6: 5200 | J6: 19595.52 | P6: 19595.52 | S6: 6945.9724 | U6: 266.82353 | X6: 7212.7959 | Y6: 1138.0012 | AA6: 3.9356471 | AB6: 1141.9369 | AC6: 7.26 | AD6: 8290.4618 | AE6: 15503.258 | AF6: 4092.2623
C7: 240716000007 | D7: 45490 | E7: 陆总 | F7: 喵喵速运-江 | G7: LUZHILONG | H7: 12.4652 | I7: 1110 | J7: 29367.14 | P7: 29367.14 | S7: 11452.769 | U7: 439.94824 | V7: 200 | X7: 12092.717 | Y7: 1876.3774 | AA7: 6.4892365 | AB7: 1882.8666 | AC7: 7.26 | AD7: 13669.612 | AE7: 25762.329 | AF7: 3604.8109
C8: 240724000025 | D8: 45498 | E8: 陆总 | F8: 喵喵速运-江 | G8: LUZHILONG | H8: 24.4728 | I8: 3060 | J8: 57259.8 | P8: 57259.8 | S8: 22125.211 | T8: 215.93647 | U8: 413.87824 | X8: 22755.025 | Y8: 3782.6059 | AA8: 12.740252 | AB8: 3795.3462 | AC8: 7.06 | AD8: 26795.144 | AE8: 49550.17 | AF8: 7709.6305
A9: 合计 | AF9: =SUM(AF5:AF8) -> 16092.639
C11: 基本任务：小于6千 | F11: 不够基本任务6千， 公司将根据空运提成里抽出补足基数 | K11: 陆总 提成
K12: 名称 | L12: 计费体积 | M12: 毛利
C13: 基本任务：6千-3.5万 | F13: 按40%提成 | K13: LOS | L13: =SUM(H5:H8) -> 46.098 | M13: =SUM(AF9) -> 16092.639
K14: 提成计数 | M14: =SUM(M13:M13) -> 16092.639
C15: 基本任务：3.5万以上 | F15: 按50%提成 | K15: 提成点数 | M15: 0.4
K16: 提成金额 | M16: =SUM(M14*M15) -> 6437.0556

Sheet 浦生
A1: LOS毛利表
A3: JOB | B3: 集装编号 | C3: 运单编号 | D3: 日期 | E3: 业务 | F3: 发货人 | G3: 收货人 | H3: 计费体积 | I3: 计费重量 | J3: 应 收 | Q3: 总应收 | R3: 起 运 港 成 本 | W3: 代垫运费 | X3: 起运港成本 合计 | Y3: 目的港成本 | AE3: 总支出 | AF3: 利润
J4: 应收RMB | K4: LOS Income(NGN)收到(奈拉) | L4: LOS 收到USD | M4: 美元汇率 dollar currency rate | N4: 应收 到付款USD | O4: 汇率 | P4: 人民币 | R4: 代理商 | S4: 运费+出口报关费 | T4: 提货费 | U4: 装卸费 | V4: 包装费 | Y4: 进口报关费 | Z4: 到门配送费 | AA4: 转运费 | AB4: 目的港支出 | AC4: 汇率 | AD4: 人民币 | AE4: 起运港+目的港
C5: 240624000056 | D5: 45477 | E5: Sam.Pao | F5: Sam.Pao | G5: TOLUBOD MOVERS | H5: 0.509 | I5: 207 | J5: 1893.7 | P5: 1893.7 | S5: 460.17343 | U5: 9.3566176 | V5: 270 | X5: 739.53004 | Y5: 79.645401 | AB5: 79.645401 | AC5: 7.1 | AD5: 565.48235 | AE5: 1305.0124 | AF5: 588.68761
C6: 240626000044 | D6: 45477 | E6: Sam.Pao | F6: Sam.Pao | G6: JunYue hotel | H6: 0.6356 | I6: 450 | J6: 1714.8 | P6: 1714.8 | S6: 574.62914 | U6: 11.683824 | X6: 586.31296 | Y6: 99.455043 | AB6: 99.455043 | AC6: 7.1 | AD6: 706.1308 | AE6: 1292.4438 | AF6: 422.35624
C7: 240703000028 | D7: 45477 | E7: Sam.Pao | F7: Sam.Pao | G7: Mr. Jiang | H7: 0.9089 | I7: 232 | J7: 3294.7 | P7: 3294.7 | S7: 821.71243 | U7: 16.707721 | X7: 838.42015 | Y7: 142.21946 | AB7: 142.21946 | AC7: 7.1 | AD7: 1009.7582 | AE7: 1848.1783 | AF7: 1446.5217
C8: 240703000030 | D8: 45477 | E8: Sam.Pao | F8: Sam.Pao | G8: JunYue hotel | H8: 1.1081 | I8: 861 | J8: 2989.7 | P8: 2989.7 | S8: 1001.8039 | U8: 20.369485 | X8: 1022.1734 | Y8: 173.38913 | AB8: 173.38913 | AC8: 7.1 | AD8: 1231.0628 | AE8: 2253.2362 | AF8: 736.46379
C9: 240704000029 | D9: 45482 | E9: Sam.Pao | F9: Sam.Pao | G9: LuZhiLong | H9: 0.7168 | I9: 230 | J9: 1792 | P9: 1792 | S9: 648.03991 | U9: 13.176471 | X9: 661.21638 | Y9: 112.16075 | AB9: 112.16075 | AC9: 7.1 | AD9: 796.34135 | AE9: 1457.5577 | AF9: 334.44228
C10: 240703000031 | D10: 45478 | E10: Sam.Pao | F10: Sam.Pao | G10: SKY JET | H10: 36.23 | I10: 4650 | J10: 63805.02 | P10: 63805.02 | S10: 32754.584 | U10: 665.99265 | X10: 33420.577 | Y10: 5669.0626 | AB10: 5669.0626 | AC10: 7.1 | AD10: 40250.345 | AE10: 73670.921 | AF10: -9865.9012
C11: 240704000018 | D11: 45477 | E11: Sam.Pao | F11: Sam.Pao | G11: MaiKaiNian | H11: 0.0287 | I11: 25 | J11: 106 | P11: 106 | S11: 25.94691 | U11: 0.52757353 | X11: 26.474484 | Y11: 4.4908114 | AB11: 4.4908114 | AC11: 7.1 | AD11: 31.884761 | AE11: 58.359245 | AF11: 47.640755
C12: 240704000029 | D12: 45482 | E12: Sam.Pao | F12: Sam.Pao | G12: LuZhiLong | H12: 13.9646 | I12: 3568 | J12: 34908 | P12: 34908 | S12: 12522.344 | T12: 25.797545 | U12: 236.16603 | X12: 12784.308 | Y12: 2172.5776 | AA12: 11.896607 | AB12: 2184.4742 | AC12: 7.1 | AD12: 15509.767 | AE12: 28294.074 | AF12: 6613.9255
C13: 240703000031 | D13: 45478 | E13: Sam.Pao | F13: Sam.Pao | G13: SKY JET | H13: 7.89 | I13: 615 | J13: 13912.77 | P13: 13912.77 | S13: 7075.1254 | T13: 14.575615 | U13: 133.43382 | X13: 7223.1349 | Y13: 1227.5065 | AA13: 6.7215838 | AB13: 1234.2281 | AC13: 7.1 | AD13: 8763.0192 | AE13: 15986.154 | AF13: -2073.3841
C14: 240705000003 | D14: 45478 | E14: Sam.Pao | F14: Sam.Pao | G14: SKY JET | H14: 29.53 | I14: 3724 | J14: 52005.58 | P14: 52005.58 | S14: 26480.159 | T14: 54.552332 | U14: 499.40441 | X14: 27034.116 | Y14: 4594.2036 | AA14: 25.156954 | AB14: 4619.3605 | AC14: 7.1 | AD14: 32797.46 | AE14: 59831.575 | AF14: -7825.9955
A15: JOB070360 | B15: COLL004060 | C15: 240618000026 | D15: 45482 | E15: Sam.Pao | F15: Sam.Pao | G15: Joshua | H15: 9.0048 | I15: 5844 | J15: 32609 | P15: 32609 | Q15: 180613.74 | R15: 华茂青松=60177 赛捷=1500 | S15: 8167.486 | U15: 291.33176 | V15: 120 | W15: 1600 | X15: 10178.818 | Y15: 1355.4859 | Z15: 513.28 | AA15: 10.313144 | AB15: 1879.0791 | AC15: 7.12 | AD15: 13379.043 | AE15: 23557.861 | AF15: 9051.1393
C16: 240704000029 | D16: 45482 | E16: Sam.Pao | F16: Sam.Pao | G16: LuZhiLong | H16: 14.9276 | I16: 11064 | J16: 37314.5 | P16: 37314.5 | S16: 13539.553 | U16: 482.95176 | X16: 14022.504 | Y16: 2247.0407 | AA16: 17.096492 | AB16: 2264.1371 | AC16: 7.12 | AD16: 16120.656 | AE16: 30143.161 | AF16: 7171.339
C17: 240707000003 | D17: 45482 | E17: Sam.Pao | F17: Sam.Pao | G17: LuZhiLong | H17: 0.1208 | I17: 69 | J17: 330.48 | P17: 330.48 | S17: 109.56738 | U17: 3.9082353 | X17: 113.47561 | Y17: 18.183935 | AA17: 0.13835153 | AB17: 18.322287 | AC17: 7.12 | AD17: 130.45468 | AE17: 243.93029 | AF17: 86.549707
C18: 240708000062 | D18: 45482 | E18: Sam.Pao | F18: Sam.Pao | G18: SKY JET | H18: 35.79 | I18: 4290.5 | J18: 62519.76 | P18: 62519.76 | S18: 32462.056 | U18: 1157.9118 | X18: 33619.968 | Y18: 5387.4424 | AA18: 40.990076 | AB18: 5428.4325 | AC18: 7.12 | AD18: 38650.439 | AE18: 72270.407 | AF18: -9750.6472
C19: 240702000027 | D19: 45490 | E19: Sam.Pao | F19: Sam.Pao | G19: Ikenna | H19: 0.9364 | I19: 230 | K19: 539654 | M19: 1694.9997 | N19: 318.38 | O19: 7.08 | P19: 2254.1304 | S19: 860.34504 | U19: 33.049412 | X19: 893.39445 | Y19: 140.9556 | AA19: 0.48747882 | AB19: 141.44308 | AC19: 7.26 | AD19: 1026.8768 | AE19: 1920.2712 | AF19: 333.85917
C20: 240715000048 | D20: 45490 | E20: Sam.Pao | F20: Sam.Pao | G20: Yusky | H20: 11.5846 | I20: 2575.5 | J20: 24968.54 | P20: 24968.54 | S20: 10643.692 | U20: 408.86824 | X20: 11052.56 | Y20: 1743.8213 | AA20: 6.0308065 | AB20: 1749.8521 | AC20: 7.26 | AD20: 12703.926 | AE20: 23756.487 | AF20: 1212.0534
C21: 240715000049 | D21: 45490 | E21: Sam.Pao | F21: Sam.Pao | G21: Yusky | H21: 5.0829 | I21: 911 | J21: 10979.06 | P21: 10979.06 | S21: 4670.0639 | U21: 179.39647 | X21: 4849.4603 | Y21: 765.1252 | AA21: 2.6460979 | AB21: 767.7713 | AC21: 7.26 | AD21: 5574.0196 | AE21: 10423.48 | AF21: 555.58004
C22: 240716000037 | D22: 45490 | E22: Sam.Pao | F22: Sam.Pao | G22: SKY JET | H22: 23.75 | I22: 3022 | J22: 41995.7 | P22: 41995.7 | S22: 21821.011 | U22: 838.23529 | X22: 22659.246 | Y22: 3575.07 | AA22: 12.363971 | AB22: 3587.434 | AC22: 7.26 | AD22: 26044.771 | AE22: 48704.017 | AF22: -6708.3172
C23: 240724000022 | D23: 45498 | E23: Sam.Pao | F23: Sam.Pao | G23: Yusky | H23: 6.0843 | I23: 633 | J23: 12265.92 | P23: 12265.92 | S23: 5500.6546 | T23: 53.685 | U23: 102.89625 | X23: 5657.2358 | Y23: 940.41178 | AA23: 3.167415 | AB23: 943.57919 | AC23: 7.06 | AD23: 6661.6691 | AE23: 12318.905 | AF23: -52.984919
C24: 240724000024 | D24: 45498 | E24: Sam.Pao | F24: Sam.Pao | G24: Yusky | H24: 0.6352 | I24: 38 | J24: 1280.59 | P24: 1280.59 | S24: 574.26751 | T24: 5.6047059 | U24: 10.742353 | X24: 590.61456 | Y24: 98.178847 | AA24: 0.33067765 | AB24: 98.509525 | AC24: 7.06 | AD24: 695.47725 | AE24: 1286.0918 | AF24: -5.5018108
C25: 240724000044 | D25: 45498 | E25: Sam.Pao | F25: Sam.Pao | G25: SKY JET | H25: 20.87 | I25: 2559.5 | J25: 34224.71 | P25: 34224.71 | S25: 18868.015 | T25: 184.14706 | U25: 352.94853 | X25: 19405.11 | Y25: 3225.7439 | AA25: 10.864676 | AB25: 3236.6086 | AC25: 7.06 | AD25: 22850.457 | AE25: 42255.567 | AF25: -8030.8569
C26: 240724000046 | D26: 45498 | E26: Sam.Pao | F26: Sam.Pao | G26: Yusky | H26: 0.6621 | I26: 270 | J26: 1334.81 | P26: 1334.81 | S26: 598.58708 | T26: 5.8420588 | U26: 11.197279 | X26: 615.62642 | Y26: 102.33661 | AA26: 0.34468147 | AB26: 102.68129 | AC26: 7.06 | AD26: 724.92992 | AE26: 1340.5563 | AF26: -5.7463412
C27: 240724000047 | D27: 45498 | E27: Sam.Pao | F27: Sam.Pao | G27: Yusky | H27: 0.2282 | I27: 54 | J27: 460.08 | P27: 460.08 | S27: 206.30958 | T27: 2.0135294 | U27: 3.8592647 | X27: 212.18237 | Y27: 35.271431 | AA27: 0.11879824 | AB27: 35.390229 | AC27: 7.06 | AD27: 249.85502 | AE27: 462.03739 | AF27: -1.9573917
C28: 240724000048 | D28: 45498 | E28: Sam.Pao | F28: Sam.Pao | G28: Yusky | H28: 3.0687 | I28: 528 | J28: 6208.07 | P28: 6208.07 | S28: 2774.3304 | T28: 27.076765 | U28: 51.897132 | X28: 2853.3043 | Y28: 474.30955 | AA28: 1.5975291 | AB28: 475.90708 | AC28: 7.06 | AD28: 3359.904 | AE28: 6213.2083 | AF28: -5.1383435
C29: 240724000054 | D29: 45498 | E29: Sam.Pao | F29: Sam.Pao | G29: LuZhiLong | H29: 2.7 | I29: 992.8 | J29: 6294.95 | P29: 6294.95 | S29: 2440.9985 | T29: 23.823529 | U29: 45.661765 | X29: 2510.4838 | Y29: 417.32193 | AA29: 1.4055882 | AB29: 418.72751 | AC29: 7.06 | AD29: 2956.2163 | AE29: 5466.7001 | AF29: 828.24992
C30: 240725000032 | D30: 45498 | E30: Sam.Pao | F30: Sam.Pao | G30: Yusky | H30: 0.3976 | I30: 178 | J30: 807.14 | P30: 807.14 | S30: 359.45964 | T30: 3.5082353 | U30: 6.7241176 | X30: 369.69199 | Y30: 61.454518 | AA30: 0.20698588 | AB30: 61.661504 | AC30: 7.06 | AD30: 435.33022 | AE30: 805.0222 | AF30: 2.117796
A31: 合计 | AF31: =SUM(AF5:AF30) -> -14895.505
C33: 基本任务：小于6千 | F33: 不够基本任务6千， 公司将根据空运提成里抽出补足基数 | K33: 浦生 提成
K34: 名称 | L34: 计费体积 | M34: 毛利
C35: 基本任务：6千-3.5万 | F35: 按40%提成 | K35: LOS | L35: =SUM(H5:H30) -> 227.3649 | M35: =SUM(AF31) -> -14895.505
K36: 基数 | M36: 6000
C37: 基本任务：3.5万以上 | F37: 按50%提成 | K37: 提成计数 | M37: =SUM(M35-M36) -> -20895.505
K38: 提成点数
K39: 提成金额

Sheet 无人
A1: LOS毛利表
A3: JOB | B3: 集装编号 | C3: 运单编号 | D3: 日期 | E3: 业务 | F3: 发货人 | G3: 收货人 | H3: 计费体积 | I3: 计费重量 | J3: 应 收 | Q3: 总应收 | R3: 起 运 港 成 本 | W3: 代垫运费 | X3: 起运港成本 合计 | Y3: 目的港成本 | AE3: 总支出 | AF3: 利润
J4: 应收RMB | K4: LOS Income(NGN)收到(奈拉) | L4: LOS 收到USD | M4: 美元汇率 dollar currency rate | N4: 应收 到付款USD | O4: 汇率 | P4: 人民币 | R4: 代理商 | S4: 运费+出口报关费 | T4: 提货费 | U4: 装卸费 | V4: 包装费 | Y4: 进口报关费 | Z4: 到门配送费 | AA4: 转运费 | AB4: 目的港支出 | AC4: 汇率 | AD4: 人民币 | AE4: 起运港+目的港
C5: 240701000054 | D5: 45477 | E5: 无人 | F5: Mailmail Abv sales person 1 | G5: Adams | H5: 2.5358 | I5: 1140 | K5: 1490760 | M5: 1639.9991 | N5: 909.0005 | O5: 7.12 | P5: 6472.0836 | S5: 2292.5497 | U5: 46.613971 | V5: 120 | X5: 2459.1636 | Y5: 396.78744 | AB5: 396.78744 | AC5: 7.1 | AD5: 2817.1908 | AE5: 5276.3545 | AF5: 1195.7291
A6: 合计 | AF6: =SUM(AF5:AF5) -> 1195.7291
C8: 基本任务：小于6千 | F8: 不够基本任务6千， 公司将根据空运提成里抽出补足基数 | K8: 无人 提成
K9: 名称 | L9: 计费体积 | M9: 毛利
C10: 基本任务：6千-3.5万 | F10: 按40%提成 | K10: LOS | L10: =SUM(H5) -> 2.5358 | M10: =SUM(AF6) -> 1195.7291
K11: 基数 | M11: 6000
C12: 基本任务：3.5万以上 | F12: 按50%提成 | K12: 提成计数 | M12: =SUM(M10-M11) -> -4804.2709
K13: 提成点数
K14: 提成金额

Sheet 提成总表
A1: 24年7月份业务员提成总表-68³
A3: 名称 姓名 | B3: LOS毛利 | C3: 计费体积 立方 | D3: 6千-3.5万 | I3: 3.5万以上 | M3: 合计 提成金额 | N3: 备注 | P3: 基本任务：小于6千 | R3: 不够基本任务6千， 公司将根据空运提成里抽出补足基数
D4: 基数 | E4: 提成计数 | F4: 提成计数 | G4: 提成点 数40% | H4: 提成金额 | I4: 基数 | J4: 提成计数 | K4: 提成点 数50% | L4: 提成金额
A5: 黄 颖 | B5: =SUM(黄颖!M24) -> 55871.515 | C5: =SUM(黄颖!L24) -> 53.034 | D5: 6000 | E5: =SUM(B5-D5) -> 49871.515 | F5: 35000 | G5: 0.4 | H5: =SUM(F5*G5) -> 14000 | I5: 35000 | J5: =SUM(E5-I5) -> 14871.515 | K5: 0.5 | L5: =SUM(J5*K5) -> 7435.7573 | M5: =SUM(H5+L5) -> 21435.757 | P5: 基本任务：6千-3.5万 | R5: 按40%提成
A6: 陈三凤 | B6: =SUM(三凤!M10) -> 2927.8738 | C6: =SUM(三凤!L10) -> 16.6069 | E6: =SUM(B6-D6) -> 2927.8738 | G6: 0.1 | H6: =SUM(E6*G6) -> 292.78738 | M6: =SUM(H6+L6) -> 292.78738 | N6: 小飞6-7月份原方案10% （减james利润的一半186.8）
A7: 朱小飞 | B7: =SUM(朱小飞!M20) -> 11639.345 | C7: =SUM(朱小飞!L20) -> 11.8325 | E7: =SUM(B7-D7) -> 11639.345 | G7: 0.1 | H7: =SUM(E7*G7) -> 1163.9345 | M7: =SUM(H7+L7) -> 1163.9345 | N7: 小飞6-7月份原方案10% （Halifa利润的一半1888.28） | P7: 基本任务：3.5万以上 | R7: 按50%提成
A8: 陆总 | B8: =SUM(陆总!M13) -> 16092.639 | C8: =SUM(陆总!L13) -> 46.098 | G8: 0.4 | H8: =SUM(B8*G8) -> 6437.0556 | M8: =SUM(H8+L8) -> 6437.0556
A9: 罗伟健 | B9: =SUM(罗伟健!M10) -> 3605.0851 | C9: =SUM(罗伟健!L10) -> 0.2991 | M9: 7815.24 | N9: 空运毛利4210.15加海运3605.09=7815.24，不达标
A10: 吕沛霖 | B10: =SUM(吕沛霖!M14) -> 4730.4657 | C10: =SUM(吕沛霖!L14) -> 4.2378 | D10: 6663.1356 | E10: =SUM(B10-D10) -> -1932.6699 | N10: 不够基数，下个月基本数为8595.81
A11: 苏慧琪 | B11: =SUM(苏慧琪!M10) -> 381.01772 | C11: =SUM(苏慧琪!L10) -> 0.3636
A12: 浦海森 | B12: =SUM(浦生!M35) -> -14895.505 | C12: =SUM(浦生!L35) -> 227.3649 | D12: 6000 | E12: =SUM(B12-D12) -> -20895.505 | P12: 领款人：
A13: 无人 | B13: =SUM(无人!M10) -> 1195.7291 | C13: =SUM(无人!L10) -> 2.5358 | P13: 日期：
A14: 合计 | B14: =SUM(B5:B13) -> 81548.165 | C14: =SUM(C5:C13) -> 362.3726 | M14: =SUM(M5:M10) -> 37144.775
A16: 确认人： | J16: 日期：

Sheet 黄颖 陈三凤 朱小飞 吕沛霖 2025年10月份发放
A1: 24年7月份业务员提成总表-68³
A3: 名称 姓名 | B3: LOS毛利 | C3: 计费体积 立方 | D3: 6千-3.5万 | I3: 3.5万以上 | M3: 合计 提成金额 | N3: 备注
D4: 基数 | E4: 提成计数 | F4: 提成计数 | G4: 提成点 数40% | H4: 提成金额 | I4: 基数 | J4: 提成计数 | K4: 提成点 数50% | L4: 提成金额
A5: 黄 颖 | B5: =SUM(黄颖!M24) -> 55871.515 | C5: =SUM(黄颖!L24) -> 53.034 | D5: 6000 | E5: =SUM(B5-D5) -> 49871.515 | F5: 35000 | G5: 0.4 | H5: =SUM(F5*G5) -> 14000 | I5: 35000 | J5: =SUM(E5-I5) -> 14871.515 | K5: 0.5 | L5: =SUM(J5*K5) -> 7435.7573 | M5: =SUM(H5+L5) -> 21435.757
L6: 领款人：
A7: 陈三凤 | B7: =SUM(三凤!M10) -> 2927.8738 | C7: =SUM(三凤!L10) -> 16.6069 | E7: =SUM(B7-D7) -> 2927.8738 | G7: 0.1 | H7: =SUM(E7*G7) -> 292.78738 | M7: =SUM(H7+L7) -> 292.78738 | N7: 小飞6-7月份原方案10% （减james利润的一半186.8）
L8: 领款人：
A9: 朱小飞 | B9: =SUM(朱小飞!M20) -> 11639.345 | C9: =SUM(朱小飞!L20) -> 11.8325 | E9: =SUM(B9-D9) -> 11639.345 | G9: 0.1 | H9: =SUM(E9*G9) -> 1163.9345 | M9: =SUM(H9+L9) -> 1163.9345 | N9: 小飞6-7月份原方案10% （Halifa利润的一半1888.28）
L10: 领款人：
A11: 吕沛霖 | B11: =SUM(吕沛霖!M14) -> 4730.4657 | C11: =SUM(吕沛霖!L14) -> 4.2378 | D11: 6663.1356 | E11: =SUM(B11-D11) -> -1932.6699 | N11: 不够基数，下个月基本数为8595.81
L12: 确认人：
A13: 合计 | B13: =SUM(B5:B11) -> 75169.199 | C13: =SUM(C5:C11) -> 85.7112 | M13: =SUM(M5:M11) -> 22892.479
A15: 确认人： | J15: 日期：
