Workbook

Sheet 黄颖
A1: LOS毛利表
A3: JOB | B3: 集装编号 | C3: 运单编号 | D3: 日期 | E3: 业务 | F3: 发货人 | G3: 收货人 | H3: 计费体积 | I3: 计费重量 | J3: 应 收 | Q3: 总应收 | R3: 起 运 港 成 本 | W3: 代垫运费 | X3: 起运港成本 合计 | Y3: 目的港成本 | AE3: 总支出 | AF3: 利润
J4: 应收RMB | K4: LOS Income(NGN)收到(奈拉) | L4: LOS 收到USD | M4: 美元汇率 dollar currency rate | N4: 应收 到付款USD | O4: 汇率 | P4: 人民币 | R4: 代理商 | S4: 运费+出口报关费 | T4: 提货费 | U4: 装卸费 | V4: 包装费 | Y4: 进口报关费 | Z4: 到门配送费 | AA4: 转运费 | AB4: 目的港支出 | AC4: 汇率 | AD4: 人民币 | AE4: 起运港+目的港
A5: JOB060384 | B5: COLL004033 | C5: 240611000035 | D5: 45470 | E5: 黄颖 | F5: ying | G5: Zhangqing | H5: 9.409 | I5: 4580 | J5: 30088 | P5: 30088 | Q5: 67487.589 | R5: 华茂青松 | S5: 9052.8417 | T5: 73.749956 | U5: 117.6125 | X5: 9244.2041 | Y5: 1472.8088 | AA5: 6.0272947 | AB5: 1478.8361 | AC5: 7.12 | AD5: 10529.313 | AE5: 19773.517 | AF5: 10314.483
C6: 240624000032 | D6: 45470 | E6: 黄颖 | F6: ying | G6: chuks | H6: 14.1194 | I6: 5232 | J6: 30090 | P6: 30090 | S6: 13584.939 | T6: 110.67118 | U6: 176.4925 | X6: 13872.103 | Y6: 2210.1367 | AA6: 9.0447215 | AB6: 2219.1814 | AC6: 7.12 | AD6: 15800.572 | AE6: 29672.674 | AF6: 417.3256
C7: 240624000052 | D7: 45470 | E7: 黄颖 | F7: ying | G7: Adindu | H7: 0.098 | I7: 5.56 | K7: 69566 | M7: 1639.934 | N7: 42.42 | O7: 7.12 | P7: 302.0304 | S7: 94.290412 | T7: 0.76814706 | U7: 1.225 | X7: 96.283559 | Y7: 15.340127 | Z7: 5.48 | AA7: 0.062777647 | AB7: 20.882905 | AC7: 7.12 | AD7: 148.68628 | AE7: 244.96984 | AF7: 57.060558
A8: 合 计 | H8: =SUM(H5:H7) -> 23.6264 | AF8: =SUM(AF5:AF7) -> 10788.869
C10: 基本任务：小于6千 | F10: 不够基本任务6千， 公司将根据空运提成里抽出补足基数 | K10: 黄颖 提成
K11: 名称 | L11: 计费体积 | M11: 毛利
C12: 基本任务：6千-3.5万 | F12: 按40%提成 | K12: LOS | L12: =SUM(H5:H7) -> 23.6264 | M12: =SUM(AF8) -> 10788.869
K13: 基数 | M13: 6000
C14: 基本任务：3.5万以上 | F14: 按50%提成 | K14: 提成计数 | M14: =SUM(M12-M13) -> 4788.8693
K15: 提成点数 | M15: 0.4
K16: 提成金额 | M16: =SUM(M14*M15) -> 1915.5477

Sheet 三凤
A1: LOS毛利表
A2: JOB | B2: 集装编号 | C2: 运单编号 | D2: 日期 | E2: 业务 | F2: 发货人 | G2: 收货人 | H2: 计费体积 | I2: 计费重量 | J2: 应 收 | Q2: 总应收 | R2: 起 运 港 成 本 | W2: 代垫运费 | X2: 起运港成本 合计 | Y2: 目的港成本 | AE2: 总支出 | AF2: 利润
J3: 应收RMB | K3: LOS Income(NGN)收到(奈拉) | L3: LOS 收到USD | M3: 美元汇率 dollar currency rate | N3: 应收 到付款USD | O3: 汇率 | P3: 人民币 | R3: 代理商 | S3: 运费+出口报关费 | T3: 提货费 | U3: 装卸费 | V3: 包装费 | Y3: 进口报关费 | Z3: 到门配送费 | AA3: 转运费 | AB3: 目的港支出 | AC3: 汇率 | AD3: 人民币 | AE3: 起运港+目的港
A4: JOB060359 | B4: COLL004009 | C4: 240605000016 | D4: 45456 | E4: Bella | F4: Bella Chan | G4: james | H4: 1.9688 | I4: 441 | L4: 807.21 | M4: 0 | N4: 807.21 | O4: 7.12 | P4: 5747.3352 | Q4: 15233.452 | R4: 智托（陆总代付） | S4: 4505.5209 | T4: 36.032211 | X4: 4541.5531 | AB4: 0 | AD4: 0 | AE4: 4541.5531 | AF4: 1205.7821
C5: 240611000023 | D5: 45456 | E5: Bella | F5: Bella Chan | G5: Shuaibu musa | H5: 3.0276 | I5: 667 | K5: 2173116 | M5: 1631.0769 | N5: 1332.3198 | O5: 7.12 | P5: 9486.117 | S5: 6928.5427 | T5: 55.409956 | X5: 6983.9527 | AB5: 0 | AD5: 0 | AE5: 6983.9527 | AF5: 2502.1643
C6: 240617000031 | D6: 45470 | E6: Bella | F6: Bella Chan | G6: zhang jian fei | H6: 1.883 | I6: 1442 | J6: 5247 | P6: 5247 | S6: 1811.7229 | T6: 14.759397 | U6: 23.5375 | X6: 1850.0198 | Y6: 294.74959 | Z6: 5.56 | AA6: 1.2062276 | AB6: 301.51582 | AC6: 7.12 | AD6: 2146.7926 | AE6: 3996.8124 | AF6: 1250.1876
C7: 240617000031 | D7: 45470 | E7: Bella | F7: Bella Chan | G7: zhang jian fei | H7: 0.1218 | I7: 88 | J7: 339 | P7: 339 | S7: 250.25122 | T7: 2.646462 | X7: 252.89768 | Y7: 2.7264341 | AB7: 2.7264341 | AC7: 7.1 | AD7: 19.357682 | AE7: 272.25536 | AF7: 66.744636
A8: 合 计 | H8: =SUM(H4:H7) -> 7.0012 | AF8: =SUM(AF4:AF7) -> 5024.8786
C10: 基本任务：小于6千 | F10: 不够基本任务6千， 公司将根据空运提成里抽出补足基数 | K10: 三凤 提成
K11: 名称 | L11: 计费体积 | M11: 毛利 | N11: 备注
C12: 基本任务：6千-3.5万 | F12: 按40%提成 | K12: LOS | L12: =SUM(H4:H7) -> 7.0012 | M12: 4421.99 | N12: 总利润减james 利润的 一半602.89
K13: 基数
C14: 基本任务：3.5万以上 | F14: 按50%提成 | K14: 提成计数
K15: 提成点数 | M15: 0.1
K16: 提成金额 | M16: =SUM(M12*M15) -> 442.199

Sheet 朱小飞
A1: LOS毛利表
A3: JOB | B3: 集装编号 | C3: 运单编号 | D3: 日期 | E3: 业务 | F3: 发货人 | G3: 收货人 | H3: 计费体积 | I3: 计费重量 | J3: 应 收 | Q3: 总应收 | R3: 起 运 港 成 本 | W3: 代垫运费 | X3: 起运港成本 合计 | Y3: 目的港成本 | AE3: 总支出 | AF3: 利润
J4: 应收RMB | K4: LOS Income(NGN)收到(奈拉) | L4: LOS 收到USD | M4: 美元汇率 dollar currency rate | N4: 应收 到付款USD | O4: 汇率 | P4: 人民币 | R4: 代理商 | S4: 运费+出口报关费 | T4: 提货费 | U4: 装卸费 | V4: 包装费 | Y4: 进口报关费 | Z4: 到门配送费 | AA4: 转运费 | AB4: 目的港支出 | AC4: 汇率 | AD4: 人民币 | AE4: 起运港+目的港
C5: 240608000016 | D5: 45456 | E5: 朱小飞 | F5: Isabel Zhu | G5: Halifa Success | H5: 0.6486 | I5: 105 | J5: 1701.18 | P5: 1701.18 | S5: 1484.2954 | T5: 11.870425 | X5: 1496.1658 | AB5: 0 | AD5: 0 | AE5: 1496.1658 | AF5: 205.01415
C6: 240618000013 | D6: 45470 | E6: 朱小飞 | F6: Isabel Zhu | G6: Lilon | H6: 17.0878 | I6: 12818 | J6: 44822.88 | P6: 44822.88 | S6: 16440.977 | T6: 133.9382 | U6: 213.5975 | X6: 16788.512 | Y6: 2674.786 | AA6: 10.946244 | AB6: 2685.7322 | AC6: 7.12 | AD6: 19122.414 | AE6: 35910.926 | AF6: 8911.9542
C7: 240627000004 | D7: 45470 | E7: 朱小飞 | F7: Isabel Zhu | G7: Victor Nnamdi | H7: 1.0982 | I7: 111.44 | K7: 649440 | M7: 1640 | N7: 396 | O7: 7.12 | P7: 2819.52 | S7: 1056.6299 | T7: 8.60795 | U7: 13.7275 | X7: 1078.9653 | Y7: 171.90335 | AA7: 0.703494 | AB7: 172.60684 | AC7: 7.12 | AD7: 1228.9607 | AE7: 2307.926 | AF7: 511.59395
A8: JOB060385 | B8: COLL004034 | C8: 240619000007 | D8: 45471 | E8: 朱小飞 | F8: Isabel Zhu | G8: Jiang Li | H8: 0.917 | I8: 510 | J8: 2914 | P8: 2914 | Q8: 26109.822 | R8: 赛捷 | S8: 1884.0753 | T8: 19.924513 | X8: 1903.9998 | Y8: 20.526602 | Z8: 73.61 | AB8: 94.136602 | AC8: 7.1 | AD8: 668.36987 | AE8: 2572.3697 | AF8: 341.63034
C9: 240626000021 | D9: 45470 | E9: 朱小飞 | F9: Isabel Zhu | G9: Ife Oyelami | H9: 0.5044 | I9: 54.9 | K9: 311202 | M9: 1695 | N9: 183.6 | O9: 7.12 | P9: 1307.232 | S9: 1036.3441 | T9: 10.959568 | X9: 1047.3037 | Y9: 11.29075 | AB9: 11.29075 | AC9: 7.1 | AD9: 80.164327 | AE9: 1127.468 | AF9: 179.76397
C10: 240627000005 | D10: 45471 | E10: 朱小飞 | F10: Isabel Zhu | G10: Jiang Li | H10: 0.2937 | I10: 24 | J10: 778 | P10: 778 | S10: 603.43829 | T10: 6.3814934 | X10: 609.81978 | Y10: 6.5743326 | AB10: 6.5743326 | AC10: 7.1 | AD10: 46.677761 | AE10: 656.49754 | AF10: 121.50246
A11: 合计 | H11: =SUM(H5:H10) -> 20.5497 | AF11: =SUM(AF5:AF10) -> 10271.459
AF12: 102.55
C13: 基本任务：小于6千 | F13: 不够基本任务6千， 公司将根据空运提成里抽出补足基数 | K13: 朱小飞 提成 | AF13: =SUM(AF11-AF12) -> 10168.909
K14: 名称 | L14: 计费体积 | M14: 毛利 | N14: 备注
C15: 基本任务：6千-3.5万 | F15: 按40%提成 | K15: LOS | L15: =SUM(H5:H10) -> 20.5497 | M15: 10168.909 | N15: 总利润减Halifa 利润的 一半102.55
K16: 基数
C17: 基本任务：3.5万以上 | F17: 按50%提成 | K17: 提成计数
K18: 提成点数 | M18: 0.1
K19: 提成金额 | M19: =SUM(M15*M18) -> 1016.8909

Sheet 吕沛霖
A1: LOS毛利表
A2: JOB | B2: 集装编号 | C2: 运单编号 | D2: 日期 | E2: 业务 | F2: 发货人 | G2: 收货人 | H2: 计费体积 | I2: 计费重量 | J2: 应 收 | Q2: 总应收 | R2: 起 运 港 成 本 | W2: 代垫运费 | X2: 起运港成本 合计 | Y2: 目的港成本 | AE2: 总支出 | AF2: 利润
J3: 应收RMB | K3: LOS Income(NGN)收到(奈拉) | L3: LOS 收到USD | M3: 美元汇率 dollar currency rate | N3: 应收 到付款USD | O3: 汇率 | P3: 人民币 | R3: 代理商 | S3: 运费+出口报关费 | T3: 提货费 | U3: 装卸费 | V3: 包装费 | Y3: 进口报关费 | Z3: 到门配送费 | AA3: 转运费 | AB3: 目的港支出 | AC3: 汇率 | AD3: 人民币 | AE3: 起运港+目的港
C4: 240617000014 | D4: 45470 | E4: 吕沛霖 | F4: 喵喵速运-Layne | G4: Abdulsheldu | H4: 0.3223 | I4: 145 | K4: 282730 | M4: 1744.4931 | N4: 162.07 | O4: 7.12 | P4: 1153.9384 | S4: 310.1 | T4: 2.5262632 | U4: 4.02875 | X4: 316.65501 | Y4: 50.450235 | Z4: 17.26 | AA4: 0.20646159 | AB4: 67.916697 | AC4: 7.12 | AD4: 483.56688 | AE4: 800.22189 | AF4: 353.71651
C5: 240621000002 | D5: 45470 | E5: 吕沛霖 | F5: 喵喵速运-Layne | G5: Ka Ka 4分部 | H5: 7.215 | I5: 975 | J5: 21110.59 | P5: 21110.59 | S5: 14823.995 | T5: 156.76702 | X5: 14980.762 | Y5: 161.50429 | AB5: 161.50429 | AC5: 7.1 | AD5: 1146.6804 | AE5: 16127.442 | AF5: 4983.1479
A6: 合计 | H6: =SUM(H4:H5) -> 7.5373 | AF6: =SUM(AF4:AF5) -> 5336.8644
C9: 基本任务：小于6千 | F9: 不够基本任务6千， 公司将根据空运提成里抽出补足基数 | K9: 吕沛霖 提成
K10: 名称 | L10: 计费体积 | M10: 毛利
C11: 基本任务：6千-3.5万 | F11: 按40%提成 | K11: LOS | L11: =SUM(H6) -> 7.5373 | M11: =SUM(AF6) -> 5336.8644
K12: 基数 | M12: 6000
C13: 基本任务：3.5万以上 | F13: 按50%提成 | K13: 提成计数 | M13: =SUM(M11-M12) -> -663.13563
K14: 提成点数
K15: 提成金额 | L15: 下个月基数为 | M15: =SUM(M12-M13) -> 6663.1356

Sheet 陆总
A1: LOS毛利表
A3: JOB | B3: 集装编号 | C3: 运单编号 | D3: 日期 | E3: 业务 | F3: 发货人 | G3: 收货人 | H3: 计费体积 | I3: 计费重量 | J3: 应 收 | Q3: 总应收 | R3: 起 运 港 成 本 | W3: 代垫运费 | X3: 起运港成本 合计 | Y3: 目的港成本 | AE3: 总支出 | AF3: 利润
J4: 应收RMB | K4: LOS Income(NGN)收到(奈拉) | L4: LOS 收到USD | M4: 美元汇率 dollar currency rate | N4: 应收 到付款USD | O4: 汇率 | P4: 人民币 | R4: 代理商 | S4: 运费+出口报关费 | T4: 提货费 | U4: 装卸费 | V4: 包装费 | Y4: 进口报关费 | Z4: 到门配送费 | AA4: 转运费 | AB4: 目的港支出 | AC4: 汇率 | AD4: 人民币 | AE4: 起运港+目的港
C5: 241031000031 | D5: 45456 | E5: 陆总 | F5: Shirley | G5: LUZILONG | H5: 4.4495 | I5: 795 | J5: 10251.65 | P5: 10251.65 | S5: 10182.505 | T5: 81.433016 | X5: 10263.938 | AB5: 0 | AD5: 0 | AE5: 10263.938 | AF5: -12.287622
C6: 240626000037 | D6: 45470 | E6: 陆总 | F6: Sam.Pao | G6: LuZhiLong | H6: 0.9428 | I6: 188 | J6: 3034.1 | P6: 3034.1 | S6: 907.11225 | T6: 7.3898882 | U6: 11.785 | X6: 926.28714 | Y6: 147.57829 | AA6: 0.60394659 | AB6: 148.18223 | AC6: 7.12 | AD6: 1055.0575 | AE6: 1981.3446 | AF6: 1052.7554
C7: 240626000038 | D7: 45470 | E7: 陆总 | F7: Sam.Pao | G7: LuZhiLong | H7: 2.178 | I7: 178 | J7: 5331.74 | P7: 5331.74 | S7: 2095.5563 | T7: 17.071676 | U7: 27.225 | X7: 2139.853 | Y7: 340.9265 | AA7: 1.3952012 | AB7: 342.32171 | AC7: 7.12 | AD7: 2437.3305 | AE7: 4577.1835 | AF7: 754.55649
C8: 240626000039 | D8: 45470 | E8: 陆总 | F8: Sam.Pao | G8: LuZhiLong | H8: 1.1137 | I8: 719 | J8: 2807.28 | P8: 2807.28 | S8: 1071.5432 | T8: 8.7294426 | U8: 13.92125 | X8: 1094.1939 | Y8: 174.32959 | AA8: 0.71342312 | AB8: 175.04301 | AC8: 7.12 | AD8: 1246.3063 | AE8: 2340.5001 | AF8: 466.77987
A9: 合计 | H9: =SUM(H5:H8) -> 8.684 | AF9: =SUM(AF5:AF8) -> 2261.8041
C11: 基本任务：小于6千 | F11: 不够基本任务6千， 公司将根据空运提成里抽出补足基数 | K11: 陆总 提成
K12: 名称 | L12: 计费体积 | M12: 毛利
C13: 基本任务：6千-3.5万 | F13: 按40%提成 | K13: LOS | L13: =SUM(H5:H8) -> 8.684 | M13: =SUM(AF9) -> 2261.8041
K14: 提成计数 | M14: =SUM(M13:M13) -> 2261.8041
C15: 基本任务：3.5万以上 | F15: 按50%提成 | K15: 提成点数 | M15: 0.4
K16: 提成金额 | M16: =SUM(M14*M15) -> 904.72164

Sheet 浦生
A1: LOS毛利表
A3: JOB | B3: 集装编号 | C3: 运单编号 | D3: 日期 | E3: 业务 | F3: 发货人 | G3: 收货人 | H3: 计费体积 | I3: 计费重量 | J3: 应 收 | Q3: 总应收 | R3: 起 运 港 成 本 | W3: 代垫运费 | X3: 起运港成本 合计 | Y3: 目的港成本 | AE3: 总支出 | AF3: 利润
J4: 应收RMB | K4: LOS Income(NGN)收到(奈拉) | L4: LOS 收到USD | M4: 美元汇率 dollar currency rate | N4: 应收 到付款USD | O4: 汇率 | P4: 人民币 | R4: 代理商 | S4: 运费+出口报关费 | T4: 提货费 | U4: 装卸费 | V4: 包装费 | Y4: 进口报关费 | Z4: 到门配送费 | AA4: 转运费 | AB4: 目的港支出 | AC4: 汇率 | AD4: 人民币 | AE4: 起运港+目的港
C5: 240607000057 | D5: 45456 | E5: Sam.Pao | F5: Sam.Pao | G5: MaiKaiNian | H5: 3.5715 | I5: 587 | J5: 9711.62 | P5: 9711.62 | S5: 8173.2364 | T5: 65.364202 | X5: 8238.6006 | AB5: 0 | AD5: 0 | AE5: 8238.6006 | AF5: 1473.0194
C6: 240619000002 | D6: 45470 | E6: Sam.Pao | F6: Sam.Pao | G6: JUNDA YU | H6: 4.1762 | I6: 308 | J6: 10081.3 | P6: 10081.3 | S6: 4018.1185 | T6: 32.734038 | U6: 52.2025 | X6: 4103.0551 | Y6: 653.70857 | AA6: 2.6752246 | AB6: 656.38379 | AC6: 7.12 | AD6: 4673.4526 | AE6: 8776.5077 | AF6: 1304.7923
C7: 240622000007 | D7: 45470 | E7: Sam.Pao | F7: Sam.Pao | G7: MaiKaiNian | H7: 0.1344 | I7: 44 | J7: 426 | P7: 426 | S7: 129.31256 | T7: 1.0534588 | U7: 1.68 | X7: 132.04602 | Y7: 21.037889 | AA7: 0.086095059 | AB7: 21.123984 | AC7: 7.12 | AD7: 150.40277 | AE7: 282.44879 | AF7: 143.55121
C8: 240625000041 | D8: 45470 | E8: Sam.Pao | F8: Sam.Pao | G8: SKY JET | H8: 19.56 | I8: 2429.25 | J8: 35563.01 | P8: 35563.01 | S8: 18819.596 | T8: 153.31588 | U8: 244.5 | X8: 19217.412 | Y8: 3061.7642 | AA8: 12.529906 | AB8: 3074.2941 | AC8: 7.12 | AD8: 21888.974 | AE8: 41106.386 | AF8: -5543.3763
C9: 240627000022 | D9: 45470 | E9: Sam.Pao | F9: Sam.Pao | G9: JunYue hotel | H9: 0.8852 | I9: 140.4 | J9: 2136.9 | P9: 2136.9 | S9: 851.69258 | T9: 6.9384059 | U9: 11.065 | X9: 869.69598 | Y9: 138.56205 | AA9: 0.56704871 | AB9: 139.1291 | AC9: 7.12 | AD9: 990.59917 | AE9: 1860.2952 | AF9: 276.60485
C10: 240625000038 | D10: 45471 | E10: Sam.Pao | F10: Sam.Pao | G10: MaiKaiNian | H10: 0.8478 | I10: 220 | J10: 2197.44 | P10: 2197.44 | S10: 1741.8964 | T10: 18.42094 | X10: 1760.3174 | Y10: 18.977593 | AB10: 18.977593 | AC10: 7.1 | AD10: 134.74091 | AE10: 1895.0583 | AF10: 302.38173
A11: 合计 | H11: =SUM(H5:H10) -> 29.1751 | AF11: =SUM(AF5:AF10) -> -2043.0268
C13: 基本任务：小于6千 | F13: 不够基本任务6千， 公司将根据空运提成里抽出补足基数 | K13: 浦生 提成
K14: 名称 | L14: 计费体积 | M14: 毛利
C15: 基本任务：6千-3.5万 | F15: 按40%提成 | K15: LOS | L15: =SUM(浦生!H5:H10) -> 29.1751 | M15: =SUM(AF11) -> -2043.0268
K16: 基数 | M16: 6000
C17: 基本任务：3.5万以上 | F17: 按50%提成 | K17: 提成计数 | M17: =SUM(M15-M16) -> -8043.0268
K18: 提成点数
K19: 提成金额

Sheet 提成总表
A1: 24年6月份业务员提成总表-68³
A3: 名称 姓名 | B3: LOS毛利 | C3: 计费体积 立方 | D3: 6千-3.5万 | I3: 3.5万以上 | M3: 合计 提成金额 | N3: 备注 | P3: 基本任务：小于6千 | R3: 不够基本任务6千， 公司将根据空运提成里抽出补足基数
D4: 基数 | E4: 提成计数 | F4: 提成计数 | G4: 提成点 数40% | H4: 提成金额 | I4: 基数 | J4: 提成计数 | K4: 提成点 数50% | L4: 提成金额
A5: 黄 颖 | B5: =SUM(黄颖!M12) -> 10788.869 | C5: =SUM(黄颖!L12) -> 23.6264 | D5: 6000 | E5: =SUM(B5-D5) -> 4788.8693 | G5: 0.4 | H5: =SUM(E5*G5) -> 1915.5477 | M5: =SUM(H5+L5) -> 1915.5477 | P5: 基本任务：6千-3.5万 | R5: 按40%提成
A6: 陈三凤 | B6: =SUM(三凤!M12) -> 4421.99 | C6: =SUM(三凤!L12) -> 7.0012 | E6: =SUM(B6-D6) -> 4421.99 | G6: 0.1 | H6: =SUM(E6*G6) -> 442.199 | M6: =SUM(H6+L6) -> 442.199 | N6: 小飞6-7月份原方案10% （减james利润的一半602.89）
A7: 朱小飞 | B7: =SUM(朱小飞!M15) -> 10168.909 | C7: =SUM(朱小飞!L15) -> 20.5497 | E7: =SUM(B7-D7) -> 10168.909 | G7: 0.1 | H7: =SUM(E7*G7) -> 1016.8909 | M7: =SUM(H7+L7) -> 1016.8909 | N7: 小飞6-7月份原方案10% （Halifa利润的一半102.55） | P7: 基本任务：3.5万以上 | R7: 按50%提成
A8: 陆总 | B8: =SUM(陆总!M13) -> 2261.8041 | C8: =SUM(陆总!L13) -> 8.684 | G8: 0.4 | H8: =SUM(B8*G8) -> 904.72164 | M8: =SUM(H8+L8) -> 904.72164
A9: 吕沛霖 | B9: =SUM(吕沛霖!M11) -> 5336.8644 | C9: =SUM(吕沛霖!L11) -> 7.5373 | D9: 6000 | E9: =SUM(B9-D9) -> -663.13563 | N9: 不够基数，下个月基本数为6663.14
A10: 浦海森 | B10: =SUM(浦生!M15) -> -2043.0268 | C10: =SUM([1]浦生!L15) -> 29.1751 | D10: 6000 | E10: =SUM(B10-D10) -> -8043.0268
A11: 合计 | B11: =SUM(B5:B10) -> 30935.41 | C11: =SUM(C5:C10) -> 96.5737 | M11: =SUM(M5:M10) -> 4279.3593
A13: 确认人： | J13: 日期：
L15: 领款人：
L16: 日期：

Sheet 提成总表 黄颖 三凤 朱小飞 吕沛霖 2025年10份发放
A1: 24年6月份业务员提成总表-68³
A3: 名称 姓名 | B3: LOS毛利 | C3: 计费体积 立方 | D3: 6千-3.5万 | I3: 3.5万以上 | M3: 合计 提成金额 | N3: 备注
D4: 基数 | E4: 提成计数 | F4: 提成计数 | G4: 提成点 数40% | H4: 提成金额 | I4: 基数 | J4: 提成计数 | K4: 提成点 数50% | L4: 提成金额
A5: 黄 颖 | B5: =SUM(黄颖!M12) -> 10788.869 | C5: =SUM(黄颖!L12) -> 23.6264 | D5: 6000 | E5: =SUM(B5-D5) -> 4788.8693 | G5: 0.4 | H5: =SUM(E5*G5) -> 1915.5477 | M5: =SUM(H5+L5) -> 1915.5477
L6: 领款人：
A7: 陈三凤 | B7: =SUM(三凤!M12) -> 4421.99 | C7: =SUM(三凤!L12) -> 7.0012 | E7: =SUM(B7-D7) -> 4421.99 | G7: 0.1 | H7: =SUM(E7*G7) -> 442.199 | M7: =SUM(H7+L7) -> 442.199 | N7: 小飞6-7月份原方案10% （减james利润的一半602.89）
L8: 领款人：
A9: 朱小飞 | B9: =SUM(朱小飞!M15) -> 10168.909 | C9: =SUM(朱小飞!L15) -> 20.5497 | E9: =SUM(B9-D9) -> 10168.909 | G9: 0.1 | H9: =SUM(E9*G9) -> 1016.8909 | M9: =SUM(H9+L9) -> 1016.8909 | N9: 小飞6-7月份原方案10% （Halifa利润的一半102.55）
L10: 领款人：
A11: 吕沛霖 | B11: =SUM(吕沛霖!M11) -> 5336.8644 | C11: =SUM(吕沛霖!L11) -> 7.5373 | D11: 6000 | E11: =SUM(B11-D11) -> -663.13563 | N11: 不够基数，下个月基本数为6663.14
L12: 确认人：
A13: 合计 | B13: =SUM(B5:B11) -> 30716.633 | C13: =SUM(C5:C11) -> 58.7146 | M13: =SUM(M5:M11) -> 3374.6376
A15: 确认人： | J15: 日期：
