Workbook

Sheet 总表 
A1: 2024年10月份LOS毛利表（海运）
A2: JOB | B2: 集装编号 | C2: 利润
A4: JOB100358 | B4: COLL004182 | C4: =SUM('JOB100358'!AF26) -> 19174.556
A25: JOB100359 | B25: COLL004278 | C25: =SUM('JOB100359'!AF15) -> 12918.367
A35: JOB100360 | B35: COLL004247 | C35: =SUM('JOB100360'!AF15) -> 21765.368
A45: JOB100361 | B45: COLL004248 | C45: =SUM('JOB100361'!AF23) -> -2488.9901
A63: JOB100331 | B63: COLL004195 | C63: =SUM('JOB100331'!AF31) -> 15990.29
A89: JOB100362 | B89: COLL004260 | C89: =SUM('JOB100362'!AF26) -> 9117.6077
A110: JOB100363 | B110: COLL004265 | C110: =SUM('JOB100363'!AF30) -> 36506.369
A135: JOB100364 | B135: COLL004268 | C135: =SUM('JOB100364'!AF25) -> 15930.088
A155: JOB100365 | B155: COLL004270 | C155: =SUM('JOB100365'!AF14) -> -6520.687
A164: JOB100366 | B164: COLL004269 | C164: =SUM('JOB100366'!AF15) -> -1425.4322
A175: JOB120359 | B175: COLL004280 | C175: =SUM('JOB120359'!AF5) -> 11665.491
A176: 合计 | C176: =SUM(C3:C175) -> 132633.03

Sheet 总表  (2)
A1: 2024年10月份LOS毛利表（海运）
A2: JOB | B2: 集装编号 | C2: 运单编号 | D2: 日期 | E2: 业务 | F2: 发货人 | G2: 收货人 | H2: 计费体积 | I2: 计费重量 | J2: 应 收 | Q2: 总应收 | R2: 起 运 港 成 本 | W2: 代垫运费 | X2: 起运港成本 合计 | Y2: 目的港成本 | AE2: 总支出 | AF2: 利润
J3: 应收RMB | K3: LOS Income(NGN)收到(奈拉) | L3: LOS 收到USD | M3: 美元汇率 dollar currency rate | N3: 应收 到付款USD | O3: 汇率 | P3: 人民币 | R3: 代理商 | S3: 运费+出口报关费 | T3: 提货费 | U3: 装卸费 | V3: 包装费 | Y3: 进口报关费 | Z3: 到门配送费 | AA3: 转运费 | AB3: 目的港支出 | AC3: 汇率 | AD3: 人民币 | AE3: 起运港+目的港
A4: JOB100358 | B4: COLL004182 | C4: 240907000011 | D4: 45563 | E4: 吕沛霖 | F4: 喵喵速运-Layne | G4: MA ZONG | H4: 0.4074 | I4: 404 | J4: 1549.3 | P4: =SUBTOTAL(9,J4) -> 1549.3 | Q4: =SUM(P4:P24) -> 163992.94 | R4: 登凯=36617 赛捷=1660 拖车费=1670 杂费=499 过磅费=69 | S4: =SUM(40515/68)*H4 -> 242.73251 | U4: =SUM(2200/68)*H4 -> 13.180588 | X4: =SUM(S4:W4) -> 255.9131 | Y4: =SUM(10381.23/68)*H4 -> 62.195781 | Z4: 48.54 | AB4: =SUM(Y4:AA4) -> 110.73578 | AC4: 7.23 | AD4: =SUM(AB4*AC4) -> 800.6197 | AE4: =SUM(X4+AD4) -> 1056.5328 | AF4: =SUM(P4-AE4) -> 492.7672
C5: 240909000011 | D5: 45563 | E5: 黄颖 | F5: ying | G5: ying | H5: 0.036 | I5: 12 | K5: 87324 | M5: =SUM(K5/N5) -> 5916.2594 | N5: 14.760002 | O5: 7.24 | P5: =SUM(N5*O5) -> 106.86241 | S5: =SUM(40515/68)*H5 -> 21.449118 | U5: =SUM(2200/68)*H5 -> 1.1647059 | X5: =SUM(S5:W5) -> 22.613824 | Y5: =SUM(10381.23/68)*H5 -> 5.4959453 | Z5: 0.54 | AB5: =SUM(Y5:AA5) -> 6.0359453 | AC5: 7.23 | AD5: =SUM(AB5*AC5) -> 43.639884 | AE5: =SUM(X5+AD5) -> 66.253708 | AF5: =SUM(P5-AE5) -> 40.608706
C6: 240915000027 | D6: 45563 | E6: 吕沛霖 | F6: 喵喵速运-Layne | G6: Gao Hui | H6: 0.554 | I6: 177 | J6: 1986.97 | P6: =SUM(J6) -> 1986.97 | S6: =SUM(40515/68)*H6 -> 330.07809 | U6: =SUM(2200/68)*H6 -> 17.923529 | V6: 60 | X6: =SUM(S6:W6) -> 408.00162 | Y6: =SUM(10381.23/68)*H6 -> 84.576491 | Z6: 83.97 | AB6: =SUM(Y6:AA6) -> 168.54649 | AC6: 7.23 | AD6: =SUM(AB6*AC6) -> 1218.5911 | AE6: =SUM(X6+AD6) -> 1626.5928 | AF6: =SUM(P6-AE6) -> 360.37725
C7: 240919000042 | D7: 45563 | E7: 黄颖 | F7: ying | G7: MISS Huang | H7: 0.2211 | I7: 118 | J7: 468.7 | P7: =SUBTOTAL(9,J7) -> 468.7 | S7: =SUM(40515/68)*H7 -> 131.73333 | U7: =SUM(2200/68)*H7 -> 7.1532353 | X7: =SUM(S7:W7) -> 138.88657 | Y7: =SUM(10381.23/68)*H7 -> 33.754264 | AB7: =SUM(Y7:AA7) -> 33.754264 | AC7: 7.23 | AD7: =SUM(AB7*AC7) -> 244.04333 | AE7: =SUM(X7+AD7) -> 382.9299 | AF7: =SUM(P7-AE7) -> 85.770105
C8: 240920000027 | D8: 45563 | E8: 吕沛霖 | F8: 喵喵速运-Layne | G8: YA | H8: 1.1252 | I8: 111 | J8: 3500.8 | P8: =SUBTOTAL(9,J8) -> 3500.8 | S8: =SUM(40515/68)*H8 -> 670.40409 | U8: =SUM(2200/68)*H8 -> 36.403529 | X8: =SUM(S8:W8) -> 706.80762 | Y8: =SUM(10381.23/68)*H8 -> 171.77882 | Z8: 8.31 | AA8: 117.69 | AB8: =SUM(Y8:AA8) -> 297.77882 | AC8: 7.23 | AD8: =SUM(AB8*AC8) -> 2152.9409 | AE8: =SUM(X8+AD8) -> 2859.7485 | AF8: =SUM(P8-AE8) -> 641.05149
C9: 240920000030 | D9: 45563 | E9: 黄颖 | F9: ying | G9: baikaibo | H9: 0.319 | I9: 321 | K9: 385317 | M9: =SUM(K9/N9) -> 1767.347 | N9: 218.02 | O9: 7.24 | P9: =SUM(N9*O9) -> 1578.4648 | S9: =SUM(40515/68)*H9 -> 190.06301 | U9: =SUM(2200/68)*H9 -> 10.320588 | X9: =SUM(S9:W9) -> 200.3836 | Y9: =SUM(10381.23/68)*H9 -> 48.700182 | Z9: 85.03 | AB9: =SUM(Y9:AA9) -> 133.73018 | AC9: 7.23 | AD9: =SUM(AB9*AC9) -> 966.86922 | AE9: =SUM(X9+AD9) -> 1167.2528 | AF9: =SUM(P9-AE9) -> 411.21198
C10: 240923000009 | D10: 45563 | E10: 朱小飞 | F10: Isabel Zhu | G10: Wu Jiao Xing | H10: 0.5281 | I10: 104.5 | K10: 313621.07 | M10: =SUM(K10/N10) -> 1855.8559 | N10: 168.98999 | O10: 7.26 | P10: =SUM(N10*O10) -> 1226.8673 | S10: =SUM(40515/68)*H10 -> 314.64664 | U10: =SUM(2200/68)*H10 -> 17.085588 | X10: =SUM(S10:W10) -> 331.73223 | Y10: =SUM(10381.23/68)*H10 -> 80.622464 | AB10: =SUM(Y10:AA10) -> 80.622464 | AC10: 7.23 | AD10: =SUM(AB10*AC10) -> 582.90042 | AE10: =SUM(X10+AD10) -> 914.63264 | AF10: =SUM(P10-AE10) -> 312.23468
C11: 240923000035 | D11: 45547 | E11: 黄颖 | F11: ying | G11: Bruce | H11: 1.0584 | I11: 465 | J11: 2082 | P11: =SUBTOTAL(9,J11) -> 2082 | S11: =SUM(40515/68)*H11 -> 630.60406 | U11: =SUM(2200/68)*H11 -> 34.242353 | X11: =SUM(S11:W11) -> 664.84641 | Y11: =SUM(10381.23/68)*H11 -> 161.58079 | AB11: =SUM(Y11:AA11) -> 161.58079 | AC11: 7.23 | AD11: =SUM(AB11*AC11) -> 1168.2291 | AE11: =SUM(X11+AD11) -> 1833.0755 | AF11: =SUM(P11-AE11) -> 248.92446
C12: 240923000047 | D12: 45563 | E12: 吕沛霖 | F12: 喵喵速运-Layne | G12: WYLB | H12: 0.8 | I12: 197 | K12: 390880 | M12: =SUM(K12/N12) -> 1744.9998 | N12: 224.00003 | O12: 7.21 | P12: =SUM(N12*O12) -> 1615.0402 | S12: =SUM(40515/68)*H12 -> 476.64706 | U12: =SUM(2200/68)*H12 -> 25.882353 | X12: =SUM(S12:W12) -> 502.52941 | Y12: =SUM(10381.23/68)*H12 -> 122.13212 | AB12: =SUM(Y12:AA12) -> 122.13212 | AC12: 7.23 | AD12: =SUM(AB12*AC12) -> 883.01521 | AE12: =SUM(X12+AD12) -> 1385.5446 | AF12: =SUM(P12-AE12) -> 229.49559
C13: 240924000001 | D13: 45563 | E13: Sam.Pao | F13: Sam.Pao | G13: Yusky | H13: 8.51 | I13: 209 | J13: 14859.77 | P13: =SUBTOTAL(9,J13) -> 14859.77 | S13: =SUM(40515/68)*H13 -> 5070.3331 | U13: =SUM(2200/68)*H13 -> 275.32353 | X13: =SUM(S13:W13) -> 5345.6566 | Y13: =SUM(10381.23/68)*H13 -> 1299.1804 | AB13: =SUM(Y13:AA13) -> 1299.1804 | AC13: 7.23 | AD13: =SUM(AB13*AC13) -> 9393.0743 | AE13: =SUM(X13+AD13) -> 14738.731 | AF13: =SUM(P13-AE13) -> 121.03908
C14: 240925000028 | D14: 45563 | E14: 朱小飞 | F14: Isabel Zhu | G14: Halifa Success | H14: 1.2354 | I14: 125 | J14: 2382.35 | P14: =SUBTOTAL(9,J14) -> 2382.35 | S14: =SUM(40515/68)*H14 -> 736.06222 | U14: =SUM(2200/68)*H14 -> 39.968824 | X14: =SUM(S14:W14) -> 776.03104 | Y14: =SUM(10381.23/68)*H14 -> 188.60252 | AB14: =SUM(Y14:AA14) -> 188.60252 | AC14: 7.23 | AD14: =SUM(AB14*AC14) -> 1363.5962 | AE14: =SUM(X14+AD14) -> 2139.6273 | AF14: =SUM(P14-AE14) -> 242.72272
C15: 240926000027 | D15: 45563 | E15: Sam.Pao | F15: Sam.Pao | G15: ShanShan | H15: 1.555 | I15: 237 | J15: 3879 | P15: =SUBTOTAL(9,J15) -> 3879 | S15: =SUM(40515/68)*H15 -> 926.48272 | U15: =SUM(2200/68)*H15 -> 50.308824 | X15: =SUM(S15:W15) -> 976.79154 | Y15: =SUM(10381.23/68)*H15 -> 237.3943 | Z15: 36.85 | AB15: =SUM(Y15:AA15) -> 274.2443 | AC15: 7.23 | AD15: =SUM(AB15*AC15) -> 1982.7863 | AE15: =SUM(X15+AD15) -> 2959.5779 | AF15: =SUM(P15-AE15) -> 919.42214
C16: 240924000057 | D16: 45564 | E16: Sam.Pao | F16: Sam.Pao | G16: Arni | H16: 5.543 | I16: 3101 | J16: 12233 | P16: =SUBTOTAL(9,J16) -> 12233 | S16: =SUM(40515/68)*H16 -> 3302.5683 | U16: =SUM(2200/68)*H16 -> 179.33235 | X16: =SUM(S16:W16) -> 3481.9007 | Y16: =SUM(10381.23/68)*H16 -> 846.22291 | AB16: =SUM(Y16:AA16) -> 846.22291 | AC16: 7.23 | AD16: =SUM(AB16*AC16) -> 6118.1916 | AE16: =SUM(X16+AD16) -> 9600.0923 | AF16: =SUM(P16-AE16) -> 2632.9077
C17: 240906000023 | D17: 45559 | E17: Sam.Pao | F17: Sam.Pao | G17: ChenGaoHong | H17: 33.5175 | I17: 8313 | J17: 68845 | P17: =SUBTOTAL(9,J17) -> 68845 | S17: =SUM(40515/68)*H17 -> 19970.022 | U17: =SUM(2200/68)*H17 -> 1084.3897 | X17: =SUM(S17:W17) -> 21054.412 | Y17: =SUM(10381.23/68)*H17 -> 5116.9541 | AB17: =SUM(Y17:AA17) -> 5116.9541 | AC17: 7.23 | AD17: =SUM(AB17*AC17) -> 36995.578 | AE17: =SUM(X17+AD17) -> 58049.99 | AF17: =SUM(P17-AE17) -> 10795.01
C18: 240927000007 | D18: 45563 | E18: 黄颖 | F18: ying | G18: MISS Huang | H18: 1.745 | I18: 656 | J18: 3441 | P18: =SUBTOTAL(9,J18) -> 3441 | S18: =SUM(40515/68)*H18 -> 1039.6864 | U18: =SUM(2200/68)*H18 -> 56.455882 | X18: =SUM(S18:W18) -> 1096.1423 | Y18: =SUM(10381.23/68)*H18 -> 266.40068 | AB18: =SUM(Y18:AA18) -> 266.40068 | AC18: 7.23 | AD18: =SUM(AB18*AC18) -> 1926.0769 | AE18: =SUM(X18+AD18) -> 3022.2192 | AF18: =SUM(P18-AE18) -> 418.78079
C19: 240927000017 | D19: 45563 | E19: 朱小飞 | F19: Isabel Zhu | G19: Lin Bao Zhen | H19: 1.1235 | I19: 241 | K19: 594820.8 | M19: =SUM(K19/N19) -> 1891.0213 | N19: 314.55002 | O19: 7.26 | P19: =SUM(N19*O19) -> 2283.6331 | S19: =SUM(40515/68)*H19 -> 669.39121 | U19: =SUM(2200/68)*H19 -> 36.348529 | X19: =SUM(S19:W19) -> 705.73974 | Y19: =SUM(10381.23/68)*H19 -> 171.51929 | AB19: =SUM(Y19:AA19) -> 171.51929 | AC19: 7.23 | AD19: =SUM(AB19*AC19) -> 1240.0845 | AE19: =SUM(X19+AD19) -> 1945.8242 | AF19: =SUM(P19-AE19) -> 337.80892
C20: 240927000029 | D20: 45563 | E20: 朱小飞 | F20: Isabel Zhu | G20: Joy | H20: 1.7289 | I20: 1316 | K20: 1061222.4 | M20: =SUM(K20/N20) -> 1612.7994 | N20: 658.00024 | O20: 7.26 | P20: =SUM(N20*O20) -> 4777.0817 | S20: =SUM(40515/68)*H20 -> 1030.0939 | U20: =SUM(2200/68)*H20 -> 55.935 | X20: =SUM(S20:W20) -> 1086.0289 | Y20: =SUM(10381.23/68)*H20 -> 263.94277 | Z20: 7.97 | AB20: =SUM(Y20:AA20) -> 271.91277 | AC20: 7.23 | AD20: =SUM(AB20*AC20) -> 1965.9293 | AE20: =SUM(X20+AD20) -> 3051.9582 | AF20: =SUM(P20-AE20) -> 1725.1235
C21: 240921000019 | D21: 45563 | E21: 陆总 | F21: 陆梓龙 | G21: xiantian | H21: 0.3318 | I21: 185 | J21: 678.17 | P21: =SUBTOTAL(9,J21) -> 678.17 | S21: =SUM(40515/68)*H21 -> 197.68937 | U21: =SUM(2200/68)*H21 -> 10.734706 | X21: =SUM(S21:W21) -> 208.42407 | Y21: =SUM(10381.23/68)*H21 -> 50.654296 | AB21: =SUM(Y21:AA21) -> 50.654296 | AC21: 7.23 | AD21: =SUM(AB21*AC21) -> 366.23056 | AE21: =SUM(X21+AD21) -> 574.65463 | AF21: =SUM(P21-AE21) -> 103.51537
C22: 240927000032 | D22: 45563 | E22: 罗珮文 | F22: Shirley | G22: Yusky | H22: 0.4929 | I22: 47.1 | J22: 860.11 | P22: =SUBTOTAL(9,J22) -> 860.11 | S22: =SUM(40515/68)*H22 -> 293.67417 | U22: =SUM(2200/68)*H22 -> 15.946765 | X22: =SUM(S22:W22) -> 309.62093 | Y22: =SUM(10381.23/68)*H22 -> 75.248651 | AB22: =SUM(Y22:AA22) -> 75.248651 | AC22: 7.23 | AD22: =SUM(AB22*AC22) -> 544.04775 | AE22: =SUM(X22+AD22) -> 853.66868 | AF22: =SUM(P22-AE22) -> 6.4413196
C23: 240927000070 | D23: 45563 | E23: 陆总 | F23: 陆梓龙 | G23: xinlong | H23: 17.4127 | I23: 10650 | J23: 29515.58 | P23: =SUBTOTAL(9,J23) -> 29515.58 | S23: =SUM(40515/68)*H23 -> 10374.64 | U23: =SUM(2200/68)*H23 -> 563.35206 | X23: =SUM(S23:W23) -> 10937.992 | Y23: =SUM(10381.23/68)*H23 -> 2658.3124 | Z23: 85.88 | AB23: =SUM(Y23:AA23) -> 2744.1924 | AC23: 7.23 | AD23: =SUM(AB23*AC23) -> 19840.511 | AE23: =SUM(X23+AD23) -> 30778.503 | AF23: =SUM(P23-AE23) -> -1262.9235
C24: 240928000018 | D24: 45563 | E24: 陆总 | F24: 陆梓龙 | G24: leoluang | H24: 3.3552 | I24: 1105 | J24: 6123.24 | P24: =SUBTOTAL(9,J24) -> 6123.24 | S24: =SUM(40515/68)*H24 -> 1999.0578 | U24: =SUM(2200/68)*H24 -> 108.55059 | X24: =SUM(S24:W24) -> 2107.6084 | Y24: =SUM(10381.23/68)*H24 -> 512.2221 | AB24: =SUM(Y24:AA24) -> 512.2221 | AC24: 7.23 | AD24: =SUM(AB24*AC24) -> 3703.3658 | AE24: =SUM(X24+AD24) -> 5810.9741 | AF24: =SUM(P24-AE24) -> 312.26585
A25: JOB100359 | B25: COLL004278 | C25: 240919000034 | D25: 45563 | E25: 朱小飞 | F25: Isabel Zhu | G25: Wu Jiao Xing | H25: 0.8132 | I25: 104 | K25: 607758.93 | M25: =SUM(K25/N25) -> 1737 | N25: 349.89 | O25: 7.26 | P25: =SUM(N25*O25) -> 2540.2014 | Q25: =SUM(P25:P34) -> 148903 | R25: 登凯=39001 赛捷=1660 | S25: =SUM(40661/68)*H25 -> 486.25772 | T25: =SUM(94.72/68)*H25 -> 1.1327398 | U25: =SUM(2000/68)*H25 -> 23.917647 | V25: 420 | X25: =SUM(S25:W25) -> 931.30811 | Y25: =SUM(10381.24/68)*H25 -> 124.14742 | AB25: =SUM(Y25:AA25) -> 124.14742 | AC25: 7.24 | AD25: =SUM(AB25*AC25) -> 898.8273 | AE25: =SUM(X25+AD25) -> 1830.1354 | AF25: =SUM(P25-AE25) -> 710.06599
C26: 240921000009 | D26: 45563 | E26: 苏慧琪 | F26: KAY | G26: OKECHUKWU | H26: 0.075 | I26: 19 | J26: 318 | P26: =SUM(J26) -> 318 | S26: =SUM(40661/68)*H26 -> 44.846691 | T26: =SUM(94.72/68)*H26 -> 0.10447059 | U26: =SUM(2000/68)*H26 -> 2.2058824 | X26: =SUM(S26:W26) -> 47.157044 | Y26: =SUM(10381.24/68)*H26 -> 11.449897 | AB26: =SUM(Y26:AA26) -> 11.449897 | AC26: 7.24 | AD26: =SUM(AB26*AC26) -> 82.897255 | AE26: =SUM(X26+AD26) -> 130.0543 | AF26: =SUM(P26-AE26) -> 187.9457
C27: 240921000019 | D27: 45563 | E27: 陆总 | F27: 陆梓龙 | G27: xiantian | H27: 10.1452 | I27: 2149.35 | J27: 20732 | P27: =SUBTOTAL(9,J27) -> 20732 | S27: =SUM(40661/68)*H27 -> 6066.382 | T27: =SUM(94.72/68)*H27 -> 14.131667 | U27: =SUM(2000/68)*H27 -> 298.38824 | V27: =SUM(450+350) -> 800 | X27: =SUM(S27:W27) -> 7178.9019 | Y27: =SUM(10381.24/68)*H27 -> 1548.8199 | AB27: =SUM(Y27:AA27) -> 1548.8199 | AC27: 7.24 | AD27: =SUM(AB27*AC27) -> 11213.456 | AE27: =SUM(X27+AD27) -> 18392.358 | AF27: =SUM(P27-AE27) -> 2339.6417
C28: 240923000035 | D28: 45563 | E28: 黄颖 | F28: ying | G28: Bruce | H28: 7.0714 | I28: 3083 | J28: 13913.3 | P28: =SUBTOTAL(9,J28) -> 13913.3 | S28: =SUM(40661/68)*H28 -> 4228.3852 | T28: =SUM(94.72/68)*H28 -> 9.8500442 | U28: =SUM(2000/68)*H28 -> 207.98235 | X28: =SUM(S28:W28) -> 4446.2176 | Y28: =SUM(10381.24/68)*H28 -> 1079.5574 | AB28: =SUM(Y28:AA28) -> 1079.5574 | AC28: 7.24 | AD28: =SUM(AB28*AC28) -> 7815.9953 | AE28: =SUM(X28+AD28) -> 12262.213 | AF28: =SUM(P28-AE28) -> 1651.0871
C29: 240906000023 | D29: 45559 | E29: Sam.Pao | F29: Sam.Pao | G29: ChenGaoHong | H29: 24.9775 | I29: 6522 | J29: 51303 | P29: =SUBTOTAL(9,J29) -> 51303 | S29: =SUM(40661/68)*H29 -> 14935.443 | T29: =SUM(94.72/68)*H29 -> 34.792188 | U29: =SUM(2000/68)*H29 -> 734.63235 | X29: =SUM(S29:W29) -> 15704.868 | Y29: =SUM(10381.24/68)*H29 -> 3813.1974 | AB29: =SUM(Y29:AA29) -> 3813.1974 | AC29: 7.24 | AD29: =SUM(AB29*AC29) -> 27607.549 | AE29: =SUM(X29+AD29) -> 43312.417 | AF29: =SUM(P29-AE29) -> 7990.5833
C30: 240919000020 | D30: 45564 | E30: 吕沛霖 | F30: 喵喵速运-Layne | G30: ABDUL | H30: 1.06 | I30: 594 | J30: 2180 | P30: =SUBTOTAL(9,J30) -> 2180 | S30: =SUM(40661/68)*H30 -> 633.83324 | T30: =SUM(94.72/68)*H30 -> 1.4765176 | U30: =SUM(2000/68)*H30 -> 31.176471 | X30: =SUM(S30:W30) -> 666.48622 | Y30: =SUM(10381.24/68)*H30 -> 161.82521 | AB30: =SUM(Y30:AA30) -> 161.82521 | AC30: 7.24 | AD30: =SUM(AB30*AC30) -> 1171.6145 | AE30: =SUM(X30+AD30) -> 1838.1008 | AF30: =SUM(P30-AE30) -> 341.89924
C31: 240924000057 | D31: 45564 | E31: Sam.Pao | F31: Sam.Pao | G31: Arni | H31: 5.543 | I31: 3097 | J31: 12233 | P31: =SUBTOTAL(9,J31) -> 12233 | S31: =SUM(40661/68)*H31 -> 3314.4695 | T31: =SUM(94.72/68)*H31 -> 7.7210729 | U31: =SUM(2000/68)*H31 -> 163.02941 | X31: =SUM(S31:W31) -> 3485.2199 | Y31: =SUM(10381.24/68)*H31 -> 846.22373 | AB31: =SUM(Y31:AA31) -> 846.22373 | AC31: 7.24 | AD31: =SUM(AB31*AC31) -> 6126.6598 | AE31: =SUM(X31+AD31) -> 9611.8797 | AF31: =SUM(P31-AE31) -> 2621.1203
C32: 240928000023 | D32: 45564 | E32: Sam.Pao | F32: Sam.Pao | G32: SKY JET | H32: 6.37 | I32: 908.5 | J32: 9341.73 | P32: =SUBTOTAL(9,J32) -> 9341.73 | S32: =SUM(40661/68)*H32 -> 3808.979 | T32: =SUM(94.72/68)*H32 -> 8.8730353 | U32: =SUM(2000/68)*H32 -> 187.35294 | X32: =SUM(S32:W32) -> 4005.2049 | Y32: =SUM(10381.24/68)*H32 -> 972.47792 | AB32: =SUM(Y32:AA32) -> 972.47792 | AC32: 7.24 | AD32: =SUM(AB32*AC32) -> 7040.7402 | AE32: =SUM(X32+AD32) -> 11045.945 | AF32: =SUM(P32-AE32) -> -1704.2151
C33: 240927000032 | D33: 45563 | E33: 罗珮文 | F33: Shirley | G33: Yusky | H33: 4.4364 | I33: 423.9 | J33: 7740.66 | P33: =SUBTOTAL(9,J33) -> 7740.66 | S33: =SUM(40661/68)*H33 -> 2652.7715 | T33: =SUM(94.72/68)*H33 -> 6.1796442 | U33: =SUM(2000/68)*H33 -> 130.48235 | X33: =SUM(S33:W33) -> 2789.4335 | Y33: =SUM(10381.24/68)*H33 -> 677.28431 | AB33: =SUM(Y33:AA33) -> 677.28431 | AC33: 7.24 | AD33: =SUM(AB33*AC33) -> 4903.5384 | AE33: =SUM(X33+AD33) -> 7692.9719 | AF33: =SUM(P33-AE33) -> 47.688116
C34: 240927000071 | D34: 45563 | E34: 陆总 | F34: 陆梓龙 | G34: xinlong | H34: 16.8732 | I34: 10470 | J34: 28601.11 | P34: =SUBTOTAL(9,J34) -> 28601.11 | S34: =SUM(40661/68)*H34 -> 10089.429 | T34: =SUM(94.72/68)*H34 -> 23.503375 | U34: =SUM(2000/68)*H34 -> 496.27059 | X34: =SUM(S34:W34) -> 10609.203 | Y34: =SUM(10381.24/68)*H34 -> 2575.952 | Z34: 84.18 | AB34: =SUM(Y34:AA34) -> 2660.132 | AC34: 7.24 | AD34: =SUM(AB34*AC34) -> 19259.356 | AE34: =SUM(X34+AD34) -> 29868.559 | AF34: =SUM(P34-AE34) -> -1267.4491
A35: JOB100360 | B35: COLL004247 | C35: 240918000046 | D35: 45564 | E35: 朱小飞 | F35: Isabel Zhu | G35: Lin Bao Zhen | H35: 11.5853 | I35: 3144 | K35: 7151961.6 | M35: =SUM(K35/N35) -> 1754.9707 | N35: 4075.2598 | O35: 7.26 | P35: =SUM(N35*O35) -> 29586.386 | Q35: =SUM(P35:P44) -> 153384.01 | R35: 登凯=36901 赛捷=2800 拖车费=1670 杂费=497 过磅费=65 | S35: =SUM(41933/68)*H35 -> 7144.2115 | U35: =SUM(1400/68)*H35 -> 238.52088 | V35: 150 | X35: =SUM(S35:W35) -> 7532.7324 | Y35: =SUM(10381.24/68)*H35 -> 1768.6732 | AB35: =SUM(Y35:AA35) -> 1768.6732 | AC35: 7.24 | AD35: =SUM(AB35*AC35) -> 12805.194 | AE35: =SUM(X35+AD35) -> 20337.927 | AF35: =SUM(P35-AE35) -> 9248.4595
C36: 240919000028 | D36: 45564 | E36: 陆总 | F36: 陆梓龙 | G36: jizong | H36: 4.5828 | I36: 3750 | J36: 10847.8 | P36: =SUBTOTAL(9,J36) -> 10847.8 | S36: =SUM(41933/68)*H36 -> 2826.0375 | U36: =SUM(1400/68)*H36 -> 94.351765 | X36: =SUM(S36:W36) -> 2920.3893 | Y36: =SUM(10381.24/68)*H36 -> 699.63451 | AB36: =SUM(Y36:AA36) -> 699.63451 | AC36: 7.24 | AD36: =SUM(AB36*AC36) -> 5065.3539 | AE36: =SUM(X36+AD36) -> 7985.7432 | AF36: =SUM(P36-AE36) -> 2862.0568
C37: 240906000023 | D37: 45559 | E37: Sam.Pao | F37: Sam.Pao | G37: ChenGaoHong | H37: 17.6195 | I37: 5514 | J37: 36190 | P37: =SUBTOTAL(9,J37) -> 36190 | S37: =SUM(41933/68)*H37 -> 10865.272 | U37: =SUM(1400/68)*H37 -> 362.75441 | X37: =SUM(S37:W37) -> 11228.026 | Y37: =SUM(10381.24/68)*H37 -> 2689.8861 | AB37: =SUM(Y37:AA37) -> 2689.8861 | AC37: 7.24 | AD37: =SUM(AB37*AC37) -> 19474.776 | AE37: =SUM(X37+AD37) -> 30702.802 | AF37: =SUM(P37-AE37) -> 5487.1979
C38: 240924000057 | D38: 45564 | E38: Sam.Pao | F38: Sam.Pao | G38: Arni | H38: 4.4869 | I38: 2510.11 | J38: 9902 | P38: =SUBTOTAL(9,J38) -> 9902 | S38: =SUM(41933/68)*H38 -> 2766.8997 | U38: =SUM(1400/68)*H38 -> 92.377353 | X38: =SUM(S38:W38) -> 2859.277 | Y38: =SUM(10381.24/68)*H38 -> 684.99391 | AB38: =SUM(Y38:AA38) -> 684.99391 | AC38: 7.24 | AD38: =SUM(AB38*AC38) -> 4959.3559 | AE38: =SUM(X38+AD38) -> 7818.6329 | AF38: =SUM(P38-AE38) -> 2083.3671
C39: 240919000020 | D39: 45564 | E39: 吕沛霖 | F39: 喵喵速运-Layne | G39: ABDUL | H39: 3.887 | I39: 1821.5 | J39: 8001.8 | P39: =SUBTOTAL(9,J39) -> 8001.8 | S39: =SUM(41933/68)*H39 -> 2396.9643 | U39: =SUM(1400/68)*H39 -> 80.026471 | X39: =SUM(S39:W39) -> 2476.9907 | Y39: =SUM(10381.24/68)*H39 -> 593.41 | AB39: =SUM(Y39:AA39) -> 593.41 | AC39: 7.24 | AD39: =SUM(AB39*AC39) -> 4296.2884 | AE39: =SUM(X39+AD39) -> 6773.2791 | AF39: =SUM(P39-AE39) -> 1228.5209
C40: 240929000009 | D40: 45564 | E40: 朱小飞 | F40: Isabel Zhu | G40: Joy | H40: 6.7645 | I40: 2500 | K40: 3821265 | M40: =SUM(K40/N40) -> 1883.3243 | N40: 2029 | O40: 7.26 | P40: =SUM(N40*O40) -> 14730.54 | S40: =SUM(41933/68)*H40 -> 4171.4085 | U40: =SUM(1400/68)*H40 -> 139.26912 | X40: =SUM(S40:W40) -> 4310.6776 | Y40: =SUM(10381.24/68)*H40 -> 1032.7044 | AB40: =SUM(Y40:AA40) -> 1032.7044 | AC40: 7.24 | AD40: =SUM(AB40*AC40) -> 7476.7797 | AE40: =SUM(X40+AD40) -> 11787.457 | AF40: =SUM(P40-AE40) -> 2943.0826
C41: 240928000023 | D41: 45564 | E41: Sam.Pao | F41: Sam.Pao | G41: SKY JET | H41: 22.557 | I41: 3296 | J41: 33080.26 | P41: =SUBTOTAL(9,J41) -> 33080.26 | S41: =SUM(41933/68)*H41 -> 13910.039 | U41: =SUM(1400/68)*H41 -> 464.40882 | X41: =SUM(S41:W41) -> 14374.448 | Y41: =SUM(10381.24/68)*H41 -> 3443.671 | AB41: =SUM(Y41:AA41) -> 3443.671 | AC41: 7.24 | AD41: =SUM(AB41*AC41) -> 24932.178 | AE41: =SUM(X41+AD41) -> 39306.627 | AF41: =SUM(P41-AE41) -> -6226.3666
C42: 240929000010 | D42: 45564 | E42: 朱小飞 | F42: Isabel Zhu | G42: Joy | H42: 1.3975 | I42: 377 | K42: 790272 | M42: =SUM(K42/N42) -> 1885.1008 | N42: 419.22003 | O42: 7.26 | P42: =SUM(N42*O42) -> 3043.5374 | S42: =SUM(41933/68)*H42 -> 861.78482 | U42: =SUM(1400/68)*H42 -> 28.772059 | X42: =SUM(S42:W42) -> 890.55687 | Y42: =SUM(10381.24/68)*H42 -> 213.34975 | Z42: 9.86 | AB42: =SUM(Y42:AA42) -> 223.20975 | AC42: 7.24 | AD42: =SUM(AB42*AC42) -> 1616.0386 | AE42: =SUM(X42+AD42) -> 2506.5955 | AF42: =SUM(P42-AE42) -> 536.94196
C43: 240929000011（补单） | D43: 45564 | E43: 朱小飞 | F43: Isabel Zhu | G43: Joy | H43: 2.4334 | I43: 2340 | K43: 1822400 | M43: =SUM(K43/N43) -> 1700 | N43: 1072 | O43: 7.29 | P43: =SUM(N43*O43) -> 7814.88 | S43: =SUM(41933/68)*H43 -> 1500.5847 | U43: =SUM(1400/68)*H43 -> 50.099412 | X43: =SUM(S43:W43) -> 1550.6842 | Y43: =SUM(10381.24/68)*H43 -> 371.49573 | AB43: =SUM(Y43:AA43) -> 371.49573 | AC43: 7.24 | AD43: =SUM(AB43*AC43) -> 2689.6291 | AE43: =SUM(X43+AD43) -> 4240.3132 | AF43: =SUM(P43-AE43) -> 3574.5668
C44: 240929000057 | D44: 45564 | E44: 陆总 | F44: 陆梓龙 | G44: luk | H44: 0.0914 | I44: 64 | J44: 186.81 | P44: =SUBTOTAL(9,J44) -> 186.81 | S44: =SUM(41933/68)*H44 -> 56.362885 | U44: =SUM(1400/68)*H44 -> 1.8817647 | X44: =SUM(S44:W44) -> 58.24465 | Y44: =SUM(10381.24/68)*H44 -> 13.953608 | AB44: =SUM(Y44:AA44) -> 13.953608 | AC44: 7.24 | AD44: =SUM(AB44*AC44) -> 101.02412 | AE44: =SUM(X44+AD44) -> 159.26877 | AF44: =SUM(P44-AE44) -> 27.541229
A45: JOB100361 | B45: COLL004248 | C45: 240906000023 | D45: 45564 | E45: Sam.Pao | F45: Sam.Pao | G45: ChenGaoHong | H45: 11.9955 | I45: 4372 | J45: 24695 | P45: =SUBTOTAL(9,J45) -> 24695 | Q45: =SUM(P45:P62) -> 122040.48 | R45: 登凯=37199 赛捷=1500 拖车费=1670 杂费=495 过磅费=50 | S45: =SUM(40914/68)*H45 -> 7217.4101 | U45: =SUM(1000/68)*H45 -> 176.40441 | V45: =SUM(800+800) -> 1600 | X45: =SUM(S45:W45) -> 8993.8145 | Y45: =SUM(10381.24/68)*H45 -> 1831.2965 | AA45: =SUM(114.28/68)*H45 -> 20.159496 | AB45: =SUM(Y45:AA45) -> 1851.456 | AC45: 7.27 | AD45: =SUM(AB45*AC45) -> 13460.085 | AE45: =SUM(X45+AD45) -> 22453.9 | AF45: =SUM(P45-AE45) -> 2241.1001
C46: 240919000020 | D46: 45564 | E46: 吕沛霖 | F46: 喵喵速运-Layne | G46: ABDUL | H46: 1.4136 | I46: 664.5 | J46: 2907 | P46: =SUBTOTAL(9,J46) -> 2907 | S46: =SUM(40914/68)*H46 -> 850.52986 | U46: =SUM(1000/68)*H46 -> 20.788235 | X46: =SUM(S46:W46) -> 871.31809 | Y46: =SUM(10381.24/68)*H46 -> 215.80766 | AA46: =SUM(114.28/68)*H46 -> 2.3756795 | AB46: =SUM(Y46:AA46) -> 218.18334 | AC46: 7.27 | AD46: =SUM(AB46*AC46) -> 1586.1929 | AE46: =SUM(X46+AD46) -> 2457.511 | AF46: =SUM(P46-AE46) -> 449.48903
C47: 240924000057 | D47: 45564 | E47: Sam.Pao | F47: Sam.Pao | G47: Arni | H47: 1.1877 | I47: 664.44 | J47: 2625 | P47: =SUBTOTAL(9,J47) -> 2625 | S47: =SUM(40914/68)*H47 -> 714.61114 | U47: =SUM(1000/68)*H47 -> 17.466176 | X47: =SUM(S47:W47) -> 732.07732 | Y47: =SUM(10381.24/68)*H47 -> 181.32057 | AA47: =SUM(114.28/68)*H47 -> 1.9960346 | AB47: =SUM(Y47:AA47) -> 183.3166 | AC47: 7.27 | AD47: =SUM(AB47*AC47) -> 1332.7117 | AE47: =SUM(X47+AD47) -> 2064.789 | AF47: =SUM(P47-AE47) -> 560.21096
C48: 240925000034 | D48: 45564 | E48: 无人 | F48: dejare James | G48: ALH RAKIM | H48: 0.8264 | I48: 605 | J48: 3329.79 | P48: =SUBTOTAL(9,J48) -> 3329.79 | S48: =SUM(40914/68)*H48 -> 497.22544 | U48: =SUM(1000/68)*H48 -> 12.152941 | X48: =SUM(S48:W48) -> 509.37838 | Y48: =SUM(10381.24/68)*H48 -> 126.1626 | Z48: 194.84 | AA48: =SUM(114.28/68)*H48 -> 1.3888381 | AB48: =SUM(Y48:AA48) -> 322.39144 | AC48: 7.27 | AD48: =SUM(AB48*AC48) -> 2343.7857 | AE48: =SUM(X48+AD48) -> 2853.1641 | AF48: =SUM(P48-AE48) -> 476.62588
C49: 240926000001 | D49: 45564 | E49: 陆总 | F49: 陆梓龙 | G49: jizong | H49: 0.5358 | I49: 276 | J49: 1095.15 | P49: =SUBTOTAL(9,J49) -> 1095.15 | S49: =SUM(40914/68)*H49 -> 322.37825 | U49: =SUM(1000/68)*H49 -> 7.8794118 | X49: =SUM(S49:W49) -> 330.25766 | Y49: =SUM(10381.24/68)*H49 -> 81.798065 | AA49: =SUM(114.28/68)*H49 -> 0.90045918 | AB49: =SUM(Y49:AA49) -> 82.698524 | AC49: 7.27 | AD49: =SUM(AB49*AC49) -> 601.21827 | AE49: =SUM(X49+AD49) -> 931.47593 | AF49: =SUM(P49-AE49) -> 163.67407
C50: 240919000043 | D50: 45564 | E50: 黄颖 | F50: ying | G50: Mr wang | H50: 0.4921 | I50: 109 | J50: 1159 | P50: =SUBTOTAL(9,J50) -> 1159 | S50: =SUM(40914/68)*H50 -> 296.08499 | U50: =SUM(1000/68)*H50 -> 7.2367647 | X50: =SUM(S50:W50) -> 303.32176 | Y50: =SUM(10381.24/68)*H50 -> 75.126591 | AA50: =SUM(114.28/68)*H50 -> 0.82701747 | AB50: =SUM(Y50:AA50) -> 75.953609 | AC50: 7.27 | AD50: =SUM(AB50*AC50) -> 552.18274 | AE50: =SUM(X50+AD50) -> 855.50449 | AF50: =SUM(P50-AE50) -> 303.49551
C51: 240926000008 | D51: 45564 | E51: 黄颖 | F51: ying | G51: Nura | H51: 0.102 | I51: 67 | J51: 223.3 | P51: =SUBTOTAL(9,J51) -> 223.3 | S51: =SUM(40914/68)*H51 -> 61.371 | U51: =SUM(1000/68)*H51 -> 1.5 | X51: =SUM(S51:W51) -> 62.871 | Y51: =SUM(10381.24/68)*H51 -> 15.57186 | AA51: =SUM(114.28/68)*H51 -> 0.17142 | AB51: =SUM(Y51:AA51) -> 15.74328 | AC51: 7.27 | AD51: =SUM(AB51*AC51) -> 114.45365 | AE51: =SUM(X51+AD51) -> 177.32465 | AF51: =SUM(P51-AE51) -> 45.975354
C52: 240928000014 | D52: 45564 | E52: 朱小飞 | F52: Isabel Zhu | G52: Halifa Success | H52: 0.6152 | I52: 107 | J52: 1191.18 | P52: =SUBTOTAL(9,J52) -> 1191.18 | S52: =SUM(40914/68)*H52 -> 370.15136 | U52: =SUM(1000/68)*H52 -> 9.0470588 | X52: =SUM(S52:W52) -> 379.19842 | Y52: =SUM(10381.24/68)*H52 -> 93.919689 | AA52: =SUM(114.28/68)*H52 -> 1.0338979 | AB52: =SUM(Y52:AA52) -> 94.953587 | AC52: 7.27 | AD52: =SUM(AB52*AC52) -> 690.31258 | AE52: =SUM(X52+AD52) -> 1069.511 | AF52: =SUM(P52-AE52) -> 121.669
C53: 240928000015 | D53: 45564 | E53: 朱小飞 | F53: Isabel Zhu | G53: Halifa Success | H53: 0.1359 | I53: 19.5 | J53: 309.58 | P53: =SUBTOTAL(9,J53) -> 309.58 | S53: =SUM(40914/68)*H53 -> 81.767832 | U53: =SUM(1000/68)*H53 -> 1.9985294 | X53: =SUM(S53:W53) -> 83.766362 | Y53: =SUM(10381.24/68)*H53 -> 20.747213 | AA53: =SUM(114.28/68)*H53 -> 0.22839194 | AB53: =SUM(Y53:AA53) -> 20.975605 | AC53: 7.27 | AD53: =SUM(AB53*AC53) -> 152.49265 | AE53: =SUM(X53+AD53) -> 236.25901 | AF53: =SUM(P53-AE53) -> 73.320987
C54: 240929000070 | D54: 45564 | E54: Sam.Pao | F54: Sam.Pao | G54: SKY JET | H54: 14.91 | I54: 1595 | J54: 21865.81 | P54: =SUBTOTAL(9,J54) -> 21865.81 | S54: =SUM(40914/68)*H54 -> 8970.9962 | U54: =SUM(1000/68)*H54 -> 219.26471 | X54: =SUM(S54:W54) -> 9190.2609 | Y54: =SUM(10381.24/68)*H54 -> 2276.2395 | AA54: =SUM(114.28/68)*H54 -> 25.057571 | AB54: =SUM(Y54:AA54) -> 2301.2971 | AC54: 7.27 | AD54: =SUM(AB54*AC54) -> 16730.43 | AE54: =SUM(X54+AD54) -> 25920.691 | AF54: =SUM(P54-AE54) -> -4054.8808
C55: 240928000023 | D55: 45564 | E55: Sam.Pao | F55: Sam.Pao | G55: SKY JET | H55: 0.8638 | I55: 110 | J55: 1266.8 | P55: =SUBTOTAL(9,J55) -> 1266.8 | S55: =SUM(40914/68)*H55 -> 519.72814 | U55: =SUM(1000/68)*H55 -> 12.702941 | X55: =SUM(S55:W55) -> 532.43108 | Y55: =SUM(10381.24/68)*H55 -> 131.87228 | AA55: =SUM(114.28/68)*H55 -> 1.4516921 | AB55: =SUM(Y55:AA55) -> 133.32397 | AC55: 7.27 | AD55: =SUM(AB55*AC55) -> 969.26528 | AE55: =SUM(X55+AD55) -> 1501.6964 | AF55: =SUM(P55-AE55) -> -234.89636
C56: 240929000001 | D56: 45564 | E56: Sam.Pao | F56: Sam.Pao | G56: SKY JET | H56: 23.97 | I56: 2873 | J56: 35152.53 | P56: =SUBTOTAL(9,J56) -> 35152.53 | S56: =SUM(40914/68)*H56 -> 14422.185 | U56: =SUM(1000/68)*H56 -> 352.5 | X56: =SUM(S56:W56) -> 14774.685 | Y56: =SUM(10381.24/68)*H56 -> 3659.3871 | AA56: =SUM(114.28/68)*H56 -> 40.2837 | AB56: =SUM(Y56:AA56) -> 3699.6708 | AC56: 7.27 | AD56: =SUM(AB56*AC56) -> 26896.607 | AE56: =SUM(X56+AD56) -> 41671.292 | AF56: =SUM(P56-AE56) -> -6518.7617
C57: 240929000009 | D57: 45564 | E57: 朱小飞 | F57: Isabel Zhu | G57: Joy | H57: 6.006 | I57: 2236 | K57: 3392789.4 | M57: =SUM(K57/N57) -> 1883 | N57: 1801.8 | O57: 7.26 | P57: =SUM(N57*O57) -> 13081.068 | S57: =SUM(40914/68)*H57 -> 3613.6689 | U57: =SUM(1000/68)*H57 -> 88.323529 | X57: =SUM(S57:W57) -> 3701.9924 | Y57: =SUM(10381.24/68)*H57 -> 916.90776 | Z57: 72.87 | AA57: =SUM(114.28/68)*H57 -> 10.093613 | AB57: =SUM(Y57:AA57) -> 999.87137 | AC57: 7.27 | AD57: =SUM(AB57*AC57) -> 7269.0649 | AE57: =SUM(X57+AD57) -> 10971.057 | AF57: =SUM(P57-AE57) -> 2110.0107
C58: 240929000042 | D58: 45564 | E58: 罗珮文 | F58: Shirley | G58: Yusky | H58: 0.3433 | I58: 125 | J58: 643.9 | P58: =SUBTOTAL(9,J58) -> 643.9 | S58: =SUM(40914/68)*H58 -> 206.55553 | U58: =SUM(1000/68)*H58 -> 5.0485294 | X58: =SUM(S58:W58) -> 211.60406 | Y58: =SUM(10381.24/68)*H58 -> 52.409995 | AA58: =SUM(114.28/68)*H58 -> 0.57694594 | AB58: =SUM(Y58:AA58) -> 52.986941 | AC58: 7.27 | AD58: =SUM(AB58*AC58) -> 385.21506 | AE58: =SUM(X58+AD58) -> 596.81913 | AF58: =SUM(P58-AE58) -> 47.080874
C59: 240921000019 | D59: 45547 | E59: 陆总 | F59: 陆梓龙 | G59: xiantian | H59: 2.7091 | I59: 1182 | J59: 5539.61 | P59: =SUBTOTAL(9,J59) -> 5539.61 | S59: =SUM(40914/68)*H59 -> 1630.0017 | U59: =SUM(1000/68)*H59 -> 39.839706 | X59: =SUM(S59:W59) -> 1669.8414 | Y59: =SUM(10381.24/68)*H59 -> 413.58555 | AA59: =SUM(114.28/68)*H59 -> 4.5528816 | AB59: =SUM(Y59:AA59) -> 418.13843 | AC59: 7.27 | AD59: =SUM(AB59*AC59) -> 3039.8664 | AE59: =SUM(X59+AD59) -> 4709.7078 | AF59: =SUM(P59-AE59) -> 829.90218
C60: 240929000044 | D60: 45564 | E60: 罗珮文 | F60: Shirley | G60: Yusky | H60: 0.701 | I60: 79 | J60: 1314.85 | P60: =SUBTOTAL(9,J60) -> 1314.85 | S60: =SUM(40914/68)*H60 -> 421.77521 | U60: =SUM(1000/68)*H60 -> 10.308824 | X60: =SUM(S60:W60) -> 432.08403 | Y60: =SUM(10381.24/68)*H60 -> 107.01837 | AA60: =SUM(114.28/68)*H60 -> 1.1780924 | AB60: =SUM(Y60:AA60) -> 108.19646 | AC60: 7.27 | AD60: =SUM(AB60*AC60) -> 786.58829 | AE60: =SUM(X60+AD60) -> 1218.6723 | AF60: =SUM(P60-AE60) -> 96.177681
C61: 240929000045 | D61: 45564 | E61: 罗珮文 | F61: Shirley | G61: Yusky | H61: 0.2958 | I61: 34 | J61: 554.85 | P61: =SUBTOTAL(9,J61) -> 554.85 | S61: =SUM(40914/68)*H61 -> 177.9759 | U61: =SUM(1000/68)*H61 -> 4.35 | X61: =SUM(S61:W61) -> 182.3259 | Y61: =SUM(10381.24/68)*H61 -> 45.158394 | AA61: =SUM(114.28/68)*H61 -> 0.497118 | AB61: =SUM(Y61:AA61) -> 45.655512 | AC61: 7.27 | AD61: =SUM(AB61*AC61) -> 331.91557 | AE61: =SUM(X61+AD61) -> 514.24147 | AF61: =SUM(P61-AE61) -> 40.608528
C62: 240929000053 | D62: 45564 | E62: 陆总 | F62: 陆梓龙 | G62: jizong | H62: 2.4883 | I62: 449.5 | J62: 5086.06 | P62: =SUBTOTAL(9,J62) -> 5086.06 | S62: =SUM(40914/68)*H62 -> 1497.1516 | U62: =SUM(1000/68)*H62 -> 36.592647 | X62: =SUM(S62:W62) -> 1533.7442 | Y62: =SUM(10381.24/68)*H62 -> 379.87705 | AA62: =SUM(114.28/68)*H62 -> 4.1818077 | AB62: =SUM(Y62:AA62) -> 384.05886 | AC62: 7.27 | AD62: =SUM(AB62*AC62) -> 2792.1079 | AE62: =SUM(X62+AD62) -> 4325.8521 | AF62: =SUM(P62-AE62) -> 760.20789
A63: JOB100331 | B63: COLL004195 | C63: 240919000043 | D63: 45580 | E63: 黄颖 | F63: ying | G63: Mr wang | H63: 0.0017 | I63: 5.5 | J63: 4 | P63: =SUBTOTAL(9,J63) -> 4 | Q63: =SUM(P63:P88) -> 140734.06 | R63: 登凯=37296 赛捷=2800 拖车费=1670 杂费=61 过磅费=68 | S63: =SUM(40096/68)*H63 -> 1.0024 | U63: =SUM(2100/68)*H63 -> 0.0525 | X63: =SUM(S63:W63) -> 1.0549 | Y63: =SUM(10477.84/68)*H63 -> 0.261946 | AA63: =SUM(222.57/68)*H63 -> 0.00556425 | AB63: =SUM(Y63:AA63) -> 0.26751025 | AC63: 7.27 | AD63: =SUM(AB63*AC63) -> 1.9447995 | AE63: =SUM(X63+AD63) -> 2.9996995 | AF63: =SUM(P63-AE63) -> 1.0003005
C64: 240926000032 | D64: 45580 | E64: 黄颖 | F64: ying | G64: Sunday Adelena | H64: 17.4746 | I64: 13114 | J64: 35735 | P64: =SUBTOTAL(9,J64) -> 35735 | S64: =SUM(40096/68)*H64 -> 10303.846 | U64: =SUM(2100/68)*H64 -> 539.65676 | X64: =SUM(S64:W64) -> 10843.503 | Y64: =SUM(10477.84/68)*H64 -> 2692.5892 | AA64: =SUM(222.57/68)*H64 -> 57.195908 | AB64: =SUM(Y64:AA64) -> 2749.7851 | AC64: 7.27 | AD64: =SUM(AB64*AC64) -> 19990.937 | AE64: =SUM(X64+AD64) -> 30834.441 | AF64: =SUM(P64-AE64) -> 4900.5593
C65: 240926000037 | D65: 45580 | E65: 黄颖 | F65: ying | G65: lihongye | H65: 0.1237 | I65: 33 | J65: 344 | P65: =SUBTOTAL(9,J65) -> 344 | S65: =SUM(40096/68)*H65 -> 72.939341 | U65: =SUM(2100/68)*H65 -> 3.8201471 | X65: =SUM(S65:W65) -> 76.759488 | Y65: =SUM(10477.84/68)*H65 -> 19.060424 | AA65: =SUM(222.57/68)*H65 -> 0.40488101 | AB65: =SUM(Y65:AA65) -> 19.465305 | AC65: 7.27 | AD65: =SUM(AB65*AC65) -> 141.51276 | AE65: =SUM(X65+AD65) -> 218.27225 | AF65: =SUM(P65-AE65) -> 125.72775
C66: 240929000070 | D66: 45580 | E66: Sam.Pao | F66: Sam.Pao | G66: SKY JET | H66: 4.8 | I66: 799 | J66: 7039.3 | P66: =SUBTOTAL(9,J66) -> 7039.3 | S66: =SUM(40096/68)*H66 -> 2830.3059 | U66: =SUM(2100/68)*H66 -> 148.23529 | X66: =SUM(S66:W66) -> 2978.5412 | Y66: =SUM(10477.84/68)*H66 -> 739.61224 | AA66: =SUM(222.57/68)*H66 -> 15.710824 | AB66: =SUM(Y66:AA66) -> 755.32306 | AC66: 7.27 | AD66: =SUM(AB66*AC66) -> 5491.1986 | AE66: =SUM(X66+AD66) -> 8469.7398 | AF66: =SUM(P66-AE66) -> -1430.4398
C67: 240930000017 | D67: 45580 | E67: 黄颖 | F67: ying | G67: jiangnan | H67: 1.6158 | I67: 511 | J67: 3453.03 | P67: =SUBTOTAL(9,J67) -> 3453.03 | S67: =SUM(40096/68)*H67 -> 952.75172 | U67: =SUM(2100/68)*H67 -> 49.899706 | X67: =SUM(S67:W67) -> 1002.6514 | Y67: =SUM(10477.84/68)*H67 -> 248.97197 | AA67: =SUM(222.57/68)*H67 -> 5.288656 | AB67: =SUM(Y67:AA67) -> 254.26062 | AC67: 7.27 | AD67: =SUM(AB67*AC67) -> 1848.4747 | AE67: =SUM(X67+AD67) -> 2851.1262 | AF67: =SUM(P67-AE67) -> 601.90384
C68: 241005000004 | D68: 45580 | E68: 朱小飞 | F68: Isabel Zhu | G68: Joy | H68: 0.5915 | I68: 456 | K68: 359040 | M68: =SUM(K68/N68) -> 1700 | N68: 211.2 | O68: 7.29 | P68: =SUM(N68*O68) -> 1539.648 | S68: =SUM(40096/68)*H68 -> 348.77624 | U68: =SUM(2100/68)*H68 -> 18.266912 | X68: =SUM(S68:W68) -> 367.04315 | Y68: =SUM(10477.84/68)*H68 -> 91.141799 | Z68: 11.56 | AA68: =SUM(222.57/68)*H68 -> 1.9360317 | AB68: =SUM(Y68:AA68) -> 104.63783 | AC68: 7.27 | AD68: =SUM(AB68*AC68) -> 760.71703 | AE68: =SUM(X68+AD68) -> 1127.7602 | AF68: =SUM(P68-AE68) -> 411.88782
C69: 241006000007 | D69: 45580 | E69: 黄颖 | F69: ying | G69: MISS Huang | H69: 0.0493 | I69: 24 | K69: 42685.5 | M69: =SUM(K69/N69) -> 1576.8563 | N69: 27.07 | O69: 7.27 | P69: =SUM(N69*O69) -> 196.7989 | S69: =SUM(40096/68)*H69 -> 29.0696 | U69: =SUM(2100/68)*H69 -> 1.5225 | X69: =SUM(S69:W69) -> 30.5921 | Y69: =SUM(10477.84/68)*H69 -> 7.596434 | AA69: =SUM(222.57/68)*H69 -> 0.16136325 | AB69: =SUM(Y69:AA69) -> 7.7577973 | AC69: 7.27 | AD69: =SUM(AB69*AC69) -> 56.399186 | AE69: =SUM(X69+AD69) -> 86.991286 | AF69: =SUM(P69-AE69) -> 109.80761
C70: 241007000009 | D70: 45580 | E70: 朱小飞 | F70: Isabel Zhu | G70: Joy | H70: 0.0252 | I70: 13 | K70: 54400 | M70: =SUM(K70/N70) -> 1700 | N70: 32 | O70: 7.29 | P70: =SUM(N70*O70) -> 233.28 | S70: =SUM(40096/68)*H70 -> 14.859106 | U70: =SUM(2100/68)*H70 -> 0.77823529 | X70: =SUM(S70:W70) -> 15.637341 | Y70: =SUM(10477.84/68)*H70 -> 3.8829642 | AA70: =SUM(222.57/68)*H70 -> 0.082481824 | AB70: =SUM(Y70:AA70) -> 3.9654461 | AC70: 7.27 | AD70: =SUM(AB70*AC70) -> 28.828793 | AE70: =SUM(X70+AD70) -> 44.466134 | AF70: =SUM(P70-AE70) -> 188.81387
C71: 241008000098 | D71: 45580 | E71: Bella | F71: Bella Chan | G71: zhang long ting | H71: 0.0392 | I71: 27 | J71: 88.47 | P71: =SUBTOTAL(9,J71) -> 88.47 | S71: =SUM(40096/68)*H71 -> 23.114165 | U71: =SUM(2100/68)*H71 -> 1.2105882 | X71: =SUM(S71:W71) -> 24.324753 | Y71: =SUM(10477.84/68)*H71 -> 6.0401666 | AA71: =SUM(222.57/68)*H71 -> 0.12830506 | AB71: =SUM(Y71:AA71) -> 6.1684716 | AC71: 7.27 | AD71: =SUM(AB71*AC71) -> 44.844789 | AE71: =SUM(X71+AD71) -> 69.169542 | AF71: =SUM(P71-AE71) -> 19.300458
C72: 241009000020 | D72: 45580 | E72: 罗珮文 | F72: Shirley | G72: Yusky | H72: 19.5527 | I72: 2326 | J72: 4260.86 | K72: 6737482 | M72: =SUM(K72/N72) -> 1544.9999 | N72: 4360.83 | O72: 7.24 | P72: =SUM(N72*O72)+J72 -> 35833.269 | S72: =SUM(40096/68)*H72 -> 11529.192 | U72: =SUM(2100/68)*H72 -> 603.83338 | X72: =SUM(S72:W72) -> 12133.025 | Y72: =SUM(10477.84/68)*H72 -> 3012.795 | AA72: =SUM(222.57/68)*H72 -> 63.997712 | AB72: =SUM(Y72:AA72) -> 3076.7927 | AC72: 7.27 | AD72: =SUM(AB72*AC72) -> 22368.283 | AE72: =SUM(X72+AD72) -> 34501.309 | AF72: =SUM(P72-AE72) -> 1331.9605
C73: 241009000046 | D73: 45580 | E73: 苏慧琪 | F73: KAY | G73: WENXIAOBING | H73: 0.0717 | I73: 25 | K73: 37653 | M73: =SUM(K73/N73) -> 1637.087 | N73: 23 | O73: 7.27 | P73: =SUM(N73*O73) -> 167.21 | S73: =SUM(40096/68)*H73 -> 42.277694 | U73: =SUM(2100/68)*H73 -> 2.2142647 | X73: =SUM(S73:W73) -> 44.491959 | Y73: =SUM(10477.84/68)*H73 -> 11.047958 | AA73: =SUM(222.57/68)*H73 -> 0.23468043 | AB73: =SUM(Y73:AA73) -> 11.282638 | AC73: 7.27 | AD73: =SUM(AB73*AC73) -> 82.02478 | AE73: =SUM(X73+AD73) -> 126.51674 | AF73: =SUM(P73-AE73) -> 40.693262
C74: 241010000043 | D74: 45580 | E74: 朱小飞 | F74: Isabel Zhu | G74: Joy | H74: 1.9259 | I74: 967 | J74: -7012.8 | K74: 2705720 | M74: =SUM(K74/N74) -> 1700 | N74: 1591.6 | O74: 7.29 | P74: =SUM(N74*O74)+J74 -> 4589.964 | S74: =SUM(40096/68)*H74 -> 1135.6013 | U74: =SUM(2100/68)*H74 -> 59.476324 | X74: =SUM(S74:W74) -> 1195.0776 | Y74: =SUM(10477.84/68)*H74 -> 296.754 | Z74: 37.74 | AA74: =SUM(222.57/68)*H74 -> 6.3036406 | AB74: =SUM(Y74:AA74) -> 340.79764 | AC74: 7.27 | AD74: =SUM(AB74*AC74) -> 2477.5989 | AE74: =SUM(X74+AD74) -> 3672.6764 | AF74: =SUM(P74-AE74) -> 917.28755
C75: 241010000044 | D75: 45580 | E75: Sam.Pao | F75: Sam.Pao | G75: Nick Wang | H75: 0.294 | I75: 17 | J75: 919.8 | P75: =SUBTOTAL(9,J75) -> 919.8 | S75: =SUM(40096/68)*H75 -> 173.35624 | U75: =SUM(2100/68)*H75 -> 9.0794118 | X75: =SUM(S75:W75) -> 182.43565 | Y75: =SUM(10477.84/68)*H75 -> 45.301249 | Z75: 73.03 | AA75: =SUM(222.57/68)*H75 -> 0.96228794 | AB75: =SUM(Y75:AA75) -> 119.29354 | AC75: 7.27 | AD75: =SUM(AB75*AC75) -> 867.26402 | AE75: =SUM(X75+AD75) -> 1049.6997 | AF75: =SUM(P75-AE75) -> -129.89966
C76: 241011000029 | D76: 45580 | E76: 罗珮文 | F76: Shirley | G76: Yusky | H76: 1.2962 | I76: 139 | K76: 506590 | M76: =SUM(K76/N76) -> 1544.9998 | N76: 327.89 | O76: 7.24 | P76: =SUM(N76*O76) -> 2373.9236 | S76: =SUM(40096/68)*H76 -> 764.30052 | U76: =SUM(2100/68)*H76 -> 40.029706 | X76: =SUM(S76:W76) -> 804.33022 | Y76: =SUM(10477.84/68)*H76 -> 199.72612 | AA76: =SUM(222.57/68)*H76 -> 4.242577 | AB76: =SUM(Y76:AA76) -> 203.9687 | AC76: 7.27 | AD76: =SUM(AB76*AC76) -> 1482.8524 | AE76: =SUM(X76+AD76) -> 2287.1827 | AF76: =SUM(P76-AE76) -> 86.740944
C77: 241011000030 | D77: 45580 | E77: 罗珮文 | F77: Shirley | G77: Yusky | H77: 0.4329 | I77: 53 | K77: 169208 | M77: =SUM(K77/N77) -> 1544.9963 | N77: 109.52 | O77: 7.24 | P77: =SUM(N77*O77) -> 792.9248 | S77: =SUM(40096/68)*H77 -> 255.25821 | U77: =SUM(2100/68)*H77 -> 13.368971 | X77: =SUM(S77:W77) -> 268.62718 | Y77: =SUM(10477.84/68)*H77 -> 66.703778 | AA77: =SUM(222.57/68)*H77 -> 1.4169199 | AB77: =SUM(Y77:AA77) -> 68.120698 | AC77: 7.27 | AD77: =SUM(AB77*AC77) -> 495.23748 | AE77: =SUM(X77+AD77) -> 763.86466 | AF77: =SUM(P77-AE77) -> 29.060141
C78: 241011000031 | D78: 45580 | E78: 罗珮文 | F78: Shirley | G78: Yusky | H78: 0.539 | I78: 103 | K78: 210691 | M78: =SUM(K78/N78) -> 1544.9952 | N78: 136.37 | O78: 7.24 | P78: =SUM(N78*O78) -> 987.3188 | S78: =SUM(40096/68)*H78 -> 317.81976 | U78: =SUM(2100/68)*H78 -> 16.645588 | X78: =SUM(S78:W78) -> 334.46535 | Y78: =SUM(10477.84/68)*H78 -> 83.052291 | AA78: =SUM(222.57/68)*H78 -> 1.7641946 | AB78: =SUM(Y78:AA78) -> 84.816485 | AC78: 7.27 | AD78: =SUM(AB78*AC78) -> 616.61585 | AE78: =SUM(X78+AD78) -> 951.0812 | AF78: =SUM(P78-AE78) -> 36.2376
C79: 241011000032 | D79: 45580 | E79: 罗珮文 | F79: Shirley | G79: Yusky | H79: 6.1972 | I79: 617 | K79: 2557147 | M79: =SUM(K79/N79) -> 1631 | N79: 1567.84 | O79: 7.35 | P79: =SUM(N79*O79) -> 11523.624 | S79: =SUM(40096/68)*H79 -> 3654.1608 | U79: =SUM(2100/68)*H79 -> 191.38412 | X79: =SUM(S79:W79) -> 3845.5449 | Y79: =SUM(10477.84/68)*H79 -> 954.90103 | AA79: =SUM(222.57/68)*H79 -> 20.283982 | AB79: =SUM(Y79:AA79) -> 975.18501 | AC79: 7.27 | AD79: =SUM(AB79*AC79) -> 7089.595 | AE79: =SUM(X79+AD79) -> 10935.14 | AF79: =SUM(P79-AE79) -> 588.48409
C80: 241011000033 | D80: 45580 | E80: 罗珮文 | F80: Shirley | G80: Yusky | H80: 0.2995 | I80: 33 | K80: 117080 | M80: =SUM(K80/N80) -> 1544.9987 | N80: 75.78 | O80: 7.24 | P80: =SUM(N80*O80) -> 548.6472 | S80: =SUM(40096/68)*H80 -> 176.59929 | U80: =SUM(2100/68)*H80 -> 9.2492647 | X80: =SUM(S80:W80) -> 185.84856 | Y80: =SUM(10477.84/68)*H80 -> 46.148722 | AA80: =SUM(222.57/68)*H80 -> 0.98028993 | AB80: =SUM(Y80:AA80) -> 47.129012 | AC80: 7.27 | AD80: =SUM(AB80*AC80) -> 342.62791 | AE80: =SUM(X80+AD80) -> 528.47647 | AF80: =SUM(P80-AE80) -> 20.170726
C81: 241011000034 | D81: 45580 | E81: 罗珮文 | F81: Shirley | G81: Yusky | H81: 0.1865 | I81: 30 | K81: 72893 | M81: =SUM(K81/N81) -> 1544.9979 | N81: 47.18 | O81: 7.24 | P81: =SUM(N81*O81) -> 341.5832 | S81: =SUM(40096/68)*H81 -> 109.96918 | U81: =SUM(2100/68)*H81 -> 5.7595588 | X81: =SUM(S81:W81) -> 115.72874 | Y81: =SUM(10477.84/68)*H81 -> 28.737017 | AA81: =SUM(222.57/68)*H81 -> 0.61043096 | AB81: =SUM(Y81:AA81) -> 29.347448 | AC81: 7.27 | AD81: =SUM(AB81*AC81) -> 213.35595 | AE81: =SUM(X81+AD81) -> 329.08468 | AF81: =SUM(P81-AE81) -> 12.498518
C82: 241011000035 | D82: 45580 | E82: 罗珮文 | F82: Shirley | G82: Yusky | H82: 0.1821 | I82: 17 | K82: 72792.6 | M82: =SUM(K82/N82) -> 1580.0434 | N82: 46.07 | O82: 7.24 | P82: =SUM(N82*O82) -> 333.5468 | S82: =SUM(40096/68)*H82 -> 107.37473 | U82: =SUM(2100/68)*H82 -> 5.6236765 | X82: =SUM(S82:W82) -> 112.99841 | Y82: =SUM(10477.84/68)*H82 -> 28.059039 | AA82: =SUM(222.57/68)*H82 -> 0.59602937 | AB82: =SUM(Y82:AA82) -> 28.655069 | AC82: 7.27 | AD82: =SUM(AB82*AC82) -> 208.32235 | AE82: =SUM(X82+AD82) -> 321.32075 | AF82: =SUM(P82-AE82) -> 12.226046
C83: 241015000033 | D83: 45580 | E83: 吕沛霖 | F83: 喵喵速运-Layne | G83: MU SHI SHI | H83: 0.138 | I83: 26 | J83: 356 | P83: =SUBTOTAL(9,J83) -> 356 | S83: =SUM(40096/68)*H83 -> 81.371294 | U83: =SUM(2100/68)*H83 -> 4.2617647 | X83: =SUM(S83:W83) -> 85.633059 | Y83: =SUM(10477.84/68)*H83 -> 21.263852 | AA83: =SUM(222.57/68)*H83 -> 0.45168618 | AB83: =SUM(Y83:AA83) -> 21.715538 | AC83: 7.27 | AD83: =SUM(AB83*AC83) -> 157.87196 | AE83: =SUM(X83+AD83) -> 243.50502 | AF83: =SUM(P83-AE83) -> 112.49498
C84: 241005000007 | D84: 45580 | E84: 黄颖 | F84: ying | G84: MISS Huang | H84: 1.7993 | I84: 702.27 | K84: 830610 | M84: =SUM(K84/N84) -> 1678 | N84: 495 | O84: 7.27 | P84: =SUM(N84*O84) -> 3598.65 | S84: =SUM(40096/68)*H84 -> 1060.952 | U84: =SUM(2100/68)*H84 -> 55.566618 | X84: =SUM(S84:W84) -> 1116.5186 | Y84: =SUM(10477.84/68)*H84 -> 277.24673 | AA84: =SUM(222.57/68)*H84 -> 5.8892677 | AB84: =SUM(Y84:AA84) -> 283.136 | AC84: 7.27 | AD84: =SUM(AB84*AC84) -> 2058.3987 | AE84: =SUM(X84+AD84) -> 3174.9173 | AF84: =SUM(P84-AE84) -> 423.73274
C85: 241012000013 | D85: 45580 | E85: 黄颖 | F85: ying | G85: Bruce | H85: 4.6667 | I85: 1862 | K85: 2104240.8 | M85: =SUM(K85/N85) -> 1639.6599 | N85: 1283.3398 | O85: 7.29 | P85: =SUM(N85*O85) -> 9355.5471 | S85: =SUM(40096/68)*H85 -> 2751.7059 | U85: =SUM(2100/68)*H85 -> 144.11868 | X85: =SUM(S85:W85) -> 2895.8246 | Y85: =SUM(10477.84/68)*H85 -> 719.07259 | AA85: =SUM(222.57/68)*H85 -> 15.274521 | AB85: =SUM(Y85:AA85) -> 734.34711 | AC85: 7.27 | AD85: =SUM(AB85*AC85) -> 5338.7035 | AE85: =SUM(X85+AD85) -> 8234.5281 | AF85: =SUM(P85-AE85) -> 1121.0191
C86: 241007000001 | D86: 45580 | E86: 陆总 | F86: 陆梓龙 | G86: jizong | H86: 5.4 | I86: 3863.5 | J86: 12614.4 | P86: =SUBTOTAL(9,J86) -> 12614.4 | S86: =SUM(40096/68)*H86 -> 3184.0941 | U86: =SUM(2100/68)*H86 -> 166.76471 | X86: =SUM(S86:W86) -> 3350.8588 | Y86: =SUM(10477.84/68)*H86 -> 832.06376 | AA86: =SUM(222.57/68)*H86 -> 17.674676 | AB86: =SUM(Y86:AA86) -> 849.73844 | AC86: 7.27 | AD86: =SUM(AB86*AC86) -> 6177.5985 | AE86: =SUM(X86+AD86) -> 9528.4573 | AF86: =SUM(P86-AE86) -> 3085.9427
C87: 241014000047 | D87: 45580 | E87: 陆总 | F87: 陆梓龙 | G87: luk | H87: 1.7401 | I87: 1028 | J87: 3551.45 | P87: =SUBTOTAL(9,J87) -> 3551.45 | S87: =SUM(40096/68)*H87 -> 1026.0448 | U87: =SUM(2100/68)*H87 -> 53.738382 | V87: 150 | X87: =SUM(S87:W87) -> 1229.7832 | Y87: =SUM(10477.84/68)*H87 -> 268.12484 | AA87: =SUM(222.57/68)*H87 -> 5.6955008 | AB87: =SUM(Y87:AA87) -> 273.82034 | AC87: 7.27 | AD87: =SUM(AB87*AC87) -> 1990.6739 | AE87: =SUM(X87+AD87) -> 3220.4571 | AF87: =SUM(P87-AE87) -> 330.99286
C88: 241015000035 | D88: 45580 | E88: 罗珮文 | F88: Shirley | G88: James | H88: 0.6634 | I88: 185 | M88: =SUM(K88/N88) -> 0 | N88: 592.5 | O88: 7.11 | P88: =SUM(N88*O88) -> 4212.675 | S88: =SUM(40096/68)*H88 -> 391.17186 | U88: =SUM(2100/68)*H88 -> 20.487353 | X88: =SUM(S88:W88) -> 411.65921 | Y88: =SUM(10477.84/68)*H88 -> 102.22057 | AA88: =SUM(222.57/68)*H88 -> 2.1713667 | AB88: =SUM(Y88:AA88) -> 104.39194 | AC88: 7.27 | AD88: =SUM(AB88*AC88) -> 758.92941 | AE88: =SUM(X88+AD88) -> 1170.5886 | AF88: =SUM(P88-AE88) -> 3042.0864
A89: JOB100362 | B89: COLL004260 | C89: 240926000039 | D89: 45583 | E89: Sam.Pao | F89: Sam.Pao | G89: ShanShan | H89: 0.3 | I89: 65 | J89: 772 | P89: =SUBTOTAL(9,J89) -> 772 | Q89: =SUM(P89:P109) -> 135484.86 | R89: 登凯=38748 赛捷=1160 拖车费=1670 杂费=61 过磅费=67 | S89: =SUM(41706/68)*H89 -> 183.99706 | T89: =SUM(99.72/68)*H89 -> 0.43994118 | U89: =SUM(1500/68)*H89 -> 6.6176471 | X89: =SUM(S89:W89) -> 191.05465 | Y89: =SUM(10523.89/68)*H89 -> 46.428926 | Z89: 14.39 | AB89: =SUM(Y89:AA89) -> 60.818926 | AC89: 7.28 | AD89: =SUM(AB89*AC89) -> 442.76178 | AE89: =SUM(X89+AD89) -> 633.81643 | AF89: =SUM(P89-AE89) -> 138.18357
C90: 240926000032 | D90: 45580 | E90: 黄颖 | F90: ying | G90: Sunday Adelena | H90: 7.5159 | I90: 6108 | J90: 15370 | P90: =SUBTOTAL(9,J90) -> 15370 | S90: =SUM(41706/68)*H90 -> 4609.6783 | T90: =SUM(99.72/68)*H90 -> 11.021846 | U90: =SUM(1500/68)*H90 -> 165.79191 | X90: =SUM(S90:W90) -> 4786.4921 | Y90: =SUM(10523.89/68)*H90 -> 1163.1839 | AB90: =SUM(Y90:AA90) -> 1163.1839 | AC90: 7.28 | AD90: =SUM(AB90*AC90) -> 8467.9788 | AE90: =SUM(X90+AD90) -> 13254.471 | AF90: =SUM(P90-AE90) -> 2115.5292
C91: 241008000045 | D91: 45580 | E91: 黄颖 | F91: ying | G91: Wuchengxing | H91: 1.3298 | I91: 142 | J91: 2841 | P91: =SUBTOTAL(9,J91) -> 2841 | S91: =SUM(41706/68)*H91 -> 815.59763 | T91: =SUM(99.72/68)*H91 -> 1.9501126 | U91: =SUM(1500/68)*H91 -> 29.333824 | X91: =SUM(S91:W91) -> 846.88157 | Y91: =SUM(10523.89/68)*H91 -> 205.80395 | AB91: =SUM(Y91:AA91) -> 205.80395 | AC91: 7.28 | AD91: =SUM(AB91*AC91) -> 1498.2528 | AE91: =SUM(X91+AD91) -> 2345.1344 | AF91: =SUM(P91-AE91) -> 495.86564
C92: 240927000028 | D92: 45583 | E92: 吕沛霖 | F92: 喵喵速运-Layne | G92: MA ZONG | H92: 1.7904 | I92: 1841 | J92: 5660.38 | P92: =SUBTOTAL(9,J92) -> 5660.38 | S92: =SUM(41706/68)*H92 -> 1098.0944 | T92: =SUM(99.72/68)*H92 -> 2.6255689 | U92: =SUM(1500/68)*H92 -> 39.494118 | V92: 450 | X92: =SUM(S92:W92) -> 1590.2141 | Y92: =SUM(10523.89/68)*H92 -> 277.08783 | Z92: 68 | AB92: =SUM(Y92:AA92) -> 345.08783 | AC92: 7.28 | AD92: =SUM(AB92*AC92) -> 2512.2394 | AE92: =SUM(X92+AD92) -> 4102.4536 | AF92: =SUM(P92-AE92) -> 1557.9264
C93: 241008000110 | D93: 45583 | E93: Sam.Pao | F93: Sam.Pao | G93: MaiKaiNian | H93: 0.1724 | I93: 432 | J93: 1396.56 | P93: =SUBTOTAL(9,J93) -> 1396.56 | S93: =SUM(41706/68)*H93 -> 105.73698 | T93: =SUM(99.72/68)*H93 -> 0.25281953 | U93: =SUM(1500/68)*H93 -> 3.8029412 | X93: =SUM(S93:W93) -> 109.79274 | Y93: =SUM(10523.89/68)*H93 -> 26.681156 | AB93: =SUM(Y93:AA93) -> 26.681156 | AC93: 7.28 | AD93: =SUM(AB93*AC93) -> 194.23882 | AE93: =SUM(X93+AD93) -> 304.03156 | AF93: =SUM(P93-AE93) -> 1092.5284
C94: 241005000007 | D94: 45580 | E94: 黄颖 | F94: ying | G94: MISS Huang | H94: 1.7287 | I94: 674.73 | K94: 797943.5 | M94: =SUM(K94/N94) -> 1679.174 | N94: 475.2 | O94: 7.27 | P94: =SUM(N94*O94) -> 3454.704 | S94: =SUM(41706/68)*H94 -> 1060.2524 | T94: =SUM(99.72/68)*H94 -> 2.5350877 | U94: =SUM(1500/68)*H94 -> 38.133088 | X94: =SUM(S94:W94) -> 1100.9206 | Y94: =SUM(10523.89/68)*H94 -> 267.53895 | AB94: =SUM(Y94:AA94) -> 267.53895 | AC94: 7.28 | AD94: =SUM(AB94*AC94) -> 1947.6836 | AE94: =SUM(X94+AD94) -> 3048.6041 | AF94: =SUM(P94-AE94) -> 406.09988
C95: 241009000019 | D95: 45583 | E95: 黄颖 | F95: ying | G95: Wole Rasak | H95: 0.7338 | I95: 73 | J95: 1502.2 | P95: =SUBTOTAL(9,J95) -> 1502.2 | S95: =SUM(41706/68)*H95 -> 450.05681 | T95: =SUM(99.72/68)*H95 -> 1.0760961 | U95: =SUM(1500/68)*H95 -> 16.186765 | X95: =SUM(S95:W95) -> 467.31967 | Y95: =SUM(10523.89/68)*H95 -> 113.56515 | Z95: 3.45 | AB95: =SUM(Y95:AA95) -> 117.01515 | AC95: 7.28 | AD95: =SUM(AB95*AC95) -> 851.87032 | AE95: =SUM(X95+AD95) -> 1319.19 | AF95: =SUM(P95-AE95) -> 183.01001
C96: 241009000033 | D96: 45583 | E96: 陆总 | F96: 陆梓龙 | G96: leoluang | H96: 5.69 | I96: 3984 | J96: 9968.88 | P96: =SUBTOTAL(9,J96) -> 9968.88 | S96: =SUM(41706/68)*H96 -> 3489.8109 | T96: =SUM(99.72/68)*H96 -> 8.3442176 | U96: =SUM(1500/68)*H96 -> 125.51471 | X96: =SUM(S96:W96) -> 3623.6698 | Y96: =SUM(10523.89/68)*H96 -> 880.60197 | AB96: =SUM(Y96:AA96) -> 880.60197 | AC96: 7.28 | AD96: =SUM(AB96*AC96) -> 6410.7824 | AE96: =SUM(X96+AD96) -> 10034.452 | AF96: =SUM(P96-AE96) -> -65.572162
C97: 241010000022 | D97: 45583 | E97: Bella | F97: Bella Chan | G97: zhong zi xin | H97: 5.5556 | I97: 5276 | J97: 16400 | P97: =SUBTOTAL(9,J97) -> 16400 | S97: =SUM(41706/68)*H97 -> 3407.3802 | T97: =SUM(99.72/68)*H97 -> 8.147124 | U97: =SUM(1500/68)*H97 -> 122.55 | X97: =SUM(S97:W97) -> 3538.0773 | Y97: =SUM(10523.89/68)*H97 -> 859.80181 | Z97: 138.17 | AB97: =SUM(Y97:AA97) -> 997.97181 | AC97: 7.28 | AD97: =SUM(AB97*AC97) -> 7265.2348 | AE97: =SUM(X97+AD97) -> 10803.312 | AF97: =SUM(P97-AE97) -> 5596.6879
C98: 241012000025 | D98: 45583 | E98: 吕沛霖 | F98: 喵喵速运-Layne | G98: Sue | H98: 0.9445 | I98: 434 | K98: 559350 | M98: =SUM(K98/N98) -> 1650 | N98: 339 | O98: 7.29 | P98: =SUM(N98*O98) -> 2471.31 | S98: =SUM(41706/68)*H98 -> 579.28407 | T98: =SUM(99.72/68)*H98 -> 1.3850815 | U98: =SUM(1500/68)*H98 -> 20.834559 | X98: =SUM(S98:W98) -> 601.50371 | Y98: =SUM(10523.89/68)*H98 -> 146.17374 | AB98: =SUM(Y98:AA98) -> 146.17374 | AC98: 7.28 | AD98: =SUM(AB98*AC98) -> 1064.1448 | AE98: =SUM(X98+AD98) -> 1665.6485 | AF98: =SUM(P98-AE98) -> 805.66148
C99: 241012000031 | D99: 45583 | E99: 黄颖 | F99: ying | G99: liufang | H99: 2.0788 | I99: 174 | K99: 1322400 | M99: =SUM(K99/N99) -> 1675.812 | N99: 789.11 | O99: 7.29 | P99: =SUM(N99*O99) -> 5752.6119 | S99: =SUM(41706/68)*H99 -> 1274.977 | T99: =SUM(99.72/68)*H99 -> 3.0484991 | U99: =SUM(1500/68)*H99 -> 45.855882 | V99: 240 | X99: =SUM(S99:W99) -> 1563.8813 | Y99: =SUM(10523.89/68)*H99 -> 321.72151 | AB99: =SUM(Y99:AA99) -> 321.72151 | AC99: 7.28 | AD99: =SUM(AB99*AC99) -> 2342.1326 | AE99: =SUM(X99+AD99) -> 3906.0139 | AF99: =SUM(P99-AE99) -> 1846.598
C100: 241014000064 | D100: 45583 | E100: 苏慧琪 | F100: KAY | G100: WENXIAOBING | H100: 0.1024 | I100: 35 | K100: 71551 | M100: =SUM(K100/N100) -> 1690.3142 | N100: 42.33 | O100: 7.27 | P100: =SUM(N100*O100) -> 307.7391 | S100: =SUM(41706/68)*H100 -> 62.804329 | T100: =SUM(99.72/68)*H100 -> 0.15016659 | U100: =SUM(1500/68)*H100 -> 2.2588235 | X100: =SUM(S100:W100) -> 65.21332 | Y100: =SUM(10523.89/68)*H100 -> 15.84774 | AB100: =SUM(Y100:AA100) -> 15.84774 | AC100: 7.28 | AD100: =SUM(AB100*AC100) -> 115.37155 | AE100: =SUM(X100+AD100) -> 180.58487 | AF100: =SUM(P100-AE100) -> 127.15423
...

Sheet JOB100358
A1: 2024年10月份LOS毛利表（海运）
A2: PSL表 | B2: 体积cbm | C2: 81.6001
A3: JOB | B3: 集装编号 | C3: 运单编号 | D3: 日期 | E3: 业务 | F3: 发货人 | G3: 收货人 | H3: 计费体积 | I3: 计费重量 | J3: 应 收 | Q3: 总应收 | R3: 起 运 港 成 本 | W3: 代垫运费 | X3: 起运港成本 合计 | Y3: 目的港成本 | AE3: 总支出 | AF3: 利润
J4: 应收RMB | K4: LOS Income(NGN)收到(奈拉) | L4: LOS 收到USD | M4: 美元汇率 dollar currency rate | N4: 应收 到付款USD | O4: 汇率 | P4: 人民币 | R4: 代理商 | S4: 运费+出口报关费 | T4: 提货费 | U4: 装卸费 | V4: 包装费 | Y4: 进口报关费 | Z4: 到门配送费 | AA4: 转运费 | AB4: 目的港支出 | AC4: 汇率 | AD4: 人民币 | AE4: 起运港+目的港
A5: JOB100358 | B5: COLL004182 | C5: 240907000011 | D5: 45563 | E5: 吕沛霖 | F5: 喵喵速运-Layne | G5: MA ZONG | H5: 0.4074 | I5: 404 | J5: 1549.3 | P5: =SUBTOTAL(9,J5) -> 1549.3 | Q5: =SUM(P5:P25) -> 163992.94 | R5: 登凯=36617 赛捷=1660 拖车费=1670 杂费=499 过磅费=69 | S5: =SUM(40515/68)*H5 -> 242.73251 | U5: =SUM(2200/68)*H5 -> 13.180588 | X5: =SUM(S5:W5) -> 255.9131 | Y5: =SUM(10381.23/68)*H5 -> 62.195781 | Z5: 48.54 | AB5: =SUM(Y5:AA5) -> 110.73578 | AC5: 7.23 | AD5: =SUM(AB5*AC5) -> 800.6197 | AE5: =SUM(X5+AD5) -> 1056.5328 | AF5: =SUM(P5-AE5) -> 492.7672
C6: 240909000011 | D6: 45563 | E6: 黄颖 | F6: ying | G6: ying | H6: 0.036 | I6: 12 | K6: 87324 | M6: =SUM(K6/N6) -> 5916.2594 | N6: 14.760002 | O6: 7.24 | P6: =SUM(N6*O6) -> 106.86241 | S6: =SUM(40515/68)*H6 -> 21.449118 | U6: =SUM(2200/68)*H6 -> 1.1647059 | X6: =SUM(S6:W6) -> 22.613824 | Y6: =SUM(10381.23/68)*H6 -> 5.4959453 | Z6: 0.54 | AB6: =SUM(Y6:AA6) -> 6.0359453 | AC6: 7.23 | AD6: =SUM(AB6*AC6) -> 43.639884 | AE6: =SUM(X6+AD6) -> 66.253708 | AF6: =SUM(P6-AE6) -> 40.608706
C7: 240915000027 | D7: 45563 | E7: 吕沛霖 | F7: 喵喵速运-Layne | G7: Gao Hui | H7: 0.554 | I7: 177 | J7: 1986.97 | P7: =SUM(J7) -> 1986.97 | S7: =SUM(40515/68)*H7 -> 330.07809 | U7: =SUM(2200/68)*H7 -> 17.923529 | V7: 60 | X7: =SUM(S7:W7) -> 408.00162 | Y7: =SUM(10381.23/68)*H7 -> 84.576491 | Z7: 83.97 | AB7: =SUM(Y7:AA7) -> 168.54649 | AC7: 7.23 | AD7: =SUM(AB7*AC7) -> 1218.5911 | AE7: =SUM(X7+AD7) -> 1626.5928 | AF7: =SUM(P7-AE7) -> 360.37725
C8: 240919000042 | D8: 45563 | E8: 黄颖 | F8: ying | G8: MISS Huang | H8: 0.2211 | I8: 118 | J8: 468.7 | P8: =SUBTOTAL(9,J8) -> 468.7 | S8: =SUM(40515/68)*H8 -> 131.73333 | U8: =SUM(2200/68)*H8 -> 7.1532353 | X8: =SUM(S8:W8) -> 138.88657 | Y8: =SUM(10381.23/68)*H8 -> 33.754264 | AB8: =SUM(Y8:AA8) -> 33.754264 | AC8: 7.23 | AD8: =SUM(AB8*AC8) -> 244.04333 | AE8: =SUM(X8+AD8) -> 382.9299 | AF8: =SUM(P8-AE8) -> 85.770105
C9: 240920000027 | D9: 45563 | E9: 吕沛霖 | F9: 喵喵速运-Layne | G9: YA | H9: 1.1252 | I9: 111 | J9: 3500.8 | P9: =SUBTOTAL(9,J9) -> 3500.8 | S9: =SUM(40515/68)*H9 -> 670.40409 | U9: =SUM(2200/68)*H9 -> 36.403529 | X9: =SUM(S9:W9) -> 706.80762 | Y9: =SUM(10381.23/68)*H9 -> 171.77882 | Z9: 8.31 | AA9: 117.69 | AB9: =SUM(Y9:AA9) -> 297.77882 | AC9: 7.23 | AD9: =SUM(AB9*AC9) -> 2152.9409 | AE9: =SUM(X9+AD9) -> 2859.7485 | AF9: =SUM(P9-AE9) -> 641.05149
C10: 240920000030 | D10: 45563 | E10: 黄颖 | F10: ying | G10: baikaibo | H10: 0.319 | I10: 321 | K10: 385317 | M10: =SUM(K10/N10) -> 1767.347 | N10: 218.02 | O10: 7.24 | P10: =SUM(N10*O10) -> 1578.4648 | S10: =SUM(40515/68)*H10 -> 190.06301 | U10: =SUM(2200/68)*H10 -> 10.320588 | X10: =SUM(S10:W10) -> 200.3836 | Y10: =SUM(10381.23/68)*H10 -> 48.700182 | Z10: 85.03 | AB10: =SUM(Y10:AA10) -> 133.73018 | AC10: 7.23 | AD10: =SUM(AB10*AC10) -> 966.86922 | AE10: =SUM(X10+AD10) -> 1167.2528 | AF10: =SUM(P10-AE10) -> 411.21198
C11: 240923000009 | D11: 45563 | E11: 朱小飞 | F11: Isabel Zhu | G11: Wu Jiao Xing | H11: 0.5281 | I11: 104.5 | K11: 313621.07 | M11: =SUM(K11/N11) -> 1855.8559 | N11: 168.98999 | O11: 7.26 | P11: =SUM(N11*O11) -> 1226.8673 | S11: =SUM(40515/68)*H11 -> 314.64664 | U11: =SUM(2200/68)*H11 -> 17.085588 | X11: =SUM(S11:W11) -> 331.73223 | Y11: =SUM(10381.23/68)*H11 -> 80.622464 | AB11: =SUM(Y11:AA11) -> 80.622464 | AC11: 7.23 | AD11: =SUM(AB11*AC11) -> 582.90042 | AE11: =SUM(X11+AD11) -> 914.63264 | AF11: =SUM(P11-AE11) -> 312.23468
C12: 240923000035 | D12: 45547 | E12: 黄颖 | F12: ying | G12: Bruce | H12: 1.0584 | I12: 465 | J12: 2082 | P12: =SUBTOTAL(9,J12) -> 2082 | S12: =SUM(40515/68)*H12 -> 630.60406 | U12: =SUM(2200/68)*H12 -> 34.242353 | X12: =SUM(S12:W12) -> 664.84641 | Y12: =SUM(10381.23/68)*H12 -> 161.58079 | AB12: =SUM(Y12:AA12) -> 161.58079 | AC12: 7.23 | AD12: =SUM(AB12*AC12) -> 1168.2291 | AE12: =SUM(X12+AD12) -> 1833.0755 | AF12: =SUM(P12-AE12) -> 248.92446
C13: 240923000047 | D13: 45563 | E13: 吕沛霖 | F13: 喵喵速运-Layne | G13: WYLB | H13: 0.8 | I13: 197 | K13: 390880 | M13: =SUM(K13/N13) -> 1744.9998 | N13: 224.00003 | O13: 7.21 | P13: =SUM(N13*O13) -> 1615.0402 | S13: =SUM(40515/68)*H13 -> 476.64706 | U13: =SUM(2200/68)*H13 -> 25.882353 | X13: =SUM(S13:W13) -> 502.52941 | Y13: =SUM(10381.23/68)*H13 -> 122.13212 | AB13: =SUM(Y13:AA13) -> 122.13212 | AC13: 7.23 | AD13: =SUM(AB13*AC13) -> 883.01521 | AE13: =SUM(X13+AD13) -> 1385.5446 | AF13: =SUM(P13-AE13) -> 229.49559
C14: 240924000001 | D14: 45563 | E14: Sam.Pao | F14: Sam.Pao | G14: Yusky | H14: 8.51 | I14: 209 | J14: 14859.77 | P14: =SUBTOTAL(9,J14) -> 14859.77 | S14: =SUM(40515/68)*H14 -> 5070.3331 | U14: =SUM(2200/68)*H14 -> 275.32353 | X14: =SUM(S14:W14) -> 5345.6566 | Y14: =SUM(10381.23/68)*H14 -> 1299.1804 | AB14: =SUM(Y14:AA14) -> 1299.1804 | AC14: 7.23 | AD14: =SUM(AB14*AC14) -> 9393.0743 | AE14: =SUM(X14+AD14) -> 14738.731 | AF14: =SUM(P14-AE14) -> 121.03908
C15: 240925000028 | D15: 45563 | E15: 朱小飞 | F15: Isabel Zhu | G15: Halifa Success | H15: 1.2354 | I15: 125 | J15: 2382.35 | P15: =SUBTOTAL(9,J15) -> 2382.35 | S15: =SUM(40515/68)*H15 -> 736.06222 | U15: =SUM(2200/68)*H15 -> 39.968824 | X15: =SUM(S15:W15) -> 776.03104 | Y15: =SUM(10381.23/68)*H15 -> 188.60252 | AB15: =SUM(Y15:AA15) -> 188.60252 | AC15: 7.23 | AD15: =SUM(AB15*AC15) -> 1363.5962 | AE15: =SUM(X15+AD15) -> 2139.6273 | AF15: =SUM(P15-AE15) -> 242.72272
C16: 240926000027 | D16: 45563 | E16: Sam.Pao | F16: Sam.Pao | G16: ShanShan | H16: 1.555 | I16: 237 | J16: 3879 | P16: =SUBTOTAL(9,J16) -> 3879 | S16: =SUM(40515/68)*H16 -> 926.48272 | U16: =SUM(2200/68)*H16 -> 50.308824 | X16: =SUM(S16:W16) -> 976.79154 | Y16: =SUM(10381.23/68)*H16 -> 237.3943 | Z16: 36.85 | AB16: =SUM(Y16:AA16) -> 274.2443 | AC16: 7.23 | AD16: =SUM(AB16*AC16) -> 1982.7863 | AE16: =SUM(X16+AD16) -> 2959.5779 | AF16: =SUM(P16-AE16) -> 919.42214
C17: 240924000057 | D17: 45564 | E17: Sam.Pao | F17: Sam.Pao | G17: Arni | H17: 5.543 | I17: 3101 | J17: 12233 | P17: =SUBTOTAL(9,J17) -> 12233 | S17: =SUM(40515/68)*H17 -> 3302.5683 | U17: =SUM(2200/68)*H17 -> 179.33235 | X17: =SUM(S17:W17) -> 3481.9007 | Y17: =SUM(10381.23/68)*H17 -> 846.22291 | AB17: =SUM(Y17:AA17) -> 846.22291 | AC17: 7.23 | AD17: =SUM(AB17*AC17) -> 6118.1916 | AE17: =SUM(X17+AD17) -> 9600.0923 | AF17: =SUM(P17-AE17) -> 2632.9077
C18: 240906000023 | D18: 45559 | E18: Sam.Pao | F18: Sam.Pao | G18: ChenGaoHong | H18: 33.5175 | I18: 8313 | J18: 68845 | P18: =SUBTOTAL(9,J18) -> 68845 | S18: =SUM(40515/68)*H18 -> 19970.022 | U18: =SUM(2200/68)*H18 -> 1084.3897 | X18: =SUM(S18:W18) -> 21054.412 | Y18: =SUM(10381.23/68)*H18 -> 5116.9541 | AB18: =SUM(Y18:AA18) -> 5116.9541 | AC18: 7.23 | AD18: =SUM(AB18*AC18) -> 36995.578 | AE18: =SUM(X18+AD18) -> 58049.99 | AF18: =SUM(P18-AE18) -> 10795.01
C19: 240927000007 | D19: 45563 | E19: 黄颖 | F19: ying | G19: MISS Huang | H19: 1.745 | I19: 656 | J19: 3441 | P19: =SUBTOTAL(9,J19) -> 3441 | S19: =SUM(40515/68)*H19 -> 1039.6864 | U19: =SUM(2200/68)*H19 -> 56.455882 | X19: =SUM(S19:W19) -> 1096.1423 | Y19: =SUM(10381.23/68)*H19 -> 266.40068 | AB19: =SUM(Y19:AA19) -> 266.40068 | AC19: 7.23 | AD19: =SUM(AB19*AC19) -> 1926.0769 | AE19: =SUM(X19+AD19) -> 3022.2192 | AF19: =SUM(P19-AE19) -> 418.78079
C20: 240927000017 | D20: 45563 | E20: 朱小飞 | F20: Isabel Zhu | G20: Lin Bao Zhen | H20: 1.1235 | I20: 241 | K20: 594820.8 | M20: =SUM(K20/N20) -> 1891.0213 | N20: 314.55002 | O20: 7.26 | P20: =SUM(N20*O20) -> 2283.6331 | S20: =SUM(40515/68)*H20 -> 669.39121 | U20: =SUM(2200/68)*H20 -> 36.348529 | X20: =SUM(S20:W20) -> 705.73974 | Y20: =SUM(10381.23/68)*H20 -> 171.51929 | AB20: =SUM(Y20:AA20) -> 171.51929 | AC20: 7.23 | AD20: =SUM(AB20*AC20) -> 1240.0845 | AE20: =SUM(X20+AD20) -> 1945.8242 | AF20: =SUM(P20-AE20) -> 337.80892
C21: 240927000029 | D21: 45563 | E21: 朱小飞 | F21: Isabel Zhu | G21: Joy | H21: 1.7289 | I21: 1316 | K21: 1061222.4 | M21: =SUM(K21/N21) -> 1612.7994 | N21: 658.00024 | O21: 7.26 | P21: =SUM(N21*O21) -> 4777.0817 | S21: =SUM(40515/68)*H21 -> 1030.0939 | U21: =SUM(2200/68)*H21 -> 55.935 | X21: =SUM(S21:W21) -> 1086.0289 | Y21: =SUM(10381.23/68)*H21 -> 263.94277 | Z21: 7.97 | AB21: =SUM(Y21:AA21) -> 271.91277 | AC21: 7.23 | AD21: =SUM(AB21*AC21) -> 1965.9293 | AE21: =SUM(X21+AD21) -> 3051.9582 | AF21: =SUM(P21-AE21) -> 1725.1235
C22: 240921000019 | D22: 45563 | E22: 陆总 | F22: 陆梓龙 | G22: xiantian | H22: 0.3318 | I22: 185 | J22: 678.17 | P22: =SUBTOTAL(9,J22) -> 678.17 | S22: =SUM(40515/68)*H22 -> 197.68937 | U22: =SUM(2200/68)*H22 -> 10.734706 | X22: =SUM(S22:W22) -> 208.42407 | Y22: =SUM(10381.23/68)*H22 -> 50.654296 | AB22: =SUM(Y22:AA22) -> 50.654296 | AC22: 7.23 | AD22: =SUM(AB22*AC22) -> 366.23056 | AE22: =SUM(X22+AD22) -> 574.65463 | AF22: =SUM(P22-AE22) -> 103.51537
C23: 240927000032 | D23: 45563 | E23: 罗珮文 | F23: Shirley | G23: Yusky | H23: 0.4929 | I23: 47.1 | J23: 860.11 | P23: =SUBTOTAL(9,J23) -> 860.11 | S23: =SUM(40515/68)*H23 -> 293.67417 | U23: =SUM(2200/68)*H23 -> 15.946765 | X23: =SUM(S23:W23) -> 309.62093 | Y23: =SUM(10381.23/68)*H23 -> 75.248651 | AB23: =SUM(Y23:AA23) -> 75.248651 | AC23: 7.23 | AD23: =SUM(AB23*AC23) -> 544.04775 | AE23: =SUM(X23+AD23) -> 853.66868 | AF23: =SUM(P23-AE23) -> 6.4413196
C24: 240927000070 | D24: 45563 | E24: 陆总 | F24: 陆梓龙 | G24: xinlong | H24: 17.4127 | I24: 10650 | J24: 29515.58 | P24: =SUBTOTAL(9,J24) -> 29515.58 | S24: =SUM(40515/68)*H24 -> 10374.64 | U24: =SUM(2200/68)*H24 -> 563.35206 | X24: =SUM(S24:W24) -> 10937.992 | Y24: =SUM(10381.23/68)*H24 -> 2658.3124 | Z24: 85.88 | AB24: =SUM(Y24:AA24) -> 2744.1924 | AC24: 7.23 | AD24: =SUM(AB24*AC24) -> 19840.511 | AE24: =SUM(X24+AD24) -> 30778.503 | AF24: =SUM(P24-AE24) -> -1262.9235
C25: 240928000018 | D25: 45563 | E25: 陆总 | F25: 陆梓龙 | G25: leoluang | H25: 3.3552 | I25: 1105 | J25: 6123.24 | P25: =SUBTOTAL(9,J25) -> 6123.24 | S25: =SUM(40515/68)*H25 -> 1999.0578 | U25: =SUM(2200/68)*H25 -> 108.55059 | X25: =SUM(S25:W25) -> 2107.6084 | Y25: =SUM(10381.23/68)*H25 -> 512.2221 | AB25: =SUM(Y25:AA25) -> 512.2221 | AC25: 7.23 | AD25: =SUM(AB25*AC25) -> 3703.3658 | AE25: =SUM(X25+AD25) -> 5810.9741 | AF25: =SUM(P25-AE25) -> 312.26585
A26: 合计 | J26: =SUM(J4:J4) -> 0 | N26: =SUM(N4:N4) -> 0 | P26: =SUM(P4:P4) -> 0 | Q26: =SUM(Q4:Q4) -> 0 | X26: =SUM(X4:X4) -> 0 | AD26: =SUM(AD4:AD4) -> 0 | AF26: =SUM(AF4:AF25) -> 19174.556

Sheet JOB100359
A1: 2024年10月份LOS毛利表（海运）
A2: PSL表 | B2: 体积cbm | C2: 77.3653
A3: JOB | B3: 集装编号 | C3: 运单编号 | D3: 日期 | E3: 业务 | F3: 发货人 | G3: 收货人 | H3: 计费体积 | I3: 计费重量 | J3: 应 收 | Q3: 总应收 | R3: 起 运 港 成 本 | W3: 代垫运费 | X3: 起运港成本 合计 | Y3: 目的港成本 | AE3: 总支出 | AF3: 利润
J4: 应收RMB | K4: LOS Income(NGN)收到(奈拉) | L4: LOS 收到USD | M4: 美元汇率 dollar currency rate | N4: 应收 到付款USD | O4: 汇率 | P4: 人民币 | R4: 代理商 | S4: 运费+出口报关费 | T4: 提货费 | U4: 装卸费 | V4: 包装费 | Y4: 进口报关费 | Z4: 到门配送费 | AA4: 转运费 | AB4: 目的港支出 | AC4: 汇率 | AD4: 人民币 | AE4: 起运港+目的港
A5: JOB100359 | B5: COLL004278 | C5: 240919000034 | D5: 45563 | E5: 朱小飞 | F5: Isabel Zhu | G5: Wu Jiao Xing | H5: 0.8132 | I5: 104 | K5: 607758.93 | M5: =SUM(K5/N5) -> 1737 | N5: 349.89 | O5: 7.26 | P5: =SUM(N5*O5) -> 2540.2014 | Q5: =SUM(P5:P14) -> 148903 | R5: 登凯=39001 赛捷=1660 | S5: =SUM(40661/68)*H5 -> 486.25772 | T5: =SUM(94.72/68)*H5 -> 1.1327398 | U5: =SUM(2000/68)*H5 -> 23.917647 | V5: 420 | X5: =SUM(S5:W5) -> 931.30811 | Y5: =SUM(10381.24/68)*H5 -> 124.14742 | AB5: =SUM(Y5:AA5) -> 124.14742 | AC5: 7.24 | AD5: =SUM(AB5*AC5) -> 898.8273 | AE5: =SUM(X5+AD5) -> 1830.1354 | AF5: =SUM(P5-AE5) -> 710.06599
C6: 240921000009 | D6: 45563 | E6: 苏慧琪 | F6: KAY | G6: OKECHUKWU | H6: 0.075 | I6: 19 | J6: 318 | P6: =SUM(J6) -> 318 | S6: =SUM(40661/68)*H6 -> 44.846691 | T6: =SUM(94.72/68)*H6 -> 0.10447059 | U6: =SUM(2000/68)*H6 -> 2.2058824 | X6: =SUM(S6:W6) -> 47.157044 | Y6: =SUM(10381.24/68)*H6 -> 11.449897 | AB6: =SUM(Y6:AA6) -> 11.449897 | AC6: 7.24 | AD6: =SUM(AB6*AC6) -> 82.897255 | AE6: =SUM(X6+AD6) -> 130.0543 | AF6: =SUM(P6-AE6) -> 187.9457
C7: 240921000019 | D7: 45563 | E7: 陆总 | F7: 陆梓龙 | G7: xiantian | H7: 10.1452 | I7: 2149.35 | J7: 20732 | P7: =SUBTOTAL(9,J7) -> 20732 | S7: =SUM(40661/68)*H7 -> 6066.382 | T7: =SUM(94.72/68)*H7 -> 14.131667 | U7: =SUM(2000/68)*H7 -> 298.38824 | V7: =SUM(450+350) -> 800 | X7: =SUM(S7:W7) -> 7178.9019 | Y7: =SUM(10381.24/68)*H7 -> 1548.8199 | AB7: =SUM(Y7:AA7) -> 1548.8199 | AC7: 7.24 | AD7: =SUM(AB7*AC7) -> 11213.456 | AE7: =SUM(X7+AD7) -> 18392.358 | AF7: =SUM(P7-AE7) -> 2339.6417
C8: 240923000035 | D8: 45563 | E8: 黄颖 | F8: ying | G8: Bruce | H8: 7.0714 | I8: 3083 | J8: 13913.3 | P8: =SUBTOTAL(9,J8) -> 13913.3 | S8: =SUM(40661/68)*H8 -> 4228.3852 | T8: =SUM(94.72/68)*H8 -> 9.8500442 | U8: =SUM(2000/68)*H8 -> 207.98235 | X8: =SUM(S8:W8) -> 4446.2176 | Y8: =SUM(10381.24/68)*H8 -> 1079.5574 | AB8: =SUM(Y8:AA8) -> 1079.5574 | AC8: 7.24 | AD8: =SUM(AB8*AC8) -> 7815.9953 | AE8: =SUM(X8+AD8) -> 12262.213 | AF8: =SUM(P8-AE8) -> 1651.0871
C9: 240906000023 | D9: 45559 | E9: Sam.Pao | F9: Sam.Pao | G9: ChenGaoHong | H9: 24.9775 | I9: 6522 | J9: 51303 | P9: =SUBTOTAL(9,J9) -> 51303 | S9: =SUM(40661/68)*H9 -> 14935.443 | T9: =SUM(94.72/68)*H9 -> 34.792188 | U9: =SUM(2000/68)*H9 -> 734.63235 | X9: =SUM(S9:W9) -> 15704.868 | Y9: =SUM(10381.24/68)*H9 -> 3813.1974 | AB9: =SUM(Y9:AA9) -> 3813.1974 | AC9: 7.24 | AD9: =SUM(AB9*AC9) -> 27607.549 | AE9: =SUM(X9+AD9) -> 43312.417 | AF9: =SUM(P9-AE9) -> 7990.5833
C10: 240919000020 | D10: 45564 | E10: 吕沛霖 | F10: 喵喵速运-Layne | G10: ABDUL | H10: 1.06 | I10: 594 | J10: 2180 | P10: =SUBTOTAL(9,J10) -> 2180 | S10: =SUM(40661/68)*H10 -> 633.83324 | T10: =SUM(94.72/68)*H10 -> 1.4765176 | U10: =SUM(2000/68)*H10 -> 31.176471 | X10: =SUM(S10:W10) -> 666.48622 | Y10: =SUM(10381.24/68)*H10 -> 161.82521 | AB10: =SUM(Y10:AA10) -> 161.82521 | AC10: 7.24 | AD10: =SUM(AB10*AC10) -> 1171.6145 | AE10: =SUM(X10+AD10) -> 1838.1008 | AF10: =SUM(P10-AE10) -> 341.89924
C11: 240924000057 | D11: 45564 | E11: Sam.Pao | F11: Sam.Pao | G11: Arni | H11: 5.543 | I11: 3097 | J11: 12233 | P11: =SUBTOTAL(9,J11) -> 12233 | S11: =SUM(40661/68)*H11 -> 3314.4695 | T11: =SUM(94.72/68)*H11 -> 7.7210729 | U11: =SUM(2000/68)*H11 -> 163.02941 | X11: =SUM(S11:W11) -> 3485.2199 | Y11: =SUM(10381.24/68)*H11 -> 846.22373 | AB11: =SUM(Y11:AA11) -> 846.22373 | AC11: 7.24 | AD11: =SUM(AB11*AC11) -> 6126.6598 | AE11: =SUM(X11+AD11) -> 9611.8797 | AF11: =SUM(P11-AE11) -> 2621.1203
C12: 240928000023 | D12: 45564 | E12: Sam.Pao | F12: Sam.Pao | G12: SKY JET | H12: 6.37 | I12: 908.5 | J12: 9341.73 | P12: =SUBTOTAL(9,J12) -> 9341.73 | S12: =SUM(40661/68)*H12 -> 3808.979 | T12: =SUM(94.72/68)*H12 -> 8.8730353 | U12: =SUM(2000/68)*H12 -> 187.35294 | X12: =SUM(S12:W12) -> 4005.2049 | Y12: =SUM(10381.24/68)*H12 -> 972.47792 | AB12: =SUM(Y12:AA12) -> 972.47792 | AC12: 7.24 | AD12: =SUM(AB12*AC12) -> 7040.7402 | AE12: =SUM(X12+AD12) -> 11045.945 | AF12: =SUM(P12-AE12) -> -1704.2151
C13: 240927000032 | D13: 45563 | E13: 罗珮文 | F13: Shirley | G13: Yusky | H13: 4.4364 | I13: 423.9 | J13: 7740.66 | P13: =SUBTOTAL(9,J13) -> 7740.66 | S13: =SUM(40661/68)*H13 -> 2652.7715 | T13: =SUM(94.72/68)*H13 -> 6.1796442 | U13: =SUM(2000/68)*H13 -> 130.48235 | X13: =SUM(S13:W13) -> 2789.4335 | Y13: =SUM(10381.24/68)*H13 -> 677.28431 | AB13: =SUM(Y13:AA13) -> 677.28431 | AC13: 7.24 | AD13: =SUM(AB13*AC13) -> 4903.5384 | AE13: =SUM(X13+AD13) -> 7692.9719 | AF13: =SUM(P13-AE13) -> 47.688116
C14: 240927000071 | D14: 45563 | E14: 陆总 | F14: 陆梓龙 | G14: xinlong | H14: 16.8732 | I14: 10470 | J14: 28601.11 | P14: =SUBTOTAL(9,J14) -> 28601.11 | S14: =SUM(40661/68)*H14 -> 10089.429 | T14: =SUM(94.72/68)*H14 -> 23.503375 | U14: =SUM(2000/68)*H14 -> 496.27059 | X14: =SUM(S14:W14) -> 10609.203 | Y14: =SUM(10381.24/68)*H14 -> 2575.952 | Z14: 84.18 | AB14: =SUM(Y14:AA14) -> 2660.132 | AC14: 7.24 | AD14: =SUM(AB14*AC14) -> 19259.356 | AE14: =SUM(X14+AD14) -> 29868.559 | AF14: =SUM(P14-AE14) -> -1267.4491
A15: 合计 | J15: =SUM(J4:J4) -> 0 | N15: =SUM(N4:N4) -> 0 | P15: =SUM(P4:P4) -> 0 | Q15: =SUM(Q4:Q4) -> 0 | X15: =SUM(X4:X4) -> 0 | AD15: =SUM(AD4:AD4) -> 0 | AF15: =SUM(AF4:AF14) -> 12918.367

Sheet JOB100360
A1: 2024年10月份LOS毛利表（海运）
A2: PSL表 | B2: 体积cbm | C2: 75.3622
A3: JOB | B3: 集装编号 | C3: 运单编号 | D3: 日期 | E3: 业务 | F3: 发货人 | G3: 收货人 | H3: 计费体积 | I3: 计费重量 | J3: 应 收 | Q3: 总应收 | R3: 起 运 港 成 本 | W3: 代垫运费 | X3: 起运港成本 合计 | Y3: 目的港成本 | AE3: 总支出 | AF3: 利润
J4: 应收RMB | K4: LOS Income(NGN)收到(奈拉) | L4: LOS 收到USD | M4: 美元汇率 dollar currency rate | N4: 应收 到付款USD | O4: 汇率 | P4: 人民币 | R4: 代理商 | S4: 运费+出口报关费 | T4: 提货费 | U4: 装卸费 | V4: 包装费 | Y4: 进口报关费 | Z4: 到门配送费 | AA4: 转运费 | AB4: 目的港支出 | AC4: 汇率 | AD4: 人民币 | AE4: 起运港+目的港
A5: JOB100360 | B5: COLL004247 | C5: 240918000046 | D5: 45564 | E5: 朱小飞 | F5: Isabel Zhu | G5: Lin Bao Zhen | H5: 11.5853 | I5: 3144 | K5: 7151961.6 | M5: =SUM(K5/N5) -> 1754.9707 | N5: 4075.2598 | O5: 7.26 | P5: =SUM(N5*O5) -> 29586.386 | Q5: =SUM(P5:P14) -> 153384.01 | R5: 登凯=36901 赛捷=2800 拖车费=1670 杂费=497 过磅费=65 | S5: =SUM(41933/68)*H5 -> 7144.2115 | U5: =SUM(1400/68)*H5 -> 238.52088 | V5: 150 | X5: =SUM(S5:W5) -> 7532.7324 | Y5: =SUM(10381.24/68)*H5 -> 1768.6732 | AB5: =SUM(Y5:AA5) -> 1768.6732 | AC5: 7.24 | AD5: =SUM(AB5*AC5) -> 12805.194 | AE5: =SUM(X5+AD5) -> 20337.927 | AF5: =SUM(P5-AE5) -> 9248.4595
C6: 240919000028 | D6: 45564 | E6: 陆总 | F6: 陆梓龙 | G6: jizong | H6: 4.5828 | I6: 3750 | J6: 10847.8 | P6: =SUBTOTAL(9,J6) -> 10847.8 | S6: =SUM(41933/68)*H6 -> 2826.0375 | U6: =SUM(1400/68)*H6 -> 94.351765 | X6: =SUM(S6:W6) -> 2920.3893 | Y6: =SUM(10381.24/68)*H6 -> 699.63451 | AB6: =SUM(Y6:AA6) -> 699.63451 | AC6: 7.24 | AD6: =SUM(AB6*AC6) -> 5065.3539 | AE6: =SUM(X6+AD6) -> 7985.7432 | AF6: =SUM(P6-AE6) -> 2862.0568
C7: 240906000023 | D7: 45559 | E7: Sam.Pao | F7: Sam.Pao | G7: ChenGaoHong | H7: 17.6195 | I7: 5514 | J7: 36190 | P7: =SUBTOTAL(9,J7) -> 36190 | S7: =SUM(41933/68)*H7 -> 10865.272 | U7: =SUM(1400/68)*H7 -> 362.75441 | X7: =SUM(S7:W7) -> 11228.026 | Y7: =SUM(10381.24/68)*H7 -> 2689.8861 | AB7: =SUM(Y7:AA7) -> 2689.8861 | AC7: 7.24 | AD7: =SUM(AB7*AC7) -> 19474.776 | AE7: =SUM(X7+AD7) -> 30702.802 | AF7: =SUM(P7-AE7) -> 5487.1979
C8: 240924000057 | D8: 45564 | E8: Sam.Pao | F8: Sam.Pao | G8: Arni | H8: 4.4869 | I8: 2510.11 | J8: 9902 | P8: =SUBTOTAL(9,J8) -> 9902 | S8: =SUM(41933/68)*H8 -> 2766.8997 | U8: =SUM(1400/68)*H8 -> 92.377353 | X8: =SUM(S8:W8) -> 2859.277 | Y8: =SUM(10381.24/68)*H8 -> 684.99391 | AB8: =SUM(Y8:AA8) -> 684.99391 | AC8: 7.24 | AD8: =SUM(AB8*AC8) -> 4959.3559 | AE8: =SUM(X8+AD8) -> 7818.6329 | AF8: =SUM(P8-AE8) -> 2083.3671
C9: 240919000020 | D9: 45564 | E9: 吕沛霖 | F9: 喵喵速运-Layne | G9: ABDUL | H9: 3.887 | I9: 1821.5 | J9: 8001.8 | P9: =SUBTOTAL(9,J9) -> 8001.8 | S9: =SUM(41933/68)*H9 -> 2396.9643 | U9: =SUM(1400/68)*H9 -> 80.026471 | X9: =SUM(S9:W9) -> 2476.9907 | Y9: =SUM(10381.24/68)*H9 -> 593.41 | AB9: =SUM(Y9:AA9) -> 593.41 | AC9: 7.24 | AD9: =SUM(AB9*AC9) -> 4296.2884 | AE9: =SUM(X9+AD9) -> 6773.2791 | AF9: =SUM(P9-AE9) -> 1228.5209
C10: 240929000009 | D10: 45564 | E10: 朱小飞 | F10: Isabel Zhu | G10: Joy | H10: 6.7645 | I10: 2500 | K10: 3821265 | M10: =SUM(K10/N10) -> 1883.3243 | N10: 2029 | O10: 7.26 | P10: =SUM(N10*O10) -> 14730.54 | S10: =SUM(41933/68)*H10 -> 4171.4085 | U10: =SUM(1400/68)*H10 -> 139.26912 | X10: =SUM(S10:W10) -> 4310.6776 | Y10: =SUM(10381.24/68)*H10 -> 1032.7044 | AB10: =SUM(Y10:AA10) -> 1032.7044 | AC10: 7.24 | AD10: =SUM(AB10*AC10) -> 7476.7797 | AE10: =SUM(X10+AD10) -> 11787.457 | AF10: =SUM(P10-AE10) -> 2943.0826
C11: 240928000023 | D11: 45564 | E11: Sam.Pao | F11: Sam.Pao | G11: SKY JET | H11: 22.557 | I11: 3296 | J11: 33080.26 | P11: =SUBTOTAL(9,J11) -> 33080.26 | S11: =SUM(41933/68)*H11 -> 13910.039 | U11: =SUM(1400/68)*H11 -> 464.40882 | X11: =SUM(S11:W11) -> 14374.448 | Y11: =SUM(10381.24/68)*H11 -> 3443.671 | AB11: =SUM(Y11:AA11) -> 3443.671 | AC11: 7.24 | AD11: =SUM(AB11*AC11) -> 24932.178 | AE11: =SUM(X11+AD11) -> 39306.627 | AF11: =SUM(P11-AE11) -> -6226.3666
C12: 240929000010 | D12: 45564 | E12: 朱小飞 | F12: Isabel Zhu | G12: Joy | H12: 1.3975 | I12: 377 | K12: 790272 | M12: =SUM(K12/N12) -> 1885.1008 | N12: 419.22003 | O12: 7.26 | P12: =SUM(N12*O12) -> 3043.5374 | S12: =SUM(41933/68)*H12 -> 861.78482 | U12: =SUM(1400/68)*H12 -> 28.772059 | X12: =SUM(S12:W12) -> 890.55687 | Y12: =SUM(10381.24/68)*H12 -> 213.34975 | Z12: 9.86 | AB12: =SUM(Y12:AA12) -> 223.20975 | AC12: 7.24 | AD12: =SUM(AB12*AC12) -> 1616.0386 | AE12: =SUM(X12+AD12) -> 2506.5955 | AF12: =SUM(P12-AE12) -> 536.94196
C13: 240929000011（补单） | D13: 45564 | E13: 朱小飞 | F13: Isabel Zhu | G13: Joy | H13: 2.4334 | I13: 2340 | K13: 1822400 | M13: =SUM(K13/N13) -> 1700 | N13: 1072 | O13: 7.29 | P13: =SUM(N13*O13) -> 7814.88 | S13: =SUM(41933/68)*H13 -> 1500.5847 | U13: =SUM(1400/68)*H13 -> 50.099412 | X13: =SUM(S13:W13) -> 1550.6842 | Y13: =SUM(10381.24/68)*H13 -> 371.49573 | AB13: =SUM(Y13:AA13) -> 371.49573 | AC13: 7.24 | AD13: =SUM(AB13*AC13) -> 2689.6291 | AE13: =SUM(X13+AD13) -> 4240.3132 | AF13: =SUM(P13-AE13) -> 3574.5668
C14: 240929000057 | D14: 45564 | E14: 陆总 | F14: 陆梓龙 | G14: luk | H14: 0.0914 | I14: 64 | J14: 186.81 | P14: =SUBTOTAL(9,J14) -> 186.81 | S14: =SUM(41933/68)*H14 -> 56.362885 | U14: =SUM(1400/68)*H14 -> 1.8817647 | X14: =SUM(S14:W14) -> 58.24465 | Y14: =SUM(10381.24/68)*H14 -> 13.953608 | AB14: =SUM(Y14:AA14) -> 13.953608 | AC14: 7.24 | AD14: =SUM(AB14*AC14) -> 101.02412 | AE14: =SUM(X14+AD14) -> 159.26877 | AF14: =SUM(P14-AE14) -> 27.541229
A15: 合计 | J15: =SUM(J4:J4) -> 0 | N15: =SUM(N4:N4) -> 0 | P15: =SUM(P4:P4) -> 0 | Q15: =SUM(Q4:Q4) -> 0 | X15: =SUM(X4:X4) -> 0 | AD15: =SUM(AD4:AD4) -> 0 | AF15: =SUM(AF4:AF14) -> 21765.368

Sheet JOB100361
A1: 2024年10月份LOS毛利表（海运）
A2: PSL表 | B2: 体积cbm | C2: 69.5919
A3: JOB | B3: 集装编号 | C3: 运单编号 | D3: 日期 | E3: 业务 | F3: 发货人 | G3: 收货人 | H3: 计费体积 | I3: 计费重量 | J3: 应 收 | Q3: 总应收 | R3: 起 运 港 成 本 | W3: 代垫运费 | X3: 起运港成本 合计 | Y3: 目的港成本 | AE3: 总支出 | AF3: 利润
J4: 应收RMB | K4: LOS Income(NGN)收到(奈拉) | L4: LOS 收到USD | M4: 美元汇率 dollar currency rate | N4: 应收 到付款USD | O4: 汇率 | P4: 人民币 | R4: 代理商 | S4: 运费+出口报关费 | T4: 提货费 | U4: 装卸费 | V4: 包装费 | Y4: 进口报关费 | Z4: 到门配送费 | AA4: 转运费 | AB4: 目的港支出 | AC4: 汇率 | AD4: 人民币 | AE4: 起运港+目的港
A5: JOB100361 | B5: COLL004248 | C5: 240906000023 | D5: 45564 | E5: Sam.Pao | F5: Sam.Pao | G5: ChenGaoHong | H5: 11.9955 | I5: 4372 | J5: 24695 | P5: =SUBTOTAL(9,J5) -> 24695 | Q5: =SUM(P5:P22) -> 122040.48 | R5: 登凯=37199 赛捷=1500 拖车费=1670 杂费=495 过磅费=50 | S5: =SUM(40914/68)*H5 -> 7217.4101 | U5: =SUM(1000/68)*H5 -> 176.40441 | V5: =SUM(800+800) -> 1600 | X5: =SUM(S5:W5) -> 8993.8145 | Y5: =SUM(10381.24/68)*H5 -> 1831.2965 | AA5: =SUM(114.28/68)*H5 -> 20.159496 | AB5: =SUM(Y5:AA5) -> 1851.456 | AC5: 7.27 | AD5: =SUM(AB5*AC5) -> 13460.085 | AE5: =SUM(X5+AD5) -> 22453.9 | AF5: =SUM(P5-AE5) -> 2241.1001
C6: 240919000020 | D6: 45564 | E6: 吕沛霖 | F6: 喵喵速运-Layne | G6: ABDUL | H6: 1.4136 | I6: 664.5 | J6: 2907 | P6: =SUBTOTAL(9,J6) -> 2907 | S6: =SUM(40914/68)*H6 -> 850.52986 | U6: =SUM(1000/68)*H6 -> 20.788235 | X6: =SUM(S6:W6) -> 871.31809 | Y6: =SUM(10381.24/68)*H6 -> 215.80766 | AA6: =SUM(114.28/68)*H6 -> 2.3756795 | AB6: =SUM(Y6:AA6) -> 218.18334 | AC6: 7.27 | AD6: =SUM(AB6*AC6) -> 1586.1929 | AE6: =SUM(X6+AD6) -> 2457.511 | AF6: =SUM(P6-AE6) -> 449.48903
C7: 240924000057 | D7: 45564 | E7: Sam.Pao | F7: Sam.Pao | G7: Arni | H7: 1.1877 | I7: 664.44 | J7: 2625 | P7: =SUBTOTAL(9,J7) -> 2625 | S7: =SUM(40914/68)*H7 -> 714.61114 | U7: =SUM(1000/68)*H7 -> 17.466176 | X7: =SUM(S7:W7) -> 732.07732 | Y7: =SUM(10381.24/68)*H7 -> 181.32057 | AA7: =SUM(114.28/68)*H7 -> 1.9960346 | AB7: =SUM(Y7:AA7) -> 183.3166 | AC7: 7.27 | AD7: =SUM(AB7*AC7) -> 1332.7117 | AE7: =SUM(X7+AD7) -> 2064.789 | AF7: =SUM(P7-AE7) -> 560.21096
C8: 240925000034 | D8: 45564 | E8: 无人 | F8: dejare James | G8: ALH RAKIM | H8: 0.8264 | I8: 605 | J8: 3329.79 | P8: =SUBTOTAL(9,J8) -> 3329.79 | S8: =SUM(40914/68)*H8 -> 497.22544 | U8: =SUM(1000/68)*H8 -> 12.152941 | X8: =SUM(S8:W8) -> 509.37838 | Y8: =SUM(10381.24/68)*H8 -> 126.1626 | Z8: 194.84 | AA8: =SUM(114.28/68)*H8 -> 1.3888381 | AB8: =SUM(Y8:AA8) -> 322.39144 | AC8: 7.27 | AD8: =SUM(AB8*AC8) -> 2343.7857 | AE8: =SUM(X8+AD8) -> 2853.1641 | AF8: =SUM(P8-AE8) -> 476.62588
C9: 240926000001 | D9: 45564 | E9: 陆总 | F9: 陆梓龙 | G9: jizong | H9: 0.5358 | I9: 276 | J9: 1095.15 | P9: =SUBTOTAL(9,J9) -> 1095.15 | S9: =SUM(40914/68)*H9 -> 322.37825 | U9: =SUM(1000/68)*H9 -> 7.8794118 | X9: =SUM(S9:W9) -> 330.25766 | Y9: =SUM(10381.24/68)*H9 -> 81.798065 | AA9: =SUM(114.28/68)*H9 -> 0.90045918 | AB9: =SUM(Y9:AA9) -> 82.698524 | AC9: 7.27 | AD9: =SUM(AB9*AC9) -> 601.21827 | AE9: =SUM(X9+AD9) -> 931.47593 | AF9: =SUM(P9-AE9) -> 163.67407
C10: 240919000043 | D10: 45564 | E10: 黄颖 | F10: ying | G10: Mr wang | H10: 0.4921 | I10: 109 | J10: 1159 | P10: =SUBTOTAL(9,J10) -> 1159 | S10: =SUM(40914/68)*H10 -> 296.08499 | U10: =SUM(1000/68)*H10 -> 7.2367647 | X10: =SUM(S10:W10) -> 303.32176 | Y10: =SUM(10381.24/68)*H10 -> 75.126591 | AA10: =SUM(114.28/68)*H10 -> 0.82701747 | AB10: =SUM(Y10:AA10) -> 75.953609 | AC10: 7.27 | AD10: =SUM(AB10*AC10) -> 552.18274 | AE10: =SUM(X10+AD10) -> 855.50449 | AF10: =SUM(P10-AE10) -> 303.49551
C11: 240926000008 | D11: 45564 | E11: 黄颖 | F11: ying | G11: Nura | H11: 0.102 | I11: 67 | J11: 223.3 | P11: =SUBTOTAL(9,J11) -> 223.3 | S11: =SUM(40914/68)*H11 -> 61.371 | U11: =SUM(1000/68)*H11 -> 1.5 | X11: =SUM(S11:W11) -> 62.871 | Y11: =SUM(10381.24/68)*H11 -> 15.57186 | AA11: =SUM(114.28/68)*H11 -> 0.17142 | AB11: =SUM(Y11:AA11) -> 15.74328 | AC11: 7.27 | AD11: =SUM(AB11*AC11) -> 114.45365 | AE11: =SUM(X11+AD11) -> 177.32465 | AF11: =SUM(P11-AE11) -> 45.975354
C12: 240928000014 | D12: 45564 | E12: 朱小飞 | F12: Isabel Zhu | G12: Halifa Success | H12: 0.6152 | I12: 107 | J12: 1191.18 | P12: =SUBTOTAL(9,J12) -> 1191.18 | S12: =SUM(40914/68)*H12 -> 370.15136 | U12: =SUM(1000/68)*H12 -> 9.0470588 | X12: =SUM(S12:W12) -> 379.19842 | Y12: =SUM(10381.24/68)*H12 -> 93.919689 | AA12: =SUM(114.28/68)*H12 -> 1.0338979 | AB12: =SUM(Y12:AA12) -> 94.953587 | AC12: 7.27 | AD12: =SUM(AB12*AC12) -> 690.31258 | AE12: =SUM(X12+AD12) -> 1069.511 | AF12: =SUM(P12-AE12) -> 121.669
C13: 240928000015 | D13: 45564 | E13: 朱小飞 | F13: Isabel Zhu | G13: Halifa Success | H13: 0.1359 | I13: 19.5 | J13: 309.58 | P13: =SUBTOTAL(9,J13) -> 309.58 | S13: =SUM(40914/68)*H13 -> 81.767832 | U13: =SUM(1000/68)*H13 -> 1.9985294 | X13: =SUM(S13:W13) -> 83.766362 | Y13: =SUM(10381.24/68)*H13 -> 20.747213 | AA13: =SUM(114.28/68)*H13 -> 0.22839194 | AB13: =SUM(Y13:AA13) -> 20.975605 | AC13: 7.27 | AD13: =SUM(AB13*AC13) -> 152.49265 | AE13: =SUM(X13+AD13) -> 236.25901 | AF13: =SUM(P13-AE13) -> 73.320987
C14: 240929000070 | D14: 45564 | E14: Sam.Pao | F14: Sam.Pao | G14: SKY JET | H14: 14.91 | I14: 1595 | J14: 21865.81 | P14: =SUBTOTAL(9,J14) -> 21865.81 | S14: =SUM(40914/68)*H14 -> 8970.9962 | U14: =SUM(1000/68)*H14 -> 219.26471 | X14: =SUM(S14:W14) -> 9190.2609 | Y14: =SUM(10381.24/68)*H14 -> 2276.2395 | AA14: =SUM(114.28/68)*H14 -> 25.057571 | AB14: =SUM(Y14:AA14) -> 2301.2971 | AC14: 7.27 | AD14: =SUM(AB14*AC14) -> 16730.43 | AE14: =SUM(X14+AD14) -> 25920.691 | AF14: =SUM(P14-AE14) -> -4054.8808
C15: 240928000023 | D15: 45564 | E15: Sam.Pao | F15: Sam.Pao | G15: SKY JET | H15: 0.8638 | I15: 110 | J15: 1266.8 | P15: =SUBTOTAL(9,J15) -> 1266.8 | S15: =SUM(40914/68)*H15 -> 519.72814 | U15: =SUM(1000/68)*H15 -> 12.702941 | X15: =SUM(S15:W15) -> 532.43108 | Y15: =SUM(10381.24/68)*H15 -> 131.87228 | AA15: =SUM(114.28/68)*H15 -> 1.4516921 | AB15: =SUM(Y15:AA15) -> 133.32397 | AC15: 7.27 | AD15: =SUM(AB15*AC15) -> 969.26528 | AE15: =SUM(X15+AD15) -> 1501.6964 | AF15: =SUM(P15-AE15) -> -234.89636
C16: 240929000001 | D16: 45564 | E16: Sam.Pao | F16: Sam.Pao | G16: SKY JET | H16: 23.97 | I16: 2873 | J16: 35152.53 | P16: =SUBTOTAL(9,J16) -> 35152.53 | S16: =SUM(40914/68)*H16 -> 14422.185 | U16: =SUM(1000/68)*H16 -> 352.5 | X16: =SUM(S16:W16) -> 14774.685 | Y16: =SUM(10381.24/68)*H16 -> 3659.3871 | AA16: =SUM(114.28/68)*H16 -> 40.2837 | AB16: =SUM(Y16:AA16) -> 3699.6708 | AC16: 7.27 | AD16: =SUM(AB16*AC16) -> 26896.607 | AE16: =SUM(X16+AD16) -> 41671.292 | AF16: =SUM(P16-AE16) -> -6518.7617
C17: 240929000009 | D17: 45564 | E17: 朱小飞 | F17: Isabel Zhu | G17: Joy | H17: 6.006 | I17: 2236 | K17: 3392789.4 | M17: =SUM(K17/N17) -> 1883 | N17: 1801.8 | O17: 7.26 | P17: =SUM(N17*O17) -> 13081.068 | S17: =SUM(40914/68)*H17 -> 3613.6689 | U17: =SUM(1000/68)*H17 -> 88.323529 | X17: =SUM(S17:W17) -> 3701.9924 | Y17: =SUM(10381.24/68)*H17 -> 916.90776 | Z17: 72.87 | AA17: =SUM(114.28/68)*H17 -> 10.093613 | AB17: =SUM(Y17:AA17) -> 999.87137 | AC17: 7.27 | AD17: =SUM(AB17*AC17) -> 7269.0649 | AE17: =SUM(X17+AD17) -> 10971.057 | AF17: =SUM(P17-AE17) -> 2110.0107
C18: 240929000042 | D18: 45564 | E18: 罗珮文 | F18: Shirley | G18: Yusky | H18: 0.3433 | I18: 125 | J18: 643.9 | P18: =SUBTOTAL(9,J18) -> 643.9 | S18: =SUM(40914/68)*H18 -> 206.55553 | U18: =SUM(1000/68)*H18 -> 5.0485294 | X18: =SUM(S18:W18) -> 211.60406 | Y18: =SUM(10381.24/68)*H18 -> 52.409995 | AA18: =SUM(114.28/68)*H18 -> 0.57694594 | AB18: =SUM(Y18:AA18) -> 52.986941 | AC18: 7.27 | AD18: =SUM(AB18*AC18) -> 385.21506 | AE18: =SUM(X18+AD18) -> 596.81913 | AF18: =SUM(P18-AE18) -> 47.080874
C19: 240921000019 | D19: 45547 | E19: 陆总 | F19: 陆梓龙 | G19: xiantian | H19: 2.7091 | I19: 1182 | J19: 5539.61 | P19: =SUBTOTAL(9,J19) -> 5539.61 | S19: =SUM(40914/68)*H19 -> 1630.0017 | U19: =SUM(1000/68)*H19 -> 39.839706 | X19: =SUM(S19:W19) -> 1669.8414 | Y19: =SUM(10381.24/68)*H19 -> 413.58555 | AA19: =SUM(114.28/68)*H19 -> 4.5528816 | AB19: =SUM(Y19:AA19) -> 418.13843 | AC19: 7.27 | AD19: =SUM(AB19*AC19) -> 3039.8664 | AE19: =SUM(X19+AD19) -> 4709.7078 | AF19: =SUM(P19-AE19) -> 829.90218
C20: 240929000044 | D20: 45564 | E20: 罗珮文 | F20: Shirley | G20: Yusky | H20: 0.701 | I20: 79 | J20: 1314.85 | P20: =SUBTOTAL(9,J20) -> 1314.85 | S20: =SUM(40914/68)*H20 -> 421.77521 | U20: =SUM(1000/68)*H20 -> 10.308824 | X20: =SUM(S20:W20) -> 432.08403 | Y20: =SUM(10381.24/68)*H20 -> 107.01837 | AA20: =SUM(114.28/68)*H20 -> 1.1780924 | AB20: =SUM(Y20:AA20) -> 108.19646 | AC20: 7.27 | AD20: =SUM(AB20*AC20) -> 786.58829 | AE20: =SUM(X20+AD20) -> 1218.6723 | AF20: =SUM(P20-AE20) -> 96.177681
C21: 240929000045 | D21: 45564 | E21: 罗珮文 | F21: Shirley | G21: Yusky | H21: 0.2958 | I21: 34 | J21: 554.85 | P21: =SUBTOTAL(9,J21) -> 554.85 | S21: =SUM(40914/68)*H21 -> 177.9759 | U21: =SUM(1000/68)*H21 -> 4.35 | X21: =SUM(S21:W21) -> 182.3259 | Y21: =SUM(10381.24/68)*H21 -> 45.158394 | AA21: =SUM(114.28/68)*H21 -> 0.497118 | AB21: =SUM(Y21:AA21) -> 45.655512 | AC21: 7.27 | AD21: =SUM(AB21*AC21) -> 331.91557 | AE21: =SUM(X21+AD21) -> 514.24147 | AF21: =SUM(P21-AE21) -> 40.608528
C22: 240929000053 | D22: 45564 | E22: 陆总 | F22: 陆梓龙 | G22: jizong | H22: 2.4883 | I22: 449.5 | J22: 5086.06 | P22: =SUBTOTAL(9,J22) -> 5086.06 | S22: =SUM(40914/68)*H22 -> 1497.1516 | U22: =SUM(1000/68)*H22 -> 36.592647 | X22: =SUM(S22:W22) -> 1533.7442 | Y22: =SUM(10381.24/68)*H22 -> 379.87705 | AA22: =SUM(114.28/68)*H22 -> 4.1818077 | AB22: =SUM(Y22:AA22) -> 384.05886 | AC22: 7.27 | AD22: =SUM(AB22*AC22) -> 2792.1079 | AE22: =SUM(X22+AD22) -> 4325.8521 | AF22: =SUM(P22-AE22) -> 760.20789
A23: 合计 | J23: =SUM(J4:J4) -> 0 | N23: =SUM(N4:N4) -> 0 | P23: =SUM(P4:P4) -> 0 | Q23: =SUM(Q4:Q4) -> 0 | X23: =SUM(X4:X4) -> 0 | AD23: =SUM(AD4:AD4) -> 0 | AF23: =SUM(AF4:AF22) -> -2488.9901

Sheet JOB100362
A1: 2024年10月份LOS毛利表（海运）
A2: PSL表 | B2: 体积cbm | C2: 70.028
A3: JOB | B3: 集装编号 | C3: 运单编号 | D3: 日期 | E3: 业务 | F3: 发货人 | G3: 收货人 | H3: 计费体积 | I3: 计费重量 | J3: 应 收 | Q3: 总应收 | R3: 起 运 港 成 本 | W3: 代垫运费 | X3: 起运港成本 合计 | Y3: 目的港成本 | AE3: 总支出 | AF3: 利润
J4: 应收RMB | K4: LOS Income(NGN)收到(奈拉) | L4: LOS 收到USD | M4: 美元汇率 dollar currency rate | N4: 应收 到付款USD | O4: 汇率 | P4: 人民币 | R4: 代理商 | S4: 运费+出口报关费 | T4: 提货费 | U4: 装卸费 | V4: 包装费 | Y4: 进口报关费 | Z4: 到门配送费 | AA4: 转运费 | AB4: 目的港支出 | AC4: 汇率 | AD4: 人民币 | AE4: 起运港+目的港
A5: JOB100362 | B5: COLL004260 | C5: 240926000039 | D5: 45583 | E5: Sam.Pao | F5: Sam.Pao | G5: ShanShan | H5: 0.3 | I5: 65 | J5: 772 | P5: =SUBTOTAL(9,J5) -> 772 | Q5: =SUM(P5:P25) -> 135484.86 | R5: 登凯=38748 赛捷=1160 拖车费=1670 杂费=61 过磅费=67 | S5: =SUM(41706/68)*H5 -> 183.99706 | T5: =SUM(99.72/68)*H5 -> 0.43994118 | U5: =SUM(1500/68)*H5 -> 6.6176471 | X5: =SUM(S5:W5) -> 191.05465 | Y5: =SUM(10523.89/68)*H5 -> 46.428926 | Z5: 14.39 | AB5: =SUM(Y5:AA5) -> 60.818926 | AC5: 7.28 | AD5: =SUM(AB5*AC5) -> 442.76178 | AE5: =SUM(X5+AD5) -> 633.81643 | AF5: =SUM(P5-AE5) -> 138.18357
C6: 240926000032 | D6: 45580 | E6: 黄颖 | F6: ying | G6: Sunday Adelena | H6: 7.5159 | I6: 6108 | J6: 15370 | P6: =SUBTOTAL(9,J6) -> 15370 | S6: =SUM(41706/68)*H6 -> 4609.6783 | T6: =SUM(99.72/68)*H6 -> 11.021846 | U6: =SUM(1500/68)*H6 -> 165.79191 | X6: =SUM(S6:W6) -> 4786.4921 | Y6: =SUM(10523.89/68)*H6 -> 1163.1839 | AB6: =SUM(Y6:AA6) -> 1163.1839 | AC6: 7.28 | AD6: =SUM(AB6*AC6) -> 8467.9788 | AE6: =SUM(X6+AD6) -> 13254.471 | AF6: =SUM(P6-AE6) -> 2115.5292
C7: 241008000045 | D7: 45580 | E7: 黄颖 | F7: ying | G7: Wuchengxing | H7: 1.3298 | I7: 142 | J7: 2841 | P7: =SUBTOTAL(9,J7) -> 2841 | S7: =SUM(41706/68)*H7 -> 815.59763 | T7: =SUM(99.72/68)*H7 -> 1.9501126 | U7: =SUM(1500/68)*H7 -> 29.333824 | X7: =SUM(S7:W7) -> 846.88157 | Y7: =SUM(10523.89/68)*H7 -> 205.80395 | AB7: =SUM(Y7:AA7) -> 205.80395 | AC7: 7.28 | AD7: =SUM(AB7*AC7) -> 1498.2528 | AE7: =SUM(X7+AD7) -> 2345.1344 | AF7: =SUM(P7-AE7) -> 495.86564
C8: 240927000028 | D8: 45583 | E8: 吕沛霖 | F8: 喵喵速运-Layne | G8: MA ZONG | H8: 1.7904 | I8: 1841 | J8: 5660.38 | P8: =SUBTOTAL(9,J8) -> 5660.38 | S8: =SUM(41706/68)*H8 -> 1098.0944 | T8: =SUM(99.72/68)*H8 -> 2.6255689 | U8: =SUM(1500/68)*H8 -> 39.494118 | V8: 450 | X8: =SUM(S8:W8) -> 1590.2141 | Y8: =SUM(10523.89/68)*H8 -> 277.08783 | Z8: 68 | AB8: =SUM(Y8:AA8) -> 345.08783 | AC8: 7.28 | AD8: =SUM(AB8*AC8) -> 2512.2394 | AE8: =SUM(X8+AD8) -> 4102.4536 | AF8: =SUM(P8-AE8) -> 1557.9264
C9: 241008000110 | D9: 45583 | E9: Sam.Pao | F9: Sam.Pao | G9: MaiKaiNian | H9: 0.1724 | I9: 432 | J9: 1396.56 | P9: =SUBTOTAL(9,J9) -> 1396.56 | S9: =SUM(41706/68)*H9 -> 105.73698 | T9: =SUM(99.72/68)*H9 -> 0.25281953 | U9: =SUM(1500/68)*H9 -> 3.8029412 | X9: =SUM(S9:W9) -> 109.79274 | Y9: =SUM(10523.89/68)*H9 -> 26.681156 | AB9: =SUM(Y9:AA9) -> 26.681156 | AC9: 7.28 | AD9: =SUM(AB9*AC9) -> 194.23882 | AE9: =SUM(X9+AD9) -> 304.03156 | AF9: =SUM(P9-AE9) -> 1092.5284
C10: 241005000007 | D10: 45580 | E10: 黄颖 | F10: ying | G10: MISS Huang | H10: 1.7287 | I10: 674.73 | K10: 797943.5 | M10: =SUM(K10/N10) -> 1679.174 | N10: 475.2 | O10: 7.27 | P10: =SUM(N10*O10) -> 3454.704 | S10: =SUM(41706/68)*H10 -> 1060.2524 | T10: =SUM(99.72/68)*H10 -> 2.5350877 | U10: =SUM(1500/68)*H10 -> 38.133088 | X10: =SUM(S10:W10) -> 1100.9206 | Y10: =SUM(10523.89/68)*H10 -> 267.53895 | AB10: =SUM(Y10:AA10) -> 267.53895 | AC10: 7.28 | AD10: =SUM(AB10*AC10) -> 1947.6836 | AE10: =SUM(X10+AD10) -> 3048.6041 | AF10: =SUM(P10-AE10) -> 406.09988
C11: 241009000019 | D11: 45583 | E11: 黄颖 | F11: ying | G11: Wole Rasak | H11: 0.7338 | I11: 73 | J11: 1502.2 | P11: =SUBTOTAL(9,J11) -> 1502.2 | S11: =SUM(41706/68)*H11 -> 450.05681 | T11: =SUM(99.72/68)*H11 -> 1.0760961 | U11: =SUM(1500/68)*H11 -> 16.186765 | X11: =SUM(S11:W11) -> 467.31967 | Y11: =SUM(10523.89/68)*H11 -> 113.56515 | Z11: 3.45 | AB11: =SUM(Y11:AA11) -> 117.01515 | AC11: 7.28 | AD11: =SUM(AB11*AC11) -> 851.87032 | AE11: =SUM(X11+AD11) -> 1319.19 | AF11: =SUM(P11-AE11) -> 183.01001
C12: 241009000033 | D12: 45583 | E12: 陆总 | F12: 陆梓龙 | G12: leoluang | H12: 5.69 | I12: 3984 | J12: 9968.88 | P12: =SUBTOTAL(9,J12) -> 9968.88 | S12: =SUM(41706/68)*H12 -> 3489.8109 | T12: =SUM(99.72/68)*H12 -> 8.3442176 | U12: =SUM(1500/68)*H12 -> 125.51471 | X12: =SUM(S12:W12) -> 3623.6698 | Y12: =SUM(10523.89/68)*H12 -> 880.60197 | AB12: =SUM(Y12:AA12) -> 880.60197 | AC12: 7.28 | AD12: =SUM(AB12*AC12) -> 6410.7824 | AE12: =SUM(X12+AD12) -> 10034.452 | AF12: =SUM(P12-AE12) -> -65.572162
C13: 241010000022 | D13: 45583 | E13: Bella | F13: Bella Chan | G13: zhong zi xin | H13: 5.5556 | I13: 5276 | J13: 16400 | P13: =SUBTOTAL(9,J13) -> 16400 | S13: =SUM(41706/68)*H13 -> 3407.3802 | T13: =SUM(99.72/68)*H13 -> 8.147124 | U13: =SUM(1500/68)*H13 -> 122.55 | X13: =SUM(S13:W13) -> 3538.0773 | Y13: =SUM(10523.89/68)*H13 -> 859.80181 | Z13: 138.17 | AB13: =SUM(Y13:AA13) -> 997.97181 | AC13: 7.28 | AD13: =SUM(AB13*AC13) -> 7265.2348 | AE13: =SUM(X13+AD13) -> 10803.312 | AF13: =SUM(P13-AE13) -> 5596.6879
C14: 241012000025 | D14: 45583 | E14: 吕沛霖 | F14: 喵喵速运-Layne | G14: Sue | H14: 0.9445 | I14: 434 | K14: 559350 | M14: =SUM(K14/N14) -> 1650 | N14: 339 | O14: 7.29 | P14: =SUM(N14*O14) -> 2471.31 | S14: =SUM(41706/68)*H14 -> 579.28407 | T14: =SUM(99.72/68)*H14 -> 1.3850815 | U14: =SUM(1500/68)*H14 -> 20.834559 | X14: =SUM(S14:W14) -> 601.50371 | Y14: =SUM(10523.89/68)*H14 -> 146.17374 | AB14: =SUM(Y14:AA14) -> 146.17374 | AC14: 7.28 | AD14: =SUM(AB14*AC14) -> 1064.1448 | AE14: =SUM(X14+AD14) -> 1665.6485 | AF14: =SUM(P14-AE14) -> 805.66148
C15: 241012000031 | D15: 45583 | E15: 黄颖 | F15: ying | G15: liufang | H15: 2.0788 | I15: 174 | K15: 1322400 | M15: =SUM(K15/N15) -> 1675.812 | N15: 789.11 | O15: 7.29 | P15: =SUM(N15*O15) -> 5752.6119 | S15: =SUM(41706/68)*H15 -> 1274.977 | T15: =SUM(99.72/68)*H15 -> 3.0484991 | U15: =SUM(1500/68)*H15 -> 45.855882 | V15: 240 | X15: =SUM(S15:W15) -> 1563.8813 | Y15: =SUM(10523.89/68)*H15 -> 321.72151 | AB15: =SUM(Y15:AA15) -> 321.72151 | AC15: 7.28 | AD15: =SUM(AB15*AC15) -> 2342.1326 | AE15: =SUM(X15+AD15) -> 3906.0139 | AF15: =SUM(P15-AE15) -> 1846.598
C16: 241014000064 | D16: 45583 | E16: 苏慧琪 | F16: KAY | G16: WENXIAOBING | H16: 0.1024 | I16: 35 | K16: 71551 | M16: =SUM(K16/N16) -> 1690.3142 | N16: 42.33 | O16: 7.27 | P16: =SUM(N16*O16) -> 307.7391 | S16: =SUM(41706/68)*H16 -> 62.804329 | T16: =SUM(99.72/68)*H16 -> 0.15016659 | U16: =SUM(1500/68)*H16 -> 2.2588235 | X16: =SUM(S16:W16) -> 65.21332 | Y16: =SUM(10523.89/68)*H16 -> 15.84774 | AB16: =SUM(Y16:AA16) -> 15.84774 | AC16: 7.28 | AD16: =SUM(AB16*AC16) -> 115.37155 | AE16: =SUM(X16+AD16) -> 180.58487 | AF16: =SUM(P16-AE16) -> 127.15423
C17: 241015000036 | D17: 45583 | E17: 罗珮文 | F17: Shirley | G17: Yusky | H17: 1.1644 | I17: 178 | K17: 480476 | M17: =SUM(K17/N17) -> 1630.999 | N17: 294.59 | O17: 7.35 | P17: =SUM(N17*O17) -> 2165.2365 | S17: =SUM(41706/68)*H17 -> 714.15392 | T17: =SUM(99.72/68)*H17 -> 1.7075584 | U17: =SUM(1500/68)*H17 -> 25.685294 | X17: =SUM(S17:W17) -> 741.54677 | Y17: =SUM(10523.89/68)*H17 -> 180.20614 | AB17: =SUM(Y17:AA17) -> 180.20614 | AC17: 7.28 | AD17: =SUM(AB17*AC17) -> 1311.9007 | AE17: =SUM(X17+AD17) -> 2053.4475 | AF17: =SUM(P17-AE17) -> 111.78903
C18: 241015000037 | D18: 45583 | E18: 罗珮文 | F18: Shirley | G18: Yusky | H18: 1.8977 | I18: 816 | K18: 783075 | M18: =SUM(K18/N18) -> 1630.9985 | N18: 480.12 | O18: 7.35 | P18: =SUM(N18*O18) -> 3528.882 | S18: =SUM(41706/68)*H18 -> 1163.9041 | T18: =SUM(99.72/68)*H18 -> 2.7829212 | U18: =SUM(1500/68)*H18 -> 41.861029 | X18: =SUM(S18:W18) -> 1208.548 | Y18: =SUM(10523.89/68)*H18 -> 293.69391 | AB18: =SUM(Y18:AA18) -> 293.69391 | AC18: 7.28 | AD18: =SUM(AB18*AC18) -> 2138.0917 | AE18: =SUM(X18+AD18) -> 3346.6397 | AF18: =SUM(P18-AE18) -> 182.2423
C19: 241015000040 | D19: 45583 | E19: 罗珮文 | F19: Shirley | G19: Yusky | H19: 1.7374 | I19: 1047 | K19: 716971 | M19: =SUM(K19/N19) -> 1630.9993 | N19: 439.59 | O19: 7.35 | P19: =SUM(N19*O19) -> 3230.9865 | S19: =SUM(41706/68)*H19 -> 1065.5883 | T19: =SUM(99.72/68)*H19 -> 2.547846 | U19: =SUM(1500/68)*H19 -> 38.325 | X19: =SUM(S19:W19) -> 1106.4611 | Y19: =SUM(10523.89/68)*H19 -> 268.88539 | AB19: =SUM(Y19:AA19) -> 268.88539 | AC19: 7.28 | AD19: =SUM(AB19*AC19) -> 1957.4856 | AE19: =SUM(X19+AD19) -> 3063.9468 | AF19: =SUM(P19-AE19) -> 167.03972
C20: 241015000046 | D20: 45583 | E20: Bella | F20: Bella Chan | G20: Shuaibu musa | H20: 0.5175 | I20: 333 | J20: 1773.41 | P20: =SUBTOTAL(9,J20) -> 1773.41 | S20: =SUM(41706/68)*H20 -> 317.39493 | T20: =SUM(99.72/68)*H20 -> 0.75889853 | U20: =SUM(1500/68)*H20 -> 11.415441 | X20: =SUM(S20:W20) -> 329.56927 | Y20: =SUM(10523.89/68)*H20 -> 80.089898 | AB20: =SUM(Y20:AA20) -> 80.089898 | AC20: 7.28 | AD20: =SUM(AB20*AC20) -> 583.05446 | AE20: =SUM(X20+AD20) -> 912.62372 | AF20: =SUM(P20-AE20) -> 860.78628
C21: 241016000013 | D21: 45583 | E21: 朱小飞 | F21: Isabel Zhu | G21: Lin Bao Zhen | H21: 0.4631 | I21: 128 | K21: 239700 | M21: =SUM(K21/N21) -> 1725.3293 | N21: 138.93 | O21: 7.26 | P21: =SUM(N21*O21) -> 1008.6318 | S21: =SUM(41706/68)*H21 -> 284.03013 | T21: =SUM(99.72/68)*H21 -> 0.67912253 | U21: =SUM(1500/68)*H21 -> 10.215441 | X21: =SUM(S21:W21) -> 294.92469 | Y21: =SUM(10523.89/68)*H21 -> 71.670786 | AB21: =SUM(Y21:AA21) -> 71.670786 | AC21: 7.28 | AD21: =SUM(AB21*AC21) -> 521.76332 | AE21: =SUM(X21+AD21) -> 816.68801 | AF21: =SUM(P21-AE21) -> 191.94379
C22: 241017000017 | D22: 45583 | E22: 朱小飞 | F22: Isabel Zhu | G22: Ife Oyelami | H22: 0.2251 | I22: 53 | K22: 130000 | M22: =SUM(K22/N22) -> 1862.9977 | N22: 69.78001 | O22: 7.27 | P22: =SUM(N22*O22) -> 507.30067 | S22: =SUM(41706/68)*H22 -> 138.05913 | T22: =SUM(99.72/68)*H22 -> 0.33010253 | U22: =SUM(1500/68)*H22 -> 4.9654412 | X22: =SUM(S22:W22) -> 143.35467 | Y22: =SUM(10523.89/68)*H22 -> 34.837171 | AB22: =SUM(Y22:AA22) -> 34.837171 | AC22: 7.28 | AD22: =SUM(AB22*AC22) -> 253.61461 | AE22: =SUM(X22+AD22) -> 396.96928 | AF22: =SUM(P22-AE22) -> 110.3314
C23: 241017000030 | D23: 45583 | E23: 朱小飞 | F23: Isabel Zhu | G23: Halifa Success | H23: 5.595 | I23: 600 | J23: 11415.02 | P23: =SUBTOTAL(9,J23) -> 11415.02 | S23: =SUM(41706/68)*H23 -> 3431.5451 | T23: =SUM(99.72/68)*H23 -> 8.2049029 | U23: =SUM(1500/68)*H23 -> 123.41912 | X23: =SUM(S23:W23) -> 3563.1692 | Y23: =SUM(10523.89/68)*H23 -> 865.89948 | AB23: =SUM(Y23:AA23) -> 865.89948 | AC23: 7.28 | AD23: =SUM(AB23*AC23) -> 6303.7482 | AE23: =SUM(X23+AD23) -> 9866.9174 | AF23: =SUM(P23-AE23) -> 1548.1026
C24: 241017000044 | D24: 45583 | E24: 朱小飞 | F24: Isabel Zhu | G24: Halifa Success | H24: 1.3776 | I24: 251 | J24: 2812.99 | P24: =SUBTOTAL(9,J24) -> 2812.99 | S24: =SUM(41706/68)*H24 -> 844.91449 | T24: =SUM(99.72/68)*H24 -> 2.0202099 | U24: =SUM(1500/68)*H24 -> 30.388235 | X24: =SUM(S24:W24) -> 877.32294 | Y24: =SUM(10523.89/68)*H24 -> 213.20163 | AB24: =SUM(Y24:AA24) -> 213.20163 | AC24: 7.28 | AD24: =SUM(AB24*AC24) -> 1552.1079 | AE24: =SUM(X24+AD24) -> 2429.4308 | AF24: =SUM(P24-AE24) -> 383.55919
C25: 241017000060 | D25: 45583 | E25: 罗珮文 | F25: Shirley | G25: SKY JET | H25: 29.42 | I25: 3712 | J25: 43145.02 | P25: =SUBTOTAL(9,J25) -> 43145.02 | S25: =SUM(41706/68)*H25 -> 18043.978 | T25: =SUM(99.72/68)*H25 -> 43.143565 | U25: =SUM(1500/68)*H25 -> 648.97059 | X25: =SUM(S25:W25) -> 18736.092 | Y25: =SUM(10523.89/68)*H25 -> 4553.1301 | AB25: =SUM(Y25:AA25) -> 4553.1301 | AC25: 7.28 | AD25: =SUM(AB25*AC25) -> 33146.787 | AE25: =SUM(X25+AD25) -> 51882.879 | AF25: =SUM(P25-AE25) -> -8737.8592
A26: 合计 | J26: =SUM(J4:J4) -> 0 | N26: =SUM(N4:N4) -> 0 | P26: =SUM(P4:P4) -> 0 | Q26: =SUM(Q4:Q4) -> 0 | X26: =SUM(X4:X4) -> 0 | AD26: =SUM(AD4:AD4) -> 0 | AF26: =SUM(AF4:AF25) -> 9117.6077

Sheet JOB100331
A1: 2024年10月份LOS毛利表（海运）
A2: PSL表 | B2: 体积cbm | C2: 70.1066
A3: JOB | B3: 集装编号 | C3: 运单编号 | D3: 日期 | E3: 业务 | F3: 发货人 | G3: 收货人 | H3: 计费体积 | I3: 计费重量 | J3: 应 收 | Q3: 总应收 | R3: 起 运 港 成 本 | W3: 代垫运费 | X3: 起运港成本 合计 | Y3: 目的港成本 | AE3: 总支出 | AF3: 利润
J4: 应收RMB | K4: LOS Income(NGN)收到(奈拉) | L4: LOS 收到USD | M4: 美元汇率 dollar currency rate | N4: 应收 到付款USD | O4: 汇率 | P4: 人民币 | R4: 代理商 | S4: 运费+出口报关费 | T4: 提货费 | U4: 装卸费 | V4: 包装费 | Y4: 进口报关费 | Z4: 到门配送费 | AA4: 转运费 | AB4: 目的港支出 | AC4: 汇率 | AD4: 人民币 | AE4: 起运港+目的港
A5: JOB100331 | B5: COLL004195 | C5: 240919000043 | D5: 45580 | E5: 黄颖 | F5: ying | G5: Mr wang | H5: 0.0017 | I5: 5.5 | J5: 4 | P5: =SUBTOTAL(9,J5) -> 4 | Q5: =SUM(P5:P30) -> 140734.06 | R5: 登凯=37296 赛捷=2800 拖车费=1670 杂费=61 过磅费=68 | S5: =SUM(40096/68)*H5 -> 1.0024 | U5: =SUM(2100/68)*H5 -> 0.0525 | X5: =SUM(S5:W5) -> 1.0549 | Y5: =SUM(10477.84/68)*H5 -> 0.261946 | AA5: =SUM(222.57/68)*H5 -> 0.00556425 | AB5: =SUM(Y5:AA5) -> 0.26751025 | AC5: 7.27 | AD5: =SUM(AB5*AC5) -> 1.9447995 | AE5: =SUM(X5+AD5) -> 2.9996995 | AF5: =SUM(P5-AE5) -> 1.0003005
C6: 240926000032 | D6: 45580 | E6: 黄颖 | F6: ying | G6: Sunday Adelena | H6: 17.4746 | I6: 13114 | J6: 35735 | P6: =SUBTOTAL(9,J6) -> 35735 | S6: =SUM(40096/68)*H6 -> 10303.846 | U6: =SUM(2100/68)*H6 -> 539.65676 | X6: =SUM(S6:W6) -> 10843.503 | Y6: =SUM(10477.84/68)*H6 -> 2692.5892 | AA6: =SUM(222.57/68)*H6 -> 57.195908 | AB6: =SUM(Y6:AA6) -> 2749.7851 | AC6: 7.27 | AD6: =SUM(AB6*AC6) -> 19990.937 | AE6: =SUM(X6+AD6) -> 30834.441 | AF6: =SUM(P6-AE6) -> 4900.5593
C7: 240926000037 | D7: 45580 | E7: 黄颖 | F7: ying | G7: lihongye | H7: 0.1237 | I7: 33 | J7: 344 | P7: =SUBTOTAL(9,J7) -> 344 | S7: =SUM(40096/68)*H7 -> 72.939341 | U7: =SUM(2100/68)*H7 -> 3.8201471 | X7: =SUM(S7:W7) -> 76.759488 | Y7: =SUM(10477.84/68)*H7 -> 19.060424 | AA7: =SUM(222.57/68)*H7 -> 0.40488101 | AB7: =SUM(Y7:AA7) -> 19.465305 | AC7: 7.27 | AD7: =SUM(AB7*AC7) -> 141.51276 | AE7: =SUM(X7+AD7) -> 218.27225 | AF7: =SUM(P7-AE7) -> 125.72775
C8: 240929000070 | D8: 45580 | E8: Sam.Pao | F8: Sam.Pao | G8: SKY JET | H8: 4.8 | I8: 799 | J8: 7039.3 | P8: =SUBTOTAL(9,J8) -> 7039.3 | S8: =SUM(40096/68)*H8 -> 2830.3059 | U8: =SUM(2100/68)*H8 -> 148.23529 | X8: =SUM(S8:W8) -> 2978.5412 | Y8: =SUM(10477.84/68)*H8 -> 739.61224 | AA8: =SUM(222.57/68)*H8 -> 15.710824 | AB8: =SUM(Y8:AA8) -> 755.32306 | AC8: 7.27 | AD8: =SUM(AB8*AC8) -> 5491.1986 | AE8: =SUM(X8+AD8) -> 8469.7398 | AF8: =SUM(P8-AE8) -> -1430.4398
C9: 240930000017 | D9: 45580 | E9: 黄颖 | F9: ying | G9: jiangnan | H9: 1.6158 | I9: 511 | J9: 3453.03 | P9: =SUBTOTAL(9,J9) -> 3453.03 | S9: =SUM(40096/68)*H9 -> 952.75172 | U9: =SUM(2100/68)*H9 -> 49.899706 | X9: =SUM(S9:W9) -> 1002.6514 | Y9: =SUM(10477.84/68)*H9 -> 248.97197 | AA9: =SUM(222.57/68)*H9 -> 5.288656 | AB9: =SUM(Y9:AA9) -> 254.26062 | AC9: 7.27 | AD9: =SUM(AB9*AC9) -> 1848.4747 | AE9: =SUM(X9+AD9) -> 2851.1262 | AF9: =SUM(P9-AE9) -> 601.90384
C10: 241005000004 | D10: 45580 | E10: 朱小飞 | F10: Isabel Zhu | G10: Joy | H10: 0.5915 | I10: 456 | K10: 359040 | M10: =SUM(K10/N10) -> 1700 | N10: 211.2 | O10: 7.29 | P10: =SUM(N10*O10) -> 1539.648 | S10: =SUM(40096/68)*H10 -> 348.77624 | U10: =SUM(2100/68)*H10 -> 18.266912 | X10: =SUM(S10:W10) -> 367.04315 | Y10: =SUM(10477.84/68)*H10 -> 91.141799 | Z10: 11.56 | AA10: =SUM(222.57/68)*H10 -> 1.9360317 | AB10: =SUM(Y10:AA10) -> 104.63783 | AC10: 7.27 | AD10: =SUM(AB10*AC10) -> 760.71703 | AE10: =SUM(X10+AD10) -> 1127.7602 | AF10: =SUM(P10-AE10) -> 411.88782
C11: 241006000007 | D11: 45580 | E11: 黄颖 | F11: ying | G11: MISS Huang | H11: 0.0493 | I11: 24 | K11: 42685.5 | M11: =SUM(K11/N11) -> 1576.8563 | N11: 27.07 | O11: 7.27 | P11: =SUM(N11*O11) -> 196.7989 | S11: =SUM(40096/68)*H11 -> 29.0696 | U11: =SUM(2100/68)*H11 -> 1.5225 | X11: =SUM(S11:W11) -> 30.5921 | Y11: =SUM(10477.84/68)*H11 -> 7.596434 | AA11: =SUM(222.57/68)*H11 -> 0.16136325 | AB11: =SUM(Y11:AA11) -> 7.7577973 | AC11: 7.27 | AD11: =SUM(AB11*AC11) -> 56.399186 | AE11: =SUM(X11+AD11) -> 86.991286 | AF11: =SUM(P11-AE11) -> 109.80761
C12: 241007000009 | D12: 45580 | E12: 朱小飞 | F12: Isabel Zhu | G12: Joy | H12: 0.0252 | I12: 13 | K12: 54400 | M12: =SUM(K12/N12) -> 1700 | N12: 32 | O12: 7.29 | P12: =SUM(N12*O12) -> 233.28 | S12: =SUM(40096/68)*H12 -> 14.859106 | U12: =SUM(2100/68)*H12 -> 0.77823529 | X12: =SUM(S12:W12) -> 15.637341 | Y12: =SUM(10477.84/68)*H12 -> 3.8829642 | AA12: =SUM(222.57/68)*H12 -> 0.082481824 | AB12: =SUM(Y12:AA12) -> 3.9654461 | AC12: 7.27 | AD12: =SUM(AB12*AC12) -> 28.828793 | AE12: =SUM(X12+AD12) -> 44.466134 | AF12: =SUM(P12-AE12) -> 188.81387
C13: 241008000098 | D13: 45580 | E13: Bella | F13: Bella Chan | G13: zhang long ting | H13: 0.0392 | I13: 27 | J13: 88.47 | P13: =SUBTOTAL(9,J13) -> 88.47 | S13: =SUM(40096/68)*H13 -> 23.114165 | U13: =SUM(2100/68)*H13 -> 1.2105882 | X13: =SUM(S13:W13) -> 24.324753 | Y13: =SUM(10477.84/68)*H13 -> 6.0401666 | AA13: =SUM(222.57/68)*H13 -> 0.12830506 | AB13: =SUM(Y13:AA13) -> 6.1684716 | AC13: 7.27 | AD13: =SUM(AB13*AC13) -> 44.844789 | AE13: =SUM(X13+AD13) -> 69.169542 | AF13: =SUM(P13-AE13) -> 19.300458
C14: 241009000020 | D14: 45580 | E14: 罗珮文 | F14: Shirley | G14: Yusky | H14: 19.5527 | I14: 2326 | J14: 4260.86 | K14: 6737482 | M14: =SUM(K14/N14) -> 1544.9999 | N14: 4360.83 | O14: 7.24 | P14: =SUM(N14*O14)+J14 -> 35833.269 | S14: =SUM(40096/68)*H14 -> 11529.192 | U14: =SUM(2100/68)*H14 -> 603.83338 | X14: =SUM(S14:W14) -> 12133.025 | Y14: =SUM(10477.84/68)*H14 -> 3012.795 | AA14: =SUM(222.57/68)*H14 -> 63.997712 | AB14: =SUM(Y14:AA14) -> 3076.7927 | AC14: 7.27 | AD14: =SUM(AB14*AC14) -> 22368.283 | AE14: =SUM(X14+AD14) -> 34501.309 | AF14: =SUM(P14-AE14) -> 1331.9605
C15: 241009000046 | D15: 45580 | E15: 苏慧琪 | F15: KAY | G15: WENXIAOBING | H15: 0.0717 | I15: 25 | K15: 37653 | M15: =SUM(K15/N15) -> 1637.087 | N15: 23 | O15: 7.27 | P15: =SUM(N15*O15) -> 167.21 | S15: =SUM(40096/68)*H15 -> 42.277694 | U15: =SUM(2100/68)*H15 -> 2.2142647 | X15: =SUM(S15:W15) -> 44.491959 | Y15: =SUM(10477.84/68)*H15 -> 11.047958 | AA15: =SUM(222.57/68)*H15 -> 0.23468043 | AB15: =SUM(Y15:AA15) -> 11.282638 | AC15: 7.27 | AD15: =SUM(AB15*AC15) -> 82.02478 | AE15: =SUM(X15+AD15) -> 126.51674 | AF15: =SUM(P15-AE15) -> 40.693262
C16: 241010000043 | D16: 45580 | E16: 朱小飞 | F16: Isabel Zhu | G16: Joy | H16: 1.9259 | I16: 967 | J16: -7012.8 | K16: 2705720 | M16: =SUM(K16/N16) -> 1700 | N16: 1591.6 | O16: 7.29 | P16: =SUM(N16*O16)+J16 -> 4589.964 | S16: =SUM(40096/68)*H16 -> 1135.6013 | U16: =SUM(2100/68)*H16 -> 59.476324 | X16: =SUM(S16:W16) -> 1195.0776 | Y16: =SUM(10477.84/68)*H16 -> 296.754 | Z16: 37.74 | AA16: =SUM(222.57/68)*H16 -> 6.3036406 | AB16: =SUM(Y16:AA16) -> 340.79764 | AC16: 7.27 | AD16: =SUM(AB16*AC16) -> 2477.5989 | AE16: =SUM(X16+AD16) -> 3672.6764 | AF16: =SUM(P16-AE16) -> 917.28755
C17: 241010000044 | D17: 45580 | E17: Sam.Pao | F17: Sam.Pao | G17: Nick Wang | H17: 0.294 | I17: 17 | J17: 919.8 | P17: =SUBTOTAL(9,J17) -> 919.8 | S17: =SUM(40096/68)*H17 -> 173.35624 | U17: =SUM(2100/68)*H17 -> 9.0794118 | X17: =SUM(S17:W17) -> 182.43565 | Y17: =SUM(10477.84/68)*H17 -> 45.301249 | Z17: 73.03 | AA17: =SUM(222.57/68)*H17 -> 0.96228794 | AB17: =SUM(Y17:AA17) -> 119.29354 | AC17: 7.27 | AD17: =SUM(AB17*AC17) -> 867.26402 | AE17: =SUM(X17+AD17) -> 1049.6997 | AF17: =SUM(P17-AE17) -> -129.89966
C18: 241011000029 | D18: 45580 | E18: 罗珮文 | F18: Shirley | G18: Yusky | H18: 1.2962 | I18: 139 | K18: 506590 | M18: =SUM(K18/N18) -> 1544.9998 | N18: 327.89 | O18: 7.24 | P18: =SUM(N18*O18) -> 2373.9236 | S18: =SUM(40096/68)*H18 -> 764.30052 | U18: =SUM(2100/68)*H18 -> 40.029706 | X18: =SUM(S18:W18) -> 804.33022 | Y18: =SUM(10477.84/68)*H18 -> 199.72612 | AA18: =SUM(222.57/68)*H18 -> 4.242577 | AB18: =SUM(Y18:AA18) -> 203.9687 | AC18: 7.27 | AD18: =SUM(AB18*AC18) -> 1482.8524 | AE18: =SUM(X18+AD18) -> 2287.1827 | AF18: =SUM(P18-AE18) -> 86.740944
C19: 241011000030 | D19: 45580 | E19: 罗珮文 | F19: Shirley | G19: Yusky | H19: 0.4329 | I19: 53 | K19: 169208 | M19: =SUM(K19/N19) -> 1544.9963 | N19: 109.52 | O19: 7.24 | P19: =SUM(N19*O19) -> 792.9248 | S19: =SUM(40096/68)*H19 -> 255.25821 | U19: =SUM(2100/68)*H19 -> 13.368971 | X19: =SUM(S19:W19) -> 268.62718 | Y19: =SUM(10477.84/68)*H19 -> 66.703778 | AA19: =SUM(222.57/68)*H19 -> 1.4169199 | AB19: =SUM(Y19:AA19) -> 68.120698 | AC19: 7.27 | AD19: =SUM(AB19*AC19) -> 495.23748 | AE19: =SUM(X19+AD19) -> 763.86466 | AF19: =SUM(P19-AE19) -> 29.060141
C20: 241011000031 | D20: 45580 | E20: 罗珮文 | F20: Shirley | G20: Yusky | H20: 0.539 | I20: 103 | K20: 210691 | M20: =SUM(K20/N20) -> 1544.9952 | N20: 136.37 | O20: 7.24 | P20: =SUM(N20*O20) -> 987.3188 | S20: =SUM(40096/68)*H20 -> 317.81976 | U20: =SUM(2100/68)*H20 -> 16.645588 | X20: =SUM(S20:W20) -> 334.46535 | Y20: =SUM(10477.84/68)*H20 -> 83.052291 | AA20: =SUM(222.57/68)*H20 -> 1.7641946 | AB20: =SUM(Y20:AA20) -> 84.816485 | AC20: 7.27 | AD20: =SUM(AB20*AC20) -> 616.61585 | AE20: =SUM(X20+AD20) -> 951.0812 | AF20: =SUM(P20-AE20) -> 36.2376
C21: 241011000032 | D21: 45580 | E21: 罗珮文 | F21: Shirley | G21: Yusky | H21: 6.1972 | I21: 617 | K21: 2557147 | M21: =SUM(K21/N21) -> 1631 | N21: 1567.84 | O21: 7.35 | P21: =SUM(N21*O21) -> 11523.624 | S21: =SUM(40096/68)*H21 -> 3654.1608 | U21: =SUM(2100/68)*H21 -> 191.38412 | X21: =SUM(S21:W21) -> 3845.5449 | Y21: =SUM(10477.84/68)*H21 -> 954.90103 | AA21: =SUM(222.57/68)*H21 -> 20.283982 | AB21: =SUM(Y21:AA21) -> 975.18501 | AC21: 7.27 | AD21: =SUM(AB21*AC21) -> 7089.595 | AE21: =SUM(X21+AD21) -> 10935.14 | AF21: =SUM(P21-AE21) -> 588.48409
C22: 241011000033 | D22: 45580 | E22: 罗珮文 | F22: Shirley | G22: Yusky | H22: 0.2995 | I22: 33 | K22: 117080 | M22: =SUM(K22/N22) -> 1544.9987 | N22: 75.78 | O22: 7.24 | P22: =SUM(N22*O22) -> 548.6472 | S22: =SUM(40096/68)*H22 -> 176.59929 | U22: =SUM(2100/68)*H22 -> 9.2492647 | X22: =SUM(S22:W22) -> 185.84856 | Y22: =SUM(10477.84/68)*H22 -> 46.148722 | AA22: =SUM(222.57/68)*H22 -> 0.98028993 | AB22: =SUM(Y22:AA22) -> 47.129012 | AC22: 7.27 | AD22: =SUM(AB22*AC22) -> 342.62791 | AE22: =SUM(X22+AD22) -> 528.47647 | AF22: =SUM(P22-AE22) -> 20.170726
C23: 241011000034 | D23: 45580 | E23: 罗珮文 | F23: Shirley | G23: Yusky | H23: 0.1865 | I23: 30 | K23: 72893 | M23: =SUM(K23/N23) -> 1544.9979 | N23: 47.18 | O23: 7.24 | P23: =SUM(N23*O23) -> 341.5832 | S23: =SUM(40096/68)*H23 -> 109.96918 | U23: =SUM(2100/68)*H23 -> 5.7595588 | X23: =SUM(S23:W23) -> 115.72874 | Y23: =SUM(10477.84/68)*H23 -> 28.737017 | AA23: =SUM(222.57/68)*H23 -> 0.61043096 | AB23: =SUM(Y23:AA23) -> 29.347448 | AC23: 7.27 | AD23: =SUM(AB23*AC23) -> 213.35595 | AE23: =SUM(X23+AD23) -> 329.08468 | AF23: =SUM(P23-AE23) -> 12.498518
C24: 241011000035 | D24: 45580 | E24: 罗珮文 | F24: Shirley | G24: Yusky | H24: 0.1821 | I24: 17 | K24: 72792.6 | M24: =SUM(K24/N24) -> 1580.0434 | N24: 46.07 | O24: 7.24 | P24: =SUM(N24*O24) -> 333.5468 | S24: =SUM(40096/68)*H24 -> 107.37473 | U24: =SUM(2100/68)*H24 -> 5.6236765 | X24: =SUM(S24:W24) -> 112.99841 | Y24: =SUM(10477.84/68)*H24 -> 28.059039 | AA24: =SUM(222.57/68)*H24 -> 0.59602937 | AB24: =SUM(Y24:AA24) -> 28.655069 | AC24: 7.27 | AD24: =SUM(AB24*AC24) -> 208.32235 | AE24: =SUM(X24+AD24) -> 321.32075 | AF24: =SUM(P24-AE24) -> 12.226046
C25: 241015000033 | D25: 45580 | E25: 吕沛霖 | F25: 喵喵速运-Layne | G25: MU SHI SHI | H25: 0.138 | I25: 26 | J25: 356 | P25: =SUBTOTAL(9,J25) -> 356 | S25: =SUM(40096/68)*H25 -> 81.371294 | U25: =SUM(2100/68)*H25 -> 4.2617647 | X25: =SUM(S25:W25) -> 85.633059 | Y25: =SUM(10477.84/68)*H25 -> 21.263852 | AA25: =SUM(222.57/68)*H25 -> 0.45168618 | AB25: =SUM(Y25:AA25) -> 21.715538 | AC25: 7.27 | AD25: =SUM(AB25*AC25) -> 157.87196 | AE25: =SUM(X25+AD25) -> 243.50502 | AF25: =SUM(P25-AE25) -> 112.49498
C26: 241005000007 | D26: 45580 | E26: 黄颖 | F26: ying | G26: MISS Huang | H26: 1.7993 | I26: 702.27 | K26: 830610 | M26: =SUM(K26/N26) -> 1678 | N26: 495 | O26: 7.27 | P26: =SUM(N26*O26) -> 3598.65 | S26: =SUM(40096/68)*H26 -> 1060.952 | U26: =SUM(2100/68)*H26 -> 55.566618 | X26: =SUM(S26:W26) -> 1116.5186 | Y26: =SUM(10477.84/68)*H26 -> 277.24673 | AA26: =SUM(222.57/68)*H26 -> 5.8892677 | AB26: =SUM(Y26:AA26) -> 283.136 | AC26: 7.27 | AD26: =SUM(AB26*AC26) -> 2058.3987 | AE26: =SUM(X26+AD26) -> 3174.9173 | AF26: =SUM(P26-AE26) -> 423.73274
C27: 241012000013 | D27: 45580 | E27: 黄颖 | F27: ying | G27: Bruce | H27: 4.6667 | I27: 1862 | K27: 2104240.8 | M27: =SUM(K27/N27) -> 1639.6599 | N27: 1283.3398 | O27: 7.29 | P27: =SUM(N27*O27) -> 9355.5471 | S27: =SUM(40096/68)*H27 -> 2751.7059 | U27: =SUM(2100/68)*H27 -> 144.11868 | X27: =SUM(S27:W27) -> 2895.8246 | Y27: =SUM(10477.84/68)*H27 -> 719.07259 | AA27: =SUM(222.57/68)*H27 -> 15.274521 | AB27: =SUM(Y27:AA27) -> 734.34711 | AC27: 7.27 | AD27: =SUM(AB27*AC27) -> 5338.7035 | AE27: =SUM(X27+AD27) -> 8234.5281 | AF27: =SUM(P27-AE27) -> 1121.0191
C28: 241007000001 | D28: 45580 | E28: 陆总 | F28: 陆梓龙 | G28: jizong | H28: 5.4 | I28: 3863.5 | J28: 12614.4 | P28: =SUBTOTAL(9,J28) -> 12614.4 | S28: =SUM(40096/68)*H28 -> 3184.0941 | U28: =SUM(2100/68)*H28 -> 166.76471 | X28: =SUM(S28:W28) -> 3350.8588 | Y28: =SUM(10477.84/68)*H28 -> 832.06376 | AA28: =SUM(222.57/68)*H28 -> 17.674676 | AB28: =SUM(Y28:AA28) -> 849.73844 | AC28: 7.27 | AD28: =SUM(AB28*AC28) -> 6177.5985 | AE28: =SUM(X28+AD28) -> 9528.4573 | AF28: =SUM(P28-AE28) -> 3085.9427
C29: 241014000047 | D29: 45580 | E29: 陆总 | F29: 陆梓龙 | G29: luk | H29: 1.7401 | I29: 1028 | J29: 3551.45 | P29: =SUBTOTAL(9,J29) -> 3551.45 | S29: =SUM(40096/68)*H29 -> 1026.0448 | U29: =SUM(2100/68)*H29 -> 53.738382 | V29: 150 | X29: =SUM(S29:W29) -> 1229.7832 | Y29: =SUM(10477.84/68)*H29 -> 268.12484 | AA29: =SUM(222.57/68)*H29 -> 5.6955008 | AB29: =SUM(Y29:AA29) -> 273.82034 | AC29: 7.27 | AD29: =SUM(AB29*AC29) -> 1990.6739 | AE29: =SUM(X29+AD29) -> 3220.4571 | AF29: =SUM(P29-AE29) -> 330.99286
C30: 241015000035 | D30: 45580 | E30: 罗珮文 | F30: Shirley | G30: James | H30: 0.6634 | I30: 185 | M30: =SUM(K30/N30) -> 0 | N30: 592.5 | O30: 7.11 | P30: =SUM(N30*O30) -> 4212.675 | S30: =SUM(40096/68)*H30 -> 391.17186 | U30: =SUM(2100/68)*H30 -> 20.487353 | X30: =SUM(S30:W30) -> 411.65921 | Y30: =SUM(10477.84/68)*H30 -> 102.22057 | AA30: =SUM(222.57/68)*H30 -> 2.1713667 | AB30: =SUM(Y30:AA30) -> 104.39194 | AC30: 7.27 | AD30: =SUM(AB30*AC30) -> 758.92941 | AE30: =SUM(X30+AD30) -> 1170.5886 | AF30: =SUM(P30-AE30) -> 3042.0864
A31: 合计 | J31: =SUM(J4:J4) -> 0 | N31: =SUM(N4:N4) -> 0 | P31: =SUM(P4:P4) -> 0 | Q31: =SUM(Q4:Q4) -> 0 | X31: =SUM(X4:X4) -> 0 | AD31: =SUM(AD4:AD4) -> 0 | AF31: =SUM(AF4:AF30) -> 15990.29

Sheet JOB100363
A1: 2024年10月份LOS毛利表（海运）
A2: PSL表 | B2: 体积cbm | C2: 75.3356
A3: JOB | B3: 集装编号 | C3: 运单编号 | D3: 日期 | E3: 业务 | F3: 发货人 | G3: 收货人 | H3: 计费体积 | I3: 计费重量 | J3: 应 收 | Q3: 总应收 | R3: 起 运 港 成 本 | W3: 代垫运费 | X3: 起运港成本 合计 | Y3: 目的港成本 | AE3: 总支出 | AF3: 利润
J4: 应收RMB | K4: LOS Income(NGN)收到(奈拉) | L4: LOS 收到USD | M4: 美元汇率 dollar currency rate | N4: 应收 到付款USD | O4: 汇率 | P4: 人民币 | R4: 代理商 | S4: 运费+出口报关费 | T4: 提货费 | U4: 装卸费 | V4: 包装费 | Y4: 进口报关费 | Z4: 到门配送费 | AA4: 转运费 | AB4: 目的港支出 | AC4: 汇率 | AD4: 人民币 | AE4: 起运港+目的港
A5: JOB100363 | B5: COLL004265 | C5: 240926000032 | D5: 45587 | E5: 黄颖 | F5: ying | G5: Sunday Adelena | H5: 18.7805 | I5: 11775 | J5: 38416 | P5: =SUBTOTAL(9,J5) -> 38416 | Q5: =SUM(P5:P29) -> 184202.95 | R5: 登凯=41870 陆总=3000 拖车费=1670 杂费=61 过磅费=69 | S5: =SUM(46670/68)*H5 -> 12889.499 | U5: =SUM(1300/68)*H5 -> 359.03897 | V5: 800 | X5: =SUM(S5:W5) -> 14048.538 | Y5: =SUM(10523.89/68)*H5 -> 2906.5282 | AB5: =SUM(Y5:AA5) -> 2906.5282 | AC5: 7.28 | AD5: =SUM(AB5*AC5) -> 21159.525 | AE5: =SUM(X5+AD5) -> 35208.063 | AF5: =SUM(P5-AE5) -> 3207.9368
C6: 241007000001 | D6: 45587 | E6: 陆总 | F6: 陆梓龙 | G6: jizong | H6: 5.4 | I6: 3863.5 | J6: 12614.4 | P6: =SUBTOTAL(9,J6) -> 12614.4 | S6: =SUM(46670/68)*H6 -> 3706.1471 | U6: =SUM(1300/68)*H6 -> 103.23529 | X6: =SUM(S6:W6) -> 3809.3824 | Y6: =SUM(10523.89/68)*H6 -> 835.72068 | AB6: =SUM(Y6:AA6) -> 835.72068 | AC6: 7.28 | AD6: =SUM(AB6*AC6) -> 6084.0465 | AE6: =SUM(X6+AD6) -> 9893.4289 | AF6: =SUM(P6-AE6) -> 2720.9711
C7: 241008000045 | D7: 45587 | E7: 黄颖 | F7: ying | G7: Wuchengxing | H7: 1.0343 | I7: 87 | J7: 2210.6 | P7: =SUBTOTAL(9,J7) -> 2210.6 | S7: =SUM(46670/68)*H7 -> 709.86443 | U7: =SUM(1300/68)*H7 -> 19.773382 | V7: 300 | X7: =SUM(S7:W7) -> 1029.6378 | Y7: =SUM(10523.89/68)*H7 -> 160.07146 | AB7: =SUM(Y7:AA7) -> 160.07146 | AC7: 7.28 | AD7: =SUM(AB7*AC7) -> 1165.3202 | AE7: =SUM(X7+AD7) -> 2194.9581 | AF7: =SUM(P7-AE7) -> 15.641947
C8: 241011000009 | D8: 45587 | E8: 黄颖 | F8: ying | G8: fanglijuan | H8: 0.7032 | I8: 282 | J8: 1819 | P8: =SUBTOTAL(9,J8) -> 1819 | S8: =SUM(46670/68)*H8 -> 482.62271 | U8: =SUM(1300/68)*H8 -> 13.443529 | X8: =SUM(S8:W8) -> 496.06624 | Y8: =SUM(10523.89/68)*H8 -> 108.8294 | AB8: =SUM(Y8:AA8) -> 108.8294 | AC8: 7.28 | AD8: =SUM(AB8*AC8) -> 792.27806 | AE8: =SUM(X8+AD8) -> 1288.3443 | AF8: =SUM(P8-AE8) -> 530.65571
C9: 241011000052 | D9: 45587 | E9: 无人 | F9: Mailmail Abv sales person 1 | G9: Pedoski | H9: 1.5798 | I9: 199 | K9: 795789 | M9: =SUM(K9/N9) -> 1736.9996 | N9: 458.14 | O9: 7.28 | P9: =SUM(N9*O9) -> 3335.2592 | S9: =SUM(46670/68)*H9 -> 1084.2539 | U9: =SUM(1300/68)*H9 -> 30.202059 | X9: =SUM(S9:W9) -> 1114.456 | Y9: =SUM(10523.89/68)*H9 -> 244.49473 | AB9: =SUM(Y9:AA9) -> 244.49473 | AC9: 7.28 | AD9: =SUM(AB9*AC9) -> 1779.9216 | AE9: =SUM(X9+AD9) -> 2894.3776 | AF9: =SUM(P9-AE9) -> 440.88162
C10: 241015000012 | D10: 45587 | E10: Sam.Pao | F10: Sam.Pao | G10: WangJianHua | H10: 0.4173 | I10: 209 | J10: 914 | P10: =SUBTOTAL(9,J10) -> 914 | S10: =SUM(46670/68)*H10 -> 286.40281 | U10: =SUM(1300/68)*H10 -> 7.9777941 | X10: =SUM(S10:W10) -> 294.3806 | Y10: =SUM(10523.89/68)*H10 -> 64.582637 | AB10: =SUM(Y10:AA10) -> 64.582637 | AC10: 7.28 | AD10: =SUM(AB10*AC10) -> 470.1616 | AE10: =SUM(X10+AD10) -> 764.5422 | AF10: =SUM(P10-AE10) -> 149.4578
C11: 241015000013 | D11: 45587 | E11: Sam.Pao | F11: Sam.Pao | G11: AiGeLi | H11: 18.4906 | I11: 7082 | J11: 57160 | P11: =SUBTOTAL(9,J11) -> 57160 | S11: =SUM(46670/68)*H11 -> 12690.534 | U11: =SUM(1300/68)*H11 -> 353.49676 | X11: =SUM(S11:W11) -> 13044.031 | Y11: =SUM(10523.89/68)*H11 -> 2861.6624 | Z11: 777.2 | AB11: =SUM(Y11:AA11) -> 3638.8624 | AC11: 7.28 | AD11: =SUM(AB11*AC11) -> 26490.918 | AE11: =SUM(X11+AD11) -> 39534.949 | AF11: =SUM(P11-AE11) -> 17625.051
C12: 241015000033 | D12: 45587 | E12: 吕沛霖 | F12: 喵喵速运-Layne | G12: MU SHI SHI | H12: 6.7059 | I12: 796 | J12: 17295.8 | P12: =SUBTOTAL(9,J12) -> 17295.8 | S12: =SUM(46670/68)*H12 -> 4602.417 | U12: =SUM(1300/68)*H12 -> 128.20103 | V12: 300 | X12: =SUM(S12:W12) -> 5030.618 | Y12: =SUM(10523.89/68)*H12 -> 1037.8258 | Z12: 299.37 | AB12: =SUM(Y12:AA12) -> 1337.1958 | AC12: 7.28 | AD12: =SUM(AB12*AC12) -> 9734.7854 | AE12: =SUM(X12+AD12) -> 14765.403 | AF12: =SUM(P12-AE12) -> 2530.3966
C13: 241016000053 | D13: 45587 | E13: 朱小飞 | F13: Isabel Zhu | G13: Halifa Success | H13: 1.2066 | I13: 116 | J13: 2950.46 | P13: =SUBTOTAL(9,J13) -> 2950.46 | S13: =SUM(46670/68)*H13 -> 828.11797 | U13: =SUM(1300/68)*H13 -> 23.067353 | V13: 300 | X13: =SUM(S13:W13) -> 1151.1853 | Y13: =SUM(10523.89/68)*H13 -> 186.73714 | AB13: =SUM(Y13:AA13) -> 186.73714 | AC13: 7.28 | AD13: =SUM(AB13*AC13) -> 1359.4464 | AE13: =SUM(X13+AD13) -> 2510.6317 | AF13: =SUM(P13-AE13) -> 439.82828
C14: 241017000056 | D14: 45587 | E14: 朱小飞 | F14: Isabel Zhu | G14: Lin Bao Zhen | H14: 8.013 | I14: 788 | K14: 4131000 | M14: =SUM(K14/N14) -> 1700 | N14: 2430 | O14: 7.26 | P14: =SUM(N14*O14) -> 17641.8 | S14: =SUM(46670/68)*H14 -> 5499.5104 | U14: =SUM(1300/68)*H14 -> 153.18971 | X14: =SUM(S14:W14) -> 5652.7001 | Y14: =SUM(10523.89/68)*H14 -> 1240.1166 | AB14: =SUM(Y14:AA14) -> 1240.1166 | AC14: 7.28 | AD14: =SUM(AB14*AC14) -> 9028.049 | AE14: =SUM(X14+AD14) -> 14680.749 | AF14: =SUM(P14-AE14) -> 2961.0508
C15: 241018000013 | D15: 45587 | E15: 黄颖 | F15: ying | G15: zhounengquan | H15: 0.0116 | I15: 31 | J15: 397.5 | P15: =SUBTOTAL(9,J15) -> 397.5 | S15: =SUM(46670/68)*H15 -> 7.9613529 | U15: =SUM(1300/68)*H15 -> 0.22176471 | W15: 62 | X15: =SUM(S15:W15) -> 70.183118 | Y15: =SUM(10523.89/68)*H15 -> 1.7952518 | Z15: 13.24 | AB15: =SUM(Y15:AA15) -> 15.035252 | AC15: 7.28 | AD15: =SUM(AB15*AC15) -> 109.45663 | AE15: =SUM(X15+AD15) -> 179.63975 | AF15: =SUM(P15-AE15) -> 217.86025
C16: 241018000027 | D16: 45587 | E16: 朱小飞 | F16: Isabel Zhu | G16: Joy | H16: 1.3662 | I16: 373 | K16: 745280 | M16: =SUM(K16/N16) -> 1700 | N16: 438.4 | O16: 7.29 | P16: =SUM(N16*O16) -> 3195.936 | S16: =SUM(46670/68)*H16 -> 937.65521 | U16: =SUM(1300/68)*H16 -> 26.118529 | X16: =SUM(S16:W16) -> 963.77374 | Y16: =SUM(10523.89/68)*H16 -> 211.43733 | Z16: 12.09 | AB16: =SUM(Y16:AA16) -> 223.52733 | AC16: 7.28 | AD16: =SUM(AB16*AC16) -> 1627.279 | AE16: =SUM(X16+AD16) -> 2591.0527 | AF16: =SUM(P16-AE16) -> 604.88329
C17: 241018000032 | D17: 45587 | E17: 黄颖 | F17: ying | G17: Wuchengxing | H17: 0.2617 | I17: 43 | J17: 595.4 | P17: =SUBTOTAL(9,J17) -> 595.4 | S17: =SUM(46670/68)*H17 -> 179.61087 | U17: =SUM(1300/68)*H17 -> 5.0030882 | X17: =SUM(S17:W17) -> 184.61396 | Y17: =SUM(10523.89/68)*H17 -> 40.5015 | AB17: =SUM(Y17:AA17) -> 40.5015 | AC17: 7.28 | AD17: =SUM(AB17*AC17) -> 294.85092 | AE17: =SUM(X17+AD17) -> 479.46488 | AF17: =SUM(P17-AE17) -> 115.93512
C18: 241018000040 | D18: 45587 | E18: Bella | F18: Bella Chan | G18: zhang long ting | H18: 0.072 | I18: 11 | J18: 153.3 | P18: =SUBTOTAL(9,J18) -> 153.3 | S18: =SUM(46670/68)*H18 -> 49.415294 | U18: =SUM(1300/68)*H18 -> 1.3764706 | X18: =SUM(S18:W18) -> 50.791765 | Y18: =SUM(10523.89/68)*H18 -> 11.142942 | AB18: =SUM(Y18:AA18) -> 11.142942 | AC18: 7.28 | AD18: =SUM(AB18*AC18) -> 81.12062 | AE18: =SUM(X18+AD18) -> 131.91239 | AF18: =SUM(P18-AE18) -> 21.387615
C19: 241019000014 | D19: 45587 | E19: 黄颖 | F19: ying | G19: MISS Huang | H19: 0.1797 | I19: 75 | K19: 98978.4 | M19: =SUM(K19/N19) -> 1867.1643 | N19: 53.01001 | O19: 7.27 | P19: =SUM(N19*O19) -> 385.38277 | S19: =SUM(46670/68)*H19 -> 123.33234 | U19: =SUM(1300/68)*H19 -> 3.4354412 | X19: =SUM(S19:W19) -> 126.76778 | Y19: =SUM(10523.89/68)*H19 -> 27.810927 | AB19: =SUM(Y19:AA19) -> 27.810927 | AC19: 7.28 | AD19: =SUM(AB19*AC19) -> 202.46355 | AE19: =SUM(X19+AD19) -> 329.23133 | AF19: =SUM(P19-AE19) -> 56.151445
C20: 241021000038 | D20: 45587 | E20: Bella | F20: Bella Chan | G20: FENG | H20: 0.443 | I20: 70 | J20: 1201 | P20: =SUBTOTAL(9,J20) -> 1201 | S20: =SUM(46670/68)*H20 -> 304.04132 | U20: =SUM(1300/68)*H20 -> 8.4691176 | X20: =SUM(S20:W20) -> 312.51044 | Y20: =SUM(10523.89/68)*H20 -> 68.560048 | AB20: =SUM(Y20:AA20) -> 68.560048 | AC20: 7.28 | AD20: =SUM(AB20*AC20) -> 499.11715 | AE20: =SUM(X20+AD20) -> 811.62759 | AF20: =SUM(P20-AE20) -> 389.37241
C21: 241021000046 | D21: 45587 | E21: 黄颖 | F21: ying | G21: Bruce | H21: 2.7577 | I21: 1156 | K21: 1342546 | M21: =SUM(K21/N21) -> 1678.602 | N21: 799.80005 | O21: 7.27 | P21: =SUM(N21*O21) -> 5814.5464 | S21: =SUM(46670/68)*H21 -> 1892.6744 | U21: =SUM(1300/68)*H21 -> 52.720735 | X21: =SUM(S21:W21) -> 1945.3951 | Y21: =SUM(10523.89/68)*H21 -> 426.79017 | AB21: =SUM(Y21:AA21) -> 426.79017 | AC21: 7.28 | AD21: =SUM(AB21*AC21) -> 3107.0324 | AE21: =SUM(X21+AD21) -> 5052.4276 | AF21: =SUM(P21-AE21) -> 762.11881
C22: 241021000062 | D22: 45587 | E22: 朱小飞 | F22: Isabel Zhu | G22: Halifa Success | H22: 0.2357 | I22: 19 | J22: 489.22 | P22: =SUBTOTAL(9,J22) -> 489.22 | S22: =SUM(46670/68)*H22 -> 161.76646 | U22: =SUM(1300/68)*H22 -> 4.5060294 | X22: =SUM(S22:W22) -> 166.27249 | Y22: =SUM(10523.89/68)*H22 -> 36.47766 | AB22: =SUM(Y22:AA22) -> 36.47766 | AC22: 7.28 | AD22: =SUM(AB22*AC22) -> 265.55736 | AE22: =SUM(X22+AD22) -> 431.82985 | AF22: =SUM(P22-AE22) -> 57.390151
C23: 241022000014 | D23: 45587 | E23: 罗珮文 | F23: Shirley | G23: Yusky | H23: 0.168 | I23: 64 | K23: 67947.46 | M23: =SUM(K23/N23) -> 1631 | N23: 41.66 | O23: 7.35 | P23: =SUM(N23*O23) -> 306.201 | S23: =SUM(46670/68)*H23 -> 115.30235 | U23: =SUM(1300/68)*H23 -> 3.2117647 | X23: =SUM(S23:W23) -> 118.51412 | Y23: =SUM(10523.89/68)*H23 -> 26.000199 | AB23: =SUM(Y23:AA23) -> 26.000199 | AC23: 7.28 | AD23: =SUM(AB23*AC23) -> 189.28145 | AE23: =SUM(X23+AD23) -> 307.79557 | AF23: =SUM(P23-AE23) -> -1.5945651
C24: 241022000015 | D24: 45587 | E24: 罗珮文 | F24: Shirley | G24: Yusky | H24: 0.145 | I24: 27 | K24: 58650.76 | M24: =SUM(K24/N24) -> 1631 | N24: 35.96 | O24: 7.35 | P24: =SUM(N24*O24) -> 264.306 | S24: =SUM(46670/68)*H24 -> 99.516912 | U24: =SUM(1300/68)*H24 -> 2.7720588 | X24: =SUM(S24:W24) -> 102.28897 | Y24: =SUM(10523.89/68)*H24 -> 22.440648 | AB24: =SUM(Y24:AA24) -> 22.440648 | AC24: 7.28 | AD24: =SUM(AB24*AC24) -> 163.36792 | AE24: =SUM(X24+AD24) -> 265.65689 | AF24: =SUM(P24-AE24) -> -1.3508865
C25: 241022000016 | D25: 45587 | E25: 罗珮文 | F25: Shirley | G25: Yusky | H25: 0.3529 | I25: 36 | K25: 142761.43 | M25: =SUM(K25/N25) -> 1631 | N25: 87.53 | O25: 7.35 | P25: =SUM(N25*O25) -> 643.3455 | S25: =SUM(46670/68)*H25 -> 242.20357 | U25: =SUM(1300/68)*H25 -> 6.7466176 | X25: =SUM(S25:W25) -> 248.95019 | Y25: =SUM(10523.89/68)*H25 -> 54.615894 | AB25: =SUM(Y25:AA25) -> 54.615894 | AC25: 7.28 | AD25: =SUM(AB25*AC25) -> 397.60371 | AE25: =SUM(X25+AD25) -> 646.5539 | AF25: =SUM(P25-AE25) -> -3.2083983
C26: 241017000051 | D26: 45593 | E26: 朱小飞 | F26: Isabel Zhu | G26: Lin Bao Zhen | H26: 3.59 | I26: 279 | K26: 2138600 | M26: =SUM(K26/N26) -> 1700 | N26: 1258 | O26: 7.26 | P26: =SUM(N26*O26) -> 9133.08 | S26: =SUM(46670/68)*H26 -> 2463.9015 | U26: =SUM(1300/68)*H26 -> 68.632353 | X26: =SUM(S26:W26) -> 2532.5338 | Y26: =SUM(10523.89/68)*H26 -> 555.59949 | AB26: =SUM(Y26:AA26) -> 555.59949 | AC26: 7.28 | AD26: =SUM(AB26*AC26) -> 4044.7643 | AE26: =SUM(X26+AD26) -> 6577.2981 | AF26: =SUM(P26-AE26) -> 2555.7819
C27: 241019000010 | D27: 45593 | E27: 黄颖 | F27: ying | G27: MISS Huang | H27: 0.5263 | I27: 165 | K27: 257287 | M27: =SUM(K27/N27) -> 1652.8781 | N27: 155.66 | O27: 7.29 | P27: =SUM(N27*O27) -> 1134.7614 | S27: =SUM(46670/68)*H27 -> 361.21207 | U27: =SUM(1300/68)*H27 -> 10.061618 | X27: =SUM(S27:W27) -> 371.27369 | Y27: =SUM(10523.89/68)*H27 -> 81.451813 | AB27: =SUM(Y27:AA27) -> 81.451813 | AC27: 7.28 | AD27: =SUM(AB27*AC27) -> 592.9692 | AE27: =SUM(X27+AD27) -> 964.24289 | AF27: =SUM(P27-AE27) -> 170.51851
C28: 241014000059 | D28: 45593 | E28: 黄颖 | F28: ying | G28: Sunday Adelena | H28: 2.7811 | I28: 410 | J28: 6035 | P28: =SUBTOTAL(9,J28) -> 6035 | S28: =SUM(46670/68)*H28 -> 1908.7344 | U28: =SUM(1300/68)*H28 -> 53.168088 | X28: =SUM(S28:W28) -> 1961.9025 | Y28: =SUM(10523.89/68)*H28 -> 430.41162 | AB28: =SUM(Y28:AA28) -> 430.41162 | AC28: 7.28 | AD28: =SUM(AB28*AC28) -> 3133.3966 | AE28: =SUM(X28+AD28) -> 5095.2991 | AF28: =SUM(P28-AE28) -> 939.70092
C29: 241022000017 | D29: 45587 | E29: 罗珮文 | F29: Shirley | G29: Yusky | H29: 0.053 | I29: 9 | K29: 21447.65 | M29: =SUM(K29/N29) -> 1631 | N29: 13.15 | O29: 7.35 | P29: =SUM(N29*O29) -> 96.6525 | S29: =SUM(46670/68)*H29 -> 36.375147 | U29: =SUM(1300/68)*H29 -> 1.0132353 | X29: =SUM(S29:W29) -> 37.388382 | Y29: =SUM(10523.89/68)*H29 -> 8.2024437 | AB29: =SUM(Y29:AA29) -> 8.2024437 | AC29: 7.28 | AD29: =SUM(AB29*AC29) -> 59.71379 | AE29: =SUM(X29+AD29) -> 97.102172 | AF29: =SUM(P29-AE29) -> -0.44967232
A30: 合计 | J30: =SUM(J4:J4) -> 0 | N30: =SUM(N4:N4) -> 0 | P30: =SUM(P4:P4) -> 0 | Q30: =SUM(Q4:Q4) -> 0 | X30: =SUM(X4:X4) -> 0 | AD30: =SUM(AD4:AD4) -> 0 | AF30: =SUM(AF4:AF29) -> 36506.369

Sheet JOB100364
A1: 2024年10月份LOS毛利表（海运）
A2: PSL表 | B2: 体积cbm | C2: 68.6891
A3: JOB | B3: 集装编号 | C3: 运单编号 | D3: 日期 | E3: 业务 | F3: 发货人 | G3: 收货人 | H3: 计费体积 | I3: 计费重量 | J3: 应 收 | Q3: 总应收 | R3: 起 运 港 成 本 | W3: 代垫运费 | X3: 起运港成本 合计 | Y3: 目的港成本 | AE3: 总支出 | AF3: 利润
J4: 应收RMB | K4: LOS Income(NGN)收到(奈拉) | L4: LOS 收到USD | M4: 美元汇率 dollar currency rate | N4: 应收 到付款USD | O4: 汇率 | P4: 人民币 | R4: 代理商 | S4: 运费+出口报关费 | T4: 提货费 | U4: 装卸费 | V4: 包装费 | Y4: 进口报关费 | Z4: 到门配送费 | AA4: 转运费 | AB4: 目的港支出 | AC4: 汇率 | AD4: 人民币 | AE4: 起运港+目的港
A5: JOB100364 | B5: COLL004268 | C5: 241009000018 | D5: 45593 | E5: 黄颖 | F5: ying | G5: Wole Rasak | H5: 5.4554 | I5: 1522 | J5: 13408.72 | P5: =SUBTOTAL(9,J5) -> 13408.72 | Q5: =SUM(P5:P24) -> 150424.74 | R5: 登凯=43830 赛捷=1480 拖车费=1670 杂费=539 过磅费=67 | S5: =SUM(47586/68)*H5 -> 3817.6568 | U5: =SUM(1900/68)*H5 -> 152.43029 | X5: =SUM(S5:W5) -> 3970.0871 | Y5: =SUM(11133.9/68)*H5 -> 893.2335 | Z5: 59.22 | AB5: =SUM(Y5:AA5) -> 952.4535 | AC5: 7.3 | AD5: =SUM(AB5*AC5) -> 6952.9106 | AE5: =SUM(X5+AD5) -> 10922.998 | AF5: =SUM(P5-AE5) -> 2485.7223
C6: 241014000044 | D6: 45593 | E6: 黄颖 | F6: ying | G6: Nura | H6: 0.6091 | I6: 363 | J6: 1326.75 | P6: =SUBTOTAL(9,J6) -> 1326.75 | S6: =SUM(47586/68)*H6 -> 426.2446 | U6: =SUM(1900/68)*H6 -> 17.018971 | X6: =SUM(S6:W6) -> 443.26357 | Y6: =SUM(11133.9/68)*H6 -> 99.730272 | AB6: =SUM(Y6:AA6) -> 99.730272 | AC6: 7.3 | AD6: =SUM(AB6*AC6) -> 728.03098 | AE6: =SUM(X6+AD6) -> 1171.2946 | AF6: =SUM(P6-AE6) -> 155.45545
C7: 241014000059 | D7: 45593 | E7: 黄颖 | F7: ying | G7: Sunday Adelena | H7: 6.7537 | I7: 2221 | J7: 14651 | P7: =SUBTOTAL(9,J7) -> 14651 | S7: =SUM(47586/68)*H7 -> 4726.1995 | U7: =SUM(1900/68)*H7 -> 188.70632 | X7: =SUM(S7:W7) -> 4914.9059 | Y7: =SUM(11133.9/68)*H7 -> 1105.8091 | AB7: =SUM(Y7:AA7) -> 1105.8091 | AC7: 7.3 | AD7: =SUM(AB7*AC7) -> 8072.4066 | AE7: =SUM(X7+AD7) -> 12987.312 | AF7: =SUM(P7-AE7) -> 1663.6875
C8: 241016000027 | D8: 45593 | E8: 黄颖 | F8: ying | G8: Wole Rasak | H8: 1.4941 | I8: 1016 | J8: 3860.6 | P8: =SUBTOTAL(9,J8) -> 3860.6 | S8: =SUM(47586/68)*H8 -> 1045.5624 | U8: =SUM(1900/68)*H8 -> 41.746912 | X8: =SUM(S8:W8) -> 1087.3093 | Y8: =SUM(11133.9/68)*H8 -> 244.63471 | Z8: 16.25 | AB8: =SUM(Y8:AA8) -> 260.88471 | AC8: 7.3 | AD8: =SUM(AB8*AC8) -> 1904.4584 | AE8: =SUM(X8+AD8) -> 2991.7677 | AF8: =SUM(P8-AE8) -> 868.83235
C9: 241016000054 | D9: 45593 | E9: 无人 | F9: dejare James | G9: ALH RAKIM | H9: 1.8336 | I9: 260 | M9: =SUM(K9/N9) -> 0 | N9: 550.08 | O9: 7.11 | P9: =SUM(N9*O9) -> 3911.0688 | S9: =SUM(47586/68)*H9 -> 1283.1425 | U9: =SUM(1900/68)*H9 -> 51.232941 | X9: =SUM(S9:W9) -> 1334.3754 | Y9: =SUM(11133.9/68)*H9 -> 300.22234 | AB9: =SUM(Y9:AA9) -> 300.22234 | AC9: 7.3 | AD9: =SUM(AB9*AC9) -> 2191.6231 | AE9: =SUM(X9+AD9) -> 3525.9985 | AF9: =SUM(P9-AE9) -> 385.07029
C10: 241017000021 | D10: 45593 | E10: 吕沛霖 | F10: 喵喵速运-Layne | G10: MA ZONG | H10: 4.4844 | I10: 764 | J10: 10328.9 | P10: =SUM(J10) -> 10328.9 | S10: =SUM(47586/68)*H10 -> 3138.1567 | U10: =SUM(1900/68)*H10 -> 125.29941 | X10: =SUM(S10:W10) -> 3263.4562 | Y10: =SUM(11133.9/68)*H10 -> 734.24796 | Z10: 109.73 | AB10: =SUM(Y10:AA10) -> 843.97796 | AC10: 7.3 | AD10: =SUM(AB10*AC10) -> 6161.0391 | AE10: =SUM(X10+AD10) -> 9424.4952 | AF10: =SUM(P10-AE10) -> 904.40475
C11: 241017000051 | D11: 45593 | E11: 朱小飞 | F11: Isabel Zhu | G11: Lin Bao Zhen | H11: 3.273 | I11: 2588 | K11: 1949050 | M11: =SUM(K11/N11) -> 1700 | N11: 1146.5 | O11: 7.26 | P11: =SUM(N11*O11) -> 8323.59 | S11: =SUM(47586/68)*H11 -> 2290.4261 | U11: =SUM(1900/68)*H11 -> 91.451471 | X11: =SUM(S11:W11) -> 2381.8776 | Y11: =SUM(11133.9/68)*H11 -> 535.9008 | AB11: =SUM(Y11:AA11) -> 535.9008 | AC11: 7.3 | AD11: =SUM(AB11*AC11) -> 3912.0759 | AE11: =SUM(X11+AD11) -> 6293.9535 | AF11: =SUM(P11-AE11) -> 2029.6365
C12: 241019000010 | D12: 45593 | E12: 黄颖 | F12: ying | G12: MISS Huang | H12: 1.4386 | I12: 615 | K12: 703277 | M12: =SUM(K12/N12) -> 1652.8638 | N12: 425.49 | O12: 7.29 | P12: =SUM(N12*O12) -> 3101.8221 | S12: =SUM(47586/68)*H12 -> 1006.7238 | U12: =SUM(1900/68)*H12 -> 40.196176 | X12: =SUM(S12:W12) -> 1046.92 | Y12: =SUM(11133.9/68)*H12 -> 235.54748 | AB12: =SUM(Y12:AA12) -> 235.54748 | AC12: 7.3 | AD12: =SUM(AB12*AC12) -> 1719.4966 | AE12: =SUM(X12+AD12) -> 2766.4166 | AF12: =SUM(P12-AE12) -> 335.40551
C13: 241021000039 | D13: 45593 | E13: 黄颖 | F13: ying | G13: mazhiwei | H13: 0.075 | I13: 11 | J13: 220.5 | P13: =SUBTOTAL(9,J13) -> 220.5 | S13: =SUM(47586/68)*H13 -> 52.484559 | U13: =SUM(1900/68)*H13 -> 2.0955882 | X13: =SUM(S13:W13) -> 54.580147 | Y13: =SUM(11133.9/68)*H13 -> 12.280037 | AB13: =SUM(Y13:AA13) -> 12.280037 | AC13: 7.3 | AD13: =SUM(AB13*AC13) -> 89.644268 | AE13: =SUM(X13+AD13) -> 144.22442 | AF13: =SUM(P13-AE13) -> 76.275585
C14: 241021000069 | D14: 45593 | E14: Sam.Pao | F14: Sam.Pao | G14: MaiKaiNian | H14: 0.9189 | I14: 373 | J14: 2175.03 | P14: =SUBTOTAL(9,J14) -> 2175.03 | S14: =SUM(47586/68)*H14 -> 643.04081 | U14: =SUM(1900/68)*H14 -> 25.675147 | V14: 96 | X14: =SUM(S14:W14) -> 764.71596 | Y14: =SUM(11133.9/68)*H14 -> 150.45501 | AB14: =SUM(Y14:AA14) -> 150.45501 | AC14: 7.3 | AD14: =SUM(AB14*AC14) -> 1098.3216 | AE14: =SUM(X14+AD14) -> 1863.0375 | AF14: =SUM(P14-AE14) -> 311.99246
C15: 241023000007 | D15: 45593 | E15: 朱小飞 | F15: Isabel Zhu | G15: Ife Oyelami | H15: 0.0575 | I15: 26 | K15: 54219 | M15: =SUM(K15/N15) -> 1643 | N15: 33 | O15: 7.29 | P15: =SUM(N15*O15) -> 240.57 | S15: =SUM(47586/68)*H15 -> 40.238162 | U15: =SUM(1900/68)*H15 -> 1.6066176 | X15: =SUM(S15:W15) -> 41.844779 | Y15: =SUM(11133.9/68)*H15 -> 9.4146949 | AB15: =SUM(Y15:AA15) -> 9.4146949 | AC15: 7.3 | AD15: =SUM(AB15*AC15) -> 68.727272 | AE15: =SUM(X15+AD15) -> 110.57205 | AF15: =SUM(P15-AE15) -> 129.99795
C16: 241023000026 | D16: 45593 | E16: 黄颖 | F16: ying | G16: Bruce | H16: 2.1367 | I16: 934 | K16: 1025772 | M16: =SUM(K16/N16) -> 1652.8714 | N16: 620.6 | O16: 7.29 | P16: =SUM(N16*O16) -> 4524.174 | S16: =SUM(47586/68)*H16 -> 1495.2501 | U16: =SUM(1900/68)*H16 -> 59.701912 | X16: =SUM(S16:W16) -> 1554.952 | Y16: =SUM(11133.9/68)*H16 -> 349.85006 | AB16: =SUM(Y16:AA16) -> 349.85006 | AC16: 7.3 | AD16: =SUM(AB16*AC16) -> 2553.9054 | AE16: =SUM(X16+AD16) -> 4108.8574 | AF16: =SUM(P16-AE16) -> 415.31655
C17: 241023000028 | D17: 45593 | E17: 陆总 | F17: 陆梓龙 | G17: luk | H17: 1.7499 | I17: 398 | J17: 3525.68 | P17: =SUBTOTAL(9,J17) -> 3525.68 | S17: =SUM(47586/68)*H17 -> 1224.5697 | U17: =SUM(1900/68)*H17 -> 48.894265 | X17: =SUM(S17:W17) -> 1273.464 | Y17: =SUM(11133.9/68)*H17 -> 286.51782 | AB17: =SUM(Y17:AA17) -> 286.51782 | AC17: 7.3 | AD17: =SUM(AB17*AC17) -> 2091.5801 | AE17: =SUM(X17+AD17) -> 3365.0441 | AF17: =SUM(P17-AE17) -> 160.63594
C18: 241023000030 | D18: 45593 | E18: 陆总 | F18: 陆梓龙 | G18: WANG | H18: 1.32 | I18: 1000 | J18: 2601.72 | P18: =SUBTOTAL(9,J18) -> 2601.72 | S18: =SUM(47586/68)*H18 -> 923.72824 | U18: =SUM(1900/68)*H18 -> 36.882353 | X18: =SUM(S18:W18) -> 960.61059 | Y18: =SUM(11133.9/68)*H18 -> 216.12865 | AB18: =SUM(Y18:AA18) -> 216.12865 | AC18: 7.3 | AD18: =SUM(AB18*AC18) -> 1577.7391 | AE18: =SUM(X18+AD18) -> 2538.3497 | AF18: =SUM(P18-AE18) -> 63.370288
C19: 241023000035 | D19: 45593 | E19: Sam.Pao | F19: Sam.Pao | G19: JunYue hotel | H19: 1.2483 | I19: 347 | J19: 2824 | P19: =SUBTOTAL(9,J19) -> 2824 | S19: =SUM(47586/68)*H19 -> 873.553 | U19: =SUM(1900/68)*H19 -> 34.878971 | X19: =SUM(S19:W19) -> 908.43197 | Y19: =SUM(11133.9/68)*H19 -> 204.38893 | AB19: =SUM(Y19:AA19) -> 204.38893 | AC19: 7.3 | AD19: =SUM(AB19*AC19) -> 1492.0392 | AE19: =SUM(X19+AD19) -> 2400.4712 | AF19: =SUM(P19-AE19) -> 423.52883
C20: 241024000016 | D20: 45593 | E20: 朱小飞 | F20: Isabel Zhu | G20: Halifa Success | H20: 0.1931 | I20: 24 | J20: 410.48 | P20: =SUBTOTAL(9,J20) -> 410.48 | S20: =SUM(47586/68)*H20 -> 135.13024 | U20: =SUM(1900/68)*H20 -> 5.3954412 | X20: =SUM(S20:W20) -> 140.52569 | Y20: =SUM(11133.9/68)*H20 -> 31.617001 | AB20: =SUM(Y20:AA20) -> 31.617001 | AC20: 7.3 | AD20: =SUM(AB20*AC20) -> 230.80411 | AE20: =SUM(X20+AD20) -> 371.32979 | AF20: =SUM(P20-AE20) -> 39.150205
C21: 241025000059 | D21: 45593 | E21: 朱小飞 | F21: Isabel Zhu | G21: Halifa Success | H21: 2.2221 | I21: 248 | J21: 4576.85 | P21: =SUBTOTAL(9,J21) -> 4576.85 | S21: =SUM(47586/68)*H21 -> 1555.0125 | U21: =SUM(1900/68)*H21 -> 62.088088 | X21: =SUM(S21:W21) -> 1617.1006 | Y21: =SUM(11133.9/68)*H21 -> 363.83293 | AB21: =SUM(Y21:AA21) -> 363.83293 | AC21: 7.3 | AD21: =SUM(AB21*AC21) -> 2655.9804 | AE21: =SUM(X21+AD21) -> 4273.081 | AF21: =SUM(P21-AE21) -> 303.76902
C22: 241026000019 | D22: 45595 | E22: 黄颖 | F22: ying | G22: MISS Huang | H22: 0.3084 | I22: 117 | K22: 150985 | M22: =SUM(K22/N22) -> 1652.8188 | N22: 91.35 | O22: 7.29 | P22: =SUM(N22*O22) -> 665.9415 | S22: =SUM(47586/68)*H22 -> 215.81651 | U22: =SUM(1900/68)*H22 -> 8.6170588 | X22: =SUM(S22:W22) -> 224.43356 | Y22: =SUM(11133.9/68)*H22 -> 50.495511 | AB22: =SUM(Y22:AA22) -> 50.495511 | AC22: 7.3 | AD22: =SUM(AB22*AC22) -> 368.61723 | AE22: =SUM(X22+AD22) -> 593.0508 | AF22: =SUM(P22-AE22) -> 72.890704
C23: 241028000021 | D23: 45593 | E23: 罗珮文 | F23: Shirley | G23: Yusky | H23: 19.7914 | I23: 1519 | K23: 8739687.4 | M23: =SUM(K23/N23) -> 1635.5521 | N23: 5343.57 | O23: 7.3 | P23: =SUM(N23*O23) -> 39008.061 | S23: =SUM(47586/68)*H23 -> 13849.905 | U23: =SUM(1900/68)*H23 -> 552.995 | X23: =SUM(S23:W23) -> 14402.9 | Y23: =SUM(11133.9/68)*H23 -> 3240.5216 | AB23: =SUM(Y23:AA23) -> 3240.5216 | AC23: 7.3 | AD23: =SUM(AB23*AC23) -> 23655.808 | AE23: =SUM(X23+AD23) -> 38058.708 | AF23: =SUM(P23-AE23) -> 949.35306
C24: 241031000026 | D24: 45593 | E24: 陆总 | F24: 陆梓龙 | G24: xinlong | H24: 13.3255 | I24: 13006 | J24: 30739.28 | P24: =SUBTOTAL(9,J24) -> 30739.28 | S24: =SUM(47586/68)*H24 -> 9325.1065 | U24: =SUM(1900/68)*H24 -> 372.33015 | X24: =SUM(S24:W24) -> 9697.4367 | Y24: =SUM(11133.9/68)*H24 -> 2181.8351 | Z24: 131.35 | AB24: =SUM(Y24:AA24) -> 2313.1851 | AC24: 7.3 | AD24: =SUM(AB24*AC24) -> 16886.251 | AE24: =SUM(X24+AD24) -> 26583.688 | AF24: =SUM(P24-AE24) -> 4155.5924
A25: 合计 | J25: =SUM(J4:J4) -> 0 | N25: =SUM(N4:N4) -> 0 | P25: =SUM(P4:P4) -> 0 | Q25: =SUM(Q4:Q4) -> 0 | X25: =SUM(X4:X4) -> 0 | AD25: =SUM(AD4:AD4) -> 0 | AF25: =SUM(AF4:AF24) -> 15930.088

Sheet JOB100365
A1: 2024年10月份LOS毛利表（海运）
A2: PSL表 | B2: 体积cbm | C2: 71.2954
A3: JOB | B3: 集装编号 | C3: 运单编号 | D3: 日期 | E3: 业务 | F3: 发货人 | G3: 收货人 | H3: 计费体积 | I3: 计费重量 | J3: 应 收 | Q3: 总应收 | R3: 起 运 港 成 本 | W3: 代垫运费 | X3: 起运港成本 合计 | Y3: 目的港成本 | AE3: 总支出 | AF3: 利润
J4: 应收RMB | K4: LOS Income(NGN)收到(奈拉) | L4: LOS 收到USD | M4: 美元汇率 dollar currency rate | N4: 应收 到付款USD | O4: 汇率 | P4: 人民币 | R4: 代理商 | S4: 运费+出口报关费 | T4: 提货费 | U4: 装卸费 | V4: 包装费 | Y4: 进口报关费 | Z4: 到门配送费 | AA4: 转运费 | AB4: 目的港支出 | AC4: 汇率 | AD4: 人民币 | AE4: 起运港+目的港
A5: JOB100365 | B5: COLL004270 | C5: 241011000005 | D5: 45595 | E5: 黄颖 | F5: ying | G5: baikaibo | H5: 3.1875 | I5: 2044 | J5: 8910 | P5: =SUBTOTAL(9,J5) -> 8910 | Q5: =SUM(P5:P13) -> 133755.67 | R5: 登凯=43830 赛捷=2960 拖车费=1670 杂费=623 过磅费=69 | S5: =SUM(49152/68)*H5 -> 2304 | U5: =SUM(1400/68)*H5 -> 65.625 | X5: =SUM(S5:W5) -> 2369.625 | Y5: =SUM(11133.9/68)*H5 -> 521.90156 | AA5: =SUM(69.17/68)*H5 -> 3.2423437 | AB5: =SUM(Y5:AA5) -> 525.14391 | AC5: 7.3 | AD5: =SUM(AB5*AC5) -> 3833.5505 | AE5: =SUM(X5+AD5) -> 6203.1755 | AF5: =SUM(P5-AE5) -> 2706.8245
C6: 241028000024 | D6: 45595 | E6: 黄颖 | F6: ying | G6: Bruce | H6: 1.5107 | I6: 646 | K6: 706092 | M6: =SUM(K6/N6) -> 1654.9678 | N6: 426.65 | O6: 7.29 | P6: =SUM(N6*O6) -> 3110.2785 | S6: =SUM(49152/68)*H6 -> 1091.9695 | U6: =SUM(1400/68)*H6 -> 31.102647 | X6: =SUM(S6:W6) -> 1123.0722 | Y6: =SUM(11133.9/68)*H6 -> 247.35269 | AA6: =SUM(69.17/68)*H6 -> 1.5366929 | AB6: =SUM(Y6:AA6) -> 248.88938 | AC6: 7.3 | AD6: =SUM(AB6*AC6) -> 1816.8925 | AE6: =SUM(X6+AD6) -> 2939.9646 | AF6: =SUM(P6-AE6) -> 170.31387
C7: 241017000025 | D7: 45595 | E7: 吕沛霖 | F7: 喵喵速运-Layne | G7: ABDUL | H7: 1.8596 | I7: 2312 | K7: 1660291 | M7: =SUM(K7/N7) -> 1730.1006 | N7: 959.65 | O7: 7.3 | P7: =SUM(N7*O7) -> 7005.445 | S7: =SUM(49152/68)*H7 -> 1344.1626 | U7: =SUM(1400/68)*H7 -> 38.285882 | X7: =SUM(S7:W7) -> 1382.4485 | Y7: =SUM(11133.9/68)*H7 -> 304.47942 | Z7: 31.41 | AA7: =SUM(69.17/68)*H7 -> 1.8915961 | AB7: =SUM(Y7:AA7) -> 337.78101 | AC7: 7.3 | AD7: =SUM(AB7*AC7) -> 2465.8014 | AE7: =SUM(X7+AD7) -> 3848.2499 | AF7: =SUM(P7-AE7) -> 3157.1951
C8: 241025000020 | D8: 45595 | E8: Bella | F8: Bella Chan | G8: zhang long ting | H8: 0.054 | I8: 11 | J8: 118 | P8: =SUBTOTAL(9,J8) -> 118 | S8: =SUM(49152/68)*H8 -> 39.032471 | U8: =SUM(1400/68)*H8 -> 1.1117647 | X8: =SUM(S8:W8) -> 40.144235 | Y8: =SUM(11133.9/68)*H8 -> 8.8416265 | AA8: =SUM(69.17/68)*H8 -> 0.054929118 | AB8: =SUM(Y8:AA8) -> 8.8965556 | AC8: 7.3 | AD8: =SUM(AB8*AC8) -> 64.944856 | AE8: =SUM(X8+AD8) -> 105.08909 | AF8: =SUM(P8-AE8) -> 12.910909
C9: 241029000029 | D9: 45595 | E9: 陆总 | F9: 陆梓龙 | G9: jizong | H9: 0.0491 | I9: 12 | J9: 107.53 | P9: =SUBTOTAL(9,J9) -> 107.53 | S9: =SUM(49152/68)*H9 -> 35.490635 | U9: =SUM(1400/68)*H9 -> 1.0108824 | X9: =SUM(S9:W9) -> 36.501518 | Y9: =SUM(11133.9/68)*H9 -> 8.0393307 | AA9: =SUM(69.17/68)*H9 -> 0.049944809 | AB9: =SUM(Y9:AA9) -> 8.0892755 | AC9: 7.3 | AD9: =SUM(AB9*AC9) -> 59.051711 | AE9: =SUM(X9+AD9) -> 95.553229 | AF9: =SUM(P9-AE9) -> 11.976771
C10: 241030000038 | D10: 45595 | E10: 罗珮文 | F10: Shirley | G10: SKY JET | H10: 43.89 | I10: 5168 | J10: 67551.98 | P10: =SUBTOTAL(9,J10) -> 67551.98 | S10: =SUM(49152/68)*H10 -> 31724.725 | U10: =SUM(1400/68)*H10 -> 903.61765 | X10: =SUM(S10:W10) -> 32628.342 | Y10: =SUM(11133.9/68)*H10 -> 7186.2775 | AA10: =SUM(69.17/68)*H10 -> 44.645166 | AB10: =SUM(Y10:AA10) -> 7230.9227 | AC10: 7.3 | AD10: =SUM(AB10*AC10) -> 52785.736 | AE10: =SUM(X10+AD10) -> 85414.078 | AF10: =SUM(P10-AE10) -> -17862.098
C11: 241030000040 | D11: 45595 | E11: 陆总 | F11: 陆梓龙 | G11: jizong | H11: 0.635 | I11: 240 | J11: 1251.59 | P11: =SUBTOTAL(9,J11) -> 1251.59 | S11: =SUM(49152/68)*H11 -> 458.99294 | U11: =SUM(1400/68)*H11 -> 13.073529 | X11: =SUM(S11:W11) -> 472.06647 | Y11: =SUM(11133.9/68)*H11 -> 103.97098 | AA11: =SUM(69.17/68)*H11 -> 0.64592574 | AB11: =SUM(Y11:AA11) -> 104.6169 | AC11: 7.3 | AD11: =SUM(AB11*AC11) -> 763.7034 | AE11: =SUM(X11+AD11) -> 1235.7699 | AF11: =SUM(P11-AE11) -> 15.820133
C12: 241030000042 | D12: 45595 | E12: 陆总 | F12: 陆梓龙 | G12: jizong | H12: 2.0475 | I12: 720 | J12: 4035.66 | P12: =SUBTOTAL(9,J12) -> 4035.66 | S12: =SUM(49152/68)*H12 -> 1479.9812 | U12: =SUM(1400/68)*H12 -> 42.154412 | X12: =SUM(S12:W12) -> 1522.1356 | Y12: =SUM(11133.9/68)*H12 -> 335.245 | AA12: =SUM(69.17/68)*H12 -> 2.082729 | AB12: =SUM(Y12:AA12) -> 337.32773 | AC12: 7.3 | AD12: =SUM(AB12*AC12) -> 2462.4924 | AE12: =SUM(X12+AD12) -> 3984.628 | AF12: =SUM(P12-AE12) -> 51.031963
C13: 241031000028 | D13: 45595 | E13: 陆总 | F13: 陆梓龙 | G13: xinlong | H13: 18.0619 | I13: 16900 | J13: 41665.19 | P13: =SUBTOTAL(9,J13) -> 41665.19 | S13: =SUM(49152/68)*H13 -> 13055.566 | U13: =SUM(1400/68)*H13 -> 371.86265 | X13: =SUM(S13:W13) -> 13427.429 | Y13: =SUM(11133.9/68)*H13 -> 2957.3439 | Z13: 178.04 | AA13: =SUM(69.17/68)*H13 -> 18.372671 | AB13: =SUM(Y13:AA13) -> 3153.7566 | AC13: 7.3 | AD13: =SUM(AB13*AC13) -> 23022.423 | AE13: =SUM(X13+AD13) -> 36449.852 | AF13: =SUM(P13-AE13) -> 5215.3377
A14: 合计 | Q14: =SUM(Q5) -> 133755.67 | X14: =SUM(X4:X4) -> 0 | AE14: =SUM(AE5:AE13) -> 140276.36 | AF14: =SUM(AF4:AF13) -> -6520.687

Sheet JOB100366
A1: 2024年10月份LOS毛利表（海运）
A2: JOB | B2: 集装编号 | C2: 运单编号 | D2: 日期 | E2: 业务 | F2: 发货人 | G2: 收货人 | H2: 计费体积 | I2: 计费重量 | J2: 应 收 | Q2: 总应收 | R2: 起 运 港 成 本 | W2: 代垫运费 | X2: 起运港成本 合计 | Y2: 目的港成本 | AE2: 总支出 | AF2: 利润
J3: 应收RMB | K3: LOS Income(NGN)收到(奈拉) | L3: LOS 收到USD | M3: 美元汇率 dollar currency rate | N3: 应收 到付款USD | O3: 汇率 | P3: 人民币 | R3: 代理商 | S3: 运费+出口报关费 | T3: 提货费 | U3: 装卸费 | V3: 包装费 | Y3: 进口报关费 | Z3: 到门配送费 | AA3: 转运费 | AB3: 目的港支出 | AC3: 汇率 | AD3: 人民币 | AE3: 起运港+目的港
A4: JOB100366 | B4: COLL004269 | C4: 241024000009 | D4: 45595 | E4: 吕沛霖 | F4: 喵喵速运-Layne | G4: Ka Ka 4分部 | H4: 1.508 | I4: 508 | K4: 1104957.1 | M4: =SUM(K4/N4) -> 1669.422 | N4: 661.88 | O4: 7.29 | P4: =SUM(N4*O4) -> 4825.1052 | Q4: =SUM(P4:P14) -> 138920.74 | R4: 登凯=43830 赛捷=1160 拖车费=1670 杂费=633 过磅费=69 | S4: =SUM(47362/68)*H4 -> 1050.322 | U4: =SUM(2400/68)*H4 -> 53.223529 | X4: =SUM(S4:W4) -> 1103.5455 | Y4: =SUM(10699.87/68)*H4 -> 237.28535 | Z4: 210.97 | AA4: =SUM(66.95/68)*H4 -> 1.4847147 | AB4: =SUM(Y4:AA4) -> 449.74007 | AC4: 7.3 | AD4: =SUM(AB4*AC4) -> 3283.1025 | AE4: =SUM(X4+AD4) -> 4386.648 | AF4: =SUM(P4-AE4) -> 438.45718
C5: 241024000010 | D5: 45595 | E5: 吕沛霖 | F5: 喵喵速运-Layne | G5: Ka Ka 4分部 | H5: 0.1128 | I5: 88 | K5: 109278 | M5: =SUM(K5/N5) -> 1669.3859 | N5: 65.46 | O5: 7.29 | P5: =SUM(N5*O5) -> 477.2034 | S5: =SUM(47362/68)*H5 -> 78.5652 | U5: =SUM(2400/68)*H5 -> 3.9811765 | X5: =SUM(S5:W5) -> 82.546376 | Y5: =SUM(10699.87/68)*H5 -> 17.749196 | Z5: 28.12 | AA5: =SUM(66.95/68)*H5 -> 0.11105824 | AB5: =SUM(Y5:AA5) -> 45.980254 | AC5: 7.3 | AD5: =SUM(AB5*AC5) -> 335.65586 | AE5: =SUM(X5+AD5) -> 418.20223 | AF5: =SUM(P5-AE5) -> 59.001167
C6: 241017000025 | D6: 45595 | E6: 吕沛霖 | F6: 喵喵速运-Layne | G6: ABDUL | H6: 0.8826 | I6: 1102 | K6: 788004 | M6: =SUM(K6/N6) -> 1730.0898 | N6: 455.47 | O6: 7.3 | P6: =SUM(N6*O6) -> 3324.931 | S6: =SUM(47362/68)*H6 -> 614.7309 | U6: =SUM(2400/68)*H6 -> 31.150588 | X6: =SUM(S6:W6) -> 645.88149 | Y6: =SUM(10699.87/68)*H6 -> 138.87802 | AA6: =SUM(66.95/68)*H6 -> 0.86897162 | AB6: =SUM(Y6:AA6) -> 139.74699 | AC6: 7.3 | AD6: =SUM(AB6*AC6) -> 1020.153 | AE6: =SUM(X6+AD6) -> 1666.0345 | AF6: =SUM(P6-AE6) -> 1658.8965
C7: 241026000019 | D7: 45595 | E7: 黄颖 | F7: ying | G7: MISS Huang | H7: 0.8568 | I7: 325 | K7: 419471 | M7: =SUM(K7/N7) -> 1652.762 | N7: 253.8 | O7: 7.29 | P7: =SUM(N7*O7) -> 1850.202 | S7: =SUM(47362/68)*H7 -> 596.7612 | U7: =SUM(2400/68)*H7 -> 30.24 | X7: =SUM(S7:W7) -> 627.0012 | Y7: =SUM(10699.87/68)*H7 -> 134.81836 | AA7: =SUM(66.95/68)*H7 -> 0.84357 | AB7: =SUM(Y7:AA7) -> 135.66193 | AC7: 7.3 | AD7: =SUM(AB7*AC7) -> 990.3321 | AE7: =SUM(X7+AD7) -> 1617.3333 | AF7: =SUM(P7-AE7) -> 232.8687
C8: 241026000022 | D8: 45595 | E8: 吕沛霖 | F8: 喵喵速运-Layne | G8: Hu Hai Liang | H8: 1.1042 | I8: 1026 | K8: 673554 | M8: =SUM(K8/N8) -> 1580 | N8: 426.3 | O8: 7.29 | P8: =SUM(N8*O8) -> 3107.727 | S8: =SUM(47362/68)*H8 -> 769.0753 | U8: =SUM(2400/68)*H8 -> 38.971765 | X8: =SUM(S8:W8) -> 808.04706 | Y8: =SUM(10699.87/68)*H8 -> 173.74701 | AA8: =SUM(66.95/68)*H8 -> 1.0871499 | AB8: =SUM(Y8:AA8) -> 174.83416 | AC8: 7.3 | AD8: =SUM(AB8*AC8) -> 1276.2893 | AE8: =SUM(X8+AD8) -> 2084.3364 | AF8: =SUM(P8-AE8) -> 1023.3906
C9: 241027000001 | D9: 45595 | E9: 朱小飞 | F9: Isabel Zhu | G9: Luxre Fashions | H9: 0.7063 | I9: 119 | K9: 368007 | M9: =SUM(K9/N9) -> 1671.9992 | N9: 220.09999 | O9: 7.3 | P9: =SUM(N9*O9) -> 1606.7299 | S9: =SUM(47362/68)*H9 -> 491.93795 | U9: =SUM(2400/68)*H9 -> 24.928235 | X9: =SUM(S9:W9) -> 516.86619 | Y9: =SUM(10699.87/68)*H9 -> 111.13703 | AA9: =SUM(66.95/68)*H9 -> 0.6953939 | AB9: =SUM(Y9:AA9) -> 111.83243 | AC9: 7.3 | AD9: =SUM(AB9*AC9) -> 816.37671 | AE9: =SUM(X9+AD9) -> 1333.2429 | AF9: =SUM(P9-AE9) -> 273.48703
C10: 241027000012 | D10: 45595 | E10: Sam.Pao | F10: Sam.Pao | G10: ShanShan | H10: 5.2289 | I10: 1231 | J10: 13095 | P10: =SUBTOTAL(9,J10) -> 13095 | S10: =SUM(47362/68)*H10 -> 3641.9288 | U10: =SUM(2400/68)*H10 -> 184.54941 | X10: =SUM(S10:W10) -> 3826.4783 | Y10: =SUM(10699.87/68)*H10 -> 822.7728 | Z10: 48.69 | AA10: =SUM(66.95/68)*H10 -> 5.1481596 | AB10: =SUM(Y10:AA10) -> 876.61096 | AC10: 7.3 | AD10: =SUM(AB10*AC10) -> 6399.26 | AE10: =SUM(X10+AD10) -> 10225.738 | AF10: =SUM(P10-AE10) -> 2869.2617
C11: 241028000024 | D11: 45595 | E11: 黄颖 | F11: ying | G11: Bruce | H11: 0.7664 | I11: 289 | K11: 358212 | M11: =SUM(K11/N11) -> 1654.9411 | N11: 216.45 | O11: 7.29 | P11: =SUM(N11*O11) -> 1577.9205 | S11: =SUM(47362/68)*H11 -> 533.7976 | U11: =SUM(2400/68)*H11 -> 27.049412 | X11: =SUM(S11:W11) -> 560.84701 | Y11: =SUM(10699.87/68)*H11 -> 120.59383 | AA11: =SUM(66.95/68)*H11 -> 0.75456588 | AB11: =SUM(Y11:AA11) -> 121.34839 | AC11: 7.3 | AD11: =SUM(AB11*AC11) -> 885.84328 | AE11: =SUM(X11+AD11) -> 1446.6903 | AF11: =SUM(P11-AE11) -> 131.23021
C12: 241029000041 | D12: 45595 | E12: 黄颖 | F12: ying | G12: Ariel | H12: 0.0009 | I12: 1 | J12: 150 | P12: =SUBTOTAL(9,J12) -> 150 | S12: =SUM(47362/68)*H12 -> 0.62685 | U12: =SUM(2400/68)*H12 -> 0.031764706 | X12: =SUM(S12:W12) -> 0.65861471 | Y12: =SUM(10699.87/68)*H12 -> 0.14161593 | AA12: =SUM(66.95/68)*H12 -> 0.00088610294 | AB12: =SUM(Y12:AA12) -> 0.14250203 | AC12: 7.3 | AD12: =SUM(AB12*AC12) -> 1.0402648 | AE12: =SUM(X12+AD12) -> 1.6988795 | AF12: =SUM(P12-AE12) -> 148.30112
C13: 241030000013 | D13: 45595 | E13: 罗珮文 | F13: Shirley | G13: SKY JET | H13: 42.49 | I13: 4990 | J13: 65397.12 | P13: =SUBTOTAL(9,J13) -> 65397.12 | S13: =SUM(47362/68)*H13 -> 29594.285 | U13: =SUM(2400/68)*H13 -> 1499.6471 | X13: =SUM(S13:W13) -> 31093.932 | Y13: =SUM(10699.87/68)*H13 -> 6685.8452 | AA13: =SUM(66.95/68)*H13 -> 41.833904 | AB13: =SUM(Y13:AA13) -> 6727.6791 | AC13: 7.3 | AD13: =SUM(AB13*AC13) -> 49112.058 | AE13: =SUM(X13+AD13) -> 80205.99 | AF13: =SUM(P13-AE13) -> -14808.87
C14: 241031000027 | D14: 45595 | E14: 陆总 | F14: 陆梓龙 | G14: xinlong | H14: 18.8611 | I14: 18408 | J14: 43508.8 | P14: =SUBTOTAL(9,J14) -> 43508.8 | S14: =SUM(47362/68)*H14 -> 13136.756 | U14: =SUM(2400/68)*H14 -> 665.68588 | X14: =SUM(S14:W14) -> 13802.442 | Y14: =SUM(10699.87/68)*H14 -> 2967.8135 | Z14: 185.92 | AA14: =SUM(66.95/68)*H14 -> 18.569862 | AB14: =SUM(Y14:AA14) -> 3172.3034 | AC14: 7.3 | AD14: =SUM(AB14*AC14) -> 23157.815 | AE14: =SUM(X14+AD14) -> 36960.257 | AF14: =SUM(P14-AE14) -> 6548.5434
A15: 合计 | J15: =SUM(J3:J3) -> 0 | N15: =SUM(N3:N3) -> 0 | P15: =SUM(P3:P3) -> 0 | Q15: =SUM(Q3:Q3) -> 0 | X15: =SUM(X3:X3) -> 0 | AD15: =SUM(AD3:AD3) -> 0 | AF15: =SUM(AF3:AF14) -> -1425.4322

Sheet JOB120359
A1: 2024年10月份LOS毛利表（海运）
A2: JOB | B2: 集装编号 | C2: 运单编号 | D2: 日期 | E2: 业务 | F2: 发货人 | G2: 收货人 | H2: 计费体积 | I2: 计费重量 | J2: 应 收 | Q2: 总应收 | R2: 起 运 港 成 本 | W2: 代垫运费 | X2: 起运港成本 合计 | Y2: 目的港成本 | AE2: 总支出 | AF2: 利润
J3: 应收RMB | K3: LOS Income(NGN)收到(奈拉) | L3: LOS 收到USD | M3: 美元汇率 dollar currency rate | N3: 应收 到付款USD | O3: 汇率 | P3: 人民币 | R3: 代理商 | S3: 运费+出口报关费 | T3: 提货费 | U3: 装卸费 | V3: 包装费 | Y3: 进口报关费 | Z3: 到门配送费 | AA3: 转运费 | AB3: 目的港支出 | AC3: 汇率 | AD3: 人民币 | AE3: 起运港+目的港
A4: JOB120359 | B4: COLL004280 | C4: 241120000026 | D4: 45592 | E4: Sam.Pao | F4: Sam.Pao | G4: ShanShan | H4: 68 | J4: 50836 | K4: 21300000 | M4: =SUM(K4/N4) -> 1669.0004 | N4: 12762.13 | O4: 7.3 | P4: =SUM(N4*O4+J4) -> 143999.55 | Q4: =SUM(P4) -> 143999.55 | R4: 登凯=44060 陆总=2500 拖车费=1670 杂费=101 过磅费=68 | S4: 48399 | X4: =SUM(S4:W4) -> 48399 | Y4: 11545.4 | AB4: =SUM(Y4:AA4) -> 11545.4 | AC4: 7.27 | AD4: =SUM(AB4*AC4) -> 83935.058 | AE4: =SUM(X4+AD4) -> 132334.06 | AF4: =SUM(Q4-AE4) -> 11665.491
A5: 合计 | J5: =SUM(J3:J3) -> 0 | N5: =SUM(N3:N3) -> 0 | P5: =SUM(P3:P3) -> 0 | Q5: =SUM(Q3:Q3) -> 0 | X5: =SUM(X3:X3) -> 0 | AD5: =SUM(AD3:AD3) -> 0 | AF5: =SUM(AF3:AF4) -> 11665.491
