Workbook

Sheet 总表 
A1: 2024年12月份LOS毛利表（海运）
A2: JOB | B2: 集装编号 | C2: 利润
A4: JOB120360 | B4: COLL004315 | C4: =SUM('JOB120360'!AF41) -> 24290.936
A40: JOB120375 | B40: COLL004323 | C40: =SUM('JOB120375'!AF18) -> 24315.892
A53: JOB120376 | B53: COLL004324 | C53: =SUM('JOB120376'!AF13) -> -3608.7565
A61: JOB120381 | B61: COLL004325 | C61: =SUM('JOB120381'!AF15) -> 764.62021
A71: JOB120387 | B71: COLL004326 | C71: =SUM('JOB120387'!AF28) -> 20710.74
A94: JOB120390 | B94: COLL004328 | C94: =SUM('JOB120390'!AF12) -> 7182.2738
A101: JOB120399 | B101: COLL004330 | C101: =SUM('JOB120399'!AF36) -> 25144.544
A132: JOB120404 | B132: COLL004342 | C132: =SUM('JOB120404'!AF18) -> 11861.717
A133: JOB120404 | B133: COLL004342
A145: JOB0202178 | B145: COLL004395 | C145: =SUM('JOB0202178'!AF6) -> 4067
A146: 合计 | C146: =SUM(C3:C145) -> 114728.96

Sheet 总表  (2)
A1: 2024年12月份LOS毛利表（海运）
A2: JOB | B2: 集装编号 | C2: 运单编号 | D2: 日期 | E2: 业务 | F2: 发货人 | G2: 收货人 | H2: 计费体积 | I2: 计费重量 | J2: 应 收 | Q2: 总应收 | R2: 起 运 港 成 本 | W2: 代垫运费 | X2: 起运港成本 合计 | Y2: 目的港成本 | AE2: 总支出 | AF2: 利润
J3: 应收RMB | K3: LOS Income(NGN)收到(奈拉) | L3: LOS 收到USD | M3: 美元汇率 dollar currency rate | N3: 应收 到付款USD | O3: 汇率 | P3: 人民币 | R3: 代理商 | S3: 运费+出口报关费 | T3: 提货费 | U3: 装卸费 | V3: 包装费 | Y3: 进口报关费 | Z3: 到门配送费 | AA3: 转运费 | AB3: 目的港支出 | AC3: 汇率 | AD3: 人民币 | AE3: 起运港+目的港
A4: JOB120360 | B4: COLL004315 | C4: 240925000017 | D4: 45631 | E4: 无人 | F4: dejare James | G4: James | H4: 0.1799 | I4: 17 | K4: 84600 | M4: =SUM(K4/N4) -> 1679.5713 | N4: 50.369995 | O4: 7.27 | P4: =SUM(N4*O4) -> 366.18986 | Q4: =SUM(P4:P39) -> 162259.24 | R4: 登凯=43870.25 创泽=1270 拖车费=1670 杂费=84 过磅费=69 | S4: =SUM(46963.25/68)*H4 -> 124.24542 | U4: =SUM(2500/68)*H4 -> 6.6139706 | X4: =SUM(S4:W4) -> 130.85939 | Y4: =SUM(11081/68)*H4 -> 29.315763 | AB4: =SUM(Y4:AA4) -> 29.315763 | AC4: 7.24 | AD4: =SUM(AB4*AC4) -> 212.24613 | AE4: =SUM(X4+AD4) -> 343.10552 | AF4: =SUM(P4-AE4) -> 23.084346
C5: 241118000063 | D5: 45631 | E5: 罗珮文 | F5: Shirley | G5: Yusky | H5: 1.6585 | I5: 270 | K5: 719837.28 | M5: =SUM(K5/N5) -> 1608 | N5: 447.66 | O5: 7.3 | P5: =SUM(N5*O5) -> 3267.918 | S5: =SUM(46963.25/68)*H5 -> 1145.4199 | U5: =SUM(2500/68)*H5 -> 60.974265 | X5: =SUM(S5:W5) -> 1206.3941 | Y5: =SUM(11081/68)*H5 -> 270.26233 | AB5: =SUM(Y5:AA5) -> 270.26233 | AC5: 7.24 | AD5: =SUM(AB5*AC5) -> 1956.6993 | AE5: =SUM(X5+AD5) -> 3163.0934 | AF5: =SUM(P5-AE5) -> 104.8246
C6: 241118000066 | D6: 45631 | E6: 罗珮文 | F6: Shirley | G6: Yusky | H6: 1.2581 | I6: 125 | K6: 546173.28 | M6: =SUM(K6/N6) -> 1608 | N6: 339.66 | O6: 7.3 | P6: =SUM(N6*O6) -> 2479.518 | S6: =SUM(46963.25/68)*H6 -> 868.88919 | U6: =SUM(2500/68)*H6 -> 46.253676 | X6: =SUM(S6:W6) -> 915.14287 | Y6: =SUM(11081/68)*H6 -> 205.0148 | AB6: =SUM(Y6:AA6) -> 205.0148 | AC6: 7.24 | AD6: =SUM(AB6*AC6) -> 1484.3071 | AE6: =SUM(X6+AD6) -> 2399.45 | AF6: =SUM(P6-AE6) -> 80.068015
C7: 241120000012 | D7: 45631 | E7: Bella | F7: Bella Chan | G7: FENG | H7: 0.1878 | I7: 62 | K7: 94651.2 | M7: =SUM(K7/N7) -> 1680.0001 | N7: 56.339996 | O7: 7.3 | P7: =SUM(N7*O7) -> 411.28197 | S7: =SUM(46963.25/68)*H7 -> 129.70145 | U7: =SUM(2500/68)*H7 -> 6.9044118 | X7: =SUM(S7:W7) -> 136.60586 | Y7: =SUM(11081/68)*H7 -> 30.603115 | AB7: =SUM(Y7:AA7) -> 30.603115 | AC7: 7.24 | AD7: =SUM(AB7*AC7) -> 221.56655 | AE7: =SUM(X7+AD7) -> 358.17241 | AF7: =SUM(P7-AE7) -> 53.109562
C8: 241120000023 | D8: 45631 | E8: Sam.Pao | F8: Sam.Pao | G8: Mr. Jiang | H8: 1.3317 | I8: 326 | J8: 4965 | P8: =SUBTOTAL(9,J8) -> 4965 | S8: =SUM(46963.25/68)*H8 -> 919.72 | U8: =SUM(2500/68)*H8 -> 48.959559 | V8: 500 | X8: =SUM(S8:W8) -> 1468.6796 | Y8: =SUM(11081/68)*H8 -> 217.00835 | AB8: =SUM(Y8:AA8) -> 217.00835 | AC8: 7.24 | AD8: =SUM(AB8*AC8) -> 1571.1404 | AE8: =SUM(X8+AD8) -> 3039.82 | AF8: =SUM(P8-AE8) -> 1925.18
C9: 241121000013 | D9: 45631 | E9: Sam.Pao | F9: Sam.Pao | G9: Mr. Jiang | H9: 2.2982 | I9: 612 | J9: 7707 | P9: =SUBTOTAL(9,J9) -> 7707 | S9: =SUM(46963.25/68)*H9 -> 1587.2197 | U9: =SUM(2500/68)*H9 -> 84.492647 | V9: 400 | X9: =SUM(S9:W9) -> 2071.7124 | Y9: =SUM(11081/68)*H9 -> 374.50521 | AB9: =SUM(Y9:AA9) -> 374.50521 | AC9: 7.24 | AD9: =SUM(AB9*AC9) -> 2711.4177 | AE9: =SUM(X9+AD9) -> 4783.1301 | AF9: =SUM(P9-AE9) -> 2923.8699
C10: 241121000018 | D10: 45631 | E10: Sam.Pao | F10: Sam.Pao | G10: Nick Wang | H10: 0.0768 | I10: 14 | J10: 296.22 | P10: =SUBTOTAL(9,J10) -> 296.22 | S10: =SUM(46963.25/68)*H10 -> 53.040847 | U10: =SUM(2500/68)*H10 -> 2.8235294 | X10: =SUM(S10:W10) -> 55.864376 | Y10: =SUM(11081/68)*H10 -> 12.515012 | Z10: 4.51 | AB10: =SUM(Y10:AA10) -> 17.025012 | AC10: 7.24 | AD10: =SUM(AB10*AC10) -> 123.26109 | AE10: =SUM(X10+AD10) -> 179.12546 | AF10: =SUM(P10-AE10) -> 117.09454
C11: 241121000019 | D11: 45631 | E11: Sam.Pao | F11: Sam.Pao | G11: Mr. Jiang | H11: 1.4834 | I11: 471 | J11: 3598 | P11: =SUBTOTAL(9,J11) -> 3598 | S11: =SUM(46963.25/68)*H11 -> 1024.4895 | U11: =SUM(2500/68)*H11 -> 54.536765 | X11: =SUM(S11:W11) -> 1079.0263 | Y11: =SUM(11081/68)*H11 -> 241.72876 | AB11: =SUM(Y11:AA11) -> 241.72876 | AC11: 7.24 | AD11: =SUM(AB11*AC11) -> 1750.1162 | AE11: =SUM(X11+AD11) -> 2829.1424 | AF11: =SUM(P11-AE11) -> 768.85756
C12: 241123000017 | D12: 45631 | E12: 黄颖 | F12: ying | G12: Nura | H12: 0.3608 | I12: 202 | J12: 792 | P12: =SUBTOTAL(9,J12) -> 792 | S12: =SUM(46963.25/68)*H12 -> 249.18148 | U12: =SUM(2500/68)*H12 -> 13.264706 | X12: =SUM(S12:W12) -> 262.44619 | Y12: =SUM(11081/68)*H12 -> 58.794482 | AB12: =SUM(Y12:AA12) -> 58.794482 | AC12: 7.24 | AD12: =SUM(AB12*AC12) -> 425.67205 | AE12: =SUM(X12+AD12) -> 688.11824 | AF12: =SUM(P12-AE12) -> 103.88176
C13: 241123000018 | D13: 45631 | E13: Bella | F13: Bella Chan | G13: zhong zi xin | H13: 11.1459 | I13: 16993 | J13: 36986 | P13: =SUBTOTAL(9,J13) -> 36986 | S13: =SUM(46963.25/68)*H13 -> 7697.7601 | U13: =SUM(2500/68)*H13 -> 409.77574 | V13: 280 | X13: =SUM(S13:W13) -> 8387.5359 | Y13: =SUM(11081/68)*H13 -> 1816.29 | Z13: 288.81 | AB13: =SUM(Y13:AA13) -> 2105.1 | AC13: 7.24 | AD13: =SUM(AB13*AC13) -> 15240.924 | AE13: =SUM(X13+AD13) -> 23628.46 | AF13: =SUM(P13-AE13) -> 13357.54
C14: 241125000061 | D14: 45631 | E14: 黄颖 | F14: ying | G14: makus | H14: 0.8795 | I14: 210 | J14: 2670.5 | P14: =SUBTOTAL(9,J14) -> 2670.5 | S14: =SUM(46963.25/68)*H14 -> 607.41439 | U14: =SUM(2500/68)*H14 -> 32.334559 | X14: =SUM(S14:W14) -> 639.74895 | Y14: =SUM(11081/68)*H14 -> 143.3197 | Z14: 104.36 | AB14: =SUM(Y14:AA14) -> 247.6797 | AC14: 7.24 | AD14: =SUM(AB14*AC14) -> 1793.201 | AE14: =SUM(X14+AD14) -> 2432.95 | AF14: =SUM(P14-AE14) -> 237.55004
C15: 241125000067 | D15: 45631 | E15: 无人 | F15: dejare James | G15: Adam e | H15: 1.0967 | I15: 203 | K15: 552736 | M15: =SUM(K15/N15) -> 1679.9977 | N15: 329.00998 | O15: 7.27 | P15: =SUM(N15*O15) -> 2391.9026 | S15: =SUM(46963.25/68)*H15 -> 757.42053 | U15: =SUM(2500/68)*H15 -> 40.319853 | X15: =SUM(S15:W15) -> 797.74039 | Y15: =SUM(11081/68)*H15 -> 178.71372 | AB15: =SUM(Y15:AA15) -> 178.71372 | AC15: 7.24 | AD15: =SUM(AB15*AC15) -> 1293.8873 | AE15: =SUM(X15+AD15) -> 2091.6277 | AF15: =SUM(P15-AE15) -> 300.27486
C16: 241127000012 | D16: 45631 | E16: 罗珮文 | F16: Shirley | G16: Yusky | H16: 3.0636 | I16: 768 | K16: 1330089.4 | M16: =SUM(K16/N16) -> 1608 | N16: 827.17 | O16: 7.3 | P16: =SUM(N16*O16) -> 6038.341 | S16: =SUM(46963.25/68)*H16 -> 2115.8325 | U16: =SUM(2500/68)*H16 -> 112.63235 | X16: =SUM(S16:W16) -> 2228.4649 | Y16: =SUM(11081/68)*H16 -> 499.23164 | AB16: =SUM(Y16:AA16) -> 499.23164 | AC16: 7.24 | AD16: =SUM(AB16*AC16) -> 3614.4371 | AE16: =SUM(X16+AD16) -> 5842.902 | AF16: =SUM(P16-AE16) -> 195.43903
C17: 241127000014 | D17: 45631 | E17: 罗珮文 | F17: Shirley | G17: Yusky | H17: 0.4158 | I17: 55 | K17: 180530.16 | M17: =SUM(K17/N17) -> 1608 | N17: 112.27 | O17: 7.3 | P17: =SUM(N17*O17) -> 819.571 | S17: =SUM(46963.25/68)*H17 -> 287.16646 | U17: =SUM(2500/68)*H17 -> 15.286765 | X17: =SUM(S17:W17) -> 302.45323 | Y17: =SUM(11081/68)*H17 -> 67.757056 | AB17: =SUM(Y17:AA17) -> 67.757056 | AC17: 7.24 | AD17: =SUM(AB17*AC17) -> 490.56108 | AE17: =SUM(X17+AD17) -> 793.01431 | AF17: =SUM(P17-AE17) -> 26.55669
C18: 241127000042 | D18: 45631 | E18: 黄颖 | F18: ying | G18: wangweijun | H18: 0.3625 | I18: 15 | J18: 870 | P18: =SUBTOTAL(9,J18) -> 870 | S18: =SUM(46963.25/68)*H18 -> 250.35556 | U18: =SUM(2500/68)*H18 -> 13.327206 | W18: =SUM(26+36) -> 62 | X18: =SUM(S18:W18) -> 325.68277 | Y18: =SUM(11081/68)*H18 -> 59.071507 | AB18: =SUM(Y18:AA18) -> 59.071507 | AC18: 7.24 | AD18: =SUM(AB18*AC18) -> 427.67771 | AE18: =SUM(X18+AD18) -> 753.36048 | AF18: =SUM(P18-AE18) -> 116.63952
C19: 241127000053 | D19: 45631 | E19: 黄颖 | F19: ying | G19: baikaibo | H19: 0.6069 | I19: 165 | J19: 2195 | P19: =SUBTOTAL(9,J19) -> 2195 | S19: =SUM(46963.25/68)*H19 -> 419.14701 | U19: =SUM(2500/68)*H19 -> 22.3125 | X19: =SUM(S19:W19) -> 441.45951 | Y19: =SUM(11081/68)*H19 -> 98.897925 | Z19: 111.31 | AB19: =SUM(Y19:AA19) -> 210.20792 | AC19: 7.24 | AD19: =SUM(AB19*AC19) -> 1521.9054 | AE19: =SUM(X19+AD19) -> 1963.3649 | AF19: =SUM(P19-AE19) -> 231.63512
C20: 241128000039 | D20: 45631 | E20: 无人 | F20: dejare James | G20: James | H20: 0.5074 | I20: 252 | K20: 239442 | M20: =SUM(K20/N20) -> 1572.9993 | N20: 152.22003 | O20: 7.27 | P20: =SUM(N20*O20) -> 1106.6396 | S20: =SUM(46963.25/68)*H20 -> 350.42872 | U20: =SUM(2500/68)*H20 -> 18.654412 | X20: =SUM(S20:W20) -> 369.08313 | Y20: =SUM(11081/68)*H20 -> 82.683815 | AB20: =SUM(Y20:AA20) -> 82.683815 | AC20: 7.24 | AD20: =SUM(AB20*AC20) -> 598.63082 | AE20: =SUM(X20+AD20) -> 967.71395 | AF20: =SUM(P20-AE20) -> 138.92567
C21: 241128000041 | D21: 45631 | E21: 黄颖 | F21: ying | G21: linxiao | H21: 0.2074 | I21: 60 | J21: 463 | P21: =SUBTOTAL(9,J21) -> 463 | S21: =SUM(46963.25/68)*H21 -> 143.23791 | U21: =SUM(2500/68)*H21 -> 7.625 | X21: =SUM(S21:W21) -> 150.86291 | Y21: =SUM(11081/68)*H21 -> 33.79705 | AB21: =SUM(Y21:AA21) -> 33.79705 | AC21: 7.24 | AD21: =SUM(AB21*AC21) -> 244.69064 | AE21: =SUM(X21+AD21) -> 395.55355 | AF21: =SUM(P21-AE21) -> 67.446445
C22: 241129000029 | D22: 45631 | E22: 陆总 | F22: 陆梓龙 | G22: xiantian | H22: 0.19 | I22: 24 | J22: 369.36 | P22: =SUBTOTAL(9,J22) -> 369.36 | S22: =SUM(46963.25/68)*H22 -> 131.22085 | U22: =SUM(2500/68)*H22 -> 6.9852941 | X22: =SUM(S22:W22) -> 138.20614 | Y22: =SUM(11081/68)*H22 -> 30.961618 | AB22: =SUM(Y22:AA22) -> 30.961618 | AC22: 7.24 | AD22: =SUM(AB22*AC22) -> 224.16211 | AE22: =SUM(X22+AD22) -> 362.36825 | AF22: =SUM(P22-AE22) -> 6.9917485
C23: 241129000035 | D23: 45631 | E23: 黄颖 | F23: ying | G23: liangdawei | H23: 0.3468 | I23: 269 | J23: 1003 | P23: =SUBTOTAL(9,J23) -> 1003 | S23: =SUM(46963.25/68)*H23 -> 239.51257 | U23: =SUM(2500/68)*H23 -> 12.75 | X23: =SUM(S23:W23) -> 252.26257 | Y23: =SUM(11081/68)*H23 -> 56.5131 | AB23: =SUM(Y23:AA23) -> 56.5131 | AC23: 7.24 | AD23: =SUM(AB23*AC23) -> 409.15484 | AE23: =SUM(X23+AD23) -> 661.41742 | AF23: =SUM(P23-AE23) -> 341.58258
C24: 241130000012 | D24: 45631 | E24: 吕沛霖 | F24: Paul | G24: Paul | H24: 0.0882 | I24: 30 | K24: 56179 | M24: =SUM(K24/N24) -> 1679.994 | N24: 33.44 | O24: 7.27 | P24: =SUM(N24*O24) -> 243.1088 | S24: =SUM(46963.25/68)*H24 -> 60.914098 | U24: =SUM(2500/68)*H24 -> 3.2426471 | X24: =SUM(S24:W24) -> 64.156745 | Y24: =SUM(11081/68)*H24 -> 14.372709 | AB24: =SUM(Y24:AA24) -> 14.372709 | AC24: 7.24 | AD24: =SUM(AB24*AC24) -> 104.05841 | AE24: =SUM(X24+AD24) -> 168.21516 | AF24: =SUM(P24-AE24) -> 74.893643
C25: 241202000005 | D25: 45631 | E25: 朱小飞 | F25: Isabel Zhu | G25: Ife Oyelami | H25: 0.8261 | I25: 59 | K25: 424545 | M25: =SUM(K25/N25) -> 1657.7959 | N25: 256.09003 | O25: 7.27 | P25: =SUM(N25*O25) -> 1861.7745 | S25: =SUM(46963.25/68)*H25 -> 570.53442 | U25: =SUM(2500/68)*H25 -> 30.371324 | X25: =SUM(S25:W25) -> 600.90575 | Y25: =SUM(11081/68)*H25 -> 134.61785 | AB25: =SUM(Y25:AA25) -> 134.61785 | AC25: 7.24 | AD25: =SUM(AB25*AC25) -> 974.63327 | AE25: =SUM(X25+AD25) -> 1575.539 | AF25: =SUM(P25-AE25) -> 286.2355
C26: 241202000011 | D26: 45631 | E26: 朱小飞 | F26: Isabel Zhu | G26: Halifa Success | H26: 0.4399 | I26: 73 | J26: 900.59 | P26: =SUBTOTAL(9,J26) -> 900.59 | S26: =SUM(46963.25/68)*H26 -> 303.81079 | U26: =SUM(2500/68)*H26 -> 16.172794 | X26: =SUM(S26:W26) -> 319.98358 | Y26: =SUM(11081/68)*H26 -> 71.684293 | AB26: =SUM(Y26:AA26) -> 71.684293 | AC26: 7.24 | AD26: =SUM(AB26*AC26) -> 518.99428 | AE26: =SUM(X26+AD26) -> 838.97786 | AF26: =SUM(P26-AE26) -> 61.612138
C27: 241202000031 | D27: 45631 | E27: 黄颖 | F27: ying | G27: Jacky | H27: 0.6255 | I27: 265 | K27: 283185 | M27: =SUM(K27/N27) -> 1588.5172 | N27: 178.27002 | O27: 7.27 | P27: =SUM(N27*O27) -> 1296.023 | S27: =SUM(46963.25/68)*H27 -> 431.99284 | U27: =SUM(2500/68)*H27 -> 22.996324 | X27: =SUM(S27:W27) -> 454.98916 | Y27: =SUM(11081/68)*H27 -> 101.9289 | AB27: =SUM(Y27:AA27) -> 101.9289 | AC27: 7.24 | AD27: =SUM(AB27*AC27) -> 737.96527 | AE27: =SUM(X27+AD27) -> 1192.9544 | AF27: =SUM(P27-AE27) -> 103.06862
C28: 241202000042 | D28: 45631 | E28: 无人 | F28: dejare James | G28: James | H28: 0.1256 | I28: 54 | K28: 63300 | M28: =SUM(K28/N28) -> 1679.9359 | N28: 37.680008 | O28: 7.27 | P28: =SUM(N28*O28) -> 273.93366 | S28: =SUM(46963.25/68)*H28 -> 86.743885 | U28: =SUM(2500/68)*H28 -> 4.6176471 | X28: =SUM(S28:W28) -> 91.361532 | Y28: =SUM(11081/68)*H28 -> 20.467259 | AB28: =SUM(Y28:AA28) -> 20.467259 | AC28: 7.24 | AD28: =SUM(AB28*AC28) -> 148.18295 | AE28: =SUM(X28+AD28) -> 239.54449 | AF28: =SUM(P28-AE28) -> 34.389172
C29: 241204000039 | D29: 45631 | E29: 陆总 | F29: 陆梓龙 | G29: xinlong | H29: 0.0608 | I29: 12 | J29: 113.83 | P29: =SUBTOTAL(9,J29) -> 113.83 | S29: =SUM(46963.25/68)*H29 -> 41.990671 | U29: =SUM(2500/68)*H29 -> 2.2352941 | X29: =SUM(S29:W29) -> 44.225965 | Y29: =SUM(11081/68)*H29 -> 9.9077176 | AB29: =SUM(Y29:AA29) -> 9.9077176 | AC29: 7.24 | AD29: =SUM(AB29*AC29) -> 71.731876 | AE29: =SUM(X29+AD29) -> 115.95784 | AF29: =SUM(P29-AE29) -> -2.1278405
C30: 241204000043 | D30: 45631 | E30: 罗珮文 | F30: Shirley | G30: Yusky | H30: 1.3963 | I30: 248 | K30: 606216 | M30: =SUM(K30/N30) -> 1608 | N30: 377 | O30: 7.3 | P30: =SUM(N30*O30) -> 2752.1 | S30: =SUM(46963.25/68)*H30 -> 964.33509 | U30: =SUM(2500/68)*H30 -> 51.334559 | X30: =SUM(S30:W30) -> 1015.6696 | Y30: =SUM(11081/68)*H30 -> 227.5353 | AB30: =SUM(Y30:AA30) -> 227.5353 | AC30: 7.24 | AD30: =SUM(AB30*AC30) -> 1647.3556 | AE30: =SUM(X30+AD30) -> 2663.0252 | AF30: =SUM(P30-AE30) -> 89.074792
C31: 241204000044 | D31: 45631 | E31: 罗珮文 | F31: Shirley | G31: Yusky | H31: 0.7235 | I31: 107 | K31: 314122.8 | M31: =SUM(K31/N31) -> 1608 | N31: 195.35 | O31: 7.3 | P31: =SUM(N31*O31) -> 1426.055 | S31: =SUM(46963.25/68)*H31 -> 499.67517 | U31: =SUM(2500/68)*H31 -> 26.599265 | X31: =SUM(S31:W31) -> 526.27443 | Y31: =SUM(11081/68)*H31 -> 117.89858 | AB31: =SUM(Y31:AA31) -> 117.89858 | AC31: 7.24 | AD31: =SUM(AB31*AC31) -> 853.58573 | AE31: =SUM(X31+AD31) -> 1379.8602 | AF31: =SUM(P31-AE31) -> 46.194842
C32: 241204000045 | D32: 45631 | E32: 罗珮文 | F32: Shirley | G32: Yusky | H32: 0.26 | I32: 48 | K32: 112929.84 | M32: =SUM(K32/N32) -> 1608 | N32: 70.23 | O32: 7.3 | P32: =SUM(N32*O32) -> 512.679 | S32: =SUM(46963.25/68)*H32 -> 179.56537 | U32: =SUM(2500/68)*H32 -> 9.5588235 | X32: =SUM(S32:W32) -> 189.12419 | Y32: =SUM(11081/68)*H32 -> 42.368529 | AB32: =SUM(Y32:AA32) -> 42.368529 | AC32: 7.24 | AD32: =SUM(AB32*AC32) -> 306.74815 | AE32: =SUM(X32+AD32) -> 495.87234 | AF32: =SUM(P32-AE32) -> 16.806656
C33: 241204000046 | D33: 45631 | E33: 罗珮文 | F33: Shirley | G33: Yusky | H33: 0.2492 | I33: 51 | K33: 108090.06 | M33: =SUM(K33/N33) -> 1606.5705 | N33: 67.28 | O33: 7.3 | P33: =SUM(N33*O33) -> 491.144 | S33: =SUM(46963.25/68)*H33 -> 172.1065 | U33: =SUM(2500/68)*H33 -> 9.1617647 | X33: =SUM(S33:W33) -> 181.26826 | Y33: =SUM(11081/68)*H33 -> 40.608606 | AB33: =SUM(Y33:AA33) -> 40.608606 | AC33: 7.24 | AD33: =SUM(AB33*AC33) -> 294.00631 | AE33: =SUM(X33+AD33) -> 475.27457 | AF33: =SUM(P33-AE33) -> 15.86943
C34: 241204000047 | D34: 45631 | E34: 罗珮文 | F34: Shirley | G34: Yusky | H34: 0.2023 | I34: 17 | K34: 87064.28 | M34: =SUM(K34/N34) -> 1594 | N34: 54.62 | O34: 7.29 | P34: =SUM(N34*O34) -> 398.1798 | S34: =SUM(46963.25/68)*H34 -> 139.71567 | U34: =SUM(2500/68)*H34 -> 7.4375 | X34: =SUM(S34:W34) -> 147.15317 | Y34: =SUM(11081/68)*H34 -> 32.965975 | AB34: =SUM(Y34:AA34) -> 32.965975 | AC34: 7.24 | AD34: =SUM(AB34*AC34) -> 238.67366 | AE34: =SUM(X34+AD34) -> 385.82683 | AF34: =SUM(P34-AE34) -> 12.352972
C35: 241204000048 | D35: 45631 | E35: 罗珮文 | F35: Shirley | G35: Yusky | H35: 0.5307 | I35: 90 | K35: 228404.26 | M35: =SUM(K35/N35) -> 1594 | N35: 143.29 | O35: 7.29 | P35: =SUM(N35*O35) -> 1044.5841 | S35: =SUM(46963.25/68)*H35 -> 366.52054 | U35: =SUM(2500/68)*H35 -> 19.511029 | X35: =SUM(S35:W35) -> 386.03157 | Y35: =SUM(11081/68)*H35 -> 86.480687 | AB35: =SUM(Y35:AA35) -> 86.480687 | AC35: 7.24 | AD35: =SUM(AB35*AC35) -> 626.12017 | AE35: =SUM(X35+AD35) -> 1012.1517 | AF35: =SUM(P35-AE35) -> 32.432358
C36: 241204000050 | D36: 45631 | E36: 罗珮文 | F36: Shirley | G36: Yusky | H36: 14.6981 | I36: 2994 | K36: 6392673.2 | M36: =SUM(K36/N36) -> 1594 | N36: 4010.46 | O36: 7.27 | P36: =SUM(N36*O36) -> 29156.044 | S36: =SUM(46963.25/68)*H36 -> 10151.037 | U36: =SUM(2500/68)*H36 -> 540.37132 | X36: =SUM(S36:W36) -> 10691.409 | Y36: =SUM(11081/68)*H36 -> 2395.1419 | AB36: =SUM(Y36:AA36) -> 2395.1419 | AC36: 7.24 | AD36: =SUM(AB36*AC36) -> 17340.827 | AE36: =SUM(X36+AD36) -> 28032.236 | AF36: =SUM(P36-AE36) -> 1123.8084
C37: 241204000052 | D37: 45631 | E37: 罗珮文 | F37: Shirley | G37: Yusky | H37: 21.052 | I37: 2202 | K37: 9257809 | M37: =SUM(K37/N37) -> 1616.7908 | N37: 5726.04 | O37: 7.22 | P37: =SUM(N37*O37) -> 41342.009 | S37: =SUM(46963.25/68)*H37 -> 14539.27 | U37: =SUM(2500/68)*H37 -> 773.97059 | X37: =SUM(S37:W37) -> 15313.24 | Y37: =SUM(11081/68)*H37 -> 3430.5472 | AB37: =SUM(Y37:AA37) -> 3430.5472 | AC37: 7.24 | AD37: =SUM(AB37*AC37) -> 24837.162 | AE37: =SUM(X37+AD37) -> 40150.402 | AF37: =SUM(P37-AE37) -> 1191.6065
C38: 241204000053 | D38: 45631 | E38: 罗珮文 | F38: Shirley | G38: Yusky | H38: 0.1958 | I38: 447 | K38: 85649.4 | M38: =SUM(K38/N38) -> 1620 | N38: 52.87 | O38: 7.22 | P38: =SUM(N38*O38) -> 381.7214 | S38: =SUM(46963.25/68)*H38 -> 135.22653 | U38: =SUM(2500/68)*H38 -> 7.1985294 | X38: =SUM(S38:W38) -> 142.42506 | Y38: =SUM(11081/68)*H38 -> 31.906762 | AB38: =SUM(Y38:AA38) -> 31.906762 | AC38: 7.24 | AD38: =SUM(AB38*AC38) -> 231.00496 | AE38: =SUM(X38+AD38) -> 373.43002 | AF38: =SUM(P38-AE38) -> 8.2913809
C39: 241204000060 | D39: 45631 | E39: 朱小飞 | F39: Isabel Zhu | G39: Halifa Success | H39: 0.6256 | I39: 144 | J39: 1269.02 | P39: =SUBTOTAL(9,J39) -> 1269.02 | S39: =SUM(46963.25/68)*H39 -> 432.0619 | U39: =SUM(2500/68)*H39 -> 23 | X39: =SUM(S39:W39) -> 455.0619 | Y39: =SUM(11081/68)*H39 -> 101.9452 | AB39: =SUM(Y39:AA39) -> 101.9452 | AC39: 7.24 | AD39: =SUM(AB39*AC39) -> 738.08325 | AE39: =SUM(X39+AD39) -> 1193.1451 | AF39: =SUM(P39-AE39) -> 75.874852
A40: JOB120375 | B40: COLL004323 | C40: 241109000014 | D40: 45636 | E40: 吕沛霖 | F40: 喵喵速运-Layne | G40: KE ZONG | H40: 1.5052 | I40: 360 | J40: 3329.55 | P40: =SUBTOTAL(9,J40) -> 3329.55 | Q40: =SUM(P40:P52) -> 166063.23 | R40: 登凯=46552.5 创泽=1215 拖车费=1670 杂费=61 过磅费=70 | S40: =SUM(49568.5/68)*H40 -> 1097.2133 | U40: =SUM(2100/68)*H40 -> 46.484118 | X40: =SUM(S40:W40) -> 1143.6974 | Y40: =SUM(11623/68)*H40 -> 257.27852 | AA40: =SUM(55.62/68)*H40 -> 1.2311651 | AB40: =SUM(Y40:AA40) -> 258.50969 | AC40: 7.3 | AD40: =SUM(AB40*AC40) -> 1887.1207 | AE40: =SUM(X40+AD40) -> 3030.8182 | AF40: =SUM(P40-AE40) -> 298.73183
C41: 241127000004 | D41: 45636 | E41: 吕沛霖 | F41: 喵喵速运-Layne | G41: Candice Ding | H41: 2.3335 | I41: 2600 | K41: 1863312 | M41: =SUM(K41/N41) -> 1600 | N41: 1164.57 | O41: 7.28 | P41: =SUM(N41*O41) -> 8478.0696 | S41: =SUM(49568.5/68)*H41 -> 1701.0014 | U41: =SUM(2100/68)*H41 -> 72.063971 | X41: =SUM(S41:W41) -> 1773.0654 | Y41: =SUM(11623/68)*H41 -> 398.85692 | AA41: =SUM(55.62/68)*H41 -> 1.9086657 | AB41: =SUM(Y41:AA41) -> 400.76558 | AC41: 7.3 | AD41: =SUM(AB41*AC41) -> 2925.5888 | AE41: =SUM(X41+AD41) -> 4698.6541 | AF41: =SUM(P41-AE41) -> 3779.4155
C42: 241128000012 | D42: 45636 | E42: Bella | F42: Bella Chan | G42: FENG | H42: 0.196 | I42: 106 | K42: 98784 | M42: =SUM(K42/N42) -> 1679.9994 | N42: 58.80002 | O42: 7.3 | P42: =SUM(N42*O42) -> 429.24015 | S42: =SUM(49568.5/68)*H42 -> 142.87391 | U42: =SUM(2100/68)*H42 -> 6.0529412 | X42: =SUM(S42:W42) -> 148.92685 | Y42: =SUM(11623/68)*H42 -> 33.501588 | AA42: =SUM(55.62/68)*H42 -> 0.16031647 | AB42: =SUM(Y42:AA42) -> 33.661905 | AC42: 7.3 | AD42: =SUM(AB42*AC42) -> 245.7319 | AE42: =SUM(X42+AD42) -> 394.65876 | AF42: =SUM(P42-AE42) -> 34.581389
C43: 241202000044 | D43: 45636 | E43: 黄颖 | F43: ying | G43: Jacky | H43: 3.774 | I43: 1521 | K43: 1698783.8 | M43: =SUM(K43/N43) -> 1579.397 | N43: 1075.5901 | O43: 7.27 | P43: =SUM(N43*O43) -> 7819.54 | S43: =SUM(49568.5/68)*H43 -> 2751.0518 | U43: =SUM(2100/68)*H43 -> 116.55 | X43: =SUM(S43:W43) -> 2867.6017 | Y43: =SUM(11623/68)*H43 -> 645.0765 | AA43: =SUM(55.62/68)*H43 -> 3.08691 | AB43: =SUM(Y43:AA43) -> 648.16341 | AC43: 7.3 | AD43: =SUM(AB43*AC43) -> 4731.5929 | AE43: =SUM(X43+AD43) -> 7599.1946 | AF43: =SUM(P43-AE43) -> 220.34538
C44: 241203000015 | D44: 45636 | E44: Bella | F44: Bella Chan | G44: zhong zi xin | H44: 7.8671 | I44: 16682 | J44: 33835.5 | P44: =SUM(J44) -> 33835.5 | S44: =SUM(49568.5/68)*H44 -> 5734.711 | U44: =SUM(2100/68)*H44 -> 242.95456 | X44: =SUM(S44:W44) -> 5977.6655 | Y44: =SUM(11623/68)*H44 -> 1344.6956 | AA44: =SUM(55.62/68)*H44 -> 6.434825 | AB44: =SUM(Y44:AA44) -> 1351.1305 | AC44: 7.3 | AD44: =SUM(AB44*AC44) -> 9863.2524 | AE44: =SUM(X44+AD44) -> 15840.918 | AF44: =SUM(P44-AE44) -> 17994.582
C45: 241204000049 | D45: 45636 | E45: 罗珮文 | F45: Shirley | G45: Yusky | H45: 14.985 | I45: 2696 | K45: 6707917.9 | M45: =SUM(K45/N45) -> 1582.8774 | N45: 4237.8 | O45: 7.18 | P45: =SUM(N45*O45) -> 30427.404 | S45: =SUM(49568.5/68)*H45 -> 10923.294 | U45: =SUM(2100/68)*H45 -> 462.77206 | X45: =SUM(S45:W45) -> 11386.066 | Y45: =SUM(11623/68)*H45 -> 2561.3332 | AA45: =SUM(55.62/68)*H45 -> 12.256849 | AB45: =SUM(Y45:AA45) -> 2573.59 | AC45: 7.3 | AD45: =SUM(AB45*AC45) -> 18787.207 | AE45: =SUM(X45+AD45) -> 30173.273 | AF45: =SUM(P45-AE45) -> 254.13115
C46: 241204000051 | D46: 45636 | E46: 罗珮文 | F46: Shirley | G46: Yusky | H46: 2.1818 | I46: 358 | K46: 966443.8 | M46: =SUM(K46/N46) -> 1582 | N46: 610.9 | O46: 7.18 | P46: =SUM(N46*O46) -> 4386.262 | S46: =SUM(49568.5/68)*H46 -> 1590.4199 | U46: =SUM(2100/68)*H46 -> 67.379118 | X46: =SUM(S46:W46) -> 1657.799 | Y46: =SUM(11623/68)*H46 -> 372.92737 | AA46: =SUM(55.62/68)*H46 -> 1.7845841 | AB46: =SUM(Y46:AA46) -> 374.71196 | AC46: 7.3 | AD46: =SUM(AB46*AC46) -> 2735.3973 | AE46: =SUM(X46+AD46) -> 4393.1963 | AF46: =SUM(P46-AE46) -> -6.9343095
C47: 241205000007 | D47: 45636 | E47: 黄颖 | F47: ying | G47: Jacky | H47: 1.2288 | I47: 508 | K47: 552776.25 | M47: =SUM(K47/N47) -> 1578.4138 | N47: 350.20996 | O47: 7.27 | P47: =SUM(N47*O47) -> 2546.0264 | S47: =SUM(49568.5/68)*H47 -> 895.73195 | U47: =SUM(2100/68)*H47 -> 37.948235 | X47: =SUM(S47:W47) -> 933.68019 | Y47: =SUM(11623/68)*H47 -> 210.03445 | AA47: =SUM(55.62/68)*H47 -> 1.0050861 | AB47: =SUM(Y47:AA47) -> 211.03953 | AC47: 7.3 | AD47: =SUM(AB47*AC47) -> 1540.5886 | AE47: =SUM(X47+AD47) -> 2474.2688 | AF47: =SUM(P47-AE47) -> 71.757629
C48: 241206000037 | D48: 45636 | E48: Sam.Pao | F48: Sam.Pao | G48: Mr. Jiang | H48: 0.6414 | I48: 108 | J48: 2673 | P48: =SUBTOTAL(9,J48) -> 2673 | S48: =SUM(49568.5/68)*H48 -> 467.54759 | U48: =SUM(2100/68)*H48 -> 19.807941 | V48: 300 | X48: =SUM(S48:W48) -> 787.35553 | Y48: =SUM(11623/68)*H48 -> 109.63224 | AA48: =SUM(55.62/68)*H48 -> 0.52462747 | AB48: =SUM(Y48:AA48) -> 110.15687 | AC48: 7.3 | AD48: =SUM(AB48*AC48) -> 804.14512 | AE48: =SUM(X48+AD48) -> 1591.5006 | AF48: =SUM(P48-AE48) -> 1081.4994
C49: 241206000040 | D49: 45636 | E49: Sam.Pao | F49: Sam.Pao | G49: Mr. Jiang | H49: 0.7876 | I49: 213 | J49: 2732 | P49: =SUBTOTAL(9,J49) -> 2732 | S49: =SUM(49568.5/68)*H49 -> 574.11986 | U49: =SUM(2100/68)*H49 -> 24.322941 | V49: 300 | X49: =SUM(S49:W49) -> 898.4428 | Y49: =SUM(11623/68)*H49 -> 134.62169 | AA49: =SUM(55.62/68)*H49 -> 0.64421047 | AB49: =SUM(Y49:AA49) -> 135.2659 | AC49: 7.3 | AD49: =SUM(AB49*AC49) -> 987.44106 | AE49: =SUM(X49+AD49) -> 1885.8839 | AF49: =SUM(P49-AE49) -> 846.11614
C50: 241216000026 | D50: 45638 | E50: 陆总 | F50: 陆梓龙 | G50: luk | H50: 12.7436 | I50: 1324.23 | J50: 22939.2 | P50: =SUBTOTAL(9,J50) -> 22939.2 | S50: =SUM(49568.5/68)*H50 -> 9289.4285 | U50: =SUM(2100/68)*H50 -> 393.55235 | X50: =SUM(S50:W50) -> 9682.9808 | Y50: =SUM(11623/68)*H50 -> 2178.2186 | AA50: =SUM(55.62/68)*H50 -> 10.423515 | AB50: =SUM(Y50:AA50) -> 2188.6421 | AC50: 7.3 | AD50: =SUM(AB50*AC50) -> 15977.087 | AE50: =SUM(X50+AD50) -> 25660.068 | AF50: =SUM(P50-AE50) -> -2720.8681
C51: 241208000009 | D51: 45636 | E51: 无人 | F51: Mailmail Abv sales person 1 | G51: Obetta U | H51: 4.1388 | I51: 540 | K51: 2050281 | M51: =SUM(K51/N51) -> 1597.9993 | N51: 1283.03 | O51: 7.27 | P51: =SUM(N51*O51) -> 9327.6281 | S51: =SUM(49568.5/68)*H51 -> 3016.9722 | U51: =SUM(2100/68)*H51 -> 127.81588 | X51: =SUM(S51:W51) -> 3144.7881 | Y51: =SUM(11623/68)*H51 -> 707.43048 | AA51: =SUM(55.62/68)*H51 -> 3.3852949 | AB51: =SUM(Y51:AA51) -> 710.81577 | AC51: 7.3 | AD51: =SUM(AB51*AC51) -> 5188.9551 | AE51: =SUM(X51+AD51) -> 8333.7432 | AF51: =SUM(P51-AE51) -> 993.88491
C52: 241210000005 | D52: 45636 | E52: 罗珮文 | F52: Shirley | G52: Abubakar Badaru Abubakar | H52: 17.6161 | I52: 1662 | K52: 7918392 | M52: =SUM(K52/N52) -> 1550 | N52: 5108.64 | O52: 7.27 | P52: =SUM(N52*O52) -> 37139.813 | S52: =SUM(49568.5/68)*H52 -> 12841.23 | U52: =SUM(2100/68)*H52 -> 544.02662 | V52: 200 | X52: =SUM(S52:W52) -> 13585.257 | Y52: =SUM(11623/68)*H52 -> 3011.0578 | AA52: =SUM(55.62/68)*H52 -> 14.408934 | AB52: =SUM(Y52:AA52) -> 3025.4667 | AC52: 7.3 | AD52: =SUM(AB52*AC52) -> 22085.907 | AE52: =SUM(X52+AD52) -> 35671.164 | AF52: =SUM(P52-AE52) -> 1468.6488
A53: JOB120376 | B53: COLL004324 | C53: 241122000025 | D53: 45636 | E53: 吕沛霖 | F53: 喵喵速运-Layne | G53: WENDY | H53: 3.6276 | I53: 1507 | K53: 2696680 | M53: =SUM(K53/N53) -> 1630.0048 | N53: 1654.4 | O53: 7.27 | P53: =SUM(N53*O53) -> 12027.488 | Q53: =SUM(P53:P60) -> 148560.87 | R53: 登凯=46552.5 报关=500 拖车费=1670 杂费=61 过磅费=68 | S53: =SUM(48851.5/68)*H53 -> 2606.0838 | U53: =SUM(1000/68)*H53 -> 53.347059 | X53: =SUM(S53:W53) -> 2659.4309 | Y53: =SUM(11570.25/68)*H53 -> 617.23881 | Z53: 315.51 | AA53: =SUM(140.12/68)*H53 -> 7.4749899 | AB53: =SUM(Y53:AA53) -> 940.2238 | AC53: 7.25 | AD53: =SUM(AB53*AC53) -> 6816.6225 | AE53: =SUM(X53+AD53) -> 9476.0534 | AF53: =SUM(P53-AE53) -> 2551.4346
C54: 241202000029 | D54: 45636 | E54: 吕沛霖 | F54: 喵喵速运-Layne | G54: Mr. Wen Pu | H54: 8.2313 | I54: 1683 | K54: 4862127 | M54: =SUM(K54/N54) -> 1630 | N54: 2982.9 | O54: 7.28 | P54: =SUM(N54*O54) -> 21715.512 | S54: =SUM(48851.5/68)*H54 -> 5913.4022 | U54: =SUM(1000/68)*H54 -> 121.04853 | X54: =SUM(S54:W54) -> 6034.4508 | Y54: =SUM(11570.25/68)*H54 -> 1400.5617 | Z54: 715.9 | AA54: =SUM(140.12/68)*H54 -> 16.96132 | AB54: =SUM(Y54:AA54) -> 2133.4231 | AC54: 7.25 | AD54: =SUM(AB54*AC54) -> 15467.317 | AE54: =SUM(X54+AD54) -> 21501.768 | AF54: =SUM(P54-AE54) -> 213.744
C55: 241203000014 | D55: 45636 | E55: Bella | F55: Bella Chan | G55: zhong zi xin | H55: 13.3392 | I55: 17441 | J55: 35368.5 | P55: =SUM(J55) -> 35368.5 | S55: =SUM(48851.5/68)*H55 -> 9582.9401 | U55: =SUM(1000/68)*H55 -> 196.16471 | X55: =SUM(S55:W55) -> 9779.1048 | Y55: =SUM(11570.25/68)*H55 -> 2269.6747 | AA55: =SUM(140.12/68)*H55 -> 27.486599 | AB55: =SUM(Y55:AA55) -> 2297.1613 | AC55: 7.25 | AD55: =SUM(AB55*AC55) -> 16654.419 | AE55: =SUM(X55+AD55) -> 26433.524 | AF55: =SUM(P55-AE55) -> 8934.9758
C56: 241204000017 | D56: 45636 | E56: 吕沛霖 | F56: 喵喵速运-Layne | G56: Frank | H56: 0.5672 | I56: 104 | K56: 270180 | M56: =SUM(K56/N56) -> 1580 | N56: 171 | O56: 7.29 | P56: =SUM(N56*O56) -> 1246.59 | S56: =SUM(48851.5/68)*H56 -> 407.47898 | U56: =SUM(1000/68)*H56 -> 8.3411765 | X56: =SUM(S56:W56) -> 415.82016 | Y56: =SUM(11570.25/68)*H56 -> 96.509497 | Z56: 49.33 | AA56: =SUM(140.12/68)*H56 -> 1.1687656 | AB56: =SUM(Y56:AA56) -> 147.00826 | AC56: 7.25 | AD56: =SUM(AB56*AC56) -> 1065.8099 | AE56: =SUM(X56+AD56) -> 1481.6301 | AF56: =SUM(P56-AE56) -> -235.04006
C57: 241209000071 | D57: 45636 | E57: Sam.Pao | F57: Sam.Pao | G57: ShanShan | H57: 0.1971 | I57: 30.5 | J57: 788.4 | P57: =SUBTOTAL(9,J57) -> 788.4 | S57: =SUM(48851.5/68)*H57 -> 141.59751 | U57: =SUM(1000/68)*H57 -> 2.8985294 | X57: =SUM(S57:W57) -> 144.49604 | Y57: =SUM(11570.25/68)*H57 -> 33.53671 | Z57: 0.84 | AA57: =SUM(140.12/68)*H57 -> 0.40614194 | AB57: =SUM(Y57:AA57) -> 34.782852 | AC57: 7.25 | AD57: =SUM(AB57*AC57) -> 252.17568 | AE57: =SUM(X57+AD57) -> 396.67172 | AF57: =SUM(P57-AE57) -> 391.72828
C58: 241216000026 | D58: 45638 | E58: 陆总 | F58: 陆梓龙 | G58: luk | H58: 11.0893 | I58: 1146.94 | J58: 19958.4 | P58: =SUBTOTAL(9,J58) -> 19958.4 | S58: =SUM(48851.5/68)*H58 -> 7966.602 | U58: =SUM(1000/68)*H58 -> 163.07794 | X58: =SUM(S58:W58) -> 8129.68 | Y58: =SUM(11570.25/68)*H58 -> 1886.8525 | AA58: =SUM(140.12/68)*H58 -> 22.850481 | AB58: =SUM(Y58:AA58) -> 1909.703 | AC58: 7.25 | AD58: =SUM(AB58*AC58) -> 13845.347 | AE58: =SUM(X58+AD58) -> 21975.027 | AF58: =SUM(P58-AE58) -> -2016.627
C59: 241210000006 | D59: 45636 | E59: 罗珮文 | F59: Shirley | G59: SKY JET | H59: 35.4 | I59: 5354 | J59: 56540.88 | P59: =SUBTOTAL(9,J59) -> 56540.88 | S59: =SUM(48851.5/68)*H59 -> 25431.516 | U59: =SUM(1000/68)*H59 -> 520.58824 | X59: =SUM(S59:W59) -> 25952.104 | Y59: =SUM(11570.25/68)*H59 -> 6023.336 | AA59: =SUM(140.12/68)*H59 -> 72.944824 | AB59: =SUM(Y59:AA59) -> 6096.2809 | AC59: 7.25 | AD59: =SUM(AB59*AC59) -> 44198.036 | AE59: =SUM(X59+AD59) -> 70150.141 | AF59: =SUM(P59-AE59) -> -13609.261
C60: 241216000056 | D60: 45636 | E60: 吕沛霖 | F60: 喵喵速运-Layne | G60: LEO WEI | H60: 0.3809 | I60: 90 | K60: 197726.1 | M60: =SUM(K60/N60) -> 1573 | N60: 125.7 | O60: 7.28 | P60: =SUM(N60*O60) -> 915.096 | S60: =SUM(48851.5/68)*H60 -> 273.64024 | U60: =SUM(1000/68)*H60 -> 5.6014706 | X60: =SUM(S60:W60) -> 279.24171 | Y60: =SUM(11570.25/68)*H60 -> 64.810415 | AA60: =SUM(140.12/68)*H60 -> 0.78487806 | AB60: =SUM(Y60:AA60) -> 65.595293 | AC60: 7.25 | AD60: =SUM(AB60*AC60) -> 475.56588 | AE60: =SUM(X60+AD60) -> 754.80759 | AF60: =SUM(P60-AE60) -> 160.28841
A61: JOB120381 | B61: COLL004325 | C61: 241023000034 | D61: 45638 | E61: Sam.Pao | F61: Sam.Pao | G61: Nick Wang | H61: 0.3134 | I61: 126 | J61: 906 | P61: =SUBTOTAL(9,J61) -> 906 | Q61: =SUM(P61:P70) -> 146435.81 | R61: 登凯=46552.5 报关=300 拖车费=1670 杂费=166 过磅费=71 | S61: =SUM(48759.5/68)*H61 -> 224.72393 | U61: =SUM(1800/68)*H61 -> 8.2958824 | X61: =SUM(S61:W61) -> 233.01981 | Y61: =SUM(11621.97/68)*H61 -> 53.563609 | AA61: =SUM(140.12/68)*H61 -> 0.64578835 | AB61: =SUM(Y61:AA61) -> 54.209397 | AC61: 7.25 | AD61: =SUM(AB61*AC61) -> 393.01813 | AE61: =SUM(X61+AD61) -> 626.03794 | AF61: =SUM(P61-AE61) -> 279.96206
C62: 241115000013 | D62: 45638 | E62: Sam.Pao | F62: Sam.Pao | G62: ChenGaoHong | H62: 0.367 | I62: 106 | J62: 780 | P62: =SUBTOTAL(9,J62) -> 780 | S62: =SUM(48759.5/68)*H62 -> 263.15789 | U62: =SUM(1800/68)*H62 -> 9.7147059 | V62: 240 | X62: =SUM(S62:W62) -> 512.8726 | Y62: =SUM(11621.97/68)*H62 -> 62.724456 | AA62: =SUM(140.12/68)*H62 -> 0.75623588 | AB62: =SUM(Y62:AA62) -> 63.480692 | AC62: 7.25 | AD62: =SUM(AB62*AC62) -> 460.23501 | AE62: =SUM(X62+AD62) -> 973.10761 | AF62: =SUM(P62-AE62) -> -193.10761
C63: 241126000049 | D63: 45638 | E63: Sam.Pao | F63: Sam.Pao | G63: AiGeLi | H63: 2.7422 | I63: 1148 | J63: 7878 | P63: =SUBTOTAL(9,J63) -> 7878 | S63: =SUM(48759.5/68)*H63 -> 1966.2985 | U63: =SUM(1800/68)*H63 -> 72.587647 | V63: 1000 | X63: =SUM(S63:W63) -> 3038.8862 | Y63: =SUM(11621.97/68)*H63 -> 468.67303 | AA63: =SUM(140.12/68)*H63 -> 5.6505451 | AB63: =SUM(Y63:AA63) -> 474.32358 | AC63: 7.25 | AD63: =SUM(AB63*AC63) -> 3438.8459 | AE63: =SUM(X63+AD63) -> 6477.7321 | AF63: =SUM(P63-AE63) -> 1400.2679
C64: 241209000082 | D64: 45638 | E64: 吕沛霖 | F64: 喵喵速运-Layne | G64: BI AN | H64: 2.4778 | I64: 1373 | J64: 6015.2 | P64: =SUBTOTAL(9,J64) -> 6015.2 | S64: =SUM(48759.5/68)*H64 -> 1776.7101 | U64: =SUM(1800/68)*H64 -> 65.588824 | X64: =SUM(S64:W64) -> 1842.299 | Y64: =SUM(11621.97/68)*H64 -> 423.48408 | AA64: =SUM(140.12/68)*H64 -> 5.1057255 | AB64: =SUM(Y64:AA64) -> 428.5898 | AC64: 7.25 | AD64: =SUM(AB64*AC64) -> 3107.2761 | AE64: =SUM(X64+AD64) -> 4949.575 | AF64: =SUM(P64-AE64) -> 1065.625
C65: 241209000084 | D65: 45638 | E65: 罗珮文 | F65: Shirley | G65: Yusky | H65: 3.5753 | I65: 397 | K65: 1527152.1 | M65: =SUM(K65/N65) -> 1582 | N65: 965.33 | O65: 7.18 | P65: =SUM(N65*O65) -> 6931.0694 | S65: =SUM(48759.5/68)*H65 -> 2563.6741 | U65: =SUM(1800/68)*H65 -> 94.640294 | X65: =SUM(S65:W65) -> 2658.3144 | Y65: =SUM(11621.97/68)*H65 -> 611.05926 | AA65: =SUM(140.12/68)*H65 -> 7.3672211 | AB65: =SUM(Y65:AA65) -> 618.42648 | AC65: 7.25 | AD65: =SUM(AB65*AC65) -> 4483.592 | AE65: =SUM(X65+AD65) -> 7141.9064 | AF65: =SUM(P65-AE65) -> -210.83697
C66: 241211000002 | D66: 45638 | E66: Bella | F66: Bella Chan | G66: zhong zi xin | H66: 13.0793 | I66: 19192 | J66: 38909 | P66: =SUM(J66) -> 38909 | S66: =SUM(48759.5/68)*H66 -> 9378.5313 | U66: =SUM(1800/68)*H66 -> 346.21676 | X66: =SUM(S66:W66) -> 9724.7481 | Y66: =SUM(11621.97/68)*H66 -> 2235.4005 | AA66: =SUM(140.12/68)*H66 -> 26.951052 | AB66: =SUM(Y66:AA66) -> 2262.3515 | AC66: 7.25 | AD66: =SUM(AB66*AC66) -> 16402.049 | AE66: =SUM(X66+AD66) -> 26126.797 | AF66: =SUM(P66-AE66) -> 12782.203
C67: 241211000045 | D67: 45638 | E67: 罗珮文 | F67: Shirley | G67: Yusky | H67: 10.4649 | I67: 835 | K67: 4470020.1 | M67: =SUM(K67/N67) -> 1582 | N67: 2825.55 | O67: 7.18 | P67: =SUM(N67*O67) -> 20287.449 | S67: =SUM(48759.5/68)*H67 -> 7503.8719 | U67: =SUM(1800/68)*H67 -> 277.01206 | X67: =SUM(S67:W67) -> 7780.884 | Y67: =SUM(11621.97/68)*H67 -> 1788.5699 | AA67: =SUM(140.12/68)*H67 -> 21.56385 | AB67: =SUM(Y67:AA67) -> 1810.1338 | AC67: 7.25 | AD67: =SUM(AB67*AC67) -> 13123.47 | AE67: =SUM(X67+AD67) -> 20904.354 | AF67: =SUM(P67-AE67) -> -616.90475
C68: 241212000002 | D68: 45638 | E68: 罗珮文 | F68: Shirley | G68: SKY JET | H68: 29.57 | I68: 4902 | J68: 47229.2 | P68: =SUBTOTAL(9,J68) -> 47229.2 | S68: =SUM(48759.5/68)*H68 -> 21203.212 | U68: =SUM(1800/68)*H68 -> 782.73529 | X68: =SUM(S68:W68) -> 21985.947 | Y68: =SUM(11621.97/68)*H68 -> 5053.8478 | AA68: =SUM(140.12/68)*H68 -> 60.931594 | AB68: =SUM(Y68:AA68) -> 5114.7794 | AC68: 7.25 | AD68: =SUM(AB68*AC68) -> 37082.151 | AE68: =SUM(X68+AD68) -> 59068.098 | AF68: =SUM(P68-AE68) -> -11838.898
C69: 241212000013 | D69: 45638 | E69: 陆总 | F69: 陆梓龙 | G69: luk | H69: 0.0957 | I69: 26 | J69: 186.05 | P69: =SUBTOTAL(9,J69) -> 186.05 | S69: =SUM(48759.5/68)*H69 -> 68.621826 | U69: =SUM(1800/68)*H69 -> 2.5332353 | X69: =SUM(S69:W69) -> 71.155061 | Y69: =SUM(11621.97/68)*H69 -> 16.356214 | AA69: =SUM(140.12/68)*H69 -> 0.19719829 | AB69: =SUM(Y69:AA69) -> 16.553412 | AC69: 7.25 | AD69: =SUM(AB69*AC69) -> 120.01224 | AE69: =SUM(X69+AD69) -> 191.1673 | AF69: =SUM(P69-AE69) -> -5.1172977
C70: 241216000026 | D70: 45638 | E70: 陆总 | F70: 陆梓龙 | G70: luk | H70: 9.6179 | I70: 931.83 | J70: 17313.84 | P70: =SUBTOTAL(9,J70) -> 17313.84 | S70: =SUM(48759.5/68)*H70 -> 6896.5293 | U70: =SUM(1800/68)*H70 -> 254.59147 | X70: =SUM(S70:W70) -> 7151.1208 | Y70: =SUM(11621.97/68)*H70 -> 1643.808 | AA70: =SUM(140.12/68)*H70 -> 19.818532 | AB70: =SUM(Y70:AA70) -> 1663.6266 | AC70: 7.25 | AD70: =SUM(AB70*AC70) -> 12061.292 | AE70: =SUM(X70+AD70) -> 19212.413 | AF70: =SUM(P70-AE70) -> -1898.5733
A71: JOB120387 | B71: COLL004326 | C71: 241127000030 | D71: 45643 | E71: 黄颖 | F71: ying | G71: baikaibo | H71: 0.4598 | I71: 114 | J71: 860.5 | P71: =SUBTOTAL(9,J71) -> 860.5 | Q71: =SUM(P71:P93) -> 185884.77 | R71: 登凯=45460.5 报关=2800 拖车费=1670 杂费=86 过磅费=64 | S71: =SUM(50080.5/68)*H71 -> 338.63256 | U71: =SUM(2000/68)*H71 -> 13.523529 | X71: =SUM(S71:W71) -> 352.15609 | Y71: =SUM(12270/68)*H71 -> 82.966853 | Z71: 76.28 | AA71: =SUM(55.42/68)*H71 -> 0.374737 | AB71: =SUM(Y71:AA71) -> 159.62159 | AC71: 7.25 | AD71: =SUM(AB71*AC71) -> 1157.2565 | AE71: =SUM(X71+AD71) -> 1509.4126 | AF71: =SUM(P71-AE71) -> -648.91261
C72: 241209000067 | D72: 45643 | E72: Sam.Pao | F72: Sam.Pao | G72: MaiKaiNian | H72: 0.023 | I72: 43 | J72: 152.5 | P72: =SUBTOTAL(9,J72) -> 152.5 | S72: =SUM(50080.5/68)*H72 -> 16.938993 | U72: =SUM(2000/68)*H72 -> 0.67647059 | X72: =SUM(S72:W72) -> 17.615463 | Y72: =SUM(12270/68)*H72 -> 4.1501471 | AA72: =SUM(55.42/68)*H72 -> 0.018745 | AB72: =SUM(Y72:AA72) -> 4.1688921 | AC72: 7.25 | AD72: =SUM(AB72*AC72) -> 30.224467 | AE72: =SUM(X72+AD72) -> 47.839931 | AF72: =SUM(P72-AE72) -> 104.66007
C73: 241209000092 | D73: 45643 | E73: 黄颖 | F73: ying | G73: yuhuichao | H73: 0.1652 | I73: 33 | J73: 565 | P73: =SUBTOTAL(9,J73) -> 565 | S73: =SUM(50080.5/68)*H73 -> 121.66616 | U73: =SUM(2000/68)*H73 -> 4.8588235 | X73: =SUM(S73:W73) -> 126.52498 | Y73: =SUM(12270/68)*H73 -> 29.808882 | Z73: 19.6 | AA73: =SUM(55.42/68)*H73 -> 0.134638 | AB73: =SUM(Y73:AA73) -> 49.54352 | AC73: 7.25 | AD73: =SUM(AB73*AC73) -> 359.19052 | AE73: =SUM(X73+AD73) -> 485.7155 | AF73: =SUM(P73-AE73) -> 79.284498
C74: 241210000030 | D74: 45643 | E74: 黄颖 | F74: ying | G74: Frank | H74: 0.5114 | I74: 65 | K74: 312494 | M74: =SUM(K74/N74) -> 1651.485 | N74: 189.22 | O74: 7.27 | P74: =SUM(N74*O74) -> 1375.6294 | S74: =SUM(50080.5/68)*H74 -> 376.63482 | U74: =SUM(2000/68)*H74 -> 15.041176 | X74: =SUM(S74:W74) -> 391.676 | Y74: =SUM(12270/68)*H74 -> 92.277618 | AA74: =SUM(55.42/68)*H74 -> 0.416791 | AB74: =SUM(Y74:AA74) -> 92.694409 | AC74: 7.25 | AD74: =SUM(AB74*AC74) -> 672.03446 | AE74: =SUM(X74+AD74) -> 1063.7105 | AF74: =SUM(P74-AE74) -> 311.91894
C75: 241210000041 | D75: 45643 | E75: 黄颖 | F75: ying | G75: Mr Rell | H75: 0.7637 | I75: 207 | J75: 1810.4 | P75: =SUBTOTAL(9,J75) -> 1810.4 | S75: =SUM(50080.5/68)*H75 -> 562.4482 | U75: =SUM(2000/68)*H75 -> 22.461765 | X75: =SUM(S75:W75) -> 584.90997 | Y75: =SUM(12270/68)*H75 -> 137.80293 | AA75: =SUM(55.42/68)*H75 -> 0.6224155 | AB75: =SUM(Y75:AA75) -> 138.42534 | AC75: 7.25 | AD75: =SUM(AB75*AC75) -> 1003.5837 | AE75: =SUM(X75+AD75) -> 1588.4937 | AF75: =SUM(P75-AE75) -> 221.9063
C76: 241211000027 | D76: 45643 | E76: Sam.Pao | F76: Sam.Pao | G76: ShanShan | H76: 23.8172 | I76: 4565 | J76: 54267 | P76: =SUBTOTAL(9,J76) -> 54267 | S76: =SUM(50080.5/68)*H76 -> 17540.842 | U76: =SUM(2000/68)*H76 -> 700.50588 | X76: =SUM(S76:W76) -> 18241.348 | Y76: =SUM(12270/68)*H76 -> 4297.6036 | Z76: 136.87 | AA76: =SUM(55.42/68)*H76 -> 19.411018 | AB76: =SUM(Y76:AA76) -> 4453.8846 | AC76: 7.25 | AD76: =SUM(AB76*AC76) -> 32290.663 | AE76: =SUM(X76+AD76) -> 50532.012 | AF76: =SUM(P76-AE76) -> 3734.9883
C77: 241212000006 | D77: 45643 | E77: 黄颖 | F77: ying | G77: MISS Huang | H77: 3.0701 | I77: 1383 | K77: 1406444 | M77: =SUM(K77/N77) -> 1607.4013 | N77: 874.98 | O77: 7.3 | P77: =SUM(N77*O77) -> 6387.354 | S77: =SUM(50080.5/68)*H77 -> 2261.0609 | U77: =SUM(2000/68)*H77 -> 90.297059 | X77: =SUM(S77:W77) -> 2351.358 | Y77: =SUM(12270/68)*H77 -> 553.97246 | AA77: =SUM(55.42/68)*H77 -> 2.5021315 | AB77: =SUM(Y77:AA77) -> 556.47459 | AC77: 7.25 | AD77: =SUM(AB77*AC77) -> 4034.4408 | AE77: =SUM(X77+AD77) -> 6385.7987 | AF77: =SUM(P77-AE77) -> 1.5552554
C78: 241212000015 | D78: 45643 | E78: Sam.Pao | F78: Sam.Pao | G78: MaiKaiNian | H78: 2.957 | I78: 1339 | J78: 7123.63 | P78: =SUBTOTAL(9,J78) -> 7123.63 | S78: =SUM(50080.5/68)*H78 -> 2177.7653 | U78: =SUM(2000/68)*H78 -> 86.970588 | X78: =SUM(S78:W78) -> 2264.7359 | Y78: =SUM(12270/68)*H78 -> 533.56456 | AA78: =SUM(55.42/68)*H78 -> 2.409955 | AB78: =SUM(Y78:AA78) -> 535.97451 | AC78: 7.25 | AD78: =SUM(AB78*AC78) -> 3885.8152 | AE78: =SUM(X78+AD78) -> 6150.5511 | AF78: =SUM(P78-AE78) -> 973.07891
C79: 241213000032 | D79: 45643 | E79: 黄颖 | F79: ying | G79: sven | H79: 1.137 | I79: 240 | J79: 2906 | P79: =SUBTOTAL(9,J79) -> 2906 | S79: =SUM(50080.5/68)*H79 -> 837.37542 | U79: =SUM(2000/68)*H79 -> 33.441176 | X79: =SUM(S79:W79) -> 870.8166 | Y79: =SUM(12270/68)*H79 -> 205.16162 | Z79: 41.99 | AA79: =SUM(55.42/68)*H79 -> 0.926655 | AB79: =SUM(Y79:AA79) -> 248.07827 | AC79: 7.25 | AD79: =SUM(AB79*AC79) -> 1798.5675 | AE79: =SUM(X79+AD79) -> 2669.3841 | AF79: =SUM(P79-AE79) -> 236.61593
C80: 241213000053 | D80: 45643 | E80: 黄颖 | F80: ying | G80: sven | H80: 0.0959 | I80: 16 | J80: 228 | P80: =SUBTOTAL(9,J80) -> 228 | S80: =SUM(50080.5/68)*H80 -> 70.628235 | U80: =SUM(2000/68)*H80 -> 2.8205882 | X80: =SUM(S80:W80) -> 73.448823 | Y80: =SUM(12270/68)*H80 -> 17.304309 | Z80: 35.58 | AA80: =SUM(55.42/68)*H80 -> 0.0781585 | AB80: =SUM(Y80:AA80) -> 52.962467 | AC80: 7.25 | AD80: =SUM(AB80*AC80) -> 383.97789 | AE80: =SUM(X80+AD80) -> 457.42671 | AF80: =SUM(P80-AE80) -> -229.42671
C81: 241213000056 | D81: 45643 | E81: 无人 | F81: dejare James | G81: James | H81: 1.2461 | I81: 230 | K81: 116181 | L81: 300 | M81: =SUM(K81/N81) -> 310.76071 | N81: 373.86 | O81: 7.27 | P81: =SUM(N81*O81) -> 2717.9622 | S81: =SUM(50080.5/68)*H81 -> 917.72516 | U81: =SUM(2000/68)*H81 -> 36.65 | X81: =SUM(S81:W81) -> 954.37516 | Y81: =SUM(12270/68)*H81 -> 224.84775 | AA81: =SUM(55.42/68)*H81 -> 1.0155715 | AB81: =SUM(Y81:AA81) -> 225.86332 | AC81: 7.25 | AD81: =SUM(AB81*AC81) -> 1637.5091 | AE81: =SUM(X81+AD81) -> 2591.8842 | AF81: =SUM(P81-AE81) -> 126.07796
C82: 241214000027 | D82: 45643 | E82: Sam.Pao | F82: Sam.Pao | G82: Sampao | H82: 0.0295 | I82: 50 | J82: 555.8 | P82: =SUBTOTAL(9,J82) -> 555.8 | S82: =SUM(50080.5/68)*H82 -> 21.726099 | U82: =SUM(2000/68)*H82 -> 0.86764706 | X82: =SUM(S82:W82) -> 22.593746 | Y82: =SUM(12270/68)*H82 -> 5.3230147 | Z82: 44.59 | AA82: =SUM(55.42/68)*H82 -> 0.0240425 | AB82: =SUM(Y82:AA82) -> 49.937057 | AC82: 7.25 | AD82: =SUM(AB82*AC82) -> 362.04366 | AE82: =SUM(X82+AD82) -> 384.63741 | AF82: =SUM(P82-AE82) -> 171.16259
C83: 241128000030 | D83: 45643 | E83: Sam.Pao | F83: Sam.Pao | G83: ShanShan | H83: 6.1439 | I83: 3510 | J83: 18062 | P83: =SUBTOTAL(9,J83) -> 18062 | S83: =SUM(50080.5/68)*H83 -> 4524.8468 | U83: =SUM(2000/68)*H83 -> 180.70294 | X83: =SUM(S83:W83) -> 4705.5498 | Y83: =SUM(12270/68)*H83 -> 1108.6125 | AA83: =SUM(55.42/68)*H83 -> 5.0072785 | AB83: =SUM(Y83:AA83) -> 1113.6198 | AC83: 7.25 | AD83: =SUM(AB83*AC83) -> 8073.7437 | AE83: =SUM(X83+AD83) -> 12779.293 | AF83: =SUM(P83-AE83) -> 5282.7065
C84: 250110000026 | D84: 45643 | E84: 吕沛霖 | F84: 喵喵速运-Layne | G84: KE ZONG | H84: 1.0248 | I84: 276 | J84: 2271.15 | P84: =SUBTOTAL(9,J84) -> 2271.15 | S84: =SUM(50080.5/68)*H84 -> 754.74259 | U84: =SUM(2000/68)*H84 -> 30.141176 | X84: =SUM(S84:W84) -> 784.88377 | Y84: =SUM(12270/68)*H84 -> 184.91612 | AA84: =SUM(55.42/68)*H84 -> 0.835212 | AB84: =SUM(Y84:AA84) -> 185.75133 | AC84: 7.25 | AD84: =SUM(AB84*AC84) -> 1346.6971 | AE84: =SUM(X84+AD84) -> 2131.5809 | AF84: =SUM(P84-AE84) -> 139.56909
C85: 241126000049 | D85: 45638 | E85: Sam.Pao | F85: Sam.Pao | G85: AiGeLi | H85: 20.5166 | I85: 8722 | J85: 58944 | P85: =SUBTOTAL(9,J85) -> 58944 | S85: =SUM(50080.5/68)*H85 -> 15110.023 | U85: =SUM(2000/68)*H85 -> 603.42941 | X85: =SUM(S85:W85) -> 15713.453 | Y85: =SUM(12270/68)*H85 -> 3702.0394 | Z85: 1082.8 | AA85: =SUM(55.42/68)*H85 -> 16.721029 | AB85: =SUM(Y85:AA85) -> 4801.5605 | AC85: 7.25 | AD85: =SUM(AB85*AC85) -> 34811.313 | AE85: =SUM(X85+AD85) -> 50524.766 | AF85: =SUM(P85-AE85) -> 8419.2339
C86: 241115000013 | D86: 45638 | E86: Sam.Pao | F86: Sam.Pao | G86: ChenGaoHong | H86: 6.3827 | I86: 2355 | J86: 13563 | P86: =SUBTOTAL(9,J86) -> 13563 | S86: =SUM(50080.5/68)*H86 -> 4700.7178 | U86: =SUM(2000/68)*H86 -> 187.72647 | X86: =SUM(S86:W86) -> 4888.4442 | Y86: =SUM(12270/68)*H86 -> 1151.7019 | AA86: =SUM(55.42/68)*H86 -> 5.2019005 | AB86: =SUM(Y86:AA86) -> 1156.9038 | AC86: 7.25 | AD86: =SUM(AB86*AC86) -> 8387.5525 | AE86: =SUM(X86+AD86) -> 13275.997 | AF86: =SUM(P86-AE86) -> 287.00324
C87: 241214000030 | D87: 45643 | E87: 黄颖 | F87: ying | G87: ss | H87: 0.823 | I87: 696 | J87: 3584 | P87: =SUBTOTAL(9,J87) -> 3584 | S87: =SUM(50080.5/68)*H87 -> 606.12135 | U87: =SUM(2000/68)*H87 -> 24.205882 | X87: =SUM(S87:W87) -> 630.32723 | Y87: =SUM(12270/68)*H87 -> 148.50309 | Z87: 136.53 | AA87: =SUM(55.42/68)*H87 -> 0.670745 | AB87: =SUM(Y87:AA87) -> 285.70383 | AC87: 7.25 | AD87: =SUM(AB87*AC87) -> 2071.3528 | AE87: =SUM(X87+AD87) -> 2701.68 | AF87: =SUM(P87-AE87) -> 882.31998
C88: 241212000021 | D88: 45643 | E88: 黄颖 | F88: ying | G88: ss | H88: 1.9011 | I88: 816.18 | K88: 846007 | M88: =SUM(K88/N88) -> 1561.4459 | N88: 541.81 | O88: 7.27 | P88: =SUM(N88*O88) -> 3938.9587 | S88: =SUM(50080.5/68)*H88 -> 1400.1182 | U88: =SUM(2000/68)*H88 -> 55.914706 | X88: =SUM(S88:W88) -> 1456.0329 | Y88: =SUM(12270/68)*H88 -> 343.03672 | AA88: =SUM(55.42/68)*H88 -> 1.5493965 | AB88: =SUM(Y88:AA88) -> 344.58612 | AC88: 7.25 | AD88: =SUM(AB88*AC88) -> 2498.2493 | AE88: =SUM(X88+AD88) -> 3954.2823 | AF88: =SUM(P88-AE88) -> -15.323569
C89: 241209000079 | D89: 45643 | E89: 黄颖 | F89: ying | G89: fanglijuan | H89: 0.0757 | I89: 16 | J89: 195 | P89: =SUBTOTAL(9,J89) -> 195 | S89: =SUM(50080.5/68)*H89 -> 55.75138 | U89: =SUM(2000/68)*H89 -> 2.2264706 | X89: =SUM(S89:W89) -> 57.977851 | Y89: =SUM(12270/68)*H89 -> 13.659397 | AA89: =SUM(55.42/68)*H89 -> 0.0616955 | AB89: =SUM(Y89:AA89) -> 13.721093 | AC89: 7.25 | AD89: =SUM(AB89*AC89) -> 99.477921 | AE89: =SUM(X89+AD89) -> 157.45577 | AF89: =SUM(P89-AE89) -> 37.544228
C90: 241217000014 | D90: 45643 | E90: 朱小飞 | F90: Isabel Zhu | G90: Maryam Tukur | H90: 1.1639 | I90: 148 | K90: 687330 | M90: =SUM(K90/N90) -> 1536.0016 | N90: 447.48 | O90: 7.27 | P90: =SUM(N90*O90) -> 3253.1796 | S90: =SUM(50080.5/68)*H90 -> 857.18668 | U90: =SUM(2000/68)*H90 -> 34.232353 | X90: =SUM(S90:W90) -> 891.41903 | Y90: =SUM(12270/68)*H90 -> 210.01549 | Z90: 66.75 | AA90: =SUM(55.42/68)*H90 -> 0.9485785 | AB90: =SUM(Y90:AA90) -> 277.71406 | AC90: 7.25 | AD90: =SUM(AB90*AC90) -> 2013.427 | AE90: =SUM(X90+AD90) -> 2904.846 | AF90: =SUM(P90-AE90) -> 348.33361
C91: 241217000015 | D91: 45643 | E91: 朱小飞 | F91: Isabel Zhu | G91: Sadiq | H91: 0.322 | I91: 85 | K91: 186847 | M91: =SUM(K91/N91) -> 1582.1084 | N91: 118.1 | O91: 7.25 | P91: =SUM(N91*O91) -> 856.225 | S91: =SUM(50080.5/68)*H91 -> 237.1459 | U91: =SUM(2000/68)*H91 -> 9.4705882 | X91: =SUM(S91:W91) -> 246.61649 | Y91: =SUM(12270/68)*H91 -> 58.102059 | AA91: =SUM(55.42/68)*H91 -> 0.26243 | AB91: =SUM(Y91:AA91) -> 58.364489 | AC91: 7.25 | AD91: =SUM(AB91*AC91) -> 423.14254 | AE91: =SUM(X91+AD91) -> 669.75903 | AF91: =SUM(P91-AE91) -> 186.46597
C92: 241217000016 | D92: 45643 | E92: 罗珮文 | F92: Shirley | G92: Abubakar Badaru Abubakar | H92: 0.6596 | I92: 58 | K92: 296670 | M92: =SUM(K92/N92) -> 1550 | N92: 191.4 | O92: 7.27 | P92: =SUM(N92*O92) -> 1391.478 | S92: =SUM(50080.5/68)*H92 -> 485.78085 | U92: =SUM(2000/68)*H92 -> 19.4 | X92: =SUM(S92:W92) -> 505.18085 | Y92: =SUM(12270/68)*H92 -> 119.019 | AA92: =SUM(55.42/68)*H92 -> 0.537574 | AB92: =SUM(Y92:AA92) -> 119.55657 | AC92: 7.25 | AD92: =SUM(AB92*AC92) -> 866.78516 | AE92: =SUM(X92+AD92) -> 1371.966 | AF92: =SUM(P92-AE92) -> 19.511989
C93: 241217000024 | D93: 45643 | E93: 黄颖 | F93: ying | G93: wuchengxing | H93: 0.4017 | I93: 36 | J93: 876 | P93: =SUBTOTAL(9,J93) -> 876 | S93: =SUM(50080.5/68)*H93 -> 295.84319 | U93: =SUM(2000/68)*H93 -> 11.814706 | X93: =SUM(S93:W93) -> 307.65789 | Y93: =SUM(12270/68)*H93 -> 72.483221 | AA93: =SUM(55.42/68)*H93 -> 0.3273855 | AB93: =SUM(Y93:AA93) -> 72.810606 | AC93: 7.25 | AD93: =SUM(AB93*AC93) -> 527.87689 | AE93: =SUM(X93+AD93) -> 835.53479 | AF93: =SUM(P93-AE93) -> 40.465211
A94: JOB120390 | B94: COLL004328 | C94: 241212000021 | D94: 46010 | E94: 黄颖 | F94: ying | G94: ss | H94: 0.1207 | I94: 51.82 | K94: 53713 | M94: =SUM(K94/N94) -> 1561.4244 | N94: 34.4 | O94: 7.27 | P94: =SUM(N94*O94) -> 250.088 | Q94: =SUM(P94:P100) -> 155095.06 | R94: 登凯=45460.5 陆总=1500 拖车费=1670 杂费=86 过磅费=61 | S94: =SUM(48777.5/68)*H94 -> 86.580062 | T94: =SUM(88.88/68)*H94 -> 0.157762 | U94: =SUM(1900/68)*H94 -> 3.3725 | X94: =SUM(S94:W94) -> 90.110325 | Y94: =SUM(12037/68)*H94 -> 21.365675 | AA94: =SUM(57.52/68)*H94 -> 0.102098 | AB94: =SUM(Y94:AA94) -> 21.467773 | AC94: 7.25 | AD94: =SUM(AB94*AC94) -> 155.64135 | AE94: =SUM(X94+AD94) -> 245.75168 | AF94: =SUM(P94-AE94) -> 4.3363213
C95: 241219000026 | D95: 46010 | E95: Sam.Pao | F95: Sam.Pao | G95: ShanShan | H95: 6.1439 | I95: 3510 | J95: 18062 | P95: =SUBTOTAL(9,J95) -> 18062 | S95: =SUM(48777.5/68)*H95 -> 4407.1189 | T95: =SUM(88.88/68)*H95 -> 8.0304387 | U95: =SUM(1900/68)*H95 -> 171.66779 | X95: =SUM(S95:W95) -> 4586.8171 | Y95: =SUM(12037/68)*H95 -> 1087.5607 | AA95: =SUM(57.52/68)*H95 -> 5.1970166 | AB95: =SUM(Y95:AA95) -> 1092.7577 | AC95: 7.25 | AD95: =SUM(AB95*AC95) -> 7922.4931 | AE95: =SUM(X95+AD95) -> 12509.31 | AF95: =SUM(P95-AE95) -> 5552.6898
C96: 241219000027 | D96: 46010 | E96: 陆总 | F96: 陆梓龙 | G96: xiantian | H96: 0.9378 | I96: 1454 | J96: 4037.69 | P96: =SUBTOTAL(9,J96) -> 4037.69 | S96: =SUM(48777.5/68)*H96 -> 672.69911 | T96: =SUM(88.88/68)*H96 -> 1.2257598 | U96: =SUM(1900/68)*H96 -> 26.203235 | X96: =SUM(S96:W96) -> 700.12811 | Y96: =SUM(12037/68)*H96 -> 166.00439 | AA96: =SUM(57.52/68)*H96 -> 0.79326847 | AB96: =SUM(Y96:AA96) -> 166.79766 | AC96: 7.25 | AD96: =SUM(AB96*AC96) -> 1209.283 | AE96: =SUM(X96+AD96) -> 1909.4111 | AF96: =SUM(P96-AE96) -> 2128.2789
C97: 241219000017 | D97: 46010 | E97: 朱小飞 | F97: Isabel Zhu | G97: Halifa Success | H97: 2.2361 | I97: 234 | J97: 4542.5 | P97: =SUBTOTAL(9,J97) -> 4542.5 | S97: =SUM(48777.5/68)*H97 -> 1603.9907 | T97: =SUM(88.88/68)*H97 -> 2.9227142 | U97: =SUM(1900/68)*H97 -> 62.479265 | X97: =SUM(S97:W97) -> 1669.3927 | Y97: =SUM(12037/68)*H97 -> 395.82258 | AA97: =SUM(57.52/68)*H97 -> 1.8914775 | AB97: =SUM(Y97:AA97) -> 397.71406 | AC97: 7.25 | AD97: =SUM(AB97*AC97) -> 2883.4269 | AE97: =SUM(X97+AD97) -> 4552.8196 | AF97: =SUM(P97-AE97) -> -10.319626
C98: 241115000013 | D98: 45638 | E98: Sam.Pao | F98: Sam.Pao | G98: ChenGaoHong | H98: 25.3204 | I98: 5102 | J98: 53816 | P98: =SUBTOTAL(9,J98) -> 53816 | S98: =SUM(48777.5/68)*H98 -> 18162.733 | T98: =SUM(88.88/68)*H98 -> 33.095252 | U98: =SUM(1900/68)*H98 -> 707.48176 | X98: =SUM(S98:W98) -> 18903.31 | Y98: =SUM(12037/68)*H98 -> 4482.0832 | AA98: =SUM(57.52/68)*H98 -> 21.41808 | AB98: =SUM(Y98:AA98) -> 4503.5012 | AC98: 7.25 | AD98: =SUM(AB98*AC98) -> 32650.384 | AE98: =SUM(X98+AD98) -> 51553.694 | AF98: =SUM(P98-AE98) -> 2262.3065
C99: 241219000028 | D99: 46010 | E99: 罗珮文 | F99: Shirley | G99: SKY JET | H99: 22.11 | I99: 2603 | J99: 36919.28 | P99: =SUBTOTAL(9,J99) -> 36919.28 | S99: =SUM(48777.5/68)*H99 -> 15859.861 | T99: =SUM(88.88/68)*H99 -> 28.899071 | U99: =SUM(1900/68)*H99 -> 617.77941 | X99: =SUM(S99:W99) -> 16506.539 | Y99: =SUM(12037/68)*H99 -> 3913.7951 | AA99: =SUM(57.52/68)*H99 -> 18.702459 | AB99: =SUM(Y99:AA99) -> 3932.4976 | AC99: 7.25 | AD99: =SUM(AB99*AC99) -> 28510.608 | AE99: =SUM(X99+AD99) -> 45017.147 | AF99: =SUM(P99-AE99) -> -8097.8668
C100: 241219000033 | D100: 46010 | E100: 黄颖 | F100: ying | G100: MISS Huang | H100: 15.7779 | I100: 9654 | J100: 37467.5 | P100: =SUBTOTAL(9,J100) -> 37467.5 | S100: =SUM(48777.5/68)*H100 -> 11317.743 | T100: =SUM(88.88/68)*H100 -> 20.622643 | U100: =SUM(1900/68)*H100 -> 440.85309 | X100: =SUM(S100:W100) -> 11779.219 | Y100: =SUM(12037/68)*H100 -> 2792.9203 | AA100: =SUM(57.52/68)*H100 -> 13.346247 | AB100: =SUM(Y100:AA100) -> 2806.2666 | AC100: 7.25 | AD100: =SUM(AB100*AC100) -> 20345.433 | AE100: =SUM(X100+AD100) -> 32124.651 | AF100: =SUM(P100-AE100) -> 5342.8487
...

Sheet JOB120360
A1: 2024年12月份LOS毛利表（海运）
A2: PSL表 | B2: 体积cbm | C2: 69.7576
A3: JOB | B3: 集装编号 | C3: 运单编号 | D3: 日期 | E3: 业务 | F3: 发货人 | G3: 收货人 | H3: 计费体积 | I3: 计费重量 | J3: 应 收 | Q3: 总应收 | R3: 起 运 港 成 本 | W3: 代垫运费 | X3: 起运港成本 合计 | Y3: 目的港成本 | AE3: 总支出 | AF3: 利润
J4: 应收RMB | K4: LOS Income(NGN)收到(奈拉) | L4: LOS 收到USD | M4: 美元汇率 dollar currency rate | N4: 应收 到付款USD | O4: 汇率 | P4: 人民币 | R4: 代理商 | S4: 运费+出口报关费 | T4: 提货费 | U4: 装卸费 | V4: 包装费 | Y4: 进口报关费 | Z4: 到门配送费 | AA4: 转运费 | AB4: 目的港支出 | AC4: 汇率 | AD4: 人民币 | AE4: 起运港+目的港
A5: JOB120360 | B5: COLL004315 | C5: 240925000017 | D5: 45631 | E5: 无人 | F5: dejare James | G5: James | H5: 0.1799 | I5: 17 | K5: 84600 | M5: =SUM(K5/N5) -> 1679.5713 | N5: 50.369995 | O5: 7.27 | P5: =SUM(N5*O5) -> 366.18986 | Q5: =SUM(P5:P40) -> 162259.24 | R5: 登凯=43870.25 创泽=1270 拖车费=1670 杂费=84 过磅费=69 | S5: =SUM(46963.25/68)*H5 -> 124.24542 | U5: =SUM(2500/68)*H5 -> 6.6139706 | X5: =SUM(S5:W5) -> 130.85939 | Y5: =SUM(11081/68)*H5 -> 29.315763 | AB5: =SUM(Y5:AA5) -> 29.315763 | AC5: 7.24 | AD5: =SUM(AB5*AC5) -> 212.24613 | AE5: =SUM(X5+AD5) -> 343.10552 | AF5: =SUM(P5-AE5) -> 23.084346
C6: 241118000063 | D6: 45631 | E6: 罗珮文 | F6: Shirley | G6: Yusky | H6: 1.6585 | I6: 270 | K6: 719837.28 | M6: =SUM(K6/N6) -> 1608 | N6: 447.66 | O6: 7.3 | P6: =SUM(N6*O6) -> 3267.918 | S6: =SUM(46963.25/68)*H6 -> 1145.4199 | U6: =SUM(2500/68)*H6 -> 60.974265 | X6: =SUM(S6:W6) -> 1206.3941 | Y6: =SUM(11081/68)*H6 -> 270.26233 | AB6: =SUM(Y6:AA6) -> 270.26233 | AC6: 7.24 | AD6: =SUM(AB6*AC6) -> 1956.6993 | AE6: =SUM(X6+AD6) -> 3163.0934 | AF6: =SUM(P6-AE6) -> 104.8246
C7: 241118000066 | D7: 45631 | E7: 罗珮文 | F7: Shirley | G7: Yusky | H7: 1.2581 | I7: 125 | K7: 546173.28 | M7: =SUM(K7/N7) -> 1608 | N7: 339.66 | O7: 7.3 | P7: =SUM(N7*O7) -> 2479.518 | S7: =SUM(46963.25/68)*H7 -> 868.88919 | U7: =SUM(2500/68)*H7 -> 46.253676 | X7: =SUM(S7:W7) -> 915.14287 | Y7: =SUM(11081/68)*H7 -> 205.0148 | AB7: =SUM(Y7:AA7) -> 205.0148 | AC7: 7.24 | AD7: =SUM(AB7*AC7) -> 1484.3071 | AE7: =SUM(X7+AD7) -> 2399.45 | AF7: =SUM(P7-AE7) -> 80.068015
C8: 241120000012 | D8: 45631 | E8: Bella | F8: Bella Chan | G8: FENG | H8: 0.1878 | I8: 62 | K8: 94651.2 | M8: =SUM(K8/N8) -> 1680.0001 | N8: 56.339996 | O8: 7.3 | P8: =SUM(N8*O8) -> 411.28197 | S8: =SUM(46963.25/68)*H8 -> 129.70145 | U8: =SUM(2500/68)*H8 -> 6.9044118 | X8: =SUM(S8:W8) -> 136.60586 | Y8: =SUM(11081/68)*H8 -> 30.603115 | AB8: =SUM(Y8:AA8) -> 30.603115 | AC8: 7.24 | AD8: =SUM(AB8*AC8) -> 221.56655 | AE8: =SUM(X8+AD8) -> 358.17241 | AF8: =SUM(P8-AE8) -> 53.109562
C9: 241120000023 | D9: 45631 | E9: Sam.Pao | F9: Sam.Pao | G9: Mr. Jiang | H9: 1.3317 | I9: 326 | J9: 4965 | P9: =SUBTOTAL(9,J9) -> 4965 | S9: =SUM(46963.25/68)*H9 -> 919.72 | U9: =SUM(2500/68)*H9 -> 48.959559 | V9: 500 | X9: =SUM(S9:W9) -> 1468.6796 | Y9: =SUM(11081/68)*H9 -> 217.00835 | AB9: =SUM(Y9:AA9) -> 217.00835 | AC9: 7.24 | AD9: =SUM(AB9*AC9) -> 1571.1404 | AE9: =SUM(X9+AD9) -> 3039.82 | AF9: =SUM(P9-AE9) -> 1925.18
C10: 241121000013 | D10: 45631 | E10: Sam.Pao | F10: Sam.Pao | G10: Mr. Jiang | H10: 2.2982 | I10: 612 | J10: 7707 | P10: =SUBTOTAL(9,J10) -> 7707 | S10: =SUM(46963.25/68)*H10 -> 1587.2197 | U10: =SUM(2500/68)*H10 -> 84.492647 | V10: 400 | X10: =SUM(S10:W10) -> 2071.7124 | Y10: =SUM(11081/68)*H10 -> 374.50521 | AB10: =SUM(Y10:AA10) -> 374.50521 | AC10: 7.24 | AD10: =SUM(AB10*AC10) -> 2711.4177 | AE10: =SUM(X10+AD10) -> 4783.1301 | AF10: =SUM(P10-AE10) -> 2923.8699
C11: 241121000018 | D11: 45631 | E11: Sam.Pao | F11: Sam.Pao | G11: Nick Wang | H11: 0.0768 | I11: 14 | J11: 296.22 | P11: =SUBTOTAL(9,J11) -> 296.22 | S11: =SUM(46963.25/68)*H11 -> 53.040847 | U11: =SUM(2500/68)*H11 -> 2.8235294 | X11: =SUM(S11:W11) -> 55.864376 | Y11: =SUM(11081/68)*H11 -> 12.515012 | Z11: 4.51 | AB11: =SUM(Y11:AA11) -> 17.025012 | AC11: 7.24 | AD11: =SUM(AB11*AC11) -> 123.26109 | AE11: =SUM(X11+AD11) -> 179.12546 | AF11: =SUM(P11-AE11) -> 117.09454
C12: 241121000019 | D12: 45631 | E12: Sam.Pao | F12: Sam.Pao | G12: Mr. Jiang | H12: 1.4834 | I12: 471 | J12: 3598 | P12: =SUBTOTAL(9,J12) -> 3598 | S12: =SUM(46963.25/68)*H12 -> 1024.4895 | U12: =SUM(2500/68)*H12 -> 54.536765 | X12: =SUM(S12:W12) -> 1079.0263 | Y12: =SUM(11081/68)*H12 -> 241.72876 | AB12: =SUM(Y12:AA12) -> 241.72876 | AC12: 7.24 | AD12: =SUM(AB12*AC12) -> 1750.1162 | AE12: =SUM(X12+AD12) -> 2829.1424 | AF12: =SUM(P12-AE12) -> 768.85756
C13: 241123000017 | D13: 45631 | E13: 黄颖 | F13: ying | G13: Nura | H13: 0.3608 | I13: 202 | J13: 792 | P13: =SUBTOTAL(9,J13) -> 792 | S13: =SUM(46963.25/68)*H13 -> 249.18148 | U13: =SUM(2500/68)*H13 -> 13.264706 | X13: =SUM(S13:W13) -> 262.44619 | Y13: =SUM(11081/68)*H13 -> 58.794482 | AB13: =SUM(Y13:AA13) -> 58.794482 | AC13: 7.24 | AD13: =SUM(AB13*AC13) -> 425.67205 | AE13: =SUM(X13+AD13) -> 688.11824 | AF13: =SUM(P13-AE13) -> 103.88176
C14: 241123000018 | D14: 45631 | E14: Bella | F14: Bella Chan | G14: zhong zi xin | H14: 11.1459 | I14: 16993 | J14: 36986 | P14: =SUBTOTAL(9,J14) -> 36986 | S14: =SUM(46963.25/68)*H14 -> 7697.7601 | U14: =SUM(2500/68)*H14 -> 409.77574 | V14: 280 | X14: =SUM(S14:W14) -> 8387.5359 | Y14: =SUM(11081/68)*H14 -> 1816.29 | Z14: 288.81 | AB14: =SUM(Y14:AA14) -> 2105.1 | AC14: 7.24 | AD14: =SUM(AB14*AC14) -> 15240.924 | AE14: =SUM(X14+AD14) -> 23628.46 | AF14: =SUM(P14-AE14) -> 13357.54
C15: 241125000061 | D15: 45631 | E15: 黄颖 | F15: ying | G15: makus | H15: 0.8795 | I15: 210 | J15: 2670.5 | P15: =SUBTOTAL(9,J15) -> 2670.5 | S15: =SUM(46963.25/68)*H15 -> 607.41439 | U15: =SUM(2500/68)*H15 -> 32.334559 | X15: =SUM(S15:W15) -> 639.74895 | Y15: =SUM(11081/68)*H15 -> 143.3197 | Z15: 104.36 | AB15: =SUM(Y15:AA15) -> 247.6797 | AC15: 7.24 | AD15: =SUM(AB15*AC15) -> 1793.201 | AE15: =SUM(X15+AD15) -> 2432.95 | AF15: =SUM(P15-AE15) -> 237.55004
C16: 241125000067 | D16: 45631 | E16: 无人 | F16: dejare James | G16: Adam e | H16: 1.0967 | I16: 203 | K16: 552736 | M16: =SUM(K16/N16) -> 1679.9977 | N16: 329.00998 | O16: 7.27 | P16: =SUM(N16*O16) -> 2391.9026 | S16: =SUM(46963.25/68)*H16 -> 757.42053 | U16: =SUM(2500/68)*H16 -> 40.319853 | X16: =SUM(S16:W16) -> 797.74039 | Y16: =SUM(11081/68)*H16 -> 178.71372 | AB16: =SUM(Y16:AA16) -> 178.71372 | AC16: 7.24 | AD16: =SUM(AB16*AC16) -> 1293.8873 | AE16: =SUM(X16+AD16) -> 2091.6277 | AF16: =SUM(P16-AE16) -> 300.27486
C17: 241127000012 | D17: 45631 | E17: 罗珮文 | F17: Shirley | G17: Yusky | H17: 3.0636 | I17: 768 | K17: 1330089.4 | M17: =SUM(K17/N17) -> 1608 | N17: 827.17 | O17: 7.3 | P17: =SUM(N17*O17) -> 6038.341 | S17: =SUM(46963.25/68)*H17 -> 2115.8325 | U17: =SUM(2500/68)*H17 -> 112.63235 | X17: =SUM(S17:W17) -> 2228.4649 | Y17: =SUM(11081/68)*H17 -> 499.23164 | AB17: =SUM(Y17:AA17) -> 499.23164 | AC17: 7.24 | AD17: =SUM(AB17*AC17) -> 3614.4371 | AE17: =SUM(X17+AD17) -> 5842.902 | AF17: =SUM(P17-AE17) -> 195.43903
C18: 241127000014 | D18: 45631 | E18: 罗珮文 | F18: Shirley | G18: Yusky | H18: 0.4158 | I18: 55 | K18: 180530.16 | M18: =SUM(K18/N18) -> 1608 | N18: 112.27 | O18: 7.3 | P18: =SUM(N18*O18) -> 819.571 | S18: =SUM(46963.25/68)*H18 -> 287.16646 | U18: =SUM(2500/68)*H18 -> 15.286765 | X18: =SUM(S18:W18) -> 302.45323 | Y18: =SUM(11081/68)*H18 -> 67.757056 | AB18: =SUM(Y18:AA18) -> 67.757056 | AC18: 7.24 | AD18: =SUM(AB18*AC18) -> 490.56108 | AE18: =SUM(X18+AD18) -> 793.01431 | AF18: =SUM(P18-AE18) -> 26.55669
C19: 241127000042 | D19: 45631 | E19: 黄颖 | F19: ying | G19: wangweijun | H19: 0.3625 | I19: 15 | J19: 870 | P19: =SUBTOTAL(9,J19) -> 870 | S19: =SUM(46963.25/68)*H19 -> 250.35556 | U19: =SUM(2500/68)*H19 -> 13.327206 | W19: =SUM(26+36) -> 62 | X19: =SUM(S19:W19) -> 325.68277 | Y19: =SUM(11081/68)*H19 -> 59.071507 | AB19: =SUM(Y19:AA19) -> 59.071507 | AC19: 7.24 | AD19: =SUM(AB19*AC19) -> 427.67771 | AE19: =SUM(X19+AD19) -> 753.36048 | AF19: =SUM(P19-AE19) -> 116.63952
C20: 241127000053 | D20: 45631 | E20: 黄颖 | F20: ying | G20: baikaibo | H20: 0.6069 | I20: 165 | J20: 2195 | P20: =SUBTOTAL(9,J20) -> 2195 | S20: =SUM(46963.25/68)*H20 -> 419.14701 | U20: =SUM(2500/68)*H20 -> 22.3125 | X20: =SUM(S20:W20) -> 441.45951 | Y20: =SUM(11081/68)*H20 -> 98.897925 | Z20: 111.31 | AB20: =SUM(Y20:AA20) -> 210.20792 | AC20: 7.24 | AD20: =SUM(AB20*AC20) -> 1521.9054 | AE20: =SUM(X20+AD20) -> 1963.3649 | AF20: =SUM(P20-AE20) -> 231.63512
C21: 241128000039 | D21: 45631 | E21: 无人 | F21: dejare James | G21: James | H21: 0.5074 | I21: 252 | K21: 239442 | M21: =SUM(K21/N21) -> 1572.9993 | N21: 152.22003 | O21: 7.27 | P21: =SUM(N21*O21) -> 1106.6396 | S21: =SUM(46963.25/68)*H21 -> 350.42872 | U21: =SUM(2500/68)*H21 -> 18.654412 | X21: =SUM(S21:W21) -> 369.08313 | Y21: =SUM(11081/68)*H21 -> 82.683815 | AB21: =SUM(Y21:AA21) -> 82.683815 | AC21: 7.24 | AD21: =SUM(AB21*AC21) -> 598.63082 | AE21: =SUM(X21+AD21) -> 967.71395 | AF21: =SUM(P21-AE21) -> 138.92567
C22: 241128000041 | D22: 45631 | E22: 黄颖 | F22: ying | G22: linxiao | H22: 0.2074 | I22: 60 | J22: 463 | P22: =SUBTOTAL(9,J22) -> 463 | S22: =SUM(46963.25/68)*H22 -> 143.23791 | U22: =SUM(2500/68)*H22 -> 7.625 | X22: =SUM(S22:W22) -> 150.86291 | Y22: =SUM(11081/68)*H22 -> 33.79705 | AB22: =SUM(Y22:AA22) -> 33.79705 | AC22: 7.24 | AD22: =SUM(AB22*AC22) -> 244.69064 | AE22: =SUM(X22+AD22) -> 395.55355 | AF22: =SUM(P22-AE22) -> 67.446445
C23: 241129000029 | D23: 45631 | E23: 陆总 | F23: 陆梓龙 | G23: xiantian | H23: 0.19 | I23: 24 | J23: 369.36 | P23: =SUBTOTAL(9,J23) -> 369.36 | S23: =SUM(46963.25/68)*H23 -> 131.22085 | U23: =SUM(2500/68)*H23 -> 6.9852941 | X23: =SUM(S23:W23) -> 138.20614 | Y23: =SUM(11081/68)*H23 -> 30.961618 | AB23: =SUM(Y23:AA23) -> 30.961618 | AC23: 7.24 | AD23: =SUM(AB23*AC23) -> 224.16211 | AE23: =SUM(X23+AD23) -> 362.36825 | AF23: =SUM(P23-AE23) -> 6.9917485
C24: 241129000035 | D24: 45631 | E24: 黄颖 | F24: ying | G24: liangdawei | H24: 0.3468 | I24: 269 | J24: 1003 | P24: =SUBTOTAL(9,J24) -> 1003 | S24: =SUM(46963.25/68)*H24 -> 239.51257 | U24: =SUM(2500/68)*H24 -> 12.75 | X24: =SUM(S24:W24) -> 252.26257 | Y24: =SUM(11081/68)*H24 -> 56.5131 | AB24: =SUM(Y24:AA24) -> 56.5131 | AC24: 7.24 | AD24: =SUM(AB24*AC24) -> 409.15484 | AE24: =SUM(X24+AD24) -> 661.41742 | AF24: =SUM(P24-AE24) -> 341.58258
C25: 241130000012 | D25: 45631 | E25: 吕沛霖 | F25: Paul | G25: Paul | H25: 0.0882 | I25: 30 | K25: 56179 | M25: =SUM(K25/N25) -> 1679.994 | N25: 33.44 | O25: 7.27 | P25: =SUM(N25*O25) -> 243.1088 | S25: =SUM(46963.25/68)*H25 -> 60.914098 | U25: =SUM(2500/68)*H25 -> 3.2426471 | X25: =SUM(S25:W25) -> 64.156745 | Y25: =SUM(11081/68)*H25 -> 14.372709 | AB25: =SUM(Y25:AA25) -> 14.372709 | AC25: 7.24 | AD25: =SUM(AB25*AC25) -> 104.05841 | AE25: =SUM(X25+AD25) -> 168.21516 | AF25: =SUM(P25-AE25) -> 74.893643
C26: 241202000005 | D26: 45631 | E26: 朱小飞 | F26: Isabel Zhu | G26: Ife Oyelami | H26: 0.8261 | I26: 59 | K26: 424545 | M26: =SUM(K26/N26) -> 1657.7959 | N26: 256.09003 | O26: 7.27 | P26: =SUM(N26*O26) -> 1861.7745 | S26: =SUM(46963.25/68)*H26 -> 570.53442 | U26: =SUM(2500/68)*H26 -> 30.371324 | X26: =SUM(S26:W26) -> 600.90575 | Y26: =SUM(11081/68)*H26 -> 134.61785 | AB26: =SUM(Y26:AA26) -> 134.61785 | AC26: 7.24 | AD26: =SUM(AB26*AC26) -> 974.63327 | AE26: =SUM(X26+AD26) -> 1575.539 | AF26: =SUM(P26-AE26) -> 286.2355
C27: 241202000011 | D27: 45631 | E27: 朱小飞 | F27: Isabel Zhu | G27: Halifa Success | H27: 0.4399 | I27: 73 | J27: 900.59 | P27: =SUBTOTAL(9,J27) -> 900.59 | S27: =SUM(46963.25/68)*H27 -> 303.81079 | U27: =SUM(2500/68)*H27 -> 16.172794 | X27: =SUM(S27:W27) -> 319.98358 | Y27: =SUM(11081/68)*H27 -> 71.684293 | AB27: =SUM(Y27:AA27) -> 71.684293 | AC27: 7.24 | AD27: =SUM(AB27*AC27) -> 518.99428 | AE27: =SUM(X27+AD27) -> 838.97786 | AF27: =SUM(P27-AE27) -> 61.612138
C28: 241202000031 | D28: 45631 | E28: 黄颖 | F28: ying | G28: Jacky | H28: 0.6255 | I28: 265 | K28: 283185 | M28: =SUM(K28/N28) -> 1588.5172 | N28: 178.27002 | O28: 7.27 | P28: =SUM(N28*O28) -> 1296.023 | S28: =SUM(46963.25/68)*H28 -> 431.99284 | U28: =SUM(2500/68)*H28 -> 22.996324 | X28: =SUM(S28:W28) -> 454.98916 | Y28: =SUM(11081/68)*H28 -> 101.9289 | AB28: =SUM(Y28:AA28) -> 101.9289 | AC28: 7.24 | AD28: =SUM(AB28*AC28) -> 737.96527 | AE28: =SUM(X28+AD28) -> 1192.9544 | AF28: =SUM(P28-AE28) -> 103.06862
C29: 241202000042 | D29: 45631 | E29: 无人 | F29: dejare James | G29: James | H29: 0.1256 | I29: 54 | K29: 63300 | M29: =SUM(K29/N29) -> 1679.9359 | N29: 37.680008 | O29: 7.27 | P29: =SUM(N29*O29) -> 273.93366 | S29: =SUM(46963.25/68)*H29 -> 86.743885 | U29: =SUM(2500/68)*H29 -> 4.6176471 | X29: =SUM(S29:W29) -> 91.361532 | Y29: =SUM(11081/68)*H29 -> 20.467259 | AB29: =SUM(Y29:AA29) -> 20.467259 | AC29: 7.24 | AD29: =SUM(AB29*AC29) -> 148.18295 | AE29: =SUM(X29+AD29) -> 239.54449 | AF29: =SUM(P29-AE29) -> 34.389172
C30: 241204000039 | D30: 45631 | E30: 陆总 | F30: 陆梓龙 | G30: xinlong | H30: 0.0608 | I30: 12 | J30: 113.83 | P30: =SUBTOTAL(9,J30) -> 113.83 | S30: =SUM(46963.25/68)*H30 -> 41.990671 | U30: =SUM(2500/68)*H30 -> 2.2352941 | X30: =SUM(S30:W30) -> 44.225965 | Y30: =SUM(11081/68)*H30 -> 9.9077176 | AB30: =SUM(Y30:AA30) -> 9.9077176 | AC30: 7.24 | AD30: =SUM(AB30*AC30) -> 71.731876 | AE30: =SUM(X30+AD30) -> 115.95784 | AF30: =SUM(P30-AE30) -> -2.1278405
C31: 241204000043 | D31: 45631 | E31: 罗珮文 | F31: Shirley | G31: Yusky | H31: 1.3963 | I31: 248 | K31: 606216 | M31: =SUM(K31/N31) -> 1608 | N31: 377 | O31: 7.3 | P31: =SUM(N31*O31) -> 2752.1 | S31: =SUM(46963.25/68)*H31 -> 964.33509 | U31: =SUM(2500/68)*H31 -> 51.334559 | X31: =SUM(S31:W31) -> 1015.6696 | Y31: =SUM(11081/68)*H31 -> 227.5353 | AB31: =SUM(Y31:AA31) -> 227.5353 | AC31: 7.24 | AD31: =SUM(AB31*AC31) -> 1647.3556 | AE31: =SUM(X31+AD31) -> 2663.0252 | AF31: =SUM(P31-AE31) -> 89.074792
C32: 241204000044 | D32: 45631 | E32: 罗珮文 | F32: Shirley | G32: Yusky | H32: 0.7235 | I32: 107 | K32: 314122.8 | M32: =SUM(K32/N32) -> 1608 | N32: 195.35 | O32: 7.3 | P32: =SUM(N32*O32) -> 1426.055 | S32: =SUM(46963.25/68)*H32 -> 499.67517 | U32: =SUM(2500/68)*H32 -> 26.599265 | X32: =SUM(S32:W32) -> 526.27443 | Y32: =SUM(11081/68)*H32 -> 117.89858 | AB32: =SUM(Y32:AA32) -> 117.89858 | AC32: 7.24 | AD32: =SUM(AB32*AC32) -> 853.58573 | AE32: =SUM(X32+AD32) -> 1379.8602 | AF32: =SUM(P32-AE32) -> 46.194842
C33: 241204000045 | D33: 45631 | E33: 罗珮文 | F33: Shirley | G33: Yusky | H33: 0.26 | I33: 48 | K33: 112929.84 | M33: =SUM(K33/N33) -> 1608 | N33: 70.23 | O33: 7.3 | P33: =SUM(N33*O33) -> 512.679 | S33: =SUM(46963.25/68)*H33 -> 179.56537 | U33: =SUM(2500/68)*H33 -> 9.5588235 | X33: =SUM(S33:W33) -> 189.12419 | Y33: =SUM(11081/68)*H33 -> 42.368529 | AB33: =SUM(Y33:AA33) -> 42.368529 | AC33: 7.24 | AD33: =SUM(AB33*AC33) -> 306.74815 | AE33: =SUM(X33+AD33) -> 495.87234 | AF33: =SUM(P33-AE33) -> 16.806656
C34: 241204000046 | D34: 45631 | E34: 罗珮文 | F34: Shirley | G34: Yusky | H34: 0.2492 | I34: 51 | K34: 108090.06 | M34: =SUM(K34/N34) -> 1606.5705 | N34: 67.28 | O34: 7.3 | P34: =SUM(N34*O34) -> 491.144 | S34: =SUM(46963.25/68)*H34 -> 172.1065 | U34: =SUM(2500/68)*H34 -> 9.1617647 | X34: =SUM(S34:W34) -> 181.26826 | Y34: =SUM(11081/68)*H34 -> 40.608606 | AB34: =SUM(Y34:AA34) -> 40.608606 | AC34: 7.24 | AD34: =SUM(AB34*AC34) -> 294.00631 | AE34: =SUM(X34+AD34) -> 475.27457 | AF34: =SUM(P34-AE34) -> 15.86943
C35: 241204000047 | D35: 45631 | E35: 罗珮文 | F35: Shirley | G35: Yusky | H35: 0.2023 | I35: 17 | K35: 87064.28 | M35: =SUM(K35/N35) -> 1594 | N35: 54.62 | O35: 7.29 | P35: =SUM(N35*O35) -> 398.1798 | S35: =SUM(46963.25/68)*H35 -> 139.71567 | U35: =SUM(2500/68)*H35 -> 7.4375 | X35: =SUM(S35:W35) -> 147.15317 | Y35: =SUM(11081/68)*H35 -> 32.965975 | AB35: =SUM(Y35:AA35) -> 32.965975 | AC35: 7.24 | AD35: =SUM(AB35*AC35) -> 238.67366 | AE35: =SUM(X35+AD35) -> 385.82683 | AF35: =SUM(P35-AE35) -> 12.352972
C36: 241204000048 | D36: 45631 | E36: 罗珮文 | F36: Shirley | G36: Yusky | H36: 0.5307 | I36: 90 | K36: 228404.26 | M36: =SUM(K36/N36) -> 1594 | N36: 143.29 | O36: 7.29 | P36: =SUM(N36*O36) -> 1044.5841 | S36: =SUM(46963.25/68)*H36 -> 366.52054 | U36: =SUM(2500/68)*H36 -> 19.511029 | X36: =SUM(S36:W36) -> 386.03157 | Y36: =SUM(11081/68)*H36 -> 86.480687 | AB36: =SUM(Y36:AA36) -> 86.480687 | AC36: 7.24 | AD36: =SUM(AB36*AC36) -> 626.12017 | AE36: =SUM(X36+AD36) -> 1012.1517 | AF36: =SUM(P36-AE36) -> 32.432358
C37: 241204000050 | D37: 45631 | E37: 罗珮文 | F37: Shirley | G37: Yusky | H37: 14.6981 | I37: 2994 | K37: 6392673.2 | M37: =SUM(K37/N37) -> 1594 | N37: 4010.46 | O37: 7.27 | P37: =SUM(N37*O37) -> 29156.044 | S37: =SUM(46963.25/68)*H37 -> 10151.037 | U37: =SUM(2500/68)*H37 -> 540.37132 | X37: =SUM(S37:W37) -> 10691.409 | Y37: =SUM(11081/68)*H37 -> 2395.1419 | AB37: =SUM(Y37:AA37) -> 2395.1419 | AC37: 7.24 | AD37: =SUM(AB37*AC37) -> 17340.827 | AE37: =SUM(X37+AD37) -> 28032.236 | AF37: =SUM(P37-AE37) -> 1123.8084
C38: 241204000052 | D38: 45631 | E38: 罗珮文 | F38: Shirley | G38: Yusky | H38: 21.052 | I38: 2202 | K38: 9257809 | M38: =SUM(K38/N38) -> 1616.7908 | N38: 5726.04 | O38: 7.22 | P38: =SUM(N38*O38) -> 41342.009 | S38: =SUM(46963.25/68)*H38 -> 14539.27 | U38: =SUM(2500/68)*H38 -> 773.97059 | X38: =SUM(S38:W38) -> 15313.24 | Y38: =SUM(11081/68)*H38 -> 3430.5472 | AB38: =SUM(Y38:AA38) -> 3430.5472 | AC38: 7.24 | AD38: =SUM(AB38*AC38) -> 24837.162 | AE38: =SUM(X38+AD38) -> 40150.402 | AF38: =SUM(P38-AE38) -> 1191.6065
C39: 241204000053 | D39: 45631 | E39: 罗珮文 | F39: Shirley | G39: Yusky | H39: 0.1958 | I39: 447 | K39: 85649.4 | M39: =SUM(K39/N39) -> 1620 | N39: 52.87 | O39: 7.22 | P39: =SUM(N39*O39) -> 381.7214 | S39: =SUM(46963.25/68)*H39 -> 135.22653 | U39: =SUM(2500/68)*H39 -> 7.1985294 | X39: =SUM(S39:W39) -> 142.42506 | Y39: =SUM(11081/68)*H39 -> 31.906762 | AB39: =SUM(Y39:AA39) -> 31.906762 | AC39: 7.24 | AD39: =SUM(AB39*AC39) -> 231.00496 | AE39: =SUM(X39+AD39) -> 373.43002 | AF39: =SUM(P39-AE39) -> 8.2913809
C40: 241204000060 | D40: 45631 | E40: 朱小飞 | F40: Isabel Zhu | G40: Halifa Success | H40: 0.6256 | I40: 144 | J40: 1269.02 | P40: =SUBTOTAL(9,J40) -> 1269.02 | S40: =SUM(46963.25/68)*H40 -> 432.0619 | U40: =SUM(2500/68)*H40 -> 23 | X40: =SUM(S40:W40) -> 455.0619 | Y40: =SUM(11081/68)*H40 -> 101.9452 | AB40: =SUM(Y40:AA40) -> 101.9452 | AC40: 7.24 | AD40: =SUM(AB40*AC40) -> 738.08325 | AE40: =SUM(X40+AD40) -> 1193.1451 | AF40: =SUM(P40-AE40) -> 75.874852
A41: 合计 | J41: =SUM(J4:J4) -> 0 | N41: =SUM(N4:N4) -> 0 | P41: =SUM(P4:P4) -> 0 | Q41: =SUM(Q4:Q4) -> 0 | X41: =SUM(X4:X4) -> 0 | AD41: =SUM(AD4:AD4) -> 0 | AF41: =SUM(AF4:AF40) -> 24290.936

Sheet JOB120375
A1: 2024年12月份LOS毛利表（海运）
A2: PSL表 | B2: 体积cbm | C2: 69.9989
A3: JOB | B3: 集装编号 | C3: 运单编号 | D3: 日期 | E3: 业务 | F3: 发货人 | G3: 收货人 | H3: 计费体积 | I3: 计费重量 | J3: 应 收 | Q3: 总应收 | R3: 起 运 港 成 本 | W3: 代垫运费 | X3: 起运港成本 合计 | Y3: 目的港成本 | AE3: 总支出 | AF3: 利润
J4: 应收RMB | K4: LOS Income(NGN)收到(奈拉) | L4: LOS 收到USD | M4: 美元汇率 dollar currency rate | N4: 应收 到付款USD | O4: 汇率 | P4: 人民币 | R4: 代理商 | S4: 运费+出口报关费 | T4: 提货费 | U4: 装卸费 | V4: 包装费 | Y4: 进口报关费 | Z4: 到门配送费 | AA4: 转运费 | AB4: 目的港支出 | AC4: 汇率 | AD4: 人民币 | AE4: 起运港+目的港
A5: JOB120375 | B5: COLL004323 | C5: 241109000014 | D5: 45636 | E5: 吕沛霖 | F5: 喵喵速运-Layne | G5: KE ZONG | H5: 1.5052 | I5: 360 | J5: 3329.55 | P5: =SUBTOTAL(9,J5) -> 3329.55 | Q5: =SUM(P5:P17) -> 166063.23 | R5: 登凯=46552.5 创泽=1215 拖车费=1670 杂费=61 过磅费=70 | S5: =SUM(49568.5/68)*H5 -> 1097.2133 | U5: =SUM(2100/68)*H5 -> 46.484118 | X5: =SUM(S5:W5) -> 1143.6974 | Y5: =SUM(11623/68)*H5 -> 257.27852 | AA5: =SUM(55.62/68)*H5 -> 1.2311651 | AB5: =SUM(Y5:AA5) -> 258.50969 | AC5: 7.3 | AD5: =SUM(AB5*AC5) -> 1887.1207 | AE5: =SUM(X5+AD5) -> 3030.8182 | AF5: =SUM(P5-AE5) -> 298.73183
C6: 241127000004 | D6: 45636 | E6: 吕沛霖 | F6: 喵喵速运-Layne | G6: Candice Ding | H6: 2.3335 | I6: 2600 | K6: 1863312 | M6: =SUM(K6/N6) -> 1600 | N6: 1164.57 | O6: 7.28 | P6: =SUM(N6*O6) -> 8478.0696 | S6: =SUM(49568.5/68)*H6 -> 1701.0014 | U6: =SUM(2100/68)*H6 -> 72.063971 | X6: =SUM(S6:W6) -> 1773.0654 | Y6: =SUM(11623/68)*H6 -> 398.85692 | AA6: =SUM(55.62/68)*H6 -> 1.9086657 | AB6: =SUM(Y6:AA6) -> 400.76558 | AC6: 7.3 | AD6: =SUM(AB6*AC6) -> 2925.5888 | AE6: =SUM(X6+AD6) -> 4698.6541 | AF6: =SUM(P6-AE6) -> 3779.4155
C7: 241128000012 | D7: 45636 | E7: Bella | F7: Bella Chan | G7: FENG | H7: 0.196 | I7: 106 | K7: 98784 | M7: =SUM(K7/N7) -> 1679.9994 | N7: 58.80002 | O7: 7.3 | P7: =SUM(N7*O7) -> 429.24015 | S7: =SUM(49568.5/68)*H7 -> 142.87391 | U7: =SUM(2100/68)*H7 -> 6.0529412 | X7: =SUM(S7:W7) -> 148.92685 | Y7: =SUM(11623/68)*H7 -> 33.501588 | AA7: =SUM(55.62/68)*H7 -> 0.16031647 | AB7: =SUM(Y7:AA7) -> 33.661905 | AC7: 7.3 | AD7: =SUM(AB7*AC7) -> 245.7319 | AE7: =SUM(X7+AD7) -> 394.65876 | AF7: =SUM(P7-AE7) -> 34.581389
C8: 241202000044 | D8: 45636 | E8: 黄颖 | F8: ying | G8: Jacky | H8: 3.774 | I8: 1521 | K8: 1698783.8 | M8: =SUM(K8/N8) -> 1579.397 | N8: 1075.5901 | O8: 7.27 | P8: =SUM(N8*O8) -> 7819.54 | S8: =SUM(49568.5/68)*H8 -> 2751.0518 | U8: =SUM(2100/68)*H8 -> 116.55 | X8: =SUM(S8:W8) -> 2867.6017 | Y8: =SUM(11623/68)*H8 -> 645.0765 | AA8: =SUM(55.62/68)*H8 -> 3.08691 | AB8: =SUM(Y8:AA8) -> 648.16341 | AC8: 7.3 | AD8: =SUM(AB8*AC8) -> 4731.5929 | AE8: =SUM(X8+AD8) -> 7599.1946 | AF8: =SUM(P8-AE8) -> 220.34538
C9: 241203000015 | D9: 45636 | E9: Bella | F9: Bella Chan | G9: zhong zi xin | H9: 7.8671 | I9: 16682 | J9: 33835.5 | P9: =SUM(J9) -> 33835.5 | S9: =SUM(49568.5/68)*H9 -> 5734.711 | U9: =SUM(2100/68)*H9 -> 242.95456 | X9: =SUM(S9:W9) -> 5977.6655 | Y9: =SUM(11623/68)*H9 -> 1344.6956 | AA9: =SUM(55.62/68)*H9 -> 6.434825 | AB9: =SUM(Y9:AA9) -> 1351.1305 | AC9: 7.3 | AD9: =SUM(AB9*AC9) -> 9863.2524 | AE9: =SUM(X9+AD9) -> 15840.918 | AF9: =SUM(P9-AE9) -> 17994.582
C10: 241204000049 | D10: 45636 | E10: 罗珮文 | F10: Shirley | G10: Yusky | H10: 14.985 | I10: 2696 | K10: 6707917.9 | M10: =SUM(K10/N10) -> 1582.8774 | N10: 4237.8 | O10: 7.18 | P10: =SUM(N10*O10) -> 30427.404 | S10: =SUM(49568.5/68)*H10 -> 10923.294 | U10: =SUM(2100/68)*H10 -> 462.77206 | X10: =SUM(S10:W10) -> 11386.066 | Y10: =SUM(11623/68)*H10 -> 2561.3332 | AA10: =SUM(55.62/68)*H10 -> 12.256849 | AB10: =SUM(Y10:AA10) -> 2573.59 | AC10: 7.3 | AD10: =SUM(AB10*AC10) -> 18787.207 | AE10: =SUM(X10+AD10) -> 30173.273 | AF10: =SUM(P10-AE10) -> 254.13115
C11: 241204000051 | D11: 45636 | E11: 罗珮文 | F11: Shirley | G11: Yusky | H11: 2.1818 | I11: 358 | K11: 966443.8 | M11: =SUM(K11/N11) -> 1582 | N11: 610.9 | O11: 7.18 | P11: =SUM(N11*O11) -> 4386.262 | S11: =SUM(49568.5/68)*H11 -> 1590.4199 | U11: =SUM(2100/68)*H11 -> 67.379118 | X11: =SUM(S11:W11) -> 1657.799 | Y11: =SUM(11623/68)*H11 -> 372.92737 | AA11: =SUM(55.62/68)*H11 -> 1.7845841 | AB11: =SUM(Y11:AA11) -> 374.71196 | AC11: 7.3 | AD11: =SUM(AB11*AC11) -> 2735.3973 | AE11: =SUM(X11+AD11) -> 4393.1963 | AF11: =SUM(P11-AE11) -> -6.9343095
C12: 241205000007 | D12: 45636 | E12: 黄颖 | F12: ying | G12: Jacky | H12: 1.2288 | I12: 508 | K12: 552776.25 | M12: =SUM(K12/N12) -> 1578.4138 | N12: 350.20996 | O12: 7.27 | P12: =SUM(N12*O12) -> 2546.0264 | S12: =SUM(49568.5/68)*H12 -> 895.73195 | U12: =SUM(2100/68)*H12 -> 37.948235 | X12: =SUM(S12:W12) -> 933.68019 | Y12: =SUM(11623/68)*H12 -> 210.03445 | AA12: =SUM(55.62/68)*H12 -> 1.0050861 | AB12: =SUM(Y12:AA12) -> 211.03953 | AC12: 7.3 | AD12: =SUM(AB12*AC12) -> 1540.5886 | AE12: =SUM(X12+AD12) -> 2474.2688 | AF12: =SUM(P12-AE12) -> 71.757629
C13: 241206000037 | D13: 45636 | E13: Sam.Pao | F13: Sam.Pao | G13: Mr. Jiang | H13: 0.6414 | I13: 108 | J13: 2673 | P13: =SUBTOTAL(9,J13) -> 2673 | S13: =SUM(49568.5/68)*H13 -> 467.54759 | U13: =SUM(2100/68)*H13 -> 19.807941 | V13: 300 | X13: =SUM(S13:W13) -> 787.35553 | Y13: =SUM(11623/68)*H13 -> 109.63224 | AA13: =SUM(55.62/68)*H13 -> 0.52462747 | AB13: =SUM(Y13:AA13) -> 110.15687 | AC13: 7.3 | AD13: =SUM(AB13*AC13) -> 804.14512 | AE13: =SUM(X13+AD13) -> 1591.5006 | AF13: =SUM(P13-AE13) -> 1081.4994
C14: 241206000040 | D14: 45636 | E14: Sam.Pao | F14: Sam.Pao | G14: Mr. Jiang | H14: 0.7876 | I14: 213 | J14: 2732 | P14: =SUBTOTAL(9,J14) -> 2732 | S14: =SUM(49568.5/68)*H14 -> 574.11986 | U14: =SUM(2100/68)*H14 -> 24.322941 | V14: 300 | X14: =SUM(S14:W14) -> 898.4428 | Y14: =SUM(11623/68)*H14 -> 134.62169 | AA14: =SUM(55.62/68)*H14 -> 0.64421047 | AB14: =SUM(Y14:AA14) -> 135.2659 | AC14: 7.3 | AD14: =SUM(AB14*AC14) -> 987.44106 | AE14: =SUM(X14+AD14) -> 1885.8839 | AF14: =SUM(P14-AE14) -> 846.11614
C15: 241216000026 | D15: 45638 | E15: 陆总 | F15: 陆梓龙 | G15: luk | H15: 12.7436 | I15: 1324.23 | J15: 22939.2 | P15: =SUBTOTAL(9,J15) -> 22939.2 | S15: =SUM(49568.5/68)*H15 -> 9289.4285 | U15: =SUM(2100/68)*H15 -> 393.55235 | X15: =SUM(S15:W15) -> 9682.9808 | Y15: =SUM(11623/68)*H15 -> 2178.2186 | AA15: =SUM(55.62/68)*H15 -> 10.423515 | AB15: =SUM(Y15:AA15) -> 2188.6421 | AC15: 7.3 | AD15: =SUM(AB15*AC15) -> 15977.087 | AE15: =SUM(X15+AD15) -> 25660.068 | AF15: =SUM(P15-AE15) -> -2720.8681
C16: 241208000009 | D16: 45636 | E16: 无人 | F16: Mailmail Abv sales person 1 | G16: Obetta U | H16: 4.1388 | I16: 540 | K16: 2050281 | M16: =SUM(K16/N16) -> 1597.9993 | N16: 1283.03 | O16: 7.27 | P16: =SUM(N16*O16) -> 9327.6281 | S16: =SUM(49568.5/68)*H16 -> 3016.9722 | U16: =SUM(2100/68)*H16 -> 127.81588 | X16: =SUM(S16:W16) -> 3144.7881 | Y16: =SUM(11623/68)*H16 -> 707.43048 | AA16: =SUM(55.62/68)*H16 -> 3.3852949 | AB16: =SUM(Y16:AA16) -> 710.81577 | AC16: 7.3 | AD16: =SUM(AB16*AC16) -> 5188.9551 | AE16: =SUM(X16+AD16) -> 8333.7432 | AF16: =SUM(P16-AE16) -> 993.88491
C17: 241210000005 | D17: 45636 | E17: 罗珮文 | F17: Shirley | G17: Abubakar Badaru Abubakar | H17: 17.6161 | I17: 1662 | K17: 7918392 | M17: =SUM(K17/N17) -> 1550 | N17: 5108.64 | O17: 7.27 | P17: =SUM(N17*O17) -> 37139.813 | S17: =SUM(49568.5/68)*H17 -> 12841.23 | U17: =SUM(2100/68)*H17 -> 544.02662 | V17: 200 | X17: =SUM(S17:W17) -> 13585.257 | Y17: =SUM(11623/68)*H17 -> 3011.0578 | AA17: =SUM(55.62/68)*H17 -> 14.408934 | AB17: =SUM(Y17:AA17) -> 3025.4667 | AC17: 7.3 | AD17: =SUM(AB17*AC17) -> 22085.907 | AE17: =SUM(X17+AD17) -> 35671.164 | AF17: =SUM(P17-AE17) -> 1468.6488
A18: 合计 | J18: =SUM(J4:J4) -> 0 | N18: =SUM(N4:N4) -> 0 | P18: =SUM(P4:P4) -> 0 | Q18: =SUM(Q4:Q4) -> 0 | X18: =SUM(X4:X4) -> 0 | AD18: =SUM(AD4:AD4) -> 0 | AF18: =SUM(AF4:AF17) -> 24315.892

Sheet JOB120376
A1: 2024年12月份LOS毛利表（海运）
A2: PSL表 | B2: 体积cbm | C2: 72.8326
A3: JOB | B3: 集装编号 | C3: 运单编号 | D3: 日期 | E3: 业务 | F3: 发货人 | G3: 收货人 | H3: 计费体积 | I3: 计费重量 | J3: 应 收 | Q3: 总应收 | R3: 起 运 港 成 本 | W3: 代垫运费 | X3: 起运港成本 合计 | Y3: 目的港成本 | AE3: 总支出 | AF3: 利润
J4: 应收RMB | K4: LOS Income(NGN)收到(奈拉) | L4: LOS 收到USD | M4: 美元汇率 dollar currency rate | N4: 应收 到付款USD | O4: 汇率 | P4: 人民币 | R4: 代理商 | S4: 运费+出口报关费 | T4: 提货费 | U4: 装卸费 | V4: 包装费 | Y4: 进口报关费 | Z4: 到门配送费 | AA4: 转运费 | AB4: 目的港支出 | AC4: 汇率 | AD4: 人民币 | AE4: 起运港+目的港
A5: JOB120376 | B5: COLL004324 | C5: 241122000025 | D5: 45636 | E5: 吕沛霖 | F5: 喵喵速运-Layne | G5: WENDY | H5: 3.6276 | I5: 1507 | K5: 2696680 | M5: =SUM(K5/N5) -> 1630.0048 | N5: 1654.4 | O5: 7.27 | P5: =SUM(N5*O5) -> 12027.488 | Q5: =SUM(P5:P12) -> 148560.87 | R5: 登凯=46552.5 报关=500 拖车费=1670 杂费=61 过磅费=68 | S5: =SUM(48851.5/68)*H5 -> 2606.0838 | U5: =SUM(1000/68)*H5 -> 53.347059 | X5: =SUM(S5:W5) -> 2659.4309 | Y5: =SUM(11570.25/68)*H5 -> 617.23881 | Z5: 315.51 | AA5: =SUM(140.12/68)*H5 -> 7.4749899 | AB5: =SUM(Y5:AA5) -> 940.2238 | AC5: 7.25 | AD5: =SUM(AB5*AC5) -> 6816.6225 | AE5: =SUM(X5+AD5) -> 9476.0534 | AF5: =SUM(P5-AE5) -> 2551.4346
C6: 241202000029 | D6: 45636 | E6: 吕沛霖 | F6: 喵喵速运-Layne | G6: Mr. Wen Pu | H6: 8.2313 | I6: 1683 | K6: 4862127 | M6: =SUM(K6/N6) -> 1630 | N6: 2982.9 | O6: 7.28 | P6: =SUM(N6*O6) -> 21715.512 | S6: =SUM(48851.5/68)*H6 -> 5913.4022 | U6: =SUM(1000/68)*H6 -> 121.04853 | X6: =SUM(S6:W6) -> 6034.4508 | Y6: =SUM(11570.25/68)*H6 -> 1400.5617 | Z6: 715.9 | AA6: =SUM(140.12/68)*H6 -> 16.96132 | AB6: =SUM(Y6:AA6) -> 2133.4231 | AC6: 7.25 | AD6: =SUM(AB6*AC6) -> 15467.317 | AE6: =SUM(X6+AD6) -> 21501.768 | AF6: =SUM(P6-AE6) -> 213.744
C7: 241203000014 | D7: 45636 | E7: Bella | F7: Bella Chan | G7: zhong zi xin | H7: 13.3392 | I7: 17441 | J7: 35368.5 | P7: =SUM(J7) -> 35368.5 | S7: =SUM(48851.5/68)*H7 -> 9582.9401 | U7: =SUM(1000/68)*H7 -> 196.16471 | X7: =SUM(S7:W7) -> 9779.1048 | Y7: =SUM(11570.25/68)*H7 -> 2269.6747 | AA7: =SUM(140.12/68)*H7 -> 27.486599 | AB7: =SUM(Y7:AA7) -> 2297.1613 | AC7: 7.25 | AD7: =SUM(AB7*AC7) -> 16654.419 | AE7: =SUM(X7+AD7) -> 26433.524 | AF7: =SUM(P7-AE7) -> 8934.9758
C8: 241204000017 | D8: 45636 | E8: 吕沛霖 | F8: 喵喵速运-Layne | G8: Frank | H8: 0.5672 | I8: 104 | K8: 270180 | M8: =SUM(K8/N8) -> 1580 | N8: 171 | O8: 7.29 | P8: =SUM(N8*O8) -> 1246.59 | S8: =SUM(48851.5/68)*H8 -> 407.47898 | U8: =SUM(1000/68)*H8 -> 8.3411765 | X8: =SUM(S8:W8) -> 415.82016 | Y8: =SUM(11570.25/68)*H8 -> 96.509497 | Z8: 49.33 | AA8: =SUM(140.12/68)*H8 -> 1.1687656 | AB8: =SUM(Y8:AA8) -> 147.00826 | AC8: 7.25 | AD8: =SUM(AB8*AC8) -> 1065.8099 | AE8: =SUM(X8+AD8) -> 1481.6301 | AF8: =SUM(P8-AE8) -> -235.04006
C9: 241209000071 | D9: 45636 | E9: Sam.Pao | F9: Sam.Pao | G9: ShanShan | H9: 0.1971 | I9: 30.5 | J9: 788.4 | P9: =SUBTOTAL(9,J9) -> 788.4 | S9: =SUM(48851.5/68)*H9 -> 141.59751 | U9: =SUM(1000/68)*H9 -> 2.8985294 | X9: =SUM(S9:W9) -> 144.49604 | Y9: =SUM(11570.25/68)*H9 -> 33.53671 | Z9: 0.84 | AA9: =SUM(140.12/68)*H9 -> 0.40614194 | AB9: =SUM(Y9:AA9) -> 34.782852 | AC9: 7.25 | AD9: =SUM(AB9*AC9) -> 252.17568 | AE9: =SUM(X9+AD9) -> 396.67172 | AF9: =SUM(P9-AE9) -> 391.72828
C10: 241216000026 | D10: 45638 | E10: 陆总 | F10: 陆梓龙 | G10: luk | H10: 11.0893 | I10: 1146.94 | J10: 19958.4 | P10: =SUBTOTAL(9,J10) -> 19958.4 | S10: =SUM(48851.5/68)*H10 -> 7966.602 | U10: =SUM(1000/68)*H10 -> 163.07794 | X10: =SUM(S10:W10) -> 8129.68 | Y10: =SUM(11570.25/68)*H10 -> 1886.8525 | AA10: =SUM(140.12/68)*H10 -> 22.850481 | AB10: =SUM(Y10:AA10) -> 1909.703 | AC10: 7.25 | AD10: =SUM(AB10*AC10) -> 13845.347 | AE10: =SUM(X10+AD10) -> 21975.027 | AF10: =SUM(P10-AE10) -> -2016.627
C11: 241210000006 | D11: 45636 | E11: 罗珮文 | F11: Shirley | G11: SKY JET | H11: 35.4 | I11: 5354 | J11: 56540.88 | P11: =SUBTOTAL(9,J11) -> 56540.88 | S11: =SUM(48851.5/68)*H11 -> 25431.516 | U11: =SUM(1000/68)*H11 -> 520.58824 | X11: =SUM(S11:W11) -> 25952.104 | Y11: =SUM(11570.25/68)*H11 -> 6023.336 | AA11: =SUM(140.12/68)*H11 -> 72.944824 | AB11: =SUM(Y11:AA11) -> 6096.2809 | AC11: 7.25 | AD11: =SUM(AB11*AC11) -> 44198.036 | AE11: =SUM(X11+AD11) -> 70150.141 | AF11: =SUM(P11-AE11) -> -13609.261
C12: 241216000056 | D12: 45636 | E12: 吕沛霖 | F12: 喵喵速运-Layne | G12: LEO WEI | H12: 0.3809 | I12: 90 | K12: 197726.1 | M12: =SUM(K12/N12) -> 1573 | N12: 125.7 | O12: 7.28 | P12: =SUM(N12*O12) -> 915.096 | S12: =SUM(48851.5/68)*H12 -> 273.64024 | U12: =SUM(1000/68)*H12 -> 5.6014706 | X12: =SUM(S12:W12) -> 279.24171 | Y12: =SUM(11570.25/68)*H12 -> 64.810415 | AA12: =SUM(140.12/68)*H12 -> 0.78487806 | AB12: =SUM(Y12:AA12) -> 65.595293 | AC12: 7.25 | AD12: =SUM(AB12*AC12) -> 475.56588 | AE12: =SUM(X12+AD12) -> 754.80759 | AF12: =SUM(P12-AE12) -> 160.28841
A13: 合计 | J13: =SUM(J4:J4) -> 0 | N13: =SUM(N4:N4) -> 0 | P13: =SUM(P4:P4) -> 0 | Q13: =SUM(Q4:Q4) -> 0 | X13: =SUM(X4:X4) -> 0 | AD13: =SUM(AD4:AD4) -> 0 | AF13: =SUM(AF4:AF12) -> -3608.7565

Sheet JOB120381
A1: 2024年12月份LOS毛利表（海运）
A2: PSL表 | B2: 体积cbm | C2: 72.3035
A3: JOB | B3: 集装编号 | C3: 运单编号 | D3: 日期 | E3: 业务 | F3: 发货人 | G3: 收货人 | H3: 计费体积 | I3: 计费重量 | J3: 应 收 | Q3: 总应收 | R3: 起 运 港 成 本 | W3: 代垫运费 | X3: 起运港成本 合计 | Y3: 目的港成本 | AE3: 总支出 | AF3: 利润
J4: 应收RMB | K4: LOS Income(NGN)收到(奈拉) | L4: LOS 收到USD | M4: 美元汇率 dollar currency rate | N4: 应收 到付款USD | O4: 汇率 | P4: 人民币 | R4: 代理商 | S4: 运费+出口报关费 | T4: 提货费 | U4: 装卸费 | V4: 包装费 | Y4: 进口报关费 | Z4: 到门配送费 | AA4: 转运费 | AB4: 目的港支出 | AC4: 汇率 | AD4: 人民币 | AE4: 起运港+目的港
A5: JOB120381 | B5: COLL004325 | C5: 241023000034 | D5: 45638 | E5: Sam.Pao | F5: Sam.Pao | G5: Nick Wang | H5: 0.3134 | I5: 126 | J5: 906 | P5: =SUBTOTAL(9,J5) -> 906 | Q5: =SUM(P5:P14) -> 146435.81 | R5: 登凯=46552.5 报关=300 拖车费=1670 杂费=166 过磅费=71 | S5: =SUM(48759.5/68)*H5 -> 224.72393 | U5: =SUM(1800/68)*H5 -> 8.2958824 | X5: =SUM(S5:W5) -> 233.01981 | Y5: =SUM(11621.97/68)*H5 -> 53.563609 | AA5: =SUM(140.12/68)*H5 -> 0.64578835 | AB5: =SUM(Y5:AA5) -> 54.209397 | AC5: 7.25 | AD5: =SUM(AB5*AC5) -> 393.01813 | AE5: =SUM(X5+AD5) -> 626.03794 | AF5: =SUM(P5-AE5) -> 279.96206
C6: 241115000013 | D6: 45638 | E6: Sam.Pao | F6: Sam.Pao | G6: ChenGaoHong | H6: 0.367 | I6: 106 | J6: 780 | P6: =SUBTOTAL(9,J6) -> 780 | S6: =SUM(48759.5/68)*H6 -> 263.15789 | U6: =SUM(1800/68)*H6 -> 9.7147059 | V6: 240 | X6: =SUM(S6:W6) -> 512.8726 | Y6: =SUM(11621.97/68)*H6 -> 62.724456 | AA6: =SUM(140.12/68)*H6 -> 0.75623588 | AB6: =SUM(Y6:AA6) -> 63.480692 | AC6: 7.25 | AD6: =SUM(AB6*AC6) -> 460.23501 | AE6: =SUM(X6+AD6) -> 973.10761 | AF6: =SUM(P6-AE6) -> -193.10761
C7: 241126000049 | D7: 45638 | E7: Sam.Pao | F7: Sam.Pao | G7: AiGeLi | H7: 2.7422 | I7: 1148 | J7: 7878 | P7: =SUBTOTAL(9,J7) -> 7878 | S7: =SUM(48759.5/68)*H7 -> 1966.2985 | U7: =SUM(1800/68)*H7 -> 72.587647 | V7: 1000 | X7: =SUM(S7:W7) -> 3038.8862 | Y7: =SUM(11621.97/68)*H7 -> 468.67303 | AA7: =SUM(140.12/68)*H7 -> 5.6505451 | AB7: =SUM(Y7:AA7) -> 474.32358 | AC7: 7.25 | AD7: =SUM(AB7*AC7) -> 3438.8459 | AE7: =SUM(X7+AD7) -> 6477.7321 | AF7: =SUM(P7-AE7) -> 1400.2679
C8: 241209000082 | D8: 45638 | E8: 吕沛霖 | F8: 喵喵速运-Layne | G8: BI AN | H8: 2.4778 | I8: 1373 | J8: 6015.2 | P8: =SUBTOTAL(9,J8) -> 6015.2 | S8: =SUM(48759.5/68)*H8 -> 1776.7101 | U8: =SUM(1800/68)*H8 -> 65.588824 | X8: =SUM(S8:W8) -> 1842.299 | Y8: =SUM(11621.97/68)*H8 -> 423.48408 | AA8: =SUM(140.12/68)*H8 -> 5.1057255 | AB8: =SUM(Y8:AA8) -> 428.5898 | AC8: 7.25 | AD8: =SUM(AB8*AC8) -> 3107.2761 | AE8: =SUM(X8+AD8) -> 4949.575 | AF8: =SUM(P8-AE8) -> 1065.625
C9: 241209000084 | D9: 45638 | E9: 罗珮文 | F9: Shirley | G9: Yusky | H9: 3.5753 | I9: 397 | K9: 1527152.1 | M9: =SUM(K9/N9) -> 1582 | N9: 965.33 | O9: 7.18 | P9: =SUM(N9*O9) -> 6931.0694 | S9: =SUM(48759.5/68)*H9 -> 2563.6741 | U9: =SUM(1800/68)*H9 -> 94.640294 | X9: =SUM(S9:W9) -> 2658.3144 | Y9: =SUM(11621.97/68)*H9 -> 611.05926 | AA9: =SUM(140.12/68)*H9 -> 7.3672211 | AB9: =SUM(Y9:AA9) -> 618.42648 | AC9: 7.25 | AD9: =SUM(AB9*AC9) -> 4483.592 | AE9: =SUM(X9+AD9) -> 7141.9064 | AF9: =SUM(P9-AE9) -> -210.83697
C10: 241211000002 | D10: 45638 | E10: Bella | F10: Bella Chan | G10: zhong zi xin | H10: 13.0793 | I10: 19192 | J10: 38909 | P10: =SUM(J10) -> 38909 | S10: =SUM(48759.5/68)*H10 -> 9378.5313 | U10: =SUM(1800/68)*H10 -> 346.21676 | X10: =SUM(S10:W10) -> 9724.7481 | Y10: =SUM(11621.97/68)*H10 -> 2235.4005 | AA10: =SUM(140.12/68)*H10 -> 26.951052 | AB10: =SUM(Y10:AA10) -> 2262.3515 | AC10: 7.25 | AD10: =SUM(AB10*AC10) -> 16402.049 | AE10: =SUM(X10+AD10) -> 26126.797 | AF10: =SUM(P10-AE10) -> 12782.203
C11: 241211000045 | D11: 45638 | E11: 罗珮文 | F11: Shirley | G11: Yusky | H11: 10.4649 | I11: 835 | K11: 4470020.1 | M11: =SUM(K11/N11) -> 1582 | N11: 2825.55 | O11: 7.18 | P11: =SUM(N11*O11) -> 20287.449 | S11: =SUM(48759.5/68)*H11 -> 7503.8719 | U11: =SUM(1800/68)*H11 -> 277.01206 | X11: =SUM(S11:W11) -> 7780.884 | Y11: =SUM(11621.97/68)*H11 -> 1788.5699 | AA11: =SUM(140.12/68)*H11 -> 21.56385 | AB11: =SUM(Y11:AA11) -> 1810.1338 | AC11: 7.25 | AD11: =SUM(AB11*AC11) -> 13123.47 | AE11: =SUM(X11+AD11) -> 20904.354 | AF11: =SUM(P11-AE11) -> -616.90475
C12: 241212000002 | D12: 45638 | E12: 罗珮文 | F12: Shirley | G12: SKY JET | H12: 29.57 | I12: 4902 | J12: 47229.2 | P12: =SUBTOTAL(9,J12) -> 47229.2 | S12: =SUM(48759.5/68)*H12 -> 21203.212 | U12: =SUM(1800/68)*H12 -> 782.73529 | X12: =SUM(S12:W12) -> 21985.947 | Y12: =SUM(11621.97/68)*H12 -> 5053.8478 | AA12: =SUM(140.12/68)*H12 -> 60.931594 | AB12: =SUM(Y12:AA12) -> 5114.7794 | AC12: 7.25 | AD12: =SUM(AB12*AC12) -> 37082.151 | AE12: =SUM(X12+AD12) -> 59068.098 | AF12: =SUM(P12-AE12) -> -11838.898
C13: 241212000013 | D13: 45638 | E13: 陆总 | F13: 陆梓龙 | G13: luk | H13: 0.0957 | I13: 26 | J13: 186.05 | P13: =SUBTOTAL(9,J13) -> 186.05 | S13: =SUM(48759.5/68)*H13 -> 68.621826 | U13: =SUM(1800/68)*H13 -> 2.5332353 | X13: =SUM(S13:W13) -> 71.155061 | Y13: =SUM(11621.97/68)*H13 -> 16.356214 | AA13: =SUM(140.12/68)*H13 -> 0.19719829 | AB13: =SUM(Y13:AA13) -> 16.553412 | AC13: 7.25 | AD13: =SUM(AB13*AC13) -> 120.01224 | AE13: =SUM(X13+AD13) -> 191.1673 | AF13: =SUM(P13-AE13) -> -5.1172977
C14: 241216000026 | D14: 45638 | E14: 陆总 | F14: 陆梓龙 | G14: luk | H14: 9.6179 | I14: 931.83 | J14: 17313.84 | P14: =SUBTOTAL(9,J14) -> 17313.84 | S14: =SUM(48759.5/68)*H14 -> 6896.5293 | U14: =SUM(1800/68)*H14 -> 254.59147 | X14: =SUM(S14:W14) -> 7151.1208 | Y14: =SUM(11621.97/68)*H14 -> 1643.808 | AA14: =SUM(140.12/68)*H14 -> 19.818532 | AB14: =SUM(Y14:AA14) -> 1663.6266 | AC14: 7.25 | AD14: =SUM(AB14*AC14) -> 12061.292 | AE14: =SUM(X14+AD14) -> 19212.413 | AF14: =SUM(P14-AE14) -> -1898.5733
A15: 合计 | J15: =SUM(J4:J4) -> 0 | N15: =SUM(N4:N4) -> 0 | P15: =SUM(P4:P4) -> 0 | Q15: =SUM(Q4:Q4) -> 0 | X15: =SUM(X4:X4) -> 0 | AD15: =SUM(AD4:AD4) -> 0 | AF15: =SUM(AF4:AF14) -> 764.62021

Sheet JOB120387
A1: 2024年12月份LOS毛利表（海运）
A2: PSL表 | B2: 体积cbm | C2: 73.6909
A3: JOB | B3: 集装编号 | C3: 运单编号 | D3: 日期 | E3: 业务 | F3: 发货人 | G3: 收货人 | H3: 计费体积 | I3: 计费重量 | J3: 应 收 | Q3: 总应收 | R3: 起 运 港 成 本 | W3: 代垫运费 | X3: 起运港成本 合计 | Y3: 目的港成本 | AE3: 总支出 | AF3: 利润
J4: 应收RMB | K4: LOS Income(NGN)收到(奈拉) | L4: LOS 收到USD | M4: 美元汇率 dollar currency rate | N4: 应收 到付款USD | O4: 汇率 | P4: 人民币 | R4: 代理商 | S4: 运费+出口报关费 | T4: 提货费 | U4: 装卸费 | V4: 包装费 | Y4: 进口报关费 | Z4: 到门配送费 | AA4: 转运费 | AB4: 目的港支出 | AC4: 汇率 | AD4: 人民币 | AE4: 起运港+目的港
A5: JOB120387 | B5: COLL004326 | C5: 241127000030 | D5: 45643 | E5: 黄颖 | F5: ying | G5: baikaibo | H5: 0.4598 | I5: 114 | J5: 860.5 | P5: =SUBTOTAL(9,J5) -> 860.5 | Q5: =SUM(P5:P27) -> 185884.77 | R5: 登凯=45460.5 报关=2800 拖车费=1670 杂费=86 过磅费=64 | S5: =SUM(50080.5/68)*H5 -> 338.63256 | U5: =SUM(2000/68)*H5 -> 13.523529 | X5: =SUM(S5:W5) -> 352.15609 | Y5: =SUM(12270/68)*H5 -> 82.966853 | Z5: 76.28 | AA5: =SUM(55.42/68)*H5 -> 0.374737 | AB5: =SUM(Y5:AA5) -> 159.62159 | AC5: 7.25 | AD5: =SUM(AB5*AC5) -> 1157.2565 | AE5: =SUM(X5+AD5) -> 1509.4126 | AF5: =SUM(P5-AE5) -> -648.91261
C6: 241209000067 | D6: 45643 | E6: Sam.Pao | F6: Sam.Pao | G6: MaiKaiNian | H6: 0.023 | I6: 43 | J6: 152.5 | P6: =SUBTOTAL(9,J6) -> 152.5 | S6: =SUM(50080.5/68)*H6 -> 16.938993 | U6: =SUM(2000/68)*H6 -> 0.67647059 | X6: =SUM(S6:W6) -> 17.615463 | Y6: =SUM(12270/68)*H6 -> 4.1501471 | AA6: =SUM(55.42/68)*H6 -> 0.018745 | AB6: =SUM(Y6:AA6) -> 4.1688921 | AC6: 7.25 | AD6: =SUM(AB6*AC6) -> 30.224467 | AE6: =SUM(X6+AD6) -> 47.839931 | AF6: =SUM(P6-AE6) -> 104.66007
C7: 241209000092 | D7: 45643 | E7: 黄颖 | F7: ying | G7: yuhuichao | H7: 0.1652 | I7: 33 | J7: 565 | P7: =SUBTOTAL(9,J7) -> 565 | S7: =SUM(50080.5/68)*H7 -> 121.66616 | U7: =SUM(2000/68)*H7 -> 4.8588235 | X7: =SUM(S7:W7) -> 126.52498 | Y7: =SUM(12270/68)*H7 -> 29.808882 | Z7: 19.6 | AA7: =SUM(55.42/68)*H7 -> 0.134638 | AB7: =SUM(Y7:AA7) -> 49.54352 | AC7: 7.25 | AD7: =SUM(AB7*AC7) -> 359.19052 | AE7: =SUM(X7+AD7) -> 485.7155 | AF7: =SUM(P7-AE7) -> 79.284498
C8: 241210000030 | D8: 45643 | E8: 黄颖 | F8: ying | G8: Frank | H8: 0.5114 | I8: 65 | K8: 312494 | M8: =SUM(K8/N8) -> 1651.485 | N8: 189.22 | O8: 7.27 | P8: =SUM(N8*O8) -> 1375.6294 | S8: =SUM(50080.5/68)*H8 -> 376.63482 | U8: =SUM(2000/68)*H8 -> 15.041176 | X8: =SUM(S8:W8) -> 391.676 | Y8: =SUM(12270/68)*H8 -> 92.277618 | AA8: =SUM(55.42/68)*H8 -> 0.416791 | AB8: =SUM(Y8:AA8) -> 92.694409 | AC8: 7.25 | AD8: =SUM(AB8*AC8) -> 672.03446 | AE8: =SUM(X8+AD8) -> 1063.7105 | AF8: =SUM(P8-AE8) -> 311.91894
C9: 241210000041 | D9: 45643 | E9: 黄颖 | F9: ying | G9: Mr Rell | H9: 0.7637 | I9: 207 | J9: 1810.4 | P9: =SUBTOTAL(9,J9) -> 1810.4 | S9: =SUM(50080.5/68)*H9 -> 562.4482 | U9: =SUM(2000/68)*H9 -> 22.461765 | X9: =SUM(S9:W9) -> 584.90997 | Y9: =SUM(12270/68)*H9 -> 137.80293 | AA9: =SUM(55.42/68)*H9 -> 0.6224155 | AB9: =SUM(Y9:AA9) -> 138.42534 | AC9: 7.25 | AD9: =SUM(AB9*AC9) -> 1003.5837 | AE9: =SUM(X9+AD9) -> 1588.4937 | AF9: =SUM(P9-AE9) -> 221.9063
C10: 241211000027 | D10: 45643 | E10: Sam.Pao | F10: Sam.Pao | G10: ShanShan | H10: 23.8172 | I10: 4565 | J10: 54267 | P10: =SUBTOTAL(9,J10) -> 54267 | S10: =SUM(50080.5/68)*H10 -> 17540.842 | U10: =SUM(2000/68)*H10 -> 700.50588 | X10: =SUM(S10:W10) -> 18241.348 | Y10: =SUM(12270/68)*H10 -> 4297.6036 | Z10: 136.87 | AA10: =SUM(55.42/68)*H10 -> 19.411018 | AB10: =SUM(Y10:AA10) -> 4453.8846 | AC10: 7.25 | AD10: =SUM(AB10*AC10) -> 32290.663 | AE10: =SUM(X10+AD10) -> 50532.012 | AF10: =SUM(P10-AE10) -> 3734.9883
C11: 241212000006 | D11: 45643 | E11: 黄颖 | F11: ying | G11: MISS Huang | H11: 3.0701 | I11: 1383 | K11: 1406444 | M11: =SUM(K11/N11) -> 1607.4013 | N11: 874.98 | O11: 7.3 | P11: =SUM(N11*O11) -> 6387.354 | S11: =SUM(50080.5/68)*H11 -> 2261.0609 | U11: =SUM(2000/68)*H11 -> 90.297059 | X11: =SUM(S11:W11) -> 2351.358 | Y11: =SUM(12270/68)*H11 -> 553.97246 | AA11: =SUM(55.42/68)*H11 -> 2.5021315 | AB11: =SUM(Y11:AA11) -> 556.47459 | AC11: 7.25 | AD11: =SUM(AB11*AC11) -> 4034.4408 | AE11: =SUM(X11+AD11) -> 6385.7987 | AF11: =SUM(P11-AE11) -> 1.5552554
C12: 241212000015 | D12: 45643 | E12: Sam.Pao | F12: Sam.Pao | G12: MaiKaiNian | H12: 2.957 | I12: 1339 | J12: 7123.63 | P12: =SUBTOTAL(9,J12) -> 7123.63 | S12: =SUM(50080.5/68)*H12 -> 2177.7653 | U12: =SUM(2000/68)*H12 -> 86.970588 | X12: =SUM(S12:W12) -> 2264.7359 | Y12: =SUM(12270/68)*H12 -> 533.56456 | AA12: =SUM(55.42/68)*H12 -> 2.409955 | AB12: =SUM(Y12:AA12) -> 535.97451 | AC12: 7.25 | AD12: =SUM(AB12*AC12) -> 3885.8152 | AE12: =SUM(X12+AD12) -> 6150.5511 | AF12: =SUM(P12-AE12) -> 973.07891
C13: 241213000032 | D13: 45643 | E13: 黄颖 | F13: ying | G13: sven | H13: 1.137 | I13: 240 | J13: 2906 | P13: =SUBTOTAL(9,J13) -> 2906 | S13: =SUM(50080.5/68)*H13 -> 837.37542 | U13: =SUM(2000/68)*H13 -> 33.441176 | X13: =SUM(S13:W13) -> 870.8166 | Y13: =SUM(12270/68)*H13 -> 205.16162 | Z13: 41.99 | AA13: =SUM(55.42/68)*H13 -> 0.926655 | AB13: =SUM(Y13:AA13) -> 248.07827 | AC13: 7.25 | AD13: =SUM(AB13*AC13) -> 1798.5675 | AE13: =SUM(X13+AD13) -> 2669.3841 | AF13: =SUM(P13-AE13) -> 236.61593
C14: 241213000053 | D14: 45643 | E14: 黄颖 | F14: ying | G14: sven | H14: 0.0959 | I14: 16 | J14: 228 | P14: =SUBTOTAL(9,J14) -> 228 | S14: =SUM(50080.5/68)*H14 -> 70.628235 | U14: =SUM(2000/68)*H14 -> 2.8205882 | X14: =SUM(S14:W14) -> 73.448823 | Y14: =SUM(12270/68)*H14 -> 17.304309 | Z14: 35.58 | AA14: =SUM(55.42/68)*H14 -> 0.0781585 | AB14: =SUM(Y14:AA14) -> 52.962467 | AC14: 7.25 | AD14: =SUM(AB14*AC14) -> 383.97789 | AE14: =SUM(X14+AD14) -> 457.42671 | AF14: =SUM(P14-AE14) -> -229.42671
C15: 241213000056 | D15: 45643 | E15: 无人 | F15: dejare James | G15: James | H15: 1.2461 | I15: 230 | K15: 116181 | L15: 300 | M15: =SUM(K15/N15) -> 310.76071 | N15: 373.86 | O15: 7.27 | P15: =SUM(N15*O15) -> 2717.9622 | S15: =SUM(50080.5/68)*H15 -> 917.72516 | U15: =SUM(2000/68)*H15 -> 36.65 | X15: =SUM(S15:W15) -> 954.37516 | Y15: =SUM(12270/68)*H15 -> 224.84775 | AA15: =SUM(55.42/68)*H15 -> 1.0155715 | AB15: =SUM(Y15:AA15) -> 225.86332 | AC15: 7.25 | AD15: =SUM(AB15*AC15) -> 1637.5091 | AE15: =SUM(X15+AD15) -> 2591.8842 | AF15: =SUM(P15-AE15) -> 126.07796
C16: 241214000027 | D16: 45643 | E16: Sam.Pao | F16: Sam.Pao | G16: Sampao | H16: 0.0295 | I16: 50 | J16: 555.8 | P16: =SUBTOTAL(9,J16) -> 555.8 | S16: =SUM(50080.5/68)*H16 -> 21.726099 | U16: =SUM(2000/68)*H16 -> 0.86764706 | X16: =SUM(S16:W16) -> 22.593746 | Y16: =SUM(12270/68)*H16 -> 5.3230147 | Z16: 44.59 | AA16: =SUM(55.42/68)*H16 -> 0.0240425 | AB16: =SUM(Y16:AA16) -> 49.937057 | AC16: 7.25 | AD16: =SUM(AB16*AC16) -> 362.04366 | AE16: =SUM(X16+AD16) -> 384.63741 | AF16: =SUM(P16-AE16) -> 171.16259
C17: 241128000030 | D17: 45643 | E17: Sam.Pao | F17: Sam.Pao | G17: ShanShan | H17: 6.1439 | I17: 3510 | J17: 18062 | P17: =SUBTOTAL(9,J17) -> 18062 | S17: =SUM(50080.5/68)*H17 -> 4524.8468 | U17: =SUM(2000/68)*H17 -> 180.70294 | X17: =SUM(S17:W17) -> 4705.5498 | Y17: =SUM(12270/68)*H17 -> 1108.6125 | AA17: =SUM(55.42/68)*H17 -> 5.0072785 | AB17: =SUM(Y17:AA17) -> 1113.6198 | AC17: 7.25 | AD17: =SUM(AB17*AC17) -> 8073.7437 | AE17: =SUM(X17+AD17) -> 12779.293 | AF17: =SUM(P17-AE17) -> 5282.7065
C18: 250110000026 | D18: 45643 | E18: 吕沛霖 | F18: 喵喵速运-Layne | G18: KE ZONG | H18: 1.0248 | I18: 276 | J18: 2271.15 | P18: =SUBTOTAL(9,J18) -> 2271.15 | S18: =SUM(50080.5/68)*H18 -> 754.74259 | U18: =SUM(2000/68)*H18 -> 30.141176 | X18: =SUM(S18:W18) -> 784.88377 | Y18: =SUM(12270/68)*H18 -> 184.91612 | AA18: =SUM(55.42/68)*H18 -> 0.835212 | AB18: =SUM(Y18:AA18) -> 185.75133 | AC18: 7.25 | AD18: =SUM(AB18*AC18) -> 1346.6971 | AE18: =SUM(X18+AD18) -> 2131.5809 | AF18: =SUM(P18-AE18) -> 139.56909
C19: 241126000049 | D19: 45638 | E19: Sam.Pao | F19: Sam.Pao | G19: AiGeLi | H19: 20.5166 | I19: 8722 | J19: 58944 | P19: =SUBTOTAL(9,J19) -> 58944 | S19: =SUM(50080.5/68)*H19 -> 15110.023 | U19: =SUM(2000/68)*H19 -> 603.42941 | X19: =SUM(S19:W19) -> 15713.453 | Y19: =SUM(12270/68)*H19 -> 3702.0394 | Z19: 1082.8 | AA19: =SUM(55.42/68)*H19 -> 16.721029 | AB19: =SUM(Y19:AA19) -> 4801.5605 | AC19: 7.25 | AD19: =SUM(AB19*AC19) -> 34811.313 | AE19: =SUM(X19+AD19) -> 50524.766 | AF19: =SUM(P19-AE19) -> 8419.2339
C20: 241115000013 | D20: 45638 | E20: Sam.Pao | F20: Sam.Pao | G20: ChenGaoHong | H20: 6.3827 | I20: 2355 | J20: 13563 | P20: =SUBTOTAL(9,J20) -> 13563 | S20: =SUM(50080.5/68)*H20 -> 4700.7178 | U20: =SUM(2000/68)*H20 -> 187.72647 | X20: =SUM(S20:W20) -> 4888.4442 | Y20: =SUM(12270/68)*H20 -> 1151.7019 | AA20: =SUM(55.42/68)*H20 -> 5.2019005 | AB20: =SUM(Y20:AA20) -> 1156.9038 | AC20: 7.25 | AD20: =SUM(AB20*AC20) -> 8387.5525 | AE20: =SUM(X20+AD20) -> 13275.997 | AF20: =SUM(P20-AE20) -> 287.00324
C21: 241214000030 | D21: 45643 | E21: 黄颖 | F21: ying | G21: ss | H21: 0.823 | I21: 696 | J21: 3584 | P21: =SUBTOTAL(9,J21) -> 3584 | S21: =SUM(50080.5/68)*H21 -> 606.12135 | U21: =SUM(2000/68)*H21 -> 24.205882 | X21: =SUM(S21:W21) -> 630.32723 | Y21: =SUM(12270/68)*H21 -> 148.50309 | Z21: 136.53 | AA21: =SUM(55.42/68)*H21 -> 0.670745 | AB21: =SUM(Y21:AA21) -> 285.70383 | AC21: 7.25 | AD21: =SUM(AB21*AC21) -> 2071.3528 | AE21: =SUM(X21+AD21) -> 2701.68 | AF21: =SUM(P21-AE21) -> 882.31998
C22: 241212000021 | D22: 45643 | E22: 黄颖 | F22: ying | G22: ss | H22: 1.9011 | I22: 816.18 | K22: 846007 | M22: =SUM(K22/N22) -> 1561.4459 | N22: 541.81 | O22: 7.27 | P22: =SUM(N22*O22) -> 3938.9587 | S22: =SUM(50080.5/68)*H22 -> 1400.1182 | U22: =SUM(2000/68)*H22 -> 55.914706 | X22: =SUM(S22:W22) -> 1456.0329 | Y22: =SUM(12270/68)*H22 -> 343.03672 | AA22: =SUM(55.42/68)*H22 -> 1.5493965 | AB22: =SUM(Y22:AA22) -> 344.58612 | AC22: 7.25 | AD22: =SUM(AB22*AC22) -> 2498.2493 | AE22: =SUM(X22+AD22) -> 3954.2823 | AF22: =SUM(P22-AE22) -> -15.323569
C23: 241209000079 | D23: 45643 | E23: 黄颖 | F23: ying | G23: fanglijuan | H23: 0.0757 | I23: 16 | J23: 195 | P23: =SUBTOTAL(9,J23) -> 195 | S23: =SUM(50080.5/68)*H23 -> 55.75138 | U23: =SUM(2000/68)*H23 -> 2.2264706 | X23: =SUM(S23:W23) -> 57.977851 | Y23: =SUM(12270/68)*H23 -> 13.659397 | AA23: =SUM(55.42/68)*H23 -> 0.0616955 | AB23: =SUM(Y23:AA23) -> 13.721093 | AC23: 7.25 | AD23: =SUM(AB23*AC23) -> 99.477921 | AE23: =SUM(X23+AD23) -> 157.45577 | AF23: =SUM(P23-AE23) -> 37.544228
C24: 241217000014 | D24: 45643 | E24: 朱小飞 | F24: Isabel Zhu | G24: Maryam Tukur | H24: 1.1639 | I24: 148 | K24: 687330 | M24: =SUM(K24/N24) -> 1536.0016 | N24: 447.48 | O24: 7.27 | P24: =SUM(N24*O24) -> 3253.1796 | S24: =SUM(50080.5/68)*H24 -> 857.18668 | U24: =SUM(2000/68)*H24 -> 34.232353 | X24: =SUM(S24:W24) -> 891.41903 | Y24: =SUM(12270/68)*H24 -> 210.01549 | Z24: 66.75 | AA24: =SUM(55.42/68)*H24 -> 0.9485785 | AB24: =SUM(Y24:AA24) -> 277.71406 | AC24: 7.25 | AD24: =SUM(AB24*AC24) -> 2013.427 | AE24: =SUM(X24+AD24) -> 2904.846 | AF24: =SUM(P24-AE24) -> 348.33361
C25: 241217000015 | D25: 45643 | E25: 朱小飞 | F25: Isabel Zhu | G25: Sadiq | H25: 0.322 | I25: 85 | K25: 186847 | M25: =SUM(K25/N25) -> 1582.1084 | N25: 118.1 | O25: 7.25 | P25: =SUM(N25*O25) -> 856.225 | S25: =SUM(50080.5/68)*H25 -> 237.1459 | U25: =SUM(2000/68)*H25 -> 9.4705882 | X25: =SUM(S25:W25) -> 246.61649 | Y25: =SUM(12270/68)*H25 -> 58.102059 | AA25: =SUM(55.42/68)*H25 -> 0.26243 | AB25: =SUM(Y25:AA25) -> 58.364489 | AC25: 7.25 | AD25: =SUM(AB25*AC25) -> 423.14254 | AE25: =SUM(X25+AD25) -> 669.75903 | AF25: =SUM(P25-AE25) -> 186.46597
C26: 241217000016 | D26: 45643 | E26: 罗珮文 | F26: Shirley | G26: Abubakar Badaru Abubakar | H26: 0.6596 | I26: 58 | K26: 296670 | M26: =SUM(K26/N26) -> 1550 | N26: 191.4 | O26: 7.27 | P26: =SUM(N26*O26) -> 1391.478 | S26: =SUM(50080.5/68)*H26 -> 485.78085 | U26: =SUM(2000/68)*H26 -> 19.4 | X26: =SUM(S26:W26) -> 505.18085 | Y26: =SUM(12270/68)*H26 -> 119.019 | AA26: =SUM(55.42/68)*H26 -> 0.537574 | AB26: =SUM(Y26:AA26) -> 119.55657 | AC26: 7.25 | AD26: =SUM(AB26*AC26) -> 866.78516 | AE26: =SUM(X26+AD26) -> 1371.966 | AF26: =SUM(P26-AE26) -> 19.511989
C27: 241217000024 | D27: 45643 | E27: 黄颖 | F27: ying | G27: wuchengxing | H27: 0.4017 | I27: 36 | J27: 876 | P27: =SUBTOTAL(9,J27) -> 876 | S27: =SUM(50080.5/68)*H27 -> 295.84319 | U27: =SUM(2000/68)*H27 -> 11.814706 | X27: =SUM(S27:W27) -> 307.65789 | Y27: =SUM(12270/68)*H27 -> 72.483221 | AA27: =SUM(55.42/68)*H27 -> 0.3273855 | AB27: =SUM(Y27:AA27) -> 72.810606 | AC27: 7.25 | AD27: =SUM(AB27*AC27) -> 527.87689 | AE27: =SUM(X27+AD27) -> 835.53479 | AF27: =SUM(P27-AE27) -> 40.465211
A28: 合计 | J28: =SUM(J4:J4) -> 0 | N28: =SUM(N4:N4) -> 0 | P28: =SUM(P4:P4) -> 0 | Q28: =SUM(Q4:Q4) -> 0 | X28: =SUM(X4:X4) -> 0 | AD28: =SUM(AD4:AD4) -> 0 | AF28: =SUM(AF4:AF27) -> 20710.74

Sheet JOB120390
A1: 2024年12月份LOS毛利表（海运）
A2: PSL表 | B2: 体积cbm | C2: 72.6467
A3: JOB | B3: 集装编号 | C3: 运单编号 | D3: 日期 | E3: 业务 | F3: 发货人 | G3: 收货人 | H3: 计费体积 | I3: 计费重量 | J3: 应 收 | Q3: 总应收 | R3: 起 运 港 成 本 | W3: 代垫运费 | X3: 起运港成本 合计 | Y3: 目的港成本 | AE3: 总支出 | AF3: 利润
J4: 应收RMB | K4: LOS Income(NGN)收到(奈拉) | L4: LOS 收到USD | M4: 美元汇率 dollar currency rate | N4: 应收 到付款USD | O4: 汇率 | P4: 人民币 | R4: 代理商 | S4: 运费+出口报关费 | T4: 提货费 | U4: 装卸费 | V4: 包装费 | Y4: 进口报关费 | Z4: 到门配送费 | AA4: 转运费 | AB4: 目的港支出 | AC4: 汇率 | AD4: 人民币 | AE4: 起运港+目的港
A5: JOB120390 | B5: COLL004328 | C5: 241212000021 | D5: 46010 | E5: 黄颖 | F5: ying | G5: ss | H5: 0.1207 | I5: 51.82 | K5: 53713 | M5: =SUM(K5/N5) -> 1561.4244 | N5: 34.4 | O5: 7.27 | P5: =SUM(N5*O5) -> 250.088 | Q5: =SUM(P5:P11) -> 155095.06 | R5: 登凯=45460.5 陆总=1500 拖车费=1670 杂费=86 过磅费=61 | S5: =SUM(48777.5/68)*H5 -> 86.580062 | T5: =SUM(88.88/68)*H5 -> 0.157762 | U5: =SUM(1900/68)*H5 -> 3.3725 | X5: =SUM(S5:W5) -> 90.110325 | Y5: =SUM(12037/68)*H5 -> 21.365675 | AA5: =SUM(57.52/68)*H5 -> 0.102098 | AB5: =SUM(Y5:AA5) -> 21.467773 | AC5: 7.25 | AD5: =SUM(AB5*AC5) -> 155.64135 | AE5: =SUM(X5+AD5) -> 245.75168 | AF5: =SUM(P5-AE5) -> 4.3363212
C6: 241219000026 | D6: 46010 | E6: Sam.Pao | F6: Sam.Pao | G6: ShanShan | H6: 6.1439 | I6: 3510 | J6: 18062 | P6: =SUBTOTAL(9,J6) -> 18062 | S6: =SUM(48777.5/68)*H6 -> 4407.1189 | T6: =SUM(88.88/68)*H6 -> 8.0304387 | U6: =SUM(1900/68)*H6 -> 171.66779 | X6: =SUM(S6:W6) -> 4586.8171 | Y6: =SUM(12037/68)*H6 -> 1087.5607 | AA6: =SUM(57.52/68)*H6 -> 5.1970166 | AB6: =SUM(Y6:AA6) -> 1092.7577 | AC6: 7.25 | AD6: =SUM(AB6*AC6) -> 7922.4931 | AE6: =SUM(X6+AD6) -> 12509.31 | AF6: =SUM(P6-AE6) -> 5552.6898
C7: 241219000027 | D7: 46010 | E7: 陆总 | F7: 陆梓龙 | G7: xiantian | H7: 0.9378 | I7: 1454 | J7: 4037.69 | P7: =SUBTOTAL(9,J7) -> 4037.69 | S7: =SUM(48777.5/68)*H7 -> 672.69911 | T7: =SUM(88.88/68)*H7 -> 1.2257598 | U7: =SUM(1900/68)*H7 -> 26.203235 | X7: =SUM(S7:W7) -> 700.12811 | Y7: =SUM(12037/68)*H7 -> 166.00439 | AA7: =SUM(57.52/68)*H7 -> 0.79326847 | AB7: =SUM(Y7:AA7) -> 166.79766 | AC7: 7.25 | AD7: =SUM(AB7*AC7) -> 1209.283 | AE7: =SUM(X7+AD7) -> 1909.4111 | AF7: =SUM(P7-AE7) -> 2128.2789
C8: 241219000017 | D8: 46010 | E8: 朱小飞 | F8: Isabel Zhu | G8: Halifa Success | H8: 2.2361 | I8: 234 | J8: 4542.5 | P8: =SUBTOTAL(9,J8) -> 4542.5 | S8: =SUM(48777.5/68)*H8 -> 1603.9907 | T8: =SUM(88.88/68)*H8 -> 2.9227142 | U8: =SUM(1900/68)*H8 -> 62.479265 | X8: =SUM(S8:W8) -> 1669.3927 | Y8: =SUM(12037/68)*H8 -> 395.82258 | AA8: =SUM(57.52/68)*H8 -> 1.8914775 | AB8: =SUM(Y8:AA8) -> 397.71406 | AC8: 7.25 | AD8: =SUM(AB8*AC8) -> 2883.4269 | AE8: =SUM(X8+AD8) -> 4552.8196 | AF8: =SUM(P8-AE8) -> -10.319626
C9: 241115000013 | D9: 45638 | E9: Sam.Pao | F9: Sam.Pao | G9: ChenGaoHong | H9: 25.3204 | I9: 5102 | J9: 53816 | P9: =SUBTOTAL(9,J9) -> 53816 | S9: =SUM(48777.5/68)*H9 -> 18162.733 | T9: =SUM(88.88/68)*H9 -> 33.095252 | U9: =SUM(1900/68)*H9 -> 707.48176 | X9: =SUM(S9:W9) -> 18903.31 | Y9: =SUM(12037/68)*H9 -> 4482.0832 | AA9: =SUM(57.52/68)*H9 -> 21.41808 | AB9: =SUM(Y9:AA9) -> 4503.5012 | AC9: 7.25 | AD9: =SUM(AB9*AC9) -> 32650.384 | AE9: =SUM(X9+AD9) -> 51553.694 | AF9: =SUM(P9-AE9) -> 2262.3065
C10: 241219000028 | D10: 46010 | E10: 罗珮文 | F10: Shirley | G10: SKY JET | H10: 22.11 | I10: 2603 | J10: 36919.28 | P10: =SUBTOTAL(9,J10) -> 36919.28 | S10: =SUM(48777.5/68)*H10 -> 15859.861 | T10: =SUM(88.88/68)*H10 -> 28.899071 | U10: =SUM(1900/68)*H10 -> 617.77941 | X10: =SUM(S10:W10) -> 16506.539 | Y10: =SUM(12037/68)*H10 -> 3913.7951 | AA10: =SUM(57.52/68)*H10 -> 18.702459 | AB10: =SUM(Y10:AA10) -> 3932.4976 | AC10: 7.25 | AD10: =SUM(AB10*AC10) -> 28510.608 | AE10: =SUM(X10+AD10) -> 45017.147 | AF10: =SUM(P10-AE10) -> -8097.8668
C11: 241219000033 | D11: 46010 | E11: 黄颖 | F11: ying | G11: MISS Huang | H11: 15.7779 | I11: 9654 | J11: 37467.5 | P11: =SUBTOTAL(9,J11) -> 37467.5 | S11: =SUM(48777.5/68)*H11 -> 11317.743 | T11: =SUM(88.88/68)*H11 -> 20.622643 | U11: =SUM(1900/68)*H11 -> 440.85309 | X11: =SUM(S11:W11) -> 11779.219 | Y11: =SUM(12037/68)*H11 -> 2792.9203 | AA11: =SUM(57.52/68)*H11 -> 13.346247 | AB11: =SUM(Y11:AA11) -> 2806.2666 | AC11: 7.25 | AD11: =SUM(AB11*AC11) -> 20345.433 | AE11: =SUM(X11+AD11) -> 32124.651 | AF11: =SUM(P11-AE11) -> 5342.8487
A12: 合计 | J12: =SUM(J4:J4) -> 0 | N12: =SUM(N4:N4) -> 0 | P12: =SUM(P4:P4) -> 0 | Q12: =SUM(Q4:Q4) -> 0 | X12: =SUM(X4:X4) -> 0 | AD12: =SUM(AD4:AD4) -> 0 | AF12: =SUM(AF4:AF11) -> 7182.2738

Sheet JOB120399
A1: 2024年12月份LOS毛利表（海运）
A2: PSL表 | B2: 体积cbm | C2: 72.7107
A3: JOB | B3: 集装编号 | C3: 运单编号 | D3: 日期 | E3: 业务 | F3: 发货人 | G3: 收货人 | H3: 计费体积 | I3: 计费重量 | J3: 应 收 | Q3: 总应收 | R3: 起 运 港 成 本 | W3: 代垫运费 | X3: 起运港成本 合计 | Y3: 目的港成本 | AE3: 总支出 | AF3: 利润
J4: 应收RMB | K4: LOS Income(NGN)收到(奈拉) | L4: LOS 收到USD | M4: 美元汇率 dollar currency rate | N4: 应收 到付款USD | O4: 汇率 | P4: 人民币 | R4: 代理商 | S4: 运费+出口报关费 | T4: 提货费 | U4: 装卸费 | V4: 包装费 | Y4: 进口报关费 | Z4: 到门配送费 | AA4: 转运费 | AB4: 目的港支出 | AC4: 汇率 | AD4: 人民币 | AE4: 起运港+目的港
A5: JOB120399 | B5: COLL004330 | C5: 241125000030 | D5: 46018 | E5: Bella | F5: Bella Chan | G5: Alice | H5: 0.0122 | I5: 2 | J5: 202 | P5: =SUBTOTAL(9,J5) -> 202 | Q5: =SUM(P5:P35) -> 174647.75 | R5: 登凯=45639 创泽=3175 拖车费=1670 杂费=61 过磅费=70 | S5: =SUM(50615/68)*H5 -> 9.0809265 | U5: =SUM(2100/68)*H5 -> 0.37676471 | X5: =SUM(S5:W5) -> 9.4576912 | Y5: =SUM(11518.15/68)*H5 -> 2.0664916 | AA5: =SUM(59.41/68)*H5 -> 0.010658853 | AB5: =SUM(Y5:AA5) -> 2.0771505 | AC5: 7.26 | AD5: =SUM(AB5*AC5) -> 15.080112 | AE5: =SUM(X5+AD5) -> 24.537804 | AF5: =SUM(P5-AE5) -> 177.4622
C6: 241205000022 | D6: 46018 | E6: 黄颖 | F6: ying | G6: linxiao | H6: 1.5787 | I6: 305 | J6: 3483.9 | P6: =SUBTOTAL(9,J6) -> 3483.9 | S6: =SUM(50615/68)*H6 -> 1175.0868 | U6: =SUM(2100/68)*H6 -> 48.753971 | X6: =SUM(S6:W6) -> 1223.8407 | Y6: =SUM(11518.15/68)*H6 -> 267.4074 | AA6: =SUM(59.41/68)*H6 -> 1.379273 | AB6: =SUM(Y6:AA6) -> 268.78668 | AC6: 7.26 | AD6: =SUM(AB6*AC6) -> 1951.3913 | AE6: =SUM(X6+AD6) -> 3175.232 | AF6: =SUM(P6-AE6) -> 308.66799
C7: 241210000059 | D7: 46018 | E7: 黄颖 | F7: ying | G7: linxiao | H7: 3.2498 | I7: 683 | K7: 1855578 | M7: =SUM(K7/N7) -> 1576.5319 | N7: 1177 | O7: 7.22 | P7: =SUM(N7*O7) -> 8497.94 | S7: =SUM(50615/68)*H7 -> 2418.9504 | U7: =SUM(2100/68)*H7 -> 100.36147 | X7: =SUM(S7:W7) -> 2519.3119 | Y7: =SUM(11518.15/68)*H7 -> 550.46594 | Z7: 251.58 | AA7: =SUM(59.41/68)*H7 -> 2.8392738 | AB7: =SUM(Y7:AA7) -> 804.88521 | AC7: 7.26 | AD7: =SUM(AB7*AC7) -> 5843.4666 | AE7: =SUM(X7+AD7) -> 8362.7785 | AF7: =SUM(P7-AE7) -> 135.16149
C8: 241211000027 | D8: 45643 | E8: Sam.Pao | F8: Sam.Pao | G8: ShanShan | H8: 0.228 | I8: 45 | J8: 520 | P8: =SUBTOTAL(9,J8) -> 520 | S8: =SUM(50615/68)*H8 -> 169.70912 | U8: =SUM(2100/68)*H8 -> 7.0411765 | X8: =SUM(S8:W8) -> 176.75029 | Y8: =SUM(11518.15/68)*H8 -> 38.619679 | AA8: =SUM(59.41/68)*H8 -> 0.19919824 | AB8: =SUM(Y8:AA8) -> 38.818878 | AC8: 7.26 | AD8: =SUM(AB8*AC8) -> 281.82505 | AE8: =SUM(X8+AD8) -> 458.57535 | AF8: =SUM(P8-AE8) -> 61.424654
C9: 241213000046 | D9: 46018 | E9: Sam.Pao | F9: Sam.Pao | G9: Mr. Jiang | H9: 5.2541 | I9: 1423 | J9: 15725.5 | P9: =SUBTOTAL(9,J9) -> 15725.5 | S9: =SUM(50615/68)*H9 -> 3910.8275 | U9: =SUM(2100/68)*H9 -> 162.25897 | X9: =SUM(S9:W9) -> 4073.0865 | Y9: =SUM(11518.15/68)*H9 -> 889.96341 | AA9: =SUM(59.41/68)*H9 -> 4.5903835 | AB9: =SUM(Y9:AA9) -> 894.55379 | AC9: 7.26 | AD9: =SUM(AB9*AC9) -> 6494.4605 | AE9: =SUM(X9+AD9) -> 10567.547 | AF9: =SUM(P9-AE9) -> 5157.953
C10: 241216000032 | D10: 46018 | E10: 朱小飞 | F10: Isabel Zhu | G10: Joy | H10: 1.8673 | I10: 857 | K10: 984715.9 | M10: =SUM(K10/N10) -> 1582 | N10: 622.45 | O10: 7.24 | P10: =SUM(N10*O10) -> 4506.538 | S10: =SUM(50615/68)*H10 -> 1389.9028 | U10: =SUM(2100/68)*H10 -> 57.666618 | X10: =SUM(S10:W10) -> 1447.5694 | Y10: =SUM(11518.15/68)*H10 -> 316.29179 | Z10: 8.14 | AA10: =SUM(59.41/68)*H10 -> 1.6314161 | AB10: =SUM(Y10:AA10) -> 326.0632 | AC10: 7.26 | AD10: =SUM(AB10*AC10) -> 2367.2189 | AE10: =SUM(X10+AD10) -> 3814.7883 | AF10: =SUM(P10-AE10) -> 691.74974
C11: 241217000015 | D11: 46018 | E11: 朱小飞 | F11: Isabel Zhu | G11: Sadiq | H11: 2.0946 | I11: 144 | K11: 1215438 | M11: =SUM(K11/N11) -> 1581.9836 | N11: 768.3 | O11: 7.25 | P11: =SUM(N11*O11) -> 5570.175 | S11: =SUM(50615/68)*H11 -> 1559.0909 | U11: =SUM(2100/68)*H11 -> 64.686176 | X11: =SUM(S11:W11) -> 1623.777 | Y11: =SUM(11518.15/68)*H11 -> 354.7929 | Z11: 103.35 | AA11: =SUM(59.41/68)*H11 -> 1.8300027 | AB11: =SUM(Y11:AA11) -> 459.9729 | AC11: 7.26 | AD11: =SUM(AB11*AC11) -> 3339.4033 | AE11: =SUM(X11+AD11) -> 4963.1803 | AF11: =SUM(P11-AE11) -> 606.9947
C12: 241218000004 | D12: 46018 | E12: 黄颖 | F12: ying | G12: ss | H12: 2.7589 | I12: 1023 | J12: 5703 | P12: =SUBTOTAL(9,J12) -> 5703 | S12: =SUM(50615/68)*H12 -> 2053.5548 | U12: =SUM(2100/68)*H12 -> 85.201324 | X12: =SUM(S12:W12) -> 2138.7561 | Y12: =SUM(11518.15/68)*H12 -> 467.31506 | AA12: =SUM(59.41/68)*H12 -> 2.410386 | AB12: =SUM(Y12:AA12) -> 469.72545 | AC12: 7.26 | AD12: =SUM(AB12*AC12) -> 3410.2067 | AE12: =SUM(X12+AD12) -> 5548.9628 | AF12: =SUM(P12-AE12) -> 154.03719
C13: 241219000017 | D13: 46018 | E13: 朱小飞 | F13: Isabel Zhu | G13: Halifa Success | H13: 1.1975 | I13: 205 | J13: 2430 | P13: =SUBTOTAL(9,J13) -> 2430 | S13: =SUM(50615/68)*H13 -> 891.34504 | U13: =SUM(2100/68)*H13 -> 36.981618 | X13: =SUM(S13:W13) -> 928.32665 | Y13: =SUM(11518.15/68)*H13 -> 202.83801 | AA13: =SUM(59.41/68)*H13 -> 1.0462276 | AB13: =SUM(Y13:AA13) -> 203.88424 | AC13: 7.26 | AD13: =SUM(AB13*AC13) -> 1480.1996 | AE13: =SUM(X13+AD13) -> 2408.5262 | AF13: =SUM(P13-AE13) -> 21.473787
C14: 241219000030 | D14: 46018 | E14: 黄颖 | F14: ying | G14: Nura | H14: 0.5462 | I14: 242 | J14: 1156 | P14: =SUBTOTAL(9,J14) -> 1156 | S14: =SUM(50615/68)*H14 -> 406.55754 | U14: =SUM(2100/68)*H14 -> 16.867941 | X14: =SUM(S14:W14) -> 423.42549 | Y14: =SUM(11518.15/68)*H14 -> 92.517846 | AA14: =SUM(59.41/68)*H14 -> 0.47720209 | AB14: =SUM(Y14:AA14) -> 92.995048 | AC14: 7.26 | AD14: =SUM(AB14*AC14) -> 675.14405 | AE14: =SUM(X14+AD14) -> 1098.5695 | AF14: =SUM(P14-AE14) -> 57.430465
C15: 241216000051 | D15: 46018 | E15: 黄颖 | F15: ying | G15: Nura | H15: 13.6398 | I15: 2540 | J15: 28688 | P15: =SUBTOTAL(9,J15) -> 28688 | S15: =SUM(50615/68)*H15 -> 10152.625 | U15: =SUM(2100/68)*H15 -> 421.22912 | X15: =SUM(S15:W15) -> 10573.854 | Y15: =SUM(11518.15/68)*H15 -> 2310.3715 | AA15: =SUM(59.41/68)*H15 -> 11.916772 | AB15: =SUM(Y15:AA15) -> 2322.2883 | AC15: 7.26 | AD15: =SUM(AB15*AC15) -> 16859.813 | AE15: =SUM(X15+AD15) -> 27433.667 | AF15: =SUM(P15-AE15) -> 1254.3333
C16: 241220000030 | D16: 46018 | E16: Bella | F16: Bella Chan | G16: new hope 边鹏飞 | H16: 0.8815 | I16: 304 | K16: 414128.7 | M16: =SUM(K16/N16) -> 1566.0003 | N16: 264.44995 | O16: 7.27 | P16: =SUM(N16*O16) -> 1922.5511 | S16: =SUM(50615/68)*H16 -> 656.13415 | U16: =SUM(2100/68)*H16 -> 27.222794 | X16: =SUM(S16:W16) -> 683.35695 | Y16: =SUM(11518.15/68)*H16 -> 149.31249 | AA16: =SUM(59.41/68)*H16 -> 0.77014581 | AB16: =SUM(Y16:AA16) -> 150.08263 | AC16: 7.26 | AD16: =SUM(AB16*AC16) -> 1089.5999 | AE16: =SUM(X16+AD16) -> 1772.9569 | AF16: =SUM(P16-AE16) -> 149.59426
C17: 241221000013 | D17: 46018 | E17: 黄颖 | F17: ying | G17: ss | H17: 2.0286 | I17: 791 | J17: 4194.5 | P17: =SUBTOTAL(9,J17) -> 4194.5 | S17: =SUM(50615/68)*H17 -> 1509.9645 | U17: =SUM(2100/68)*H17 -> 62.647941 | X17: =SUM(S17:W17) -> 1572.6125 | Y17: =SUM(11518.15/68)*H17 -> 343.61352 | AA17: =SUM(59.41/68)*H17 -> 1.7723401 | AB17: =SUM(Y17:AA17) -> 345.38586 | AC17: 7.26 | AD17: =SUM(AB17*AC17) -> 2507.5013 | AE17: =SUM(X17+AD17) -> 4080.1138 | AF17: =SUM(P17-AE17) -> 114.3862
C18: 241222000003 | D18: 46018 | E18: 黄颖 | F18: ying | G18: ss | H18: 11.2441 | I18: 3412 | J18: 24501 | P18: =SUBTOTAL(9,J18) -> 24501 | S18: =SUM(50615/68)*H18 -> 8369.4136 | U18: =SUM(2100/68)*H18 -> 347.24426 | X18: =SUM(S18:W18) -> 8716.6578 | Y18: =SUM(11518.15/68)*H18 -> 1904.5769 | AA18: =SUM(59.41/68)*H18 -> 9.8237056 | AB18: =SUM(Y18:AA18) -> 1914.4006 | AC18: 7.26 | AD18: =SUM(AB18*AC18) -> 13898.549 | AE18: =SUM(X18+AD18) -> 22615.206 | AF18: =SUM(P18-AE18) -> 1885.7937
C19: 241223000042 | D19: 46018 | E19: 苏慧琪 | F19: KAY | G19: WENXIAOBING | H19: 0.0662 | I19: 13 | J19: 155.7 | P19: =SUM(J19) -> 155.7 | S19: =SUM(50615/68)*H19 -> 49.275191 | U19: =SUM(2100/68)*H19 -> 2.0444118 | X19: =SUM(S19:W19) -> 51.319603 | Y19: =SUM(11518.15/68)*H19 -> 11.213258 | AA19: =SUM(59.41/68)*H19 -> 0.057837382 | AB19: =SUM(Y19:AA19) -> 11.271095 | AC19: 7.26 | AD19: =SUM(AB19*AC19) -> 81.828151 | AE19: =SUM(X19+AD19) -> 133.14775 | AF19: =SUM(P19-AE19) -> 22.552246
C20: 241223000044 | D20: 46018 | E20: 无人 | F20: dejare James | G20: James | H20: 0.7236 | I20: 173 | K20: 336691 | M20: =SUM(K20/N20) -> 1550.9991 | N20: 217.08008 | O20: 7.24 | P20: =SUM(N20*O20) -> 1571.6598 | S20: =SUM(50615/68)*H20 -> 538.60315 | U20: =SUM(2100/68)*H20 -> 22.346471 | X20: =SUM(S20:W20) -> 560.94962 | Y20: =SUM(11518.15/68)*H20 -> 122.56667 | AA20: =SUM(59.41/68)*H20 -> 0.63219229 | AB20: =SUM(Y20:AA20) -> 123.19886 | AC20: 7.26 | AD20: =SUM(AB20*AC20) -> 894.42372 | AE20: =SUM(X20+AD20) -> 1455.3733 | AF20: =SUM(P20-AE20) -> 116.28644
C21: 241223000048 | D21: 46018 | E21: Sam.Pao | F21: Sam.Pao | G21: Mr. Jiang | H21: 0.8576 | I21: 189 | J21: 3063 | P21: =SUBTOTAL(9,J21) -> 3063 | S21: =SUM(50615/68)*H21 -> 638.34447 | U21: =SUM(2100/68)*H21 -> 26.484706 | W21: 53.42 | X21: =SUM(S21:W21) -> 718.24918 | Y21: =SUM(11518.15/68)*H21 -> 145.2642 | AA21: =SUM(59.41/68)*H21 -> 0.74926494 | AB21: =SUM(Y21:AA21) -> 146.01346 | AC21: 7.26 | AD21: =SUM(AB21*AC21) -> 1060.0577 | AE21: =SUM(X21+AD21) -> 1778.3069 | AF21: =SUM(P21-AE21) -> 1284.6931
C22: 241223000069 | D22: 46018 | E22: 朱小飞 | F22: Isabel Zhu | G22: Halifa Success | H22: 5.4144 | I22: 1858 | J22: 10997.45 | P22: =SUBTOTAL(9,J22) -> 10997.45 | S22: =SUM(50615/68)*H22 -> 4030.1449 | U22: =SUM(2100/68)*H22 -> 167.20941 | X22: =SUM(S22:W22) -> 4197.3544 | Y22: =SUM(11518.15/68)*H22 -> 917.11576 | AA22: =SUM(59.41/68)*H22 -> 4.7304339 | AB22: =SUM(Y22:AA22) -> 921.84619 | AC22: 7.26 | AD22: =SUM(AB22*AC22) -> 6692.6033 | AE22: =SUM(X22+AD22) -> 10889.958 | AF22: =SUM(P22-AE22) -> 107.49231
C23: 241224000009 | D23: 46018 | E23: 朱小飞 | F23: Isabel Zhu | G23: Halifa Success | H23: 3.9648 | I23: 516 | J23: 8070.22 | P23: =SUBTOTAL(9,J23) -> 8070.22 | S23: =SUM(50615/68)*H23 -> 2951.1522 | U23: =SUM(2100/68)*H23 -> 122.44235 | X23: =SUM(S23:W23) -> 3073.5946 | Y23: =SUM(11518.15/68)*H23 -> 671.5759 | AA23: =SUM(59.41/68)*H23 -> 3.4639525 | AB23: =SUM(Y23:AA23) -> 675.03985 | AC23: 7.26 | AD23: =SUM(AB23*AC23) -> 4900.7893 | AE23: =SUM(X23+AD23) -> 7974.3839 | AF23: =SUM(P23-AE23) -> 95.836091
C24: 241224000024 | D24: 46018 | E24: 罗珮文 | F24: Shirley | G24: Yusky | H24: 1.4079 | I24: 246 | K24: 605826.9 | M24: =SUM(K24/N24) -> 1582 | N24: 382.95 | O24: 7.18 | P24: =SUM(N24*O24) -> 2749.581 | S24: =SUM(50615/68)*H24 -> 1047.9538 | U24: =SUM(2100/68)*H24 -> 43.479265 | X24: =SUM(S24:W24) -> 1091.4331 | Y24: =SUM(11518.15/68)*H24 -> 238.47652 | AA24: =SUM(59.41/68)*H24 -> 1.2300491 | AB24: =SUM(Y24:AA24) -> 239.70657 | AC24: 7.26 | AD24: =SUM(AB24*AC24) -> 1740.2697 | AE24: =SUM(X24+AD24) -> 2831.7028 | AF24: =SUM(P24-AE24) -> -82.121761
C25: 241224000025 | D25: 46018 | E25: 罗珮文 | F25: Shirley | G25: Yusky | H25: 2.2252 | I25: 847 | K25: 957505.5 | M25: =SUM(K25/N25) -> 1582 | N25: 605.25 | O25: 7.18 | P25: =SUM(N25*O25) -> 4345.695 | S25: =SUM(50615/68)*H25 -> 1656.3014 | U25: =SUM(2100/68)*H25 -> 68.719412 | X25: =SUM(S25:W25) -> 1725.0209 | Y25: =SUM(11518.15/68)*H25 -> 376.91452 | AA25: =SUM(59.41/68)*H25 -> 1.9441049 | AB25: =SUM(Y25:AA25) -> 378.85863 | AC25: 7.26 | AD25: =SUM(AB25*AC25) -> 2750.5136 | AE25: =SUM(X25+AD25) -> 4475.5345 | AF25: =SUM(P25-AE25) -> -129.83947
C26: 241224000026 | D26: 46018 | E26: 罗珮文 | F26: Shirley | G26: Yusky | H26: 0.8547 | I26: 81 | K26: 367783.36 | M26: =SUM(K26/N26) -> 1582 | N26: 232.48 | O26: 7.18 | P26: =SUM(N26*O26) -> 1669.2064 | S26: =SUM(50615/68)*H26 -> 636.18589 | U26: =SUM(2100/68)*H26 -> 26.395147 | X26: =SUM(S26:W26) -> 662.58104 | Y26: =SUM(11518.15/68)*H26 -> 144.77298 | AA26: =SUM(59.41/68)*H26 -> 0.74673128 | AB26: =SUM(Y26:AA26) -> 145.51971 | AC26: 7.26 | AD26: =SUM(AB26*AC26) -> 1056.4731 | AE26: =SUM(X26+AD26) -> 1719.0542 | AF26: =SUM(P26-AE26) -> -49.847758
C27: 241224000028 | D27: 46018 | E27: 无人 | F27: dejare James | G27: James | H27: 0.4936 | I27: 87 | K27: 229672 | M27: =SUM(K27/N27) -> 1550.9996 | N27: 148.07999 | O27: 7.24 | P27: =SUM(N27*O27) -> 1072.0991 | S27: =SUM(50615/68)*H27 -> 367.40535 | U27: =SUM(2100/68)*H27 -> 15.243529 | X27: =SUM(S27:W27) -> 382.64888 | Y27: =SUM(11518.15/68)*H27 -> 83.608218 | AA27: =SUM(59.41/68)*H27 -> 0.43124671 | AB27: =SUM(Y27:AA27) -> 84.039465 | AC27: 7.26 | AD27: =SUM(AB27*AC27) -> 610.12652 | AE27: =SUM(X27+AD27) -> 992.7754 | AF27: =SUM(P27-AE27) -> 79.32373
C28: 241224000043 | D28: 46018 | E28: Sam.Pao | F28: Sam.Pao | G28: Mr. Jiang | H28: 0.4278 | I28: 118 | J28: 1777 | P28: =SUBTOTAL(9,J28) -> 1777 | S28: =SUM(50615/68)*H28 -> 318.4279 | U28: =SUM(2100/68)*H28 -> 13.211471 | W28: 57.82 | X28: =SUM(S28:W28) -> 389.45937 | Y28: =SUM(11518.15/68)*H28 -> 72.462714 | AA28: =SUM(59.41/68)*H28 -> 0.37375879 | AB28: =SUM(Y28:AA28) -> 72.836473 | AC28: 7.26 | AD28: =SUM(AB28*AC28) -> 528.79279 | AE28: =SUM(X28+AD28) -> 918.25216 | AF28: =SUM(P28-AE28) -> 858.74784
C29: 241126000018 | D29: 46018 | E29: 吕沛霖 | F29: 喵喵速运-Layne | G29: MA ZONG | H29: 4.3979 | I29: 10079 | J29: 20016.76 | P29: =SUBTOTAL(9,J29) -> 20016.76 | S29: =SUM(50615/68)*H29 -> 3273.5251 | U29: =SUM(2100/68)*H29 -> 135.8175 | W29: 255 | X29: =SUM(S29:W29) -> 3664.3426 | Y29: =SUM(11518.15/68)*H29 -> 744.93635 | AA29: =SUM(59.41/68)*H29 -> 3.8423418 | AB29: =SUM(Y29:AA29) -> 748.77869 | AC29: 7.26 | AD29: =SUM(AB29*AC29) -> 5436.1333 | AE29: =SUM(X29+AD29) -> 9100.4759 | AF29: =SUM(P29-AE29) -> 10916.284
C30: 241226000023 | D30: 46018 | E30: 朱小飞 | F30: Isabel Zhu | G30: Maryam Tukur | H30: 0.8304 | I30: 88 | K30: 488305 | M30: =SUM(K30/N30) -> 1581.2986 | N30: 308.8 | O30: 7.27 | P30: =SUM(N30*O30) -> 2244.976 | S30: =SUM(50615/68)*H30 -> 618.09847 | U30: =SUM(2100/68)*H30 -> 25.644706 | X30: =SUM(S30:W30) -> 643.74318 | Y30: =SUM(11518.15/68)*H30 -> 140.65694 | Z30: 35.59 | AA30: =SUM(59.41/68)*H30 -> 0.72550094 | AB30: =SUM(Y30:AA30) -> 176.97244 | AC30: 7.26 | AD30: =SUM(AB30*AC30) -> 1284.8199 | AE30: =SUM(X30+AD30) -> 1928.5631 | AF30: =SUM(P30-AE30) -> 316.41292
C31: 241226000032 | D31: 46018 | E31: 罗珮文 | F31: Shirley | G31: Yusky | H31: 0.19 | I31: 26 | K31: 81805.22 | M31: =SUM(K31/N31) -> 1582 | N31: 51.71 | O31: 7.18 | P31: =SUM(N31*O31) -> 371.2778 | S31: =SUM(50615/68)*H31 -> 141.42426 | U31: =SUM(2100/68)*H31 -> 5.8676471 | X31: =SUM(S31:W31) -> 147.29191 | Y31: =SUM(11518.15/68)*H31 -> 32.183066 | AA31: =SUM(59.41/68)*H31 -> 0.16599853 | AB31: =SUM(Y31:AA31) -> 32.349065 | AC31: 7.26 | AD31: =SUM(AB31*AC31) -> 234.85421 | AE31: =SUM(X31+AD31) -> 382.14612 | AF31: =SUM(P31-AE31) -> -10.868322
C32: 241023000034 | D32: 45617 | E32: Sam.Pao | F32: Sam.Pao | G32: Nick Wang | H32: 0.0452 | I32: 13 | J32: 131.2 | P32: =SUBTOTAL(9,J32) -> 131.2 | S32: =SUM(50615/68)*H32 -> 33.644088 | U32: =SUM(2100/68)*H32 -> 1.3958824 | X32: =SUM(S32:W32) -> 35.039971 | Y32: =SUM(11518.15/68)*H32 -> 7.6561821 | AA32: =SUM(59.41/68)*H32 -> 0.039490176 | AB32: =SUM(Y32:AA32) -> 7.6956722 | AC32: 7.26 | AD32: =SUM(AB32*AC32) -> 55.87058 | AE32: =SUM(X32+AD32) -> 90.910551 | AF32: =SUM(P32-AE32) -> 40.289449
C33: 241226000033 | D33: 46018 | E33: 罗珮文 | F33: Shirley | G33: Yusky | H33: 1.481 | I33: 251 | K33: 637277.06 | M33: =SUM(K33/N33) -> 1582 | N33: 402.83 | O33: 7.18 | P33: =SUM(N33*O33) -> 2892.3194 | S33: =SUM(50615/68)*H33 -> 1102.3649 | U33: =SUM(2100/68)*H33 -> 45.736765 | X33: =SUM(S33:W33) -> 1148.1017 | Y33: =SUM(11518.15/68)*H33 -> 250.85853 | AA33: =SUM(59.41/68)*H33 -> 1.2939149 | AB33: =SUM(Y33:AA33) -> 252.15245 | AC33: 7.26 | AD33: =SUM(AB33*AC33) -> 1830.6268 | AE33: =SUM(X33+AD33) -> 2978.7285 | AF33: =SUM(P33-AE33) -> -86.409053
C34: 241225000006 | D34: 46020 | E34: 朱小飞 | F34: Isabel Zhu | G34: Joy | H34: 2.399 | I34: 1988 | K34: 1244263 | M34: =SUM(K34/N34) -> 1573.0253 | N34: 791 | O34: 7.25 | P34: =SUM(N34*O34) -> 5734.75 | S34: =SUM(50615/68)*H34 -> 1785.6674 | U34: =SUM(2100/68)*H34 -> 74.086765 | X34: =SUM(S34:W34) -> 1859.7542 | Y34: =SUM(11518.15/68)*H34 -> 406.35356 | AA34: =SUM(59.41/68)*H34 -> 2.0959499 | AB34: =SUM(Y34:AA34) -> 408.44951 | AC34: 7.26 | AD34: =SUM(AB34*AC34) -> 2965.3434 | AE34: =SUM(X34+AD34) -> 4825.0976 | AF34: =SUM(P34-AE34) -> 909.65239
C35: 241226000034 | D35: 46018 | E35: 罗珮文 | F35: Shirley | G35: Yusky | H35: 0.3501 | I35: 96 | K35: 150653.86 | M35: =SUM(K35/N35) -> 1582 | N35: 95.23 | O35: 7.18 | P35: =SUM(N35*O35) -> 683.7514 | S35: =SUM(50615/68)*H35 -> 260.59282 | U35: =SUM(2100/68)*H35 -> 10.811912 | X35: =SUM(S35:W35) -> 271.40473 | Y35: =SUM(11518.15/68)*H35 -> 59.301534 | AA35: =SUM(59.41/68)*H35 -> 0.30587413 | AB35: =SUM(Y35:AA35) -> 59.607408 | AC35: 7.26 | AD35: =SUM(AB35*AC35) -> 432.74978 | AE35: =SUM(X35+AD35) -> 704.15451 | AF35: =SUM(P35-AE35) -> -20.403111
A36: 合计 | J36: =SUM(J4:J4) -> 0 | N36: =SUM(N4:N4) -> 0 | P36: =SUM(P4:P4) -> 0 | Q36: =SUM(Q4:Q4) -> 0 | X36: =SUM(X4:X4) -> 0 | AD36: =SUM(AD4:AD4) -> 0 | AF36: =SUM(AF4:AF35) -> 25144.544

Sheet JOB120404
A1: 2024年12月份LOS毛利表（海运）
A2: PSL表 | B2: 体积cbm | C2: 73.7379
A3: JOB | B3: 集装编号 | C3: 运单编号 | D3: 日期 | E3: 业务 | F3: 发货人 | G3: 收货人 | H3: 计费体积 | I3: 计费重量 | J3: 应 收 | Q3: 总应收 | R3: 起 运 港 成 本 | W3: 代垫运费 | X3: 起运港成本 合计 | Y3: 目的港成本 | AE3: 总支出 | AF3: 利润
J4: 应收RMB | K4: LOS Income(NGN)收到(奈拉) | L4: LOS 收到USD | M4: 美元汇率 dollar currency rate | N4: 应收 到付款USD | O4: 汇率 | P4: 人民币 | R4: 代理商 | S4: 运费+出口报关费 | T4: 提货费 | U4: 装卸费 | V4: 包装费 | Y4: 进口报关费 | Z4: 到门配送费 | AA4: 转运费 | AB4: 目的港支出 | AC4: 汇率 | AD4: 人民币 | AE4: 起运港+目的港
A5: JOB120404 | B5: COLL004342 | C5: 241128000030 | D5: 46020 | E5: Sam.Pao | F5: Sam.Pao | G5: ShanShan | H5: 5.8708 | I5: 3354 | J5: 17261.3 | P5: =SUBTOTAL(9,J5) -> 17261.3 | Q5: =SUM(P5:P17) -> 158708.12 | R5: 登凯=45401 报关=2960 拖车费=1670 杂费=89 过磅费=70 | S5: =SUM(50190/68)*H5 -> 4333.1684 | U5: =SUM(1800/68)*H5 -> 155.40353 | X5: =SUM(S5:W5) -> 4488.5719 | Y5: =SUM(11143.04/68)*H5 -> 962.03764 | Z5: 114.79 | AA5: =SUM(134.1/68)*H5 -> 11.577563 | AB5: =SUM(Y5:AA5) -> 1088.4052 | AC5: 7.25 | AD5: =SUM(AB5*AC5) -> 7890.9377 | AE5: =SUM(X5+AD5) -> 12379.51 | AF5: =SUM(P5-AE5) -> 4881.7904
A6: JOB120404 | B6: COLL004342 | C6: 241126000018 | D6: 46020 | E6: 吕沛霖 | F6: 喵喵速运-Layne | G6: MA ZONG | H6: 4.16 | I6: 10000 | J6: 18934.4 | P6: =SUBTOTAL(9,J6) -> 18934.4 | S6: =SUM(50190/68)*H6 -> 3070.4471 | U6: =SUM(1800/68)*H6 -> 110.11765 | X6: =SUM(S6:W6) -> 3180.5647 | Y6: =SUM(11143.04/68)*H6 -> 681.69186 | AA6: =SUM(134.1/68)*H6 -> 8.2037647 | AB6: =SUM(Y6:AA6) -> 689.89562 | AC6: 7.25 | AD6: =SUM(AB6*AC6) -> 5001.7433 | AE6: =SUM(X6+AD6) -> 8182.308 | AF6: =SUM(P6-AE6) -> 10752.092
C7: 241209000079 | D7: 46020 | E7: 黄颖 | F7: ying | G7: fanglijuan | H7: 3.7703 | I7: 879 | J7: 9709 | P7: =SUBTOTAL(9,J7) -> 9709 | S7: =SUM(50190/68)*H7 -> 2782.8141 | U7: =SUM(1800/68)*H7 -> 99.802059 | X7: =SUM(S7:W7) -> 2882.6161 | Y7: =SUM(11143.04/68)*H7 -> 617.83241 | AA7: =SUM(134.1/68)*H7 -> 7.4352534 | AB7: =SUM(Y7:AA7) -> 625.26766 | AC7: 7.25 | AD7: =SUM(AB7*AC7) -> 4533.1905 | AE7: =SUM(X7+AD7) -> 7415.8067 | AF7: =SUM(P7-AE7) -> 2293.1933
C8: 241220000032 | D8: 46020 | E8: 朱小飞 | F8: Isabel Zhu | G8: Halifa Success | H8: 0.1307 | I8: 18 | J8: 264.26 | P8: =SUBTOTAL(9,J8) -> 264.26 | S8: =SUM(50190/68)*H8 -> 96.468132 | U8: =SUM(1800/68)*H8 -> 3.4597059 | X8: =SUM(S8:W8) -> 99.927838 | Y8: =SUM(11143.04/68)*H8 -> 21.417578 | AA8: =SUM(134.1/68)*H8 -> 0.25774809 | AB8: =SUM(Y8:AA8) -> 21.675326 | AC8: 7.25 | AD8: =SUM(AB8*AC8) -> 157.14612 | AE8: =SUM(X8+AD8) -> 257.07395 | AF8: =SUM(P8-AE8) -> 7.1860451
C9: 241220000033 | D9: 46020 | E9: 朱小飞 | F9: Isabel Zhu | G9: Halifa Success | H9: 4.4833 | I9: 535 | J9: 9724.04 | P9: =SUBTOTAL(9,J9) -> 9724.04 | S9: =SUM(50190/68)*H9 -> 3309.071 | U9: =SUM(1800/68)*H9 -> 118.67559 | V9: 600 | X9: =SUM(S9:W9) -> 4027.7466 | Y9: =SUM(11143.04/68)*H9 -> 734.67046 | AA9: =SUM(134.1/68)*H9 -> 8.8413313 | AB9: =SUM(Y9:AA9) -> 743.51179 | AC9: 7.25 | AD9: =SUM(AB9*AC9) -> 5390.4605 | AE9: =SUM(X9+AD9) -> 9418.2071 | AF9: =SUM(P9-AE9) -> 305.83294
C10: 241222000001 | D10: 46020 | E10: Sam.Pao | F10: Sam.Pao | G10: AiGeLi | H10: 2.8117 | I10: 782 | J10: 7663 | P10: =SUBTOTAL(9,J10) -> 7663 | S10: =SUM(50190/68)*H10 -> 2075.2827 | U10: =SUM(1800/68)*H10 -> 74.427353 | X10: =SUM(S10:W10) -> 2149.71 | Y10: =SUM(11143.04/68)*H10 -> 460.74832 | AA10: =SUM(134.1/68)*H10 -> 5.5448378 | AB10: =SUM(Y10:AA10) -> 466.29315 | AC10: 7.25 | AD10: =SUM(AB10*AC10) -> 3380.6254 | AE10: =SUM(X10+AD10) -> 5530.3354 | AF10: =SUM(P10-AE10) -> 2132.6646
C11: 241225000006 | D11: 46020 | E11: 朱小飞 | F11: Isabel Zhu | G11: Joy | H11: 1.7317 | I11: 1184 | K11: 898163 | M11: =SUM(K11/N11) -> 1572.965 | N11: 571 | O11: 7.25 | P11: =SUM(N11*O11) -> 4139.75 | S11: =SUM(50190/68)*H11 -> 1278.1474 | U11: =SUM(1800/68)*H11 -> 45.839118 | X11: =SUM(S11:W11) -> 1323.9865 | Y11: =SUM(11143.04/68)*H11 -> 283.77062 | Z11: 52.28 | AA11: =SUM(134.1/68)*H11 -> 3.4150143 | AB11: =SUM(Y11:AA11) -> 339.46564 | AC11: 7.25 | AD11: =SUM(AB11*AC11) -> 2461.1259 | AE11: =SUM(X11+AD11) -> 3785.1124 | AF11: =SUM(P11-AE11) -> 354.63761
C12: 241227000020 | D12: 46020 | E12: Bella | F12: Bella Chan | G12: zhong zi xin | H12: 13.5726 | I12: 6092 | J12: 27674.5 | P12: =SUBTOTAL(9,J12) -> 27674.5 | S12: =SUM(50190/68)*H12 -> 10017.776 | U12: =SUM(1800/68)*H12 -> 359.27471 | X12: =SUM(S12:W12) -> 10377.051 | Y12: =SUM(11143.04/68)*H12 -> 2224.118 | AA12: =SUM(134.1/68)*H12 -> 26.765966 | AB12: =SUM(Y12:AA12) -> 2250.884 | AC12: 7.25 | AD12: =SUM(AB12*AC12) -> 16318.909 | AE12: =SUM(X12+AD12) -> 26695.96 | AF12: =SUM(P12-AE12) -> 978.54009
C13: 241227000049 | D13: 46020 | E13: 陆总 | F13: 陆梓龙 | G13: WANG | H13: 2.8728 | I13: 1490 | J13: 5584.75 | P13: =SUBTOTAL(9,J13) -> 5584.75 | S13: =SUM(50190/68)*H13 -> 2120.3799 | U13: =SUM(1800/68)*H13 -> 76.044706 | X13: =SUM(S13:W13) -> 2196.4246 | Y13: =SUM(11143.04/68)*H13 -> 470.76067 | AA13: =SUM(134.1/68)*H13 -> 5.6653306 | AB13: =SUM(Y13:AA13) -> 476.426 | AC13: 7.25 | AD13: =SUM(AB13*AC13) -> 3454.0885 | AE13: =SUM(X13+AD13) -> 5650.5131 | AF13: =SUM(P13-AE13) -> -65.763066
C14: 241227000050 | D14: 46020 | E14: 陆总 | F14: 陆梓龙 | G14: xinlong | H14: 0.4118 | I14: 482 | J14: 1338.62 | P14: =SUBTOTAL(9,J14) -> 1338.62 | S14: =SUM(50190/68)*H14 -> 303.94474 | U14: =SUM(1800/68)*H14 -> 10.900588 | X14: =SUM(S14:W14) -> 314.84532 | Y14: =SUM(11143.04/68)*H14 -> 67.480939 | AA14: =SUM(134.1/68)*H14 -> 0.81209382 | AB14: =SUM(Y14:AA14) -> 68.293033 | AC14: 7.25 | AD14: =SUM(AB14*AC14) -> 495.12449 | AE14: =SUM(X14+AD14) -> 809.96981 | AF14: =SUM(P14-AE14) -> 528.65019
C15: 241227000051 | D15: 46020 | E15: 陆总 | F15: 陆梓龙 | G15: luk | H15: 0.0622 | I15: 8 | J15: 120.89 | P15: =SUBTOTAL(9,J15) -> 120.89 | S15: =SUM(50190/68)*H15 -> 45.909088 | U15: =SUM(1800/68)*H15 -> 1.6464706 | X15: =SUM(S15:W15) -> 47.555559 | Y15: =SUM(11143.04/68)*H15 -> 10.192604 | AA15: =SUM(134.1/68)*H15 -> 0.12266206 | AB15: =SUM(Y15:AA15) -> 10.315266 | AC15: 7.25 | AD15: =SUM(AB15*AC15) -> 74.785681 | AE15: =SUM(X15+AD15) -> 122.34124 | AF15: =SUM(P15-AE15) -> -1.4512395
C16: 241229000001 | D16: 46020 | E16: 罗珮文 | F16: Shirley | G16: SKY JET | H16: 32.35 | I16: 3811 | J16: 53783.17 | P16: =SUBTOTAL(9,J16) -> 53783.17 | S16: =SUM(50190/68)*H16 -> 23877.154 | U16: =SUM(1800/68)*H16 -> 856.32353 | X16: =SUM(S16:W16) -> 24733.478 | Y16: =SUM(11143.04/68)*H16 -> 5301.1374 | AA16: =SUM(134.1/68)*H16 -> 63.796103 | AB16: =SUM(Y16:AA16) -> 5364.9335 | AC16: 7.25 | AD16: =SUM(AB16*AC16) -> 38895.768 | AE16: =SUM(X16+AD16) -> 63629.246 | AF16: =SUM(P16-AE16) -> -9846.0759
C17: 241229000003 | D17: 46020 | E17: 罗珮文 | F17: Shirley | G17: SKY JET | H17: 1.51 | I17: 270 | J17: 2510.44 | P17: =SUBTOTAL(9,J17) -> 2510.44 | S17: =SUM(50190/68)*H17 -> 1114.5132 | U17: =SUM(1800/68)*H17 -> 39.970588 | X17: =SUM(S17:W17) -> 1154.4838 | Y17: =SUM(11143.04/68)*H17 -> 247.44104 | AA17: =SUM(134.1/68)*H17 -> 2.9778088 | AB17: =SUM(Y17:AA17) -> 250.41884 | AC17: 7.25 | AD17: =SUM(AB17*AC17) -> 1815.5366 | AE17: =SUM(X17+AD17) -> 2970.0204 | AF17: =SUM(P17-AE17) -> -459.58044
A18: 合计 | J18: =SUM(J4:J4) -> 0 | N18: =SUM(N4:N4) -> 0 | P18: =SUM(P4:P4) -> 0 | Q18: =SUM(Q4:Q4) -> 0 | X18: =SUM(X4:X4) -> 0 | AD18: =SUM(AD4:AD4) -> 0 | AF18: =SUM(AF4:AF17) -> 11861.717

Sheet JOB0202178
A1: 2024年12月份LOS毛利表（海运）
A2: PSL表 | B2: 体积cbm | C2: 18.78
A3: JOB | B3: 集装编号 | C3: 运单编号 | D3: 日期 | E3: 业务 | F3: 发货人 | G3: 收货人 | H3: 计费体积 | I3: 计费重量 | J3: 应 收 | Q3: 总应收 | R3: 起 运 港 成 本 | W3: 代垫运费 | X3: 起运港成本 合计 | Y3: 目的港成本 | AE3: 总支出 | AF3: 利润
J4: 应收RMB | K4: LOS Income(NGN)收到(奈拉) | L4: LOS 收到USD | M4: 美元汇率 dollar currency rate | N4: 应收 到付款USD | O4: 汇率 | P4: 人民币 | R4: 代理商 | S4: 运费+出口报关费 | T4: 提货费 | U4: 装卸费 | V4: 包装费 | Y4: 进口报关费 | Z4: 到门配送费 | AA4: 转运费 | AB4: 目的港支出 | AC4: 汇率 | AD4: 人民币 | AE4: 起运港+目的港
A5: JOB0202178 | B5: COLL004395 | C5: 241124000003 | D5: 46018 | E5: 黄颖 | F5: ying | G5: MISS Huang | H5: 18.78 | I5: 11408 | J5: 37467.5 | P5: =SUM(J5) -> 37467.5 | Q5: =SUM(P5) -> 37467.5 | R5: 赛捷 | S5: 32772 | V5: =SUM(351+277.5) -> 628.5 | X5: =SUM(S5:W5) -> 33400.5 | AB5: =SUM(Y5:AA5) -> 0 | AD5: =SUM(AB5*AC5) -> 0 | AE5: =SUM(X5+AD5) -> 33400.5 | AF5: =SUM(Q5-AE5) -> 4067
A6: 合计 | J6: =SUM(J4:J4) -> 0 | N6: =SUM(N4:N4) -> 0 | P6: =SUM(P4:P4) -> 0 | Q6: =SUM(Q4:Q4) -> 0 | X6: =SUM(X4:X4) -> 0 | AD6: =SUM(AD4:AD4) -> 0 | AF6: =SUM(AF4:AF5) -> 4067
