Workbook

Sheet 总表 
A1: 2024年11月份LOS毛利表（海运）
A2: JOB | B2: 集装编号 | C2: 利润
A4: JOB120361 | B4: COLL004287 | C4: =SUM('JOB120361'!AF22) -> 18752.529
A21: JOB120362 | B21: COLL004290 | C21: =SUM('JOB120362'!AF19) -> 3646.6843
A35: JOB120363 | B35: COLL004291 | C35: =SUM('JOB120363'!AF27) -> 16693.821
A57: JOB120364 | B57: COLL004298 | C57: =SUM('JOB120364'!AF25) -> 1768.3255
A77: JOB120365 | B77: COLL004301 | C77: =SUM('JOB120365'!AF22) -> 22745.723
A94: JOB120366 | B94: COLL004305 | C94: =SUM('JOB120366'!AF19) -> 6096.0564
A108: JOB120367 | B108: COLL004308 | C108: =SUM('JOB120367'!AF20) -> -13853.56
A123: JOB120368 | B123: COLL004310 | C123: =SUM('JOB120368'!AF26) -> 4132.9719
A144: 合计 | C144: =SUM(C3:C143) -> 59982.552

Sheet 总表  (2)
A1: 2024年11月份LOS毛利表（海运）
A2: JOB | B2: 集装编号 | C2: 运单编号 | D2: 日期 | E2: 业务 | F2: 发货人 | G2: 收货人 | H2: 计费体积 | I2: 计费重量 | J2: 应 收 | Q2: 总应收 | R2: 起 运 港 成 本 | W2: 代垫运费 | X2: 起运港成本 合计 | Y2: 目的港成本 | AE2: 总支出 | AF2: 利润
J3: 应收RMB | K3: LOS Income(NGN)收到(奈拉) | L3: LOS 收到USD | M3: 美元汇率 dollar currency rate | N3: 应收 到付款USD | O3: 汇率 | P3: 人民币 | R3: 代理商 | S3: 运费+出口报关费 | T3: 提货费 | U3: 装卸费 | V3: 包装费 | Y3: 进口报关费 | Z3: 到门配送费 | AA3: 转运费 | AB3: 目的港支出 | AC3: 汇率 | AD3: 人民币 | AE3: 起运港+目的港
A4: JOB120361 | B4: COLL004287 | C4: 240910000015 | D4: 45601 | E4: 吕沛霖 | F4: 喵喵速运-Layne | G4: Hu Hai Liang | H4: 5.1959 | I4: 743 | K4: 2382640 | M4: =SUM(K4/N4) -> 1580 | N4: 1508 | O4: 7.29 | P4: =SUM(N4*O4) -> 10993.32 | Q4: =SUM(P4:P20) -> 165324.28 | R4: 登凯=46189.5 陆总=1200 拖车费=1670 杂费=89 过磅费=66 | S4: =SUM(49214.5/68)*H4 -> 3760.4944 | T4: =SUM(113.64/68)*H4 -> 8.6832658 | U4: =SUM(2400/68)*H4 -> 183.38471 | X4: =SUM(S4:W4) -> 3952.5624 | Y4: =SUM(10949.72/68)*H4 -> 836.67133 | AB4: =SUM(Y4:AA4) -> 836.67133 | AC4: 7.33 | AD4: =SUM(AB4*AC4) -> 6132.8008 | AE4: =SUM(X4+AD4) -> 10085.363 | AF4: =SUM(P4-AE4) -> 907.95679
C5: 241023000029 | D5: 45601 | E5: 黄颖 | F5: ying | G5: Wole Rasak | H5: 0.0288 | I5: 5 | J5: 224.75 | P5: =SUBTOTAL(9,J5) -> 224.75 | S5: =SUM(49214.5/68)*H5 -> 20.843788 | T5: =SUM(113.64/68)*H5 -> 0.048129882 | U5: =SUM(2400/68)*H5 -> 1.0164706 | X5: =SUM(S5:W5) -> 21.908389 | Y5: =SUM(10949.72/68)*H5 -> 4.6375285 | AB5: =SUM(Y5:AA5) -> 4.6375285 | AC5: 7.33 | AD5: =SUM(AB5*AC5) -> 33.993084 | AE5: =SUM(X5+AD5) -> 55.901472 | AF5: =SUM(P5-AE5) -> 168.84853
C6: 241025000058 | D6: 45601 | E6: 苏慧琪 | F6: KAY | G6: BOYOU 吕 | H6: 13.7 | I6: 2550 | K6: 7067746.5 | M6: =SUM(K6/N6) -> 1648.8039 | N6: 4286.59 | O6: 7.29 | P6: =SUM(N6*O6) -> 31249.241 | S6: =SUM(49214.5/68)*H6 -> 9915.2743 | T6: =SUM(113.64/68)*H6 -> 22.895118 | U6: =SUM(2400/68)*H6 -> 483.52941 | X6: =SUM(S6:W6) -> 10421.699 | Y6: =SUM(10949.72/68)*H6 -> 2206.0465 | Z6: 90.97 | AB6: =SUM(Y6:AA6) -> 2297.0165 | AC6: 7.33 | AD6: =SUM(AB6*AC6) -> 16837.131 | AE6: =SUM(X6+AD6) -> 27258.83 | AF6: =SUM(P6-AE6) -> 3990.4111
C7: 241026000006 | D7: 45601 | E7: 吕沛霖 | F7: 喵喵速运-Layne | G7: LEO WEI | H7: 0.6549 | I7: 72 | K7: 363730 | M7: =SUM(K7/N7) -> 1683.0002 | N7: 216.12 | O7: 7.3 | P7: =SUM(N7*O7) -> 1577.676 | S7: =SUM(49214.5/68)*H7 -> 473.97906 | T7: =SUM(113.64/68)*H7 -> 1.0944535 | U7: =SUM(2400/68)*H7 -> 23.114118 | X7: =SUM(S7:W7) -> 498.18763 | Y7: =SUM(10949.72/68)*H7 -> 105.45547 | AB7: =SUM(Y7:AA7) -> 105.45547 | AC7: 7.33 | AD7: =SUM(AB7*AC7) -> 772.98856 | AE7: =SUM(X7+AD7) -> 1271.1762 | AF7: =SUM(P7-AE7) -> 306.49981
C8: 241027000011 | D8: 45601 | E8: 朱小飞 | F8: Isabel Zhu | G8: Maryam Tukur | H8: 0.5618 | I8: 55 | K8: 434000 | M8: =SUM(K8/N8) -> 1671.8028 | N8: 259.6 | O8: 7.3 | P8: =SUM(N8*O8) -> 1895.08 | S8: =SUM(49214.5/68)*H8 -> 406.59862 | T8: =SUM(113.64/68)*H8 -> 0.93886694 | U8: =SUM(2400/68)*H8 -> 19.828235 | V8: 310 | W8: 59 | X8: =SUM(S8:W8) -> 796.36572 | Y8: =SUM(10949.72/68)*H8 -> 90.46401 | AB8: =SUM(Y8:AA8) -> 90.46401 | AC8: 7.33 | AD8: =SUM(AB8*AC8) -> 663.1012 | AE8: =SUM(X8+AD8) -> 1459.4669 | AF8: =SUM(P8-AE8) -> 435.61308
C9: 241031000033 | D9: 45601 | E9: 黄颖 | F9: ying | G9: Bruce | H9: 1.9968 | I9: 845 | K9: 960734 | M9: =SUM(K9/N9) -> 1653.0179 | N9: 581.2 | O9: 7.29 | P9: =SUM(N9*O9) -> 4236.948 | S9: =SUM(49214.5/68)*H9 -> 1445.1693 | T9: =SUM(113.64/68)*H9 -> 3.3370052 | U9: =SUM(2400/68)*H9 -> 70.475294 | X9: =SUM(S9:W9) -> 1518.9816 | Y9: =SUM(10949.72/68)*H9 -> 321.53531 | AB9: =SUM(Y9:AA9) -> 321.53531 | AC9: 7.33 | AD9: =SUM(AB9*AC9) -> 2356.8538 | AE9: =SUM(X9+AD9) -> 3875.8354 | AF9: =SUM(P9-AE9) -> 361.11258
C10: 241028000022 | D10: 45601 | E10: 黄颖 | F10: ying | G10: Barrister Hammed | H10: 1.211 | I10: 331 | J10: 2690 | P10: =SUBTOTAL(9,J10) -> 2690 | S10: =SUM(49214.5/68)*H10 -> 876.45235 | T10: =SUM(113.64/68)*H10 -> 2.0237947 | U10: =SUM(2400/68)*H10 -> 42.741176 | X10: =SUM(S10:W10) -> 921.21732 | Y10: =SUM(10949.72/68)*H10 -> 195.00163 | AB10: =SUM(Y10:AA10) -> 195.00163 | AC10: 7.33 | AD10: =SUM(AB10*AC10) -> 1429.362 | AE10: =SUM(X10+AD10) -> 2350.5793 | AF10: =SUM(P10-AE10) -> 339.42073
C11: 241028000025 | D11: 45601 | E11: 吕沛霖 | F11: 喵喵速运-Layne | G11: Candice Ding | H11: 0.7015 | I11: 168 | K11: 432424.8 | M11: =SUM(K11/N11) -> 1710 | N11: 252.88 | O11: 7.3 | P11: =SUM(N11*O11) -> 1846.024 | S11: =SUM(49214.5/68)*H11 -> 507.70547 | T11: =SUM(113.64/68)*H11 -> 1.1723303 | U11: =SUM(2400/68)*H11 -> 24.758824 | X11: =SUM(S11:W11) -> 533.63662 | Y11: =SUM(10949.72/68)*H11 -> 112.95924 | Z11: 42.43 | AB11: =SUM(Y11:AA11) -> 155.38924 | AC11: 7.33 | AD11: =SUM(AB11*AC11) -> 1139.0032 | AE11: =SUM(X11+AD11) -> 1672.6398 | AF11: =SUM(P11-AE11) -> 173.38422
C12: 241028000036 | D12: 45601 | E12: Sam.Pao | F12: Sam.Pao | G12: Chizoba | H12: 19.1974 | I12: 2413 | J12: 38000 | P12: =SUBTOTAL(9,J12) -> 38000 | S12: =SUM(49214.5/68)*H12 -> 13893.977 | T12: =SUM(113.64/68)*H12 -> 32.082243 | U12: =SUM(2400/68)*H12 -> 677.55529 | X12: =SUM(S12:W12) -> 14603.615 | Y12: =SUM(10949.72/68)*H12 -> 3091.267 | AB12: =SUM(Y12:AA12) -> 3091.267 | AC12: 7.33 | AD12: =SUM(AB12*AC12) -> 22658.987 | AE12: =SUM(X12+AD12) -> 37262.602 | AF12: =SUM(P12-AE12) -> 737.3984
C13: 241028000057 | D13: 45601 | E13: 朱小飞 | F13: Isabel Zhu | G13: Halifa Success | H13: 0.8721 | I13: 153 | J13: 1785.59 | P13: =SUBTOTAL(9,J13) -> 1785.59 | S13: =SUM(49214.5/68)*H13 -> 631.17596 | T13: =SUM(113.64/68)*H13 -> 1.457433 | U13: =SUM(2400/68)*H13 -> 30.78 | X13: =SUM(S13:W13) -> 663.4134 | Y13: =SUM(10949.72/68)*H13 -> 140.43016 | AB13: =SUM(Y13:AA13) -> 140.43016 | AC13: 7.33 | AD13: =SUM(AB13*AC13) -> 1029.3531 | AE13: =SUM(X13+AD13) -> 1692.7665 | AF13: =SUM(P13-AE13) -> 92.823539
C14: 241029000017 | D14: 45601 | E14: 黄颖 | F14: ying | G14: jiangnan | H14: 0.2948 | I14: 65 | J14: 683.5 | P14: =SUBTOTAL(9,J14) -> 683.5 | S14: =SUM(49214.5/68)*H14 -> 213.35933 | T14: =SUM(113.64/68)*H14 -> 0.49266282 | U14: =SUM(2400/68)*H14 -> 10.404706 | X14: =SUM(S14:W14) -> 224.2567 | Y14: =SUM(10949.72/68)*H14 -> 47.470257 | AB14: =SUM(Y14:AA14) -> 47.470257 | AC14: 7.33 | AD14: =SUM(AB14*AC14) -> 347.95698 | AE14: =SUM(X14+AD14) -> 572.21368 | AF14: =SUM(P14-AE14) -> 111.28632
C15: 241030000002 | D15: 45601 | E15: 吕沛霖 | F15: 喵喵速运-Layne | G15: Mu Shi Shi | H15: 7.4945 | I15: 520 | J15: 18324.8 | P15: =SUBTOTAL(9,J15) -> 18324.8 | S15: =SUM(49214.5/68)*H15 -> 5424.0893 | T15: =SUM(113.64/68)*H15 -> 12.524632 | U15: =SUM(2400/68)*H15 -> 264.51176 | X15: =SUM(S15:W15) -> 5701.1257 | Y15: =SUM(10949.72/68)*H15 -> 1206.8041 | Z15: 47.85 | AB15: =SUM(Y15:AA15) -> 1254.6541 | AC15: 7.33 | AD15: =SUM(AB15*AC15) -> 9196.6143 | AE15: =SUM(X15+AD15) -> 14897.74 | AF15: =SUM(P15-AE15) -> 3427.06
C16: 241030000039 | D16: 45601 | E16: 黄颖 | F16: ying | G16: jiangnan | H16: 1.069 | I16: 138 | J16: 2506 | P16: =SUBTOTAL(9,J16) -> 2506 | S16: =SUM(49214.5/68)*H16 -> 773.68089 | T16: =SUM(113.64/68)*H16 -> 1.7864876 | U16: =SUM(2400/68)*H16 -> 37.729412 | X16: =SUM(S16:W16) -> 813.19679 | Y16: =SUM(10949.72/68)*H16 -> 172.13604 | AB16: =SUM(Y16:AA16) -> 172.13604 | AC16: 7.33 | AD16: =SUM(AB16*AC16) -> 1261.7572 | AE16: =SUM(X16+AD16) -> 2074.954 | AF16: =SUM(P16-AE16) -> 431.04604
C17: 241030000041 | D17: 45601 | E17: 吕沛霖 | F17: 喵喵速运-Layne | G17: WEI PING | H17: 1.5338 | I17: 336 | K17: 755361 | M17: =SUM(K17/N17) -> 1700 | N17: 444.33 | O17: 7.27 | P17: =SUM(N17*O17) -> 3230.2791 | S17: =SUM(49214.5/68)*H17 -> 1110.0765 | T17: =SUM(113.64/68)*H17 -> 2.5632505 | U17: =SUM(2400/68)*H17 -> 54.134118 | X17: =SUM(S17:W17) -> 1166.7738 | Y17: =SUM(10949.72/68)*H17 -> 246.9806 | Z17: 29.9 | AB17: =SUM(Y17:AA17) -> 276.8806 | AC17: 7.33 | AD17: =SUM(AB17*AC17) -> 2029.5348 | AE17: =SUM(X17+AD17) -> 3196.3086 | AF17: =SUM(P17-AE17) -> 33.97049
C18: 241101000029 | D18: 45601 | E18: 吕沛霖 | F18: 喵喵速运-Layne | G18: YA | H18: 0.8656 | I18: 346 | J18: 2978.64 | P18: =SUM(J18) -> 2978.64 | S18: =SUM(49214.5/68)*H18 -> 626.47164 | T18: =SUM(113.64/68)*H18 -> 1.4465704 | U18: =SUM(2400/68)*H18 -> 30.550588 | X18: =SUM(S18:W18) -> 658.46879 | Y18: =SUM(10949.72/68)*H18 -> 139.38349 | Z18: 12.36 | AA18: 83.19 | AB18: =SUM(Y18:AA18) -> 234.93349 | AC18: 7.33 | AD18: =SUM(AB18*AC18) -> 1722.0625 | AE18: =SUM(X18+AD18) -> 2380.5313 | AF18: =SUM(P18-AE18) -> 598.10869
C19: 241101000033 | D19: 45601 | E19: 朱小飞 | F19: Isabel Zhu | G19: Halifa Success | H19: 0.8844 | I19: 155 | J19: 1806.11 | P19: =SUBTOTAL(9,J19) -> 1806.11 | S19: =SUM(49214.5/68)*H19 -> 640.078 | T19: =SUM(113.64/68)*H19 -> 1.4779885 | U19: =SUM(2400/68)*H19 -> 31.214118 | X19: =SUM(S19:W19) -> 672.7701 | Y19: =SUM(10949.72/68)*H19 -> 142.41077 | AB19: =SUM(Y19:AA19) -> 142.41077 | AC19: 7.33 | AD19: =SUM(AB19*AC19) -> 1043.8709 | AE19: =SUM(X19+AD19) -> 1716.641 | AF19: =SUM(P19-AE19) -> 89.468952
C20: 241209000060 | D20: 45601 | E20: 陆总 | F20: 陆梓龙 | G20: xinlong | H20: 17.902 | I20: 17472 | J20: 41296.32 | P20: =SUBTOTAL(9,J20) -> 41296.32 | S20: =SUM(49214.5/68)*H20 -> 12956.441 | T20: =SUM(113.64/68)*H20 -> 29.917401 | U20: =SUM(2400/68)*H20 -> 631.83529 | X20: =SUM(S20:W20) -> 13618.194 | Y20: =SUM(10949.72/68)*H20 -> 2882.6748 | AB20: =SUM(Y20:AA20) -> 2882.6748 | AC20: 7.33 | AD20: =SUM(AB20*AC20) -> 21130.006 | AE20: =SUM(X20+AD20) -> 34748.2 | AF20: =SUM(P20-AE20) -> 6548.12
A21: JOB120362 | B21: COLL004290 | C21: 241028000047 | D21: 45602 | E21: Sam.Pao | F21: Sam.Pao | G21: Nick Wang | H21: 3.0981 | I21: 231 | J21: 8037.16 | P21: =SUBTOTAL(9,J21) -> 8037.16 | Q21: =SUM(P21:P34) -> 134933.06 | R21: 登凯=46189.5 陆总=800 拖车费=1670 杂费=61 过磅费=68 | S21: =SUM(48788.5/68)*H21 -> 2222.8184 | U21: =SUM(1800/68)*H21 -> 82.008529 | X21: =SUM(S21:W21) -> 2304.8269 | Y21: =SUM(10716.46/68)*H21 -> 488.24507 | AA21: =SUM(50.64/68)*H21 -> 2.3071733 | AB21: =SUM(Y21:AA21) -> 490.55224 | AC21: 7.33 | AD21: =SUM(AB21*AC21) -> 3595.7479 | AE21: =SUM(X21+AD21) -> 5900.5749 | AF21: =SUM(P21-AE21) -> 2136.5851
C22: 241029000048 | D22: 45602 | E22: 黄颖 | F22: ying | G22: Sunday Adelena | H22: 0.4438 | I22: 310 | J22: 964.05 | P22: =SUBTOTAL(9,J22) -> 964.05 | S22: =SUM(48788.5/68)*H22 -> 318.41671 | U22: =SUM(1800/68)*H22 -> 11.747647 | X22: =SUM(S22:W22) -> 330.16436 | Y22: =SUM(10716.46/68)*H22 -> 69.940661 | AA22: =SUM(50.64/68)*H22 -> 0.33050047 | AB22: =SUM(Y22:AA22) -> 70.271161 | AC22: 7.33 | AD22: =SUM(AB22*AC22) -> 515.08761 | AE22: =SUM(X22+AD22) -> 845.25197 | AF22: =SUM(P22-AE22) -> 118.79803
C23: 241030000021 | D23: 45602 | E23: 吕沛霖 | F23: 喵喵速运-Layne | G23: MA ZONG | H23: 0.6626 | I23: 405 | J23: 1624.5 | P23: =SUBTOTAL(9,J23) -> 1624.5 | S23: =SUM(48788.5/68)*H23 -> 475.40088 | U23: =SUM(1800/68)*H23 -> 17.539412 | X23: =SUM(S23:W23) -> 492.9403 | Y23: =SUM(10716.46/68)*H23 -> 104.42245 | Z23: 35.38 | AA23: =SUM(50.64/68)*H23 -> 0.49344212 | AB23: =SUM(Y23:AA23) -> 140.29589 | AC23: 7.33 | AD23: =SUM(AB23*AC23) -> 1028.3689 | AE23: =SUM(X23+AD23) -> 1521.3092 | AF23: =SUM(P23-AE23) -> 103.19084
C24: 241030000025 | D24: 45602 | E24: 黄颖 | F24: ying | G24: Nura | H24: 0.4092 | I24: 180 | J24: 876.05 | P24: =SUBTOTAL(9,J24) -> 876.05 | S24: =SUM(48788.5/68)*H24 -> 293.59197 | U24: =SUM(1800/68)*H24 -> 10.831765 | X24: =SUM(S24:W24) -> 304.42374 | Y24: =SUM(10716.46/68)*H24 -> 64.487874 | AA24: =SUM(50.64/68)*H24 -> 0.30473365 | AB24: =SUM(Y24:AA24) -> 64.792608 | AC24: 7.33 | AD24: =SUM(AB24*AC24) -> 474.92981 | AE24: =SUM(X24+AD24) -> 779.35355 | AF24: =SUM(P24-AE24) -> 96.696448
C25: 241031000033 | D25: 45602 | E25: 黄颖 | F25: ying | G25: Bruce | H25: 0.5837 | I25: 247 | K25: 280840 | M25: =SUM(K25/N25) -> 1652.9723 | N25: 169.9 | O25: 7.29 | P25: =SUM(N25*O25) -> 1238.571 | S25: =SUM(48788.5/68)*H25 -> 418.79187 | U25: =SUM(1800/68)*H25 -> 15.450882 | X25: =SUM(S25:W25) -> 434.24276 | Y25: =SUM(10716.46/68)*H25 -> 91.988202 | AA25: =SUM(50.64/68)*H25 -> 0.43468482 | AB25: =SUM(Y25:AA25) -> 92.422886 | AC25: 7.33 | AD25: =SUM(AB25*AC25) -> 677.45976 | AE25: =SUM(X25+AD25) -> 1111.7025 | AF25: =SUM(P25-AE25) -> 126.86849
C26: 241101000057 | D26: 45602 | E26: 陆总 | F26: 陆梓龙 | G26: jizong | H26: 1.1063 | I26: 567 | J26: 2422.8 | P26: =SUBTOTAL(9,J26) -> 2422.8 | S26: =SUM(48788.5/68)*H26 -> 793.74585 | U26: =SUM(1800/68)*H26 -> 29.284412 | X26: =SUM(S26:W26) -> 823.03026 | Y26: =SUM(10716.46/68)*H26 -> 174.34735 | AA26: =SUM(50.64/68)*H26 -> 0.82386812 | AB26: =SUM(Y26:AA26) -> 175.17122 | AC26: 7.33 | AD26: =SUM(AB26*AC26) -> 1284.005 | AE26: =SUM(X26+AD26) -> 2107.0353 | AF26: =SUM(P26-AE26) -> 315.76472
C27: 241104000038 | D27: 45602 | E27: 黄颖 | F27: ying | G27: Sunday Adelena | H27: 0.0737 | I27: 26 | J27: 214.23 | P27: =SUBTOTAL(9,J27) -> 214.23 | S27: =SUM(48788.5/68)*H27 -> 52.878124 | U27: =SUM(1800/68)*H27 -> 1.9508824 | X27: =SUM(S27:W27) -> 54.829007 | Y27: =SUM(10716.46/68)*H27 -> 11.614752 | AA27: =SUM(50.64/68)*H27 -> 0.054884824 | AB27: =SUM(Y27:AA27) -> 11.669636 | AC27: 7.33 | AD27: =SUM(AB27*AC27) -> 85.538434 | AE27: =SUM(X27+AD27) -> 140.36744 | AF27: =SUM(P27-AE27) -> 73.862559
C28: 241022000035 | D28: 45602 | E28: Bella | F28: Bella Chan | G28: zhong zi xin | H28: 27.424 | I28: 19896 | J28: 60720 | P28: =SUBTOTAL(9,J28) -> 60720 | S28: =SUM(48788.5/68)*H28 -> 19676.115 | U28: =SUM(1800/68)*H28 -> 725.92941 | X28: =SUM(S28:W28) -> 20402.044 | Y28: =SUM(10716.46/68)*H28 -> 4321.8853 | AA28: =SUM(50.64/68)*H28 -> 20.422814 | AB28: =SUM(Y28:AA28) -> 4342.3081 | AC28: 7.33 | AD28: =SUM(AB28*AC28) -> 31829.118 | AE28: =SUM(X28+AD28) -> 52231.163 | AF28: =SUM(P28-AE28) -> 8488.8372
C29: 241105000034 | D29: 45602 | E29: 朱小飞 | F29: Isabel Zhu | G29: Joy | H29: 0.7455 | I29: 854 | K29: 641427.2 | M29: =SUM(K29/N29) -> 1643 | N29: 390.4 | O29: 7.3 | P29: =SUM(N29*O29) -> 2849.92 | S29: =SUM(48788.5/68)*H29 -> 534.87981 | U29: =SUM(1800/68)*H29 -> 19.733824 | X29: =SUM(S29:W29) -> 554.61363 | Y29: =SUM(10716.46/68)*H29 -> 117.48707 | Z29: 29.21 | AA29: =SUM(50.64/68)*H29 -> 0.55517824 | AB29: =SUM(Y29:AA29) -> 147.25225 | AC29: 7.33 | AD29: =SUM(AB29*AC29) -> 1079.359 | AE29: =SUM(X29+AD29) -> 1633.9726 | AF29: =SUM(P29-AE29) -> 1215.9474
C30: 241106000001 | D30: 45602 | E30: Sam.Pao | F30: Sam.Pao | G30: MaiKaiNian | H30: 0.4542 | I30: 69 | J30: 1060.98 | P30: =SUBTOTAL(9,J30) -> 1060.98 | S30: =SUM(48788.5/68)*H30 -> 325.87848 | U30: =SUM(1800/68)*H30 -> 12.022941 | X30: =SUM(S30:W30) -> 337.90142 | Y30: =SUM(10716.46/68)*H30 -> 71.579649 | AA30: =SUM(50.64/68)*H30 -> 0.33824541 | AB30: =SUM(Y30:AA30) -> 71.917894 | AC30: 7.33 | AD30: =SUM(AB30*AC30) -> 527.15817 | AE30: =SUM(X30+AD30) -> 865.05959 | AF30: =SUM(P30-AE30) -> 195.92041
C31: 241106000002 | D31: 45602 | E31: Sam.Pao | F31: Sam.Pao | G31: Angel | H31: 0.3458 | I31: 98 | J31: 757 | P31: =SUBTOTAL(9,J31) -> 757 | S31: =SUM(48788.5/68)*H31 -> 248.10387 | U31: =SUM(1800/68)*H31 -> 9.1535294 | X31: =SUM(S31:W31) -> 257.2574 | Y31: =SUM(10716.46/68)*H31 -> 54.496351 | AA31: =SUM(50.64/68)*H31 -> 0.25751929 | AB31: =SUM(Y31:AA31) -> 54.75387 | AC31: 7.33 | AD31: =SUM(AB31*AC31) -> 401.34587 | AE31: =SUM(X31+AD31) -> 658.60327 | AF31: =SUM(P31-AE31) -> 98.396729
C32: 241106000018 | D32: 45602 | E32: Bella | F32: Bella Chan | G32: zhang long ting | H32: 0.0019 | I32: 1 | K32: 51150 | M32: =SUM(K32/N32) -> 1650 | N32: 31 | O32: 7.2 | P32: =SUM(N32*O32) -> 223.2 | S32: =SUM(48788.5/68)*H32 -> 1.3632081 | U32: =SUM(1800/68)*H32 -> 0.050294118 | X32: =SUM(S32:W32) -> 1.4135022 | Y32: =SUM(10716.46/68)*H32 -> 0.2994305 | AA32: =SUM(50.64/68)*H32 -> 0.0014149412 | AB32: =SUM(Y32:AA32) -> 0.30084544 | AC32: 7.33 | AD32: =SUM(AB32*AC32) -> 2.2051971 | AE32: =SUM(X32+AD32) -> 3.6186993 | AF32: =SUM(P32-AE32) -> 219.5813
C33: 241106000037 | D33: 45602 | E33: Sam.Pao | F33: Sam.Pao | G33: JunYue hotel | H33: 0.6996 | I33: 76 | J33: 1583.01 | P33: =SUBTOTAL(9,J33) -> 1583.01 | S33: =SUM(48788.5/68)*H33 -> 501.94757 | U33: =SUM(1800/68)*H33 -> 18.518824 | X33: =SUM(S33:W33) -> 520.46639 | Y33: =SUM(10716.46/68)*H33 -> 110.25346 | AA33: =SUM(50.64/68)*H33 -> 0.52099624 | AB33: =SUM(Y33:AA33) -> 110.77446 | AC33: 7.33 | AD33: =SUM(AB33*AC33) -> 811.97678 | AE33: =SUM(X33+AD33) -> 1332.4432 | AF33: =SUM(P33-AE33) -> 250.56683
C34: 241107000022 | D34: 45602 | E34: 罗珮文 | F34: Shirley | G34: SKY JET | H34: 32.635 | I34: 4165 | J34: 52361.59 | P34: =SUBTOTAL(9,J34) -> 52361.59 | S34: =SUM(48788.5/68)*H34 -> 23414.893 | U34: =SUM(1800/68)*H34 -> 863.86765 | X34: =SUM(S34:W34) -> 24278.76 | Y34: =SUM(10716.46/68)*H34 -> 5143.1128 | AA34: =SUM(50.64/68)*H34 -> 24.303476 | AB34: =SUM(Y34:AA34) -> 5167.4163 | AC34: 7.33 | AD34: =SUM(AB34*AC34) -> 37877.161 | AE34: =SUM(X34+AD34) -> 62155.922 | AF34: =SUM(P34-AE34) -> -9794.3317
A35: JOB120363 | B35: COLL004291 | C35: 240930000009 | D35: 45608 | E35: 黄颖 | F35: ying | G35: Tom chen | H35: 0.0977 | I35: 28.5 | K35: 132820 | M35: =SUM(K35/N35) -> 1648.9137 | N35: 80.55 | O35: 7.3 | P35: =SUM(N35*O35) -> 588.015 | Q35: =SUM(P35:P56) -> 188664.54 | R35: 登凯=43330 陆总=8000 拖车费=1670 杂费=93 过磅费=125 | S35: =SUM(53218/68)*H35 -> 76.461744 | U35: =SUM(1955/68)*H35 -> 2.808875 | X35: =SUM(S35:W35) -> 79.270619 | Y35: =SUM(11360.84/68)*H35 -> 16.322854 | Z35: 11.38 | AA35: =SUM(53.54/68)*H35 -> 0.076924382 | AB35: =SUM(Y35:AA35) -> 27.779778 | AC35: 7.3 | AD35: =SUM(AB35*AC35) -> 202.79238 | AE35: =SUM(X35+AD35) -> 282.063 | AF35: =SUM(P35-AE35) -> 305.952
C36: 241015000034 | D36: 45608 | E36: 朱小飞 | F36: Isabel Zhu | G36: Halifa Success | H36: 4.77 | I36: 451 | J36: 9789.95 | P36: =SUBTOTAL(9,J36) -> 9789.95 | S36: =SUM(53218/68)*H36 -> 3733.0862 | U36: =SUM(1955/68)*H36 -> 137.1375 | X36: =SUM(S36:W36) -> 3870.2237 | Y36: =SUM(11360.84/68)*H36 -> 796.92951 | AA36: =SUM(53.54/68)*H36 -> 3.7556735 | AB36: =SUM(Y36:AA36) -> 800.68519 | AC36: 7.3 | AD36: =SUM(AB36*AC36) -> 5845.0019 | AE36: =SUM(X36+AD36) -> 9715.2255 | AF36: =SUM(P36-AE36) -> 74.724471
C37: 241021000005 | D37: 45608 | E37: 吕沛霖 | F37: 喵喵速运-Layne | G37: Hu Hai Liang | H37: 1.1795 | I37: 335 | K37: 583853 | M37: =SUM(K37/N37) -> 1650.0015 | N37: 353.84998 | O37: 7.3 | P37: =SUM(N37*O37) -> 2583.1049 | S37: =SUM(53218/68)*H37 -> 923.09751 | U37: =SUM(1955/68)*H37 -> 33.910625 | X37: =SUM(S37:W37) -> 957.00814 | Y37: =SUM(11360.84/68)*H37 -> 197.06045 | AA37: =SUM(53.54/68)*H37 -> 0.92868279 | AB37: =SUM(Y37:AA37) -> 197.98914 | AC37: 7.3 | AD37: =SUM(AB37*AC37) -> 1445.3207 | AE37: =SUM(X37+AD37) -> 2402.3288 | AF37: =SUM(P37-AE37) -> 180.77603
C38: 241022000035 | D38: 45608 | E38: Bella | F38: Bella Chan | G38: zhong zi xin | H38: 28.3553 | I38: 15100 | J38: 62780 | P38: =SUBTOTAL(9,J38) -> 62780 | S38: =SUM(53218/68)*H38 -> 22191.358 | U38: =SUM(1955/68)*H38 -> 815.21488 | V38: 300 | X38: =SUM(S38:W38) -> 23306.573 | Y38: =SUM(11360.84/68)*H38 -> 4737.3533 | Z38: =SUM(413.88+371.27) -> 785.15 | AA38: =SUM(53.54/68)*H38 -> 22.325629 | AB38: =SUM(Y38:AA38) -> 5544.829 | AC38: 7.3 | AD38: =SUM(AB38*AC38) -> 40477.251 | AE38: =SUM(X38+AD38) -> 63783.824 | AF38: =SUM(P38-AE38) -> -1003.8244
C39: 241024000054 | D39: 45608 | E39: Sam.Pao | F39: Sam.Pao | G39: ShanShan | H39: 16.835 | I39: 7500 | J39: 48779 | P39: =SUBTOTAL(9,J39) -> 48779 | S39: =SUM(53218/68)*H39 -> 13175.368 | U39: =SUM(1955/68)*H39 -> 484.00625 | X39: =SUM(S39:W39) -> 13659.374 | Y39: =SUM(11360.84/68)*H39 -> 2812.6433 | Z39: 97.38 | AA39: =SUM(53.54/68)*H39 -> 13.255087 | AB39: =SUM(Y39:AA39) -> 2923.2783 | AC39: 7.3 | AD39: =SUM(AB39*AC39) -> 21339.932 | AE39: =SUM(X39+AD39) -> 34999.306 | AF39: =SUM(P39-AE39) -> 13779.694
C40: 241104000057 | D40: 45608 | E40: 朱小飞 | F40: Isabel Zhu | G40: Halifa Success | H40: 2.3978 | I40: 447 | J40: 4925.76 | P40: =SUBTOTAL(9,J40) -> 4925.76 | S40: =SUM(53218/68)*H40 -> 1876.5606 | U40: =SUM(1955/68)*H40 -> 68.93675 | X40: =SUM(S40:W40) -> 1945.4973 | Y40: =SUM(11360.84/68)*H40 -> 400.60327 | AA40: =SUM(53.54/68)*H40 -> 1.8879149 | AB40: =SUM(Y40:AA40) -> 402.49118 | AC40: 7.3 | AD40: =SUM(AB40*AC40) -> 2938.1856 | AE40: =SUM(X40+AD40) -> 4883.683 | AF40: =SUM(P40-AE40) -> 42.077029
C41: 241104000071 | D41: 45608 | E41: Bella | F41: Bella Chan | G41: FENG | H41: 0.2523 | I41: 27 | K41: 116127 | M41: =SUM(K41/N41) -> 1684.4648 | N41: 68.94 | O41: 7.3 | P41: =SUM(N41*O41) -> 503.262 | S41: =SUM(53218/68)*H41 -> 197.45443 | U41: =SUM(1955/68)*H41 -> 7.253625 | X41: =SUM(S41:W41) -> 204.70806 | Y41: =SUM(11360.84/68)*H41 -> 42.152058 | AA41: =SUM(53.54/68)*H41 -> 0.19864915 | AB41: =SUM(Y41:AA41) -> 42.350707 | AC41: 7.3 | AD41: =SUM(AB41*AC41) -> 309.16016 | AE41: =SUM(X41+AD41) -> 513.86822 | AF41: =SUM(P41-AE41) -> -10.606218
C42: 241105000024 | D42: 45608 | E42: 陆总 | F42: 陆梓龙 | G42: luk | H42: 2.0026 | I42: 262.5 | J42: 4385.69 | P42: =SUBTOTAL(9,J42) -> 4385.69 | S42: =SUM(53218/68)*H42 -> 1567.2701 | U42: =SUM(1955/68)*H42 -> 57.57475 | X42: =SUM(S42:W42) -> 1624.8448 | Y42: =SUM(11360.84/68)*H42 -> 334.57674 | AA42: =SUM(53.54/68)*H42 -> 1.576753 | AB42: =SUM(Y42:AA42) -> 336.15349 | AC42: 7.3 | AD42: =SUM(AB42*AC42) -> 2453.9205 | AE42: =SUM(X42+AD42) -> 4078.7653 | AF42: =SUM(P42-AE42) -> 306.92467
C43: 241105000025 | D43: 45608 | E43: 黄颖 | F43: ying | G43: Oba Adeoriyomi Oyebo | H43: 3.7323 | I43: 536 | K43: 1998941 | M43: =SUM(K43/N43) -> 1712.4484 | N43: 1167.3 | O43: 7.3 | P43: =SUM(N43*O43) -> 8521.29 | S43: =SUM(53218/68)*H43 -> 2920.9638 | U43: =SUM(1955/68)*H43 -> 107.30362 | W43: 350 | X43: =SUM(S43:W43) -> 3378.2675 | Y43: =SUM(11360.84/68)*H43 -> 623.55975 | AA43: =SUM(53.54/68)*H43 -> 2.9386374 | AB43: =SUM(Y43:AA43) -> 626.49839 | AC43: 7.3 | AD43: =SUM(AB43*AC43) -> 4573.4382 | AE43: =SUM(X43+AD43) -> 7951.7057 | AF43: =SUM(P43-AE43) -> 569.58429
C44: 241105000054 | D44: 45608 | E44: 苏慧琪 | F44: KAY | G44: R李金 | H44: 0.3709 | I44: 167 | K44: 206012.98 | M44: =SUM(K44/N44) -> 1664.8859 | N44: 123.74 | O44: 7.27 | P44: =SUM(N44*O44) -> 899.5898 | S44: =SUM(53218/68)*H44 -> 290.27289 | U44: =SUM(1955/68)*H44 -> 10.663375 | X44: =SUM(S44:W44) -> 300.93626 | Y44: =SUM(11360.84/68)*H44 -> 61.966699 | AA44: =SUM(53.54/68)*H44 -> 0.29202921 | AB44: =SUM(Y44:AA44) -> 62.258729 | AC44: 7.3 | AD44: =SUM(AB44*AC44) -> 454.48872 | AE44: =SUM(X44+AD44) -> 755.42498 | AF44: =SUM(P44-AE44) -> 144.16482
C45: 241106000015 | D45: 45608 | E45: 朱小飞 | F45: Isabel Zhu | G45: Komebility gift | H45: 0.2358 | I45: 43 | K45: 132422.4 | M45: =SUM(K45/N45) -> 1672 | N45: 79.2 | O45: 7.3 | P45: =SUM(N45*O45) -> 578.16 | S45: =SUM(53218/68)*H45 -> 184.54124 | U45: =SUM(1955/68)*H45 -> 6.77925 | X45: =SUM(S45:W45) -> 191.32049 | Y45: =SUM(11360.84/68)*H45 -> 39.395383 | AA45: =SUM(53.54/68)*H45 -> 0.18565782 | AB45: =SUM(Y45:AA45) -> 39.581041 | AC45: 7.3 | AD45: =SUM(AB45*AC45) -> 288.9416 | AE45: =SUM(X45+AD45) -> 480.26209 | AF45: =SUM(P45-AE45) -> 97.897908
C46: 241106000020 | D46: 45608 | E46: 黄颖 | F46: ying | G46: yuhuichao | H46: 0.3 | I46: 65 | J46: 908 | P46: =SUBTOTAL(9,J46) -> 908 | S46: =SUM(53218/68)*H46 -> 234.78529 | U46: =SUM(1955/68)*H46 -> 8.625 | X46: =SUM(S46:W46) -> 243.41029 | Y46: =SUM(11360.84/68)*H46 -> 50.121353 | Z46: 34.85 | AA46: =SUM(53.54/68)*H46 -> 0.23620588 | AB46: =SUM(Y46:AA46) -> 85.207559 | AC46: 7.3 | AD46: =SUM(AB46*AC46) -> 622.01518 | AE46: =SUM(X46+AD46) -> 865.42547 | AF46: =SUM(P46-AE46) -> 42.574526
C47: 241106000026 | D47: 45608 | E47: 吕沛霖 | F47: 喵喵速运-Layne | G47: Mr.Shen | H47: 0.1938 | I47: 63 | K47: 188972 | M47: =SUM(K47/N47) -> 1700 | N47: 111.16 | O47: 7.27 | P47: =SUM(N47*O47) -> 808.1332 | S47: =SUM(53218/68)*H47 -> 151.6713 | U47: =SUM(1955/68)*H47 -> 5.57175 | X47: =SUM(S47:W47) -> 157.24305 | Y47: =SUM(11360.84/68)*H47 -> 32.378394 | Z47: 53.58 | AA47: =SUM(53.54/68)*H47 -> 0.152589 | AB47: =SUM(Y47:AA47) -> 86.110983 | AC47: 7.3 | AD47: =SUM(AB47*AC47) -> 628.61018 | AE47: =SUM(X47+AD47) -> 785.85323 | AF47: =SUM(P47-AE47) -> 22.279974
C48: 241106000034 | D48: 45608 | E48: 黄颖 | F48: ying | G48: Mr.zhang | H48: 0.3814 | I48: 55 | J48: 1213 | P48: =SUBTOTAL(9,J48) -> 1213 | S48: =SUM(53218/68)*H48 -> 298.49037 | U48: =SUM(1955/68)*H48 -> 10.96525 | X48: =SUM(S48:W48) -> 309.45562 | Y48: =SUM(11360.84/68)*H48 -> 63.720947 | Z48: 44.32 | AA48: =SUM(53.54/68)*H48 -> 0.30029641 | AB48: =SUM(Y48:AA48) -> 108.34124 | AC48: 7.3 | AD48: =SUM(AB48*AC48) -> 790.89107 | AE48: =SUM(X48+AD48) -> 1100.3467 | AF48: =SUM(P48-AE48) -> 112.6533
C49: 241106000049 | D49: 45608 | E49: 黄颖 | F49: ying | G49: wuchengxing | H49: 0.0224 | I49: 5.5 | J49: 228 | P49: =SUBTOTAL(9,J49) -> 228 | S49: =SUM(53218/68)*H49 -> 17.530635 | U49: =SUM(1955/68)*H49 -> 0.644 | X49: =SUM(S49:W49) -> 18.174635 | Y49: =SUM(11360.84/68)*H49 -> 3.7423944 | AA49: =SUM(53.54/68)*H49 -> 0.017636706 | AB49: =SUM(Y49:AA49) -> 3.7600311 | AC49: 7.3 | AD49: =SUM(AB49*AC49) -> 27.448227 | AE49: =SUM(X49+AD49) -> 45.622862 | AF49: =SUM(P49-AE49) -> 182.37714
C50: 241107000010 | D50: 45608 | E50: 朱小飞 | F50: Isabel Zhu | G50: Joy | H50: 0.616 | I50: 188 | K50: 331724.8 | M50: =SUM(K50/N50) -> 1672 | N50: 198.4 | O50: 7.3 | P50: =SUM(N50*O50) -> 1448.32 | S50: =SUM(53218/68)*H50 -> 482.09247 | U50: =SUM(1955/68)*H50 -> 17.71 | X50: =SUM(S50:W50) -> 499.80247 | Y50: =SUM(11360.84/68)*H50 -> 102.91584 | Z50: 3.11 | AA50: =SUM(53.54/68)*H50 -> 0.48500941 | AB50: =SUM(Y50:AA50) -> 106.51085 | AC50: 7.3 | AD50: =SUM(AB50*AC50) -> 777.52924 | AE50: =SUM(X50+AD50) -> 1277.3317 | AF50: =SUM(P50-AE50) -> 170.98829
C51: 241107000011 | D51: 45608 | E51: 朱小飞 | F51: Isabel Zhu | G51: Joy | H51: 2.028 | I51: 358 | K51: 1086131.2 | M51: =SUM(K51/N51) -> 1672 | N51: 649.6 | O51: 7.3 | P51: =SUM(N51*O51) -> 4742.08 | S51: =SUM(53218/68)*H51 -> 1587.1486 | U51: =SUM(1955/68)*H51 -> 58.305 | X51: =SUM(S51:W51) -> 1645.4536 | Y51: =SUM(11360.84/68)*H51 -> 338.82035 | Z51: 10.18 | AA51: =SUM(53.54/68)*H51 -> 1.5967518 | AB51: =SUM(Y51:AA51) -> 350.5971 | AC51: 7.3 | AD51: =SUM(AB51*AC51) -> 2559.3588 | AE51: =SUM(X51+AD51) -> 4204.8124 | AF51: =SUM(P51-AE51) -> 537.2676
C52: 241107000012 | D52: 45608 | E52: 朱小飞 | F52: Isabel Zhu | G52: Joy | H52: 7.8483 | I52: 1598 | K52: 4200064 | M52: =SUM(K52/N52) -> 1672 | N52: 2512 | O52: 7.3 | P52: =SUM(N52*O52) -> 18337.6 | S52: =SUM(53218/68)*H52 -> 6142.2181 | U52: =SUM(1955/68)*H52 -> 225.63862 | X52: =SUM(S52:W52) -> 6367.8567 | Y52: =SUM(11360.84/68)*H52 -> 1311.2247 | Z52: 39.27 | AA52: =SUM(53.54/68)*H52 -> 6.1793821 | AB52: =SUM(Y52:AA52) -> 1356.6741 | AC52: 7.3 | AD52: =SUM(AB52*AC52) -> 9903.7209 | AE52: =SUM(X52+AD52) -> 16271.578 | AF52: =SUM(P52-AE52) -> 2066.0224
C53: 241108000001 | D53: 45608 | E53: Sam.Pao | F53: Sam.Pao | G53: Mr. Jiang | H53: 1.6887 | I53: 558 | J53: 5053 | P53: =SUBTOTAL(9,J53) -> 5053 | S53: =SUM(53218/68)*H53 -> 1321.6064 | U53: =SUM(1955/68)*H53 -> 48.550125 | X53: =SUM(S53:W53) -> 1370.1565 | Y53: =SUM(11360.84/68)*H53 -> 282.1331 | Z53: 57.94 | AA53: =SUM(53.54/68)*H53 -> 1.3296029 | AB53: =SUM(Y53:AA53) -> 341.4027 | AC53: 7.3 | AD53: =SUM(AB53*AC53) -> 2492.2397 | AE53: =SUM(X53+AD53) -> 3862.3962 | AF53: =SUM(P53-AE53) -> 1190.6038
C54: 241109000008 | D54: 45608 | E54: 朱小飞 | F54: Isabel Zhu | G54: Komebility gift | H54: 1.344 | I54: 254 | K54: 696622.08 | M54: =SUM(K54/N54) -> 1672 | N54: 416.64 | O54: 7.3 | P54: =SUM(N54*O54) -> 3041.472 | S54: =SUM(53218/68)*H54 -> 1051.8381 | U54: =SUM(1955/68)*H54 -> 38.64 | X54: =SUM(S54:W54) -> 1090.4781 | Y54: =SUM(11360.84/68)*H54 -> 224.54366 | AA54: =SUM(53.54/68)*H54 -> 1.0582024 | AB54: =SUM(Y54:AA54) -> 225.60186 | AC54: 7.3 | AD54: =SUM(AB54*AC54) -> 1646.8936 | AE54: =SUM(X54+AD54) -> 2737.3717 | AF54: =SUM(P54-AE54) -> 304.10028
C55: 241210000044 | D55: 45609 | E55: 罗珮文 | F55: Shirley | G55: SKY JET | H55: 5.104 | I55: 471 | J55: 7929.81 | P55: =SUBTOTAL(9,J55) -> 7929.81 | S55: =SUM(53218/68)*H55 -> 3994.4805 | U55: =SUM(1955/68)*H55 -> 146.74 | X55: =SUM(S55:W55) -> 4141.2205 | Y55: =SUM(11360.84/68)*H55 -> 852.73128 | AA55: =SUM(53.54/68)*H55 -> 4.0186494 | AB55: =SUM(Y55:AA55) -> 856.74993 | AC55: 7.3 | AD55: =SUM(AB55*AC55) -> 6254.2745 | AE55: =SUM(X55+AD55) -> 10395.495 | AF55: =SUM(P55-AE55) -> -2465.685
C56: 241112000025 | D56: 45608 | E56: 陆总 | F56: 陆梓龙 | G56: xinlong | H56: 0.2838 | I56: 166 | J56: 621.3 | P56: =SUBTOTAL(9,J56) -> 621.3 | S56: =SUM(53218/68)*H56 -> 222.10689 | U56: =SUM(1955/68)*H56 -> 8.15925 | X56: =SUM(S56:W56) -> 230.26614 | Y56: =SUM(11360.84/68)*H56 -> 47.4148 | AA56: =SUM(53.54/68)*H56 -> 0.22345076 | AB56: =SUM(Y56:AA56) -> 47.638251 | AC56: 7.3 | AD56: =SUM(AB56*AC56) -> 347.75923 | AE56: =SUM(X56+AD56) -> 578.02537 | AF56: =SUM(P56-AE56) -> 43.274632
A57: JOB120364 | B57: COLL004298 | C57: 241030000025 | D57: 45609 | E57: 黄颖 | F57: ying | G57: Nura | H57: 0.0306 | I57: 10 | J57: 65 | P57: =SUBTOTAL(9,J57) -> 65 | Q57: =SUM(P57:P76) -> 145491.1 | R57: 登凯=43330 赛捷=1660 拖车费=1670 杂费=73 过磅费=70 | S57: =SUM(46803/68)*H57 -> 21.06135 | U57: =SUM(1800/68)*H57 -> 0.81 | X57: =SUM(S57:W57) -> 21.87135 | Y57: =SUM(10793.87/68)*H57 -> 4.8572415 | AA57: =SUM(94.98/68)*H57 -> 0.042741 | AB57: =SUM(Y57:AA57) -> 4.8999825 | AC57: 7.33 | AD57: =SUM(AB57*AC57) -> 35.916872 | AE57: =SUM(X57+AD57) -> 57.788222 | AF57: =SUM(P57-AE57) -> 7.2117783
C58: 241102000008 | D58: 45609 | E58: 黄颖 | F58: ying | G58: Bruce | H58: 2.0582 | I58: 755 | K58: 957151 | M58: =SUM(K58/N58) -> 1603.5903 | N58: 596.88 | O58: 7.3 | P58: =SUM(N58*O58) -> 4357.224 | S58: =SUM(46803/68)*H58 -> 1416.6167 | U58: =SUM(1800/68)*H58 -> 54.481765 | X58: =SUM(S58:W58) -> 1471.0984 | Y58: =SUM(10793.87/68)*H58 -> 326.70505 | AA58: =SUM(94.98/68)*H58 -> 2.8748211 | AB58: =SUM(Y58:AA58) -> 329.57987 | AC58: 7.33 | AD58: =SUM(AB58*AC58) -> 2415.8204 | AE58: =SUM(X58+AD58) -> 3886.9189 | AF58: =SUM(P58-AE58) -> 470.30511
C59: 241107000009 | D59: 45609 | E59: 黄颖 | F59: ying | G59: MISS Huang | H59: 1.6128 | I59: 1251 | J59: 3794.79 | P59: =SUBTOTAL(9,J59) -> 3794.79 | S59: =SUM(46803/68)*H59 -> 1110.057 | U59: =SUM(1800/68)*H59 -> 42.691765 | X59: =SUM(S59:W59) -> 1152.7488 | Y59: =SUM(10793.87/68)*H59 -> 256.0052 | AA59: =SUM(94.98/68)*H59 -> 2.2527021 | AB59: =SUM(Y59:AA59) -> 258.2579 | AC59: 7.33 | AD59: =SUM(AB59*AC59) -> 1893.0304 | AE59: =SUM(X59+AD59) -> 3045.7792 | AF59: =SUM(P59-AE59) -> 749.01078
C60: 241104000001 | D60: 45609 | E60: 吕沛霖 | F60: 喵喵速运-Layne | G60: Isa | H60: 0.462 | I60: 90 | K60: 368397.9 | M60: =SUM(K60/N60) -> 1665 | N60: 221.26 | O60: 7.3 | P60: =SUM(N60*O60) -> 1615.198 | S60: =SUM(46803/68)*H60 -> 317.98509 | U60: =SUM(1800/68)*H60 -> 12.229412 | X60: =SUM(S60:W60) -> 330.2145 | Y60: =SUM(10793.87/68)*H60 -> 73.334823 | Z60: 57.94 | AA60: =SUM(94.98/68)*H60 -> 0.64530529 | AB60: =SUM(Y60:AA60) -> 131.92013 | AC60: 7.33 | AD60: =SUM(AB60*AC60) -> 966.97454 | AE60: =SUM(X60+AD60) -> 1297.189 | AF60: =SUM(P60-AE60) -> 318.00896
C61: 241105000045 | D61: 45609 | E61: 吕沛霖 | F61: 喵喵速运-Layne | G61: Abdulsheldu | H61: 0.8486 | I61: 297 | K61: 432928.65 | M61: =SUM(K61/N61) -> 1663.255 | N61: 260.29 | O61: 7.3 | P61: =SUM(N61*O61) -> 1900.117 | S61: =SUM(46803/68)*H61 -> 584.07391 | U61: =SUM(1800/68)*H61 -> 22.462941 | X61: =SUM(S61:W61) -> 606.53685 | Y61: =SUM(10793.87/68)*H61 -> 134.70115 | Z61: 10.07 | AA61: =SUM(94.98/68)*H61 -> 1.1852945 | AB61: =SUM(Y61:AA61) -> 145.95644 | AC61: 7.33 | AD61: =SUM(AB61*AC61) -> 1069.8607 | AE61: =SUM(X61+AD61) -> 1676.3976 | AF61: =SUM(P61-AE61) -> 223.71942
C62: 241108000043 | D62: 45609 | E62: Bella | F62: Bella Chan | G62: weng zixian | H62: 1.4833 | I62: 598 | K62: 1160958 | M62: =SUM(K62/N62) -> 1666.4389 | N62: 696.67 | O62: 7.3 | P62: =SUM(N62*O62) -> 5085.691 | S62: =SUM(46803/68)*H62 -> 1020.9249 | U62: =SUM(1800/68)*H62 -> 39.263824 | X62: =SUM(S62:W62) -> 1060.1887 | Y62: =SUM(10793.87/68)*H62 -> 235.44923 | Z62: 251.65 | AA62: =SUM(94.98/68)*H62 -> 2.0718211 | AB62: =SUM(Y62:AA62) -> 489.17105 | AC62: 7.33 | AD62: =SUM(AB62*AC62) -> 3585.6238 | AE62: =SUM(X62+AD62) -> 4645.8125 | AF62: =SUM(P62-AE62) -> 439.87855
C63: 241111000011 | D63: 45609 | E63: 朱小飞 | F63: Isabel Zhu | G63: Ope Olofinjana | H63: 0.1421 | I63: 36 | K63: 93936 | M63: =SUM(K63/N63) -> 1651.1865 | N63: 56.89 | O63: 7.3 | P63: =SUM(N63*O63) -> 415.297 | S63: =SUM(46803/68)*H63 -> 97.804504 | U63: =SUM(1800/68)*H63 -> 3.7614706 | X63: =SUM(S63:W63) -> 101.56597 | Y63: =SUM(10793.87/68)*H63 -> 22.556014 | Z63: 10 | AA63: =SUM(94.98/68)*H63 -> 0.19848026 | AB63: =SUM(Y63:AA63) -> 32.754494 | AC63: 7.33 | AD63: =SUM(AB63*AC63) -> 240.09044 | AE63: =SUM(X63+AD63) -> 341.65642 | AF63: =SUM(P63-AE63) -> 73.640585
C64: 241111000012 | D64: 45609 | E64: 朱小飞 | F64: Isabel Zhu | G64: Ope Olofinjana | H64: 0.2386 | I64: 52 | K64: 148176 | M64: =SUM(K64/N64) -> 1651.17 | N64: 89.74 | O64: 7.3 | P64: =SUM(N64*O64) -> 655.102 | S64: =SUM(46803/68)*H64 -> 164.22347 | U64: =SUM(1800/68)*H64 -> 6.3158824 | X64: =SUM(S64:W64) -> 170.53935 | Y64: =SUM(10793.87/68)*H64 -> 37.873785 | Z64: 11.3 | AA64: =SUM(94.98/68)*H64 -> 0.33326806 | AB64: =SUM(Y64:AA64) -> 49.507053 | AC64: 7.33 | AD64: =SUM(AB64*AC64) -> 362.8867 | AE64: =SUM(X64+AD64) -> 533.42605 | AF64: =SUM(P64-AE64) -> 121.67595
C65: 241111000032 | D65: 45609 | E65: Bella | F65: Bella Chan | G65: FENG | H65: 0.2174 | I65: 57 | K65: 107613 | M65: =SUM(K65/N65) -> 1650.0003 | N65: 65.21999 | O65: 7.2 | P65: =SUM(N65*O65) -> 469.58393 | S65: =SUM(46803/68)*H65 -> 149.63194 | U65: =SUM(1800/68)*H65 -> 5.7547059 | X65: =SUM(S65:W65) -> 155.38665 | Y65: =SUM(10793.87/68)*H65 -> 34.508637 | AA65: =SUM(94.98/68)*H65 -> 0.30365665 | AB65: =SUM(Y65:AA65) -> 34.812294 | AC65: 7.33 | AD65: =SUM(AB65*AC65) -> 255.17411 | AE65: =SUM(X65+AD65) -> 410.56076 | AF65: =SUM(P65-AE65) -> 59.023163
C66: 241111000039 | D66: 45609 | E66: 无人 | F66: dejare James | G66: James | H66: 1.8662 | I66: 626 | L66: 559.83 | M66: =SUM(K66/N66) -> 0 | N66: 559.82996 | O66: 7.3 | P66: =SUM(N66*O66) -> 4086.7587 | S66: =SUM(46803/68)*H66 -> 1284.467 | U66: =SUM(1800/68)*H66 -> 49.399412 | X66: =SUM(S66:W66) -> 1333.8664 | Y66: =SUM(10793.87/68)*H66 -> 296.22824 | AA66: =SUM(94.98/68)*H66 -> 2.6066423 | AB66: =SUM(Y66:AA66) -> 298.83488 | AC66: 7.33 | AD66: =SUM(AB66*AC66) -> 2190.4597 | AE66: =SUM(X66+AD66) -> 3524.3261 | AF66: =SUM(P66-AE66) -> 562.43258
C67: 241111000055 | D67: 45609 | E67: 朱小飞 | F67: Isabel Zhu | G67: Halifa Success | H67: 2.9026 | I67: 435 | J67: 5972.48 | P67: =SUBTOTAL(9,J67) -> 5972.48 | S67: =SUM(46803/68)*H67 -> 1997.7998 | U67: =SUM(1800/68)*H67 -> 76.833529 | V67: 20 | X67: =SUM(S67:W67) -> 2094.6334 | Y67: =SUM(10793.87/68)*H67 -> 460.73952 | AA67: =SUM(94.98/68)*H67 -> 4.0542492 | AB67: =SUM(Y67:AA67) -> 464.79376 | AC67: 7.33 | AD67: =SUM(AB67*AC67) -> 3406.9383 | AE67: =SUM(X67+AD67) -> 5501.5716 | AF67: =SUM(P67-AE67) -> 470.90835
C68: 241111000056 | D68: 45609 | E68: 朱小飞 | F68: Isabel Zhu | G68: Halifa Success | H68: 2.4588 | I68: 346 | J68: 5048.9 | P68: =SUBTOTAL(9,J68) -> 5048.9 | S68: =SUM(46803/68)*H68 -> 1692.3414 | U68: =SUM(1800/68)*H68 -> 65.085882 | X68: =SUM(S68:W68) -> 1757.4273 | Y68: =SUM(10793.87/68)*H68 -> 390.29364 | AA68: =SUM(94.98/68)*H68 -> 3.4343651 | AB68: =SUM(Y68:AA68) -> 393.72801 | AC68: 7.33 | AD68: =SUM(AB68*AC68) -> 2886.0263 | AE68: =SUM(X68+AD68) -> 4643.4536 | AF68: =SUM(P68-AE68) -> 405.44642
C69: 241112000043 | D69: 45609 | E69: Sam.Pao | F69: Sam.Pao | G69: MaiKaiNian | H69: 4.9039 | I69: 546 | J69: 10739.54 | P69: =SUBTOTAL(9,J69) -> 10739.54 | S69: =SUM(46803/68)*H69 -> 3375.2534 | U69: =SUM(1800/68)*H69 -> 129.80912 | X69: =SUM(S69:W69) -> 3505.0625 | Y69: =SUM(10793.87/68)*H69 -> 778.41263 | AA69: =SUM(94.98/68)*H69 -> 6.8495944 | AB69: =SUM(Y69:AA69) -> 785.26223 | AC69: 7.33 | AD69: =SUM(AB69*AC69) -> 5755.9721 | AE69: =SUM(X69+AD69) -> 9261.0347 | AF69: =SUM(P69-AE69) -> 1478.5053
C70: 241112000044 | D70: 45609 | E70: 朱小飞 | F70: Isabel Zhu | G70: Halifa Success | H70: 0.936 | I70: 422 | J70: 2195.26 | P70: =SUBTOTAL(9,J70) -> 2195.26 | S70: =SUM(46803/68)*H70 -> 644.22953 | U70: =SUM(1800/68)*H70 -> 24.776471 | W70: 266 | X70: =SUM(S70:W70) -> 935.006 | Y70: =SUM(10793.87/68)*H70 -> 148.57445 | Z70: 17.33 | AA70: =SUM(94.98/68)*H70 -> 1.3073718 | AB70: =SUM(Y70:AA70) -> 167.21182 | AC70: 7.33 | AD70: =SUM(AB70*AC70) -> 1225.6626 | AE70: =SUM(X70+AD70) -> 2160.6686 | AF70: =SUM(P70-AE70) -> 34.591377
C71: 241113000012 | D71: 45609 | E71: 罗珮文 | F71: Shirley | G71: Yusky | H71: 5.5016 | I71: 2874 | K71: 2264723.3 | M71: =SUM(K71/N71) -> 1608 | N71: 1408.41 | O71: 7.3 | P71: =SUM(N71*O71) -> 10281.393 | S71: =SUM(46803/68)*H71 -> 3786.638 | U71: =SUM(1800/68)*H71 -> 145.63059 | X71: =SUM(S71:W71) -> 3932.2686 | Y71: =SUM(10793.87/68)*H71 -> 873.28758 | AA71: =SUM(94.98/68)*H71 -> 7.6844407 | AB71: =SUM(Y71:AA71) -> 880.97202 | AC71: 7.33 | AD71: =SUM(AB71*AC71) -> 6457.5249 | AE71: =SUM(X71+AD71) -> 10389.793 | AF71: =SUM(P71-AE71) -> -108.40049
C72: 241113000017 | D72: 45609 | E72: Sam.Pao | F72: Sam.Pao | G72: FanXiangGuo | H72: 1.4152 | I72: 656 | K72: 851651 | M72: =SUM(K72/N72) -> 1671.5099 | N72: 509.51 | O72: 7.29 | P72: =SUM(N72*O72) -> 3714.3279 | S72: =SUM(46803/68)*H72 -> 974.05302 | U72: =SUM(1800/68)*H72 -> 37.461176 | W72: 98.72 | X72: =SUM(S72:W72) -> 1110.2342 | Y72: =SUM(10793.87/68)*H72 -> 224.63948 | AA72: =SUM(94.98/68)*H72 -> 1.9767014 | AB72: =SUM(Y72:AA72) -> 226.61618 | AC72: 7.33 | AD72: =SUM(AB72*AC72) -> 1661.0966 | AE72: =SUM(X72+AD72) -> 2771.3308 | AF72: =SUM(P72-AE72) -> 942.99707
C73: 241209000061 | D73: 45609 | E73: 陆总 | F73: 陆梓龙 | G73: xinlong | H73: 16.4369 | I73: 16042 | J73: 37916.64 | P73: =SUBTOTAL(9,J73) -> 37916.64 | S73: =SUM(46803/68)*H73 -> 11313.18 | U73: =SUM(1800/68)*H73 -> 435.09441 | X73: =SUM(S73:W73) -> 11748.274 | Y73: =SUM(10793.87/68)*H73 -> 2609.0847 | Z73: 162.02 | AA73: =SUM(94.98/68)*H73 -> 22.958482 | AB73: =SUM(Y73:AA73) -> 2794.0632 | AC73: 7.33 | AD73: =SUM(AB73*AC73) -> 20480.483 | AE73: =SUM(X73+AD73) -> 32228.758 | AF73: =SUM(P73-AE73) -> 5687.8824
C74: 241210000044 | D74: 45609 | E74: 罗珮文 | F74: Shirley | G74: SKY JET | H74: 5.896 | I74: 922 | J74: 9160.23 | P74: =SUBTOTAL(9,J74) -> 9160.23 | S74: =SUM(46803/68)*H74 -> 4058.0954 | U74: =SUM(1800/68)*H74 -> 156.07059 | X74: =SUM(S74:W74) -> 4214.166 | Y74: =SUM(10793.87/68)*H74 -> 935.89202 | AA74: =SUM(94.98/68)*H74 -> 8.2353247 | AB74: =SUM(Y74:AA74) -> 944.12735 | AC74: 7.33 | AD74: =SUM(AB74*AC74) -> 6920.4535 | AE74: =SUM(X74+AD74) -> 11134.619 | AF74: =SUM(P74-AE74) -> -1974.3895
C75: 241213000052 | D75: 45609 | E75: 罗珮文 | F75: Shirley | G75: SKY JET | H75: 20.97 | I75: 2633 | J75: 32579.83 | P75: =SUBTOTAL(9,J75) -> 32579.83 | S75: =SUM(46803/68)*H75 -> 14433.219 | U75: =SUM(1800/68)*H75 -> 555.08824 | X75: =SUM(S75:W75) -> 14988.308 | Y75: =SUM(10793.87/68)*H75 -> 3328.639 | AA75: =SUM(94.98/68)*H75 -> 29.290156 | AB75: =SUM(Y75:AA75) -> 3357.9292 | AC75: 7.33 | AD75: =SUM(AB75*AC75) -> 24613.621 | AE75: =SUM(X75+AD75) -> 39601.928 | AF75: =SUM(P75-AE75) -> -7022.0984
C76: 241213000054 | D76: 45609 | E76: 罗珮文 | F76: Shirley | G76: SKY JET | H76: 3.5 | I76: 419 | J76: 5437.74 | P76: =SUBTOTAL(9,J76) -> 5437.74 | S76: =SUM(46803/68)*H76 -> 2408.9779 | U76: =SUM(1800/68)*H76 -> 92.647059 | X76: =SUM(S76:W76) -> 2501.625 | Y76: =SUM(10793.87/68)*H76 -> 555.56684 | AA76: =SUM(94.98/68)*H76 -> 4.8886765 | AB76: =SUM(Y76:AA76) -> 560.45551 | AC76: 7.33 | AD76: =SUM(AB76*AC76) -> 4108.1389 | AE76: =SUM(X76+AD76) -> 6609.7639 | AF76: =SUM(P76-AE76) -> -1172.0239
A77: JOB120365 | B77: COLL004301 | C77: 241030000050 | D77: 45615 | E77: 黄颖 | F77: ying | G77: Sunday Adelena | H77: 20.9121 | I77: 2224 | J77: 44817.94 | P77: =SUBTOTAL(9,J77) -> 44817.94 | Q77: =SUM(P77:P93) -> 168658.33 | R77: 登凯=43386.5 陆总=1800 拖车费=1670 杂费=661 过磅费=71 | S77: =SUM(47588.5/68)*H77 -> 14634.933 | U77: =SUM(2300/68)*H77 -> 707.32103 | X77: =SUM(S77:W77) -> 15342.254 | Y77: =SUM(11085/68)*H77 -> 3408.9798 | AA77: =SUM(75.12/68)*H77 -> 23.10172 | AB77: =SUM(Y77:AA77) -> 3432.0816 | AC77: 7.3 | AD77: =SUM(AB77*AC77) -> 25054.195 | AE77: =SUM(X77+AD77) -> 40396.45 | AF77: =SUM(P77-AE77) -> 4421.4903
C78: 241102000012 | D78: 45615 | E78: 黄颖 | F78: ying | G78: Bruce | H78: 2.1458 | I78: 808 | K78: 1041860 | M78: =SUM(K78/N78) -> 1674.262 | N78: 622.28015 | O78: 7.27 | P78: =SUM(N78*O78) -> 4523.9767 | S78: =SUM(47588.5/68)*H78 -> 1501.6971 | U78: =SUM(2300/68)*H78 -> 72.578529 | X78: =SUM(S78:W78) -> 1574.2756 | Y78: =SUM(11085/68)*H78 -> 349.79696 | AA78: =SUM(75.12/68)*H78 -> 2.3704779 | AB78: =SUM(Y78:AA78) -> 352.16743 | AC78: 7.3 | AD78: =SUM(AB78*AC78) -> 2570.8223 | AE78: =SUM(X78+AD78) -> 4145.0979 | AF78: =SUM(P78-AE78) -> 378.87879
C79: 241102000009 | D79: 45615 | E79: 黄颖 | F79: ying | G79: Bruce | H79: 1.3109 | I79: 450 | K79: 638809 | M79: =SUM(K79/N79) -> 1680.413 | N79: 380.15 | O79: 7.27 | P79: =SUM(N79*O79) -> 2763.6905 | S79: =SUM(47588.5/68)*H79 -> 917.4083 | U79: =SUM(2300/68)*H79 -> 44.339265 | X79: =SUM(S79:W79) -> 961.74757 | Y79: =SUM(11085/68)*H79 -> 213.69598 | AA79: =SUM(75.12/68)*H79 -> 1.4481589 | AB79: =SUM(Y79:AA79) -> 215.14414 | AC79: 7.3 | AD79: =SUM(AB79*AC79) -> 1570.5522 | AE79: =SUM(X79+AD79) -> 2532.2998 | AF79: =SUM(P79-AE79) -> 231.39073
C80: 241107000048 | D80: 45615 | E80: 黄颖 | F80: ying | G80: Nura | H80: 1.9284 | I80: 1039 | J80: 4628 | P80: =SUBTOTAL(9,J80) -> 4628 | S80: =SUM(47588.5/68)*H80 -> 1349.5539 | U80: =SUM(2300/68)*H80 -> 65.225294 | X80: =SUM(S80:W80) -> 1414.7792 | Y80: =SUM(11085/68)*H80 -> 314.35756 | AA80: =SUM(75.12/68)*H80 -> 2.1303148 | AB80: =SUM(Y80:AA80) -> 316.48787 | AC80: 7.3 | AD80: =SUM(AB80*AC80) -> 2310.3615 | AE80: =SUM(X80+AD80) -> 3725.1406 | AF80: =SUM(P80-AE80) -> 902.85935
C81: 241107000009 | D81: 45615 | E81: 黄颖 | F81: ying | G81: MISS Huang | H81: 18.3103 | I81: 10792 | J81: 43083.21 | P81: =SUBTOTAL(9,J81) -> 43083.21 | S81: =SUM(47588.5/68)*H81 -> 12814.113 | U81: =SUM(2300/68)*H81 -> 619.31897 | X81: =SUM(S81:W81) -> 13433.432 | Y81: =SUM(11085/68)*H81 -> 2984.8482 | AA81: =SUM(75.12/68)*H81 -> 20.227496 | AB81: =SUM(Y81:AA81) -> 3005.0757 | AC81: 7.3 | AD81: =SUM(AB81*AC81) -> 21937.052 | AE81: =SUM(X81+AD81) -> 35370.485 | AF81: =SUM(P81-AE81) -> 7712.7253
C82: 241116000004 | D82: 45615 | E82: 黄颖 | F82: ying | G82: wangmuma | H82: 0.9249 | I82: 172 | J82: 3030 | P82: =SUBTOTAL(9,J82) -> 3030 | S82: =SUM(47588.5/68)*H82 -> 647.27358 | U82: =SUM(2300/68)*H82 -> 31.283382 | X82: =SUM(S82:W82) -> 678.55697 | Y82: =SUM(11085/68)*H82 -> 150.7723 | AA82: =SUM(75.12/68)*H82 -> 1.0217425 | AB82: =SUM(Y82:AA82) -> 151.79404 | AC82: 7.3 | AD82: =SUM(AB82*AC82) -> 1108.0965 | AE82: =SUM(X82+AD82) -> 1786.6535 | AF82: =SUM(P82-AE82) -> 1243.3465
C83: 241111000061 | D83: 45615 | E83: 苏慧琪 | F83: KAY | G83: xiaobai小白 | H83: 0.45 | I83: 124 | J83: 1257.4 | P83: =SUM(J83) -> 1257.4 | S83: =SUM(47588.5/68)*H83 -> 314.9239 | U83: =SUM(2300/68)*H83 -> 15.220588 | X83: =SUM(S83:W83) -> 330.14449 | Y83: =SUM(11085/68)*H83 -> 73.356618 | Z83: 20.81 | AA83: =SUM(75.12/68)*H83 -> 0.49711765 | AB83: =SUM(Y83:AA83) -> 94.663735 | AC83: 7.3 | AD83: =SUM(AB83*AC83) -> 691.04527 | AE83: =SUM(X83+AD83) -> 1021.1898 | AF83: =SUM(P83-AE83) -> 236.21025
C84: 241112000045 | D84: 45615 | E84: 朱小飞 | F84: Isabel Zhu | G84: Mr Zhou | H84: 0.8383 | I84: 181 | J84: 3448 | P84: =SUBTOTAL(9,J84) -> 3448 | S84: =SUM(47588.5/68)*H84 -> 586.66823 | U84: =SUM(2300/68)*H84 -> 28.354265 | X84: =SUM(S84:W84) -> 615.02249 | Y84: =SUM(11085/68)*H84 -> 136.65523 | Z84: 95.12 | AA84: =SUM(75.12/68)*H84 -> 0.92607494 | AB84: =SUM(Y84:AA84) -> 232.7013 | AC84: 7.3 | AD84: =SUM(AB84*AC84) -> 1698.7195 | AE84: =SUM(X84+AD84) -> 2313.742 | AF84: =SUM(P84-AE84) -> 1134.258
C85: 241113000029 | D85: 45615 | E85: 朱小飞 | F85: Isabel Zhu | G85: Mr Olusola Abidemi | H85: 1.7575 | I85: 1244.5 | K85: 1064044.8 | M85: =SUM(K85/N85) -> 1680.0004 | N85: 633.35986 | O85: 7.27 | P85: =SUM(N85*O85) -> 4604.5262 | S85: =SUM(47588.5/68)*H85 -> 1229.9528 | T85: 735 | U85: =SUM(2300/68)*H85 -> 59.444853 | X85: =SUM(S85:W85) -> 2024.3976 | Y85: =SUM(11085/68)*H85 -> 286.49835 | AA85: =SUM(75.12/68)*H85 -> 1.9415206 | AB85: =SUM(Y85:AA85) -> 288.43987 | AC85: 7.3 | AD85: =SUM(AB85*AC85) -> 2105.611 | AE85: =SUM(X85+AD85) -> 4130.0087 | AF85: =SUM(P85-AE85) -> 474.51753
C86: 241113000042 | D86: 45615 | E86: 黄颖 | F86: ying | G86: Nura | H86: 0.3419 | I86: 190 | J86: 748.5 | P86: =SUBTOTAL(9,J86) -> 748.5 | S86: =SUM(47588.5/68)*H86 -> 239.27218 | U86: =SUM(2300/68)*H86 -> 11.564265 | X86: =SUM(S86:W86) -> 250.83644 | Y86: =SUM(11085/68)*H86 -> 55.734728 | AA86: =SUM(75.12/68)*H86 -> 0.37769894 | AB86: =SUM(Y86:AA86) -> 56.112427 | AC86: 7.3 | AD86: =SUM(AB86*AC86) -> 409.62072 | AE86: =SUM(X86+AD86) -> 660.45716 | AF86: =SUM(P86-AE86) -> 88.04284
C87: 241114000023 | D87: 45615 | E87: 黄颖 | F87: ying | G87: Hao wangjun | H87: 3.1076 | I87: 643 | J87: 6811 | P87: =SUBTOTAL(9,J87) -> 6811 | S87: =SUM(47588.5/68)*H87 -> 2174.7944 | U87: =SUM(2300/68)*H87 -> 105.11 | X87: =SUM(S87:W87) -> 2279.9044 | Y87: =SUM(11085/68)*H87 -> 506.5845 | AA87: =SUM(75.12/68)*H87 -> 3.432984 | AB87: =SUM(Y87:AA87) -> 510.01748 | AC87: 7.3 | AD87: =SUM(AB87*AC87) -> 3723.1276 | AE87: =SUM(X87+AD87) -> 6003.0321 | AF87: =SUM(P87-AE87) -> 807.96792
C88: 241114000046 | D88: 45615 | E88: Bella | F88: Bella Chan | G88: new hope 边鹏飞 | H88: 0.0703 | I88: 43 | K88: 47100 | M88: =SUM(K88/N88) -> 2230.1133 | N88: 21.120003 | O88: 7.28 | P88: =SUM(N88*O88) -> 153.75362 | S88: =SUM(47588.5/68)*H88 -> 49.198111 | U88: =SUM(2300/68)*H88 -> 2.3777941 | X88: =SUM(S88:W88) -> 51.575905 | Y88: =SUM(11085/68)*H88 -> 11.459934 | AA88: =SUM(75.12/68)*H88 -> 0.077660824 | AB88: =SUM(Y88:AA88) -> 11.537595 | AC88: 7.3 | AD88: =SUM(AB88*AC88) -> 84.224441 | AE88: =SUM(X88+AD88) -> 135.80035 | AF88: =SUM(P88-AE88) -> 17.953276
C89: 241115000005 | D89: 45615 | E89: 朱小飞 | F89: Isabel Zhu | G89: Halifa Success | H89: 1.0641 | I89: 52 | J89: 2244.61 | P89: =SUBTOTAL(9,J89) -> 2244.61 | S89: =SUM(47588.5/68)*H89 -> 744.69004 | U89: =SUM(2300/68)*H89 -> 35.991618 | W89: 72.29 | X89: =SUM(S89:W89) -> 852.97166 | Y89: =SUM(11085/68)*H89 -> 173.46395 | AA89: =SUM(75.12/68)*H89 -> 1.1755175 | AB89: =SUM(Y89:AA89) -> 174.63947 | AC89: 7.3 | AD89: =SUM(AB89*AC89) -> 1274.8681 | AE89: =SUM(X89+AD89) -> 2127.8398 | AF89: =SUM(P89-AE89) -> 116.77024
C90: 241116000018 | D90: 45615 | E90: Sam.Pao | F90: Sam.Pao | G90: MaiKaiNian | H90: 6.0469 | I90: 528 | J90: 13684.14 | P90: =SUBTOTAL(9,J90) -> 13684.14 | S90: =SUM(47588.5/68)*H90 -> 4231.8074 | U90: =SUM(2300/68)*H90 -> 204.5275 | X90: =SUM(S90:W90) -> 4436.3349 | Y90: =SUM(11085/68)*H90 -> 985.73362 | AA90: =SUM(75.12/68)*H90 -> 6.680046 | AB90: =SUM(Y90:AA90) -> 992.41367 | AC90: 7.3 | AD90: =SUM(AB90*AC90) -> 7244.6198 | AE90: =SUM(X90+AD90) -> 11680.955 | AF90: =SUM(P90-AE90) -> 2003.1853
C91: 241118000073 | D91: 45615 | E91: 陆总 | F91: 陆梓龙 | G91: xiantian | H91: 10.1365 | I91: 5464 | J91: 21201.16 | P91: =SUBTOTAL(9,J91) -> 21201.16 | S91: =SUM(47588.5/68)*H91 -> 7093.8357 | U91: =SUM(2300/68)*H91 -> 342.85221 | X91: =SUM(S91:W91) -> 7436.6879 | Y91: =SUM(11085/68)*H91 -> 1652.3986 | AA91: =SUM(75.12/68)*H91 -> 11.197851 | AB91: =SUM(Y91:AA91) -> 1663.5964 | AC91: 7.3 | AD91: =SUM(AB91*AC91) -> 12144.254 | AE91: =SUM(X91+AD91) -> 19580.942 | AF91: =SUM(P91-AE91) -> 1620.2182
C92: 241209000062 | D92: 45615 | E92: 陆总 | F92: 陆梓龙 | G92: xinlong | H92: 4.9817 | I92: 4862 | J92: 11334.38 | P92: =SUBTOTAL(9,J92) -> 11334.38 | S92: =SUM(47588.5/68)*H92 -> 3486.3475 | U92: =SUM(2300/68)*H92 -> 168.49868 | X92: =SUM(S92:W92) -> 3654.8462 | Y92: =SUM(11085/68)*H92 -> 812.09036 | Z92: 77.38 | AA92: =SUM(75.12/68)*H92 -> 5.5033133 | AB92: =SUM(Y92:AA92) -> 894.97367 | AC92: 7.3 | AD92: =SUM(AB92*AC92) -> 6533.3078 | AE92: =SUM(X92+AD92) -> 10188.154 | AF92: =SUM(P92-AE92) -> 1146.226
C93: 241218000023 | D93: 45615 | E93: 吕沛霖 | F93: 喵喵速运-Layne | G93: Isa | H93: 0.0592 | I93: 10 | K93: 70231 | M93: =SUM(K93/N93) -> 1580 | N93: 44.45 | O93: 7.29 | P93: =SUM(N93*O93) -> 324.0405 | S93: =SUM(47588.5/68)*H93 -> 41.429988 | U93: =SUM(2300/68)*H93 -> 2.0023529 | X93: =SUM(S93:W93) -> 43.432341 | Y93: =SUM(11085/68)*H93 -> 9.6504706 | AA93: =SUM(75.12/68)*H93 -> 0.065398588 | AB93: =SUM(Y93:AA93) -> 9.7158692 | AC93: 7.3 | AD93: =SUM(AB93*AC93) -> 70.925845 | AE93: =SUM(X93+AD93) -> 114.35819 | AF93: =SUM(P93-AE93) -> 209.68231
A94: JOB120366 | B94: COLL004305 | C94: 241102000009 | D94: 45616 | E94: 黄颖 | F94: ying | G94: Bruce | H94: 0.3399 | I94: 118 | K94: 165636 | M94: =SUM(K94/N94) -> 1680.2191 | N94: 98.58 | O94: 7.27 | P94: =SUM(N94*O94) -> 716.6766 | Q94: =SUM(P94:P107) -> 147610.5 | R94: 登凯=43386.5 赛捷=500 拖车费=1670 杂费=61 过磅费=68 | S94: =SUM(45685.5/68)*H94 -> 228.36032 | U94: =SUM(2000/68)*H94 -> 9.9970588 | X94: =SUM(S94:W94) -> 238.35737 | Y94: =SUM(11085/68)*H94 -> 55.408699 | AA94: =SUM(77.38/68)*H94 -> 0.38678621 | AB94: =SUM(Y94:AA94) -> 55.795485 | AC94: 7.3 | AD94: =SUM(AB94*AC94) -> 407.30704 | AE94: =SUM(X94+AD94) -> 645.66441 | AF94: =SUM(P94-AE94) -> 71.012187
C95: 241107000009 | D95: 45616 | E95: 黄颖 | F95: ying | G95: MISS Huang | H95: 6.8102 | I95: 4442 | J95: 16020.41 | P95: =SUBTOTAL(9,J95) -> 16020.41 | S95: =SUM(45685.5/68)*H95 -> 4575.4028 | U95: =SUM(2000/68)*H95 -> 200.3 | X95: =SUM(S95:W95) -> 4775.7028 | Y95: =SUM(11085/68)*H95 -> 1110.1627 | AA95: =SUM(77.38/68)*H95 -> 7.749607 | AB95: =SUM(Y95:AA95) -> 1117.9124 | AC95: 7.3 | AD95: =SUM(AB95*AC95) -> 8160.7602 | AE95: =SUM(X95+AD95) -> 12936.463 | AF95: =SUM(P95-AE95) -> 3083.947
C96: 241106000050 | D96: 45616 | E96: 黄颖 | F96: ying | G96: Sunday Adelena | H96: 0.6913 | I96: 774 | J96: 3860.58 | P96: =SUBTOTAL(9,J96) -> 3860.58 | S96: =SUM(45685.5/68)*H96 -> 464.44686 | U96: =SUM(2000/68)*H96 -> 20.332353 | V96: 150 | X96: =SUM(S96:W96) -> 634.77921 | Y96: =SUM(11085/68)*H96 -> 112.69207 | AA96: =SUM(77.38/68)*H96 -> 0.78665874 | AB96: =SUM(Y96:AA96) -> 113.47872 | AC96: 7.3 | AD96: =SUM(AB96*AC96) -> 828.39469 | AE96: =SUM(X96+AD96) -> 1463.1739 | AF96: =SUM(P96-AE96) -> 2397.4061
C97: 241106000051 | D97: 45616 | E97: 黄颖 | F97: ying | G97: Sunday Adelena | H97: 0.4698 | I97: 547 | J97: 1670.3 | P97: =SUBTOTAL(9,J97) -> 1670.3 | S97: =SUM(45685.5/68)*H97 -> 315.63306 | U97: =SUM(2000/68)*H97 -> 13.817647 | X97: =SUM(S97:W97) -> 329.4507 | Y97: =SUM(11085/68)*H97 -> 76.584309 | AA97: =SUM(77.38/68)*H97 -> 0.53460476 | AB97: =SUM(Y97:AA97) -> 77.118914 | AC97: 7.3 | AD97: =SUM(AB97*AC97) -> 562.96807 | AE97: =SUM(X97+AD97) -> 892.41877 | AF97: =SUM(P97-AE97) -> 777.88123
C98: 241113000044 | D98: 45616 | E98: 罗珮文 | F98: Shirley | G98: Yusky | H98: 2.0156 | I98: 301 | K98: 829711.92 | M98: =SUM(K98/N98) -> 1608 | N98: 515.99 | O98: 7.3 | P98: =SUM(N98*O98) -> 3766.727 | S98: =SUM(45685.5/68)*H98 -> 1354.172 | U98: =SUM(2000/68)*H98 -> 59.282353 | X98: =SUM(S98:W98) -> 1413.4543 | Y98: =SUM(11085/68)*H98 -> 328.57244 | AA98: =SUM(77.38/68)*H98 -> 2.2936342 | AB98: =SUM(Y98:AA98) -> 330.86608 | AC98: 7.3 | AD98: =SUM(AB98*AC98) -> 2415.3224 | AE98: =SUM(X98+AD98) -> 3828.7767 | AF98: =SUM(P98-AE98) -> -62.049671
C99: 241114000013 | D99: 45616 | E99: 罗珮文 | F99: Shirley | G99: Yusky | H99: 0.0902 | I99: 76 | K99: 37176.96 | M99: =SUM(K99/N99) -> 1608 | N99: 23.12 | O99: 7.3 | P99: =SUM(N99*O99) -> 168.776 | S99: =SUM(45685.5/68)*H99 -> 60.600472 | U99: =SUM(2000/68)*H99 -> 2.6529412 | X99: =SUM(S99:W99) -> 63.253413 | Y99: =SUM(11085/68)*H99 -> 14.703926 | AA99: =SUM(77.38/68)*H99 -> 0.10264229 | AB99: =SUM(Y99:AA99) -> 14.806569 | AC99: 7.3 | AD99: =SUM(AB99*AC99) -> 108.08795 | AE99: =SUM(X99+AD99) -> 171.34137 | AF99: =SUM(P99-AE99) -> -2.5653652
C100: 241114000027 | D100: 45616 | E100: 吕沛霖 | F100: 喵喵速运-Layne | G100: Abdulsheldu | H100: 7.3094 | I100: 4250 | K100: 3823031.5 | M100: =SUM(K100/N100) -> 1663.2 | N100: 2298.6 | O100: 7.3 | P100: =SUM(N100*O100) -> 16779.78 | S100: =SUM(45685.5/68)*H100 -> 4910.7881 | U100: =SUM(2000/68)*H100 -> 214.98235 | X100: =SUM(S100:W100) -> 5125.7705 | Y100: =SUM(11085/68)*H100 -> 1191.5397 | Z100: 97.22 | AA100: =SUM(77.38/68)*H100 -> 8.3176672 | AB100: =SUM(Y100:AA100) -> 1297.0774 | AC100: 7.3 | AD100: =SUM(AB100*AC100) -> 9468.6647 | AE100: =SUM(X100+AD100) -> 14594.435 | AF100: =SUM(P100-AE100) -> 2185.3448
...

Sheet JOB120361
A1: 2024年11月份LOS毛利表（海运）
A2: PSL表 | B2: 体积cbm | C2: 74.1647
A3: JOB | B3: 集装编号 | C3: 运单编号 | D3: 日期 | E3: 业务 | F3: 发货人 | G3: 收货人 | H3: 计费体积 | I3: 计费重量 | J3: 应 收 | Q3: 总应收 | R3: 起 运 港 成 本 | W3: 代垫运费 | X3: 起运港成本 合计 | Y3: 目的港成本 | AE3: 总支出 | AF3: 利润
J4: 应收RMB | K4: LOS Income(NGN)收到(奈拉) | L4: LOS 收到USD | M4: 美元汇率 dollar currency rate | N4: 应收 到付款USD | O4: 汇率 | P4: 人民币 | R4: 代理商 | S4: 运费+出口报关费 | T4: 提货费 | U4: 装卸费 | V4: 包装费 | Y4: 进口报关费 | Z4: 到门配送费 | AA4: 转运费 | AB4: 目的港支出 | AC4: 汇率 | AD4: 人民币 | AE4: 起运港+目的港
A5: JOB120361 | B5: COLL004287 | C5: 240910000015 | D5: 45601 | E5: 吕沛霖 | F5: 喵喵速运-Layne | G5: Hu Hai Liang | H5: 5.1959 | I5: 743 | K5: 2382640 | M5: =SUM(K5/N5) -> 1580 | N5: 1508 | O5: 7.29 | P5: =SUM(N5*O5) -> 10993.32 | Q5: =SUM(P5:P21) -> 165324.28 | R5: 登凯=46189.5 陆总=1200 拖车费=1670 杂费=89 过磅费=66 | S5: =SUM(49214.5/68)*H5 -> 3760.4944 | T5: =SUM(113.64/68)*H5 -> 8.6832658 | U5: =SUM(2400/68)*H5 -> 183.38471 | X5: =SUM(S5:W5) -> 3952.5624 | Y5: =SUM(10949.72/68)*H5 -> 836.67133 | AB5: =SUM(Y5:AA5) -> 836.67133 | AC5: 7.33 | AD5: =SUM(AB5*AC5) -> 6132.8008 | AE5: =SUM(X5+AD5) -> 10085.363 | AF5: =SUM(P5-AE5) -> 907.95679
C6: 241023000029 | D6: 45601 | E6: 黄颖 | F6: ying | G6: Wole Rasak | H6: 0.0288 | I6: 5 | J6: 224.75 | P6: =SUBTOTAL(9,J6) -> 224.75 | S6: =SUM(49214.5/68)*H6 -> 20.843788 | T6: =SUM(113.64/68)*H6 -> 0.048129882 | U6: =SUM(2400/68)*H6 -> 1.0164706 | X6: =SUM(S6:W6) -> 21.908389 | Y6: =SUM(10949.72/68)*H6 -> 4.6375285 | AB6: =SUM(Y6:AA6) -> 4.6375285 | AC6: 7.33 | AD6: =SUM(AB6*AC6) -> 33.993084 | AE6: =SUM(X6+AD6) -> 55.901472 | AF6: =SUM(P6-AE6) -> 168.84853
C7: 241025000058 | D7: 45601 | E7: 苏慧琪 | F7: KAY | G7: BOYOU 吕 | H7: 13.7 | I7: 2550 | K7: 7067746.5 | M7: =SUM(K7/N7) -> 1648.8039 | N7: 4286.59 | O7: 7.29 | P7: =SUM(N7*O7) -> 31249.241 | S7: =SUM(49214.5/68)*H7 -> 9915.2743 | T7: =SUM(113.64/68)*H7 -> 22.895118 | U7: =SUM(2400/68)*H7 -> 483.52941 | X7: =SUM(S7:W7) -> 10421.699 | Y7: =SUM(10949.72/68)*H7 -> 2206.0465 | Z7: 90.97 | AB7: =SUM(Y7:AA7) -> 2297.0165 | AC7: 7.33 | AD7: =SUM(AB7*AC7) -> 16837.131 | AE7: =SUM(X7+AD7) -> 27258.83 | AF7: =SUM(P7-AE7) -> 3990.4111
C8: 241026000006 | D8: 45601 | E8: 吕沛霖 | F8: 喵喵速运-Layne | G8: LEO WEI | H8: 0.6549 | I8: 72 | K8: 363730 | M8: =SUM(K8/N8) -> 1683.0002 | N8: 216.12 | O8: 7.3 | P8: =SUM(N8*O8) -> 1577.676 | S8: =SUM(49214.5/68)*H8 -> 473.97906 | T8: =SUM(113.64/68)*H8 -> 1.0944535 | U8: =SUM(2400/68)*H8 -> 23.114118 | X8: =SUM(S8:W8) -> 498.18763 | Y8: =SUM(10949.72/68)*H8 -> 105.45547 | AB8: =SUM(Y8:AA8) -> 105.45547 | AC8: 7.33 | AD8: =SUM(AB8*AC8) -> 772.98856 | AE8: =SUM(X8+AD8) -> 1271.1762 | AF8: =SUM(P8-AE8) -> 306.49981
C9: 241027000011 | D9: 45601 | E9: 朱小飞 | F9: Isabel Zhu | G9: Maryam Tukur | H9: 0.5618 | I9: 55 | K9: 434000 | M9: =SUM(K9/N9) -> 1671.8028 | N9: 259.6 | O9: 7.3 | P9: =SUM(N9*O9) -> 1895.08 | S9: =SUM(49214.5/68)*H9 -> 406.59862 | T9: =SUM(113.64/68)*H9 -> 0.93886694 | U9: =SUM(2400/68)*H9 -> 19.828235 | V9: 310 | W9: 59 | X9: =SUM(S9:W9) -> 796.36572 | Y9: =SUM(10949.72/68)*H9 -> 90.46401 | AB9: =SUM(Y9:AA9) -> 90.46401 | AC9: 7.33 | AD9: =SUM(AB9*AC9) -> 663.1012 | AE9: =SUM(X9+AD9) -> 1459.4669 | AF9: =SUM(P9-AE9) -> 435.61308
C10: 241031000033 | D10: 45601 | E10: 黄颖 | F10: ying | G10: Bruce | H10: 1.9968 | I10: 845 | K10: 960734 | M10: =SUM(K10/N10) -> 1653.0179 | N10: 581.2 | O10: 7.29 | P10: =SUM(N10*O10) -> 4236.948 | S10: =SUM(49214.5/68)*H10 -> 1445.1693 | T10: =SUM(113.64/68)*H10 -> 3.3370052 | U10: =SUM(2400/68)*H10 -> 70.475294 | X10: =SUM(S10:W10) -> 1518.9816 | Y10: =SUM(10949.72/68)*H10 -> 321.53531 | AB10: =SUM(Y10:AA10) -> 321.53531 | AC10: 7.33 | AD10: =SUM(AB10*AC10) -> 2356.8538 | AE10: =SUM(X10+AD10) -> 3875.8354 | AF10: =SUM(P10-AE10) -> 361.11258
C11: 241028000022 | D11: 45601 | E11: 黄颖 | F11: ying | G11: Barrister Hammed | H11: 1.211 | I11: 331 | J11: 2690 | P11: =SUBTOTAL(9,J11) -> 2690 | S11: =SUM(49214.5/68)*H11 -> 876.45235 | T11: =SUM(113.64/68)*H11 -> 2.0237947 | U11: =SUM(2400/68)*H11 -> 42.741176 | X11: =SUM(S11:W11) -> 921.21732 | Y11: =SUM(10949.72/68)*H11 -> 195.00163 | AB11: =SUM(Y11:AA11) -> 195.00163 | AC11: 7.33 | AD11: =SUM(AB11*AC11) -> 1429.362 | AE11: =SUM(X11+AD11) -> 2350.5793 | AF11: =SUM(P11-AE11) -> 339.42073
C12: 241028000025 | D12: 45601 | E12: 吕沛霖 | F12: 喵喵速运-Layne | G12: Candice Ding | H12: 0.7015 | I12: 168 | K12: 432424.8 | M12: =SUM(K12/N12) -> 1710 | N12: 252.88 | O12: 7.3 | P12: =SUM(N12*O12) -> 1846.024 | S12: =SUM(49214.5/68)*H12 -> 507.70547 | T12: =SUM(113.64/68)*H12 -> 1.1723303 | U12: =SUM(2400/68)*H12 -> 24.758824 | X12: =SUM(S12:W12) -> 533.63662 | Y12: =SUM(10949.72/68)*H12 -> 112.95924 | Z12: 42.43 | AB12: =SUM(Y12:AA12) -> 155.38924 | AC12: 7.33 | AD12: =SUM(AB12*AC12) -> 1139.0032 | AE12: =SUM(X12+AD12) -> 1672.6398 | AF12: =SUM(P12-AE12) -> 173.38422
C13: 241028000036 | D13: 45601 | E13: Sam.Pao | F13: Sam.Pao | G13: Chizoba | H13: 19.1974 | I13: 2413 | J13: 38000 | P13: =SUBTOTAL(9,J13) -> 38000 | S13: =SUM(49214.5/68)*H13 -> 13893.977 | T13: =SUM(113.64/68)*H13 -> 32.082243 | U13: =SUM(2400/68)*H13 -> 677.55529 | X13: =SUM(S13:W13) -> 14603.615 | Y13: =SUM(10949.72/68)*H13 -> 3091.267 | AB13: =SUM(Y13:AA13) -> 3091.267 | AC13: 7.33 | AD13: =SUM(AB13*AC13) -> 22658.987 | AE13: =SUM(X13+AD13) -> 37262.602 | AF13: =SUM(P13-AE13) -> 737.3984
C14: 241028000057 | D14: 45601 | E14: 朱小飞 | F14: Isabel Zhu | G14: Halifa Success | H14: 0.8721 | I14: 153 | J14: 1785.59 | P14: =SUBTOTAL(9,J14) -> 1785.59 | S14: =SUM(49214.5/68)*H14 -> 631.17596 | T14: =SUM(113.64/68)*H14 -> 1.457433 | U14: =SUM(2400/68)*H14 -> 30.78 | X14: =SUM(S14:W14) -> 663.4134 | Y14: =SUM(10949.72/68)*H14 -> 140.43016 | AB14: =SUM(Y14:AA14) -> 140.43016 | AC14: 7.33 | AD14: =SUM(AB14*AC14) -> 1029.3531 | AE14: =SUM(X14+AD14) -> 1692.7665 | AF14: =SUM(P14-AE14) -> 92.823539
C15: 241029000017 | D15: 45601 | E15: 黄颖 | F15: ying | G15: jiangnan | H15: 0.2948 | I15: 65 | J15: 683.5 | P15: =SUBTOTAL(9,J15) -> 683.5 | S15: =SUM(49214.5/68)*H15 -> 213.35933 | T15: =SUM(113.64/68)*H15 -> 0.49266282 | U15: =SUM(2400/68)*H15 -> 10.404706 | X15: =SUM(S15:W15) -> 224.2567 | Y15: =SUM(10949.72/68)*H15 -> 47.470257 | AB15: =SUM(Y15:AA15) -> 47.470257 | AC15: 7.33 | AD15: =SUM(AB15*AC15) -> 347.95698 | AE15: =SUM(X15+AD15) -> 572.21368 | AF15: =SUM(P15-AE15) -> 111.28632
C16: 241030000002 | D16: 45601 | E16: 吕沛霖 | F16: 喵喵速运-Layne | G16: Mu Shi Shi | H16: 7.4945 | I16: 520 | J16: 18324.8 | P16: =SUBTOTAL(9,J16) -> 18324.8 | S16: =SUM(49214.5/68)*H16 -> 5424.0893 | T16: =SUM(113.64/68)*H16 -> 12.524632 | U16: =SUM(2400/68)*H16 -> 264.51176 | X16: =SUM(S16:W16) -> 5701.1257 | Y16: =SUM(10949.72/68)*H16 -> 1206.8041 | Z16: 47.85 | AB16: =SUM(Y16:AA16) -> 1254.6541 | AC16: 7.33 | AD16: =SUM(AB16*AC16) -> 9196.6143 | AE16: =SUM(X16+AD16) -> 14897.74 | AF16: =SUM(P16-AE16) -> 3427.06
C17: 241030000039 | D17: 45601 | E17: 黄颖 | F17: ying | G17: jiangnan | H17: 1.069 | I17: 138 | J17: 2506 | P17: =SUBTOTAL(9,J17) -> 2506 | S17: =SUM(49214.5/68)*H17 -> 773.68089 | T17: =SUM(113.64/68)*H17 -> 1.7864876 | U17: =SUM(2400/68)*H17 -> 37.729412 | X17: =SUM(S17:W17) -> 813.19679 | Y17: =SUM(10949.72/68)*H17 -> 172.13604 | AB17: =SUM(Y17:AA17) -> 172.13604 | AC17: 7.33 | AD17: =SUM(AB17*AC17) -> 1261.7572 | AE17: =SUM(X17+AD17) -> 2074.954 | AF17: =SUM(P17-AE17) -> 431.04604
C18: 241030000041 | D18: 45601 | E18: 吕沛霖 | F18: 喵喵速运-Layne | G18: WEI PING | H18: 1.5338 | I18: 336 | K18: 755361 | M18: =SUM(K18/N18) -> 1700 | N18: 444.33 | O18: 7.27 | P18: =SUM(N18*O18) -> 3230.2791 | S18: =SUM(49214.5/68)*H18 -> 1110.0765 | T18: =SUM(113.64/68)*H18 -> 2.5632505 | U18: =SUM(2400/68)*H18 -> 54.134118 | X18: =SUM(S18:W18) -> 1166.7738 | Y18: =SUM(10949.72/68)*H18 -> 246.9806 | Z18: 29.9 | AB18: =SUM(Y18:AA18) -> 276.8806 | AC18: 7.33 | AD18: =SUM(AB18*AC18) -> 2029.5348 | AE18: =SUM(X18+AD18) -> 3196.3086 | AF18: =SUM(P18-AE18) -> 33.97049
C19: 241101000029 | D19: 45601 | E19: 吕沛霖 | F19: 喵喵速运-Layne | G19: YA | H19: 0.8656 | I19: 346 | J19: 2978.64 | P19: =SUM(J19) -> 2978.64 | S19: =SUM(49214.5/68)*H19 -> 626.47164 | T19: =SUM(113.64/68)*H19 -> 1.4465704 | U19: =SUM(2400/68)*H19 -> 30.550588 | X19: =SUM(S19:W19) -> 658.46879 | Y19: =SUM(10949.72/68)*H19 -> 139.38349 | Z19: 12.36 | AA19: 83.19 | AB19: =SUM(Y19:AA19) -> 234.93349 | AC19: 7.33 | AD19: =SUM(AB19*AC19) -> 1722.0625 | AE19: =SUM(X19+AD19) -> 2380.5313 | AF19: =SUM(P19-AE19) -> 598.10869
C20: 241101000033 | D20: 45601 | E20: 朱小飞 | F20: Isabel Zhu | G20: Halifa Success | H20: 0.8844 | I20: 155 | J20: 1806.11 | P20: =SUBTOTAL(9,J20) -> 1806.11 | S20: =SUM(49214.5/68)*H20 -> 640.078 | T20: =SUM(113.64/68)*H20 -> 1.4779885 | U20: =SUM(2400/68)*H20 -> 31.214118 | X20: =SUM(S20:W20) -> 672.7701 | Y20: =SUM(10949.72/68)*H20 -> 142.41077 | AB20: =SUM(Y20:AA20) -> 142.41077 | AC20: 7.33 | AD20: =SUM(AB20*AC20) -> 1043.8709 | AE20: =SUM(X20+AD20) -> 1716.641 | AF20: =SUM(P20-AE20) -> 89.468952
C21: 241209000060 | D21: 45601 | E21: 陆总 | F21: 陆梓龙 | G21: xinlong | H21: 17.902 | I21: 17472 | J21: 41296.32 | P21: =SUBTOTAL(9,J21) -> 41296.32 | S21: =SUM(49214.5/68)*H21 -> 12956.441 | T21: =SUM(113.64/68)*H21 -> 29.917401 | U21: =SUM(2400/68)*H21 -> 631.83529 | X21: =SUM(S21:W21) -> 13618.194 | Y21: =SUM(10949.72/68)*H21 -> 2882.6748 | AB21: =SUM(Y21:AA21) -> 2882.6748 | AC21: 7.33 | AD21: =SUM(AB21*AC21) -> 21130.006 | AE21: =SUM(X21+AD21) -> 34748.2 | AF21: =SUM(P21-AE21) -> 6548.12
A22: 合计 | J22: =SUM(J4:J4) -> 0 | N22: =SUM(N4:N4) -> 0 | P22: =SUM(P4:P4) -> 0 | Q22: =SUM(Q4:Q4) -> 0 | X22: =SUM(X4:X4) -> 0 | AD22: =SUM(AD4:AD4) -> 0 | AF22: =SUM(AF4:AF21) -> 18752.529

Sheet JOB120362
A1: 2024年11月份LOS毛利表（海运）
A2: PSL表 | B2: 体积cbm | C2: 68.6834
A3: JOB | B3: 集装编号 | C3: 运单编号 | D3: 日期 | E3: 业务 | F3: 发货人 | G3: 收货人 | H3: 计费体积 | I3: 计费重量 | J3: 应 收 | Q3: 总应收 | R3: 起 运 港 成 本 | W3: 代垫运费 | X3: 起运港成本 合计 | Y3: 目的港成本 | AE3: 总支出 | AF3: 利润
J4: 应收RMB | K4: LOS Income(NGN)收到(奈拉) | L4: LOS 收到USD | M4: 美元汇率 dollar currency rate | N4: 应收 到付款USD | O4: 汇率 | P4: 人民币 | R4: 代理商 | S4: 运费+出口报关费 | T4: 提货费 | U4: 装卸费 | V4: 包装费 | Y4: 进口报关费 | Z4: 到门配送费 | AA4: 转运费 | AB4: 目的港支出 | AC4: 汇率 | AD4: 人民币 | AE4: 起运港+目的港
A5: JOB120362 | B5: COLL004290 | C5: 241028000047 | D5: 45602 | E5: Sam.Pao | F5: Sam.Pao | G5: Nick Wang | H5: 3.0981 | I5: 231 | J5: 8037.16 | P5: =SUBTOTAL(9,J5) -> 8037.16 | Q5: =SUM(P5:P18) -> 134933.06 | R5: 登凯=46189.5 陆总=800 拖车费=1670 杂费=61 过磅费=68 | S5: =SUM(48788.5/68)*H5 -> 2222.8184 | U5: =SUM(1800/68)*H5 -> 82.008529 | X5: =SUM(S5:W5) -> 2304.8269 | Y5: =SUM(10716.46/68)*H5 -> 488.24507 | AA5: =SUM(50.64/68)*H5 -> 2.3071733 | AB5: =SUM(Y5:AA5) -> 490.55224 | AC5: 7.33 | AD5: =SUM(AB5*AC5) -> 3595.7479 | AE5: =SUM(X5+AD5) -> 5900.5749 | AF5: =SUM(P5-AE5) -> 2136.5851
C6: 241029000048 | D6: 45602 | E6: 黄颖 | F6: ying | G6: Sunday Adelena | H6: 0.4438 | I6: 310 | J6: 964.05 | P6: =SUBTOTAL(9,J6) -> 964.05 | S6: =SUM(48788.5/68)*H6 -> 318.41671 | U6: =SUM(1800/68)*H6 -> 11.747647 | X6: =SUM(S6:W6) -> 330.16436 | Y6: =SUM(10716.46/68)*H6 -> 69.940661 | AA6: =SUM(50.64/68)*H6 -> 0.33050047 | AB6: =SUM(Y6:AA6) -> 70.271161 | AC6: 7.33 | AD6: =SUM(AB6*AC6) -> 515.08761 | AE6: =SUM(X6+AD6) -> 845.25197 | AF6: =SUM(P6-AE6) -> 118.79803
C7: 241030000021 | D7: 45602 | E7: 吕沛霖 | F7: 喵喵速运-Layne | G7: MA ZONG | H7: 0.6626 | I7: 405 | J7: 1624.5 | P7: =SUBTOTAL(9,J7) -> 1624.5 | S7: =SUM(48788.5/68)*H7 -> 475.40088 | U7: =SUM(1800/68)*H7 -> 17.539412 | X7: =SUM(S7:W7) -> 492.9403 | Y7: =SUM(10716.46/68)*H7 -> 104.42245 | Z7: 35.38 | AA7: =SUM(50.64/68)*H7 -> 0.49344212 | AB7: =SUM(Y7:AA7) -> 140.29589 | AC7: 7.33 | AD7: =SUM(AB7*AC7) -> 1028.3689 | AE7: =SUM(X7+AD7) -> 1521.3092 | AF7: =SUM(P7-AE7) -> 103.19084
C8: 241030000025 | D8: 45602 | E8: 黄颖 | F8: ying | G8: Nura | H8: 0.4092 | I8: 180 | J8: 876.05 | P8: =SUBTOTAL(9,J8) -> 876.05 | S8: =SUM(48788.5/68)*H8 -> 293.59197 | U8: =SUM(1800/68)*H8 -> 10.831765 | X8: =SUM(S8:W8) -> 304.42374 | Y8: =SUM(10716.46/68)*H8 -> 64.487874 | AA8: =SUM(50.64/68)*H8 -> 0.30473365 | AB8: =SUM(Y8:AA8) -> 64.792608 | AC8: 7.33 | AD8: =SUM(AB8*AC8) -> 474.92981 | AE8: =SUM(X8+AD8) -> 779.35355 | AF8: =SUM(P8-AE8) -> 96.696448
C9: 241031000033 | D9: 45602 | E9: 黄颖 | F9: ying | G9: Bruce | H9: 0.5837 | I9: 247 | K9: 280840 | M9: =SUM(K9/N9) -> 1652.9723 | N9: 169.9 | O9: 7.29 | P9: =SUM(N9*O9) -> 1238.571 | S9: =SUM(48788.5/68)*H9 -> 418.79187 | U9: =SUM(1800/68)*H9 -> 15.450882 | X9: =SUM(S9:W9) -> 434.24276 | Y9: =SUM(10716.46/68)*H9 -> 91.988202 | AA9: =SUM(50.64/68)*H9 -> 0.43468482 | AB9: =SUM(Y9:AA9) -> 92.422886 | AC9: 7.33 | AD9: =SUM(AB9*AC9) -> 677.45976 | AE9: =SUM(X9+AD9) -> 1111.7025 | AF9: =SUM(P9-AE9) -> 126.86849
C10: 241101000057 | D10: 45602 | E10: 陆总 | F10: 陆梓龙 | G10: jizong | H10: 1.1063 | I10: 567 | J10: 2422.8 | P10: =SUBTOTAL(9,J10) -> 2422.8 | S10: =SUM(48788.5/68)*H10 -> 793.74585 | U10: =SUM(1800/68)*H10 -> 29.284412 | X10: =SUM(S10:W10) -> 823.03026 | Y10: =SUM(10716.46/68)*H10 -> 174.34735 | AA10: =SUM(50.64/68)*H10 -> 0.82386812 | AB10: =SUM(Y10:AA10) -> 175.17122 | AC10: 7.33 | AD10: =SUM(AB10*AC10) -> 1284.005 | AE10: =SUM(X10+AD10) -> 2107.0353 | AF10: =SUM(P10-AE10) -> 315.76472
C11: 241104000038 | D11: 45602 | E11: 黄颖 | F11: ying | G11: Sunday Adelena | H11: 0.0737 | I11: 26 | J11: 214.23 | P11: =SUBTOTAL(9,J11) -> 214.23 | S11: =SUM(48788.5/68)*H11 -> 52.878124 | U11: =SUM(1800/68)*H11 -> 1.9508824 | X11: =SUM(S11:W11) -> 54.829007 | Y11: =SUM(10716.46/68)*H11 -> 11.614752 | AA11: =SUM(50.64/68)*H11 -> 0.054884824 | AB11: =SUM(Y11:AA11) -> 11.669636 | AC11: 7.33 | AD11: =SUM(AB11*AC11) -> 85.538434 | AE11: =SUM(X11+AD11) -> 140.36744 | AF11: =SUM(P11-AE11) -> 73.862559
C12: 241022000035 | D12: 45602 | E12: Bella | F12: Bella Chan | G12: zhong zi xin | H12: 27.424 | I12: 19896 | J12: 60720 | P12: =SUBTOTAL(9,J12) -> 60720 | S12: =SUM(48788.5/68)*H12 -> 19676.115 | U12: =SUM(1800/68)*H12 -> 725.92941 | X12: =SUM(S12:W12) -> 20402.044 | Y12: =SUM(10716.46/68)*H12 -> 4321.8853 | AA12: =SUM(50.64/68)*H12 -> 20.422814 | AB12: =SUM(Y12:AA12) -> 4342.3081 | AC12: 7.33 | AD12: =SUM(AB12*AC12) -> 31829.118 | AE12: =SUM(X12+AD12) -> 52231.163 | AF12: =SUM(P12-AE12) -> 8488.8372
C13: 241105000034 | D13: 45602 | E13: 朱小飞 | F13: Isabel Zhu | G13: Joy | H13: 0.7455 | I13: 854 | K13: 641427.2 | M13: =SUM(K13/N13) -> 1643 | N13: 390.4 | O13: 7.3 | P13: =SUM(N13*O13) -> 2849.92 | S13: =SUM(48788.5/68)*H13 -> 534.87981 | U13: =SUM(1800/68)*H13 -> 19.733824 | X13: =SUM(S13:W13) -> 554.61363 | Y13: =SUM(10716.46/68)*H13 -> 117.48707 | Z13: 29.21 | AA13: =SUM(50.64/68)*H13 -> 0.55517824 | AB13: =SUM(Y13:AA13) -> 147.25225 | AC13: 7.33 | AD13: =SUM(AB13*AC13) -> 1079.359 | AE13: =SUM(X13+AD13) -> 1633.9726 | AF13: =SUM(P13-AE13) -> 1215.9474
C14: 241106000001 | D14: 45602 | E14: Sam.Pao | F14: Sam.Pao | G14: MaiKaiNian | H14: 0.4542 | I14: 69 | J14: 1060.98 | P14: =SUBTOTAL(9,J14) -> 1060.98 | S14: =SUM(48788.5/68)*H14 -> 325.87848 | U14: =SUM(1800/68)*H14 -> 12.022941 | X14: =SUM(S14:W14) -> 337.90142 | Y14: =SUM(10716.46/68)*H14 -> 71.579649 | AA14: =SUM(50.64/68)*H14 -> 0.33824541 | AB14: =SUM(Y14:AA14) -> 71.917894 | AC14: 7.33 | AD14: =SUM(AB14*AC14) -> 527.15817 | AE14: =SUM(X14+AD14) -> 865.05959 | AF14: =SUM(P14-AE14) -> 195.92041
C15: 241106000002 | D15: 45602 | E15: Sam.Pao | F15: Sam.Pao | G15: Angel | H15: 0.3458 | I15: 98 | J15: 757 | P15: =SUBTOTAL(9,J15) -> 757 | S15: =SUM(48788.5/68)*H15 -> 248.10387 | U15: =SUM(1800/68)*H15 -> 9.1535294 | X15: =SUM(S15:W15) -> 257.2574 | Y15: =SUM(10716.46/68)*H15 -> 54.496351 | AA15: =SUM(50.64/68)*H15 -> 0.25751929 | AB15: =SUM(Y15:AA15) -> 54.75387 | AC15: 7.33 | AD15: =SUM(AB15*AC15) -> 401.34587 | AE15: =SUM(X15+AD15) -> 658.60327 | AF15: =SUM(P15-AE15) -> 98.396729
C16: 241106000018 | D16: 45602 | E16: Bella | F16: Bella Chan | G16: zhang long ting | H16: 0.0019 | I16: 1 | K16: 51150 | M16: =SUM(K16/N16) -> 1650 | N16: 31 | O16: 7.2 | P16: =SUM(N16*O16) -> 223.2 | S16: =SUM(48788.5/68)*H16 -> 1.3632081 | U16: =SUM(1800/68)*H16 -> 0.050294118 | X16: =SUM(S16:W16) -> 1.4135022 | Y16: =SUM(10716.46/68)*H16 -> 0.2994305 | AA16: =SUM(50.64/68)*H16 -> 0.0014149412 | AB16: =SUM(Y16:AA16) -> 0.30084544 | AC16: 7.33 | AD16: =SUM(AB16*AC16) -> 2.2051971 | AE16: =SUM(X16+AD16) -> 3.6186993 | AF16: =SUM(P16-AE16) -> 219.5813
C17: 241106000037 | D17: 45602 | E17: Sam.Pao | F17: Sam.Pao | G17: JunYue hotel | H17: 0.6996 | I17: 76 | J17: 1583.01 | P17: =SUBTOTAL(9,J17) -> 1583.01 | S17: =SUM(48788.5/68)*H17 -> 501.94757 | U17: =SUM(1800/68)*H17 -> 18.518824 | X17: =SUM(S17:W17) -> 520.46639 | Y17: =SUM(10716.46/68)*H17 -> 110.25346 | AA17: =SUM(50.64/68)*H17 -> 0.52099624 | AB17: =SUM(Y17:AA17) -> 110.77446 | AC17: 7.33 | AD17: =SUM(AB17*AC17) -> 811.97678 | AE17: =SUM(X17+AD17) -> 1332.4432 | AF17: =SUM(P17-AE17) -> 250.56683
C18: 241107000022 | D18: 45602 | E18: 罗珮文 | F18: Shirley | G18: SKY JET | H18: 32.635 | I18: 4165 | J18: 52361.59 | P18: =SUBTOTAL(9,J18) -> 52361.59 | S18: =SUM(48788.5/68)*H18 -> 23414.893 | U18: =SUM(1800/68)*H18 -> 863.86765 | X18: =SUM(S18:W18) -> 24278.76 | Y18: =SUM(10716.46/68)*H18 -> 5143.1128 | AA18: =SUM(50.64/68)*H18 -> 24.303476 | AB18: =SUM(Y18:AA18) -> 5167.4163 | AC18: 7.33 | AD18: =SUM(AB18*AC18) -> 37877.161 | AE18: =SUM(X18+AD18) -> 62155.922 | AF18: =SUM(P18-AE18) -> -9794.3317
A19: 合计 | J19: =SUM(J4:J4) -> 0 | N19: =SUM(N4:N4) -> 0 | P19: =SUM(P4:P4) -> 0 | Q19: =SUM(Q4:Q4) -> 0 | X19: =SUM(X4:X4) -> 0 | AD19: =SUM(AD4:AD4) -> 0 | AF19: =SUM(AF4:AF18) -> 3646.6843

Sheet JOB120363
A1: 2024年11月份LOS毛利表（海运）
A2: PSL表 | B2: 体积cbm | C2: 80.0396
A3: JOB | B3: 集装编号 | C3: 运单编号 | D3: 日期 | E3: 业务 | F3: 发货人 | G3: 收货人 | H3: 计费体积 | I3: 计费重量 | J3: 应 收 | Q3: 总应收 | R3: 起 运 港 成 本 | W3: 代垫运费 | X3: 起运港成本 合计 | Y3: 目的港成本 | AE3: 总支出 | AF3: 利润
J4: 应收RMB | K4: LOS Income(NGN)收到(奈拉) | L4: LOS 收到USD | M4: 美元汇率 dollar currency rate | N4: 应收 到付款USD | O4: 汇率 | P4: 人民币 | R4: 代理商 | S4: 运费+出口报关费 | T4: 提货费 | U4: 装卸费 | V4: 包装费 | Y4: 进口报关费 | Z4: 到门配送费 | AA4: 转运费 | AB4: 目的港支出 | AC4: 汇率 | AD4: 人民币 | AE4: 起运港+目的港
A5: JOB120363 | B5: COLL004291 | C5: 240930000009 | D5: 45608 | E5: 黄颖 | F5: ying | G5: Tom chen | H5: 0.0977 | I5: 28.5 | K5: 132820 | M5: =SUM(K5/N5) -> 1648.9137 | N5: 80.55 | O5: 7.3 | P5: =SUM(N5*O5) -> 588.015 | Q5: =SUM(P5:P26) -> 188664.54 | R5: 登凯=43330 陆总=8000 拖车费=1670 杂费=93 过磅费=125 | S5: =SUM(53218/68)*H5 -> 76.461744 | U5: =SUM(1955/68)*H5 -> 2.808875 | X5: =SUM(S5:W5) -> 79.270619 | Y5: =SUM(11360.84/68)*H5 -> 16.322854 | Z5: 11.38 | AA5: =SUM(53.54/68)*H5 -> 0.076924382 | AB5: =SUM(Y5:AA5) -> 27.779778 | AC5: 7.3 | AD5: =SUM(AB5*AC5) -> 202.79238 | AE5: =SUM(X5+AD5) -> 282.063 | AF5: =SUM(P5-AE5) -> 305.952
C6: 241015000034 | D6: 45608 | E6: 朱小飞 | F6: Isabel Zhu | G6: Halifa Success | H6: 4.77 | I6: 451 | J6: 9789.95 | P6: =SUBTOTAL(9,J6) -> 9789.95 | S6: =SUM(53218/68)*H6 -> 3733.0862 | U6: =SUM(1955/68)*H6 -> 137.1375 | X6: =SUM(S6:W6) -> 3870.2237 | Y6: =SUM(11360.84/68)*H6 -> 796.92951 | AA6: =SUM(53.54/68)*H6 -> 3.7556735 | AB6: =SUM(Y6:AA6) -> 800.68519 | AC6: 7.3 | AD6: =SUM(AB6*AC6) -> 5845.0019 | AE6: =SUM(X6+AD6) -> 9715.2255 | AF6: =SUM(P6-AE6) -> 74.724471
C7: 241021000005 | D7: 45608 | E7: 吕沛霖 | F7: 喵喵速运-Layne | G7: Hu Hai Liang | H7: 1.1795 | I7: 335 | K7: 583853 | M7: =SUM(K7/N7) -> 1650.0015 | N7: 353.84998 | O7: 7.3 | P7: =SUM(N7*O7) -> 2583.1049 | S7: =SUM(53218/68)*H7 -> 923.09751 | U7: =SUM(1955/68)*H7 -> 33.910625 | X7: =SUM(S7:W7) -> 957.00814 | Y7: =SUM(11360.84/68)*H7 -> 197.06045 | AA7: =SUM(53.54/68)*H7 -> 0.92868279 | AB7: =SUM(Y7:AA7) -> 197.98914 | AC7: 7.3 | AD7: =SUM(AB7*AC7) -> 1445.3207 | AE7: =SUM(X7+AD7) -> 2402.3288 | AF7: =SUM(P7-AE7) -> 180.77603
C8: 241022000035 | D8: 45608 | E8: Bella | F8: Bella Chan | G8: zhong zi xin | H8: 28.3553 | I8: 15100 | J8: 62780 | P8: =SUBTOTAL(9,J8) -> 62780 | S8: =SUM(53218/68)*H8 -> 22191.358 | U8: =SUM(1955/68)*H8 -> 815.21488 | V8: 300 | X8: =SUM(S8:W8) -> 23306.573 | Y8: =SUM(11360.84/68)*H8 -> 4737.3533 | Z8: =SUM(413.88+371.27) -> 785.15 | AA8: =SUM(53.54/68)*H8 -> 22.325629 | AB8: =SUM(Y8:AA8) -> 5544.829 | AC8: 7.3 | AD8: =SUM(AB8*AC8) -> 40477.251 | AE8: =SUM(X8+AD8) -> 63783.824 | AF8: =SUM(P8-AE8) -> -1003.8244
C9: 241024000054 | D9: 45608 | E9: Sam.Pao | F9: Sam.Pao | G9: ShanShan | H9: 16.835 | I9: 7500 | J9: 48779 | P9: =SUBTOTAL(9,J9) -> 48779 | S9: =SUM(53218/68)*H9 -> 13175.368 | U9: =SUM(1955/68)*H9 -> 484.00625 | X9: =SUM(S9:W9) -> 13659.374 | Y9: =SUM(11360.84/68)*H9 -> 2812.6433 | Z9: 97.38 | AA9: =SUM(53.54/68)*H9 -> 13.255087 | AB9: =SUM(Y9:AA9) -> 2923.2783 | AC9: 7.3 | AD9: =SUM(AB9*AC9) -> 21339.932 | AE9: =SUM(X9+AD9) -> 34999.306 | AF9: =SUM(P9-AE9) -> 13779.694
C10: 241104000057 | D10: 45608 | E10: 朱小飞 | F10: Isabel Zhu | G10: Halifa Success | H10: 2.3978 | I10: 447 | J10: 4925.76 | P10: =SUBTOTAL(9,J10) -> 4925.76 | S10: =SUM(53218/68)*H10 -> 1876.5606 | U10: =SUM(1955/68)*H10 -> 68.93675 | X10: =SUM(S10:W10) -> 1945.4973 | Y10: =SUM(11360.84/68)*H10 -> 400.60327 | AA10: =SUM(53.54/68)*H10 -> 1.8879149 | AB10: =SUM(Y10:AA10) -> 402.49118 | AC10: 7.3 | AD10: =SUM(AB10*AC10) -> 2938.1856 | AE10: =SUM(X10+AD10) -> 4883.683 | AF10: =SUM(P10-AE10) -> 42.077029
C11: 241104000071 | D11: 45608 | E11: Bella | F11: Bella Chan | G11: FENG | H11: 0.2523 | I11: 27 | K11: 116127 | M11: =SUM(K11/N11) -> 1684.4648 | N11: 68.94 | O11: 7.3 | P11: =SUM(N11*O11) -> 503.262 | S11: =SUM(53218/68)*H11 -> 197.45443 | U11: =SUM(1955/68)*H11 -> 7.253625 | X11: =SUM(S11:W11) -> 204.70806 | Y11: =SUM(11360.84/68)*H11 -> 42.152058 | AA11: =SUM(53.54/68)*H11 -> 0.19864915 | AB11: =SUM(Y11:AA11) -> 42.350707 | AC11: 7.3 | AD11: =SUM(AB11*AC11) -> 309.16016 | AE11: =SUM(X11+AD11) -> 513.86822 | AF11: =SUM(P11-AE11) -> -10.606218
C12: 241105000024 | D12: 45608 | E12: 陆总 | F12: 陆梓龙 | G12: luk | H12: 2.0026 | I12: 262.5 | J12: 4385.69 | P12: =SUBTOTAL(9,J12) -> 4385.69 | S12: =SUM(53218/68)*H12 -> 1567.2701 | U12: =SUM(1955/68)*H12 -> 57.57475 | X12: =SUM(S12:W12) -> 1624.8448 | Y12: =SUM(11360.84/68)*H12 -> 334.57674 | AA12: =SUM(53.54/68)*H12 -> 1.576753 | AB12: =SUM(Y12:AA12) -> 336.15349 | AC12: 7.3 | AD12: =SUM(AB12*AC12) -> 2453.9205 | AE12: =SUM(X12+AD12) -> 4078.7653 | AF12: =SUM(P12-AE12) -> 306.92467
C13: 241105000025 | D13: 45608 | E13: 黄颖 | F13: ying | G13: Oba Adeoriyomi Oyebo | H13: 3.7323 | I13: 536 | K13: 1998941 | M13: =SUM(K13/N13) -> 1712.4484 | N13: 1167.3 | O13: 7.3 | P13: =SUM(N13*O13) -> 8521.29 | S13: =SUM(53218/68)*H13 -> 2920.9638 | U13: =SUM(1955/68)*H13 -> 107.30362 | W13: 350 | X13: =SUM(S13:W13) -> 3378.2675 | Y13: =SUM(11360.84/68)*H13 -> 623.55975 | AA13: =SUM(53.54/68)*H13 -> 2.9386374 | AB13: =SUM(Y13:AA13) -> 626.49839 | AC13: 7.3 | AD13: =SUM(AB13*AC13) -> 4573.4382 | AE13: =SUM(X13+AD13) -> 7951.7057 | AF13: =SUM(P13-AE13) -> 569.58429
C14: 241105000054 | D14: 45608 | E14: 苏慧琪 | F14: KAY | G14: R李金 | H14: 0.3709 | I14: 167 | K14: 206012.98 | M14: =SUM(K14/N14) -> 1664.8859 | N14: 123.74 | O14: 7.27 | P14: =SUM(N14*O14) -> 899.5898 | S14: =SUM(53218/68)*H14 -> 290.27289 | U14: =SUM(1955/68)*H14 -> 10.663375 | X14: =SUM(S14:W14) -> 300.93626 | Y14: =SUM(11360.84/68)*H14 -> 61.966699 | AA14: =SUM(53.54/68)*H14 -> 0.29202921 | AB14: =SUM(Y14:AA14) -> 62.258729 | AC14: 7.3 | AD14: =SUM(AB14*AC14) -> 454.48872 | AE14: =SUM(X14+AD14) -> 755.42498 | AF14: =SUM(P14-AE14) -> 144.16482
C15: 241106000015 | D15: 45608 | E15: 朱小飞 | F15: Isabel Zhu | G15: Komebility gift | H15: 0.2358 | I15: 43 | K15: 132422.4 | M15: =SUM(K15/N15) -> 1672 | N15: 79.2 | O15: 7.3 | P15: =SUM(N15*O15) -> 578.16 | S15: =SUM(53218/68)*H15 -> 184.54124 | U15: =SUM(1955/68)*H15 -> 6.77925 | X15: =SUM(S15:W15) -> 191.32049 | Y15: =SUM(11360.84/68)*H15 -> 39.395383 | AA15: =SUM(53.54/68)*H15 -> 0.18565782 | AB15: =SUM(Y15:AA15) -> 39.581041 | AC15: 7.3 | AD15: =SUM(AB15*AC15) -> 288.9416 | AE15: =SUM(X15+AD15) -> 480.26209 | AF15: =SUM(P15-AE15) -> 97.897908
C16: 241106000020 | D16: 45608 | E16: 黄颖 | F16: ying | G16: yuhuichao | H16: 0.3 | I16: 65 | J16: 908 | P16: =SUBTOTAL(9,J16) -> 908 | S16: =SUM(53218/68)*H16 -> 234.78529 | U16: =SUM(1955/68)*H16 -> 8.625 | X16: =SUM(S16:W16) -> 243.41029 | Y16: =SUM(11360.84/68)*H16 -> 50.121353 | Z16: 34.85 | AA16: =SUM(53.54/68)*H16 -> 0.23620588 | AB16: =SUM(Y16:AA16) -> 85.207559 | AC16: 7.3 | AD16: =SUM(AB16*AC16) -> 622.01518 | AE16: =SUM(X16+AD16) -> 865.42547 | AF16: =SUM(P16-AE16) -> 42.574526
C17: 241106000026 | D17: 45608 | E17: 吕沛霖 | F17: 喵喵速运-Layne | G17: Mr.Shen | H17: 0.1938 | I17: 63 | K17: 188972 | M17: =SUM(K17/N17) -> 1700 | N17: 111.16 | O17: 7.27 | P17: =SUM(N17*O17) -> 808.1332 | S17: =SUM(53218/68)*H17 -> 151.6713 | U17: =SUM(1955/68)*H17 -> 5.57175 | X17: =SUM(S17:W17) -> 157.24305 | Y17: =SUM(11360.84/68)*H17 -> 32.378394 | Z17: 53.58 | AA17: =SUM(53.54/68)*H17 -> 0.152589 | AB17: =SUM(Y17:AA17) -> 86.110983 | AC17: 7.3 | AD17: =SUM(AB17*AC17) -> 628.61018 | AE17: =SUM(X17+AD17) -> 785.85323 | AF17: =SUM(P17-AE17) -> 22.279974
C18: 241106000034 | D18: 45608 | E18: 黄颖 | F18: ying | G18: Mr.zhang | H18: 0.3814 | I18: 55 | J18: 1213 | P18: =SUBTOTAL(9,J18) -> 1213 | S18: =SUM(53218/68)*H18 -> 298.49037 | U18: =SUM(1955/68)*H18 -> 10.96525 | X18: =SUM(S18:W18) -> 309.45562 | Y18: =SUM(11360.84/68)*H18 -> 63.720947 | Z18: 44.32 | AA18: =SUM(53.54/68)*H18 -> 0.30029641 | AB18: =SUM(Y18:AA18) -> 108.34124 | AC18: 7.3 | AD18: =SUM(AB18*AC18) -> 790.89107 | AE18: =SUM(X18+AD18) -> 1100.3467 | AF18: =SUM(P18-AE18) -> 112.6533
C19: 241106000049 | D19: 45608 | E19: 黄颖 | F19: ying | G19: wuchengxing | H19: 0.0224 | I19: 5.5 | J19: 228 | P19: =SUBTOTAL(9,J19) -> 228 | S19: =SUM(53218/68)*H19 -> 17.530635 | U19: =SUM(1955/68)*H19 -> 0.644 | X19: =SUM(S19:W19) -> 18.174635 | Y19: =SUM(11360.84/68)*H19 -> 3.7423944 | AA19: =SUM(53.54/68)*H19 -> 0.017636706 | AB19: =SUM(Y19:AA19) -> 3.7600311 | AC19: 7.3 | AD19: =SUM(AB19*AC19) -> 27.448227 | AE19: =SUM(X19+AD19) -> 45.622862 | AF19: =SUM(P19-AE19) -> 182.37714
C20: 241107000010 | D20: 45608 | E20: 朱小飞 | F20: Isabel Zhu | G20: Joy | H20: 0.616 | I20: 188 | K20: 331724.8 | M20: =SUM(K20/N20) -> 1672 | N20: 198.4 | O20: 7.3 | P20: =SUM(N20*O20) -> 1448.32 | S20: =SUM(53218/68)*H20 -> 482.09247 | U20: =SUM(1955/68)*H20 -> 17.71 | X20: =SUM(S20:W20) -> 499.80247 | Y20: =SUM(11360.84/68)*H20 -> 102.91584 | Z20: 3.11 | AA20: =SUM(53.54/68)*H20 -> 0.48500941 | AB20: =SUM(Y20:AA20) -> 106.51085 | AC20: 7.3 | AD20: =SUM(AB20*AC20) -> 777.52924 | AE20: =SUM(X20+AD20) -> 1277.3317 | AF20: =SUM(P20-AE20) -> 170.98829
C21: 241107000011 | D21: 45608 | E21: 朱小飞 | F21: Isabel Zhu | G21: Joy | H21: 2.028 | I21: 358 | K21: 1086131.2 | M21: =SUM(K21/N21) -> 1672 | N21: 649.6 | O21: 7.3 | P21: =SUM(N21*O21) -> 4742.08 | S21: =SUM(53218/68)*H21 -> 1587.1486 | U21: =SUM(1955/68)*H21 -> 58.305 | X21: =SUM(S21:W21) -> 1645.4536 | Y21: =SUM(11360.84/68)*H21 -> 338.82035 | Z21: 10.18 | AA21: =SUM(53.54/68)*H21 -> 1.5967518 | AB21: =SUM(Y21:AA21) -> 350.5971 | AC21: 7.3 | AD21: =SUM(AB21*AC21) -> 2559.3588 | AE21: =SUM(X21+AD21) -> 4204.8124 | AF21: =SUM(P21-AE21) -> 537.2676
C22: 241107000012 | D22: 45608 | E22: 朱小飞 | F22: Isabel Zhu | G22: Joy | H22: 7.8483 | I22: 1598 | K22: 4200064 | M22: =SUM(K22/N22) -> 1672 | N22: 2512 | O22: 7.3 | P22: =SUM(N22*O22) -> 18337.6 | S22: =SUM(53218/68)*H22 -> 6142.2181 | U22: =SUM(1955/68)*H22 -> 225.63862 | X22: =SUM(S22:W22) -> 6367.8567 | Y22: =SUM(11360.84/68)*H22 -> 1311.2247 | Z22: 39.27 | AA22: =SUM(53.54/68)*H22 -> 6.1793821 | AB22: =SUM(Y22:AA22) -> 1356.6741 | AC22: 7.3 | AD22: =SUM(AB22*AC22) -> 9903.7209 | AE22: =SUM(X22+AD22) -> 16271.578 | AF22: =SUM(P22-AE22) -> 2066.0224
C23: 241108000001 | D23: 45608 | E23: Sam.Pao | F23: Sam.Pao | G23: Mr. Jiang | H23: 1.6887 | I23: 558 | J23: 5053 | P23: =SUBTOTAL(9,J23) -> 5053 | S23: =SUM(53218/68)*H23 -> 1321.6064 | U23: =SUM(1955/68)*H23 -> 48.550125 | X23: =SUM(S23:W23) -> 1370.1565 | Y23: =SUM(11360.84/68)*H23 -> 282.1331 | Z23: 57.94 | AA23: =SUM(53.54/68)*H23 -> 1.3296029 | AB23: =SUM(Y23:AA23) -> 341.4027 | AC23: 7.3 | AD23: =SUM(AB23*AC23) -> 2492.2397 | AE23: =SUM(X23+AD23) -> 3862.3962 | AF23: =SUM(P23-AE23) -> 1190.6038
C24: 241109000008 | D24: 45608 | E24: 朱小飞 | F24: Isabel Zhu | G24: Komebility gift | H24: 1.344 | I24: 254 | K24: 696622.08 | M24: =SUM(K24/N24) -> 1672 | N24: 416.64 | O24: 7.3 | P24: =SUM(N24*O24) -> 3041.472 | S24: =SUM(53218/68)*H24 -> 1051.8381 | U24: =SUM(1955/68)*H24 -> 38.64 | X24: =SUM(S24:W24) -> 1090.4781 | Y24: =SUM(11360.84/68)*H24 -> 224.54366 | AA24: =SUM(53.54/68)*H24 -> 1.0582024 | AB24: =SUM(Y24:AA24) -> 225.60186 | AC24: 7.3 | AD24: =SUM(AB24*AC24) -> 1646.8936 | AE24: =SUM(X24+AD24) -> 2737.3717 | AF24: =SUM(P24-AE24) -> 304.10028
C25: 241210000044 | D25: 45609 | E25: 罗珮文 | F25: Shirley | G25: SKY JET | H25: 5.104 | I25: 471 | J25: 7929.81 | P25: =SUBTOTAL(9,J25) -> 7929.81 | S25: =SUM(53218/68)*H25 -> 3994.4805 | U25: =SUM(1955/68)*H25 -> 146.74 | X25: =SUM(S25:W25) -> 4141.2205 | Y25: =SUM(11360.84/68)*H25 -> 852.73128 | AA25: =SUM(53.54/68)*H25 -> 4.0186494 | AB25: =SUM(Y25:AA25) -> 856.74993 | AC25: 7.3 | AD25: =SUM(AB25*AC25) -> 6254.2745 | AE25: =SUM(X25+AD25) -> 10395.495 | AF25: =SUM(P25-AE25) -> -2465.685
C26: 241112000025 | D26: 45608 | E26: 陆总 | F26: 陆梓龙 | G26: xinlong | H26: 0.2838 | I26: 166 | J26: 621.3 | P26: =SUBTOTAL(9,J26) -> 621.3 | S26: =SUM(53218/68)*H26 -> 222.10689 | U26: =SUM(1955/68)*H26 -> 8.15925 | X26: =SUM(S26:W26) -> 230.26614 | Y26: =SUM(11360.84/68)*H26 -> 47.4148 | AA26: =SUM(53.54/68)*H26 -> 0.22345076 | AB26: =SUM(Y26:AA26) -> 47.638251 | AC26: 7.3 | AD26: =SUM(AB26*AC26) -> 347.75923 | AE26: =SUM(X26+AD26) -> 578.02537 | AF26: =SUM(P26-AE26) -> 43.274632
A27: 合计 | J27: =SUM(J4:J4) -> 0 | N27: =SUM(N4:N4) -> 0 | P27: =SUM(P4:P4) -> 0 | Q27: =SUM(Q4:Q4) -> 0 | X27: =SUM(X4:X4) -> 0 | AD27: =SUM(AD4:AD4) -> 0 | AF27: =SUM(AF4:AF26) -> 16693.821

Sheet JOB120364
A1: 2024年11月份LOS毛利表（海运）
A2: PSL表 | B2: 体积cbm | C2: 73.881
A3: JOB | B3: 集装编号 | C3: 运单编号 | D3: 日期 | E3: 业务 | F3: 发货人 | G3: 收货人 | H3: 计费体积 | I3: 计费重量 | J3: 应 收 | Q3: 总应收 | R3: 起 运 港 成 本 | W3: 代垫运费 | X3: 起运港成本 合计 | Y3: 目的港成本 | AE3: 总支出 | AF3: 利润
J4: 应收RMB | K4: LOS Income(NGN)收到(奈拉) | L4: LOS 收到USD | M4: 美元汇率 dollar currency rate | N4: 应收 到付款USD | O4: 汇率 | P4: 人民币 | R4: 代理商 | S4: 运费+出口报关费 | T4: 提货费 | U4: 装卸费 | V4: 包装费 | Y4: 进口报关费 | Z4: 到门配送费 | AA4: 转运费 | AB4: 目的港支出 | AC4: 汇率 | AD4: 人民币 | AE4: 起运港+目的港
A5: JOB120364 | B5: COLL004298 | C5: 241030000025 | D5: 45609 | E5: 黄颖 | F5: ying | G5: Nura | H5: 0.0306 | I5: 10 | J5: 65 | P5: =SUBTOTAL(9,J5) -> 65 | Q5: =SUM(P5:P24) -> 145491.1 | R5: 登凯=43330 赛捷=1660 拖车费=1670 杂费=73 过磅费=70 | S5: =SUM(46803/68)*H5 -> 21.06135 | U5: =SUM(1800/68)*H5 -> 0.81 | X5: =SUM(S5:W5) -> 21.87135 | Y5: =SUM(10793.87/68)*H5 -> 4.8572415 | AA5: =SUM(94.98/68)*H5 -> 0.042741 | AB5: =SUM(Y5:AA5) -> 4.8999825 | AC5: 7.33 | AD5: =SUM(AB5*AC5) -> 35.916872 | AE5: =SUM(X5+AD5) -> 57.788222 | AF5: =SUM(P5-AE5) -> 7.2117783
C6: 241102000008 | D6: 45609 | E6: 黄颖 | F6: ying | G6: Bruce | H6: 2.0582 | I6: 755 | K6: 957151 | M6: =SUM(K6/N6) -> 1603.5903 | N6: 596.88 | O6: 7.3 | P6: =SUM(N6*O6) -> 4357.224 | S6: =SUM(46803/68)*H6 -> 1416.6167 | U6: =SUM(1800/68)*H6 -> 54.481765 | X6: =SUM(S6:W6) -> 1471.0984 | Y6: =SUM(10793.87/68)*H6 -> 326.70505 | AA6: =SUM(94.98/68)*H6 -> 2.8748211 | AB6: =SUM(Y6:AA6) -> 329.57987 | AC6: 7.33 | AD6: =SUM(AB6*AC6) -> 2415.8204 | AE6: =SUM(X6+AD6) -> 3886.9189 | AF6: =SUM(P6-AE6) -> 470.30511
C7: 241107000009 | D7: 45609 | E7: 黄颖 | F7: ying | G7: MISS Huang | H7: 1.6128 | I7: 1251 | J7: 3794.79 | P7: =SUBTOTAL(9,J7) -> 3794.79 | S7: =SUM(46803/68)*H7 -> 1110.057 | U7: =SUM(1800/68)*H7 -> 42.691765 | X7: =SUM(S7:W7) -> 1152.7488 | Y7: =SUM(10793.87/68)*H7 -> 256.0052 | AA7: =SUM(94.98/68)*H7 -> 2.2527021 | AB7: =SUM(Y7:AA7) -> 258.2579 | AC7: 7.33 | AD7: =SUM(AB7*AC7) -> 1893.0304 | AE7: =SUM(X7+AD7) -> 3045.7792 | AF7: =SUM(P7-AE7) -> 749.01078
C8: 241104000001 | D8: 45609 | E8: 吕沛霖 | F8: 喵喵速运-Layne | G8: Isa | H8: 0.462 | I8: 90 | K8: 368397.9 | M8: =SUM(K8/N8) -> 1665 | N8: 221.26 | O8: 7.3 | P8: =SUM(N8*O8) -> 1615.198 | S8: =SUM(46803/68)*H8 -> 317.98509 | U8: =SUM(1800/68)*H8 -> 12.229412 | X8: =SUM(S8:W8) -> 330.2145 | Y8: =SUM(10793.87/68)*H8 -> 73.334823 | Z8: 57.94 | AA8: =SUM(94.98/68)*H8 -> 0.64530529 | AB8: =SUM(Y8:AA8) -> 131.92013 | AC8: 7.33 | AD8: =SUM(AB8*AC8) -> 966.97454 | AE8: =SUM(X8+AD8) -> 1297.189 | AF8: =SUM(P8-AE8) -> 318.00896
C9: 241105000045 | D9: 45609 | E9: 吕沛霖 | F9: 喵喵速运-Layne | G9: Abdulsheldu | H9: 0.8486 | I9: 297 | K9: 432928.65 | M9: =SUM(K9/N9) -> 1663.255 | N9: 260.29 | O9: 7.3 | P9: =SUM(N9*O9) -> 1900.117 | S9: =SUM(46803/68)*H9 -> 584.07391 | U9: =SUM(1800/68)*H9 -> 22.462941 | X9: =SUM(S9:W9) -> 606.53685 | Y9: =SUM(10793.87/68)*H9 -> 134.70115 | Z9: 10.07 | AA9: =SUM(94.98/68)*H9 -> 1.1852945 | AB9: =SUM(Y9:AA9) -> 145.95644 | AC9: 7.33 | AD9: =SUM(AB9*AC9) -> 1069.8607 | AE9: =SUM(X9+AD9) -> 1676.3976 | AF9: =SUM(P9-AE9) -> 223.71942
C10: 241108000043 | D10: 45609 | E10: Bella | F10: Bella Chan | G10: weng zixian | H10: 1.4833 | I10: 598 | K10: 1160958 | M10: =SUM(K10/N10) -> 1666.4389 | N10: 696.67 | O10: 7.3 | P10: =SUM(N10*O10) -> 5085.691 | S10: =SUM(46803/68)*H10 -> 1020.9249 | U10: =SUM(1800/68)*H10 -> 39.263824 | X10: =SUM(S10:W10) -> 1060.1887 | Y10: =SUM(10793.87/68)*H10 -> 235.44923 | Z10: 251.65 | AA10: =SUM(94.98/68)*H10 -> 2.0718211 | AB10: =SUM(Y10:AA10) -> 489.17105 | AC10: 7.33 | AD10: =SUM(AB10*AC10) -> 3585.6238 | AE10: =SUM(X10+AD10) -> 4645.8125 | AF10: =SUM(P10-AE10) -> 439.87855
C11: 241111000011 | D11: 45609 | E11: 朱小飞 | F11: Isabel Zhu | G11: Ope Olofinjana | H11: 0.1421 | I11: 36 | K11: 93936 | M11: =SUM(K11/N11) -> 1651.1865 | N11: 56.89 | O11: 7.3 | P11: =SUM(N11*O11) -> 415.297 | S11: =SUM(46803/68)*H11 -> 97.804504 | U11: =SUM(1800/68)*H11 -> 3.7614706 | X11: =SUM(S11:W11) -> 101.56597 | Y11: =SUM(10793.87/68)*H11 -> 22.556014 | Z11: 10 | AA11: =SUM(94.98/68)*H11 -> 0.19848026 | AB11: =SUM(Y11:AA11) -> 32.754494 | AC11: 7.33 | AD11: =SUM(AB11*AC11) -> 240.09044 | AE11: =SUM(X11+AD11) -> 341.65642 | AF11: =SUM(P11-AE11) -> 73.640585
C12: 241111000012 | D12: 45609 | E12: 朱小飞 | F12: Isabel Zhu | G12: Ope Olofinjana | H12: 0.2386 | I12: 52 | K12: 148176 | M12: =SUM(K12/N12) -> 1651.17 | N12: 89.74 | O12: 7.3 | P12: =SUM(N12*O12) -> 655.102 | S12: =SUM(46803/68)*H12 -> 164.22347 | U12: =SUM(1800/68)*H12 -> 6.3158824 | X12: =SUM(S12:W12) -> 170.53935 | Y12: =SUM(10793.87/68)*H12 -> 37.873785 | Z12: 11.3 | AA12: =SUM(94.98/68)*H12 -> 0.33326806 | AB12: =SUM(Y12:AA12) -> 49.507053 | AC12: 7.33 | AD12: =SUM(AB12*AC12) -> 362.8867 | AE12: =SUM(X12+AD12) -> 533.42605 | AF12: =SUM(P12-AE12) -> 121.67595
C13: 241111000032 | D13: 45609 | E13: Bella | F13: Bella Chan | G13: FENG | H13: 0.2174 | I13: 57 | K13: 107613 | M13: =SUM(K13/N13) -> 1650.0003 | N13: 65.21999 | O13: 7.2 | P13: =SUM(N13*O13) -> 469.58393 | S13: =SUM(46803/68)*H13 -> 149.63194 | U13: =SUM(1800/68)*H13 -> 5.7547059 | X13: =SUM(S13:W13) -> 155.38665 | Y13: =SUM(10793.87/68)*H13 -> 34.508637 | AA13: =SUM(94.98/68)*H13 -> 0.30365665 | AB13: =SUM(Y13:AA13) -> 34.812294 | AC13: 7.33 | AD13: =SUM(AB13*AC13) -> 255.17411 | AE13: =SUM(X13+AD13) -> 410.56076 | AF13: =SUM(P13-AE13) -> 59.023163
C14: 241111000039 | D14: 45609 | E14: 无人 | F14: dejare James | G14: James | H14: 1.8662 | I14: 626 | L14: 559.83 | M14: =SUM(K14/N14) -> 0 | N14: 559.82996 | O14: 7.3 | P14: =SUM(N14*O14) -> 4086.7587 | S14: =SUM(46803/68)*H14 -> 1284.467 | U14: =SUM(1800/68)*H14 -> 49.399412 | X14: =SUM(S14:W14) -> 1333.8664 | Y14: =SUM(10793.87/68)*H14 -> 296.22824 | AA14: =SUM(94.98/68)*H14 -> 2.6066423 | AB14: =SUM(Y14:AA14) -> 298.83488 | AC14: 7.33 | AD14: =SUM(AB14*AC14) -> 2190.4597 | AE14: =SUM(X14+AD14) -> 3524.3261 | AF14: =SUM(P14-AE14) -> 562.43258
C15: 241111000055 | D15: 45609 | E15: 朱小飞 | F15: Isabel Zhu | G15: Halifa Success | H15: 2.9026 | I15: 435 | J15: 5972.48 | P15: =SUBTOTAL(9,J15) -> 5972.48 | S15: =SUM(46803/68)*H15 -> 1997.7998 | U15: =SUM(1800/68)*H15 -> 76.833529 | V15: 20 | X15: =SUM(S15:W15) -> 2094.6334 | Y15: =SUM(10793.87/68)*H15 -> 460.73952 | AA15: =SUM(94.98/68)*H15 -> 4.0542492 | AB15: =SUM(Y15:AA15) -> 464.79376 | AC15: 7.33 | AD15: =SUM(AB15*AC15) -> 3406.9383 | AE15: =SUM(X15+AD15) -> 5501.5716 | AF15: =SUM(P15-AE15) -> 470.90835
C16: 241111000056 | D16: 45609 | E16: 朱小飞 | F16: Isabel Zhu | G16: Halifa Success | H16: 2.4588 | I16: 346 | J16: 5048.9 | P16: =SUBTOTAL(9,J16) -> 5048.9 | S16: =SUM(46803/68)*H16 -> 1692.3414 | U16: =SUM(1800/68)*H16 -> 65.085882 | X16: =SUM(S16:W16) -> 1757.4273 | Y16: =SUM(10793.87/68)*H16 -> 390.29364 | AA16: =SUM(94.98/68)*H16 -> 3.4343651 | AB16: =SUM(Y16:AA16) -> 393.72801 | AC16: 7.33 | AD16: =SUM(AB16*AC16) -> 2886.0263 | AE16: =SUM(X16+AD16) -> 4643.4536 | AF16: =SUM(P16-AE16) -> 405.44642
C17: 241112000043 | D17: 45609 | E17: Sam.Pao | F17: Sam.Pao | G17: MaiKaiNian | H17: 4.9039 | I17: 546 | J17: 10739.54 | P17: =SUBTOTAL(9,J17) -> 10739.54 | S17: =SUM(46803/68)*H17 -> 3375.2534 | U17: =SUM(1800/68)*H17 -> 129.80912 | X17: =SUM(S17:W17) -> 3505.0625 | Y17: =SUM(10793.87/68)*H17 -> 778.41263 | AA17: =SUM(94.98/68)*H17 -> 6.8495944 | AB17: =SUM(Y17:AA17) -> 785.26223 | AC17: 7.33 | AD17: =SUM(AB17*AC17) -> 5755.9721 | AE17: =SUM(X17+AD17) -> 9261.0347 | AF17: =SUM(P17-AE17) -> 1478.5053
C18: 241112000044 | D18: 45609 | E18: 朱小飞 | F18: Isabel Zhu | G18: Halifa Success | H18: 0.936 | I18: 422 | J18: 2195.26 | P18: =SUBTOTAL(9,J18) -> 2195.26 | S18: =SUM(46803/68)*H18 -> 644.22953 | U18: =SUM(1800/68)*H18 -> 24.776471 | W18: 266 | X18: =SUM(S18:W18) -> 935.006 | Y18: =SUM(10793.87/68)*H18 -> 148.57445 | Z18: 17.33 | AA18: =SUM(94.98/68)*H18 -> 1.3073718 | AB18: =SUM(Y18:AA18) -> 167.21182 | AC18: 7.33 | AD18: =SUM(AB18*AC18) -> 1225.6626 | AE18: =SUM(X18+AD18) -> 2160.6686 | AF18: =SUM(P18-AE18) -> 34.591377
C19: 241113000012 | D19: 45609 | E19: 罗珮文 | F19: Shirley | G19: Yusky | H19: 5.5016 | I19: 2874 | K19: 2264723.3 | M19: =SUM(K19/N19) -> 1608 | N19: 1408.41 | O19: 7.3 | P19: =SUM(N19*O19) -> 10281.393 | S19: =SUM(46803/68)*H19 -> 3786.638 | U19: =SUM(1800/68)*H19 -> 145.63059 | X19: =SUM(S19:W19) -> 3932.2686 | Y19: =SUM(10793.87/68)*H19 -> 873.28758 | AA19: =SUM(94.98/68)*H19 -> 7.6844407 | AB19: =SUM(Y19:AA19) -> 880.97202 | AC19: 7.33 | AD19: =SUM(AB19*AC19) -> 6457.5249 | AE19: =SUM(X19+AD19) -> 10389.793 | AF19: =SUM(P19-AE19) -> -108.40049
C20: 241113000017 | D20: 45609 | E20: Sam.Pao | F20: Sam.Pao | G20: FanXiangGuo | H20: 1.4152 | I20: 656 | K20: 851651 | M20: =SUM(K20/N20) -> 1671.5099 | N20: 509.51 | O20: 7.29 | P20: =SUM(N20*O20) -> 3714.3279 | S20: =SUM(46803/68)*H20 -> 974.05302 | U20: =SUM(1800/68)*H20 -> 37.461176 | W20: 98.72 | X20: =SUM(S20:W20) -> 1110.2342 | Y20: =SUM(10793.87/68)*H20 -> 224.63948 | AA20: =SUM(94.98/68)*H20 -> 1.9767014 | AB20: =SUM(Y20:AA20) -> 226.61618 | AC20: 7.33 | AD20: =SUM(AB20*AC20) -> 1661.0966 | AE20: =SUM(X20+AD20) -> 2771.3308 | AF20: =SUM(P20-AE20) -> 942.99707
C21: 241209000061 | D21: 45609 | E21: 陆总 | F21: 陆梓龙 | G21: xinlong | H21: 16.4369 | I21: 16042 | J21: 37916.64 | P21: =SUBTOTAL(9,J21) -> 37916.64 | S21: =SUM(46803/68)*H21 -> 11313.18 | U21: =SUM(1800/68)*H21 -> 435.09441 | X21: =SUM(S21:W21) -> 11748.274 | Y21: =SUM(10793.87/68)*H21 -> 2609.0847 | Z21: 162.02 | AA21: =SUM(94.98/68)*H21 -> 22.958482 | AB21: =SUM(Y21:AA21) -> 2794.0632 | AC21: 7.33 | AD21: =SUM(AB21*AC21) -> 20480.483 | AE21: =SUM(X21+AD21) -> 32228.758 | AF21: =SUM(P21-AE21) -> 5687.8824
C22: 241210000044 | D22: 45609 | E22: 罗珮文 | F22: Shirley | G22: SKY JET | H22: 5.896 | I22: 922 | J22: 9160.23 | P22: =SUBTOTAL(9,J22) -> 9160.23 | S22: =SUM(46803/68)*H22 -> 4058.0954 | U22: =SUM(1800/68)*H22 -> 156.07059 | X22: =SUM(S22:W22) -> 4214.166 | Y22: =SUM(10793.87/68)*H22 -> 935.89202 | AA22: =SUM(94.98/68)*H22 -> 8.2353247 | AB22: =SUM(Y22:AA22) -> 944.12735 | AC22: 7.33 | AD22: =SUM(AB22*AC22) -> 6920.4535 | AE22: =SUM(X22+AD22) -> 11134.619 | AF22: =SUM(P22-AE22) -> -1974.3895
C23: 241213000052 | D23: 45609 | E23: 罗珮文 | F23: Shirley | G23: SKY JET | H23: 20.97 | I23: 2633 | J23: 32579.83 | P23: =SUBTOTAL(9,J23) -> 32579.83 | S23: =SUM(46803/68)*H23 -> 14433.219 | U23: =SUM(1800/68)*H23 -> 555.08824 | X23: =SUM(S23:W23) -> 14988.308 | Y23: =SUM(10793.87/68)*H23 -> 3328.639 | AA23: =SUM(94.98/68)*H23 -> 29.290156 | AB23: =SUM(Y23:AA23) -> 3357.9292 | AC23: 7.33 | AD23: =SUM(AB23*AC23) -> 24613.621 | AE23: =SUM(X23+AD23) -> 39601.928 | AF23: =SUM(P23-AE23) -> -7022.0984
C24: 241213000054 | D24: 45609 | E24: 罗珮文 | F24: Shirley | G24: SKY JET | H24: 3.5 | I24: 419 | J24: 5437.74 | P24: =SUBTOTAL(9,J24) -> 5437.74 | S24: =SUM(46803/68)*H24 -> 2408.9779 | U24: =SUM(1800/68)*H24 -> 92.647059 | X24: =SUM(S24:W24) -> 2501.625 | Y24: =SUM(10793.87/68)*H24 -> 555.56684 | AA24: =SUM(94.98/68)*H24 -> 4.8886765 | AB24: =SUM(Y24:AA24) -> 560.45551 | AC24: 7.33 | AD24: =SUM(AB24*AC24) -> 4108.1389 | AE24: =SUM(X24+AD24) -> 6609.7639 | AF24: =SUM(P24-AE24) -> -1172.0239
A25: 合计 | J25: =SUM(J4:J4) -> 0 | N25: =SUM(N4:N4) -> 0 | P25: =SUM(P4:P4) -> 0 | Q25: =SUM(Q4:Q4) -> 0 | X25: =SUM(X4:X4) -> 0 | AD25: =SUM(AD4:AD4) -> 0 | AF25: =SUM(AF4:AF24) -> 1768.3255

Sheet JOB120365
A1: 2024年11月份LOS毛利表（海运）
A2: PSL表 | B2: 体积cbm | C2: 74.3865
A3: JOB | B3: 集装编号 | C3: 运单编号 | D3: 日期 | E3: 业务 | F3: 发货人 | G3: 收货人 | H3: 计费体积 | I3: 计费重量 | J3: 应 收 | Q3: 总应收 | R3: 起 运 港 成 本 | W3: 代垫运费 | X3: 起运港成本 合计 | Y3: 目的港成本 | AE3: 总支出 | AF3: 利润
J4: 应收RMB | K4: LOS Income(NGN)收到(奈拉) | L4: LOS 收到USD | M4: 美元汇率 dollar currency rate | N4: 应收 到付款USD | O4: 汇率 | P4: 人民币 | R4: 代理商 | S4: 运费+出口报关费 | T4: 提货费 | U4: 装卸费 | V4: 包装费 | Y4: 进口报关费 | Z4: 到门配送费 | AA4: 转运费 | AB4: 目的港支出 | AC4: 汇率 | AD4: 人民币 | AE4: 起运港+目的港
A5: JOB120365 | B5: COLL004301 | C5: 241030000050 | D5: 45615 | E5: 黄颖 | F5: ying | G5: Sunday Adelena | H5: 20.9121 | I5: 2224 | J5: 44817.94 | P5: =SUBTOTAL(9,J5) -> 44817.94 | Q5: =SUM(P5:P21) -> 168658.33 | R5: 登凯=43386.5 陆总=1800 拖车费=1670 杂费=661 过磅费=71 | S5: =SUM(47588.5/68)*H5 -> 14634.933 | U5: =SUM(2300/68)*H5 -> 707.32103 | X5: =SUM(S5:W5) -> 15342.254 | Y5: =SUM(11085/68)*H5 -> 3408.9798 | AA5: =SUM(75.12/68)*H5 -> 23.10172 | AB5: =SUM(Y5:AA5) -> 3432.0816 | AC5: 7.3 | AD5: =SUM(AB5*AC5) -> 25054.195 | AE5: =SUM(X5+AD5) -> 40396.45 | AF5: =SUM(P5-AE5) -> 4421.4903
C6: 241102000012 | D6: 45615 | E6: 黄颖 | F6: ying | G6: Bruce | H6: 2.1458 | I6: 808 | K6: 1041860 | M6: =SUM(K6/N6) -> 1674.262 | N6: 622.28015 | O6: 7.27 | P6: =SUM(N6*O6) -> 4523.9767 | S6: =SUM(47588.5/68)*H6 -> 1501.6971 | U6: =SUM(2300/68)*H6 -> 72.578529 | X6: =SUM(S6:W6) -> 1574.2756 | Y6: =SUM(11085/68)*H6 -> 349.79696 | AA6: =SUM(75.12/68)*H6 -> 2.3704779 | AB6: =SUM(Y6:AA6) -> 352.16743 | AC6: 7.3 | AD6: =SUM(AB6*AC6) -> 2570.8223 | AE6: =SUM(X6+AD6) -> 4145.0979 | AF6: =SUM(P6-AE6) -> 378.87879
C7: 241102000009 | D7: 45615 | E7: 黄颖 | F7: ying | G7: Bruce | H7: 1.3109 | I7: 450 | K7: 638809 | M7: =SUM(K7/N7) -> 1680.413 | N7: 380.15 | O7: 7.27 | P7: =SUM(N7*O7) -> 2763.6905 | S7: =SUM(47588.5/68)*H7 -> 917.4083 | U7: =SUM(2300/68)*H7 -> 44.339265 | X7: =SUM(S7:W7) -> 961.74757 | Y7: =SUM(11085/68)*H7 -> 213.69598 | AA7: =SUM(75.12/68)*H7 -> 1.4481589 | AB7: =SUM(Y7:AA7) -> 215.14414 | AC7: 7.3 | AD7: =SUM(AB7*AC7) -> 1570.5522 | AE7: =SUM(X7+AD7) -> 2532.2998 | AF7: =SUM(P7-AE7) -> 231.39073
C8: 241107000048 | D8: 45615 | E8: 黄颖 | F8: ying | G8: Nura | H8: 1.9284 | I8: 1039 | J8: 4628 | P8: =SUBTOTAL(9,J8) -> 4628 | S8: =SUM(47588.5/68)*H8 -> 1349.5539 | U8: =SUM(2300/68)*H8 -> 65.225294 | X8: =SUM(S8:W8) -> 1414.7792 | Y8: =SUM(11085/68)*H8 -> 314.35756 | AA8: =SUM(75.12/68)*H8 -> 2.1303148 | AB8: =SUM(Y8:AA8) -> 316.48787 | AC8: 7.3 | AD8: =SUM(AB8*AC8) -> 2310.3615 | AE8: =SUM(X8+AD8) -> 3725.1406 | AF8: =SUM(P8-AE8) -> 902.85935
C9: 241107000009 | D9: 45615 | E9: 黄颖 | F9: ying | G9: MISS Huang | H9: 18.3103 | I9: 10792 | J9: 43083.21 | P9: =SUBTOTAL(9,J9) -> 43083.21 | S9: =SUM(47588.5/68)*H9 -> 12814.113 | U9: =SUM(2300/68)*H9 -> 619.31897 | X9: =SUM(S9:W9) -> 13433.432 | Y9: =SUM(11085/68)*H9 -> 2984.8482 | AA9: =SUM(75.12/68)*H9 -> 20.227496 | AB9: =SUM(Y9:AA9) -> 3005.0757 | AC9: 7.3 | AD9: =SUM(AB9*AC9) -> 21937.052 | AE9: =SUM(X9+AD9) -> 35370.485 | AF9: =SUM(P9-AE9) -> 7712.7253
C10: 241116000004 | D10: 45615 | E10: 黄颖 | F10: ying | G10: wangmuma | H10: 0.9249 | I10: 172 | J10: 3030 | P10: =SUBTOTAL(9,J10) -> 3030 | S10: =SUM(47588.5/68)*H10 -> 647.27358 | U10: =SUM(2300/68)*H10 -> 31.283382 | X10: =SUM(S10:W10) -> 678.55697 | Y10: =SUM(11085/68)*H10 -> 150.7723 | AA10: =SUM(75.12/68)*H10 -> 1.0217425 | AB10: =SUM(Y10:AA10) -> 151.79404 | AC10: 7.3 | AD10: =SUM(AB10*AC10) -> 1108.0965 | AE10: =SUM(X10+AD10) -> 1786.6535 | AF10: =SUM(P10-AE10) -> 1243.3465
C11: 241111000061 | D11: 45615 | E11: 苏慧琪 | F11: KAY | G11: xiaobai小白 | H11: 0.45 | I11: 124 | J11: 1257.4 | P11: =SUM(J11) -> 1257.4 | S11: =SUM(47588.5/68)*H11 -> 314.9239 | U11: =SUM(2300/68)*H11 -> 15.220588 | X11: =SUM(S11:W11) -> 330.14449 | Y11: =SUM(11085/68)*H11 -> 73.356618 | Z11: 20.81 | AA11: =SUM(75.12/68)*H11 -> 0.49711765 | AB11: =SUM(Y11:AA11) -> 94.663735 | AC11: 7.3 | AD11: =SUM(AB11*AC11) -> 691.04527 | AE11: =SUM(X11+AD11) -> 1021.1898 | AF11: =SUM(P11-AE11) -> 236.21025
C12: 241112000045 | D12: 45615 | E12: 朱小飞 | F12: Isabel Zhu | G12: Mr Zhou | H12: 0.8383 | I12: 181 | J12: 3448 | P12: =SUBTOTAL(9,J12) -> 3448 | S12: =SUM(47588.5/68)*H12 -> 586.66823 | U12: =SUM(2300/68)*H12 -> 28.354265 | X12: =SUM(S12:W12) -> 615.02249 | Y12: =SUM(11085/68)*H12 -> 136.65523 | Z12: 95.12 | AA12: =SUM(75.12/68)*H12 -> 0.92607494 | AB12: =SUM(Y12:AA12) -> 232.7013 | AC12: 7.3 | AD12: =SUM(AB12*AC12) -> 1698.7195 | AE12: =SUM(X12+AD12) -> 2313.742 | AF12: =SUM(P12-AE12) -> 1134.258
C13: 241113000029 | D13: 45615 | E13: 朱小飞 | F13: Isabel Zhu | G13: Mr Olusola Abidemi | H13: 1.7575 | I13: 1244.5 | K13: 1064044.8 | M13: =SUM(K13/N13) -> 1680.0004 | N13: 633.35986 | O13: 7.27 | P13: =SUM(N13*O13) -> 4604.5262 | S13: =SUM(47588.5/68)*H13 -> 1229.9528 | T13: 735 | U13: =SUM(2300/68)*H13 -> 59.444853 | X13: =SUM(S13:W13) -> 2024.3976 | Y13: =SUM(11085/68)*H13 -> 286.49835 | AA13: =SUM(75.12/68)*H13 -> 1.9415206 | AB13: =SUM(Y13:AA13) -> 288.43987 | AC13: 7.3 | AD13: =SUM(AB13*AC13) -> 2105.611 | AE13: =SUM(X13+AD13) -> 4130.0087 | AF13: =SUM(P13-AE13) -> 474.51753
C14: 241113000042 | D14: 45615 | E14: 黄颖 | F14: ying | G14: Nura | H14: 0.3419 | I14: 190 | J14: 748.5 | P14: =SUBTOTAL(9,J14) -> 748.5 | S14: =SUM(47588.5/68)*H14 -> 239.27218 | U14: =SUM(2300/68)*H14 -> 11.564265 | X14: =SUM(S14:W14) -> 250.83644 | Y14: =SUM(11085/68)*H14 -> 55.734728 | AA14: =SUM(75.12/68)*H14 -> 0.37769894 | AB14: =SUM(Y14:AA14) -> 56.112427 | AC14: 7.3 | AD14: =SUM(AB14*AC14) -> 409.62072 | AE14: =SUM(X14+AD14) -> 660.45716 | AF14: =SUM(P14-AE14) -> 88.04284
C15: 241114000023 | D15: 45615 | E15: 黄颖 | F15: ying | G15: Hao wangjun | H15: 3.1076 | I15: 643 | J15: 6811 | P15: =SUBTOTAL(9,J15) -> 6811 | S15: =SUM(47588.5/68)*H15 -> 2174.7944 | U15: =SUM(2300/68)*H15 -> 105.11 | X15: =SUM(S15:W15) -> 2279.9044 | Y15: =SUM(11085/68)*H15 -> 506.5845 | AA15: =SUM(75.12/68)*H15 -> 3.432984 | AB15: =SUM(Y15:AA15) -> 510.01748 | AC15: 7.3 | AD15: =SUM(AB15*AC15) -> 3723.1276 | AE15: =SUM(X15+AD15) -> 6003.0321 | AF15: =SUM(P15-AE15) -> 807.96792
C16: 241114000046 | D16: 45615 | E16: Bella | F16: Bella Chan | G16: new hope 边鹏飞 | H16: 0.0703 | I16: 43 | K16: 47100 | M16: =SUM(K16/N16) -> 2230.1133 | N16: 21.120003 | O16: 7.28 | P16: =SUM(N16*O16) -> 153.75362 | S16: =SUM(47588.5/68)*H16 -> 49.198111 | U16: =SUM(2300/68)*H16 -> 2.3777941 | X16: =SUM(S16:W16) -> 51.575905 | Y16: =SUM(11085/68)*H16 -> 11.459934 | AA16: =SUM(75.12/68)*H16 -> 0.077660824 | AB16: =SUM(Y16:AA16) -> 11.537595 | AC16: 7.3 | AD16: =SUM(AB16*AC16) -> 84.224441 | AE16: =SUM(X16+AD16) -> 135.80035 | AF16: =SUM(P16-AE16) -> 17.953276
C17: 241115000005 | D17: 45615 | E17: 朱小飞 | F17: Isabel Zhu | G17: Halifa Success | H17: 1.0641 | I17: 52 | J17: 2244.61 | P17: =SUBTOTAL(9,J17) -> 2244.61 | S17: =SUM(47588.5/68)*H17 -> 744.69004 | U17: =SUM(2300/68)*H17 -> 35.991618 | W17: 72.29 | X17: =SUM(S17:W17) -> 852.97166 | Y17: =SUM(11085/68)*H17 -> 173.46395 | AA17: =SUM(75.12/68)*H17 -> 1.1755175 | AB17: =SUM(Y17:AA17) -> 174.63947 | AC17: 7.3 | AD17: =SUM(AB17*AC17) -> 1274.8681 | AE17: =SUM(X17+AD17) -> 2127.8398 | AF17: =SUM(P17-AE17) -> 116.77024
C18: 241116000018 | D18: 45615 | E18: Sam.Pao | F18: Sam.Pao | G18: MaiKaiNian | H18: 6.0469 | I18: 528 | J18: 13684.14 | P18: =SUBTOTAL(9,J18) -> 13684.14 | S18: =SUM(47588.5/68)*H18 -> 4231.8074 | U18: =SUM(2300/68)*H18 -> 204.5275 | X18: =SUM(S18:W18) -> 4436.3349 | Y18: =SUM(11085/68)*H18 -> 985.73362 | AA18: =SUM(75.12/68)*H18 -> 6.680046 | AB18: =SUM(Y18:AA18) -> 992.41367 | AC18: 7.3 | AD18: =SUM(AB18*AC18) -> 7244.6198 | AE18: =SUM(X18+AD18) -> 11680.955 | AF18: =SUM(P18-AE18) -> 2003.1853
C19: 241118000073 | D19: 45615 | E19: 陆总 | F19: 陆梓龙 | G19: xiantian | H19: 10.1365 | I19: 5464 | J19: 21201.16 | P19: =SUBTOTAL(9,J19) -> 21201.16 | S19: =SUM(47588.5/68)*H19 -> 7093.8357 | U19: =SUM(2300/68)*H19 -> 342.85221 | X19: =SUM(S19:W19) -> 7436.6879 | Y19: =SUM(11085/68)*H19 -> 1652.3986 | AA19: =SUM(75.12/68)*H19 -> 11.197851 | AB19: =SUM(Y19:AA19) -> 1663.5964 | AC19: 7.3 | AD19: =SUM(AB19*AC19) -> 12144.254 | AE19: =SUM(X19+AD19) -> 19580.942 | AF19: =SUM(P19-AE19) -> 1620.2182
C20: 241209000062 | D20: 45615 | E20: 陆总 | F20: 陆梓龙 | G20: xinlong | H20: 4.9817 | I20: 4862 | J20: 11334.38 | P20: =SUBTOTAL(9,J20) -> 11334.38 | S20: =SUM(47588.5/68)*H20 -> 3486.3475 | U20: =SUM(2300/68)*H20 -> 168.49868 | X20: =SUM(S20:W20) -> 3654.8462 | Y20: =SUM(11085/68)*H20 -> 812.09036 | Z20: 77.38 | AA20: =SUM(75.12/68)*H20 -> 5.5033133 | AB20: =SUM(Y20:AA20) -> 894.97367 | AC20: 7.3 | AD20: =SUM(AB20*AC20) -> 6533.3078 | AE20: =SUM(X20+AD20) -> 10188.154 | AF20: =SUM(P20-AE20) -> 1146.226
C21: 241218000023 | D21: 45615 | E21: 吕沛霖 | F21: 喵喵速运-Layne | G21: Isa | H21: 0.0592 | I21: 10 | K21: 70231 | M21: =SUM(K21/N21) -> 1580 | N21: 44.45 | O21: 7.29 | P21: =SUM(N21*O21) -> 324.0405 | S21: =SUM(47588.5/68)*H21 -> 41.429988 | U21: =SUM(2300/68)*H21 -> 2.0023529 | X21: =SUM(S21:W21) -> 43.432341 | Y21: =SUM(11085/68)*H21 -> 9.6504706 | AA21: =SUM(75.12/68)*H21 -> 0.065398588 | AB21: =SUM(Y21:AA21) -> 9.7158692 | AC21: 7.3 | AD21: =SUM(AB21*AC21) -> 70.925845 | AE21: =SUM(X21+AD21) -> 114.35819 | AF21: =SUM(P21-AE21) -> 209.68231
A22: 合计 | J22: =SUM(J4:J4) -> 0 | N22: =SUM(N4:N4) -> 0 | P22: =SUM(P4:P4) -> 0 | Q22: =SUM(Q4:Q4) -> 0 | X22: =SUM(X4:X4) -> 0 | AD22: =SUM(AD4:AD4) -> 0 | AF22: =SUM(AF4:AF21) -> 22745.723

Sheet JOB120366
A1: 2024年11月份LOS毛利表（海运）
A2: PSL表 | B2: 体积cbm | C2: 74.0456
A3: JOB | B3: 集装编号 | C3: 运单编号 | D3: 日期 | E3: 业务 | F3: 发货人 | G3: 收货人 | H3: 计费体积 | I3: 计费重量 | J3: 应 收 | Q3: 总应收 | R3: 起 运 港 成 本 | W3: 代垫运费 | X3: 起运港成本 合计 | Y3: 目的港成本 | AE3: 总支出 | AF3: 利润
J4: 应收RMB | K4: LOS Income(NGN)收到(奈拉) | L4: LOS 收到USD | M4: 美元汇率 dollar currency rate | N4: 应收 到付款USD | O4: 汇率 | P4: 人民币 | R4: 代理商 | S4: 运费+出口报关费 | T4: 提货费 | U4: 装卸费 | V4: 包装费 | Y4: 进口报关费 | Z4: 到门配送费 | AA4: 转运费 | AB4: 目的港支出 | AC4: 汇率 | AD4: 人民币 | AE4: 起运港+目的港
A5: JOB120366 | B5: COLL004305 | C5: 241102000009 | D5: 45616 | E5: 黄颖 | F5: ying | G5: Bruce | H5: 0.3399 | I5: 118 | K5: 165636 | M5: =SUM(K5/N5) -> 1680.2191 | N5: 98.58 | O5: 7.27 | P5: =SUM(N5*O5) -> 716.6766 | Q5: =SUM(P5:P18) -> 147610.5 | R5: 登凯=43386.5 赛捷=500 拖车费=1670 杂费=61 过磅费=68 | S5: =SUM(45685.5/68)*H5 -> 228.36032 | U5: =SUM(2000/68)*H5 -> 9.9970588 | X5: =SUM(S5:W5) -> 238.35737 | Y5: =SUM(11085/68)*H5 -> 55.408699 | AA5: =SUM(77.38/68)*H5 -> 0.38678621 | AB5: =SUM(Y5:AA5) -> 55.795485 | AC5: 7.3 | AD5: =SUM(AB5*AC5) -> 407.30704 | AE5: =SUM(X5+AD5) -> 645.66441 | AF5: =SUM(P5-AE5) -> 71.012187
C6: 241107000009 | D6: 45616 | E6: 黄颖 | F6: ying | G6: MISS Huang | H6: 6.8102 | I6: 4442 | J6: 16020.41 | P6: =SUBTOTAL(9,J6) -> 16020.41 | S6: =SUM(45685.5/68)*H6 -> 4575.4028 | U6: =SUM(2000/68)*H6 -> 200.3 | X6: =SUM(S6:W6) -> 4775.7028 | Y6: =SUM(11085/68)*H6 -> 1110.1627 | AA6: =SUM(77.38/68)*H6 -> 7.749607 | AB6: =SUM(Y6:AA6) -> 1117.9124 | AC6: 7.3 | AD6: =SUM(AB6*AC6) -> 8160.7602 | AE6: =SUM(X6+AD6) -> 12936.463 | AF6: =SUM(P6-AE6) -> 3083.947
C7: 241106000050 | D7: 45616 | E7: 黄颖 | F7: ying | G7: Sunday Adelena | H7: 0.6913 | I7: 774 | J7: 3860.58 | P7: =SUBTOTAL(9,J7) -> 3860.58 | S7: =SUM(45685.5/68)*H7 -> 464.44686 | U7: =SUM(2000/68)*H7 -> 20.332353 | V7: 150 | X7: =SUM(S7:W7) -> 634.77921 | Y7: =SUM(11085/68)*H7 -> 112.69207 | AA7: =SUM(77.38/68)*H7 -> 0.78665874 | AB7: =SUM(Y7:AA7) -> 113.47872 | AC7: 7.3 | AD7: =SUM(AB7*AC7) -> 828.39469 | AE7: =SUM(X7+AD7) -> 1463.1739 | AF7: =SUM(P7-AE7) -> 2397.4061
C8: 241106000051 | D8: 45616 | E8: 黄颖 | F8: ying | G8: Sunday Adelena | H8: 0.4698 | I8: 547 | J8: 1670.3 | P8: =SUBTOTAL(9,J8) -> 1670.3 | S8: =SUM(45685.5/68)*H8 -> 315.63306 | U8: =SUM(2000/68)*H8 -> 13.817647 | X8: =SUM(S8:W8) -> 329.4507 | Y8: =SUM(11085/68)*H8 -> 76.584309 | AA8: =SUM(77.38/68)*H8 -> 0.53460476 | AB8: =SUM(Y8:AA8) -> 77.118914 | AC8: 7.3 | AD8: =SUM(AB8*AC8) -> 562.96807 | AE8: =SUM(X8+AD8) -> 892.41877 | AF8: =SUM(P8-AE8) -> 777.88123
C9: 241113000044 | D9: 45616 | E9: 罗珮文 | F9: Shirley | G9: Yusky | H9: 2.0156 | I9: 301 | K9: 829711.92 | M9: =SUM(K9/N9) -> 1608 | N9: 515.99 | O9: 7.3 | P9: =SUM(N9*O9) -> 3766.727 | S9: =SUM(45685.5/68)*H9 -> 1354.172 | U9: =SUM(2000/68)*H9 -> 59.282353 | X9: =SUM(S9:W9) -> 1413.4543 | Y9: =SUM(11085/68)*H9 -> 328.57244 | AA9: =SUM(77.38/68)*H9 -> 2.2936342 | AB9: =SUM(Y9:AA9) -> 330.86608 | AC9: 7.3 | AD9: =SUM(AB9*AC9) -> 2415.3224 | AE9: =SUM(X9+AD9) -> 3828.7767 | AF9: =SUM(P9-AE9) -> -62.049671
C10: 241114000013 | D10: 45616 | E10: 罗珮文 | F10: Shirley | G10: Yusky | H10: 0.0902 | I10: 76 | K10: 37176.96 | M10: =SUM(K10/N10) -> 1608 | N10: 23.12 | O10: 7.3 | P10: =SUM(N10*O10) -> 168.776 | S10: =SUM(45685.5/68)*H10 -> 60.600472 | U10: =SUM(2000/68)*H10 -> 2.6529412 | X10: =SUM(S10:W10) -> 63.253413 | Y10: =SUM(11085/68)*H10 -> 14.703926 | AA10: =SUM(77.38/68)*H10 -> 0.10264229 | AB10: =SUM(Y10:AA10) -> 14.806569 | AC10: 7.3 | AD10: =SUM(AB10*AC10) -> 108.08795 | AE10: =SUM(X10+AD10) -> 171.34137 | AF10: =SUM(P10-AE10) -> -2.5653652
C11: 241114000027 | D11: 45616 | E11: 吕沛霖 | F11: 喵喵速运-Layne | G11: Abdulsheldu | H11: 7.3094 | I11: 4250 | K11: 3823031.5 | M11: =SUM(K11/N11) -> 1663.2 | N11: 2298.6 | O11: 7.3 | P11: =SUM(N11*O11) -> 16779.78 | S11: =SUM(45685.5/68)*H11 -> 4910.7881 | U11: =SUM(2000/68)*H11 -> 214.98235 | X11: =SUM(S11:W11) -> 5125.7705 | Y11: =SUM(11085/68)*H11 -> 1191.5397 | Z11: 97.22 | AA11: =SUM(77.38/68)*H11 -> 8.3176672 | AB11: =SUM(Y11:AA11) -> 1297.0774 | AC11: 7.3 | AD11: =SUM(AB11*AC11) -> 9468.6647 | AE11: =SUM(X11+AD11) -> 14594.435 | AF11: =SUM(P11-AE11) -> 2185.3448
C12: 241115000042 | D12: 45616 | E12: 黄颖 | F12: ying | G12: MISS Huang | H12: 2.5805 | I12: 1066 | K12: 1255187.8 | M12: =SUM(K12/N12) -> 1706.7169 | N12: 735.43994 | O12: 7.27 | P12: =SUM(N12*O12) -> 5346.6484 | S12: =SUM(45685.5/68)*H12 -> 1733.6975 | U12: =SUM(2000/68)*H12 -> 75.897059 | X12: =SUM(S12:W12) -> 1809.5946 | Y12: =SUM(11085/68)*H12 -> 420.65945 | AA12: =SUM(77.38/68)*H12 -> 2.9364572 | AB12: =SUM(Y12:AA12) -> 423.59591 | AC12: 7.3 | AD12: =SUM(AB12*AC12) -> 3092.2501 | AE12: =SUM(X12+AD12) -> 4901.8447 | AF12: =SUM(P12-AE12) -> 444.80365
C13: 241118000051 | D13: 45616 | E13: 黄颖 | F13: ying | G13: wuchengxing | H13: 0.2898 | I13: 30 | J13: 639.5 | P13: =SUBTOTAL(9,J13) -> 639.5 | S13: =SUM(45685.5/68)*H13 -> 194.70085 | U13: =SUM(2000/68)*H13 -> 8.5235294 | X13: =SUM(S13:W13) -> 203.22438 | Y13: =SUM(11085/68)*H13 -> 47.241662 | AA13: =SUM(77.38/68)*H13 -> 0.32977535 | AB13: =SUM(Y13:AA13) -> 47.571437 | AC13: 7.3 | AD13: =SUM(AB13*AC13) -> 347.27149 | AE13: =SUM(X13+AD13) -> 550.49587 | AF13: =SUM(P13-AE13) -> 89.004128
C14: 241118000062 | D14: 45616 | E14: 罗珮文 | F14: Shirley | G14: Yusky | H14: 0.3791 | I14: 53 | K14: 156056.4 | M14: =SUM(K14/N14) -> 1608 | N14: 97.05 | O14: 7.3 | P14: =SUM(N14*O14) -> 708.465 | S14: =SUM(45685.5/68)*H14 -> 254.69666 | U14: =SUM(2000/68)*H14 -> 11.15 | X14: =SUM(S14:W14) -> 265.84666 | Y14: =SUM(11085/68)*H14 -> 61.798875 | AA14: =SUM(77.38/68)*H14 -> 0.4313935 | AB14: =SUM(Y14:AA14) -> 62.230269 | AC14: 7.3 | AD14: =SUM(AB14*AC14) -> 454.28096 | AE14: =SUM(X14+AD14) -> 720.12762 | AF14: =SUM(P14-AE14) -> -11.662623
C15: 241119000022 | D15: 45616 | E15: 罗珮文 | F15: Shirley | G15: Yusky | H15: 2.3578 | I15: 388 | K15: 970588.8 | M15: =SUM(K15/N15) -> 1608 | N15: 603.6 | O15: 7.3 | P15: =SUM(N15*O15) -> 4406.28 | S15: =SUM(45685.5/68)*H15 -> 1584.0775 | U15: =SUM(2000/68)*H15 -> 69.347059 | X15: =SUM(S15:W15) -> 1653.4246 | Y15: =SUM(11085/68)*H15 -> 384.35607 | AA15: =SUM(77.38/68)*H15 -> 2.6830377 | AB15: =SUM(Y15:AA15) -> 387.03911 | AC15: 7.3 | AD15: =SUM(AB15*AC15) -> 2825.3855 | AE15: =SUM(X15+AD15) -> 4478.8101 | AF15: =SUM(P15-AE15) -> -72.530099
C16: 241113000043 | D16: 45616 | E16: 罗珮文 | F16: Shirley | G16: Yusky | H16: 7.2261 | I16: 7740 | K16: 2974607 | M16: =SUM(K16/N16) -> 1608 | N16: 1849.88 | O16: 7.3 | P16: =SUM(N16*O16) -> 13504.124 | S16: =SUM(45685.5/68)*H16 -> 4854.8234 | U16: =SUM(2000/68)*H16 -> 212.53235 | X16: =SUM(S16:W16) -> 5067.3558 | Y16: =SUM(11085/68)*H16 -> 1177.9606 | AA16: =SUM(77.38/68)*H16 -> 8.2228767 | AB16: =SUM(Y16:AA16) -> 1186.1834 | AC16: 7.3 | AD16: =SUM(AB16*AC16) -> 8659.1391 | AE16: =SUM(X16+AD16) -> 13726.495 | AF16: =SUM(P16-AE16) -> -222.37089
C17: 241118000049 | D17: 45616 | E17: Sam.Pao | F17: Sam.Pao | G17: Mr LiuQiSheng | H17: 18.8558 | I17: 3372 | J17: 41577.26 | P17: =SUBTOTAL(9,J17) -> 41577.26 | S17: =SUM(45685.5/68)*H17 -> 12668.186 | U17: =SUM(2000/68)*H17 -> 554.58235 | X17: =SUM(S17:W17) -> 13222.768 | Y17: =SUM(11085/68)*H17 -> 3073.7727 | AA17: =SUM(77.38/68)*H17 -> 21.456791 | AB17: =SUM(Y17:AA17) -> 3095.2295 | AC17: 7.3 | AD17: =SUM(AB17*AC17) -> 22595.175 | AE17: =SUM(X17+AD17) -> 35817.944 | AF17: =SUM(P17-AE17) -> 5759.3164
C18: 241120000022 | D18: 45616 | E18: 罗珮文 | F18: Shirley | G18: SKY JET | H18: 24.63 | I18: 3402 | J18: 38444.97 | P18: =SUBTOTAL(9,J18) -> 38444.97 | S18: =SUM(45685.5/68)*H18 -> 16547.557 | U18: =SUM(2000/68)*H18 -> 724.41176 | X18: =SUM(S18:W18) -> 17271.969 | Y18: =SUM(11085/68)*H18 -> 4015.0522 | AA18: =SUM(77.38/68)*H18 -> 28.027491 | AB18: =SUM(Y18:AA18) -> 4043.0797 | AC18: 7.3 | AD18: =SUM(AB18*AC18) -> 29514.482 | AE18: =SUM(X18+AD18) -> 46786.45 | AF18: =SUM(P18-AE18) -> -8341.4804
A19: 合计 | J19: =SUM(J4:J4) -> 0 | N19: =SUM(N4:N4) -> 0 | P19: =SUM(P4:P4) -> 0 | Q19: =SUM(Q4:Q4) -> 0 | X19: =SUM(X4:X4) -> 0 | AD19: =SUM(AD4:AD4) -> 0 | AF19: =SUM(AF4:AF18) -> 6096.0564

Sheet JOB120367
A1: 2024年11月份LOS毛利表（海运）
A2: PSL表 | B2: 体积cbm | C2: 77.0138
A3: JOB | B3: 集装编号 | C3: 运单编号 | D3: 日期 | E3: 业务 | F3: 发货人 | G3: 收货人 | H3: 计费体积 | I3: 计费重量 | J3: 应 收 | Q3: 总应收 | R3: 起 运 港 成 本 | W3: 代垫运费 | X3: 起运港成本 合计 | Y3: 目的港成本 | AE3: 总支出 | AF3: 利润
J4: 应收RMB | K4: LOS Income(NGN)收到(奈拉) | L4: LOS 收到USD | M4: 美元汇率 dollar currency rate | N4: 应收 到付款USD | O4: 汇率 | P4: 人民币 | R4: 代理商 | S4: 运费+出口报关费 | T4: 提货费 | U4: 装卸费 | V4: 包装费 | Y4: 进口报关费 | Z4: 到门配送费 | AA4: 转运费 | AB4: 目的港支出 | AC4: 汇率 | AD4: 人民币 | AE4: 起运港+目的港
A5: JOB120367 | B5: COLL004308 | C5: 241107000009 | D5: 45617 | E5: 黄颖 | F5: ying | G5: MISS Huang | H5: 3.597 | I5: 2893 | J5: 8527.49 | P5: =SUBTOTAL(9,J5) -> 8527.49 | Q5: =SUM(P5:P19) -> 149572.52 | R5: 登凯=43386.5 赛捷=600 拖车费=1670 杂费=75 过磅费=57 | S5: =SUM(45788.5/68)*H5 -> 2422.077 | U5: =SUM(1300/68)*H5 -> 68.766176 | X5: =SUM(S5:W5) -> 2490.8432 | Y5: =SUM(11233/68)*H5 -> 594.19266 | AA5: =SUM(209.95/68)*H5 -> 11.105738 | AB5: =SUM(Y5:AA5) -> 605.2984 | AC5: 7.3 | AD5: =SUM(AB5*AC5) -> 4418.6783 | AE5: =SUM(X5+AD5) -> 6909.5215 | AF5: =SUM(P5-AE5) -> 1617.9685
C6: 241108000020 | D6: 45617 | E6: 黄颖 | F6: ying | G6: shola | H6: 4.4226 | I6: 1416 | J6: 13696 | P6: =SUBTOTAL(9,J6) -> 13696 | S6: =SUM(45788.5/68)*H6 -> 2978.0032 | U6: =SUM(1300/68)*H6 -> 84.549706 | V6: 800 | W6: 80 | X6: =SUM(S6:W6) -> 3942.5529 | Y6: =SUM(11233/68)*H6 -> 730.5745 | Z6: 256.98 | AA6: =SUM(209.95/68)*H6 -> 13.654777 | AB6: =SUM(Y6:AA6) -> 1001.2093 | AC6: 7.3 | AD6: =SUM(AB6*AC6) -> 7308.8277 | AE6: =SUM(X6+AD6) -> 11251.381 | AF6: =SUM(P6-AE6) -> 2444.6194
C7: 241113000043 | D7: 45617 | E7: 罗珮文 | F7: Shirley | G7: Yusky | H7: 4.8174 | I7: 5160 | K7: 1944345.4 | M7: =SUM(K7/N7) -> 1608 | N7: 1209.17 | O7: 7.3 | P7: =SUM(N7*O7) -> 8826.941 | S7: =SUM(45788.5/68)*H7 -> 3243.8459 | U7: =SUM(1300/68)*H7 -> 92.097353 | X7: =SUM(S7:W7) -> 3335.9432 | Y7: =SUM(11233/68)*H7 -> 795.79197 | AA7: =SUM(209.95/68)*H7 -> 14.873722 | AB7: =SUM(Y7:AA7) -> 810.6657 | AC7: 7.3 | AD7: =SUM(AB7*AC7) -> 5917.8596 | AE7: =SUM(X7+AD7) -> 9253.8028 | AF7: =SUM(P7-AE7) -> -426.86181
C8: 241113000045 | D8: 45617 | E8: 罗珮文 | F8: Shirley | G8: Yusky | H8: 0.164 | I8: 134 | K8: 66217.44 | M8: =SUM(K8/N8) -> 1608 | N8: 41.18 | O8: 7.3 | P8: =SUM(N8*O8) -> 300.614 | S8: =SUM(45788.5/68)*H8 -> 110.43109 | U8: =SUM(1300/68)*H8 -> 3.1352941 | X8: =SUM(S8:W8) -> 113.56638 | Y8: =SUM(11233/68)*H8 -> 27.091353 | AA8: =SUM(209.95/68)*H8 -> 0.50635 | AB8: =SUM(Y8:AA8) -> 27.597703 | AC8: 7.3 | AD8: =SUM(AB8*AC8) -> 201.46323 | AE8: =SUM(X8+AD8) -> 315.02961 | AF8: =SUM(P8-AE8) -> -14.415614
C9: 241114000012 | D9: 45617 | E9: 罗珮文 | F9: Shirley | G9: Yusky | H9: 4.9075 | I9: 496 | K9: 1980702.2 | M9: =SUM(K9/N9) -> 1608 | N9: 1231.78 | O9: 7.3 | P9: =SUM(N9*O9) -> 8991.994 | S9: =SUM(45788.5/68)*H9 -> 3304.5156 | U9: =SUM(1300/68)*H9 -> 93.819853 | X9: =SUM(S9:W9) -> 3398.3355 | Y9: =SUM(11233/68)*H9 -> 810.6757 | AA9: =SUM(209.95/68)*H9 -> 15.151906 | AB9: =SUM(Y9:AA9) -> 825.8276 | AC9: 7.3 | AD9: =SUM(AB9*AC9) -> 6028.5415 | AE9: =SUM(X9+AD9) -> 9426.877 | AF9: =SUM(P9-AE9) -> -434.88301
C10: 241118000049 | D10: 45617 | E10: Sam.Pao | F10: Sam.Pao | G10: Mr LiuQiSheng | H10: 18.8558 | I10: 3470 | J10: 41577.26 | P10: =SUBTOTAL(9,J10) -> 41577.26 | S10: =SUM(45788.5/68)*H10 -> 12696.747 | U10: =SUM(1300/68)*H10 -> 360.47853 | X10: =SUM(S10:W10) -> 13057.226 | Y10: =SUM(11233/68)*H10 -> 3114.8118 | Z10: 1481.48 | AA10: =SUM(209.95/68)*H10 -> 58.217283 | AB10: =SUM(Y10:AA10) -> 4654.5091 | AC10: 7.3 | AD10: =SUM(AB10*AC10) -> 33977.916 | AE10: =SUM(X10+AD10) -> 47035.142 | AF10: =SUM(P10-AE10) -> -5457.8818
C11: 241023000034 | D11: 45617 | E11: Sam.Pao | F11: Sam.Pao | G11: Nick Wang | H11: 0.535 | I11: 223 | J11: 1547 | P11: =SUBTOTAL(9,J11) -> 1547 | S11: =SUM(45788.5/68)*H11 -> 360.24776 | U11: =SUM(1300/68)*H11 -> 10.227941 | X11: =SUM(S11:W11) -> 370.4757 | Y11: =SUM(11233/68)*H11 -> 88.377279 | AA11: =SUM(209.95/68)*H11 -> 1.6518125 | AB11: =SUM(Y11:AA11) -> 90.029092 | AC11: 7.3 | AD11: =SUM(AB11*AC11) -> 657.21237 | AE11: =SUM(X11+AD11) -> 1027.6881 | AF11: =SUM(P11-AE11) -> 519.31193
C12: 241115000013 | D12: 45617 | E12: Sam.Pao | F12: Sam.Pao | G12: ChenGaoHong | H12: 0.0579 | I12: 37 | J12: 123 | P12: =SUBTOTAL(9,J12) -> 123 | S12: =SUM(45788.5/68)*H12 -> 38.987561 | U12: =SUM(1300/68)*H12 -> 1.1069118 | X12: =SUM(S12:W12) -> 40.094473 | Y12: =SUM(11233/68)*H12 -> 9.5645691 | AA12: =SUM(209.95/68)*H12 -> 0.17876625 | AB12: =SUM(Y12:AA12) -> 9.7433354 | AC12: 7.3 | AD12: =SUM(AB12*AC12) -> 71.126348 | AE12: =SUM(X12+AD12) -> 111.22082 | AF12: =SUM(P12-AE12) -> 11.779179
C13: 241118000061 | D13: 45617 | E13: 罗珮文 | F13: Shirley | G13: Yusky | H13: 0.2475 | I13: 27 | K13: 99937.2 | M13: =SUM(K13/N13) -> 1608 | N13: 62.15 | O13: 7.3 | P13: =SUM(N13*O13) -> 453.695 | S13: =SUM(45788.5/68)*H13 -> 166.65667 | U13: =SUM(1300/68)*H13 -> 4.7316176 | X13: =SUM(S13:W13) -> 171.38829 | Y13: =SUM(11233/68)*H13 -> 40.884816 | AA13: =SUM(209.95/68)*H13 -> 0.76415625 | AB13: =SUM(Y13:AA13) -> 41.648972 | AC13: 7.3 | AD13: =SUM(AB13*AC13) -> 304.0375 | AE13: =SUM(X13+AD13) -> 475.42579 | AF13: =SUM(P13-AE13) -> -21.730789
C14: 241118000064 | D14: 45617 | E14: 罗珮文 | F14: Shirley | G14: Yusky | H14: 0.0647 | I14: 9 | K14: 26097.84 | M14: =SUM(K14/N14) -> 1608 | N14: 16.23 | O14: 7.3 | P14: =SUM(N14*O14) -> 118.479 | S14: =SUM(45788.5/68)*H14 -> 43.566411 | U14: =SUM(1300/68)*H14 -> 1.2369118 | X14: =SUM(S14:W14) -> 44.803323 | Y14: =SUM(11233/68)*H14 -> 10.687869 | AA14: =SUM(209.95/68)*H14 -> 0.19976125 | AB14: =SUM(Y14:AA14) -> 10.88763 | AC14: 7.3 | AD14: =SUM(AB14*AC14) -> 79.479702 | AE14: =SUM(X14+AD14) -> 124.28302 | AF14: =SUM(P14-AE14) -> -5.8040245
C15: 241118000074 | D15: 45617 | E15: 陆总 | F15: 陆梓龙 | G15: jizong | H15: 4.524 | I15: 2048 | J15: 10687.32 | P15: =SUBTOTAL(9,J15) -> 10687.32 | S15: =SUM(45788.5/68)*H15 -> 3046.282 | U15: =SUM(1300/68)*H15 -> 86.488235 | X15: =SUM(S15:W15) -> 3132.7702 | Y15: =SUM(11233/68)*H15 -> 747.32488 | Z15: 262.87 | AA15: =SUM(209.95/68)*H15 -> 13.96785 | AB15: =SUM(Y15:AA15) -> 1024.1627 | AC15: 7.3 | AD15: =SUM(AB15*AC15) -> 7476.3879 | AE15: =SUM(X15+AD15) -> 10609.158 | AF15: =SUM(P15-AE15) -> 78.161848
C16: 241119000018 | D16: 45617 | E16: 罗珮文 | F16: Shirley | G16: Yusky | H16: 0.3528 | I16: 60 | K16: 142388.4 | M16: =SUM(K16/N16) -> 1608 | N16: 88.55 | O16: 7.3 | P16: =SUM(N16*O16) -> 646.415 | S16: =SUM(45788.5/68)*H16 -> 237.56151 | U16: =SUM(1300/68)*H16 -> 6.7447059 | X16: =SUM(S16:W16) -> 244.30622 | Y16: =SUM(11233/68)*H16 -> 58.279447 | AA16: =SUM(209.95/68)*H16 -> 1.08927 | AB16: =SUM(Y16:AA16) -> 59.368717 | AC16: 7.3 | AD16: =SUM(AB16*AC16) -> 433.39163 | AE16: =SUM(X16+AD16) -> 677.69785 | AF16: =SUM(P16-AE16) -> -31.282852
C17: 241119000019 | D17: 45617 | E17: 罗珮文 | F17: Shirley | G17: Yusky | H17: 0.8465 | I17: 76 | K17: 341667.84 | M17: =SUM(K17/N17) -> 1608 | N17: 212.48 | O17: 7.3 | P17: =SUM(N17*O17) -> 1551.104 | S17: =SUM(45788.5/68)*H17 -> 569.99949 | U17: =SUM(1300/68)*H17 -> 16.183088 | X17: =SUM(S17:W17) -> 586.18258 | Y17: =SUM(11233/68)*H17 -> 139.83433 | AA17: =SUM(209.95/68)*H17 -> 2.6135688 | AB17: =SUM(Y17:AA17) -> 142.4479 | AC17: 7.3 | AD17: =SUM(AB17*AC17) -> 1039.8697 | AE17: =SUM(X17+AD17) -> 1626.0522 | AF17: =SUM(P17-AE17) -> -74.948245
C18: 241119000020 | D18: 45617 | E18: 罗珮文 | F18: Shirley | G18: Yusky | H18: 0.1709 | I18: 14 | K18: 68967.12 | M18: =SUM(K18/N18) -> 1608 | N18: 42.89 | O18: 7.3 | P18: =SUM(N18*O18) -> 313.097 | S18: =SUM(45788.5/68)*H18 -> 115.07727 | U18: =SUM(1300/68)*H18 -> 3.2672059 | X18: =SUM(S18:W18) -> 118.34448 | Y18: =SUM(11233/68)*H18 -> 28.231172 | AA18: =SUM(209.95/68)*H18 -> 0.52765375 | AB18: =SUM(Y18:AA18) -> 28.758826 | AC18: 7.3 | AD18: =SUM(AB18*AC18) -> 209.93943 | AE18: =SUM(X18+AD18) -> 328.28391 | AF18: =SUM(P18-AE18) -> -15.186909
C19: 241120000030 | D19: 45617 | E19: 罗珮文 | F19: Shirley | G19: SKY JET | H19: 33.45 | I19: 4005 | J19: 52212.11 | P19: =SUBTOTAL(9,J19) -> 52212.11 | S19: =SUM(45788.5/68)*H19 -> 22523.902 | U19: =SUM(1300/68)*H19 -> 639.48529 | X19: =SUM(S19:W19) -> 23163.387 | Y19: =SUM(11233/68)*H19 -> 5525.6449 | AA19: =SUM(209.95/68)*H19 -> 103.27688 | AB19: =SUM(Y19:AA19) -> 5628.9217 | AC19: 7.3 | AD19: =SUM(AB19*AC19) -> 41091.129 | AE19: =SUM(X19+AD19) -> 64254.516 | AF19: =SUM(P19-AE19) -> -12042.406
A20: 合计 | J20: =SUM(J4:J4) -> 0 | N20: =SUM(N4:N4) -> 0 | P20: =SUM(P4:P4) -> 0 | Q20: =SUM(Q4:Q4) -> 0 | X20: =SUM(X4:X4) -> 0 | AD20: =SUM(AD4:AD4) -> 0 | AF20: =SUM(AF4:AF19) -> -13853.56

Sheet JOB120368
A1: 2024年11月份LOS毛利表（海运）
A2: PSL表 | B2: 体积cbm | C2: 75.228
A3: JOB | B3: 集装编号 | C3: 运单编号 | D3: 日期 | E3: 业务 | F3: 发货人 | G3: 收货人 | H3: 计费体积 | I3: 计费重量 | J3: 应 收 | Q3: 总应收 | R3: 起 运 港 成 本 | W3: 代垫运费 | X3: 起运港成本 合计 | Y3: 目的港成本 | AE3: 总支出 | AF3: 利润
J4: 应收RMB | K4: LOS Income(NGN)收到(奈拉) | L4: LOS 收到USD | M4: 美元汇率 dollar currency rate | N4: 应收 到付款USD | O4: 汇率 | P4: 人民币 | R4: 代理商 | S4: 运费+出口报关费 | T4: 提货费 | U4: 装卸费 | V4: 包装费 | Y4: 进口报关费 | Z4: 到门配送费 | AA4: 转运费 | AB4: 目的港支出 | AC4: 汇率 | AD4: 人民币 | AE4: 起运港+目的港
A5: JOB120368 | B5: COLL004310 | C5: 241116000004 | D5: 45623 | E5: 黄颖 | F5: ying | G5: wangmuma | H5: 0.076 | I5: 13 | J5: 250 | P5: =SUBTOTAL(9,J5) -> 250 | Q5: =SUM(P5:P25) -> 157301.51 | R5: 登凯=43941.65 创泽=1300 拖车费=1670 杂费=63 过磅费=59 | S5: =SUM(47033.65/68)*H5 -> 52.567021 | U5: =SUM(1900/68)*H5 -> 2.1235294 | X5: =SUM(S5:W5) -> 54.69055 | Y5: =SUM(11081/68)*H5 -> 12.384647 | Z5: 59.52 | AA5: =SUM(53.57/68)*H5 -> 0.059872353 | AB5: =SUM(Y5:AA5) -> 71.964519 | AC5: 7.3 | AD5: =SUM(AB5*AC5) -> 525.34099 | AE5: =SUM(X5+AD5) -> 580.03154 | AF5: =SUM(P5-AE5) -> -330.03154
C6: 241118000058 | D6: 45623 | E6: 罗珮文 | F6: Shirley | G6: Yusky | H6: 0.5167 | I6: 71 | K6: 214362.48 | M6: =SUM(K6/N6) -> 1608 | N6: 133.31 | O6: 7.3 | P6: =SUM(N6*O6) -> 973.163 | S6: =SUM(47033.65/68)*H6 -> 357.38657 | U6: =SUM(1900/68)*H6 -> 14.437206 | X6: =SUM(S6:W6) -> 371.82378 | Y6: =SUM(11081/68)*H6 -> 84.199304 | AA6: =SUM(53.57/68)*H6 -> 0.40705322 | AB6: =SUM(Y6:AA6) -> 84.606358 | AC6: 7.3 | AD6: =SUM(AB6*AC6) -> 617.62641 | AE6: =SUM(X6+AD6) -> 989.45019 | AF6: =SUM(P6-AE6) -> -16.287189
C7: 241118000059 | D7: 45623 | E7: 罗珮文 | F7: Shirley | G7: Yusky | H7: 0.8256 | I7: 31 | K7: 342504 | M7: =SUM(K7/N7) -> 1608 | N7: 213 | O7: 7.3 | P7: =SUM(N7*O7) -> 1554.9 | S7: =SUM(47033.65/68)*H7 -> 571.04384 | U7: =SUM(1900/68)*H7 -> 23.068235 | X7: =SUM(S7:W7) -> 594.11208 | Y7: =SUM(11081/68)*H7 -> 134.53638 | AA7: =SUM(53.57/68)*H7 -> 0.65040282 | AB7: =SUM(Y7:AA7) -> 135.18678 | AC7: 7.3 | AD7: =SUM(AB7*AC7) -> 986.86349 | AE7: =SUM(X7+AD7) -> 1580.9756 | AF7: =SUM(P7-AE7) -> -26.075569
C8: 241118000060 | D8: 45623 | E8: 罗珮文 | F8: Shirley | G8: Yusky | H8: 0.132 | I8: 50 | K8: 54768.48 | M8: =SUM(K8/N8) -> 1608 | N8: 34.06 | O8: 7.3 | P8: =SUM(N8*O8) -> 248.638 | S8: =SUM(47033.65/68)*H8 -> 91.300615 | U8: =SUM(1900/68)*H8 -> 3.6882353 | X8: =SUM(S8:W8) -> 94.98885 | Y8: =SUM(11081/68)*H8 -> 21.510176 | AA8: =SUM(53.57/68)*H8 -> 0.10398882 | AB8: =SUM(Y8:AA8) -> 21.614165 | AC8: 7.3 | AD8: =SUM(AB8*AC8) -> 157.78341 | AE8: =SUM(X8+AD8) -> 252.77226 | AF8: =SUM(P8-AE8) -> -4.1342566
C9: 241118000065 | D9: 45623 | E9: 罗珮文 | F9: Shirley | G9: Yusky | H9: 1.2613 | I9: 266 | K9: 523146.72 | M9: =SUM(K9/N9) -> 1608 | N9: 325.34 | O9: 7.3 | P9: =SUM(N9*O9) -> 2374.982 | S9: =SUM(47033.65/68)*H9 -> 872.40504 | U9: =SUM(1900/68)*H9 -> 35.242206 | X9: =SUM(S9:W9) -> 907.64725 | Y9: =SUM(11081/68)*H9 -> 205.53625 | AA9: =SUM(53.57/68)*H9 -> 0.99364472 | AB9: =SUM(Y9:AA9) -> 206.5299 | AC9: 7.3 | AD9: =SUM(AB9*AC9) -> 1507.6683 | AE9: =SUM(X9+AD9) -> 2415.3155 | AF9: =SUM(P9-AE9) -> -40.33351
C10: 241118000067 | D10: 45623 | E10: 罗珮文 | F10: Shirley | G10: Yusky | H10: 0.2938 | I10: 56 | K10: 121886.4 | M10: =SUM(K10/N10) -> 1608 | N10: 75.8 | O10: 7.3 | P10: =SUM(N10*O10) -> 553.34 | S10: =SUM(47033.65/68)*H10 -> 203.21303 | U10: =SUM(1900/68)*H10 -> 8.2091176 | X10: =SUM(S10:W10) -> 211.42215 | Y10: =SUM(11081/68)*H10 -> 47.876438 | AA10: =SUM(53.57/68)*H10 -> 0.23145391 | AB10: =SUM(Y10:AA10) -> 48.107892 | AC10: 7.3 | AD10: =SUM(AB10*AC10) -> 351.18761 | AE10: =SUM(X10+AD10) -> 562.60977 | AF10: =SUM(P10-AE10) -> -9.2697652
C11: 241127000014 | D11: 45623 | E11: 罗珮文 | F11: Shirley | G11: Yusky | H11: 0.8732 | I11: 115 | K11: 362266.32 | M11: =SUM(K11/N11) -> 1608 | N11: 225.29 | O11: 7.3 | P11: =SUM(N11*O11) -> 1644.617 | S11: =SUM(47033.65/68)*H11 -> 603.9674 | U11: =SUM(1900/68)*H11 -> 24.398235 | X11: =SUM(S11:W11) -> 628.36563 | Y11: =SUM(11081/68)*H11 -> 142.29308 | AA11: =SUM(53.57/68)*H11 -> 0.68790182 | AB11: =SUM(Y11:AA11) -> 142.98098 | AC11: 7.3 | AD11: =SUM(AB11*AC11) -> 1043.7611 | AE11: =SUM(X11+AD11) -> 1672.1268 | AF11: =SUM(P11-AE11) -> -27.509777
C12: 241119000012 | D12: 45623 | E12: 朱小飞 | F12: Isabel Zhu | G12: Halifa Success | H12: 0.9901 | I12: 222 | J12: 2046.8 | P12: =SUBTOTAL(9,J12) -> 2046.8 | S12: =SUM(47033.65/68)*H12 -> 684.82378 | U12: =SUM(1900/68)*H12 -> 27.664559 | X12: =SUM(S12:W12) -> 712.48834 | Y12: =SUM(11081/68)*H12 -> 161.34262 | AA12: =SUM(53.57/68)*H12 -> 0.77999496 | AB12: =SUM(Y12:AA12) -> 162.12261 | AC12: 7.3 | AD12: =SUM(AB12*AC12) -> 1183.4951 | AE12: =SUM(X12+AD12) -> 1895.9834 | AF12: =SUM(P12-AE12) -> 150.81658
C13: 241119000021 | D13: 45623 | E13: 罗珮文 | F13: Shirley | G13: Yusky | H13: 1.3774 | I13: 231 | K13: 571274.16 | M13: =SUM(K13/N13) -> 1608 | N13: 355.27 | O13: 7.3 | P13: =SUM(N13*O13) -> 2593.471 | S13: =SUM(47033.65/68)*H13 -> 952.70808 | U13: =SUM(1900/68)*H13 -> 38.486176 | X13: =SUM(S13:W13) -> 991.19426 | Y13: =SUM(11081/68)*H13 -> 224.45543 | AA13: =SUM(53.57/68)*H13 -> 1.0851076 | AB13: =SUM(Y13:AA13) -> 225.54054 | AC13: 7.3 | AD13: =SUM(AB13*AC13) -> 1646.4459 | AE13: =SUM(X13+AD13) -> 2637.6402 | AF13: =SUM(P13-AE13) -> -44.169199
C14: 241119000027 | D14: 45623 | E14: 黄颖 | F14: ying | G14: wuchengxing | H14: 0.0148 | I14: 6 | J14: 220 | P14: =SUBTOTAL(9,J14) -> 220 | S14: =SUM(47033.65/68)*H14 -> 10.236736 | U14: =SUM(1900/68)*H14 -> 0.41352941 | X14: =SUM(S14:W14) -> 10.650265 | Y14: =SUM(11081/68)*H14 -> 2.4117471 | AA14: =SUM(53.57/68)*H14 -> 0.011659353 | AB14: =SUM(Y14:AA14) -> 2.4234064 | AC14: 7.3 | AD14: =SUM(AB14*AC14) -> 17.690867 | AE14: =SUM(X14+AD14) -> 28.341132 | AF14: =SUM(P14-AE14) -> 191.65887
C15: 241120000029 | D15: 45623 | E15: Sam.Pao | F15: Sam.Pao | G15: Nick Wang | H15: 1.1485 | I15: 243 | J15: 4092.46 | P15: =SUBTOTAL(9,J15) -> 4092.46 | S15: =SUM(47033.65/68)*H15 -> 794.38452 | U15: =SUM(1900/68)*H15 -> 32.090441 | V15: 230 | W15: 408 | X15: =SUM(S15:W15) -> 1464.475 | Y15: =SUM(11081/68)*H15 -> 187.15483 | Z15: 67.46 | AA15: =SUM(53.57/68)*H15 -> 0.90478154 | AB15: =SUM(Y15:AA15) -> 255.51961 | AC15: 7.3 | AD15: =SUM(AB15*AC15) -> 1865.2932 | AE15: =SUM(X15+AD15) -> 3329.7681 | AF15: =SUM(P15-AE15) -> 762.69187
C16: 241121000012 | D16: 45623 | E16: Sam.Pao | F16: Sam.Pao | G16: AiGeLi | H16: 21.5631 | I16: 10414 | J16: 62286 | P16: =SUBTOTAL(9,J16) -> 62286 | S16: =SUM(47033.65/68)*H16 -> 14914.578 | U16: =SUM(1900/68)*H16 -> 602.49838 | V16: 800 | X16: =SUM(S16:W16) -> 16317.076 | Y16: =SUM(11081/68)*H16 -> 3513.834 | Z16: 902.53 | AA16: =SUM(53.57/68)*H16 -> 16.987283 | AB16: =SUM(Y16:AA16) -> 4433.3513 | AC16: 7.3 | AD16: =SUM(AB16*AC16) -> 32363.464 | AE16: =SUM(X16+AD16) -> 48680.541 | AF16: =SUM(P16-AE16) -> 13605.459
C17: 241121000016 | D17: 45623 | E17: 吕沛霖 | F17: 喵喵速运-Layne | G17: Hu Hai Liang | H17: 2.2928 | I17: 1066 | K17: 1070400 | M17: =SUM(K17/N17) -> 1600 | N17: 669 | O17: 7.27 | P17: =SUM(N17*O17) -> 4863.63 | S17: =SUM(47033.65/68)*H17 -> 1585.864 | U17: =SUM(1900/68)*H17 -> 64.063529 | X17: =SUM(S17:W17) -> 1649.9275 | Y17: =SUM(11081/68)*H17 -> 373.62525 | AA17: =SUM(53.57/68)*H17 -> 1.8062544 | AB17: =SUM(Y17:AA17) -> 375.4315 | AC17: 7.3 | AD17: =SUM(AB17*AC17) -> 2740.65 | AE17: =SUM(X17+AD17) -> 4390.5775 | AF17: =SUM(P17-AE17) -> 473.0525
C18: 241124000008 | D18: 45623 | E18: 朱小飞 | F18: Isabel Zhu | G18: Halifa Success | H18: 3.0541 | I18: 317 | J18: 6242.74 | P18: =SUBTOTAL(9,J18) -> 6242.74 | S18: =SUM(47033.65/68)*H18 -> 2112.4334 | U18: =SUM(1900/68)*H18 -> 85.335147 | X18: =SUM(S18:W18) -> 2197.7685 | Y18: =SUM(11081/68)*H18 -> 497.68356 | AA18: =SUM(53.57/68)*H18 -> 2.406002 | AB18: =SUM(Y18:AA18) -> 500.08956 | AC18: 7.3 | AD18: =SUM(AB18*AC18) -> 3650.6538 | AE18: =SUM(X18+AD18) -> 5848.4223 | AF18: =SUM(P18-AE18) -> 394.31766
C19: 241125000029 | D19: 45623 | E19: Bella | F19: Bella Chan | G19: FENG | H19: 0.2641 | I19: 318 | K19: 228967.2 | M19: =SUM(K19/N19) -> 1680.0002 | N19: 136.28998 | O19: 7.3 | P19: =SUM(N19*O19) -> 994.91685 | S19: =SUM(47033.65/68)*H19 -> 182.6704 | U19: =SUM(1900/68)*H19 -> 7.3792647 | X19: =SUM(S19:W19) -> 190.04966 | Y19: =SUM(11081/68)*H19 -> 43.036649 | AA19: =SUM(53.57/68)*H19 -> 0.20805643 | AB19: =SUM(Y19:AA19) -> 43.244705 | AC19: 7.3 | AD19: =SUM(AB19*AC19) -> 315.68635 | AE19: =SUM(X19+AD19) -> 505.73601 | AF19: =SUM(P19-AE19) -> 489.18085
C20: 241125000035 | D20: 45623 | E20: 朱小飞 | F20: Isabel Zhu | G20: Halifa Success | H20: 1.1856 | I20: 142 | J20: 2595.69 | P20: =SUBTOTAL(9,J20) -> 2595.69 | S20: =SUM(47033.65/68)*H20 -> 820.04552 | U20: =SUM(1900/68)*H20 -> 33.127059 | W20: 157.53 | X20: =SUM(S20:W20) -> 1010.7026 | Y20: =SUM(11081/68)*H20 -> 193.20049 | AA20: =SUM(53.57/68)*H20 -> 0.93400871 | AB20: =SUM(Y20:AA20) -> 194.1345 | AC20: 7.3 | AD20: =SUM(AB20*AC20) -> 1417.1819 | AE20: =SUM(X20+AD20) -> 2427.8845 | AF20: =SUM(P20-AE20) -> 167.80555
C21: 241125000066 | D21: 45623 | E21: 无人 | F21: dejare James | G21: James | H21: 0.151 | I21: 45 | K21: 76000 | M21: =SUM(K21/N21) -> 1677.7041 | N21: 45.300003 | O21: 7.2 | P21: =SUM(N21*O21) -> 326.16002 | S21: =SUM(47033.65/68)*H21 -> 104.44237 | U21: =SUM(1900/68)*H21 -> 4.2191176 | X21: =SUM(S21:W21) -> 108.66149 | Y21: =SUM(11081/68)*H21 -> 24.606338 | AA21: =SUM(53.57/68)*H21 -> 0.11895691 | AB21: =SUM(Y21:AA21) -> 24.725295 | AC21: 7.3 | AD21: =SUM(AB21*AC21) -> 180.49465 | AE21: =SUM(X21+AD21) -> 289.15614 | AF21: =SUM(P21-AE21) -> 37.00388
C22: 241126000027 | D22: 45623 | E22: 朱小飞 | F22: Isabel Zhu | G22: Halifa Success | H22: 0.4539 | I22: 85 | J22: 921.06 | P22: =SUBTOTAL(9,J22) -> 921.06 | S22: =SUM(47033.65/68)*H22 -> 313.94961 | U22: =SUM(1900/68)*H22 -> 12.6825 | X22: =SUM(S22:W22) -> 326.63211 | Y22: =SUM(11081/68)*H22 -> 73.965675 | AA22: =SUM(53.57/68)*H22 -> 0.35757975 | AB22: =SUM(Y22:AA22) -> 74.323255 | AC22: 7.3 | AD22: =SUM(AB22*AC22) -> 542.55976 | AE22: =SUM(X22+AD22) -> 869.19187 | AF22: =SUM(P22-AE22) -> 51.868127
C23: 241127000011 | D23: 45623 | E23: 罗珮文 | F23: Shirley | G23: Yusky | H23: 2.5492 | I23: 684 | K23: 1057565.5 | M23: =SUM(K23/N23) -> 1608 | N23: 657.69 | O23: 7.3 | P23: =SUM(N23*O23) -> 4801.137 | S23: =SUM(47033.65/68)*H23 -> 1763.2085 | U23: =SUM(1900/68)*H23 -> 71.227647 | X23: =SUM(S23:W23) -> 1834.4362 | Y23: =SUM(11081/68)*H23 -> 415.40714 | AA23: =SUM(53.57/68)*H23 -> 2.0082448 | AB23: =SUM(Y23:AA23) -> 417.41538 | AC23: 7.3 | AD23: =SUM(AB23*AC23) -> 3047.1323 | AE23: =SUM(X23+AD23) -> 4881.5685 | AF23: =SUM(P23-AE23) -> -80.431459
C24: 241127000015 | D24: 45623 | E24: 罗珮文 | F24: Shirley | G24: SKY JET | H24: 33.06 | I24: 5293 | J24: 51603.35 | P24: =SUBTOTAL(9,J24) -> 51603.35 | S24: =SUM(47033.65/68)*H24 -> 22866.654 | U24: =SUM(1900/68)*H24 -> 923.73529 | X24: =SUM(S24:W24) -> 23790.389 | Y24: =SUM(11081/68)*H24 -> 5387.3215 | AA24: =SUM(53.57/68)*H24 -> 26.044474 | AB24: =SUM(Y24:AA24) -> 5413.3659 | AC24: 7.3 | AD24: =SUM(AB24*AC24) -> 39517.571 | AE24: =SUM(X24+AD24) -> 63307.961 | AF24: =SUM(P24-AE24) -> -11704.611
C25: 241127000027 | D25: 45623 | E25: 陆总 | F25: 陆梓龙 | G25: xiantian | H25: 3.145 | I25: 1753 | J25: 6114.46 | P25: =SUBTOTAL(9,J25) -> 6114.46 | S25: =SUM(47033.65/68)*H25 -> 2175.3063 | U25: =SUM(1900/68)*H25 -> 87.875 | X25: =SUM(S25:W25) -> 2263.1813 | Y25: =SUM(11081/68)*H25 -> 512.49625 | AA25: =SUM(53.57/68)*H25 -> 2.4776125 | AB25: =SUM(Y25:AA25) -> 514.97386 | AC25: 7.3 | AD25: =SUM(AB25*AC25) -> 3759.3092 | AE25: =SUM(X25+AD25) -> 6022.4905 | AF25: =SUM(P25-AE25) -> 91.969491
A26: 合计 | J26: =SUM(J4:J4) -> 0 | N26: =SUM(N4:N4) -> 0 | P26: =SUM(P4:P4) -> 0 | Q26: =SUM(Q4:Q4) -> 0 | X26: =SUM(X4:X4) -> 0 | AD26: =SUM(AD4:AD4) -> 0 | AF26: =SUM(AF4:AF25) -> 4132.9719
