Workbook

Sheet 1月份 
A1: 尼日利亚拉各斯（LOS） 应收利润明细表
A2: JOB | B2: 集装编号 | C2: 运单编号 | D2: 日期 | E2: 发货人 | F2: 收货人 | G2: 计费重量 | H2: 应 收 | O2: 总应收 | P2: 起 运 港 成 本 | U2: 代垫运费 | V2: 起运港成本 合计 | W2: 目的港成本 | AC2: 总支出 | AD2: 利润
H3: 应收RMB | I3: LOS Income(NGN) 收到(奈拉) | J3: LOS 收到USD | K3: 美元汇率 dollar currency rate | L3: 应收 到付款USD | M3: 汇率 | N3: 人民币 | P3: 代理商 | Q3: 运费 | R3: 提货费 | S3: 送货费 | T3: 包装费 | W3: 进口报关费 | X3: 到门配送费 | Y3: 转运费 | Z3: 目的港支出 | AA3: 汇率 | AB3: 人民币 | AC3: 起运港+目的港
A4: JOB010270 | B4: COLL003764 | C4: 231219000049 | D4: 45293 | E4: ying | F4: yanjian | G4: 3.5 | H4: 325.4 | N4: 325.4 | O4: 175736.21 | P4: 顶派=95589 广州通达=4832.8 | Q4: 100421.8 | S4: 243 | V4: 101389.8 | W4: 2817.74 | X4: 9.1 | Z4: 2861.99 | AA4: 7.17 | AB4: 20520.468 | AC4: 121910.27 | AD4: 53825.946
C5: 231222000006 | D5: 45293 | E5: Kaylee | F5: Tengsifan | G5: 9.5 | I5: 120120 | K5: 1262.0298 | L5: 95.18 | M5: 7.17 | N5: 682.4406 | T5: 40
C6: 231222000020 | D6: 45293 | E6: Isabel Zhu | F6: Zi Xuan Wang | G6: 6 | I6: 71400 | K6: 1254.833 | L6: 56.9 | M6: 7.17 | N6: 407.973
C7: 231223000002 | D7: 45293 | E7: Kaylee | F7: Ezeilo Eugene | G7: 40.5 | H7: 2106 | N7: 2106
C8: 231223000003 | D8: 45293 | E8: Kaylee | F8: kevin | G8: 0.98 | I8: 12848 | K8: 1262.0825 | L8: 10.18 | M8: 7.17 | N8: 72.9906
C9: 231223000005 | D9: 45293 | E9: 喵喵速运-Layne | F9: ZUBBY EQUIPMENT TECHNOLOGY | G9: 15 | I9: 132060 | K9: 1240 | L9: 106.5 | M9: 7.17 | N9: 763.605
C10: 231223000006 | D10: 45293 | E10: 喵喵速运-Layne | F10: Lukas | G10: 2.5 | I10: 22250 | K10: 1276.5347 | L10: 17.43 | M10: 7.17 | N10: 124.9731
C11: 231223000008 | D11: 45293 | E11: 喵喵速运-Layne | F11: fast hours DM NIGHT LED | G11: 3 | I11: 39362.4 | K11: 1325.3333 | L11: 29.7 | M11: 7.17 | N11: 212.949
C12: 231223000010 | D12: 45293 | E12: ying | F12: SEGUN | G12: 48.5 | H12: 3197 | N12: 3197 | U12: 190
C13: 231225000001 | D13: 45293 | E13: Isabel Zhu | F13: Mr Xiang | G13: 4 | H13: 283 | N13: 283
C14: 231225000004 | D14: 45293 | E14: Isabel Zhu | F14: Ope Olofinjana | G14: 32 | I14: 362435 | K14: 1239.9418 | L14: 292.3 | M14: 7.17 | N14: 2095.791
C15: 231225000006 | D15: 45293 | E15: Kaylee | F15: Wangpengtao王鹏涛 | G15: 47.5 | H15: 3105 | N15: 3105 | U15: 10
C16: 231225000008 | D16: 45293 | E16: Bella Chan | F16: Jimmy | G16: 33.5 | H16: 1708.5 | N16: 1708.5
C17: 231225000010 | D17: 45293 | E17: 喵喵速运-Layne | F17: Miss Yang Jun | G17: 73.5 | H17: 3864 | N17: 3864
C18: 231225000012 | D18: 45293 | E18: ying | F18: felix | G18: 38.5 | H18: 1963.5 | N18: 1963.5
C19: 231225000014 | D19: 45293 | E19: 喵喵速运-Layne | F19: Ye Hui | G19: 33 | H19: 1716 | N19: 1716
C20: 231225000016 | D20: 45293 | E20: 喵喵速运-Layne | F20: William Xu | G20: 5.5 | I20: 68670 | K20: 1563.1687 | L20: 43.93 | M20: 7.17 | N20: 314.9781 | T20: 40
C21: 231225000018 | D21: 45293 | E21: 喵喵速运-Layne | F21: ZHABV | G21: 1.5 | H21: 123 | N21: 123
C22: 231225000023 | D22: 45293 | E22: 喵喵速运-Layne | F22: SF 覃晓 | G22: 411.5 | H22: 18517.5 | N22: 18517.5
C23: 231225000025 | D23: 45293 | E23: 喵喵速运-Layne | F23: Leon | G23: 3.5 | I23: 36960 | K23: 1262.2951 | L23: 29.28 | M23: 7.17 | N23: 209.9376
C24: 231225000027 | D24: 45293 | E24: ying | F24: abu | G24: 6 | H24: 318 | N24: 318
C25: 231225000028 | D25: 45293 | E25: Sam.Pao | F25: AiGeLi | G25: 30.5 | H25: 1925 | N25: 1925
C26: 231225000029 | D26: 45293 | E26: Bella Chan | F26: li tao | G26: 2 | H26: 113 | N26: 113
C27: 231225000030 | D27: 45293 | E27: 喵喵速运-Layne | F27: Wen Yi Min | G27: 51.5 | I27: 528360 | K27: 1326.4712 | L27: 398.32 | M27: 7.17 | N27: 2855.9544
C28: 231225000031 | D28: 45293 | E28: DUDUHE鹤 | F28: SHAN NAN | G28: 23 | I28: 260896 | K28: 1240 | L28: 210.4 | M28: 7.17 | N28: 1508.568
C29: 231225000033 | D29: 45293 | E29: ying | F29: LI XING MAO | G29: 37.5 | I29: 455087 | K29: 1254.7547 | L29: 362.69 | M29: 7.17 | N29: 2600.4873 | U29: 80
C30: 231225000034 | D30: 45293 | E30: ying | F30: Mark Hu | G30: 13.5 | H30: 910.5 | N30: 910.5
C31: 231225000036 | D31: 45293 | E31: Sam.Pao | F31: David Wei | G31: 159 | I31: 1564420 | K31: 1276.0983 | L31: 1225.94 | M31: 7.17 | N31: 8789.9898
C32: 231225000039 | D32: 45293 | E32: 喵喵速运-Layne | F32: Zhou Ji BBQ | G32: 20 | H32: 1140 | N32: 1140 | T32: 40
C33: 231226000001 | D33: 45293 | E33: 喵喵速运-Layne | F33: REMI | G33: 13.5 | I33: 148500 | K33: 1577.4379 | L33: 94.14 | M33: 7.17 | N33: 674.9838
C34: 231226000003 | D34: 45293 | E34: Isabel Zhu | F34: Mr Zheng | G34: 50.5 | I34: 521362 | K34: 1295.0519 | L34: 402.58 | M34: 7.17 | N34: 2886.4986
C35: 231226000005 | D35: 45293 | E35: ying | F35: yunus | G35: 14 | I35: 166144 | K35: 1262.0129 | L35: 131.65 | M35: 7.17 | N35: 943.9305
C36: 231226000015 | D36: 45293 | E36: 喵喵速运-Layne | F36: REMI | G36: 3 | I36: 33000 | K36: 1577.4379 | L36: 20.92 | M36: 7.17 | N36: 149.9964
C37: 231226000016 | D37: 45293 | E37: ying | F37: liangyu | G37: 17.5 | H37: 916 | N37: 916
C38: 231226000017 | D38: 45293 | E38: Sam.Pao | F38: Wilson Liang | G38: 241 | I38: 2497680 | K38: 1278.0891 | L38: 1954.23 | M38: 7.17 | N38: 14011.829
C39: 231226000020 | D39: 45293 | E39: Bella Chan | F39: John Jiang | G39: 43.5 | H39: 2295 | N39: 2295 | X39: 35.15
C40: 231226000021 | D40: 45293 | E40: Isabel Zhu | F40: Halifa Success | G40: 5 | H40: 282.5 | N40: 282.5
C41: 231226000023 | D41: 45293 | E41: ying | F41: Mr Eliyas | G41: 2.5 | H41: 234.5 | N41: 234.5
C42: 231226000025 | D42: 45293 | E42: 喵喵速运-Layne | F42: LEO WEI | G42: 0.9 | I42: 11505 | K42: 1269.8675 | L42: 9.06 | M42: 7.17 | N42: 64.9602
C43: 231226000026 | D43: 45293 | E43: 喵喵速运-Layne | F43: Zhou Ji BBQ | G43: 2 | H43: 120 | N43: 120
C44: 231226000029 | D44: 45293 | E44: 喵喵速运-Layne | F44: CHM IRON AND STEEL FZE | G44: 5 | H44: 300 | N44: 300
C45: 231226000030 | D45: 45293 | E45: 喵喵速运-Layne | F45: REMI | G45: 0.16 | H45: 50 | N45: 50
C46: 231226000031 | D46: 45293 | E46: ying | F46: DV | G46: 0.5 | H46: 58 | N46: 58
C47: 231227000002 | D47: 45293 | E47: Isabel Zhu | F47: Semiu Biliaminu | G47: 200 | H47: 9800 | N47: 9800
C48: 231227000004 | D48: 45293 | E48: Isabel Zhu | F48: Wu Jiao Xing | G48: 0.19 | H48: 58 | N48: 58
C49: 231227000008 | D49: 45293 | E49: 喵喵速运-Layne | F49: REMI | G49: 6.5 | I49: 62725 | K49: 1384.0468 | L49: 45.32 | M49: 7.17 | N49: 324.9444
C50: 231227000012 | D50: 45293 | E50: Sam.Pao | F50: Yuan | G50: 23.5 | H50: 1057.5 | N50: 1057.5
C51: 231227000014 | D51: 45293 | E51: ying | F51: wenweiguo | G51: 3 | H51: 168 | N51: 168
C52: 231227000015 | D52: 45293 | E52: ying | F52: JOHNNIE CHAK | G52: 2.5 | H52: 140.5 | N52: 140.5
C53: 231227000018 | D53: 45293 | E53: Bella Chan | F53: ZOU Qiyang | G53: 1245 | H53: 65985 | N53: 65985 | T53: 120 | U53: 96
C54: 231227000025 | D54: 45293 | E54: Kaylee | F54: David | G54: 4 | H54: 223 | N54: 223
C55: 231227000026 | D55: 45293 | E55: 喵喵速运-Layne | F55: Halo Cargo | G55: 163 | H55: 6357 | N55: 6357
C56: 231227000027 | D56: 45293 | E56: Isabel Zhu | F56: Gene | G56: 13.5 | H56: 828 | N56: 828 | T56: 40
C57: 231227000031 | D57: 45293 | E57: Mailmail Abv sales person 1 | F57: Kalio Edith | G57: 31 | I57: 317289 | K57: 1454.7868 | L57: 218.1 | M57: 7.17 | N57: 1563.777
C58: 231228000001 | D58: 45293 | E58: Kaylee | F58: Chen Hai Bing | G58: 12.5 | H58: 656 | N58: 656
C59: 231228000002 | D59: 45293 | E59: ying | F59: zhi hui zhou | G59: 28.5 | H59: 1425 | N59: 1425
C60: 231228000003 | D60: 45293 | E60: 喵喵速运-Layne | F60: ZHABV | G60: 0.32 | H60: 63 | N60: 63
C61: 231228000009 | D61: 45293 | E61: 喵喵速运-Layne | F61: MR.WANG | G61: 7.5 | H61: 459 | N61: 459 | U61: 69
C62: 231228000010 | D62: 45293 | E62: 喵喵速运-Layne | F62: SF 覃晓 | G62: 12 | H62: 540 | N62: 540
C63: 231228000018 | D63: 45293 | E63: Bella Chan | F63: wang hong sheng | G63: 1.5 | I63: 19680 | K63: 1644.1103 | L63: 11.97 | M63: 7.17 | N63: 85.8249
C64: 231228000023 | D64: 45293 | E64: 喵喵速运-Layne | F64: FRANK | G64: 23.5 | I64: 186120 | K64: 1262.0016 | L64: 147.48 | M64: 7.17 | N64: 1057.4316
A65: JOB010271 | B65: COLL003767 | C65: 231225000011 | D65: 45293 | E65: ying | F65: SEGUN | G65: 43 | H65: 2207 | N65: 2207 | O65: 186465.93 | P65: 顶派=127692 广州通达=5118.4 | Q65: 132810.4 | S65: 222.2 | T65: 100 | U65: 153 | V65: 133901.6 | W65: 2355.12 | Z65: 2366.32 | AA65: 7.17 | AB65: 16966.514 | AC65: 150868.11 | AD65: 35597.82
C66: 231226000002 | D66: 45293 | E66: 易小羔 | F66: Robin Tai | G66: 22 | H66: 1108 | N66: 1108
C67: 231226000007 | D67: 45293 | E67: Isabel Zhu | F67: Mr Huang | G67: 561 | H67: 25926 | N67: 25926 | T67: 120
C68: 231227000005 | D68: 45293 | E68: Kaylee | F68: John 张 | G68: 0.65 | H68: 63 | N68: 63
C69: 231227000006 | D69: 45293 | E69: ying | F69: CHE YUAN | G69: 11 | H69: 643 | N69: 643
C70: 231227000009 | D70: 45293 | E70: 喵喵速运-Layne | F70: GONG | G70: 150 | H70: 6970 | N70: 6970 | T70: 70
C71: 231227000016 | D71: 45293 | E71: 喵喵速运-Layne | F71: LI LING BO | G71: 5.5 | H71: 318 | N71: 318 | U71: 43
C72: 231227000019 | D72: 45293 | E72: ying | F72: lituo | G72: 7.5 | H72: 440 | N72: 440
C73: 231228000004 | D73: 45293 | E73: ying | F73: Zhang Pengpeng | G73: 5 | H73: 278 | N73: 278
C74: 231228000008 | D74: 45293 | E74: 喵喵速运-Layne | F74: REMI | G74: 1.5 | H74: 75 | N74: 75
C75: 231228000011 | D75: 45293 | E75: ying | F75: FeLiX | G75: 9.5 | H75: 430 | N75: 430
C76: 231228000012 | D76: 45293 | E76: Isabel Zhu | F76: Mr Pan Li | G76: 778.5 | H76: 36411 | N76: 36411
C77: 231228000015 | D77: 45293 | E77: ying | F77: Hillter | G77: 0.9 | H77: 81 | N77: 81 | U77: 23
C78: 231228000024 | D78: 45293 | E78: Sam.Pao | F78: Seman | G78: 1189.5 | I78: 8383750 | K78: 1278.9679 | L78: 6555.09 | M78: 7.17 | N78: 46999.995 | T78: 240
C79: 231229000003 | D79: 45293 | E79: Isabel Zhu | F79: Mr Huang | G79: 939.5 | H79: 34881 | N79: 34881 | T79: 120
C80: 231229000005 | D80: 45293 | E80: Sam.Pao | F80: XiongQiJun | G80: 3 | H80: 168 | N80: 168
C81: 231229000007 | D81: 45293 | E81: 鸿 | F81: Alice08105750388 | G81: 30 | I81: 235773.6 | K81: 1239.9999 | L81: 190.14001 | M81: 7.17 | N81: 1363.3039
C82: 231229000008 | D82: 45293 | E82: Sam.Pao | F82: Johnson Zhu | G82: 38.5 | H82: 2005 | N82: 2005 | X82: 11.2
C83: 231229000010 | D83: 45293 | E83: ying | F83: hanzong | G83: 208 | H83: 8944 | N83: 8944
C84: 231229000014 | D84: 45293 | E84: Isabel Zhu | F84: Ope Olofinjana | G84: 0.26 | I84: 10000.44 | K84: 1234.6222 | L84: 8.1 | M84: 7.17 | N84: 58.077
C85: 231229000017 | D85: 45293 | E85: Bella Chan | F85: Stanley | G85: 33 | I85: 288176 | K85: 1240 | L85: 232.4 | M85: 7.17 | N85: 1666.308
C86: 231229000029 | D86: 45293 | E86: Isabel Zhu | F86: Halifa Success | G86: 7 | H86: 339 | N86: 339
C87: 231229000031 | D87: 45293 | E87: Sam.Pao | F87: Nkechi | G87: 364.5 | H87: 14033.25 | N87: 14033.25
C88: 231229000033 | D88: 45293 | E88: Sam.Pao | F88: LuZhiLong | G88: 21 | H88: 1058 | N88: 1058
A89: JOB010272 | B89: COLL003775 | C89: 231017000004 | D89: 45295 | E89: Isabel Zhu | F89: Mr Wu | G89: 7.4514 | H89: 22753.5 | N89: 22753.5 | O89: 28844.5 | P89: 阿米拉海运 | Q89: 16807.5 | S89: 148 | V89: 16955.5 | X89: 584.68 | Z89: 584.68 | AA89: 7.17 | AB89: 4192.1556 | AC89: 21147.656 | AD89: 7696.8444
C90: 231020000043 | D90: 45295 | E90: Bella Chan | F90: ODEYALE | G90: 2.0219 | I90: 883344 | K90: 1261.92 | L90: 700 | M90: 7.17 | N90: 5019
C91: 231027000021 | D91: 45295 | E91: 易小羔 | F91: peter | G91: 0.1862 | H91: 1072 | N91: 1072
A92: JOB010273 | B92: COLL003776 | C92: 231030000030 | D92: 45295 | E92: ying | F92: OSIM | G92: 0.7848 | H92: 2008 | N92: 2008 | O92: 2008 | P92: 捷道 | Q92: 1219.41 | V92: 1219.41 | W92: 0 | Z92: 0 | AB92: 0 | AC92: 1219.41 | AD92: 788.59
A93: JOB010274 | B93: COLL003777 | C93: 231227000020 | D93: 45296 | E93: 家峰 | F93: jiafeng | G93: 0.94 | I93: 21838 | K93: 1240.0909 | L93: 17.61 | M93: 7.17 | N93: 126.2637 | O93: 13123.823 | P93: 富姐 | Q93: 4400 | S93: 63.92 | V93: 4463.92 | W93: 130.97 | Z93: 130.97 | AA93: 7.17 | AB93: 939.0549 | AC93: 5402.9749 | AD93: 7720.8479
C94: 231229000016 | D94: 45296 | E94: Bella Chan | F94: huang | G94: 0.38 | H94: 125 | N94: 125
C95: 231229000032 | D95: 45296 | E95: ying | F95: Charles | G95: 0.83 | H95: 125 | N95: 125
C96: 231230000005 | D96: 45296 | E96: 东东 | F96: Yang | G96: 5.5 | H96: 715 | N96: 715
C97: 231231000003 | D97: 45296 | E97: 易小羔 | F97: xieziqing | G97: 0.72 | H97: 130 | N97: 130
C98: 240102000013 | D98: 45296 | E98: 喵喵速运-Layne | F98: Joker | G98: 0.5 | I98: 22000 | K98: 1262.1916 | L98: 17.43 | M98: 7.17 | N98: 124.9731
C99: 240102000019 | D99: 45296 | E99: ying | F99: Sophia | G99: 6.5 | H99: 1007.5 | N99: 1007.5
C100: 240102000021 | D100: 45296 | E100: ying | F100: Shang yafei | G100: 3 | H100: 480 | N100: 480
...

Sheet 2月份
A1: 尼日利亚拉各斯（LOS） 应收利润明细表
A2: JOB | B2: 集装编号 | C2: 运单编号 | D2: 日期 | E2: 发货人 | F2: 收货人 | G2: 计费重量 | H2: 应 收 | O2: 总应收 | P2: 起 运 港 成 本 | U2: 代垫运费 | V2: 起运港成本 合计 | W2: 目的港成本 | AC2: 总支出 | AD2: 利润
H3: 应收RMB | I3: LOS Income(NGN) 收到(奈拉) | J3: LOS 收到USD | K3: 美元汇率 dollar currency rate | L3: 应收 到付款USD | M3: 汇率 | N3: 人民币 | P3: 代理商 | Q3: 运费 | R3: 提货费 | S3: 送货费 | T3: 包装费 | W3: 进口报关费 | X3: 到门配送费 | Y3: 转运费 | Z3: 目的港支出 | AA3: 汇率 | AB3: 人民币 | AC3: 起运港+目的港
A4: JOB020137 | B4: COLL003812 | C4: 240125000046 | D4: 45324 | E4: ying | F4: peter | G4: 18 | H4: 2250 | N4: 2250 | O4: 3774 | P4: 富姐 | Q4: 2200 | S4: 0 | V4: 2224 | W4: 44.57 | Z4: 44.57 | AA4: 7.19 | AB4: 320.4583 | AC4: 2544.4583 | AD4: 1229.5417
C5: 240126000040 | D5: 45324 | E5: 喵喵速运-Layne | F5: Tia | G5: 2 | H5: 250 | N5: 250
C6: 240126000043 | D6: 45324 | E6: Sam.Pao | F6: David Zhao | G6: 8.5 | H6: 1062.5 | N6: 1062.5
C7: 240129000048 | D7: 45324 | E7: ying | F7: Sagamu | G7: 1.5 | H7: 211.5 | N7: 211.5 | U7: 24
A8: JOB020138 | B8: COLL003814 | C8: 240202000025 | D8: 45324 | E8: Sam.Pao | F8: Sampao | G8: 551 | H8: 27558 | N8: 27558 | O8: 27558 | P8: 顶派 | Q8: 41352 | V8: 41352 | W8: 497.42 | Z8: 497.42 | AA8: 7.19 | AB8: 3576.4498 | AC8: 44928.45 | AD8: -17370.45
A9: JOB020139 | B9: COLL003815 | C9: 240202000026 | D9: 45324 | E9: Sam.Pao | F9: Sampao | G9: 296 | H9: 14808 | N9: 14808 | O9: 14808 | V9: 0 | W9: 303.62 | X9: 3167 | Z9: 3470.62 | AA9: 7.19 | AB9: 24953.758 | AC9: 24953.758 | AD9: -10145.758
A10: JOB020140 | B10: COLL003817 | C10: 240126000027 | D10: 45325 | E10: ying | F10: xiongge | G10: 1.5 | H10: 0 | N10: 0 | O10: 24252.585 | P10: 富姐 | Q10: 11400 | S10: 205.43 | V10: 11605.43 | W10: 369.41 | Z10: 374.21 | AA10: 7.19 | AB10: 2690.5699 | AC10: 14296 | AD10: 9956.5847
C11: 240127000011 | D11: 45325 | E11: ying | F11: Steven Abuja | G11: 0.73 | I11: 27950 | K11: 1545.9071 | L11: 18.08 | M11: 7.19 | N11: 129.9952
C12: 240128000005 | D12: 45325 | E12: Julie LEE | F12: Julie lee | G12: 3 | H12: 390 | N12: 390
C13: 240129000036 | D13: 45325 | E13: 易小羔 | F13: Robin Tai | G13: 2 | H13: 250 | N13: 250
C14: 240129000037 | D14: 45325 | E14: 喵喵速运-Layne | F14: William Xu | G14: 0.6 | I14: 34880 | K14: 1567.6404 | L14: 22.25 | M14: 7.19 | N14: 159.9775
C15: 240129000039 | D15: 45325 | E15: ying | F15: xiongge | G15: 8 | I15: 215000 | K15: 1545.8729 | L15: 139.08 | M15: 7.19 | N15: 999.9852
C16: 240129000064 | D16: 45325 | E16: 喵喵速运-Layne | F16: GONG | G16: 20 | I16: 666500 | K16: 1545.8657 | L16: 431.15 | M16: 7.19 | N16: 3099.9685
C17: 240129000065 | D17: 45325 | E17: 喵喵速运-Layne | F17: GONG | G17: 20 | I17: 666500 | K17: 1545.8657 | L17: 431.15 | M17: 7.19 | N17: 3099.9685
C18: 240129000070 | D18: 45325 | E18: Bella Chan | F18: wang hong sheng | G18: 2.5 | I18: 68127.48 | K18: 1547.9999 | L18: 44.010002 | M18: 7.19 | N18: 316.43191
C19: 240129000073 | D19: 45325 | E19: ying | F19: felix | G19: 3 | H19: 410 | N19: 410 | X19: 4.8
C20: 240130000008 | D20: 45325 | E20: 喵喵速运-Layne | F20: MA ZONG | G20: 0.26 | H20: 130 | N20: 130
C21: 240130000025 | D21: 45325 | E21: Bella Chan | F21: chi de jian | G21: 0.38 | H21: 125 | N21: 125
C22: 240130000040 | D22: 45325 | E22: Sam.Pao | F22: Angel | G22: 7 | H22: 875 | N22: 875
C23: 240131000008 | D23: 45325 | E23: 喵喵速运-Layne | F23: Song Wen Tao | G23: 1.5 | I23: 65600 | K23: 1474.1573 | L23: 44.5 | M23: 7.19 | N23: 319.955
C24: 240131000013 | D24: 45325 | E24: Bella Chan | F24: Zhang cui | G24: 3 | H24: 219 | N24: 219
C25: 240131000023 | D25: 45325 | E25: ying | F25: xiongge | G25: 3 | I25: 90625 | K25: 1737.7756 | L25: 52.15 | M25: 7.19 | N25: 374.9585
C26: 240131000026 | D26: 45325 | E26: 喵喵速运-Layne | F26: GONG | G26: 7.5 | I26: 267375 | K26: 1653.7296 | L26: 161.68 | M26: 7.19 | N26: 1162.4792
C27: 240131000029 | D27: 45325 | E27: 喵喵速运-Layne | F27: GONG | G27: 7.5 | I27: 249937.5 | K27: 1545.8777 | L27: 161.68 | M27: 7.19 | N27: 1162.4792
C28: 240131000030 | D28: 45325 | E28: 喵喵速运-Layne | F28: GONG | G28: 7.5 | I28: 249937.5 | K28: 1545.8777 | L28: 161.68 | M28: 7.19 | N28: 1162.4792
C29: 240131000035 | D29: 45325 | E29: 喵喵速运-Layne | F29: Guo Hui 郭总 | G29: 1 | I29: 50640 | K29: 1517.5307 | L29: 33.37 | M29: 7.19 | N29: 239.9303
C30: 240131000040 | D30: 45325 | E30: Sam.Pao | F30: Angel | G30: 1 | H30: 125 | N30: 125
C31: 240131000041 | D31: 45325 | E31: 易小羔 | F31: yuanbiao | G31: 13 | H31: 1690 | N31: 1690
C32: 240131000045 | D32: 45325 | E32: Bella Chan | F32: tang qiao lin | G32: 1.5 | I32: 86000 | K32: 1545.9285 | L32: 55.63 | M32: 7.19 | N32: 399.9797
C33: 240131000047 | D33: 45325 | E33: 易小羔 | F33: PAN | G33: 11.5 | I33: 294687.5 | K33: 1473.9534 | L33: 199.93 | M33: 7.19 | N33: 1437.4967
C34: 240131000052 | D34: 45325 | E34: ying | F34: mr | G34: 7.5 | H34: 1127.5 | N34: 1127.5
C35: 240201000002 | D35: 45325 | E35: Isabel Zhu | F35: Long Er | G35: 4 | H35: 520 | N35: 520
C36: 240201000016 | D36: 45325 | E36: 易小羔 | F36: laohuang | G36: 4.5 | H36: 562.5 | N36: 562.5
C37: 240201000035 | D37: 45325 | E37: 易小羔 | F37: zhouyicheng | G37: 4 | H37: 520 | N37: 520
C38: 240202000012 | D38: 45325 | E38: 喵喵速运-Layne | F38: Lee Wen Wei | G38: 3 | H38: 375 | N38: 375
C39: 240202000020 | D39: 45325 | E39: ying | F39: Chinex | G39: 18.5 | H39: 2867.5 | N39: 2867.5
A40: JOB020141 | B40: COLL003819 | C40: 240202000041 | D40: 45326 | E40: 喵喵速运-Layne | F40: NENG SHI | G40: 0.812 | H40: 2278 | N40: 2278 | O40: 4870 | P40: 捷道 | Q40: 3386.8 | V40: 3386.8 | Z40: 0 | AB40: 0 | AC40: 3386.8 | AD40: 1483.2
C41: 240202000042 | D41: 45326 | E41: 喵喵速运-Layne | F41: NENG SHI | G41: 1.0815 | H41: 2592 | N41: 2592
A42: JOB020142 | B42: COLL003820 | C42: 231120000065 | D42: 45326 | E42: Sam.Pao | F42: Bolaji Abidoye | G42: 34.9091 | H42: 72931.25 | N42: 72931.25 | O42: 72931.25 | P42: 阿米拉海运 | Q42: 56564 | S42: 0 | V42: 56564 | W42: 1658.55 | Z42: 1658.55 | AA42: 7.19 | AB42: 11924.975 | AC42: 68488.974 | AD42: 4442.2755
C43: 231120000066 | D43: 45326 | E43: Sam.Pao | F43: Bolaji Abidoye | G43: 26.2876 | H43: 53440.63 | N43: 53440.63 | O43: 53440.63 | P43: 阿米拉海运 | Q43: 42160 | V43: 42160 | Z43: 0 | AA43: 7.19 | AB43: 0 | AC43: 42160 | AD43: 11280.63
C44: 231121000021 | D44: 45326 | E44: Bella Chan | F44: James | G44: 1.9058 | J44: 560 | K44: 0 | L44: 560 | M44: 7.19 | N44: 4026.4 | O44: 4026.4 | P44: 阿米拉海运 | Q44: 3247.84 | S44: 144 | V44: 3391.84 | Z44: 0 | AA44: 7.19 | AB44: 0 | AC44: 3391.84 | AD44: 634.56
C45: 231125000001 | D45: 45326 | E45: Kaylee | F45: ABDULRAHMANE DANMAALLAM | G45: 4.1594 | H45: 14161 | N45: 14161 | O45: 14161 | P45: 阿米拉海运 | Q45: 6680 | S45: 0 | V45: 6680 | Z45: 0 | AA45: 7.19 | AB45: 0 | AC45: 6680 | AD45: 7481
C46: 231204000024 | D46: 45326 | E46: Sam.Pao | F46: XiongQiJun | G46: 0.0303 | H46: 370 | N46: 370 | O46: 370 | P46: 阿米拉海运 | Q46: 56 | V46: 56 | Z46: 0 | AA46: 7.19 | AB46: 0 | AC46: 56 | AD46: 314
C47: 231206000012 | D47: 45326 | E47: Sam.Pao | F47: ShanShan | G47: 11.4031 | H47: 23092 | N47: 23092 | O47: 23092 | P47: 阿米拉海运 | Q47: 16749.12 | V47: 16749.12 | Z47: 0 | AA47: 7.19 | AB47: 0 | AC47: 16749.12 | AD47: 6342.88
C48: 231204000041 | D48: 45326 | E48: Bella Chan | F48: james | G48: 9.0797 | J48: 2660 | K48: 0 | L48: 2660 | M48: 7.19 | N48: 19125.4 | O48: 19125.4 | P48: 阿米拉海运 | Q48: 14582 | S48: 179.2 | V48: 14761.2 | Z48: 0 | AA48: 7.19 | AB48: 0 | AC48: 14761.2 | AD48: 4364.2
C49: 231207000022 | D49: 45326 | E49: Bella Chan | F49: james | G49: 6.1718 | J49: 1820 | L49: 1820 | M49: 7.19 | N49: 13085.8 | O49: 13085.8 | P49: 阿米拉海运 | Q49: 9579.6 | S49: 100 | V49: 9679.6 | Z49: 0 | AA49: 7.19 | AB49: 0 | AC49: 9679.6 | AD49: 3406.2
C50: 231208000023 | D50: 45326 | E50: Sam.Pao | F50: WangXianTao | G50: 2.0996 | H50: 4890.75 | N50: 4890.75 | O50: 4890.75 | P50: 阿米拉海运 | Q50: 3678.47 | V50: 3678.47 | Z50: 0 | AA50: 7.19 | AB50: 0 | AC50: 3678.47 | AD50: 1212.28
C51: 231208000025 | D51: 45326 | E51: Sam.Pao | F51: WangXianTao | G51: 1.7994 | H51: 9521.5 | N51: 9521.5 | O51: 9521.5 | P51: 阿米拉海运 | Q51: 6754.32 | V51: 6754.32 | Z51: 0 | AA51: 7.19 | AB51: 0 | AC51: 6754.32 | AD51: 2767.18
A52: JOB020143 | B52: COLL003821 | C52: 240124000024 | D52: 45326 | E52: ying | F52: xiongge | G52: 5 | I52: 118250.5 | K52: 1700.4674 | L52: 69.54 | M52: 7.19 | N52: 499.9926 | O52: 17625.916 | P52: 富姐 | Q52: 9820 | S52: 68.81 | V52: 9888.81 | W52: 282.52 | Z52: 282.52 | AA52: 7.19 | AB52: 2031.3188 | AC52: 11920.129 | AD52: 5705.7873
C53: 240129000002 | D53: 45326 | E53: Bella Chan | F53: wei hui zhu | G53: 9 | H53: 440 | N53: 440
C54: 240129000018 | D54: 45326 | E54: Bella Chan | F54: a niu ge | G54: 0.96 | H54: 125 | N54: 125
C55: 240129000032 | D55: 45326 | E55: 喵喵速运-Layne | F55: William Xu | G55: 5 | I55: 141700 | K55: 1567.4779 | L55: 90.4 | M55: 7.19 | N55: 649.976
C56: 240129000063 | D56: 45326 | E56: 喵喵速运-Layne | F56: GONG | G56: 19 | I56: 677350 | K56: 1653.7269 | L56: 409.59 | M56: 7.19 | N56: 2944.9521
C57: 240131000027 | D57: 45326 | E57: 喵喵速运-Layne | F57: GONG | G57: 7.5 | I57: 267375 | K57: 1653.7296 | L57: 161.68 | M57: 7.19 | N57: 1162.4792
C58: 240131000028 | D58: 45326 | E58: 喵喵速运-Layne | F58: GONG | G58: 7.5 | I58: 267375 | K58: 1653.7296 | L58: 161.68 | M58: 7.19 | N58: 1162.4792
C59: 240201000028 | D59: 45326 | E59: Sam.Pao | F59: YingYi | G59: 25.5 | H59: 3315 | N59: 3315
C60: 240202000003 | D60: 45326 | E60: Isabel Zhu | F60: Long Er | G60: 1.5 | H60: 195 | N60: 195
C61: 240202000024 | D61: 45326 | E61: ying | F61: xiongge | G61: 7.5 | I61: 177375 | K61: 1700.4602 | L61: 104.31 | M61: 7.19 | N61: 749.9889
C62: 240202000045 | D62: 45326 | E62: Isabel Zhu | F62: Kelly He | G62: 4.5 | H62: 562 | N62: 562
C63: 240202000050 | D63: 45326 | E63: ying | F63: JOHNNIE | G63: 2.5 | I63: 64000 | K63: 1472.6185 | L63: 43.46 | M63: 7.19 | N63: 312.4774
C64: 240202000059 | D64: 45326 | E64: Mailmail Abv sales person 1 | F64: Fafunso | G64: 0.3 | I64: 27260 | K64: 1547.9841 | L64: 17.61 | M64: 7.19 | N64: 126.6159
C65: 240203000008 | D65: 45326 | E65: ying | F65: Lissi | G65: 1.5 | H65: 380 | N65: 380
C66: 240203000009 | D66: 45326 | E66: ying | F66: Chinex | G66: 35 | H66: 4375 | N66: 4375
C67: 240203000012 | D67: 45326 | E67: ying | F67: xiongge | G67: 5.5 | I67: 147812.5 | K67: 1700.558 | L67: 86.92 | M67: 7.19 | N67: 624.9548
A68: JOB020144 | B68: COLL003811 | C68: 240119000016 | D68: 45326 | E68: 喵喵国际 | F68: David | G68: 21.5 | H68: 1299.6 | N68: 1299.6 | O68: 118689.06 | P68: 顶派 | Q68: 89213.5 | S68: 145 | V68: 92310.8 | W68: 1424.83 | Z68: 1452.63 | AA68: 7.19 | AB68: 10444.41 | AC68: 102755.21 | AD68: 15933.85
C69: 240123000024 | D69: 45326 | E69: Mikey | F69: penglijuan | G69: 21 | H69: 1269.6 | N69: 1269.6
C70: 240123000033 | D70: 45326 | E70: 喵喵速运-Layne | F70: Lisa | G70: 1.5 | H70: 90 | N70: 90
C71: 240124000018 | D71: 45326 | E71: 喵喵国际 | F71: Ben | G71: 3 | H71: 201.6 | N71: 201.6
C72: 240124000030 | D72: 45326 | E72: 喵喵国际 | F72: Weiwei | G72: 8 | H72: 562.8 | N72: 562.8
C73: 240124000036 | D73: 45326 | E73: ying | F73: zhuyongjie | G73: 40 | H73: 4400 | N73: 4400 | T73: 2392
C74: 240125000028 | D74: 45326 | E74: ying | F74: peter | G74: 1.5 | H74: 102.6 | N74: 102.6
C75: 240125000033 | D75: 45326 | E75: Mikey | F75: maohaiming | G75: 9 | H75: 527 | N75: 527
C76: 240125000052 | D76: 45326 | E76: Sam.Pao | F76: Yangbin | G76: 5 | I76: 78205 | K76: 1548.0009 | L76: 50.519997 | M76: 7.19 | N76: 363.23878
C77: 240126000001 | D77: 45326 | E77: 慌慌 | F77: Hillter | G77: 53.5 | H77: 3756.2 | N77: 3756.2
C78: 240126000002 | D78: 45326 | E78: Isabel Zhu | F78: Xu Jie | G78: 6 | H78: 402 | N78: 402
C79: 240126000008 | D79: 45326 | E79: Bella Chan | F79: Jahnson | G79: 2 | H79: 206.8 | N79: 206.8
C80: 240126000009 | D80: 45326 | E80: Bella Chan | F80: Val | G80: 3 | H80: 178 | N80: 178
C81: 240126000015 | D81: 45326 | E81: ying | F81: SEGUN | G81: 26 | H81: 1840.3 | N81: 1840.3 | U81: 280.3
C82: 240126000023 | D82: 45326 | E82: Sam.Pao | F82: ChenGaoHong | G82: 71 | I82: 926355.2 | K82: 1524.2874 | L82: 607.73 | M82: 7.19 | N82: 4369.5787 | T82: 100
C83: 240126000034 | D83: 45326 | E83: Bella Chan | F83: fang ming | G83: 14.5 | H83: 1015.2 | N83: 1015.2
C84: 240126000035 | D84: 45326 | E84: Isabel Zhu | F84: OBONGHA UKET UBANGH | G84: 7 | H84: 604 | N84: 604
C85: 240126000055 | D85: 45326 | E85: 袁安医生 Dr. Andy | F85: Andy Yuan | G85: 18.5 | H85: 1509.2 | N85: 1509.2
C86: 240127000001 | D86: 45326 | E86: Mikey | F86: Mr. ＡLLEN | G86: 11 | H86: 968 | N86: 968
C87: 240127000005 | D87: 45326 | E87: Sam.Pao | F87: Charles zhao | G87: 4.5 | H87: 300.6 | N87: 300.6
C88: 240127000006 | D88: 45326 | E88: ying | F88: jiangxia | G88: 18 | I88: 313745 | K88: 1538.72 | L88: 203.9 | M88: 7.19 | N88: 1466.041 | T88: 80
C89: 240127000008 | D89: 45326 | E89: ying | F89: Emma YE | G89: 15.5 | H89: 1210 | N89: 1210 | X89: 27.8
C90: 240127000013 | D90: 45326 | E90: Sam.Pao | F90: MaiKaiNian | G90: 5.5 | H90: 440 | N90: 440
C91: 240127000017 | D91: 45326 | E91: Isabel Zhu | F91: Joy | G91: 40 | I91: 630672.5 | K91: 1576.6813 | L91: 400 | M91: 7.19 | N91: 2876
C92: 240128000001 | D92: 45326 | E92: Mailmail Abv sales person 1 | F92: Kalio Edith | G92: 13.5 | I92: 150595 | K92: 1554.9303 | L92: 96.85 | M92: 7.19 | N92: 696.3515
C93: 240129000009 | D93: 45326 | E93: 喵喵速运-Layne | F93: Mr.Tabrat | G93: 5.5 | I93: 88642.5 | K93: 1603.5185 | L93: 55.28 | M93: 7.19 | N93: 397.4632
C94: 240129000011 | D94: 45326 | E94: 喵喵速运-Layne | F94: Mr.Bernie | G94: 16 | I94: 231920 | K94: 1603.4292 | L94: 144.64 | M94: 7.19 | N94: 1039.9616
C95: 240129000016 | D95: 45326 | E95: Bella Chan | F95: James | G95: 13 | I95: 195000 | K95: 1543.21 | L95: 126.35999 | M95: 7.19 | N95: 908.52833
C96: 240129000025 | D96: 45326 | E96: 喵喵国际 | F96: LOMO | G96: 12 | I96: 161784 | K96: 1538.7483 | L96: 105.14 | M96: 7.19 | N96: 755.9566
C97: 240129000027 | D97: 45326 | E97: Bella Chan | F97: Precious Ali | G97: 3 | H97: 337.2 | N97: 337.2
C98: 240129000046 | D98: 45326 | E98: 喵喵速运-Layne | F98: Zhang Guo Ren | G98: 2 | H98: 135.6 | N98: 135.6
C99: 240129000052 | D99: 45326 | E99: 喵喵速运-Layne | F99: Rachel | G99: 249 | H99: 13554 | N99: 13554 | T99: 100
C100: 240129000054 | D100: 45326 | E100: 喵喵速运-Layne | F100: Peter | G100: 2.5 | H100: 168.6 | N100: 168.6
...

Sheet 3月份
A1: 尼日利亚拉各斯（LOS） 应收利润明细表
A2: JOB | B2: 集装编号 | C2: 运单编号 | D2: 日期 | E2: 发货人 | F2: 收货人 | G2: 计费重量 | H2: 应 收 | O2: 总应收 | P2: 起 运 港 成 本 | U2: 代垫运费 | V2: 起运港成本 合计 | W2: 目的港成本 | AC2: 总支出 | AD2: 利润
H3: 应收RMB | I3: LOS Income(NGN) 收到(奈拉) | J3: LOS 收到USD | K3: 美元汇率 dollar currency rate | L3: 应收 到付款USD | M3: 汇率 | N3: 人民币 | P3: 代理商 | Q3: 运费 | R3: 提货费 | S3: 送货费 | T3: 包装费 | W3: 进口报关费 | X3: 到门配送费 | Y3: 转运费 | Z3: 目的港支出 | AA3: 汇率 | AB3: 人民币 | AC3: 起运港+目的港
A4: JOB030324 | B4: COLL003836 | C4: 240220000004 | D4: 45353 | E4: Bella Chan | F4: li tao | G4: 1.5 | H4: 88.2 | N4: 88.2 | O4: 80342.69 | P4: 顶派 | Q4: 63773.2 | S4: 125 | V4: 64800.2 | W4: 1114.79 | Z4: 1114.79 | AA4: 7.19 | AB4: 8015.3401 | AC4: 72815.54 | AD4: 7527.1495
C5: 240220000041 | D5: 45353 | E5: Isabel Zhu | F5: Emmanuel | G5: 0.97 | H5: 125 | N5: 125
C6: 240221000024 | D6: 45353 | E6: 喵喵速运-Layne | F6: Mr.Cheng | G6: 78.5 | I6: 769350 | K6: 1603.3804 | L6: 479.83 | M6: 7.19 | N6: 3449.9777
C7: 240222000009 | D7: 45353 | E7: ying | F7: chuks | G7: 281 | I7: 3822220 | K7: 1603.3744 | L7: 2383.86 | M7: 7.19 | N7: 17139.953 | T7: 280
C8: 240223000006 | D8: 45353 | E8: 喵喵速运-Layne | F8: Wang Jiu Lin | G8: 31 | H8: 1981.2 | N8: 1981.2 | T8: 160
C9: 240223000009 | D9: 45353 | E9: Mikey | F9: Chenyun | G9: 6 | H9: 324 | N9: 324
C10: 240223000010 | D10: 45353 | E10: Mikey | F10: SIMON OMALE | G10: 6.5 | H10: 397.2 | N10: 397.2
C11: 240223000011 | D11: 45353 | E11: ying | F11: qianqian | G11: 10 | H11: 588 | N11: 588
C12: 240223000018 | D12: 45353 | E12: Isabel Zhu | F12: Colin | G12: 33.5 | I12: 395664 | K12: 1600 | L12: 247.29 | M12: 7.19 | N12: 1778.0151
C13: 240223000020 | D13: 45353 | E13: Mikey | F13: Blessing | G13: 56.5 | H13: 3729 | N13: 3729
C14: 240224000001 | D14: 45353 | E14: Isabel Zhu | F14: Lisa | G14: 9 | H14: 547 | N14: 547
C15: 240224000004 | D15: 45353 | E15: Isabel Zhu | F15: Sesan | G15: 30 | H15: 1671 | N15: 1671
C16: 240224000007 | D16: 45353 | E16: Isabel Zhu | F16: Joy | G16: 15 | I16: 240000 | K16: 1600 | L16: 150 | M16: 7.19 | N16: 1078.5
C17: 240226000002 | D17: 45353 | E17: Isabel Zhu | F17: Lynda | G17: 31 | H17: 1646 | N17: 1646 | U17: 65
C18: 240226000003 | D18: 45353 | E18: Isabel Zhu | F18: Wu Jiao Xing | G18: 0.36 | H18: 60 | N18: 60
C19: 240226000004 | D19: 45353 | E19: Isabel Zhu | F19: Shan Nan | G19: 6 | H19: 378 | N19: 378
C20: 240226000010 | D20: 45353 | E20: 喵喵速运-Layne | F20: Yang Peng Tao | G20: 2 | I20: 27875 | K20: 1603.855 | L20: 17.38 | M20: 7.19 | N20: 124.9622
C21: 240226000026 | D21: 45353 | E21: MailMail速运 | F21: chen a tong | G21: 8.5 | H21: 456 | N21: 456
C22: 240226000027 | D22: 45353 | E22: MailMail速运 | F22: John 张 | G22: 3 | H22: 194.4 | N22: 194.4
C23: 240226000044 | D23: 45353 | E23: ying | F23: Chinex | G23: 408.5 | H23: 21026.25 | N23: 21026.25 | U23: 397
C24: 240227000009 | D24: 45353 | E24: ying | F24: Wu Zhe | G24: 10 | H24: 535.2 | N24: 535.2
C25: 240227000015 | D25: 45353 | E25: Isabel Zhu | F25: Shan Nan | G25: 1.5 | I25: 19968 | K25: 1600 | L25: 12.48 | M25: 7.19 | N25: 89.7312
C26: 240227000020 | D26: 45353 | E26: Sam.Pao | F26: Nkechi | G26: 115.5 | H26: 5297.5 | N26: 5297.5
C27: 240227000030 | D27: 45353 | E27: 喵喵速运-Layne | F27: Zhang Guo Ren | G27: 2 | H27: 135.8 | N27: 135.8
C28: 240227000032 | D28: 45353 | E28: Isabel Zhu | F28: Halifa Success | G28: 1.5 | H28: 147 | N28: 147
C29: 240227000033 | D29: 45353 | E29: Isabel Zhu | F29: Halifa Success | G29: 3 | H29: 172.8 | N29: 172.8
C30: 240301000026 | D30: 45353 | E30: Sam.Pao | F30: SKY JET | G30: 390.5 | H30: 17182 | N30: 17182
A31: JOB030325 | B31: COLL003838 | C31: 240223000030 | D31: 45353 | E31: Sam.Pao | F31: MR HE | G31: 4.5 | I31: 121696 | K31: 1600 | L31: 76.06 | M31: 7.19 | N31: 546.8714 | O31: 8365.283 | P31: 富姐 | Q31: 4400 | S31: 68.81 | V31: 4486.81 | W31: 172.57 | Z31: 172.57 | AA31: 7.19 | AB31: 1240.7783 | AC31: 5727.5883 | AD31: 2637.6947
C32: 240226000015 | D32: 45353 | E32: 喵喵速运-Layne | F32: Cheng | G32: 4.5 | H32: 1035 | N32: 1035
C33: 240227000005 | D33: 45353 | E33: Isabel Zhu | F33: Long Er | G33: 2.5 | H33: 300 | N33: 300
C34: 240227000011 | D34: 45353 | E34: ying | F34: Shang yafei | G34: 25.5 | H34: 3060 | N34: 3060
C35: 240227000022 | D35: 45353 | E35: Bella Chan | F35: han bin | G35: 0.52 | H35: 180 | N35: 180
C36: 240227000023 | D36: 45353 | E36: Bella Chan | F36: Eric Qu | G36: 2 | H36: 290 | N36: 290
C37: 240227000024 | D37: 45353 | E37: 喵喵速运-Layne | F37: Ke Ren | G37: 3.5 | H37: 391 | N37: 391
C38: 240227000031 | D38: 45353 | F38: Jinggang Pan | G38: 3.5 | I38: 90704 | K38: 1599.9999 | L38: 56.690002 | M38: 7.19 | N38: 407.60111
C39: 240227000034 | D39: 45353 | E39: Sam.Pao | F39: YunLong Hu | G39: 15 | I39: 388720 | K39: 1600 | L39: 242.95 | M39: 7.19 | N39: 1746.8105
C40: 240228000025 | D40: 45353 | E40: Sam.Pao | F40: MaiKaiNian | G40: 1.5 | H40: 235.5 | N40: 235.5 | U40: 18
C41: 240301000002 | D41: 45353 | E41: ying | F41: JOHNNIE | G41: 1.5 | H41: 172.5 | N41: 172.5
A42: JOB030326 | B42: COLL003842 | C42: 240229000001 | D42: 45354 | E42: Isabel Zhu | F42: Li Si Zhe | G42: 0.486 | H42: 115 | N42: 115 | O42: 25852.18 | P42: 富姐 | Q42: 15400 | S42: 67.81 | V42: 15467.81 | W42: 153.75 | Z42: 153.75 | AA42: 7.19 | AB42: 1105.4625 | AC42: 16573.272 | AD42: 9278.9077
C43: 240229000020 | D43: 45354 | E43: JiaFeng | F43: jiafeng | G43: 0.94 | I43: 25920 | K43: 1600 | L43: 16.2 | M43: 7.19 | N43: 116.478
C44: 240229000021 | D44: 45354 | E44: JiaFeng | F44: jiafeng | G44: 0.36 | I44: 25920 | K44: 1600 | L44: 16.2 | M44: 7.19 | N44: 116.478
C45: 240302000009 | D45: 45354 | E45: 鸿 | F45: Alice08105750388 | G45: 219 | I45: 6384924 | K45: 1800 | L45: 3547.18 | M45: 7.19 | N45: 25504.224
A46: JOB030327 | B46: COLL003840 | C46: 240226000018 | D46: 45355 | E46: ying | F46: baozi | G46: 236 | I46: 3449005 | K46: 1674.4368 | L46: 2059.8 | M46: 7.19 | N46: 14809.962 | O46: 89808.253 | P46: 顶派 | Q46: 68581.1 | S46: 120 | T46: 180 | V46: 69341.1 | W46: 1434.3 | Z46: 1434.3 | AA46: 7.19 | AB46: 10312.617 | AC46: 79653.717 | AD46: 10154.536
C47: 240226000021 | D47: 45355 | E47: 喵喵速运-Layne | F47: MA ZONG | G47: 17 | H47: 935 | N47: 935
C48: 240226000025 | D48: 45355 | E48: 喵喵速运-Layne | F48: CHENG ZHONG | G48: 2.5 | I48: 32640 | L48: 20.4 | M48: 7.19 | N48: 146.676
C49: 240226000028 | D49: 45355 | E49: 喵喵速运-Layne | F49: fast hours DM NIGHT LED | G49: 3.5 | H49: 201 | N49: 201
C50: 240226000030 | D50: 45355 | E50: Isabel Zhu | F50: Zhang Hao | G50: 7.5 | H50: 433 | N50: 433 | T50: 30
C51: 240227000002 | D51: 45355 | E51: William Wei | F51: William Wei | G51: 4.5 | H51: 257.4 | N51: 257.4
C52: 240227000019 | D52: 45355 | E52: 喵喵速运-Layne | F52: Lisa | G52: 2.5 | H52: 144.6 | N52: 144.6
C53: 240227000026 | D53: 45355 | E53: Kaylee Tan | F53: EY | G53: 23 | H53: 1363.6 | N53: 1363.6
C54: 240227000028 | D54: 45355 | E54: Kaylee Tan | F54: EY | G54: 0.21 | H54: 70 | N54: 70
C55: 240227000029 | D55: 45355 | E55: 喵喵速运-Layne | F55: MA ZONG | G55: 40.5 | I55: 516802.5 | K55: 1603.3833 | L55: 322.32 | M55: 7.19 | N55: 2317.4808 | T55: 90
C56: 240228000007 | D56: 45355 | E56: 喵喵速运-Layne | F56: Zhao Xin | G56: 2 | H56: 130.8 | N56: 130.8
C57: 240228000009 | D57: 45355 | E57: 喵喵速运-Layne | F57: James Lee | G57: 6.5 | H57: 397.2 | N57: 397.2
C58: 240228000010 | D58: 45355 | E58: 喵喵速运-Layne | F58: fast hours DM NIGHT LED | G58: 1.5 | H58: 88.2 | N58: 88.2
C59: 240228000017 | D59: 45355 | E59: Bella Chan | F59: zhang guang li | G59: 18.5 | I59: 296015 | K59: 1599.9946 | L59: 185.01 | M59: 7.19 | N59: 1330.2219
C60: 240228000022 | D60: 45355 | E60: 喵喵速运-Layne | F60: Tomonsachi | G60: 6.5 | H60: 506 | N60: 506
C61: 240229000002 | D61: 45355 | E61: Isabel Zhu | F61: Wu Jiao Xing | G61: 0.52 | H61: 60 | N61: 60
C62: 240229000004 | D62: 45355 | E62: MailMail速运 | F62: JEFF | G62: 12 | H62: 640.8 | N62: 640.8
C63: 240229000007 | D63: 45355 | E63: 喵喵速运-Layne | F63: OTW 埃德维 ABV | G63: 8 | H63: 440 | N63: 440
C64: 240229000008 | D64: 45355 | E64: 喵喵速运-Layne | F64: OTW 埃德维 ABV | G64: 12.5 | H64: 687.5 | N64: 687.5
C65: 240229000012 | D65: 45355 | E65: 喵喵速运-Layne | F65: Ye Zheng Rong | G65: 5 | I65: 63688 | K65: 1603.424 | L65: 39.72 | M65: 7.19 | N65: 285.5868
C66: 240301000006 | D66: 45355 | E66: ying | F66: Shang yafei | G66: 3 | H66: 194.4 | N66: 194.4
C67: 240301000011 | D67: 45355 | E67: Isabel Zhu | F67: Wu Jiao Xing | G67: 0.14 | H67: 60 | N67: 60
C68: 240301000015 | D68: 45355 | E68: Sam.Pao | F68: Nkechi | G68: 257 | H68: 12157 | N68: 12157
C69: 240301000017 | D69: 45355 | E69: 喵喵速运-Layne | F69: David | G69: 2.5 | H69: 144.6 | N69: 144.6
C70: 240301000018 | D70: 45355 | E70: 喵喵速运-Layne | F70: David | G70: 4 | H70: 340 | N70: 340
C71: 240301000021 | D71: 45355 | E71: Isabel Zhu | F71: Halifa Success | G71: 3.5 | H71: 303.8 | N71: 303.8
C72: 240301000023 | D72: 45355 | E72: ying | F72: chuks | G72: 499.5 | I72: 6759130 | K72: 1603.3727 | L72: 4215.57 | M72: 7.19 | N72: 30309.948 | T72: 340
C73: 240301000036 | D73: 45355 | E73: 喵喵速运-Layne | F73: Peace Elechi | G73: 4.5 | H73: 220 | N73: 220
C74: 240301000038 | D74: 45355 | E74: Sam.Pao | F74: SKY JET | G74: 429 | H74: 18876 | N74: 18876
C75: 240301000039 | D75: 45355 | E75: Sam.Pao | F75: Yuan | G75: 43.5 | I75: 442395 | K75: 1624.9587 | L75: 272.25 | M75: 7.19 | N75: 1957.4775
A76: JOB030328 | B76: COLL003841 | C76: 240226000006 | D76: 45355 | E76: ying | F76: Boulos Enterprises Limited | G76: 3.5 | H76: 167.5 | N76: 167.5 | O76: 117648.18 | P76: 顶派=79939.5 广州通达=4326.4 | Q76: 84265.9 | S76: 207.54 | V76: 85146.44 | W76: 1988.41 | Z76: 1988.41 | AA76: 7.19 | AB76: 14296.668 | AC76: 99443.108 | AD76: 18205.068
C77: 240226000029 | D77: 45355 | E77: Isabel Zhu | F77: Zhang Hao | G77: 13.5 | H77: 600 | N77: 600
C78: 240226000034 | D78: 45355 | E78: Mikey | F78: xieziqing | G78: 3.5 | H78: 188.5 | N78: 188.5
C79: 240226000046 | D79: 45355 | E79: Isabel Zhu | F79: Colin | G79: 2.5 | I79: 27200 | K79: 1600 | L79: 17 | M79: 7.19 | N79: 122.23
C80: 240226000048 | D80: 45355 | E80: 喵喵速运-Layne | F80: William Xu | G80: 59 | I80: 438134 | K80: 1136.0334 | L80: 385.67 | M80: 7.19 | N80: 2772.9673
C81: 240227000004 | D81: 45355 | E81: Isabel Zhu | F81: Wu Jiao Xing | G81: 3 | H81: 144 | N81: 144
C82: 240227000006 | D82: 45355 | E82: Isabel Zhu | F82: Mr Pan Li | G82: 37 | H82: 1665 | N82: 1665
C83: 240227000007 | D83: 45355 | E83: Isabel Zhu | F83: Mr Pan Li | G83: 73 | H83: 3585 | N83: 3585
C84: 240227000010 | D84: 45355 | E84: Bella Chan | F84: li tao | G84: 8.5 | H84: 380 | N84: 380
C85: 240227000013 | D85: 45355 | E85: Isabel Zhu | F85: Wu Jiao Xing | G85: 0.4 | H85: 50 | N85: 50
C86: 240227000014 | D86: 45355 | E86: 喵喵速运-Layne | F86: ZHENWEI YUE | G86: 0.86 | I86: 10035 | K86: 1605.6 | L86: 6.25 | M86: 7.19 | N86: 44.9375
C87: 240227000021 | D87: 45355 | E87: Bella Chan | F87: fang ming | G87: 75 | H87: 3534 | N87: 3534
C88: 240227000027 | D88: 45355 | E88: 喵喵速运-Layne | F88: 21th CENTURY | G88: 22 | I88: 301264 | K88: 1599.9999 | L88: 188.29001 | M88: 7.19 | N88: 1353.8052
C89: 240228000001 | D89: 45355 | E89: 13635229849 | F89: weng zixian | G89: 9.5 | I89: 101692 | K89: 1489.9927 | L89: 68.25 | M89: 7.19 | N89: 490.7175
C90: 240228000002 | D90: 45355 | E90: clarkzeng2 | F90: zengyugui | G90: 4 | H90: 215 | N90: 215
C91: 240228000003 | D91: 45355 | E91: clarkzeng2 | F91: zengyugui | G91: 2.5 | H91: 135.5 | N91: 135.5
C92: 240228000004 | D92: 45355 | E92: 喵喵速运-Layne | F92: Guo Hui 郭总 | G92: 0.187 | H92: 45 | N92: 45
C93: 240228000008 | D93: 45355 | E93: 喵喵速运-Layne | F93: Wang Yan Tao | G93: 1.5 | H93: 67.5 | N93: 67.5
C94: 240228000011 | D94: 45355 | E94: 喵喵速运-Layne | F94: LEO WEI | G94: 61 | I94: 716053 | K94: 1603.3789 | L94: 446.59 | M94: 7.19 | N94: 3210.9821 | U94: 283
C95: 240228000012 | D95: 45355 | E95: 喵喵速运-Layne | F95: REMI | G95: 0.9 | I95: 8610 | K95: 1474.3151 | L95: 5.84 | M95: 7.19 | N95: 41.9896
C96: 240228000014 | D96: 45355 | E96: ying | F96: chenhuaping | G96: 3 | H96: 144 | N96: 144
C97: 240228000015 | D97: 45355 | E97: ying | F97: SEGUN | G97: 65 | H97: 2730 | N97: 2730
C98: 240228000016 | D98: 45355 | E98: ying | F98: Chinex | G98: 2 | H98: 97 | N98: 97
C99: 240228000023 | D99: 45355 | E99: Bella Chan | F99: fang ming | G99: 160 | H99: 7529 | N99: 7529
C100: 240228000024 | D100: 45355 | E100: Sam.Pao | F100: Feny | G100: 32.5 | H100: 1373 | N100: 1373
...

Sheet 4月份
A1: 尼日利亚拉各斯（LOS） 应收利润明细表
A2: JOB | B2: 集装编号 | C2: 运单编号 | D2: 日期 | E2: 发货人 | F2: 收货人 | G2: 计费重量 | H2: 应 收 | O2: 总应收 | P2: 起 运 港 成 本 | U2: 代垫运费 | V2: 起运港成本 合计 | W2: 目的港成本 | AC2: 总支出 | AD2: 利润
H3: 应收RMB | I3: LOS Income(NGN) 收到(奈拉) | J3: LOS 收到USD | K3: 美元汇率 dollar currency rate | L3: 应收 到付款USD | M3: 汇率 | N3: 人民币 | P3: 代理商 | Q3: 运费 | R3: 提货费 | S3: 送货费 | T3: 包装费 | W3: 进口报关费 | X3: 到门配送费 | Y3: 转运费 | Z3: 目的港支出 | AA3: 汇率 | AB3: 人民币 | AC3: 起运港+目的港
A4: JOB040316 | B4: COLL003887 | C4: 240326000032 | D4: 45383 | E4: 喵喵速运-Layne | F4: William Xu | G4: 16.5 | I4: 312840 | K4: 1142.3772 | L4: 273.85 | M4: 7.23 | N4: 1979.9355 | O4: 4182.9204 | P4: 富姐 | Q4: 2200 | S4: 68.81 | V4: 2268.81 | W4: 57.01 | Z4: 57.01 | AA4: 7.23 | AB4: 412.1823 | AC4: 2680.9923 | AD4: 1501.9281
C5: 240328000011 | D5: 45383 | E5: Sam.Pao | F5: Jhon | G5: 11 | I5: 260590 | L5: 174.96 | M5: 7.23 | N5: 1264.9608
C6: 240329000017 | D6: 45383 | E6: Isabel Zhu | F6: Long Er | G6: 2.5 | H6: 300 | N6: 300
C7: 240329000024 | D7: 45383 | E7: ying | F7: luzong | G7: 4.5 | H7: 517.5 | N7: 517.5
C8: 240331000001 | D8: 45383 | E8: Bella Chan | F8: zhang jian fei | G8: 0.24933334 | I8: 22505 | L8: 16.67 | M8: 7.23 | N8: 120.5241
A9: JOB040317 | B9: COLL003882 | C9: 240324000003 | D9: 45383 | E9: ying | F9: Shijianguo | G9: 39 | H9: 2028 | N9: 2028 | O9: 101407.31 | P9: 顶派=80256 广州通达=3039.4 | Q9: 83295.4 | R9: 85.35 | S9: 217.54 | V9: 84738.29 | W9: 1563.98 | Z9: 1563.98 | AA9: 7.23 | AB9: 11307.575 | AC9: 96045.865 | AD9: 5361.4451
C10: 240325000034 | D10: 45383 | E10: Bella Chan | F10: huang peng | G10: 55 | H10: 2758 | N10: 2758
C11: 240325000037 | D11: 45383 | E11: ying | F11: wangweijun | G11: 5.5 | I11: 55907 | K11: 1323.2426 | L11: 42.25 | M11: 7.23 | N11: 305.4675
C12: 240325000038 | D12: 45383 | E12: ying | F12: lituo | G12: 7 | H12: 412 | N12: 412
C13: 240325000039 | D13: 45383 | E13: ying | F13: Huangpu | G13: 81 | I13: 615195 | K13: 1120.6554 | L13: 548.96 | M13: 7.23 | N13: 3968.9808
C14: 240325000043 | D14: 45383 | E14: dejare James | F14: Adam e | G14: 2.5 | I14: 24885 | K14: 1260 | L14: 19.75 | M14: 7.23 | N14: 142.7925
C15: 240326000012 | D15: 45383 | E15: Bella Chan | F15: los徐周鹏 | G15: 104 | I15: 982232.8 | K15: 1360 | L15: 722.23 | M15: 7.23 | N15: 5221.7229
C16: 240326000013 | D16: 45383 | E16: 喵喵速运-Layne | F16: ZHENWEI YUE | G16: 54.5 | I16: 422375 | K16: 1120.6553 | L16: 376.9 | M16: 7.23 | N16: 2724.987
C17: 240326000015 | D17: 45383 | E17: ying | F17: zhangjingcheng | G17: 7.5 | H17: 396 | N17: 396
C18: 240326000016 | D18: 45383 | E18: ying | F18: FeLiX | G18: 4 | H18: 200 | N18: 200
C19: 240326000017 | D19: 45383 | E19: Bella Chan | F19: Chi de jian | G19: 701.5 | H19: 33620.5 | N19: 33620.5 | U19: 650
C20: 240326000024 | D20: 45383 | E20: Isabel Zhu | F20: Shen Zhuo Wei | G20: 4 | H20: 223 | N20: 223
C21: 240326000030 | D21: 45383 | E21: 喵喵速运-Layne | F21: Spring 盛世飞扬 | G21: 3 | H21: 141 | N21: 141
C22: 240327000003 | D22: 45383 | E22: 喵喵速运-Layne | F22: ABV 胡立新 | G22: 2 | H22: 125 | N22: 125
C23: 240327000004 | D23: 45383 | E23: 喵喵速运-Layne | F23: Tuntex | G23: 4 | I23: 39438 | L23: 31.3 | M23: 7.23 | N23: 226.299
C24: 240327000009 | D24: 45383 | E24: 喵喵速运-Layne | F24: Zhao Xin | G24: 4 | H24: 247 | N24: 247
C25: 240327000010 | D25: 45383 | E25: Isabel Zhu | F25: Ope Olofinjana | G25: 0.86 | I25: 10340.2 | K25: 1261 | L25: 8.2 | M25: 7.23 | N25: 59.286
C26: 240327000011 | D26: 45383 | E26: Bella Chan | F26: fang ming | G26: 9.5 | H26: 522.5 | N26: 522.5
C27: 240327000015 | D27: 45383 | E27: ying | F27: Mr.Kola | G27: 173 | H27: 8827 | N27: 8827 | U27: 350
C28: 240327000017 | D28: 45383 | E28: ying | F28: xiaosichaoshi | G28: 0.43 | H28: 58 | N28: 58
C29: 240327000018 | D29: 45383 | E29: 喵喵速运-Layne | F29: REMI | G29: 4.5 | I29: 34618.5 | K29: 1135.4051 | L29: 30.49 | M29: 7.23 | N29: 220.4427
C30: 240327000021 | D30: 45383 | E30: ying | F30: abu | G30: 6.5 | H30: 344 | N30: 344
C31: 240327000032 | D31: 45383 | E31: Bella Chan | F31: james | G31: 87 | I31: 756378 | K31: 1260 | L31: 600.3 | M31: 7.23 | N31: 4340.169
C32: 240328000002 | D32: 45383 | E32: clarkzeng2 | F32: zengyugui | G32: 27.5 | H32: 1521.5 | N32: 1521.5
C33: 240328000004 | D33: 45383 | E33: ying | F33: Cindy | G33: 4 | H33: 223 | N33: 223
C34: 240328000005 | D34: 45383 | E34: 喵喵速运-Layne | F34: William Xu | G34: 19 | I34: 212135 | K34: 1467.7576 | L34: 144.53 | M34: 7.23 | N34: 1044.9519
C35: 240328000009 | D35: 45383 | E35: ying | F35: zoukai | G35: 18 | H35: 1100 | N35: 1100 | T35: 50
C36: 240328000010 | D36: 45383 | E36: ying | F36: mr | G36: 5 | H36: 278 | N36: 278
C37: 240328000012 | D37: 45383 | E37: Sam.Pao | F37: Jhon | G37: 20.5 | I37: 231750 | L37: 155.6 | M37: 7.23 | N37: 1124.988
C38: 240328000014 | D38: 45383 | E38: Mikey | F38: chenxiaoru | G38: 38 | H38: 1859 | N38: 1859
C39: 240328000018 | D39: 45383 | E39: 喵喵速运-Layne | F39: fast hours DM NIGHT LED | G39: 4.5 | I39: 43086 | K39: 1243.8222 | L39: 34.64 | M39: 7.23 | N39: 250.4472
C40: 240328000025 | D40: 45383 | E40: Sam.Pao | F40: XiongQiJun | G40: 5 | H40: 278 | N40: 278
C41: 240328000026 | D41: 45383 | E41: Isabel Zhu | F41: Ope Olofinjana | G41: 31.5 | I41: 279563.7 | K41: 1261 | L41: 221.7 | M41: 7.23 | N41: 1602.891
C42: 240328000029 | D42: 45383 | E42: ying | F42: shola | G42: 0.36 | H42: 64 | N42: 64
C43: 240328000030 | D43: 45383 | E43: 喵喵速运-Layne | F43: FRANK | G43: 20 | I43: 162000 | K43: 1171.2819 | L43: 138.31 | M43: 7.23 | N43: 999.9813
C44: 240328000031 | D44: 45383 | E44: 喵喵速运-Layne | F44: Ka Ka 4分部 | G44: 5.5 | H44: 302.5 | N44: 302.5
C45: 240328000032 | D45: 45383 | E45: ying | F45: tanghaiou | G45: 10.5 | H45: 607.2 | N45: 607.2
C46: 240328000035 | D46: 45383 | E46: Isabel Zhu | F46: Joy | G46: 49.5 | I46: 638750 | K46: 1265.102 | L46: 504.9 | M46: 7.23 | N46: 3650.427 | U46: 70
C47: 240328000036 | D47: 45383 | E47: Isabel Zhu | F47: Yang Jun Jie | G47: 7 | H47: 412 | N47: 412
C48: 240328000039 | D48: 45383 | E48: Bella Chan | F48: jason | G48: 1.5 | H48: 94.5 | N48: 94.5
C49: 240328000040 | D49: 45383 | E49: 慌慌 | F49: Hillter | G49: 11.5 | H49: 575 | N49: 575
C50: 240329000002 | D50: 45383 | E50: Bella Chan | F50: james | G50: 3.5 | J50: 30.22 | K50: 0 | L50: 30.220001 | M50: 7.23 | N50: 218.49061 | U50: 20
C51: 240329000003 | D51: 45383 | E51: Isabel Zhu | F51: Wu Jiao Xing | G51: 0.48 | H51: 58 | N51: 58
C52: 240329000007 | D52: 45383 | E52: Isabel Zhu | F52: Joy | G52: 57 | I52: 721175 | K52: 1265.2193 | L52: 570 | M52: 7.23 | N52: 4121.1
C53: 240329000012 | D53: 45383 | E53: 喵喵速运-Layne | F53: Zhao Xin | G53: 1.5 | H53: 93 | N53: 93
C54: 240329000014 | D54: 45383 | E54: Isabel Zhu | F54: Ope Olofinjana | G54: 0.36 | I54: 10340.2 | K54: 1261 | L54: 8.2 | M54: 7.23 | N54: 59.286
C55: 240329000016 | D55: 45383 | E55: Bella Chan | F55: james | G55: 34 | I55: 291312 | K55: 1260 | L55: 231.2 | M55: 7.23 | N55: 1671.576
C56: 240329000018 | D56: 45383 | E56: Sam.Pao | F56: Yangbin | G56: 7.5 | H56: 441 | N56: 441
C57: 240329000019 | D57: 45383 | E57: ying | F57: wangweijun | G57: 7.5 | I57: 68112 | K57: 1243.6005 | L57: 54.77 | M57: 7.23 | N57: 395.9871
C58: 240329000022 | D58: 45383 | E58: MailMail速运-演员 | F58: OGAR DENIS OGIDI PHONE | G58: 0.84 | H58: 108 | N58: 108
C59: 240329000023 | D59: 45383 | E59: 慌慌 | F59: Hillter | G59: 7.5 | H59: 375 | N59: 375
C60: 240329000029 | D60: 45383 | E60: ying | F60: Gao Tian | G60: 2.5 | I60: 27594 | K60: 1260 | L60: 21.9 | M60: 7.23 | N60: 158.337
C61: 240329000031 | D61: 45383 | E61: Isabel Zhu | F61: Halifa Success | G61: 205 | H61: 10332 | N61: 10332
C62: 240330000002 | D62: 45383 | E62: ying | F62: FeLiX | G62: 5.5 | H62: 275 | N62: 275
A63: JOB040318 | B63: COLL003884 | C63: 240323000011 | D63: 45385 | E63: Bella Chan | F63: zhang long ting | G63: 9 | H63: 486 | N63: 486 | O63: 104117.13 | P63: 顶派 | Q63: 74030.4 | S63: 130 | V63: 74323.4 | W63: 1394.91 | Z63: 1405.98 | AA63: 7.23 | AB63: 10165.235 | AC63: 84488.635 | AD63: 19628.49
C64: 240325000018 | D64: 45385 | E64: 喵喵速运-Layne | F64: Robert Hu | G64: 4.5 | H64: 325.55 | N64: 325.55 | X64: 6.9
C65: 240325000021 | D65: 45385 | E65: 喵喵速运-Layne | F65: fast hours DM NIGHT LED | G65: 4 | I65: 42228.6 | K65: 1244.9469 | L65: 33.92 | M65: 7.23 | N65: 245.2416
C66: 240325000041 | D66: 45385 | E66: ying | F66: Liwei | G66: 4.5 | H66: 305.25 | N66: 305.25
C67: 240325000042 | D67: 45385 | E67: ying | F67: Wangxiangru | G67: 3.5 | H67: 215.05 | N67: 215.05
C68: 240326000005 | D68: 45385 | E68: Bella Chan | F68: ZUO Qiyang | G68: 34.5 | H68: 2097.5 | N68: 2097.5
C69: 240326000006 | D69: 45385 | E69: 喵喵速运-Layne | F69: LEO WEI | G69: 18.5 | H69: 1073 | N69: 1073
C70: 240326000027 | D70: 45385 | E70: Julie LEE | F70: Julie lee | G70: 2.5 | H70: 171.05 | N70: 171.05
C71: 240326000031 | D71: 45385 | E71: Bella Chan | F71: ZOU Qiyang | G71: 50.5 | I71: 633360 | K71: 1467.7079 | L71: 431.53 | M71: 7.23 | N71: 3119.9619 | T71: 70
C72: 240326000033 | D72: 45385 | E72: 喵喵速运-Layne | F72: SF Jerry 顾 | G72: 5.5 | H72: 302.5 | N72: 302.5
C73: 240327000002 | D73: 45385 | E73: 喵喵速运-Layne | F73: Jerry Zhang | G73: 3 | H73: 180 | N73: 180
C74: 240327000008 | D74: 45385 | E74: 风儿吹 | F74: gan lan | G74: 7.5 | H74: 488 | N74: 488 | T74: 40
C75: 240327000012 | D75: 45385 | E75: Mikey | F75: penglijuan | G75: 8.5 | H75: 627.2 | N75: 627.2
C76: 240327000013 | D76: 45385 | E76: Bella Chan | F76: shangyafei | G76: 0.75 | H76: 70.4 | N76: 70.4
C77: 240327000025 | D77: 45385 | E77: ying | F77: Guo ZhaoXu | G77: 17 | H77: 1382.4 | N77: 1382.4 | T77: 40
C78: 240327000030 | D78: 45385 | E78: ying | F78: yunus | G78: 10 | I78: 99520 | K78: 1243.6891 | L78: 80.02 | M78: 7.23 | N78: 578.5446
C79: 240327000033 | D79: 45385 | E79: ying | F79: SEGUN | G79: 15.5 | H79: 899 | N79: 899
C80: 240327000034 | D80: 45385 | E80: ying | F80: zhaochuanhong | G80: 2 | H80: 180.8 | N80: 180.8
C81: 240327000035 | D81: 45385 | E81: ying | F81: Eric Wang | G81: 0.1 | H81: 63.8 | N81: 63.8
C82: 240328000001 | D82: 45385 | E82: clarkzeng2 | F82: zengyugui | G82: 18 | H82: 1470 | N82: 1470
C83: 240328000003 | D83: 45385 | E83: clarkzeng2 | F83: zengyugui | G83: 20 | H83: 1632.4 | N83: 1632.4
C84: 240328000006 | D84: 45385 | E84: 喵喵速运-Layne | F84: William Xu | G84: 1 | I84: 12180 | K84: 1469.24 | L84: 8.29 | M84: 7.23 | N84: 59.9367
C85: 240328000007 | D85: 45385 | E85: Isabel Zhu | F85: Gbenga | G85: 24 | I85: 298164.24 | K85: 1602 | L85: 186.12 | M85: 7.23 | N85: 1345.6476
C86: 240328000016 | D86: 45385 | E86: ying | F86: zouqiyang | G86: 5.5 | H86: 503.9 | N86: 503.9 | X86: 4.17
C87: 240328000019 | D87: 45385 | E87: Bella Chan | F87: mike anya | G87: 71 | I87: 906724 | K87: 1300 | L87: 697.48 | M87: 7.23 | N87: 5042.7804
C88: 240328000020 | D88: 45385 | E88: ying | F88: Tina | G88: 4 | H88: 271.7 | N88: 271.7
C89: 240328000021 | D89: 45385 | E89: Bella Chan | F89: he ling | G89: 4 | H89: 345.8 | N89: 345.8
C90: 240328000028 | D90: 45385 | E90: Bella Chan | F90: huang peng | G90: 12.5 | H90: 721.6 | N90: 721.6
C91: 240328000033 | D91: 45385 | E91: Bella Chan | F91: los徐周鹏 | G91: 50.5 | I91: 586791.2 | K91: 1503.9373 | L91: 390.17 | M91: 7.23 | N91: 2820.9291
C92: 240329000005 | D92: 45385 | E92: Isabel Zhu | F92: Xin Ting | G92: 12 | H92: 772 | N92: 772
C93: 240329000006 | D93: 45385 | E93: Isabel Zhu | F93: Long Er | G93: 4.5 | H93: 305 | N93: 305
C94: 240329000008 | D94: 45385 | E94: Isabel Zhu | F94: Joy | G94: 96.5 | I94: 1220975 | K94: 1265.2591 | L94: 965 | M94: 7.23 | N94: 6976.95
C95: 240329000009 | D95: 45385 | E95: Isabel Zhu | F95: Joy | G95: 101.5 | I95: 1268274 | K95: 1249.531 | L95: 1015 | M95: 7.23 | N95: 7338.45
C96: 240329000013 | D96: 45385 | E96: Isabel Zhu | F96: Ope Olofinjana | G96: 37 | I96: 360399.9 | K96: 1259.1709 | L96: 286.22 | M96: 7.23 | N96: 2069.3706
C97: 240329000015 | D97: 45385 | E97: 喵喵速运-Layne | F97: REMI | G97: 69 | I97: 574149 | K97: 1135.1305 | L97: 505.8 | M97: 7.23 | N97: 3656.934
C98: 240329000021 | D98: 45385 | E98: Mikey | F98: chenxiaoru | G98: 3.5 | H98: 215 | N98: 215
C99: 240329000025 | D99: 45385 | E99: Sam.Pao | F99: Nkechi | G99: 383 | H99: 18324.5 | N99: 18324.5
C100: 240329000032 | D100: 45385 | E100: Bella Chan | F100: james | G100: 2 | I100: 24318 | K100: 1260 | L100: 19.3 | M100: 7.23 | N100: 139.539 | U100: 13
...

Sheet 5月份
A1: 尼日利亚拉各斯（LOS） 应收利润明细表
A2: JOB | B2: 集装编号 | C2: 运单编号 | D2: 日期 | E2: 发货人 | F2: 收货人 | G2: 计费重量 | H2: 应 收 | O2: 总应收 | P2: 起 运 港 成 本 | U2: 代垫运费 | V2: 起运港成本 合计 | W2: 目的港成本 | AC2: 总支出 | AD2: 利润
H3: 应收RMB | I3: LOS Income(NGN) 收到(奈拉) | J3: LOS 收到USD | K3: 美元汇率 dollar currency rate | L3: 应收 到付款USD | M3: 汇率 | N3: 人民币 | P3: 代理商 | Q3: 运费 | R3: 提货费 | S3: 送货费 | T3: 包装费 | W3: 进口报关费 | X3: 到门配送费 | Y3: 转运费 | Z3: 目的港支出 | AA3: 汇率 | AB3: 人民币 | AC3: 起运港+目的港
A4: JOB050323 | B4: COLL003928 | C4: 240426000049 | D4: 45413 | E4: Isabel Zhu | F4: Kelly He | G4: 2.5 | H4: 287 | N4: 287 | O4: 4185.1776 | P4: 富姐 | Q4: 1600 | S4: 69.27 | V4: 1685.27 | W4: 77.9 | Z4: 77.9 | AA4: 7.22 | AB4: 562.438 | AC4: 2247.708 | AD4: 1937.4696
C5: 240428000011 | D5: 45413 | E5: 喵喵速运-Layne | F5: CHENG ZHONG | G5: 1.5 | I5: 32564 | K5: 1488.9803 | L5: 21.87 | M5: 7.22 | N5: 157.9014
C6: 240428000022 | D6: 45413 | E6: ying | F6: leoyang | G6: 2.5 | H6: 397 | N6: 397
C7: 240428000039 | D7: 45413 | E7: Bella Chan | F7: shangyafei | G7: 4 | H7: 472 | N7: 472
C8: 240428000047 | D8: 45413 | E8: 13635229849 | F8: weng zixian | G8: 0.98 | I8: 23540 | K8: 1412.9652 | L8: 16.66 | M8: 7.22 | N8: 120.2852
C9: 240429000016 | D9: 45413 | E9: ying | F9: IVAN | G9: 2.5 | I9: 59400 | K9: 1429.6029 | L9: 41.55 | M9: 7.22 | N9: 299.991
C10: 240429000022 | D10: 45413 | E10: Bella Chan | F10: YEMI | G10: 2.5 | H10: 303.5 | N10: 303.5 | U10: 16
C11: 240429000024 | D11: 45413 | E11: Bella Chan | F11: shangyafei | G11: 3 | H11: 360 | N11: 360
C12: 240430000004 | D12: 45413 | E12: Bella Chan | F12: huang peng | G12: 14.5 | H12: 1667.5 | N12: 1667.5
C13: 240430000027 | D13: 45413 | E13: Sam.Pao | F13: SHI | G13: 0.64 | H13: 120 | N13: 120
A14: JOB050324 | B14: COLL003920 | C14: 240423000032 | D14: 45413 | E14: 喵喵速运-Layne | F14: Brian | G14: 3 | I14: 37515 | K14: 1466.0023 | L14: 25.59 | M14: 7.22 | N14: 184.7598 | O14: 152511.02 | P14: 顶派 | Q14: 108643.8 | S14: 130 | V14: 109353.8 | W14: 2475.24 | Z14: 2481.47 | AA14: 7.22 | AB14: 17916.213 | AC14: 127270.01 | AD14: 25241.004
C15: 240423000041 | D15: 45413 | E15: 喵喵速运-Layne | F15: GONG | G15: 34.5 | H15: 1878.5 | N15: 1878.5 | T15: 50
C16: 240424000007 | D16: 45413 | E16: ying | F16: Ajibola Awojobi | G16: 171 | H16: 17756 | N16: 17756
C17: 240424000019 | D17: 45413 | E17: 喵喵速运-Layne | F17: Japhia 于佳慧 | G17: 3 | H17: 184.8 | N17: 184.8
C18: 240424000022 | D18: 45413 | E18: ying | F18: chenhuaping | G18: 10 | H18: 550 | N18: 550
C19: 240424000025 | D19: 45413 | E19: MailMail速运-演员 | F19: Steve | G19: 3 | H19: 184.8 | N19: 184.8
C20: 240424000027 | D20: 45413 | E20: ying | F20: kasle | G20: 0.32 | H20: 63.8 | N20: 63.8
C21: 240424000031 | D21: 45413 | E21: ying | F21: Effiong Okonessien | G21: 7.5 | H21: 565 | N21: 565 | T21: 30
C22: 240425000008 | D22: 45413 | E22: 喵喵速运-Layne | F22: Kola | G22: 10.5 | H22: 651 | N22: 651
C23: 240425000009 | D23: 45413 | E23: 喵喵速运-Layne | F23: Allen Answer | G23: 8 | H23: 464.2 | N23: 464.2
C24: 240425000014 | D24: 45413 | E24: 喵喵速运-Layne | F24: CHENG ZHONG | G24: 3 | I24: 38431 | K24: 1480.9634 | L24: 25.95 | M24: 7.22 | N24: 187.359
C25: 240425000016 | D25: 45413 | E25: Sam.Pao | F25: ShanShan | G25: 366 | H25: 26290 | N25: 26290 | T25: 400
C26: 240425000017 | D26: 45413 | E26: Isabel Zhu | F26: Mr Atama CSO | G26: 10 | H26: 700 | N26: 700
C27: 240425000018 | D27: 45413 | E27: ying | F27: Engr. Kola Balogun | G27: 3 | H27: 320 | N27: 320 | X27: 6.23
C28: 240425000019 | D28: 45413 | E28: Bella Chan | F28: zhang yong chong | G28: 0.89 | I28: 12950.53 | K28: 1466.6512 | L28: 8.83 | M28: 7.22 | N28: 63.7526
C29: 240425000027 | D29: 45413 | E29: Sam.Pao | F29: MR HU | G29: 92.5 | H29: 5596 | N29: 5596
C30: 240425000028 | D30: 45413 | E30: Sam.Pao | F30: ChenGaoHong | G30: 182.5 | H30: 10682.65 | N30: 10682.65 | T30: 50
C31: 240426000003 | D31: 45413 | E31: 喵喵速运-Layne | F31: fast hours DM NIGHT LED | G31: 7.5 | I31: 93415 | K31: 1465.1035 | L31: 63.76 | M31: 7.22 | N31: 460.3472
C32: 240426000014 | D32: 45413 | E32: 喵喵速运-Layne | F32: Lukas | G32: 3 | I32: 62496 | K32: 1516.5251 | L32: 41.21 | M32: 7.22 | N32: 297.5362
C33: 240426000018 | D33: 45413 | E33: 喵喵速运-Layne | F33: SHD-Egbe | G33: 68.5 | H33: 4110 | N33: 4110
C34: 240426000019 | D34: 45413 | E34: Sam.Pao | F34: Mr. Jiang | G34: 163 | H34: 13979 | N34: 13979
C35: 240426000020 | D35: 45413 | E35: Kaylee Tan | F35: EY | G35: 6.5 | H35: 508 | N35: 508
C36: 240426000023 | D36: 45413 | E36: Isabel Zhu | F36: Gao Yang | G36: 2 | H36: 158 | N36: 158
C37: 240426000029 | D37: 45413 | E37: 袁安医生 Dr. Andy | F37: Andy Yuan | G37: 10 | I37: 171678 | K37: 1481.0041 | L37: 115.92 | M37: 7.22 | N37: 836.9424
C38: 240426000032 | D38: 45413 | E38: 喵喵速运-Layne | F38: Hu Hai Liang | G38: 26 | I38: 392700 | K38: 1516.2162 | L38: 259 | M38: 7.22 | N38: 1869.98 | T38: 50
C39: 240426000033 | D39: 45413 | E39: Isabel Zhu | F39: Dou Dou | G39: 12.5 | H39: 762 | N39: 762
C40: 240426000035 | D40: 45413 | E40: Isabel Zhu | F40: Halifa Success | G40: 7.5 | H40: 561 | N40: 561
C41: 240426000036 | D41: 45413 | E41: Isabel Zhu | F41: Halifa Success | G41: 1.5 | H41: 155.25 | N41: 155.25
C42: 240426000039 | D42: 45413 | E42: Sam.Pao | F42: Nkechi | G42: 344.5 | H42: 17756.5 | N42: 17756.5
C43: 240426000043 | D43: 45413 | E43: Isabel Zhu | F43: Obinna Peter | G43: 28 | I43: 371598 | K43: 1481.0012 | L43: 250.91 | M43: 7.22 | N43: 1811.5702
C44: 240427000003 | D44: 45413 | E44: Sam.Pao | F44: SKY JET | G44: 797 | H44: 39451.5 | N44: 39451.5
C45: 240427000004 | D45: 45413 | E45: 亚丽 | F45: Mr zhang | G45: 1.5 | H45: 91.07001 | N45: 91.07001
C46: 240428000006 | D46: 45413 | E46: Isabel Zhu | F46: Declan | G46: 0.64 | H46: 68 | N46: 68
C47: 240428000024 | D47: 45413 | E47: 喵喵速运-Layne | F47: OTW 埃德维 | G47: 0.58 | H47: 65 | N47: 65
C48: 240428000030 | D48: 45413 | E48: Sam.Pao | F48: LuZhiLong | G48: 12.5 | H48: 970.9 | N48: 970.9
C49: 240428000033 | D49: 45413 | E49: Sam.Pao | F49: Yangbin | G49: 11 | H49: 744.7 | N49: 744.7
C50: 240428000034 | D50: 45413 | E50: Sam.Pao | F50: Xue | G50: 6 | H50: 369.6 | N50: 369.6
C51: 240428000036 | D51: 45413 | E51: Sam.Pao | F51: MaiKaiNian | G51: 12.5 | H51: 1062.5 | N51: 1062.5
C52: 240428000040 | D52: 45413 | E52: Sam.Pao | F52: DengYaDi | G52: 1.5 | H52: 99 | N52: 99
A53: JOB050325 | B53: COLL003921 | C53: 240423000050 | D53: 45413 | E53: ying | F53: Vicky Kuo | G53: 156.5 | H53: 7825 | N53: 7825 | O53: 200335.86 | P53: 顶派 | Q53: 153022 | S53: 657.99 | V53: 154972.99 | W53: 2696.39 | Z53: 2696.39 | AA53: 7.22 | AB53: 19467.936 | AC53: 174440.93 | AD53: 25894.932
C54: 240424000021 | D54: 45413 | E54: ying | F54: HWANI INDUSTRY (NIGERIA) CO.,LTD | G54: 375 | H54: 19818 | N54: 19818 | U54: 1068
C55: 240424000026 | D55: 45413 | E55: Sam.Pao | F55: Lawson Gbola | G55: 33.5 | I55: 449194 | K55: 1580 | L55: 284.3 | M55: 7.22 | N55: 2052.646
C56: 240424000036 | D56: 45413 | E56: Sam.Pao | F56: Yusky | G56: 730 | H56: 40005 | N56: 40005
C57: 240425000001 | D57: 45413 | E57: Julie LEE | F57: Julie lee | G57: 16.5 | H57: 1003 | N57: 1003 | T57: 40
C58: 240425000007 | D58: 45413 | E58: 喵喵速运-Layne | F58: Ye Hui | G58: 14 | I58: 204330 | K58: 1516.2511 | L58: 134.76 | M58: 7.22 | N58: 972.9672 | U58: 155
C59: 240425000010 | D59: 45413 | E59: Bella Chan | F59: adeniyi | G59: 116 | H59: 6032 | N59: 6032
C60: 240425000012 | D60: 45413 | E60: 喵喵速运-Layne | F60: Wen Yi Min | G60: 8 | I60: 99630 | K60: 1480.1664 | L60: 67.31 | M60: 7.22 | N60: 485.9782 | T60: 30
C61: 240426000016 | D61: 45413 | E61: Sam.Pao | F61: Wilson Liang | G61: 628.5 | I61: 6993688 | K61: 1497.6033 | L61: 4669.9204 | M61: 7.22 | N61: 33716.825
C62: 240426000022 | D62: 45413 | E62: Sam.Pao | F62: Mrs Chen | G62: 731 | H62: 39093 | N62: 39093
C63: 240426000024 | D63: 45413 | E63: 喵喵速运-Layne | F63: Kim | G63: 111.5 | I63: 1300827.5 | K63: 1480.1137 | L63: 878.87 | M63: 7.22 | N63: 6345.4414
C64: 240426000038 | D64: 45413 | E64: Sam.Pao | F64: Cherry | G64: 78 | H64: 3908 | N64: 3908
C65: 240426000052 | D65: 45413 | E65: Sam.Pao | F65: Yusky | G65: 824 | H65: 39078 | N65: 39078
A66: JOB050326 | B66: COLL003925 | C66: 240405000011 | D66: 45416 | E66: 13635229849 | F66: weng zixian | G66: 1.5 | I66: 20870 | K66: 1507.948 | L66: 13.84 | M66: 7.22 | N66: 99.9248 | O66: 241750.54 | P66: 顶派 | Q66: 176802 | S66: 211 | V66: 177748 | W66: 3021.6 | Z66: 3074.89 | AA66: 7.22 | AB66: 22200.706 | AC66: 199948.71 | AD66: 41801.838
C67: 240422000063 | D67: 45416 | E67: 13635229849 | F67: weng zixian | G67: 1.5 | I67: 19965 | K67: 1507.9305 | L67: 13.24 | M67: 7.22 | N67: 95.5928
C68: 240423000019 | D68: 45416 | E68: ying | F68: Sunday Adelena | G68: 430 | H68: 22544.22 | N68: 22544.22
C69: 240423000024 | D69: 45416 | E69: MailMail速运-演员 | F69: fengshaozheng | G69: 2.5 | H69: 220.5 | N69: 220.5
C70: 240423000028 | D70: 45416 | E70: Bella Chan | F70: james | G70: 8 | J70: 62.5 | K70: 0 | L70: 62.5 | M70: 7.22 | N70: 451.25
C71: 240423000034 | D71: 45416 | E71: Bella Chan | F71: Emmanuela Ndinwa | G71: 1.5 | I71: 14235 | K71: 1300 | L71: 10.95 | M71: 7.22 | N71: 79.059
C72: 240423000036 | D72: 45416 | E72: ying | F72: Effiong Okonessien | G72: 72 | H72: 3840 | N72: 3840 | T72: 140
C73: 240423000040 | D73: 45416 | E73: ying | F73: Eberechukwu Agwu | G73: 1.5 | I73: 20600 | K73: 1574.9235 | L73: 13.08 | M73: 7.22 | N73: 94.4376
C74: 240423000042 | D74: 45416 | E74: ying | F74: Charles | G74: 0.62 | H74: 67 | N74: 67
C75: 240423000044 | D75: 45416 | E75: Isabel Zhu | F75: Josen | G75: 0.56 | I75: 13952 | K75: 1574.7178 | L75: 8.86 | M75: 7.22 | N75: 63.9692
C76: 240423000048 | D76: 45416 | E76: Bella Chan | F76: AFRAB-CHEM Ltd. | G76: 3 | H76: 150 | N76: 150
C77: 240424000003 | D77: 45416 | E77: 慌慌 | F77: Hillter | G77: 0.2 | H77: 50 | N77: 50
C78: 240424000005 | D78: 45416 | E78: Isabel Zhu | F78: Mr Xu | G78: 0.4 | H78: 64 | N78: 64
C79: 240424000009 | D79: 45416 | E79: Kelly | F79: Lee Ming | G79: 0.68 | I79: 11685 | K79: 1425 | L79: 8.2 | M79: 7.22 | N79: 59.204
C80: 240424000012 | D80: 45416 | E80: Isabel Zhu | F80: Ope Olofinjana | G80: 0.54 | I80: 12480 | K80: 1521.9512 | L80: 8.2 | M80: 7.22 | N80: 59.204
C81: 240424000018 | D81: 45416 | E81: 慌慌 | F81: Hillter | G81: 4.5 | H81: 225 | N81: 225
C82: 240424000020 | D82: 45416 | E82: 喵喵速运-Layne | F82: YI | G82: 5 | H82: 278 | N82: 278
C83: 240424000023 | D83: 45416 | E83: Bella Chan | F83: li tao | G83: 10 | H83: 526 | N83: 526
C84: 240424000029 | D84: 45416 | E84: Bella Chan | F84: los徐周鹏 | G84: 235.5 | I84: 2485838.4 | K84: 1520.0001 | L84: 1635.4199 | M84: 7.22 | N84: 11807.732
C85: 240424000037 | D85: 45416 | E85: MailMail速运-演员 | F85: Chen Quan | G85: 2 | H85: 113 | N85: 113
C86: 240425000003 | D86: 45416 | E86: Isabel Zhu | F86: Michael Ma | G86: 2 | H86: 119 | N86: 119
C87: 240425000004 | D87: 45416 | E87: ying | F87: Hillter | G87: 22.5 | H87: 1192.5 | N87: 1192.5
C88: 240425000006 | D88: 45416 | E88: ying | F88: leoyang | G88: 0.46 | H88: 58 | N88: 58
C89: 240425000020 | D89: 45416 | E89: Isabel Zhu | F89: Kong Lei | G89: 0.9 | I89: 13000 | K89: 1618.929 | L89: 8.03 | M89: 7.22 | N89: 57.9766
C90: 240425000021 | D90: 45416 | E90: 喵喵速运-Layne | F90: SHAEK | G90: 52.5 | I90: 581438 | K90: 1509.0135 | L90: 385.31 | M90: 7.22 | N90: 2781.9382
C91: 240425000022 | D91: 45416 | E91: MailMail速运-演员 | F91: Lily | G91: 4.5 | H91: 264 | N91: 264
C92: 240425000023 | D92: 45416 | E92: Bella Chan | F92: li tao | G92: 4.5 | H92: 264 | N92: 264
C93: 240425000024 | D93: 45416 | E93: 喵喵速运-Layne | F93: William Xu | G93: 232 | I93: 2684472 | K93: 1465.6672 | L93: 1831.57 | M93: 7.22 | N93: 13223.935
C94: 240425000025 | D94: 45416 | E94: 喵喵速运-Layne | F94: ZHENWEI YUE | G94: 84 | I94: 930468 | K94: 1508.9812 | L94: 616.62 | M94: 7.22 | N94: 4451.9964
C95: 240426000001 | D95: 45416 | E95: Isabel Zhu | F95: Wu Jiao Xing | G95: 0.12 | H95: 58 | N95: 58
C96: 240426000002 | D96: 45416 | E96: Kelly | F96: Lee Ming | G96: 1.5 | I96: 19475.24 | K96: 1424.6701 | L96: 13.67 | M96: 7.22 | N96: 98.6974 | U96: 19
C97: 240426000007 | D97: 45416 | E97: 喵喵速运-Layne | F97: Shiana | G97: 9 | I97: 150420 | K97: 1574.0896 | L97: 95.56 | M97: 7.22 | N97: 689.9432 | T97: 40
C98: 240426000008 | D98: 45416 | E98: 喵喵速运-Layne | F98: Lin Qing Yuan | G98: 254.5 | I98: 2667000 | K98: 1516.2024 | L98: 1759 | M98: 7.22 | N98: 12699.98
C99: 240426000009 | D99: 45416 | E99: ying | F99: Adeyinka Rasheed | G99: 8 | H99: 446 | N99: 446
C100: 240426000011 | D100: 45416 | E100: 喵喵速运-Layne | F100: REMI | G100: 0.17 | I100: 11395 | K100: 1552.4523 | L100: 7.34 | M100: 7.22 | N100: 52.9948
...

Sheet 6月份
A1: 尼日利亚拉各斯（LOS） 应收利润明细表
A2: JOB | B2: 集装编号 | C2: 运单编号 | D2: 日期 | E2: 发货人 | F2: 收货人 | G2: 计费重量 | H2: 应 收 | O2: 总应收 | P2: 起 运 港 成 本 | U2: 代垫运费 | V2: 起运港成本 合计 | W2: 目的港成本 | AC2: 总支出 | AD2: 利润
H3: 应收RMB | I3: LOS Income(NGN) 收到(奈拉) | J3: LOS 收到USD | K3: 美元汇率 dollar currency rate | L3: 应收 到付款USD | M3: 汇率 | N3: 人民币 | P3: 代理商 | Q3: 运费 | R3: 提货费 | S3: 送货费 | T3: 包装费 | W3: 进口报关费 | X3: 到门配送费 | Y3: 转运费 | Z3: 目的港支出 | AA3: 汇率 | AB3: 人民币 | AC3: 起运港+目的港
A4: JOB060330 | B4: COLL003976 | C4: 240529000001 | D4: 45447 | E4: Julie LEE | F4: Julie lee | G4: 1.5 | H4: 180 | N4: 180 | O4: 4233.4424 | P4: 富姐 | Q4: 2400 | R4: 52.41 | V4: 2482.41 | W4: 37.28 | Z4: 37.28 | AA4: 7.24 | AB4: 269.9072 | AC4: 2752.3172 | AD4: 1481.1252
C5: 240529000005 | D5: 45447 | E5: Isabel Zhu | F5: Li Chuan Qiang | G5: 0.6 | H5: 250 | N5: 250
C6: 240530000014 | D6: 45447 | E6: Bella Chan | F6: YEMI | G6: 3.5 | H6: 402.5 | N6: 402.5
C7: 240530000019 | D7: 45447 | E7: Isabel Zhu | F7: Emmanuel Folu | G7: 0.66 | I7: 23920 | K7: 1506.2972 | L7: 15.88 | M7: 7.24 | N7: 114.9712
C8: 240530000026 | D8: 45447 | E8: 喵喵速运-Layne | F8: WEI PING | G8: 6 | H8: 690 | N8: 690
C9: 240531000014 | D9: 45447 | E9: ying | F9: yuwang | G9: 3 | H9: 375 | N9: 375 | T9: 30
C10: 240531000042 | D10: 45447 | E10: ying | F10: leoyang | G10: 0.2 | H10: 115 | N10: 115
C11: 240601000003 | D11: 45447 | E11: Isabel Zhu | F11: Mr Q | G11: 18 | I11: 430560 | K11: 1480.198 | L11: 290.88 | M11: 7.24 | N11: 2105.9712
A12: JOB060332 | B12: COLL003978 | C12: 240527000014 | D12: 45449 | E12: ying | F12: Sunday Adelena | G12: 725 | H12: 40025 | N12: 40025 | O12: 171150.17 | P12: 顶派 | Q12: 130662 | S12: 320.61 | T12: 150 | V12: 132715.61 | W12: 2144.68 | Z12: 2144.68 | AA12: 7.24 | AB12: 15527.483 | AC12: 148243.09 | AD12: 22907.082
C13: 240531000007 | D13: 45449 | E13: 喵喵速运-Layne | F13: Lin Qing Yuan | G13: 333.5 | I13: 3711855 | K13: 1520.4046 | L13: 2441.36 | M13: 7.24 | N13: 17675.446
C14: 240531000027 | D14: 45449 | E14: 喵喵速运-Layne | F14: ZHENWEI YUE | G14: 38 | I14: 416898 | K14: 1498.7166 | L14: 278.17 | M14: 7.24 | N14: 2013.9508
C15: 240531000037 | D15: 45449 | E15: Bella Chan | F15: los徐周鹏 | G15: 39 | I15: 487872 | K15: 1584 | L15: 308 | M15: 7.24 | N15: 2229.92 | T15: 80
C16: 240531000044 | D16: 45449 | E16: 喵喵速运-Layne | F16: MA ZONG | G16: 5 | H16: 290 | N16: 290
C17: 240601000006 | D17: 45449 | E17: Isabel Zhu | F17: Zhou Jia Liang | G17: 5.5 | H17: 322 | N17: 322
C18: 240601000011 | D18: 45449 | E18: 喵喵速运-Layne | F18: Mr.Cheng | G18: 1 | H18: 53 | N18: 53
C19: 240601000012 | D19: 45449 | E19: Anny | F19: Anny | G19: 2 | H19: 119 | N19: 119
C20: 240602000002 | D20: 45449 | E20: 东东 | F20: Yang | G20: 0.62 | H20: 67 | N20: 67
C21: 240602000003 | D21: 45449 | E21: 东东 | F21: Yang | G21: 2.5 | H21: 163 | N21: 163
C22: 240602000005 | D22: 45449 | E22: 喵喵速运-Layne | F22: Amy | G22: 31.5 | I22: 345586.5 | K22: 1498.7055 | L22: 230.59 | M22: 7.24 | N22: 1669.4716
C23: 240602000011 | D23: 45449 | E23: 喵喵速运-Layne | F23: Li Ce | G23: 1.5 | H23: 138 | N23: 138 | U23: 13
C24: 240602000013 | D24: 45449 | E24: 喵喵速运-Layne | F24: ZHENWEI YUE | G24: 0.92 | I24: 10971 | K24: 1498.7705 | L24: 7.32 | M24: 7.24 | N24: 52.9968
C25: 240603000013 | D25: 45449 | E25: Sam.Pao | F25: WuTao | G25: 1756 | H25: 91396 | N25: 91396 | T25: 1490
C26: 240603000016 | D26: 45449 | E26: 喵喵速运-Layne | F26: REMI | G26: 116.5 | I26: 1346041 | K26: 1578.3228 | L26: 852.83 | M26: 7.24 | N26: 6174.4892
C27: 240603000028 | D27: 45449 | E27: Isabel Zhu | F27: Halifa Success | G27: 159 | H27: 8760.9 | N27: 8760.9
A28: JOB060333 | B28: COLL003982 | C28: 240530000023 | D28: 45450 | E28: Isabel Zhu | F28: Musa Mohammed | G28: 0.92 | H28: 145 | N28: 145 | O28: 4875.118 | P28: 富姐 | Q28: 2400 | S28: 54.77 | V28: 2454.77 | W28: 130.24 | Z28: 130.24 | AA28: 7.24 | AB28: 942.9376 | AC28: 3397.7076 | AD28: 1477.4104
C29: 240531000008 | D29: 45450 | E29: 喵喵速运-Layne | F29: LUO XIANG DONG | G29: 3.5 | H29: 417.5 | N29: 417.5
C30: 240602000004 | D30: 45450 | E30: Paul | F30: Paul | G30: 3 | I30: 75100 | K30: 1502 | L30: 50 | M30: 7.24 | N30: 362
C31: 240602000008 | D31: 45450 | E31: 喵喵速运-Layne | F31: William Xu | G31: 0.62 | I31: 36320 | K31: 1644.1829 | L31: 22.09 | M31: 7.24 | N31: 159.9316
C32: 240602000009 | D32: 45450 | E32: Julie LEE | F32: Julie lee | G32: 6.5 | H32: 780 | N32: 780
C33: 240604000011 | D33: 45450 | E33: ying | F33: leoyang | G33: 4.5 | H33: 517.5 | N33: 517.5
C34: 240604000021 | D34: 45450 | E34: Bella Chan | F34: YEMI | G34: 0.67 | H34: 115 | N34: 115
C35: 240604000029 | D35: 45450 | E35: ying | F35: weixiangmin | G35: 0.14 | H35: 120 | N35: 120
C36: 240605000026 | D36: 45450 | E36: Bella Chan | F36: zheng xian sheng | G36: 2.5 | H36: 990 | N36: 990
C37: 240606000010 | D37: 45450 | E37: 鸿 | F37: Mr.Leo | G37: 5 | I37: 119949.72 | K37: 1502 | L37: 79.86 | M37: 7.24 | N37: 578.1864
C38: 240606000013 | D38: 45450 | E38: MailMail速运-演员 | F38: Chuanwei | G38: 6 | H38: 690 | N38: 690
A39: JOB060334 | B39: COLL003983 | C39: 240605000039 | D39: 45451 | E39: Isabel Zhu | F39: luka | G39: 0.44 | I39: 31050 | K39: 1499.2757 | L39: 20.71 | M39: 7.24 | N39: 149.9404 | O39: 4614.9404 | P39: 富姐 | Q39: 2400 | S39: 54.19 | V39: 2454.19 | W39: 123.17 | Z39: 123.17 | AA39: 7.24 | AB39: 891.7508 | AC39: 3345.9408 | AD39: 1268.9996
C40: 240605000047 | D40: 45451 | E40: 喵喵速运-Layne | F40: Lee Wen Wei | G40: 8.5 | H40: 1600 | N40: 1600
C41: 240606000011 | D41: 45451 | E41: ying | F41: LIXINGMAO | G41: 0.54 | H41: 115 | N41: 115
C42: 240606000019 | D42: 45451 | E42: Julie LEE | F42: Julie lee | G42: 0.52 | H42: 120 | N42: 120
C43: 240606000026 | D43: 45451 | E43: Sam.Pao | F43: YingYi | G43: 20 | H43: 2400 | N43: 2400
C44: 240607000005 | D44: 45451 | E44: 喵喵速运-Layne | F44: Lee Wen Wei | G44: 2 | H44: 230 | N44: 230
A45: JOB060335 | B45: COLL003984 | C45: 240603000009 | D45: 45453 | E45: Bella Chan | F45: YEMI | G45: 1.5 | H45: 172.5 | N45: 172.5 | O45: 6432.5932 | P45: 富姐 | Q45: 2300 | S45: 54.77 | V45: 2354.77 | W45: 78.89 | Z45: 86.14 | AA45: 7.24 | AB45: 623.6536 | AC45: 2978.4236 | AD45: 3454.1696
C46: 240604000032 | D46: 45453 | E46: ying | F46: liuqiaoying | G46: 1.5 | H46: 197.5 | N46: 197.5 | X46: 3.45
C47: 240605000014 | D47: 45453 | E47: Bella Chan | F47: zhou jia jun | G47: 6.5 | I47: 155923 | K47: 1502.0037 | L47: 103.81 | M47: 7.24 | N47: 751.5844
C48: 240605000017 | D48: 45453 | E48: ying | F48: authority | G48: 4.5 | H48: 545.5 | N48: 545.5 | X48: 3.8
C49: 240605000021 | D49: 45453 | E49: ying | F49: IVAN | G49: 3 | H49: 950 | N49: 950
C50: 240605000048 | D50: 45453 | E50: Mailmail Abv sales person 1 | F50: Fafunso | G50: 0.59 | I50: 24002 | K50: 1502.0025 | L50: 15.98 | M50: 7.24 | N50: 115.6952
C51: 240606000024 | D51: 45453 | E51: Bella Chan | F51: los徐周鹏 | G51: 31 | I51: 784301.76 | K51: 1584 | L51: 495.14 | M51: 7.24 | N51: 3584.8136
C52: 240608000006 | D52: 45453 | E52: ying | F52: leoyang | G52: 0.19 | H52: 115 | N52: 115
A53: JOB060335 | B53: COLL003985 | C53: 240607000029 | D53: 45453 | E53: Sam.Pao | F53: WuTao | G53: 11 | I53: 285660 | K53: 1498.7408 | L53: 190.6 | M53: 7.24 | N53: 1379.944 | O53: 1914.944 | P53: 富姐 | Q53: 2300 | S53: 54.77 | V53: 2354.77 | W53: 0 | Z53: 0 | AA53: 7.24 | AB53: 0 | AC53: 2354.77 | AD53: -439.826
C54: 240608000015 | D54: 45453 | E54: Bella Chan | F54: YEMI | G54: 0.52 | H54: 115 | N54: 115
C55: 240608000018 | D55: 45453 | E55: Julie LEE | F55: Julie lee | G55: 3.5 | H55: 420 | N55: 420
A56: JOB060336 | B56: COLL003981 | C56: 240602000019 | D56: 45454 | E56: 喵喵速运-Layne | F56: Fidelis ashinegwani | G56: 1.5 | H56: 90 | N56: 90 | O56: 229324.89 | P56: 顶派 | Q56: 156402 | S56: 536.96 | V56: 159791.5 | W56: 3188.23 | Z56: 3188.23 | AA56: 7.24 | AB56: 23082.785 | AC56: 182874.29 | AD56: 46450.603
C57: 240602000021 | D57: 45454 | E57: ying | F57: jiyingfeng | G57: 97.5 | I57: 1303458.3 | K57: 1498.693 | L57: 869.73 | M57: 7.24 | N57: 6296.8452 | T57: 110
C58: 240602000022 | D58: 45454 | E58: ying | F58: Nicole li | G58: 8.5 | I58: 113229 | K58: 1532.1922 | L58: 73.9 | M58: 7.24 | N58: 535.036
C59: 240602000025 | D59: 45454 | E59: ying | F59: JOSIAS/ZHANGZHAO | G59: 62.5 | H59: 6875 | N59: 6875
C60: 240603000003 | D60: 45454 | E60: ying | F60: Shijianguo | G60: 8 | H60: 462 | N60: 462
C61: 240603000004 | D61: 45454 | E61: ying | F61: zhounengquan | G61: 12 | H61: 780 | N61: 780
C62: 240603000006 | D62: 45454 | E62: ying | F62: SEGUN | G62: 22.5 | H62: 1192.5 | N62: 1192.5
C63: 240603000007 | D63: 45454 | E63: ying | F63: Cindy | G63: 2 | H63: 119 | N63: 119
C64: 240603000008 | D64: 45454 | E64: Sam.Pao | F64: Eric Ren | G64: 89 | H64: 6473 | N64: 6473
C65: 240603000017 | D65: 45454 | E65: ying | F65: felix | G65: 18 | I65: 197478 | K65: 1498.7705 | L65: 131.76 | M65: 7.24 | N65: 953.9424
C66: 240603000021 | D66: 45454 | E66: Bella Chan | F66: weng zixian | G66: 14 | I66: 182042.4 | K66: 1502 | L66: 121.2 | M66: 7.24 | N66: 877.488
C67: 240603000022 | D67: 45454 | E67: Bella Chan | F67: Wallace | G67: 27 | H67: 1439 | N67: 1439
C68: 240603000024 | D68: 45454 | E68: Bella Chan | F68: James | G68: 3 | I68: 41154 | K68: 1501.9708 | L68: 27.4 | M68: 7.24 | N68: 198.376
C69: 240603000025 | D69: 45454 | E69: ying | F69: Mr .Abubaka | G69: 8.5 | I69: 120013 | L69: 73.9 | M69: 7.24 | N69: 535.036
C70: 240603000026 | D70: 45454 | E70: 喵喵速运-Layne | F70: OTW 埃德维 | G70: 0.21 | H70: 53 | N70: 53
C71: 240604000001 | D71: 45454 | E71: 喵喵速运-Layne | F71: LOS Liu ZhongHua | G71: 229 | H71: 15445 | N71: 15445 | T71: 60
C72: 240604000002 | D72: 45454 | E72: 广州万峰非洲仓国际物流万先生 | F72: John Atageum Tata | G72: 0.5 | H72: 61 | N72: 61
C73: 240604000003 | D73: 45454 | E73: 喵喵速运-Layne | F73: Mr.Bernie | G73: 5 | I73: 72000 | K73: 1629.3279 | L73: 44.19 | M73: 7.24 | N73: 319.9356
C74: 240604000004 | D74: 45454 | E74: 喵喵速运-Layne | F74: Mr.Bernie | G74: 20.5 | I74: 276750 | K74: 1629.0911 | L74: 169.88 | M74: 7.24 | N74: 1229.9312
C75: 240604000005 | D75: 45454 | E75: 喵喵速运-Layne | F75: William Xu | G75: 45 | I75: 684859 | K75: 1643.4907 | L75: 416.71 | M75: 7.24 | N75: 3016.9804 | U75: 407
C76: 240604000009 | D76: 45454 | E76: Isabel Zhu | F76: Ope Olofinjana | G76: 1.5 | I76: 19000.3 | K76: 1501.9999 | L76: 12.650001 | M76: 7.24 | N76: 91.586007
C77: 240604000010 | D77: 45454 | E77: 喵喵速运-Layne | F77: Spring 盛世飞扬 | G77: 502 | H77: 28250 | N77: 28250 | T77: 420 | U77: 157
C78: 240604000012 | D78: 45454 | E78: Bella Chan | F78: zhang yong chong | G78: 1.5 | I78: 19051 | K78: 1506.0078 | L78: 12.650001 | M78: 7.24 | N78: 91.586007
C79: 240604000014 | D79: 45454 | E79: Isabel Zhu | F79: Halifa Success | G79: 482 | H79: 27758.2 | N79: 27758.2 | T79: 950
C80: 240604000015 | D80: 45454 | E80: Sam.Pao | F80: ChenBin | G80: 16.5 | H80: 946.5 | N80: 946.5
C81: 240604000017 | D81: 45454 | E81: ying | F81: Al Ameen Aminu | G81: 13 | H81: 799 | N81: 799
C82: 240604000020 | D82: 45454 | E82: 喵喵速运-Layne | F82: ZHENWEI YUE | G82: 11 | H82: 583 | N82: 583
C83: 240604000023 | D83: 45454 | E83: Bella Chan | F83: huang peng | G83: 24 | H83: 1328 | N83: 1328
C84: 240604000026 | D84: 45454 | E84: 喵喵速运-Layne | F84: REMI | G84: 2 | I84: 28885 | K84: 1578.4153 | L84: 18.3 | M84: 7.24 | N84: 132.492 | U84: 13
C85: 240604000030 | D85: 45454 | E85: MailMail速运-演员 | F85: David | G85: 6.5 | H85: 363.5 | N85: 363.5
C86: 240604000033 | D86: 45454 | E86: Bella Chan | F86: los徐周鹏 | G86: 315 | I86: 3728615 | K86: 1506 | L86: 2475.84 | M86: 7.24 | N86: 17925.082 | T86: 320
C87: 240605000001 | D87: 45454 | E87: ying | F87: yuwang | G87: 3 | I87: 36639 | K87: 1499.1408 | L87: 24.44 | M87: 7.24 | N87: 176.9456
C88: 240605000002 | D88: 45454 | E88: ying | F88: jiyingfeng | G88: 67.5 | I88: 835038 | K88: 1498.6862 | L88: 557.18 | M88: 7.24 | N88: 4033.9832 | T88: 110
C89: 240605000007 | D89: 45454 | E89: Sam.Pao | F89: Samuel | G89: 1.5 | H89: 151 | N89: 151
C90: 240605000008 | D90: 45454 | E90: Isabel Zhu | F90: Maureen Kingsley | G90: 4.5 | I90: 55498.9 | K90: 1502 | L90: 36.95 | M90: 7.24 | N90: 267.518
C91: 240605000009 | D91: 45454 | E91: Isabel Zhu | F91: Qingqing Zhang | G91: 20 | H91: 1060 | N91: 1060
C92: 240605000010 | D92: 45454 | E92: Isabel Zhu | F92: Li Chang Rong | G92: 81.5 | H92: 4701 | N92: 4701
C93: 240605000011 | D93: 45454 | E93: Danny | F93: zhu shen de 朱神德 | G93: 6.5 | H93: 402.5 | N93: 402.5
C94: 240605000012 | D94: 45454 | E94: ying | F94: zhuyalin | G94: 4.5 | I94: 56511 | K94: 1498.9655 | L94: 37.7 | M94: 7.24 | N94: 272.948
C95: 240605000013 | D95: 45454 | E95: Isabel Zhu | F95: Keangz Basil | G95: 2.5 | I95: 30500 | K95: 1506.1728 | L95: 20.25 | M95: 7.24 | N95: 146.61
C96: 240605000015 | D96: 45454 | E96: ying | F96: Ms Li | G96: 5 | I96: 66861 | K96: 1498.7895 | L96: 44.61 | M96: 7.24 | N96: 322.9764
C97: 240605000018 | D97: 45454 | E97: 喵喵速运-Layne | F97: Funtua Mr Lee | G97: 90 | I97: 901320 | K97: 1520.4197 | L97: 592.81 | M97: 7.24 | N97: 4291.9444
C98: 240605000019 | D98: 45454 | E98: 喵喵速运-Layne | F98: Yang Yu | G98: 0.6 | I98: 12688 | K98: 1506.8884 | L98: 8.42 | M98: 7.24 | N98: 60.9608
C99: 240605000024 | D99: 45454 | E99: ying | F99: Huangpu | G99: 0.88 | H99: 61 | N99: 61
C100: 240605000025 | D100: 45454 | E100: 喵喵速运-Layne | F100: ZHENWEI YUE | G100: 1.5 | H100: 79.5 | N100: 79.5
...

Sheet 7月份
A1: 尼日利亚拉各斯（LOS） 应收利润明细表
A2: JOB | B2: 集装编号 | C2: 运单编号 | D2: 日期 | E2: 发货人 | F2: 收货人 | G2: 计费重量 | H2: 应 收 | O2: 总应收 | P2: 起 运 港 成 本 | U2: 代垫运费 | V2: 起运港成本 合计 | W2: 目的港成本 | AC2: 总支出 | AD2: 利润
H3: 应收RMB | I3: LOS Income(NGN) 收到(奈拉) | J3: LOS 收到USD | K3: 美元汇率 dollar currency rate | L3: 应收 到付款USD | M3: 汇率 | N3: 人民币 | P3: 代理商 | Q3: 运费 | R3: 提货费 | S3: 送货费 | T3: 包装费 | W3: 进口报关费 | X3: 到门配送费 | Y3: 转运费 | Z3: 目的港支出 | AA3: 汇率 | AB3: 人民币 | AC3: 起运港+目的港
A4: JOB070339 | B4: COLL004040 | C4: 240626000043 | D4: 45477 | E4: Sam.Pao | F4: ShanShan | G4: 0.56 | H4: 115 | N4: 115 | O4: 9541.5796 | P4: 富姐 | Q4: 5000 | S4: 113.54 | V4: 5113.54 | W4: 220.25 | Z4: 231.25 | AA4: 7.26 | AB4: 1678.875 | AC4: 6792.415 | AD4: 2749.1646
C5: 240627000010 | D5: 45477 | E5: 喵喵速运-Layne | F5: Li 明亮 | G5: 13 | I5: 363285 | K5: 1764.2045 | L5: 205.92 | M5: 7.26 | N5: 1494.9792
C6: 240627000012 | D6: 45477 | E6: 喵喵速运-Layne | F6: Rose 徐艳秋 | G6: 1.5 | I6: 38100 | K6: 1536.91 | L6: 24.79 | M6: 7.26 | N6: 179.9754
C7: 240628000026 | D7: 45477 | E7: ying | F7: luzong | G7: 3 | H7: 515 | N7: 515 | X7: 11
C8: 240628000034 | D8: 45477 | E8: Bella Chan | F8: Henry Yu | G8: 2.5 | H8: 300 | N8: 300
C9: 240628000039 | D9: 45477 | E9: Bella Chan | F9: fang ming | G9: 3.5 | H9: 420 | N9: 420
C10: 240628000041 | D10: 45477 | E10: JiaFeng | F10: jiafeng | G10: 3 | I10: 72170 | K10: 1506.0518 | L10: 47.92 | M10: 7.26 | N10: 347.8992
C11: 240630000004 | D11: 45477 | E11: 鸿 | F11: Mr.Leo | G11: 6 | I11: 144319.98 | K11: 1506 | L11: 95.83 | M11: 7.26 | N11: 695.7258
C12: 240701000001 | D12: 45477 | E12: MailMail速运-演员 | F12: chen a tong | G12: 0.1 | H12: 120 | N12: 120
C13: 240701000012 | D13: 45477 | E13: Isabel Zhu | F13: Long Er | G13: 2.5 | H13: 300 | N13: 300
C14: 240701000039 | D14: 45477 | E14: Isabel Zhu | F14: Sadiq bangaje | G14: 0.37 | H14: 120 | N14: 120
C15: 240701000040 | D15: 45477 | E15: Sam.Pao | F15: Mr Guan | G15: 2 | H15: 310 | N15: 310
C16: 240701000051 | D16: 45477 | E16: Sam.Pao | F16: SHI | G16: 19 | H16: 2280 | N16: 2280
C17: 240701000057 | D17: 45477 | E17: Sam.Pao | F17: ChenBin | G17: 1 | H17: 123 | N17: 123
C18: 240702000015 | D18: 45477 | E18: Isabel Zhu | F18: KeKe | G18: 0.89416665 | H18: 120 | N18: 120
C19: 240702000025 | D19: 45477 | E19: 喵喵速运-Layne | F19: Jack | G19: 9.5 | H19: 2100 | N19: 2100
A20: JOB070340 | B20: COLL004035 | C20: 240625000028 | D20: 45477 | E20: Bella Chan | F20: huang peng | G20: 10 | H20: 576 | N20: 576 | O20: 122449.58 | P20: 顶派=93163 广州通达=5204.2 | Q20: 98367.2 | S20: 239.19 | V20: 99816.39 | W20: 1201.83 | Z20: 1251.76 | AA20: 7.26 | AB20: 9087.7776 | AC20: 108904.17 | AD20: 13545.408
C21: 240625000037 | D21: 45477 | E21: Sam.Pao | F21: MaiKaiNian | G21: 31 | H21: 1713 | N21: 1713
C22: 240625000042 | D22: 45477 | E22: ying | F22: liangyu | G22: 8.5 | H22: 490.5 | N22: 490.5
C23: 240625000046 | D23: 45477 | E23: Bella Chan | F23: huang | G23: 5.5 | H23: 333 | N23: 333
C24: 240626000007 | D24: 45477 | E24: Bella Chan | F24: Zou Qiyang | G24: 10.5 | H24: 630 | N24: 630
C25: 240626000008 | D25: 45477 | E25: 喵喵速运-Layne | F25: Lin Kai | G25: 74 | H25: 350 | K25: 0 | L25: 564.73 | M25: 7.26 | N25: 4449.9398 | T25: 30
C26: 240626000024 | D26: 45477 | E26: Isabel Zhu | F26: Ope Olofinjana | G26: 0.26 | I26: 14062.4 | K26: 1598 | L26: 8.8 | M26: 7.26 | N26: 63.888
C27: 240626000028 | D27: 45477 | E27: Bella Chan | F27: Los王红升 | G27: 6.5 | I27: 89077 | K27: 1704.823 | L27: 52.25 | M27: 7.26 | N27: 379.335 | X27: 3.79
C28: 240626000031 | D28: 45477 | E28: 喵喵速运-Layne | F28: OTW 埃德维 | G28: 1.5 | H28: 132.5 | N28: 132.5
C29: 240626000034 | D29: 45477 | E29: ying | F29: wangweijun | G29: 0.6586667 | I29: 13850 | K29: 1597.4625 | L29: 8.67 | M29: 7.26 | N29: 62.9442
C30: 240626000036 | D30: 45477 | E30: ying | F30: yingyunjiao | G30: 4 | H30: 267 | N30: 267
C31: 240626000042 | D31: 45477 | E31: 土狗泥 | F31: TOYIN S.ADEKUNLE | G31: 9.5 | H31: 602.25 | N31: 602.25
C32: 240627000001 | D32: 45477 | E32: 东东 | F32: Yang | G32: 0.32 | H32: 69 | N32: 69
C33: 240627000006 | D33: 45477 | E33: Isabel Zhu | F33: Ope Olofinjana | G33: 0.52 | I33: 14062.4 | K33: 1598 | L33: 8.8 | M33: 7.26 | N33: 63.888
C34: 240627000008 | D34: 45477 | E34: 喵喵速运-Layne | F34: SHAEK | G34: 0.62 | H34: 55 | N34: 55
C35: 240627000011 | D35: 45477 | E35: 喵喵速运-Layne | F35: William Xu | G35: 15.5 | I35: 211110 | K35: 1643.5189 | L35: 128.45 | M35: 7.26 | N35: 932.547
C36: 240627000013 | D36: 45477 | E36: 喵喵速运-Layne | F36: Robin Tai | G36: 10 | H36: 576 | N36: 576
C37: 240627000014 | D37: 45477 | E37: 喵喵速运-Layne | F37: Mr.Bernie | G37: 0.62 | I37: 15525 | K37: 1634.2105 | L37: 9.5 | M37: 7.26 | N37: 68.97
C38: 240627000015 | D38: 45477 | E38: ying | F38: huangdan | G38: 0.2 | H38: 63 | N38: 63
C39: 240627000016 | D39: 45477 | E39: 喵喵速运-Layne | F39: Hu Hai Liang | G39: 64 | I39: 862400 | K39: 1778.7311 | L39: 484.84 | M39: 7.26 | N39: 3519.9384
C40: 240627000020 | D40: 45477 | E40: ying | F40: Hillter | G40: 1.5 | H40: 82.5 | N40: 82.5
C41: 240627000021 | D41: 45477 | E41: ying | F41: Hillter | G41: 3.5 | H41: 192.5 | N41: 192.5
C42: 240627000025 | D42: 45477 | E42: 喵喵速运-Layne | F42: Sue | G42: 1.5 | H42: 117.5 | N42: 117.5 | X42: 4.82
C43: 240628000001 | D43: 45477 | E43: 喵喵速运-Layne | F43: fast hours DM NIGHT LED | G43: 4 | I43: 52731 | K43: 1575.4706 | L43: 33.47 | M43: 7.26 | N43: 242.9922
C44: 240628000004 | D44: 45477 | E44: 喵喵速运-Layne | F44: Gao Hui | G44: 14 | H44: 787.5 | N44: 787.5
C45: 240628000008 | D45: 45477 | E45: Bella Chan | F45: zhang long ting | G45: 10 | H45: 576 | N45: 576
C46: 240628000009 | D46: 45477 | E46: Isabel Zhu | F46: Joy | G46: 5 | I46: 79900 | K46: 1902.381 | L46: 42 | M46: 7.26 | N46: 304.92
C47: 240628000010 | D47: 45477 | E47: Isabel Zhu | F47: HARAFOAM | G47: 5 | I47: 75591 | K47: 1648.2992 | L47: 45.86 | M47: 7.26 | N47: 332.9436
C48: 240628000013 | D48: 45477 | E48: Isabel Zhu | F48: Li Chang Rong | G48: 27 | H48: 1785 | N48: 1785 | X48: 41.32
C49: 240628000014 | D49: 45477 | E49: 喵喵速运-Layne | F49: remi | G49: 11 | I49: 148500 | K49: 1633.6634 | L49: 90.9 | M49: 7.26 | N49: 659.934
C50: 240628000015 | D50: 45477 | E50: ying | F50: Hillter | G50: 119 | H50: 6895 | N50: 6895
C51: 240628000018 | D51: 45477 | E51: 春城 | F51: David Lee | G51: 14 | I51: 178177 | K51: 1598 | L51: 111.5 | M51: 7.26 | N51: 809.49
C52: 240628000021 | D52: 45477 | E52: ying | F52: Cindy | G52: 150 | H52: 9180 | N52: 9180 | T52: 130
C53: 240628000022 | D53: 45477 | E53: Sam.Pao | F53: Aluminium Smelter | G53: 6 | H53: 433 | N53: 433
C54: 240628000024 | D54: 45477 | E54: ying | F54: JACK | G54: 15.5 | H54: 1383.5 | N54: 1383.5
C55: 240628000025 | D55: 45477 | E55: ying | F55: chenhuaping | G55: 587.5 | I55: 6857500 | K55: 1452.0019 | L55: 4722.79 | M55: 7.26 | N55: 34287.455 | T55: 300 | U55: 90
C56: 240628000029 | D56: 45477 | E56: Bella Chan | F56: zhou ji kao rou | G56: 0.62 | H56: 69 | N56: 69
C57: 240628000030 | D57: 45477 | E57: 喵喵速运-Layne | F57: William Xu | G57: 23 | I57: 313260 | K57: 1648.0429 | L57: 190.08 | M57: 7.26 | N57: 1379.9808
C58: 240628000032 | D58: 45477 | E58: 13635229849 | F58: weng zixian | G58: 2 | I58: 30042 | K58: 1597.9787 | L58: 18.8 | M58: 7.26 | N58: 136.488
C59: 240628000035 | D59: 45477 | E59: Bella Chan | F59: zhang long ting | G59: 2 | H59: 123 | N59: 123
C60: 240628000037 | D60: 45477 | E60: Isabel Zhu | F60: Mr Peter | G60: 0.38 | I60: 14301 | K60: 1649.481 | L60: 8.67 | M60: 7.26 | N60: 62.9442
C61: 240628000038 | D61: 45477 | E61: Isabel Zhu | F61: Qingqing Zhang | G61: 19.5 | H61: 1156 | N61: 1156
C62: 240629000001 | D62: 45477 | E62: ying | F62: Nicole li | G62: 23 | I62: 306360 | K62: 1611.7424 | L62: 190.08 | M62: 7.26 | N62: 1379.9808
C63: 240629000002 | D63: 45477 | E63: Isabel Zhu | F63: Ope Olofinjana | G63: 23.5 | I63: 287320 | K63: 1597.9978 | L63: 179.8 | M63: 7.26 | N63: 1305.348
C64: 240629000003 | D64: 45477 | E64: Isabel Zhu | F64: Ope Olofinjana | G64: 0.1 | I64: 14062.4 | K64: 1598 | L64: 8.8 | M64: 7.26 | N64: 63.888
C65: 240629000004 | D65: 45477 | E65: MailMail速运-演员 | F65: LOMO | G65: 64.5 | I65: 909589 | K65: 1648.045 | L65: 551.92 | M65: 7.26 | N65: 4006.9392
C66: 240629000006 | D66: 45477 | E66: Sam.Pao | F66: TangQian | G66: 76.5 | H66: 4599 | N66: 4599
C67: 240629000007 | D67: 45477 | E67: Sam.Pao | F67: SHI | G67: 255.5 | H67: 16170 | N67: 16170 | U67: 380
C68: 240630000003 | D68: 45477 | E68: Sam.Pao | F68: Gabi | G68: 2 | H68: 135 | N68: 135
C69: 240630000005 | D69: 45477 | E69: 鸿 | F69: Alice08105750388 | G69: 55 | I69: 732783 | K69: 1589.9993 | L69: 460.87 | M69: 7.26 | N69: 3345.9162 | T69: 190
C70: 240701000003 | D70: 45477 | E70: Isabel Zhu | F70: Maureen Kingsley | G70: 3 | I70: 40386 | K70: 1590 | L70: 25.4 | M70: 7.26 | N70: 184.404
C71: 240701000007 | D71: 45477 | E71: ying | F71: Atten Engr Kola Balogun | G71: 7.5 | H71: 433.5 | N71: 433.5
C72: 240701000009 | D72: 45477 | E72: 喵喵速运-Layne | F72: William Xu | G72: 20.5 | I72: 279210 | K72: 1648.0345 | L72: 169.42 | M72: 7.26 | N72: 1229.9892
C73: 240701000016 | D73: 45477 | E73: 喵喵速运-Layne | F73: WEI | G73: 2.5 | H73: 168 | N73: 168
C74: 240701000021 | D74: 45477 | E74: 喵喵速运-Layne | F74: Ka Ka 4分部 | G74: 8.5 | H74: 637.5 | N74: 637.5
C75: 240701000022 | D75: 45477 | E75: Isabel Zhu | F75: Wu Jiao Xing | G75: 1.5 | H75: 93 | N75: 93
C76: 240701000024 | D76: 45477 | E76: ying | F76: zhounengquan | G76: 13 | H76: 830 | N76: 830
C77: 240701000031 | D77: 45477 | E77: Bella Chan | F77: zhang yong chong | G77: 0.95 | I77: 15546 | K77: 1605.9917 | L77: 9.68 | M77: 7.26 | N77: 70.2768
C78: 240701000033 | D78: 45477 | E78: Bella Chan | F78: Alex | G78: 32.5 | I78: 387779 | K78: 1574.9929 | L78: 246.21 | M78: 7.26 | N78: 1787.4846
C79: 240701000035 | D79: 45477 | E79: Bella Chan | F79: zhang long ting | G79: 25 | H79: 1383 | N79: 1383
C80: 240701000053 | D80: 45477 | E80: 喵喵速运-Layne | F80: Aminu yaro | G80: 141.5 | H80: 8580 | N80: 8580 | T80: 90
A81: JOB070341 | B81: COLL004036 | C81: 240624000044 | D81: 45477 | E81: Danny | F81: wang王鸿辉 | G81: 8 | H81: 561 | N81: 561 | O81: 71661.683 | P81: 顶派 | Q81: 60566.8 | S81: 120 | V81: 60896.8 | W81: 911.73 | Z81: 911.73 | AA81: 7.26 | AB81: 6619.1598 | AC81: 67515.96 | AD81: 4145.723
C82: 240625000001 | D82: 45477 | E82: MailMail速运-演员 | F82: Abigail Ekeke | G82: 3.5 | H82: 257.4 | N82: 257.4
C83: 240625000013 | D83: 45477 | E83: ying | F83: zhaochuanhong | G83: 2 | H83: 135.3 | N83: 135.3
C84: 240626000004 | D84: 45477 | E84: Isabel Zhu | F84: Halifa Success | G84: 0.18 | H84: 78.1 | N84: 78.1
C85: 240626000019 | D85: 45477 | E85: ying | F85: liangdawei | G85: 4.5 | I85: 62850 | K85: 1521.0552 | L85: 41.32 | M85: 7.26 | N85: 299.9832
C86: 240626000020 | D86: 45477 | E86: Isabel Zhu | F86: Lisa | G86: 20 | H86: 1393 | N86: 1393
C87: 240626000030 | D87: 45477 | E87: ying | F87: xiaohanbing | G87: 13.5 | H87: 942.15 | N87: 942.15
C88: 240626000035 | D88: 45477 | E88: ying | F88: wangleishan | G88: 30 | I88: 437580 | K88: 1597.2405 | L88: 273.96 | M88: 7.26 | N88: 1988.9496
C89: 240627000003 | D89: 45477 | E89: MailMail速运-演员 | F89: Gege | G89: 6.5 | H89: 414.15 | N89: 414.15
C90: 240627000009 | D90: 45477 | E90: 喵喵速运-Layne | F90: MA ZONG | G90: 13.5 | H90: 877.5 | N90: 877.5
C91: 240627000019 | D91: 45477 | E91: Isabel Zhu | F91: Charles obiora chukwuekmeka | G91: 20 | I91: 265464 | K91: 1568.1947 | L91: 169.28 | M91: 7.26 | N91: 1228.9728
C92: 240627000023 | D92: 45477 | E92: ying | F92: Hua Junxian | G92: 4 | H92: 297.3 | N92: 297.3 | T92: 30
C93: 240627000024 | D93: 45477 | E93: Bella Chan | F93: new hope 边鹏飞 | G93: 3.5 | I93: 51690.9 | L93: 32.51 | M93: 7.26 | N93: 236.0226
C94: 240627000027 | D94: 45477 | E94: ying | F94: lilaijuan | G94: 25 | I94: 425611.2 | K94: 1590 | L94: 267.68 | M94: 7.26 | N94: 1943.3568
C95: 240627000028 | D95: 45477 | E95: Bella Chan | F95: James | G95: 3.5 | I95: 46984 | K95: 1589.9831 | L95: 29.55 | M95: 7.26 | N95: 214.533
C96: 240628000002 | D96: 45477 | E96: 喵喵速运-Layne | F96: fast hours DM NIGHT LED | G96: 0.74 | I96: 14619.8 | K96: 1532.4738 | L96: 9.54 | M96: 7.26 | N96: 69.2604
C97: 240628000003 | D97: 45477 | E97: 喵喵速运-Layne | F97: Rachel | G97: 36 | H97: 2308 | N97: 2308
C98: 240628000011 | D98: 45477 | E98: Isabel Zhu | F98: Zhou Jia Liang | G98: 10.5 | I98: 143640 | K98: 1568.2935 | L98: 91.59 | M98: 7.26 | N98: 664.9434
C99: 240628000023 | D99: 45477 | E99: Paul | F99: Paul | G99: 5.5 | I99: 89199 | K99: 1590 | L99: 56.1 | M99: 7.26 | N99: 407.286
C100: 240628000027 | D100: 45477 | E100: Sam.Pao | F100: SKY JET | G100: 524 | H100: 27248 | N100: 27248
...

Sheet 8月份
A1: 尼日利亚拉各斯（LOS） 应收利润明细表
A2: JOB | B2: 集装编号 | C2: 运单编号 | D2: 日期 | E2: 发货人 | F2: 收货人 | G2: 计费重量 | H2: 应 收 | O2: 总应收 | P2: 起 运 港 成 本 | U2: 代垫运费 | V2: 起运港成本 合计 | W2: 目的港成本 | AC2: 总支出 | AD2: 利润
H3: 应收RMB | I3: LOS Income(NGN) 收到(奈拉) | J3: LOS 收到USD | K3: 美元汇率 dollar currency rate | L3: 应收 到付款USD | M3: 汇率 | N3: 人民币 | P3: 代理商 | Q3: 运费 | R3: 提货费 | S3: 送货费 | T3: 包装费 | W3: 进口报关费 | X3: 到门配送费 | Y3: 转运费 | Z3: 目的港支出 | AA3: 汇率 | AB3: 人民币 | AC3: 起运港+目的港
A4: JOB080355 | B4: COLL004086 | C4: 240729000061 | D4: 45509 | E4: 喵喵速运-Layne | F4: SHAEK | G4: 25.5 | I4: 286905 | K4: 1594.5368 | L4: 179.93 | M4: 7.15 | N4: 1286.4995 | O4: 64818.44 | P4: 顶派 | Q4: 49189 | S4: 181.75 | V4: 49658.75 | W4: 855.97 | Z4: 876.41 | AA4: 7.15 | AB4: 6266.3315 | AC4: 55925.082 | AD4: 8893.3585
C5: 240730000028 | D5: 45509 | E5: ying | F5: zhounengquan | G5: 3 | H5: 159 | N5: 159
C6: 240730000034 | D6: 45509 | E6: ying | F6: zhounengquan | G6: 0.28 | H6: 53 | N6: 53
C7: 240731000002 | D7: 45509 | E7: Isabel Zhu | F7: Wu Jiao Xing | G7: 3.5 | I7: 52182 | K7: 1592.8571 | L7: 32.76 | M7: 7.15 | N7: 234.234
C8: 240731000005 | D8: 45509 | E8: 喵喵速运-Layne | F8: Jinggang Pan | G8: 0.69 | I8: 14291 | K8: 1623.9773 | L8: 8.8 | M8: 7.15 | N8: 62.92
C9: 240731000006 | D9: 45509 | E9: 喵喵速运-Layne | F9: SHAEK | G9: 62.5 | I9: 737238 | K9: 1594.4763 | L9: 462.37 | M9: 7.15 | N9: 3305.9455 | U9: 181
C10: 240731000007 | D10: 45509 | E10: 喵喵速运-Layne | F10: Xiao Xiao | G10: 0.36 | H10: 94 | N10: 94 | X10: 3.44
C11: 240731000021 | D11: 45509 | E11: ying | F11: zhaojiqiang | G11: 648.5 | H11: 35667.5 | N11: 35667.5
C12: 240731000025 | D12: 45509 | E12: 喵喵速运-Layne | F12: REMI | G12: 0.36 | I12: 19120 | K12: 1710.1968 | L12: 11.18 | M12: 7.15 | N12: 79.937 | U12: 12
C13: 240731000026 | D13: 45509 | E13: Bella Chan | F13: li tao | G13: 4.5 | H13: 273 | N13: 273
C14: 240731000028 | D14: 45509 | E14: 喵喵速运-Layne | F14: William Xu | G14: 30.5 | I14: 401563 | K14: 1623.067 | L14: 247.41 | M14: 7.15 | N14: 1768.9815
C15: 240731000029 | D15: 45509 | E15: ying | F15: chenxiaojie | G15: 7 | I15: 93483 | K15: 1650.4767 | L15: 56.64 | M15: 7.15 | N15: 404.976
C16: 240731000033 | D16: 45509 | E16: ying | F16: Miss Yemisi | G16: 1 | H16: 63 | N16: 63
C17: 240731000035 | D17: 45509 | E17: Sam.Pao | F17: MaiKaiNian | G17: 27.5 | H17: 1585.5 | N17: 1585.5 | U17: 65
C18: 240731000037 | D18: 45509 | E18: Bella Chan | F18: new hope 边鹏飞 | G18: 94 | I18: 1160368.8 | K18: 1616 | L18: 718.05 | M18: 7.15 | N18: 5134.0575
C19: 240731000039 | D19: 45509 | E19: clarkzeng2 | F19: zengyugui | G19: 7.5 | H19: 478.5 | N19: 478.5
C20: 240801000002 | D20: 45509 | E20: Sam.Pao | F20: LiGuoFeng | G20: 12.5 | I20: 179939 | K20: 1623.9982 | L20: 110.8 | M20: 7.15 | N20: 792.22
C21: 240801000007 | D21: 45509 | E21: Isabel Zhu | F21: Gbenga | G21: 25.5 | I21: 336980 | K21: 1773.5789 | L21: 190 | M21: 7.15 | N21: 1358.5 | X21: 17
C22: 240801000008 | D22: 45509 | E22: Bella Chan | F22: new hope 边鹏飞 | G22: 0.82 | I22: 12346.24 | L22: 7.6400003 | M22: 7.15 | N22: 54.626002
C23: 240801000009 | D23: 45509 | E23: ying | F23: zhounengquan | G23: 2.5 | H23: 132.5 | N23: 132.5
C24: 240801000010 | D24: 45509 | E24: 喵喵速运-Layne | F24: Lin Qing Yuan | G24: 2 | I24: 25520 | K24: 1659.2978 | L24: 15.38 | M24: 7.15 | N24: 109.967
C25: 240801000011 | D25: 45509 | E25: 喵喵速运-Layne | F25: Ka Ka 4分部 | G25: 10 | H25: 600 | N25: 600
C26: 240801000012 | D26: 45509 | E26: 喵喵速运-Layne | F26: LEO WEI | G26: 31 | I26: 397358 | K26: 1580.2036 | L26: 251.46 | M26: 7.15 | N26: 1797.939
C27: 240801000016 | D27: 45509 | E27: Mr Wang | F27: Sowsco Well Services Nig Ltd | G27: 4 | H27: 374 | N27: 374
C28: 240801000021 | D28: 45509 | E28: Sam.Pao | F28: Jhon | G28: 2 | I28: 39144 | K28: 1666.4112 | L28: 23.49 | M28: 7.15 | N28: 167.9535
C29: 240802000003 | D29: 45509 | E29: Isabel Zhu | F29: Liang Liu Liu | G29: 2 | H29: 135 | N29: 135
C30: 240802000007 | D30: 45509 | E30: 喵喵速运-Layne | F30: REMI | G30: 67 | I30: 848689 | K30: 1708.8615 | L30: 496.64 | M30: 7.15 | N30: 3550.976
C31: 240802000011 | D31: 45509 | E31: 喵喵速运-Layne | F31: CHENG ZHONG | G31: 9 | I31: 123700 | K31: 1623.9989 | L31: 76.17 | M31: 7.15 | N31: 544.6155 | T31: 30
C32: 240802000014 | D32: 45509 | E32: Bella Chan | F32: Mary Oyebade | G32: 10 | I32: 129757.6 | K32: 1624 | L32: 79.9 | M32: 7.15 | N32: 571.285
C33: 240802000027 | D33: 45509 | E33: ying | F33: wangweijun | G33: 1.5 | I33: 20553 | K33: 1581 | L33: 13 | M33: 7.15 | N33: 92.95
C34: 240802000030 | D34: 45509 | E34: Isabel Zhu | F34: Latoyaandstyles | G34: 0.54 | I34: 14191.2 | K34: 1612.6364 | L34: 8.8 | M34: 7.15 | N34: 62.92
C35: 240802000031 | D35: 45509 | E35: 喵喵速运-Layne | F35: SF Jerry 顾 | G35: 4.5 | H35: 238.5 | N35: 238.5
C36: 240802000039 | D36: 45509 | E36: 喵喵速运-Layne | F36: William Xu | G36: 3 | I36: 39498 | K36: 1623.4279 | L36: 24.33 | M36: 7.15 | N36: 173.9595
C37: 240802000040 | D37: 45509 | E37: 喵喵速运-Layne | F37: Hu Hai Liang | G37: 60.5 | I37: 785592.5 | K37: 1751.756 | L37: 448.46 | M37: 7.15 | N37: 3206.489
C38: 240802000041 | D38: 45509 | E38: 喵喵速运-Layne | F38: William Xu | G38: 3.5 | I38: 46081 | K38: 1623.142 | L38: 28.39 | M38: 7.15 | N38: 202.9885
A39: JOB080356 | B39: COLL004090 | C39: 240731000036 | D39: 45510 | E39: 喵喵速运-Layne | F39: Ye Hui | G39: 8.5 | I39: 219895 | K39: 1580.1595 | L39: 139.16 | M39: 7.15 | N39: 994.994 | O39: 4889.91 | P39: 富姐 | Q39: 2400 | S39: 63.65 | U39: 75.5 | V39: 2539.15 | W39: 108.19 | Z39: 108.19 | AA39: 7.15 | AB39: 773.5585 | AC39: 3312.7085 | AD39: 1577.2015
C40: 240802000034 | D40: 45510 | E40: 喵喵速运-Layne | F40: SF Jerry 顾 | G40: 9 | H40: 1035 | N40: 1035
C41: 240803000001 | D41: 45510 | E41: ying | F41: Charles | G41: 0.1 | I41: 25415 | K41: 1580.5348 | L41: 16.08 | M41: 7.15 | N41: 114.972
C42: 240803000002 | D42: 45510 | E42: ying | F42: Charles | G42: 0.24 | I42: 25415 | K42: 1580.5348 | L42: 16.08 | M42: 7.15 | N42: 114.972
C43: 240803000003 | D43: 45510 | E43: MailMail速运-演员 | F43: Li Feilong | G43: 0.1 | I43: 25415 | K43: 1580.5348 | L43: 16.08 | M43: 7.15 | N43: 114.972
C44: 240803000019 | D44: 45510 | E44: ying | F44: LOUIS | G44: 0.5 | H44: 115 | N44: 115
C45: 240805000005 | D45: 45510 | E45: 喵喵速运-Layne | F45: WEI PING | G45: 19 | H45: 2230 | N45: 2230
C46: 240805000022 | D46: 45510 | E46: 喵喵速运-Layne | F46: NAN GUA | G46: 1.5 | H46: 170 | N46: 170
A47: JOB080357 | B47: COLL004092 | C47: 240417000037 | D47: 45510 | E47: ying | F47: Adindu | G47: 1.176 | I47: 823567 | K47: 1483.6372 | L47: 555.1 | M47: 7.15 | N47: 3968.965 | O47: 3968.965 | P47: 阿米拉海运 | Q47: 2415.7245 | S47: 69.9 | T47: 170 | V47: 2655.6245 | Z47: 0 | AB47: 0 | AC47: 2655.6245 | AD47: 1313.3405
C48: 240422000032 | D48: 45510 | E48: Isabel Zhu | F48: Halifa Success | G48: 1.4556 | H48: 3078.12 | N48: 3078.12 | O48: 3078.12 | P48: 阿米拉海运 | Q48: 2888.63 | V48: 2888.63 | Z48: 0 | AB48: 0 | AC48: 2888.63 | AD48: 189.49
C49: 240423000006 | D49: 45510 | E49: Isabel Zhu | F49: Halifa Success | G49: 0.2385 | H49: 505.99 | N49: 505.99 | O49: 505.99 | P49: 阿米拉海运 | Q49: 473.3 | V49: 473.3 | Z49: 0 | AB49: 0 | AC49: 473.3 | AD49: 32.69
C50: 240423000007 | D50: 45510 | E50: Isabel Zhu | F50: Halifa Success | G50: 10.6928 | H50: 22558.812 | N50: 22558.812 | O50: 22558.812 | P50: 阿米拉海运 | Q50: 21219.7 | V50: 21219.7 | Z50: 0 | AB50: 0 | AC50: 21219.7 | AD50: 1339.112
C51: 240423000020 | D51: 45510 | E51: ying | F51: Sunday Adelena | G51: 0.8999 | H51: 3194.55 | N51: 3194.55 | O51: 3194.55 | P51: 阿米拉海运 | Q51: 2882.7435 | V51: 2882.7435 | Z51: 0 | AB51: 0 | AC51: 2882.7435 | AD51: 311.8065
C52: 240426000045 | D52: 45510 | E52: Isabel Zhu | F52: David | G52: 2.7559 | I52: 1709040 | K52: 1598.0102 | L52: 1069.48 | M52: 7.15 | N52: 7646.782 | O52: 7646.782 | P52: 阿米拉海运 | Q52: 5469.0615 | U52: 1950 | V52: 7419.0615 | Z52: 0 | AB52: 0 | AC52: 7419.0615 | AD52: 227.7205
C53: 240430000009 | D53: 45510 | E53: ying | F53: Nura | G53: 0.2444 | H53: 1066 | N53: 1066 | O53: 1066 | P53: 阿米拉海运 | Q53: 484.806 | V53: 484.806 | Z53: 0 | AB53: 0 | AC53: 484.806 | AD53: 581.194
C54: 240506000049 | D54: 45510 | E54: Sam.Pao | F54: MaiKaiNian | G54: 0.206 | H54: 556 | N54: 556 | O54: 556 | P54: 阿米拉海运 | Q54: 510.0165 | V54: 510.0165 | Z54: 0 | AB54: 0 | AC54: 510.0165 | AD54: 45.9835
C55: 240506000052 | D55: 45510 | E55: Bella Chan | F55: james | G55: 1.9048 | J55: 611.2 | L55: 611.19995 | M55: 7.15 | N55: 4370.0796 | O55: 4370.0796 | P55: 阿米拉海运 | Q55: 4256.091 | V55: 4256.091 | Z55: 0 | AB55: 0 | AC55: 4256.091 | AD55: 113.98864
C56: 240509000007 | D56: 45510 | E56: Isabel Zhu | F56: Halifa Success | G56: 0.734 | H56: 1613.23 | N56: 1613.23 | O56: 1613.23 | P56: 阿米拉海运 | Q56: 1512.04 | V56: 1512.04 | Z56: 0 | AB56: 0 | AC56: 1512.04 | AD56: 101.19
C57: 240511000020 | D57: 45510 | E57: ying | F57: Chinwe | G57: 2.8418 | H57: 7884 | N57: 7884 | O57: 7884 | P57: 阿米拉海运 | Q57: 6266.169 | V57: 6266.169 | Z57: 0 | AB57: 0 | AC57: 6266.169 | AD57: 1617.831
C58: 240513000044 | D58: 45510 | E58: Isabel Zhu | F58: Halifa Success | G58: 4.537 | H58: 9571.68 | N58: 9571.68 | O58: 9571.68 | P58: 阿米拉海运 | Q58: 9003.456 | V58: 9003.456 | Z58: 0 | AB58: 0 | AC58: 9003.456 | AD58: 568.224
C59: 240513000049 | D59: 45510 | E59: Isabel Zhu | F59: Halifa Success | G59: 0.2282 | H59: 484.91003 | N59: 484.91003 | O59: 484.91003 | P59: 阿米拉海运 | Q59: 469.4445 | V59: 469.4445 | Z59: 0 | AB59: 0 | AC59: 469.4445 | AD59: 15.46553
C60: 240523000022 | D60: 45510 | E60: Sam.Pao | F60: Nick Wang | G60: 0.2559 | H60: 1795 | N60: 1795 | O60: 1795 | P60: 阿米拉海运 | Q60: 534.051 | V60: 534.051 | Z60: 0 | AB60: 0 | AC60: 534.051 | AD60: 1260.949
C61: 240613000019 | D61: 45510 | E61: 喵喵速运-Layne | F61: WENDY | G61: 1.7727 | H61: 3836.7 | N61: 3836.7 | O61: 3836.7 | P61: 阿米拉海运 | Q61: 3648.246 | V61: 3648.246 | Z61: 0 | AB61: 0 | AC61: 3648.246 | AD61: 188.454
C62: 240702000032 | D62: 45510 | E62: Sam.Pao | F62: Mr Zhuan | G62: 7.0018 | H62: 15692 | N62: 15692 | O62: 15692 | P62: 阿米拉海运 | Q62: 12865.66 | V62: 12865.66 | Z62: 0 | AB62: 0 | AC62: 12865.66 | AD62: 2826.3395
C63: 240716000033 | D63: 45510 | E63: Sam.Pao | F63: Tunde Adisa | G63: 1.5347 | H63: 3626.4 | N63: 3626.4 | O63: 3626.4 | P63: 阿米拉海运 | Q63: 3270.9705 | V63: 3270.9705 | X63: 27.44 | Z63: 27.44 | AA63: 7.15 | AB63: 196.196 | AC63: 3467.1665 | AD63: 159.2335
C64: 240716000036 | D64: 45510 | E64: Sam.Pao | F64: DING | G64: 0.1268 | H64: 520 | N64: 520 | O64: 520 | P64: 阿米拉海运 | Q64: 279.3735 | V64: 279.3735 | Z64: 0 | AB64: 0 | AC64: 279.3735 | AD64: 240.6265
C65: 240722000033 | D65: 45510 | E65: 喵喵速运-Layne | F65: Wendy | G65: 35.0267 | H65: 79936.44 | N65: 79936.44 | O65: 79936.44 | P65: 阿米拉海运 | Q65: 66806.21 | V65: 66806.21 | X65: 1341.46 | Z65: 1341.46 | AA65: 7.15 | AB65: 9591.439 | AC65: 76397.649 | AD65: 3538.791
C66: 240723000023 | D66: 45510 | E66: 喵喵速运-Layne | F66: Blessing | G66: 24.0556 | H66: 59692.99 | N66: 59692.99 | O66: 59692.99 | P66: 阿米拉海运 | Q66: 47738.544 | V66: 47738.544 | X66: 1234.17 | Z66: 1234.17 | AA66: 7.15 | AB66: 8824.3155 | AC66: 56562.859 | AD66: 3130.1305
A67: JOB080358 | B67: COLL004091 | C67: 240802000036 | D67: 45510 | E67: JiaFeng | F67: jiafeng | G67: 2.5 | I67: 64850 | K67: 1624.0922 | L67: 39.93 | M67: 7.15 | N67: 285.4995 | O67: 3794.452 | P67: 富姐 | Q67: 2400 | S67: 63.65 | V67: 2622.65 | W67: 104.99 | Z67: 104.99 | AA67: 7.15 | AB67: 750.6785 | AC67: 3373.3285 | AD67: 421.1235
C68: 240802000037 | D68: 45510 | E68: ying | F68: shagamu | G68: 0.76 | H68: 190 | N68: 190
C69: 240805000010 | D69: 45510 | E69: Isabel Zhu | F69: Wang Jian | G69: 14.5 | I69: 400341.5 | K69: 1580.1914 | L69: 253.35 | M69: 7.15 | N69: 1811.4525 | U69: 144
C70: 240805000019 | D70: 45510 | E70: Bella Chan | F70: Shuai ge | G70: 7.5 | H70: 900 | N70: 900
C71: 240805000028 | D71: 45510 | E71: 喵喵速运-Layne | F71: Lee Wen Wei | G71: 2.5 | H71: 362.5 | N71: 362.5
C72: 240805000046 | D72: 45510 | E72: Bella Chan | F72: YEMI | G72: 2 | H72: 245 | N72: 245 | U72: 15
A73: JOB080359 | B73: COLL004084 | C73: 240724000013 | D73: 45512 | E73: ying | F73: Wangxiangru | G73: 34.5 | H73: 2096 | N73: 2096 | O73: 92702.254 | P73: 顶派 | Q73: 71408.4 | S73: 130 | V73: 72467.4 | W73: 994.62 | Z73: 1059.74 | AA73: 7.15 | AB73: 7577.141 | AC73: 80044.541 | AD73: 12657.713
C74: 240727000011 | D74: 45512 | E74: ying | F74: Oba Adeoriyomi Oyebo | G74: 177.5 | I74: 2599425 | K74: 1608.7542 | L74: 1615.8 | M74: 7.15 | N74: 11552.97 | T74: 450
C75: 240729000016 | D75: 45512 | E75: 喵喵速运-Layne | F75: Jerry Zhang | G75: 2 | H75: 137.5 | N75: 137.5
C76: 240729000024 | D76: 45512 | E76: ying | F76: Charles | G76: 7.5 | I76: 106337 | K76: 1594.4969 | L76: 66.69 | M76: 7.15 | N76: 476.8335
C77: 240729000033 | D77: 45512 | E77: 喵喵速运-Layne | F77: WEI | G77: 4.5 | H77: 292.5 | N77: 292.5
C78: 240729000044 | D78: 45512 | E78: Isabel Zhu | F78: Li Si Zhe | G78: 2 | H78: 135 | N78: 135
C79: 240729000049 | D79: 45512 | E79: William Wei | F79: William Wei | G79: 0.55 | H79: 88.2 | N79: 88.2
C80: 240730000006 | D80: 45512 | E80: Bella Chan | F80: zhang long ting | G80: 14 | H80: 884.4 | N80: 884.4
C81: 240730000011 | D81: 45512 | E81: ying | F81: zhounengquan | G81: 0.6 | H81: 69 | N81: 69
C82: 240730000012 | D82: 45512 | E82: ying | F82: MIranda | G82: 50 | H82: 3033.8 | N82: 3033.8
C83: 240730000014 | D83: 45512 | E83: ying | F83: wangmeng | G83: 7 | H83: 550.5 | N83: 550.5 | X83: 14.46
C84: 240730000021 | D84: 45512 | E84: Jr.Feng.Shiue | F84: Abubakar | G84: 10.5 | H84: 934.5 | N84: 934.5
C85: 240730000037 | D85: 45512 | E85: Mailmail Abv sales person 1 | F85: Kalio Edith | G85: 97 | I85: 1159496 | K85: 1623.7165 | L85: 714.10004 | M85: 7.15 | N85: 5105.8153 | T85: 40
C86: 240730000044 | D86: 45512 | E86: ying | F86: Sagamu | G86: 0.45 | H86: 88.2 | N86: 88.2
C87: 240730000045 | D87: 45512 | E87: 喵喵速运-Layne | F87: NAN GUA | G87: 0.72 | H87: 80 | N87: 80
C88: 240730000046 | D88: 45512 | E88: 喵喵速运-Layne | F88: SF Jerry 顾 | G88: 0.97 | H88: 60 | N88: 60
C89: 240730000047 | D89: 45512 | E89: 喵喵速运-Layne | F89: Ding Hui Fang | G89: 3 | H89: 201.3 | N89: 201.3
C90: 240730000049 | D90: 45512 | E90: Bella Chan | F90: zhou ji kao rou | G90: 0.88 | H90: 96 | N90: 96
C91: 240731000004 | D91: 45512 | E91: Bella Chan | F91: Johnson | G91: 3.5 | H91: 360.25 | N91: 360.25
C92: 240731000009 | D92: 45512 | E92: 喵喵速运-Layne | F92: Lukas | G92: 2.5 | I92: 40840 | K92: 1580.4954 | L92: 25.84 | M92: 7.15 | N92: 184.756
C93: 240731000011 | D93: 45512 | E93: 喵喵速运-Layne | F93: Zhao Xin | G93: 12 | H93: 782 | N93: 782
C94: 240731000013 | D94: 45512 | E94: ying | F94: hujunle | G94: 9 | H94: 570.9 | N94: 570.9
C95: 240731000016 | D95: 45512 | E95: MailMail速运-演员 | F95: chenchen | G95: 4 | H95: 299.3 | N95: 299.3 | X95: 4.4
C96: 240731000017 | D96: 45512 | E96: Sam.Pao | F96: ShanShan | G96: 19.5 | H96: 1269.25 | N96: 1269.25 | T96: 40
C97: 240731000020 | D97: 45512 | E97: MailMail速运-演员 | F97: David | G97: 67 | H97: 2399 | N97: 2399 | T97: 140
C98: 240731000027 | D98: 45512 | E98: Isabel Zhu | F98: Auwal Tee | G98: 6 | I98: 93081.6 | K98: 1616 | L98: 57.6 | M98: 7.15 | N98: 411.84
C99: 240731000030 | D99: 45512 | E99: ying | F99: Harry | G99: 20 | H99: 1121.6 | N99: 1121.6
C100: 240731000034 | D100: 45512 | E100: Isabel Zhu | F100: Li Si Zhe | G100: 2 | H100: 135 | N100: 135
...

Sheet 9月份
A1: 尼日利亚拉各斯（LOS） 应收利润明细表
A2: JOB | B2: 集装编号 | C2: 运单编号 | D2: 日期 | E2: 发货人 | F2: 收货人 | G2: 计费重量 | H2: 应 收 | O2: 总应收 | P2: 起 运 港 成 本 | U2: 代垫运费 | V2: 起运港成本 合计 | W2: 目的港成本 | AC2: 总支出 | AD2: 利润
H3: 应收RMB | I3: LOS Income(NGN) 收到(奈拉) | J3: LOS 收到USD | K3: 美元汇率 dollar currency rate | L3: 应收 到付款USD | M3: 汇率 | N3: 人民币 | P3: 代理商 | Q3: 运费 | R3: 提货费 | S3: 送货费 | T3: 包装费 | W3: 进口报关费 | X3: 到门配送费 | Y3: 转运费 | Z3: 目的港支出 | AA3: 汇率 | AB3: 人民币 | AC3: 起运港+目的港
A4: JOB090348 | B4: COLL004137 | C4: 240823000023 | D4: 45537 | E4: MailMail速运-演员 | F4: chenchen | G4: 2.5 | H4: 319.5 | N4: 319.5 | O4: 5142.9024 | P4: 富姐 | Q4: 2500 | S4: 71.98 | V4: 2669.98 | W4: 129.27 | Z4: 129.27 | AA4: 7.08 | AB4: 915.2316 | AC4: 3585.2116 | AD4: 1557.6908
C5: 240828000001 | D5: 45537 | E5: Sam.Pao | F5: YunLong Hu | G5: 9 | I5: 238050 | K5: 1628.4717 | L5: 146.18 | M5: 7.08 | N5: 1034.9544
C6: 240828000006 | D6: 45537 | E6: Isabel Zhu | F6: KeKe | G6: 3.5 | H6: 420 | N6: 420
C7: 240828000068 | D7: 45537 | E7: Bella Chan | F7: Ai Ge Li | G7: 0.85866666 | H7: 255 | N7: 255
C8: 240829000002 | D8: 45537 | E8: Isabel Zhu | F8: Jumoke | G8: 3.5 | H8: 402 | N8: 402
C9: 240829000008 | D9: 45537 | E9: 喵喵速运-Layne | F9: Chen Yi | G9: 1.5 | I9: 56643 | K9: 1678.3111 | L9: 33.75 | M9: 7.08 | N9: 238.95
C10: 240829000027 | D10: 45537 | E10: 喵喵速运-Layne | F10: Mr.Jin | G10: 1.5 | H10: 172.5 | N10: 172.5
C11: 240829000035 | D11: 45537 | E11: 喵喵速运-Layne | F11: NAN GUA | G11: 0.52 | H11: 170 | N11: 170
C12: 240829000038 | D12: 45537 | E12: 喵喵速运-Layne | F12: MA ZONG | G12: 0.94 | H12: 120 | N12: 120
C13: 240830000006 | D13: 45537 | E13: Isabel Zhu | F13: Liu Mao | G13: 0.5 | H13: 170 | N13: 170
C14: 240830000007 | D14: 45537 | E14: Isabel Zhu | F14: Liu Mao | G14: 0.8 | H14: 255 | N14: 255
C15: 240830000008 | D15: 45537 | E15: Isabel Zhu | F15: Liu Mao | G15: 0.9 | H15: 170 | N15: 170
C16: 240830000009 | D16: 45537 | E16: Isabel Zhu | F16: Liu Mao | G16: 0.8 | H16: 170 | N16: 170
C17: 240830000011 | D17: 45537 | E17: Isabel Zhu | F17: Liu Mao | G17: 0.68 | H17: 170 | N17: 170
C18: 240830000043 | D18: 45537 | E18: 喵喵速运-Layne | F18: Lin Qing Yuan | G18: 6.5 | I18: 207025 | K18: 1734.6041 | L18: 119.35 | M18: 7.08 | N18: 844.998 | U18: 98
C19: 240831000001 | D19: 45537 | E19: Sam.Pao | F19: ChenBin | G19: 2 | H19: 230 | N19: 230
A20: JOB090349 | B20: COLL004140 | C20: 240829000031 | D20: 45538 | E20: Bella Chan | F20: Jahnson | G20: 2 | H20: 360 | N20: 360 | O20: 10760 | P20: 富姐 | Q20: 4800 | S20: 55.98 | V20: 4855.98 | W20: 252.83 | Z20: 273.95 | AA20: 7.08 | AB20: 1939.566 | AC20: 6795.546 | AD20: 3964.454
C21: 240830000010 | D21: 45538 | E21: Isabel Zhu | F21: Liu Mao | G21: 0.68 | H21: 170 | N21: 170
C22: 240830000012 | D22: 45538 | E22: Isabel Zhu | F22: Liu Mao | G22: 0.9 | H22: 170 | N22: 170
C23: 240830000032 | D23: 45538 | E23: ying | F23: luzong | G23: 0.56 | H23: 115 | N23: 115
C24: 240831000017 | D24: 45538 | E24: 喵喵速运-Layne | F24: LING | G24: 2 | H24: 340 | N24: 340
C25: 240831000018 | D25: 45538 | E25: 喵喵速运-Layne | F25: MA ZONG | G25: 6.5 | H25: 780 | N25: 780
C26: 240901000007 | D26: 45538 | E26: ying | F26: Han | G26: 2 | H26: 300 | N26: 300
C27: 240901000008 | D27: 45538 | E27: 喵喵速运-Layne | F27: Zheng Hao | G27: 15 | H27: 1800 | N27: 1800
C28: 240902000001 | D28: 45538 | E28: Julie LEE | F28: Julie lee | G28: 6 | H28: 720 | N28: 720
C29: 240902000004 | D29: 45538 | E29: Julie LEE | F29: Julie lee | G29: 1.5 | H29: 180 | N29: 180
C30: 240902000019 | D30: 45538 | E30: 喵喵速运-Layne | F30: Sule Adekunle | G30: 8 | H30: 950 | N30: 950 | X30: 21.12
C31: 240902000051 | D31: 45538 | E31: 喵喵速运-Layne | F31: Rabiu Mohammed | G31: 7.5 | H31: 1560 | N31: 1560
C32: 240902000052 | D32: 45538 | E32: 喵喵速运-Layne | F32: Rabiu Mohammed | G32: 5.5 | H32: 1365 | N32: 1365
C33: 240902000053 | D33: 45538 | E33: 喵喵速运-Layne | F33: Rabiu Mohammed | G33: 9 | H33: 1950 | N33: 1950
A34: JOB090353 | B34: COLL004146 | C34: 240830000034 | D34: 45540 | E34: ying | F34: jj | G34: 0.7475 | I34: 35550 | K34: 1678.4703 | L34: 21.18 | M34: 7.08 | N34: 149.9544 | O34: 8272.4544 | P34: 富姐 | Q34: 4800 | S34: 51.08 | V34: 4946.08 | W34: 177.2 | Z34: 177.2 | AA34: 7.08 | AB34: 1254.576 | AC34: 6200.656 | AD34: 2071.7984
C35: 240902000002 | D35: 45540 | E35: Julie LEE | F35: Julie lee | G35: 1.5 | H35: 120 | N35: 120
C36: 240902000010 | D36: 45540 | E36: 喵喵速运-Layne | F36: Lee Wen Wei | G36: 5 | H36: 800 | N36: 800
C37: 240902000026 | D37: 45540 | E37: Isabel Zhu | F37: Mr.Wang Mian | G37: 0.76 | H37: 115 | N37: 115
C38: 240902000035 | D38: 45540 | E38: Isabel Zhu | F38: Long Er | G38: 9 | H38: 1080 | N38: 1080
C39: 240903000023 | D39: 45540 | E39: Bella Chan | F39: shangyafei | G39: 45.5 | H39: 5555 | N39: 5555 | T39: 95
C40: 240903000036 | D40: 45540 | E40: Sam.Pao | F40: MaiKaiNian | G40: 1.5 | H40: 172.5 | N40: 172.5
C41: 240903000049 | D41: 45540 | E41: 喵喵速运-Layne | F41: Japhia 于佳慧 | G41: 1 | H41: 100 | N41: 100
C42: 240904000019 | D42: 45540 | E42: Bella Chan | F42: xu ming | G42: 0.48 | H42: 180 | N42: 180
A43: JOB090354 | B43: COLL004141 | C43: 240826000043 | D43: 45541 | E43: Bella Chan | F43: los徐周鹏 | G43: 21.5 | I43: 271814.4 | K43: 1760 | L43: 154.44 | M43: 7.08 | N43: 1093.4352 | O43: 63532.478 | P43: 顶派 | Q43: 44582 | S43: 172.75 | V43: 45082.75 | W43: 1040.23 | Z43: 1040.23 | AA43: 7.08 | AB43: 7364.8284 | AC43: 52447.578 | AD43: 11084.899
C44: 240828000039 | D44: 45541 | E44: 喵喵速运-Layne | F44: Leng Feng | G44: 4.5 | H44: 360 | N44: 360
C45: 240828000059 | D45: 45541 | E45: 喵喵速运-Layne | F45: REMI | G45: 11.5 | I45: 143692.5 | K45: 1734.7881 | L45: 82.83 | M45: 7.08 | N45: 586.4364
C46: 240829000014 | D46: 45541 | E46: ying | F46: Hillter | G46: 0.7 | H46: 51 | N46: 51
C47: 240829000024 | D47: 45541 | E47: Isabel Zhu | F47: Olatunde Mustapha | G47: 7 | H47: 399 | N47: 399
C48: 240830000025 | D48: 45541 | E48: ying | F48: Tom chen | G48: 0.51 | I48: 16326 | K48: 1700.625 | L48: 9.6 | M48: 7.08 | N48: 67.968
C49: 240830000031 | D49: 45541 | E49: Bella Chan | F49: zhang long ting | G49: 11 | H49: 633 | N49: 633
C50: 240830000036 | D50: 45541 | E50: ying | F50: Cui Jinghui | G50: 22.5 | H50: 1427 | N50: 1427
C51: 240830000038 | D51: 45541 | E51: ying | F51: Ayo | G51: 353.5 | H51: 20503 | N51: 20503
C52: 240830000039 | D52: 45541 | E52: 喵喵速运-Layne | F52: fast hours DM NIGHT LED | G52: 0.34 | H52: 63 | N52: 63
C53: 240830000042 | D53: 45541 | E53: Sam.Pao | F53: Ah Jie | G53: 32.5 | I53: 463767 | K53: 1711.0017 | L53: 271.05 | M53: 7.08 | N53: 1919.034
C54: 240830000049 | D54: 45541 | F54: javen | G54: 0.45 | I54: 14916 | K54: 1695 | L54: 8.8 | M54: 7.08 | N54: 62.304
C55: 240831000005 | D55: 45541 | E55: 喵喵速运-Layne | F55: JoJo | G55: 1 | I55: 20170.5 | K55: 1695 | L55: 11.9 | M55: 7.08 | N55: 84.252 | U55: 22
C56: 240831000007 | D56: 45541 | E56: ying | F56: Desmond | G56: 17.5 | H56: 1100 | N56: 1100
C57: 240831000010 | D57: 45541 | E57: ying | F57: Shijianguo | G57: 2 | H57: 123 | N57: 123
C58: 240901000002 | D58: 45541 | E58: ying | F58: Cindy | G58: 8 | H58: 462 | N58: 462
C59: 240901000004 | D59: 45541 | E59: ying | F59: Frank | G59: 5 | I59: 71659.5 | K59: 1674.6787 | L59: 42.79 | M59: 7.08 | N59: 302.9532
C60: 240901000006 | D60: 45541 | E60: clarkzeng2 | F60: zengyugui | G60: 25.5 | H60: 1539 | N60: 1539
C61: 240902000018 | D61: 45541 | E61: MailMail速运-演员 | F61: HRH Iowe Augustine Nwankwo | G61: 2 | H61: 123 | N61: 123
C62: 240902000022 | D62: 45541 | E62: Isabel Zhu | F62: Mr Zhou Jia Liang | G62: 11.5 | I62: 157100 | K62: 1681.4728 | L62: 93.43 | M62: 7.08 | N62: 661.4844
C63: 240902000028 | D63: 45541 | E63: Isabel Zhu | F63: Lizzy | G63: 4.5 | I63: 64156 | K63: 1695.0066 | L63: 37.85 | M63: 7.08 | N63: 267.978
C64: 240902000029 | D64: 45541 | E64: 喵喵速运-Layne | F64: Leng Feng | G64: 0.62 | H64: 65 | N64: 65
C65: 240902000030 | D65: 45541 | E65: Isabel Zhu | F65: Wu Jiao Xing | G65: 5.5 | H65: 333 | N65: 333
C66: 240902000033 | D66: 45541 | E66: Isabel Zhu | F66: Joy | G66: 57 | I66: 966150 | K66: 1695 | L66: 570 | M66: 7.08 | N66: 4035.6
C67: 240902000034 | D67: 45541 | E67: ying | F67: Hillter | G67: 6 | H67: 306 | N67: 306
C68: 240902000036 | D68: 45541 | E68: Isabel Zhu | F68: Halifa Success | G68: 8.5 | H68: 578 | N68: 578
C69: 240902000037 | D69: 45541 | E69: Isabel Zhu | F69: Halifa Success | G69: 15 | H69: 986 | N69: 986
C70: 240902000045 | D70: 45541 | E70: Bella Chan | F70: zhang long ting | G70: 22.5 | H70: 1415.05 | N70: 1415.05 | U70: 45
C71: 240902000047 | D71: 45541 | E71: Bella Chan | F71: FENG | G71: 0.18 | I71: 14746 | K71: 1694.9425 | L71: 8.7 | M71: 7.08 | N71: 61.596
C72: 240902000050 | D72: 45541 | E72: Unique Desh logistics | F72: Mailmail/Taiwo | G72: 2.5 | I72: 32544 | K72: 1531.4824 | L72: 21.25 | M72: 7.08 | N72: 150.45
C73: 240902000054 | D73: 45541 | E73: 喵喵速运-Layne | F73: SF Jerry 顾 | G73: 17 | H73: 1150 | N73: 1150
C74: 240903000001 | D74: 45541 | E74: 喵喵速运-Layne | F74: William Xu | G74: 7 | I74: 95256 | K74: 1720.6647 | L74: 55.36 | M74: 7.08 | N74: 391.9488
C75: 240903000003 | D75: 45541 | E75: 喵喵速运-Layne | F75: LEO WEI | G75: 15.5 | I75: 238877 | K75: 1663.8365 | L75: 143.57 | M75: 7.08 | N75: 1016.4756 | U75: 226
C76: 240903000013 | D76: 45541 | E76: Isabel Zhu | F76: Li Si Zhe | G76: 0.46 | H76: 63 | N76: 63
C77: 240903000016 | D77: 45541 | E77: Isabel Zhu | F77: Annie | G77: 81.5 | I77: 1132768 | K77: 1694.9993 | L77: 668.3 | M77: 7.08 | N77: 4731.564
C78: 240903000018 | D78: 45541 | E78: Bella Chan | F78: zhang long ting | G78: 6.5 | H78: 411.5 | N78: 411.5 | T78: 35
C79: 240903000026 | D79: 45541 | E79: Bella Chan | F79: Jason | G79: 0.92 | H79: 69 | N79: 69
C80: 240903000027 | D80: 45541 | E80: ying | F80: Yang yinhua | G80: 3.5 | H80: 234 | N80: 234
C81: 240903000034 | D81: 45541 | E81: 喵喵速运-Layne | F81: REMI | G81: 46 | I81: 574770 | K81: 1734.6311 | L81: 331.35 | M81: 7.08 | N81: 2345.958
C82: 240903000039 | D82: 45541 | E82: 喵喵速运-Layne | F82: William Xu | G82: 201 | I82: 2856708 | K82: 1720.442 | L82: 1660.45 | M82: 7.08 | N82: 11755.986
C83: 240903000042 | D83: 45541 | E83: Isabel Zhu | F83: Mr Ola | G83: 26 | I83: 336966 | K83: 1695 | L83: 198.8 | M83: 7.08 | N83: 1407.504
C84: 240903000043 | D84: 45541 | E84: 喵喵速运-Layne | F84: Mu Shi Shi | G84: 3.5 | H84: 196 | N84: 196
A85: JOB090355 | B85: COLL004148 | C85: 240902000012 | D85: 45542 | E85: 喵喵速运-Layne | F85: Karl | G85: 0.98 | I85: 27025 | K85: 1664.101 | L85: 16.24 | M85: 7.08 | N85: 114.9792 | O85: 4862.1636 | P85: 富姐 | Q85: 2400 | S85: 87.49 | V85: 2487.49 | W85: 129.49 | Z85: 129.49 | AA85: 7.08 | AB85: 916.7892 | AC85: 3404.2792 | AD85: 1457.8844
C86: 240902000027 | D86: 45542 | E86: Isabel Zhu | F86: Zhang Wen Hao | G86: 2.5 | H86: 345 | N86: 345
C87: 240902000058 | D87: 45542 | E87: ying | F87: zhounengquan | G87: 4 | H87: 460 | N87: 460
C88: 240903000022 | D88: 45542 | E88: Bella Chan | F88: huang | G88: 7 | H88: 805 | N88: 805
C89: 240903000032 | D89: 45542 | E89: dejare James | F89: James | G89: 2 | I89: 57291 | K89: 1695 | L89: 33.8 | M89: 7.08 | N89: 239.304
C90: 240903000048 | D90: 45542 | E90: ying | F90: yunus | G90: 3.5 | I90: 94587 | K90: 1663.7995 | L90: 56.85 | M90: 7.08 | N90: 402.498
C91: 240905000006 | D91: 45542 | E91: 喵喵速运-Layne | F91: Laura | G91: 7.5 | H91: 1750 | N91: 1750
C92: 240906000012 | D92: 45542 | E92: 鸿 | F92: Alice08105750388 | G92: 6.5 | I92: 178450 | K92: 1695.0038 | L92: 105.28 | M92: 7.08 | N92: 745.3824
A93: JOB090356 | B93: COLL004150 | C93: 240903000010 | D93: 45543 | E93: Isabel Zhu | F93: Omolade | G93: 0.8 | H93: 150 | N93: 150 | O93: 4865.3652 | P93: 富姐 | Q93: 2400 | S93: 0 | V93: 2400 | W93: 77.05 | Z93: 77.05 | AA93: 7.08 | AB93: 545.514 | AC93: 2945.514 | AD93: 1919.8512
C94: 240904000043 | D94: 45543 | E94: Julie LEE | F94: Julie lee | G94: 7 | H94: 1050 | N94: 1050
C95: 240905000002 | D95: 45543 | E95: 喵喵速运-Layne | F95: LU FANG YAN | G95: 0.52 | I95: 18375 | K95: 1735.1275 | L95: 10.59 | M95: 7.08 | N95: 74.9772
C96: 240905000003 | D96: 45543 | E96: 喵喵速运-Layne | F96: Allen Answer | G96: 3.5 | H96: 402.5 | N96: 402.5
C97: 240905000013 | D97: 45543 | E97: 13635229849 | F97: weng zixian | G97: 0.55 | I97: 28239 | K97: 1695.018 | L97: 16.66 | M97: 7.08 | N97: 117.9528
C98: 240905000035 | D98: 45543 | E98: 喵喵速运-Layne | F98: Sue | G98: 10.5 | H98: 1417.5 | N98: 1417.5
C99: 240906000001 | D99: 45543 | E99: Isabel Zhu | F99: Anthony | G99: 0.64 | I99: 28500 | K99: 1682.4085 | L99: 16.94 | M99: 7.08 | N99: 119.9352
C100: 240906000015 | D100: 45543 | E100: Bella Chan | F100: a niu ge | G100: 5.5 | H100: 632.5 | N100: 632.5
...

Sheet 10月份
A1: 尼日利亚拉各斯（LOS） 应收利润明细表
A2: JOB | B2: 集装编号 | C2: 运单编号 | D2: 日期 | E2: 发货人 | F2: 收货人 | G2: 计费重量 | H2: 应 收 | O2: 总应收 | P2: 起 运 港 成 本 | U2: 代垫运费 | V2: 起运港成本 合计 | W2: 目的港成本 | AC2: 总支出 | AD2: 利润
H3: 应收RMB | I3: LOS Income(NGN) 收到(奈拉) | J3: LOS 收到USD | K3: 美元汇率 dollar currency rate | L3: 应收 到付款USD | M3: 汇率 | N3: 人民币 | P3: 代理商 | Q3: 运费 | R3: 提货费 | S3: 送货费 | T3: 包装费 | W3: 进口报关费 | X3: 到门配送费 | Y3: 转运费 | Z3: 目的港支出 | AA3: 汇率 | AB3: 人民币 | AC3: 起运港+目的港
A4: JOB100324 | B4: COLL004186 | C4: 240930000011 | D4: 45572 | E4: ying | F4: zhang feng | G4: 17.5 | H4: 2537.5 | N4: 2537.5 | O4: 9845.6346 | P4: 富姐 | Q4: 4800 | S4: 50.98 | V4: 4850.98 | W4: 217.37 | Z4: 217.37 | AA4: 7.11 | AB4: 1545.5007 | AC4: 6396.4807 | AD4: 3449.1539
C5: 240930000013 | D5: 45572 | E5: Isabel Zhu | F5: Liu Mao | G5: 5.5 | H5: 632 | N5: 632
C6: 240930000049 | D6: 45572 | E6: KAY | F6: YEMBA BOB MAI | G6: 0.1 | H6: 120 | N6: 120
C7: 241002000009 | D7: 45572 | E7: Sam.Pao | F7: ChengZhen | G7: 8 | H7: 1620 | N7: 1620
C8: 241002000012 | D8: 45572 | E8: Sam.Pao | F8: MaiKaiNian | G8: 1.5 | H8: 172.5 | N8: 172.5
C9: 241003000001 | D9: 45572 | E9: Isabel Zhu | F9: Tony | G9: 5.5 | H9: 660 | N9: 660
C10: 241004000010 | D10: 45572 | E10: Julie LEE | F10: Julie lee | G10: 9.5 | H10: 1140 | N10: 1140
C11: 241004000013 | D11: 45572 | E11: JiaFeng | F11: jiafeng | G11: 2 | I11: 56224 | K11: 1711.0164 | L11: 32.86 | M11: 7.11 | N11: 233.6346
C12: 241004000014 | D12: 45572 | E12: Bella Chan | F12: Dan Dan | G12: 21.5 | H12: 2580 | N12: 2580
C13: 241004000018 | D13: 45572 | E13: KAY | F13: CHIMEZIE MARTIN | G13: 0.1 | H13: 150 | N13: 150
A14: JOB100325 | B14: COLL004190 | C14: 241005000006 | D14: 45575 | E14: Isabel Zhu | F14: A Lan | G14: 3 | I14: 88896 | K14: 1728.4853 | L14: 51.43 | M14: 7.11 | N14: 365.6673 | O14: 4808.8697 | P14: 富姐 | Q14: 2400 | S14: 78.67 | V14: 2509.67 | W14: 140.27 | Z14: 146.59 | AA14: 7.11 | AB14: 1042.2549 | AC14: 3551.9249 | AD14: 1256.9448
C15: 241005000009 | D15: 45575 | E15: Isabel Zhu | F15: Lin Ming Ze | G15: 0.5 | I15: 65660 | K15: 1742.1067 | L15: 37.69 | M15: 7.11 | N15: 267.9759 | U15: 18
C16: 241006000008 | D16: 45575 | E16: Sam.Pao | F16: Diana | G16: 6 | I16: 137655 | K16: 1702.1763 | L16: 80.87 | M16: 7.11 | N16: 574.9857
C17: 241006000010 | D17: 45575 | E17: Julie LEE | F17: Julie lee | G17: 2 | H17: 240 | N17: 240
C18: 241007000002 | D18: 45575 | E18: Sam.Pao | F18: Angel | G18: 1.5 | H18: 172.5 | N18: 172.5
C19: 241007000003 | D19: 45575 | E19: Sam.Pao | F19: XianShiRenSheng | G19: 3 | H19: 435 | N19: 435
C20: 241007000005 | D20: 45575 | E20: Isabel Zhu | F20: Liu Mao | G20: 0.58 | H20: 115 | N20: 115
C21: 241008000011 | D21: 45575 | E21: 喵喵速运-Layne | F21: BFSH | G21: 3.5 | H21: 420 | N21: 420
C22: 241008000025 | D22: 45575 | E22: 喵喵速运-Layne | F22: jeason Cai | G22: 1 | H22: 145 | N22: 145
C23: 241008000062 | D23: 45575 | E23: JiaFeng | F23: jiafeng | G23: 1.5 | I23: 42200 | K23: 1712.6623 | L23: 24.64 | M23: 7.11 | N23: 175.1904
C24: 241008000070 | D24: 45575 | E24: Kelly | F24: AKai | G24: 0.42 | I24: 28181 | K24: 1711.0504 | L24: 16.47 | M24: 7.11 | N24: 117.1017
C25: 241008000079 | D25: 45575 | E25: Bella Chan | F25: YEMI | G25: 0.8 | I25: 31104 | K25: 1728 | L25: 18 | M25: 7.11 | N25: 127.98 | U25: 13
C26: 241008000081 | D26: 45575 | E26: 喵喵速运-Layne | F26: Sue | G26: 2 | H26: 275 | N26: 275 | X26: 6.32
C27: 241008000090 | D27: 45575 | E27: ying | F27: wangmeng | G27: 0.1 | H27: 115 | N27: 115
C28: 241008000093 | D28: 45575 | E28: ying | F28: Wangjianshe | G28: 0.5 | H28: 190 | N28: 190
C29: 241008000097 | D29: 45575 | E29: MailMail速运-演员 | F29: Miss Chen | G29: 0.4 | H29: 145 | N29: 145
C30: 241008000104 | D30: 45575 | E30: 喵喵速运-Layne | F30: SF Jerry 顾 | G30: 6.5 | H30: 812.5 | N30: 812.5
C31: 241008000107 | D31: 45575 | E31: Sam.Pao | F31: Diana | G31: 0.28 | I31: 27945 | K31: 1728.2004 | L31: 16.17 | M31: 7.11 | N31: 114.9687
A32: JOB100328 | B32: COLL004193 | C32: 240928000020 | D32: 45578 | E32: Sam.Pao | F32: JACK | G32: 5.5 | I32: 89424 | K32: 1728 | L32: 51.75 | M32: 7.11 | N32: 367.9425 | O32: 4037.9821 | P32: 富姐 | Q32: 2400 | S32: 55.98 | V32: 2473.98 | W32: 130.03 | Z32: 130.03 | AA32: 7.11 | AB32: 924.5133 | AC32: 3398.4933 | AD32: 639.4888
C33: 241008000005 | D33: 45578 | E33: 喵喵速运-Layne | F33: Robin Tai | G33: 0.78 | I33: 28002.5 | K33: 1731.7563 | L33: 16.17 | M33: 7.11 | N33: 114.9687
C34: 241008000033 | D34: 45578 | E34: 喵喵速运-Layne | F34: SHAEK | G34: 3.5 | H34: 402.5 | N34: 402.5
C35: 241008000052 | D35: 45578 | E35: Isabel Zhu | F35: Cammille | G35: 4.5 | I35: 132300 | K35: 1742.1649 | L35: 75.94 | M35: 7.11 | N35: 539.9334
C36: 241008000067 | D36: 45578 | E36: ying | F36: DAVID | G36: 0.79 | H36: 106.2 | N36: 106.2 | U36: 18
C37: 241009000024 | D37: 45578 | E37: Kelly | F37: AKai | G37: 2.5 | I37: 66944.1 | K37: 1630 | L37: 41.07 | M37: 7.11 | N37: 292.0077
C38: 241009000025 | D38: 45578 | E38: Kelly | F38: AKai | G38: 7 | I38: 187450 | K38: 1630 | L38: 115 | M38: 7.11 | N38: 817.65
C39: 241009000034 | D39: 45578 | E39: 13635229849 | F39: weng zixian | G39: 0.56 | I39: 29627 | K39: 1728.5298 | L39: 17.14 | M39: 7.11 | N39: 121.8654
C40: 241009000039 | D40: 45578 | E40: 土狗泥 | F40: TOYIN S.ADEKUNLE | G40: 3.5 | H40: 402.5 | N40: 402.5
C41: 241010000002 | D41: 45578 | E41: Isabel Zhu | F41: Li Si Zhe | G41: 0.46 | I41: 28002.5 | K41: 1731.7563 | L41: 16.17 | M41: 7.11 | N41: 114.9687
C42: 241010000006 | D42: 45578 | E42: Sam.Pao | F42: Angel | G42: 1.5 | H42: 172.5 | N42: 172.5
C43: 241010000014 | D43: 45578 | E43: 喵喵速运-Layne | F43: SHAEK | G43: 0.56 | H43: 115 | N43: 115
C44: 241010000040 | D44: 45578 | E44: 喵喵速运-Layne | F44: SF Jerry 顾 | G44: 2.5 | H44: 350 | N44: 350
C45: 241011000010 | D45: 45578 | E45: Isabel Zhu | F45: Cammille | G45: 0.66 | I45: 29400 | K45: 1742.7386 | L45: 16.87 | M45: 7.11 | N45: 119.9457
A46: JOB100329 | B46: COLL004188 | C46: 240929000008 | D46: 45578 | E46: ying | F46: lituo | G46: 5 | H46: 333 | N46: 333 | O46: 150840.55 | P46: 顶派 | Q46: 97587.5 | S46: 172.75 | V46: 98181.25 | W46: 1788.74 | Z46: 1835.28 | AA46: 7.11 | AB46: 13048.841 | AC46: 111230.09 | AD46: 39610.46
C47: 240929000049 | D47: 45578 | E47: ying | F47: Abdul Majeed Baba | G47: 371.5 | H47: 22984 | N47: 22984
C48: 240929000068 | D48: 45578 | E48: Sam.Pao | F48: DING | G48: 13 | H48: 825 | N48: 825
C49: 240929000069 | D49: 45578 | E49: Sam.Pao | F49: SHI | G49: 8.5 | H49: 541.5 | N49: 541.5
C50: 240930000007 | D50: 45578 | E50: MailMail速运-演员 | F50: David | G50: 15 | H50: 894 | N50: 894
C51: 240930000014 | D51: 45578 | E51: Isabel Zhu | F51: Aminu | G51: 0.52 | I51: 16801.5 | K51: 1732.1134 | L51: 9.7 | M51: 7.11 | N51: 68.967
C52: 240930000015 | D52: 45578 | E52: ying | F52: Cindy | G52: 24.5 | H52: 1355.5 | N52: 1355.5
C53: 240930000029 | D53: 45578 | E53: ying | F53: Damilola | G53: 1.5 | H53: 93 | N53: 93
C54: 240930000040 | D54: 45578 | E54: Bella Chan | F54: los徐周鹏 | G54: 185.5 | I54: 2638116.8 | K54: 1760.0001 | L54: 1498.9299 | M54: 7.11 | N54: 10657.392
C55: 240930000041 | D55: 45578 | E55: Isabel Zhu | F55: Aminu | G55: 6 | I55: 87660 | K55: 1731.3846 | L55: 50.63 | M55: 7.11 | N55: 359.9793
C56: 241002000006 | D56: 45578 | E56: Bella Chan | F56: Jahnson | G56: 4.5 | H56: 420.5 | N56: 420.5
C57: 241002000014 | D57: 45578 | E57: Sam.Pao | F57: MaiKaiNian | G57: 274 | H57: 15078 | N57: 15078
C58: 241003000002 | D58: 45578 | E58: Isabel Zhu | F58: Joy | G58: 10.5 | I58: 181492.5 | K58: 1728.5 | L58: 105 | M58: 7.11 | N58: 746.55
C59: 241003000004 | D59: 45578 | E59: Isabel Zhu | F59: Lizzy | G59: 6 | I59: 85123 | K59: 1711.0151 | L59: 49.75 | M59: 7.11 | N59: 353.7225
C60: 241003000005 | D60: 45578 | E60: Isabel Zhu | F60: Yuan Shi Jin | G60: 68.5 | H60: 3918.5 | N60: 3918.5 | U60: 151
C61: 241004000001 | D61: 45578 | E61: ying | F61: CHIGBO CHIDOZIE CHRISTIAN | G61: 2 | I61: 38230 | K61: 1731.4312 | L61: 22.08 | M61: 7.11 | N61: 156.9888 | U61: 34
C62: 241004000002 | D62: 45578 | E62: ying | F62: Joseph abba | G62: 0.1 | I62: 15350 | K62: 1726.6592 | L62: 8.89 | M62: 7.11 | N62: 63.2079
C63: 241004000003 | D63: 45578 | E63: ying | F63: shagamu | G63: 10 | H63: 576 | N63: 576
C64: 241004000006 | D64: 45578 | E64: ying | F64: Joseph abba | G64: 0.56 | H64: 63 | N64: 63
C65: 241004000007 | D65: 45578 | E65: ying | F65: Steven Abuja | G65: 2 | H65: 135 | N65: 135
C66: 241004000012 | D66: 45578 | E66: Bella Chan | F66: li tao | G66: 0.1 | H66: 86 | N66: 86 | U66: 23
C67: 241004000015 | D67: 45578 | E67: Isabel Zhu | F67: Engr. Tijjani Abubakar | G67: 0.84 | I67: 17452 | K67: 1710.9804 | L67: 10.2 | M67: 7.11 | N67: 72.522
C68: 241004000016 | D68: 45578 | E68: Isabel Zhu | F68: Lilon | G68: 2 | H68: 123 | N68: 123
C69: 241004000019 | D69: 45578 | E69: 13635229849 | F69: weng zixian | G69: 5.5 | I69: 90383 | K69: 1728.4949 | L69: 52.29 | M69: 7.11 | N69: 371.7819
C70: 241005000002 | D70: 45578 | E70: ying | F70: chenxin | G70: 5 | H70: 303 | N70: 303
C71: 241005000005 | D71: 45578 | E71: Bella Chan | F71: fang ming | G71: 0.1 | H71: 69 | N71: 69
C72: 241005000008 | D72: 45578 | E72: 13635229849 | F72: weng zixian | G72: 2.5 | I72: 41484 | K72: 1728.5 | L72: 24 | M72: 7.11 | N72: 170.64
C73: 241005000010 | D73: 45578 | E73: Isabel Zhu | F73: Chibuzor Victoria | G73: 4.5 | H73: 274.7 | N73: 274.7
C74: 241006000005 | D74: 45578 | E74: Mailmail Abv sales person 1 | F74: Adams | G74: 6 | I74: 100298.82 | K74: 2016.0567 | L74: 49.75 | M74: 7.11 | N74: 353.7225 | U74: 63
C75: 241006000006 | D75: 45578 | E75: dejare James | F75: Mr IGE | G75: 6.5 | I75: 92900 | K75: 1726.1241 | L75: 53.82 | M75: 7.11 | N75: 382.6602
C76: 241006000009 | D76: 45578 | E76: Sam.Pao | F76: Jhon | G76: 48 | I76: 648186 | K76: 1511.5925 | L76: 428.81 | M76: 7.08 | N76: 3035.9748
C77: 241007000010 | D77: 45578 | E77: Isabel Zhu | F77: Joy | G77: 46 | I77: 795110 | K77: 1728.5 | L77: 460 | M77: 7.11 | N77: 3270.6
C78: 241007000011 | D78: 45578 | E78: Isabel Zhu | F78: Joy | G78: 15 | I78: 259275 | K78: 1728.5 | L78: 150 | M78: 7.11 | N78: 1066.5
C79: 241007000012 | D79: 45578 | E79: Bella Chan | F79: li tao | G79: 13 | H79: 747 | N79: 747
C80: 241007000013 | D80: 45578 | E80: Bella Chan | F80: Emmanuel Agwegiokhe | G80: 0.16 | J80: 9 | L80: 9 | M80: 7.11 | N80: 63.99
C81: 241008000002 | D81: 45578 | E81: 喵喵速运-Layne | F81: LEO WEI | G81: 9 | I81: 125646 | K81: 1731.3766 | L81: 72.57 | M81: 7.11 | N81: 515.9727 | U81: 39
C82: 241008000007 | D82: 45578 | E82: 喵喵速运-Layne | F82: kevin | G82: 1.5 | H82: 102 | N82: 102
C83: 241008000008 | D83: 45578 | E83: 喵喵速运-Layne | F83: Bao Bao | G83: 5.5 | H83: 366 | N83: 366
C84: 241008000015 | D84: 45578 | E84: 喵喵速运-Layne | F84: Kim | G84: 103 | I84: 1431250 | K84: 1628.1967 | L84: 879.04 | M84: 7.11 | N84: 6249.9744 | T84: 70
C85: 241008000017 | D85: 45578 | E85: 喵喵速运-Layne | F85: LI DKM | G85: 3 | H85: 201 | N85: 201
C86: 241008000022 | D86: 45578 | E86: 喵喵速运-Layne | F86: MA ZONG | G86: 2.5 | H86: 150 | N86: 150
C87: 241008000023 | D87: 45578 | E87: 喵喵速运-Layne | F87: MA ZONG | G87: 0.36 | H87: 60 | N87: 60
C88: 241008000024 | D88: 45578 | E88: 喵喵速运-Layne | F88: William Xu | G88: 4.5 | I88: 75573 | K88: 1727.7778 | L88: 43.74 | M88: 7.11 | N88: 310.9914 | U88: 41
C89: 241008000026 | D89: 45578 | E89: 喵喵速运-Layne | F89: Xu Xin Tao | G89: 0.84 | H89: 63 | N89: 63
C90: 241008000028 | D90: 45578 | E90: 喵喵速运-Layne | F90: Kola | G90: 98 | H90: 6272 | N90: 6272 | X90: 27.56
C91: 241008000047 | D91: 45578 | E91: ying | F91: Cindy | G91: 3.5 | H91: 213 | N91: 213
C92: 241008000064 | D92: 45578 | E92: ying | F92: Jahmin Emenyonu | G92: 140.5 | H92: 8565 | N92: 8565 | X92: 18.98
C93: 241008000069 | D93: 45578 | E93: 喵喵速运-Layne | F93: Zhang Mei Li | G93: 133 | H93: 7815 | N93: 7815
C94: 241008000082 | D94: 45578 | E94: 陆梓龙 | F94: luk | G94: 158 | H94: 7742 | N94: 7742
C95: 241008000085 | D95: 45578 | E95: 陆梓龙 | F95: luk | G95: 31.5 | H95: 1740.5 | N95: 1740.5
C96: 241008000089 | D96: 45578 | E96: 喵喵速运-Layne | F96: Gao Yun | G96: 551 | I96: 7401450 | K96: 1741.9521 | L96: 4248.94 | M96: 7.11 | N96: 30209.963
C97: 241008000099 | D97: 45578 | E97: 喵喵速运-Layne | F97: Rabiu Mohammed | G97: 33 | H97: 1683 | N97: 1683
C98: 241008000102 | D98: 45578 | E98: 喵喵速运-Layne | F98: SF Jerry 顾 | G98: 91.5 | H98: 4895.25 | N98: 4895.25
C99: 241008000105 | D99: 45578 | E99: Sam.Pao | F99: Ah May | G99: 59 | H99: 3071 | N99: 3071
C100: 241008000112 | D100: 45578 | E100: 喵喵速运-Layne | F100: Ke Zong | G100: 12 | H100: 600 | N100: 600
...

Sheet 11月份
A1: 尼日利亚拉各斯（LOS） 应收利润明细表
A2: JOB | B2: 集装编号 | C2: 运单编号 | D2: 日期 | E2: 发货人 | F2: 收货人 | G2: 计费重量 | H2: 应 收 | O2: 总应收 | P2: 起 运 港 成 本 | U2: 代垫运费 | V2: 起运港成本 合计 | W2: 目的港成本 | AC2: 总支出 | AD2: 利润
H3: 应收RMB | I3: LOS Income(NGN) 收到(奈拉) | J3: LOS 收到USD | K3: 美元汇率 dollar currency rate | L3: 应收 到付款USD | M3: 汇率 | N3: 人民币 | P3: 代理商 | Q3: 运费 | R3: 提货费 | S3: 送货费 | T3: 包装费 | W3: 进口报关费 | X3: 到门配送费 | Y3: 转运费 | Z3: 目的港支出 | AA3: 汇率 | AB3: 人民币 | AC3: 起运港+目的港
A4: JOB110333 | B4: COLL004227 | C4: 241028000050 | D4: 45598 | E4: ying | F4: leoyang | G4: 2 | H4: 230 | N4: 230 | O4: 12226.288 | P4: 富姐 | Q4: 7200 | S4: 55.98 | V4: 7255.98 | W4: 194.17 | Z4: 199.97 | AA4: 7.2 | AB4: 1439.784 | AC4: 8695.764 | AD4: 3530.524
C5: 241029000015 | D5: 45598 | E5: ying | F5: CAO ZHIJUN | G5: 1.5 | I5: 29645 | K5: 1764.5833 | L5: 16.8 | M5: 7.2 | N5: 120.96
C6: 241029000043 | D6: 45598 | E6: dejare James | F6: COD victor | G6: 1.5 | L6: 25.35 | M6: 7.2 | N6: 182.52
C7: 241030000018 | D7: 45598 | E7: ying | F7: chenxiaojie | G7: 49.5 | I7: 1383277.5 | K7: 1749.6111 | L7: 790.62 | M7: 7.2 | N7: 5692.464
C8: 241030000023 | D8: 45598 | E8: 喵喵速运-Layne | F8: Le Bin | G8: 0.9375 | H8: 120 | N8: 120
C9: 241031000004 | D9: 45598 | E9: 喵喵速运-Layne | F9: FEN | G9: 5 | H9: 550 | N9: 550
C10: 241031000005 | D10: 45598 | E10: 喵喵速运-Layne | F10: MO JI | G10: 0.14 | I10: 29400 | K10: 1764.7059 | L10: 16.66 | M10: 7.2 | N10: 119.952
C11: 241031000010 | D11: 45598 | E11: Julie LEE | F11: Julie lee | G11: 0.83 | H11: 120 | N11: 120
C12: 241031000016 | D12: 45598 | E12: Bella Chan | F12: zhang yong chong | G12: 0.1 | I12: 28251 | K12: 1744.9661 | L12: 16.189999 | M12: 7.2 | N12: 116.56799
C13: 241031000017 | D13: 45598 | E13: ying | F13: chenxiaojie | G13: 3 | I13: 83835 | K13: 1749.8435 | L13: 47.91 | M13: 7.2 | N13: 344.952
C14: 241031000038 | D14: 45598 | E14: Julie LEE | F14: Julie lee | G14: 3 | H14: 360 | N14: 360
C15: 241031000040 | D15: 45598 | E15: Isabel Zhu | F15: Mr Li | G15: 7.5 | I15: 219466 | K15: 1748.1759 | L15: 125.54 | M15: 7.2 | N15: 903.888 | X15: 5.8
C16: 241031000049 | D16: 45598 | E16: 喵喵速运-Layne | F16: Li Li | G16: 1.5 | H16: 370 | N16: 370
C17: 241101000001 | D17: 45598 | E17: 喵喵速运-Layne | F17: Li Li | G17: 0.7 | H17: 330 | N17: 330
C18: 241101000007 | D18: 45598 | E18: Sam.Pao | F18: Mr. Jiang | G18: 6 | H18: 690 | N18: 690
C19: 241101000013 | D19: 45598 | E19: 喵喵速运-Layne | F19: Kola | G19: 5.5 | H19: 660 | N19: 660
C20: 241101000014 | D20: 45598 | E20: Bella Chan | F20: shangyafei | G20: 10 | H20: 1200 | N20: 1200
C21: 241101000036 | D21: 45598 | E21: 喵喵速运-Layne | F21: jeason Cai | G21: 0.36 | I21: 28175 | K21: 1764.2455 | L21: 15.97 | M21: 7.2 | N21: 114.984
A22: JOB110334 | B22: COLL004228 | C22: 241031000009 | D22: 45599 | E22: Julie LEE | F22: Julie lee | G22: 2 | H22: 240 | N22: 240 | O22: 3612.452 | P22: 富姐 | Q22: 2400 | S22: 55.98 | V22: 2455.98 | W22: 49.44 | Z22: 49.44 | AA22: 7.2 | AB22: 355.968 | AC22: 2811.948 | AD22: 800.504
C23: 241031000014 | D23: 45599 | E23: Isabel Zhu | F23: Bruce | G23: 8 | H23: 920 | N23: 920
C24: 241101000006 | D24: 45599 | E24: 喵喵速运-Layne | F24: Rabiu Mohammed | G24: 11.5 | H24: 1322.5 | N24: 1322.5
C25: 241102000020 | D25: 45599 | E25: 喵喵速运-Layne | F25: Rabiu Mohammed | G25: 5.5 | H25: 632.5 | N25: 632.5
C26: 241102000021 | D26: 45599 | E26: 喵喵速运-Layne | F26: DIKE | G26: 2 | I26: 51450 | K26: 1764.4033 | L26: 29.16 | M26: 7.2 | N26: 209.952
C27: 241102000024 | D27: 45599 | E27: 喵喵速运-Layne | F27: YI YUE | G27: 2.5 | H27: 287.5 | N27: 287.5
A28: JOB110337 | B28: COLL004231 | C28: 241029000022 | D28: 45600 | E28: Bella Chan | F28: Zou Qiyang | G28: 106 | H28: 12850 | N28: 12850 | O28: 100026.98 | P28: 方显 | Q28: 76600 | S28: 174.5 | V28: 77442.5 | W28: 1337.25 | Z28: 1580.82 | AA28: 7.2 | AB28: 11381.904 | AC28: 88824.404 | AD28: 11202.58
C29: 241029000033 | D29: 45600 | E29: ying | F29: Vicky Kuo | G29: 162.5 | H29: 10093 | N29: 10093 | T29: 120 | U29: 548
C30: 241031000011 | D30: 45600 | E30: Isabel Zhu | F30: Mr Chen | G30: 131 | H30: 8160 | N30: 8160 | X30: 42.19
C31: 241101000044 | D31: 45600 | E31: 喵喵速运-Layne | F31: Sun Li | G31: 719.5 | I31: 10931900 | K31: 1764.0006 | L31: 6197.22 | M31: 7.2 | N31: 44619.984 | X31: 201.38
C32: 241101000055 | D32: 45600 | E32: 陆梓龙 | F32: lagosxu | G32: 434 | H32: 24304 | N32: 24304
A33: JOB110338 | B33: COLL004219 | C33: 241026000011 | D33: 45601 | E33: 喵喵速运-Layne | F33: LING | G33: 0.68 | H33: 72 | N33: 72 | O33: 147005.59 | P33: 顶派=113263 广州通达=6034.4 | Q33: 119297.4 | R33: 76.68 | S33: 188.91 | V33: 120784.99 | W33: 1322.57 | Z33: 1374.6 | AA33: 7.2 | AB33: 9897.12 | AC33: 130682.11 | AD33: 16323.478
C34: 241027000013 | D34: 45601 | E34: Sam.Pao | F34: XianShiRenSheng | G34: 11.5 | H34: 731 | N34: 731
C35: 241028000004 | D35: 45601 | E35: 喵喵速运-Layne | F35: Shu He | G35: 4 | H35: 263 | N35: 263
C36: 241028000007 | D36: 45601 | E36: 喵喵速运-Layne | F36: Li Yang Yang | G36: 65.5 | I36: 1013198 | K36: 1764.0162 | L36: 574.37 | M36: 7.2 | N36: 4135.464
C37: 241028000016 | D37: 45601 | E37: Isabel Zhu | F37: Zhao Zi Cheng | G37: 5.5 | H37: 439 | N37: 439
C38: 241028000019 | D38: 45601 | E38: Bella Chan | F38: zhang yong chong | G38: 1.5 | I38: 24900 | K38: 1744.9194 | L38: 14.27 | M38: 7.2 | N38: 102.744
C39: 241028000033 | D39: 45601 | E39: ying | F39: Arvin | G39: 1.5 | H39: 106.5 | N39: 106.5
C40: 241028000042 | D40: 45601 | E40: Bella Chan | F40: chidi | G40: 103 | I40: 1538741 | K40: 1745 | L40: 881.8 | M40: 7.2 | N40: 6348.96
C41: 241028000046 | D41: 45601 | E41: ying | F41: zhangjingcheng | G41: 0.34 | H41: 66 | N41: 66
C42: 241028000058 | D42: 45601 | E42: Jr.Feng.Shiue | F42: Abubakar | G42: 1.5 | H42: 110.5 | N42: 110.5
C43: 241029000001 | D43: 45601 | E43: 喵喵速运-Layne | F43: LEO WEI | G43: 15 | I43: 238875 | K43: 1764.0868 | L43: 135.41 | M43: 7.2 | N43: 974.952
C44: 241029000004 | D44: 45601 | E44: 喵喵速运-Layne | F44: SHAEK | G44: 122.5 | H44: 7105 | N44: 7105
C45: 241029000009 | D45: 45601 | E45: 喵喵速运-Layne | F45: NAN GUA | G45: 4.5 | H45: 386 | N45: 386
C46: 241029000012 | D46: 45601 | E46: Isabel Zhu | F46: Gbenga | G46: 2.5 | I46: 41269 | K46: 1744.9893 | L46: 23.650002 | M46: 7.2 | N46: 170.28001
C47: 241029000019 | D47: 45601 | E47: Isabel Zhu | F47: Ope Olofinjana | G47: 24 | I47: 347516.75 | K47: 1745 | L47: 199.15 | M47: 7.2 | N47: 1433.88
C48: 241029000020 | D48: 45601 | E48: ying | F48: yangweiqiang | G48: 72.5 | H48: 4205 | N48: 4205
C49: 241029000023 | D49: 45601 | E49: Bella Chan | F49: Jason | G49: 0.94 | H49: 74 | N49: 74
C50: 241029000024 | D50: 45601 | E50: ying | F50: Mark | G50: 3.5 | I50: 56473 | K50: 1764.2299 | L50: 32.01 | M50: 7.2 | N50: 230.472
C51: 241029000026 | D51: 45601 | E51: Isabel Zhu | F51: Wu Jiao Xing | G51: 2 | H51: 133 | N51: 133
C52: 241029000031 | D52: 45601 | E52: Bella Chan | F52: li tao | G52: 0.44 | H52: 68 | N52: 68
C53: 241029000032 | D53: 45601 | E53: ying | F53: chenxiaojie | G53: 4 | H53: 263 | N53: 263
C54: 241029000034 | D54: 45601 | E54: ying | F54: Mark | G54: 10 | I54: 153370 | K54: 1764.0902 | L54: 86.94 | M54: 7.2 | N54: 625.968
C55: 241029000036 | D55: 45601 | E55: Bella Chan | F55: los徐周鹏 | G55: 30 | I55: 437125.59 | K55: 1683.0001 | L55: 259.72998 | M55: 7.2 | N55: 1870.0559 | U55: 104
C56: 241029000037 | D56: 45601 | E56: Bella Chan | F56: panda | G56: 33.5 | I56: 528386 | K56: 1745 | L56: 302.8 | M56: 7.2 | N56: 2180.16
C57: 241029000038 | D57: 45601 | E57: Shirley | F57: Mr. Chen | G57: 7.5 | H57: 471 | N57: 471
C58: 241029000040 | D58: 45601 | E58: 13635229849 | F58: weng zixian | G58: 3.5 | I58: 63363 | K58: 1764.0033 | L58: 35.92 | M58: 7.2 | N58: 258.624
C59: 241029000045 | D59: 45601 | E59: Sam.Pao | F59: ERIC | G59: 123.5 | H59: 7418 | N59: 7418
C60: 241029000047 | D60: 45601 | E60: MailMail速运-演员 | F60: 陈 权 | G60: 0.96 | H60: 68 | N60: 68
C61: 241029000049 | D61: 45601 | E61: 喵喵速运-Layne | F61: Mr Folabidayo | G61: 36 | I61: 529200 | K61: 1764 | L61: 300 | M61: 7.2 | N61: 2160
C62: 241029000050 | D62: 45601 | E62: 喵喵速运-Layne | F62: Lin Lin | G62: 10.5 | H62: 720 | N62: 720
C63: 241030000006 | D63: 45601 | E63: 喵喵速运-Layne | F63: Robin Tai | G63: 22 | I63: 320705 | K63: 1764.0539 | L63: 181.8 | M63: 7.2 | N63: 1308.96
C64: 241030000009 | D64: 45601 | E64: Isabel Zhu | F64: Maryam Tukur | G64: 18 | I64: 306247 | K64: 1744.9972 | L64: 175.5 | M64: 7.2 | N64: 1263.6
C65: 241030000011 | D65: 45601 | E65: Isabel Zhu | F65: Gbenga | G65: 0.53 | I65: 16927 | K65: 1745.0515 | L65: 9.7 | M65: 7.2 | N65: 69.84
C66: 241030000015 | D66: 45601 | E66: Bella Chan | F66: panda | G66: 5.5 | I66: 98034 | K66: 1744.9982 | L66: 56.18 | M66: 7.2 | N66: 404.496
C67: 241030000027 | D67: 45601 | E67: Kelly | F67: AKai | G67: 8.5 | I67: 132742 | K67: 1848.0022 | L67: 71.83 | M67: 7.2 | N67: 517.176
C68: 241030000028 | D68: 45601 | E68: dejare James | F68: Nkiru | G68: 20 | I68: 310348.25 | L68: 177.85 | M68: 7.2 | N68: 1280.52
C69: 241030000030 | D69: 45601 | E69: 喵喵速运-Layne | F69: James | G69: 10 | I69: 151900 | K69: 1764.0228 | L69: 86.11 | M69: 7.2 | N69: 619.992 | U69: 20
C70: 241030000032 | D70: 45601 | E70: Isabel Zhu | F70: Ope Olofinjana | G70: 2 | I70: 33155 | K70: 1745 | L70: 19 | M70: 7.2 | N70: 136.8
C71: 241030000033 | D71: 45601 | E71: Isabel Zhu | F71: Ma Chao | G71: 4 | H71: 290 | N71: 290
C72: 241030000035 | D72: 45601 | E72: Isabel Zhu | F72: Femi Austin | G72: 8 | I72: 114912 | K72: 1680 | L72: 68.4 | M72: 7.2 | N72: 492.48
C73: 241030000036 | D73: 45601 | E73: 喵喵速运-Layne | F73: REMI | G73: 38.5 | I73: 531300 | K73: 1656.0172 | L73: 320.83 | M73: 7.2 | N73: 2309.976
C74: 241030000044 | D74: 45601 | E74: Isabel Zhu | F74: Mr Chen | G74: 239 | H74: 15118 | N74: 15118 | X74: 42.19
C75: 241030000047 | D75: 45601 | E75: Bella Chan | F75: Dan Dan | G75: 0.3 | H75: 74 | N75: 74
C76: 241030000049 | D76: 45601 | E76: 陆梓龙 | F76: WANG | G76: 83 | H76: 5154 | N76: 5154
C77: 241031000002 | D77: 45601 | E77: 喵喵速运-Layne | F77: Ye Hui | G77: 9 | H77: 540 | N77: 540
C78: 241031000006 | D78: 45601 | E78: 喵喵速运-Layne | F78: ZHENG ZONG | G78: 40.5 | H78: 2744.5 | N78: 2744.5 | U78: 193
C79: 241031000013 | D79: 45601 | E79: Isabel Zhu | F79: Li Si Zhe | G79: 7.5 | I79: 115395 | K79: 1764.1798 | L79: 65.41 | M79: 7.2 | N79: 470.952
C80: 241031000018 | D80: 45601 | E80: 喵喵速运-Layne | F80: ZENITH BANK | G80: 110.5 | H80: 6759 | N80: 6759
C81: 241031000022 | D81: 45601 | E81: ying | F81: chenxiaojie | G81: 7.5 | H81: 501 | N81: 501
C82: 241031000025 | D82: 45601 | E82: Bella Chan | F82: dong wu lin | G82: 3.5 | I82: 45037.5 | K82: 1366.8437 | L82: 32.95 | M82: 7.2 | N82: 237.24
C83: 241031000035 | D83: 45601 | E83: ying | F83: Hubin | G83: 1.5 | H83: 138 | N83: 138 | X83: 9.84
C84: 241031000036 | D84: 45601 | E84: 喵喵速运-Layne | F84: REMI | G84: 299.5 | I84: 3995330 | K84: 1656.0061 | L84: 2412.63 | M84: 7.2 | N84: 17370.936
C85: 241031000042 | D85: 45601 | E85: Isabel Zhu | F85: Halifa Success | G85: 10 | H85: 726 | N85: 726
C86: 241031000043 | D86: 45601 | E86: ying | F86: Leo Liang | G86: 3 | I86: 54269.5 | K86: 1745.0001 | L86: 31.099998 | M86: 7.2 | N86: 223.91999
C87: 241031000044 | D87: 45601 | E87: ying | F87: Okosubide Mozimo | G87: 52 | H87: 3140 | N87: 3140
C88: 241031000045 | D88: 45601 | E88: dejare James | F88: James | G88: 45.5 | I88: 680846.65 | L88: 390.17 | M88: 7.2 | N88: 2809.224
C89: 241031000051 | D89: 45601 | E89: 喵喵速运-Layne | F89: Ke Zong | G89: 2 | H89: 147 | N89: 147 | U89: 14
C90: 241101000004 | D90: 45601 | E90: 喵喵速运-Layne | F90: Han Xiang Yang | G90: 128 | I90: 1888950 | K90: 1764.0055 | L90: 1070.83 | M90: 7.2 | N90: 7709.976 | T90: 30
C91: 241101000005 | D91: 45601 | E91: 喵喵速运-Layne | F91: Han Xiang Yang | G91: 0.15 | I91: 14770 | K91: 1773.1092 | L91: 8.33 | M91: 7.2 | N91: 59.976
C92: 241101000012 | D92: 45601 | E92: Bella Chan | F92: new hope 边鹏飞 | G92: 16.5 | I92: 259078.68 | K92: 1764 | L92: 146.87 | M92: 7.2 | N92: 1057.464
C93: 241101000017 | D93: 45601 | E93: 喵喵速运-Layne | F93: Jeffrey-Wang | G93: 0.92 | H93: 74 | N93: 74
C94: 241101000020 | D94: 45601 | E94: ying | F94: Olufade Adekunle | G94: 250 | H94: 18775 | N94: 18775
C95: 241101000031 | D95: 45601 | E95: 喵喵速运-Layne | F95: REMI | G95: 4.5 | I95: 62100 | K95: 1656 | L95: 37.5 | M95: 7.2 | N95: 270
C96: 241101000034 | D96: 45601 | E96: 喵喵速运-Layne | F96: Zhang Xin Jian | G96: 26 | H96: 1690 | N96: 1690
C97: 241101000039 | D97: 45601 | E97: ying | F97: SEGUN | G97: 83 | H97: 5917 | N97: 5917 | U97: 771
C98: 241101000048 | D98: 45601 | E98: Sam.Pao | F98: Yusky | G98: 26.5 | H98: 1590 | N98: 1590
C99: 241101000050 | D99: 45601 | E99: 喵喵速运-Layne | F99: SF Jerry 顾 | G99: 13 | H99: 767 | N99: 767
C100: 241101000056 | D100: 45601 | E100: 陆梓龙 | F100: luk | G100: 15.5 | H100: 1057 | N100: 1057 | T100: 90
...

Sheet 12月份
A1: 尼日利亚拉各斯（LOS） 应收利润明细表
A2: JOB | B2: 集装编号 | C2: 运单编号 | D2: 日期 | E2: 发货人 | F2: 收货人 | G2: 计费重量 | H2: 应 收 | O2: 总应收 | P2: 起 运 港 成 本 | U2: 代垫运费 | V2: 起运港成本 合计 | W2: 目的港成本 | AC2: 总支出 | AD2: 利润
H3: 应收RMB | I3: LOS Income(NGN) 收到(奈拉) | J3: LOS 收到USD | K3: 美元汇率 dollar currency rate | L3: 应收 到付款USD | M3: 汇率 | N3: 人民币 | P3: 代理商 | Q3: 运费 | R3: 提货费 | S3: 送货费 | T3: 包装费 | W3: 进口报关费 | X3: 到门配送费 | Y3: 转运费 | Z3: 目的港支出 | AA3: 汇率 | AB3: 人民币 | AC3: 起运港+目的港
A4: JOB120355 | B4: COLL004274 | C4: 241126000002 | D4: 45628 | E4: Isabel Zhu | F4: Yang Xin Hui | G4: 1.5 | H4: 180 | N4: 180 | O4: 13623.496 | P4: 富姐 | Q4: 7740 | S4: 70.98 | V4: 7810.98 | W4: 288.25 | Z4: 293.11 | AA4: 7.27 | AB4: 2130.9097 | AC4: 9941.8897 | AD4: 3681.606
C5: 241127000016 | D5: 45628 | E5: KAY | F5: Liu | G5: 2 | H5: 230 | N5: 230
C6: 241127000018 | D6: 45628 | E6: 喵喵速运-Layne | F6: Li Li | G6: 1.5 | H6: 172.5 | N6: 172.5
C7: 241127000020 | D7: 45628 | E7: 喵喵速运-Layne | F7: Liu Yan | G7: 1.5 | I7: 78880 | K7: 1686.9119 | L7: 46.76 | M7: 7.27 | N7: 339.9452
C8: 241127000029 | D8: 45628 | E8: Isabel Zhu | F8: Eric | G8: 5 | H8: 575 | N8: 575
C9: 241128000004 | D9: 45628 | E9: Isabel Zhu | F9: Liu Mao | G9: 37.5 | H9: 4312 | N9: 4312
C10: 241128000006 | D10: 45628 | E10: Isabel Zhu | F10: Ibrahim Abdullahi | G10: 3 | H10: 360 | N10: 360
C11: 241128000018 | D11: 45628 | E11: Isabel Zhu | F11: Wu Jiao Xing | G11: 1.5 | H11: 172.5 | N11: 172.5
C12: 241128000032 | D12: 45628 | E12: KAY | F12: Ah Ming | G12: 2.5 | H12: 287.5 | N12: 287.5
C13: 241129000004 | D13: 45628 | E13: Isabel Zhu | F13: Ge Ge | G13: 1.5 | H13: 373 | N13: 373
C14: 241129000007 | D14: 45628 | E14: Isabel Zhu | F14: Wu Jiao Xing | G14: 3.5 | H14: 402.5 | N14: 402.5
C15: 241129000016 | D15: 45628 | E15: Bella Chan | F15: Doris | G15: 2 | I15: 56350 | K15: 1781.5365 | L15: 31.63 | M15: 7.27 | N15: 229.9501
C16: 241129000030 | D16: 45628 | E16: Mailmail Abv sales person 1 | F16: Fafunso | G16: 0.1 | I16: 27900 | K16: 1747.0258 | L16: 15.969999 | M16: 7.27 | N16: 116.10189
C17: 241129000032 | D17: 45628 | E17: 喵喵速运-Layne | F17: Jimmy | G17: 2.5 | H17: 680 | N17: 680
C18: 241129000041 | D18: 45628 | E18: Isabel Zhu | F18: Liu Mao | G18: 12.5 | H18: 1437.5 | N18: 1437.5
C19: 241129000047 | D19: 45628 | E19: ying | F19: liangdawei | G19: 0.45 | H19: 150 | N19: 150 | X19: 4.86
C20: 241129000048 | D20: 45628 | E20: ying | F20: liangdawei | G20: 0.56666666 | H20: 145 | N20: 145
C21: 241129000049 | D21: 45628 | E21: ying | F21: liangdawei | G21: 0.38 | H21: 115 | N21: 115
C22: 241129000050 | D22: 45628 | E22: ying | F22: liangdawei | G22: 1 | H22: 145 | N22: 145
C23: 241129000055 | D23: 45628 | E23: 喵喵速运-Layne | F23: Lin Qing Yuan | G23: 19 | I23: 502550 | K23: 1672.1011 | L23: 300.55 | M23: 7.27 | N23: 2184.9985
C24: 241130000026 | D24: 45628 | E24: KAY | F24: AILI | G24: 0.5 | H24: 250 | N24: 250
C25: 241130000027 | D25: 45628 | E25: ying | F25: Pela | G25: 3 | H25: 345 | N25: 345
C26: 241201000006 | D26: 45628 | E26: KAY | F26: Cathy Chiu | G26: 3.5 | H26: 420 | N26: 420
A27: JOB120356 | B27: COLL004275 | C27: 241202000032 | D27: 45993 | E27: Sam.Pao | F27: SAMPAO | G27: 1040 | I27: 1149500 | K27: 1672 | L27: 687.5 | M27: 7.27 | N27: 4998.125 | O27: 4998.125 | P27: 代清关 | V27: 0 | W27: 714.37 | Z27: 714.37 | AA27: 7.27 | AB27: 5193.4699 | AC27: 5193.4699 | AD27: -195.3449
A28: JOB120357 | B28: COLL004277 | C28: 241202000033 | D28: 45993 | E28: Sam.Pao | F28: SAMPAO | G28: 1140 | I28: 727100 | K28: 61.321753 | L28: 11857.13 | M28: 7.27 | N28: 86201.335 | O28: 86201.335 | P28: 代清关 | V28: 0 | W28: 767.66 | Z28: 767.66 | AA28: 7.27 | AB28: 5580.8882 | AC28: 5580.8882 | AD28: 80620.447
A29: JOB120358 | B29: COLL004276 | C29: 241129000033 | D29: 45630 | E29: Isabel Zhu | F29: Fareeda Aminu isah | G29: 2 | H29: 320 | N29: 320 | O29: 16142.457 | P29: 富姐 | Q29: 9600 | S29: 121.96 | V29: 9797.96 | W29: 251.95 | Z29: 251.95 | AA29: 7.27 | AB29: 1831.6765 | AC29: 11629.637 | AD29: 4512.8207
C30: 241129000042 | D30: 45630 | E30: Isabel Zhu | F30: Liu Mao | G30: 42 | H30: 5250 | N30: 5250
C31: 241130000006 | D31: 45630 | E31: Isabel Zhu | F31: Wu Jiao Xing | G31: 0.28 | H31: 115 | N31: 115
C32: 241130000010 | D32: 45630 | E32: Sam.Pao | F32: Oxford Niu | G32: 24 | H32: 2760 | N32: 2760
C33: 241130000011 | D33: 45630 | E33: Bella Chan | F33: fang ming | G33: 19 | H33: 2280 | N33: 2280
C34: 241130000016 | D34: 45630 | E34: Isabel Zhu | F34: Wu Jiao Xing | G34: 6 | H34: 690 | N34: 690
C35: 241130000023 | D35: 45630 | E35: ying | F35: chenxiaojie | G35: 9 | I35: 240120 | K35: 1686.7097 | L35: 142.36 | M35: 7.27 | N35: 1034.9572 | U35: 76
C36: 241130000025 | D36: 45630 | E36: KAY | F36: KANWUPING | G36: 1.5 | H36: 180 | N36: 180
C37: 241201000001 | D37: 45630 | E37: 喵喵速运-Layne | F37: WEI PING | G37: 12 | H37: 1437.5 | N37: 1437.5
C38: 241201000004 | D38: 45630 | E38: 喵喵速运-Layne | F38: LING | G38: 0.96 | H38: 340 | N38: 340
C39: 241202000001 | D39: 45630 | E39: MailMail速运-演员 | F39: 陈 权 | G39: 0.9 | H39: 115 | N39: 115
C40: 241202000020 | D40: 45630 | E40: Bella Chan | F40: dan dan | G40: 13.5 | H40: 1620 | N40: 1620
A41: JOB120369 | B41: COLL004281 | C41: 241201000011 | D41: 45631 | E41: 喵喵速运-Layne | F41: Jerry Zhang | G41: 13.5 | H41: 1687.5 | N41: 1687.5 | O41: 4494.5 | P41: 富姐 | Q41: 2400 | S41: 0 | V41: 2400 | W41: 78.44 | Z41: 82.6 | AA41: 7.27 | AB41: 600.502 | AC41: 3000.502 | AD41: 1493.998
C42: 241201000012 | D42: 45631 | E42: KAY | F42: LIANCHEN | G42: 6 | H42: 752 | N42: 752
C43: 241202000017 | D43: 45631 | E43: ying | F43: Mr | G43: 13.5 | H43: 1500 | N43: 1500
C44: 241202000023 | D44: 45631 | E44: ying | F44: Mrs | G44: 0.24 | H44: 125 | N44: 125
C45: 241203000004 | D45: 45631 | E45: Isabel Zhu | F45: Tony | G45: 0.8 | H45: 130 | N45: 130
C46: 241203000007 | D46: 45631 | E46: KAY | F46: CHENYUNREN | G46: 0.5 | H46: 115 | N46: 115
C47: 241203000040 | D47: 45631 | E47: MailMail速运-演员 | F47: BOSS | G47: 0.72 | H47: 185 | N47: 185 | X47: 4.16
A48: JOB120370 | B48: COLL004282 | C48: 241130000008 | D48: 45632 | E48: Isabel Zhu | F48: Wang Hui Feng | G48: 32.5 | I48: 840937.5 | K48: 1635.7788 | L48: 514.09 | M48: 7.27 | N48: 3737.4343 | O48: 12527.71 | P48: 富姐 | Q48: 8540 | S48: 60.98 | V48: 8693.98 | W48: 122.16 | Z48: 122.16 | AA48: 7.27 | AB48: 888.1032 | AC48: 9582.0832 | AD48: 2945.6263
C49: 241130000009 | D49: 45632 | E49: Sam.Pao | F49: YuShao | G49: 4 | H49: 500 | N49: 500
C50: 241130000013 | D50: 45632 | E50: Isabel Zhu | F50: Wu Jiao Xing | G50: 0.576 | H50: 125 | N50: 125
C51: 241130000015 | D51: 45632 | E51: Isabel Zhu | F51: Wu Jiao Xing | G51: 4 | H51: 460 | N51: 460
C52: 241130000017 | D52: 45632 | E52: Isabel Zhu | F52: Wu Jiao Xing | G52: 9 | H52: 1125 | N52: 1125
C53: 241202000045 | D53: 45632 | E53: 喵喵速运-Layne | F53: CENTURY INDUSTRIAL FZE | G53: 11 | I53: 313490 | K53: 1708.4855 | L53: 183.49 | M53: 7.27 | N53: 1333.9723 | U53: 14
C54: 241203000001 | D54: 45632 | E54: Kelly | F54: AKai | G54: 7.5 | I54: 200049.3 | K54: 1670 | L54: 119.79 | M54: 7.27 | N54: 870.8733
C55: 241203000008 | D55: 45632 | E55: Bella Chan | F55: huang peng | G55: 7 | H55: 875 | N55: 875
C56: 241203000028 | D56: 45632 | E56: 喵喵速运-Layne | F56: WEI PING | G56: 0.84 | H56: 249 | N56: 249
C57: 241203000042 | D57: 45632 | E57: KAY | F57: Liu | G57: 0.58 | H57: 125 | N57: 125
C58: 241203000052 | D58: 45632 | E58: ying | F58: Charles | G58: 0.53 | H58: 125 | N58: 125
C59: 241204000007 | D59: 45632 | E59: KAY | F59: Tie fa | G59: 5 | I59: 151875 | K59: 1766.8101 | L59: 85.96 | M59: 7.27 | N59: 624.9292
C60: 241204000009 | D60: 45632 | E60: Bella Chan | F60: huang zong | G60: 3 | H60: 375 | N60: 375
C61: 241204000015 | D61: 45632 | E61: Isabel Zhu | F61: Mr Zheng | G61: 4 | H61: 566 | N61: 566 | U61: 66
C62: 241204000080 | D62: 45632 | E62: Julie LEE | F62: Julie lee | G62: 9 | H62: 1170 | N62: 1170
C63: 241205000006 | D63: 45632 | E63: Bella Chan | F63: Ayandeko Adeyemi | G63: 2 | I63: 63728 | K63: 1745.0164 | L63: 36.52 | M63: 7.27 | N63: 265.5004 | U63: 13
A64: JOB120371 | B64: COLL004279 | C64: 241031000020 | D64: 45633 | E64: MailMail速运-演员 | F64: 方 丽 娟 | G64: 21.5 | H64: 1570 | N64: 1570 | O64: 199734.12 | P64: 顶派=160594 广州通达=4895.6 | Q64: 165489.6 | S64: 162.75 | V64: 166262.35 | W64: 2133.11 | Z64: 2144.52 | AA64: 7.27 | AB64: 15590.66 | AC64: 181853.01 | AD64: 17881.11
C65: 241125000003 | D65: 45633 | E65: 喵喵速运-Layne | F65: A YU | G65: 0.26 | H65: 80 | N65: 80
C66: 241127000009 | D66: 45633 | E66: Isabel Zhu | F66: Maureen Kingsley | G66: 31 | I66: 540295.1 | K66: 1670 | L66: 323.53 | M66: 7.27 | N66: 2352.0631
C67: 241128000024 | D67: 45633 | E67: Bella Chan | F67: Mary Oyebade | G67: 70 | I67: 1217647.1 | K67: 1670 | L67: 729.13 | M67: 7.27 | N67: 5300.7751
C68: 241129000014 | D68: 45633 | E68: Bella Chan | F68: new hope 边鹏飞 | G68: 3.5 | I68: 74218.6 | K68: 1668.5836 | L68: 44.48 | M68: 7.27 | N68: 323.3696
C69: 241129000024 | D69: 45633 | E69: ying | F69: jiaqi huang | G69: 14.5 | H69: 1087.5 | N69: 1087.5
C70: 241129000034 | D70: 45633 | E70: ying | F70: Mark | G70: 2 | I70: 40490 | K70: 1673.1405 | L70: 24.2 | M70: 7.27 | N70: 175.934
C71: 241129000040 | D71: 45633 | E71: Bella Chan | F71: new hope 边鹏飞 | G71: 8 | I71: 144338.1 | K71: 1670 | L71: 86.43 | M71: 7.27 | N71: 628.3461
C72: 241129000044 | D72: 45633 | E72: KAY | F72: CHENFUDE | G72: 2 | H72: 171 | N72: 171
C73: 241129000046 | D73: 45633 | E73: ying | F73: Bubunmi | G73: 131 | H73: 10087 | N73: 10087
C74: 241130000002 | D74: 45633 | E74: Bella Chan | F74: zhang long ting | G74: 10 | H74: 776 | N74: 776
C75: 241130000003 | D75: 45633 | E75: Bella Chan | F75: li tao | G75: 6.5 | H75: 506.5 | N75: 506.5
C76: 241130000004 | D76: 45633 | E76: Isabel Zhu | F76: Grace Ordu | G76: 10.5 | I76: 187624.5 | K76: 1670 | L76: 112.35 | M76: 7.27 | N76: 816.7845
C77: 241130000005 | D77: 45633 | E77: Isabel Zhu | F77: Ope Olofinjana | G77: 0.51 | I77: 19255 | K77: 1669.9913 | L77: 11.53 | M77: 7.27 | N77: 83.8231
C78: 241130000018 | D78: 45633 | E78: Bella Chan | F78: li tao | G78: 4 | H78: 323 | N78: 323
C79: 241130000019 | D79: 45633 | E79: Bella Chan | F79: li tao | G79: 4 | H79: 323 | N79: 323
C80: 241130000020 | D80: 45633 | E80: Mailmail Abv sales person 1 | F80: Mr Olatunde | G80: 2.5 | I80: 47111 | K80: 1670.0106 | L80: 28.21 | M80: 7.27 | N80: 205.0867
C81: 241201000003 | D81: 45633 | E81: 喵喵速运-Layne | F81: Wang Jian | G81: 2 | H81: 246 | N81: 246 | X81: 11.41
C82: 241201000008 | D82: 45633 | E82: 喵喵速运-Layne | F82: William Xu | G82: 133 | I82: 2484440 | K82: 1697.5552 | L82: 1463.54 | M82: 7.27 | N82: 10639.936
C83: 241201000009 | D83: 45633 | E83: 喵喵速运-Layne | F83: William Xu | G83: 227.5 | I83: 4249700 | K83: 1697.551 | L83: 2503.43 | M83: 7.27 | N83: 18199.936
C84: 241201000010 | D84: 45633 | E84: 喵喵速运-Layne | F84: Ke Ren | G84: 0.57 | H84: 83 | N84: 83
C85: 241201000013 | D85: 45633 | E85: Bella Chan | F85: li tao | G85: 5.5 | H85: 443 | N85: 443
C86: 241201000014 | D86: 45633 | E86: KAY | F86: KELE | G86: 14.5 | I86: 280830 | K86: 1672.1048 | L86: 167.95 | M86: 7.27 | N86: 1220.9965
C87: 241201000015 | D87: 45633 | F87: javen | G87: 0.4 | I87: 19250 | K87: 1669.5577 | L87: 11.53 | M87: 7.27 | N87: 83.8231
C88: 241202000003 | D88: 45633 | E88: Isabel Zhu | F88: Wu Jiao Xing | G88: 14 | H88: 1084 | N88: 1084
C89: 241202000006 | D89: 45633 | E89: 喵喵速运-Layne | F89: LEO WEI | G89: 37 | I89: 643800 | K89: 1686.6649 | L89: 381.7 | M89: 7.27 | N89: 2774.959
C90: 241202000009 | D90: 45633 | E90: ying | F90: Bubunmi | G90: 73 | H90: 5475 | N90: 5475
C91: 241202000018 | D91: 45633 | E91: Bella Chan | F91: chidi | G91: 6 | I91: 108600 | L91: 65.03 | M91: 7.27 | N91: 472.7681
C92: 241202000022 | D92: 45633 | E92: ying | F92: zhangjingcheng | G92: 10 | H92: 776 | N92: 776
C93: 241202000027 | D93: 45633 | E93: Sam.Pao | F93: Olodeokuta Abiodun | G93: 203.5 | I93: 3652239.9 | K93: 1670 | L93: 2186.97 | M93: 7.27 | N93: 15899.272
C94: 241202000028 | D94: 45633 | E94: 喵喵速运-Layne | F94: FRANK | G94: 23.5 | I94: 468400 | K94: 1780.5824 | L94: 263.06 | M94: 7.27 | N94: 1912.4462 | U94: 150
C95: 241202000035 | D95: 45633 | E95: ying | F95: Landry | G95: 226.5 | H95: 20590 | N95: 20590 | T95: 350
C96: 241202000037 | D96: 45633 | E96: 喵喵速运-Layne | F96: jeason Cai | G96: 16 | H96: 1462.5 | N96: 1462.5
C97: 241202000038 | D97: 45633 | E97: ying | F97: wangyuanguo | G97: 4 | H97: 545 | N97: 545
C98: 241202000046 | D98: 45633 | E98: Shirley | F98: Mr. Chen | G98: 2.5 | H98: 203 | N98: 203
C99: 241202000047 | D99: 45633 | E99: 喵喵速运-Layne | F99: SF Jerry 顾 | G99: 154 | I99: 2603370 | K99: 1672.1068 | L99: 1556.94 | M99: 7.27 | N99: 11318.954
C100: 241202000048 | D100: 45633 | E100: dejare James | F100: James | G100: 5.5 | I100: 100482 | K100: 1631.9961 | L100: 61.57 | M100: 7.27 | N100: 447.6139
...

Sheet 应收统计表
A1: 2024年应收统计表(Statistical tables receivable)
A2: 月份 month | B2: 到付金额 Amount paid | C2: 目的港成本 Port of destination cost | D2: 应收到付款（USD） Payment due | E2: 汇率 exchange rate | F2: 应收到付款 Payment due (RMB) | G2: 实收（LOS）拉各斯金额 Collection(LOS) Lagos amount | H2: 减LOS/ABV办公室 日常支出费用 | I2: 欠款金额 Amount owed | J2: 备注 remarks
A3: 23年12月31止欠 | I3: 5029741.7
A4: 44929 | F4: 50000 | I4: =SUM(I3+F4-G4-H4) -> 5079741.7 | J4: 兴业银行支付：LOS代收客户运费由公司支付人民币张洋
A5: 44930 | F5: 40000 | I5: =SUM(I4+F5-G5-H5) -> 5119741.7 | J5: 微信支付：LOS代收客户运费由公司支付人民币（张长鑫）张洋
A6: 45307 | F6: 34012.46 | I6: =SUM(I5+F6-G6-H6) -> 5153754.2 | J6: 支付宝支付：LOS代收客户运费由公司支付人民币张建兴
A7: 45304 | G7: 141243 | I7: =SUM(I6+F7-G7-H7) -> 5012511.2 | J7: 广州银行LOS回款
A8: 45301 | G8: 67396 | I8: =SUM(I7+F8-G8-H8) -> 4945115.2 | J8: 广州银行LOS回款
A9: 45301 | G9: 76945 | I9: =SUM(I8+F9-G9-H9) -> 4868170.2 | J9: 广州银行LOS回款
A10: 44957 | B10: =SUM('1月份 '!L904) -> 95253.51 | C10: =SUM('1月份 '!Z904) -> 38612.6 | D10: =SUM(B10-C10) -> 56640.91 | E10: 7.17 | F10: =SUM(D10*E10) -> 406115.32 | H10: 19931.49 | I10: =SUM(I9+F10-G10-H10) -> 5254354
A11: 45351 | G11: 285714 | I11: =SUM(I10+F11-G11-H11) -> 4968640 | J11: 收到：LOS到付款129168+100000+56546=285714元 直接支付顶派
A12: 45329 | G12: 28000 | I12: =SUM(I11+F12-G12-H12) -> 4940640 | J12: 兴业银行收到LOS回款
A13: 45329 | G13: 94249 | I13: =SUM(I12+F13-G13-H13) -> 4846391 | J13: 兴业银行收到LOS回款
A14: 45330 | G14: 22725 | I14: =SUM(I13+F14-G14-H14) -> 4823666 | J14: 兴业银行收到LOS回款
A15: 45330 | G15: 42050 | I15: =SUM(I14+F15-G15-H15) -> 4781616 | J15: 兴业银行收到LOS回款
A16: 45330 | F16: 38235 | I16: =SUM(I15+F16-G16-H16) -> 4819851 | J16: 兴业银行支付：LOS代收客户运费由公司支付人民币张长鑫
A17: 45330 | F17: 43059 | I17: =SUM(I16+F17-G17-H17) -> 4862910 | J17: 兴业银行支付：LOS代收客户运费由公司支付人民币姚小红
A18: 45351 | B18: =SUM('2月份'!L569) -> 68020.04 | C18: =SUM('2月份'!Z569) -> 31804.95 | D18: =SUM(B18-C18) -> 36215.09 | E18: 7.19 | F18: =SUM(D18*E18) -> 260386.5 | H18: 50282.64 | I18: =SUM(I17+F18-G18-H18) -> 5073013.9
A19: 45362 | F19: 60000 | I19: =SUM(I18+F19-G19-H19) -> 5133013.9 | J19: 广州银行支付：LOS代收客户运费由公司支付人民币姚小红
A20: 45357 | F20: 60000 | I20: =SUM(I19+F20-G20-H20) -> 5193013.9 | J20: 广州银行支付：LOS代收客户运费由公司支付人民币郭强
A21: 45358 | F21: 30194 | I21: =SUM(I20+F21-G21-H21) -> 5223207.9 | J21: 广州银行支付：LOS代收客户运费由公司支付人民币郭强
A22: 45365 | G22: 318897 | I22: =SUM(I21+F22-G22-H22) -> 4904310.9 | J22: 收到：LOS到付款176530+100000+42367=318897元 直接支付顶派
A23: 45371 | G23: 327102 | I23: =SUM(I22+F23-G23-H23) -> 4577208.9 | J23: 收到：LOS到付款160000+167102=327102元 直接支付顶派
A24: 45382 | G24: 145848 | I24: =SUM(I23+F24-G24-H24) -> 4431360.9 | J24: 兴业银行收到LOS回款
A25: 45382 | B25: =SUM('3月份'!L887) -> 124721.07 | C25: =SUM('3月份'!Z887) -> 36063.01 | D25: =SUM(B25-C25) -> 88658.06 | E25: 7.19 | F25: =SUM(D25*E25) -> 637451.45 | H25: 26468.08 | I25: =SUM(I24+F25-G25-H25) -> 5042344.2
A26: 45384 | F26: 7103 | I26: =SUM(I25+F26-G26-H26) -> 5049447.2 | J26: 广州银行支付：LOS代收客户运费由公司支付人民币（佘斌哲 ）
A27: 45383 | G27: 139164 | I27: =SUM(I26+F27-G27-H27) -> 4910283.2 | J27: 兴业银行收到LOS回款
A28: 45412 | G28: 495700.9 | I28: =SUM(I27+F28-G28-H28) -> 4414582.3 | J28: 工行公账收到LOS回款
A29: 45412 | B29: =SUM('4月份'!L884) -> 66631.74 | C29: =SUM('4月份'!Z884) -> 64587.35 | D29: =SUM(B29-C29) -> 2044.3898 | E29: 7.23 | F29: =SUM(D29*E29) -> 14780.939 | H29: 19890.47 | I29: =SUM(I28+F29-G29-H29) -> 4409472.8
A30: 45443 | B30: =SUM('5月份'!L1159) -> 116634.87 | C30: =SUM('5月份'!Z1159) -> 40394.064 | D30: =SUM(B30-C30) -> 76240.806 | E30: 7.22 | F30: =SUM(D30*E30) -> 550458.62 | H30: 20042.357 | I30: =SUM(I29+F30-G30-H30) -> 4939889.1
A31: 45460 | G31: 97999 | I31: =SUM(I30+F31-G31-H31) -> 4841890.1 | J31: 兴业银行收到LOS回款
A32: 45461 | G32: 97087 | I32: =SUM(I31+F32-G32-H32) -> 4744803.1 | J32: 兴业银行收到LOS回款
A33: 45473 | B33: =SUM('6月份'!L787) -> 89630.309 | C33: =SUM('6月份'!Z787) -> 68155.89 | D33: =SUM(B33-C33) -> 21474.419 | E33: 7.24 | F33: =SUM(D33*E33) -> 155474.79 | H33: 149574.58 | I33: =SUM(I32+F33-G33-H33) -> 4750703.3
A34: 45473 | F34: -57273.709 | I34: =SUM(I33+F34-G34-H34) -> 4693429.6 | J34: 应收海运运费
A35: 45504 | B35: =SUM('7月份'!L1039) -> 129515.75 | C35: =SUM('7月份'!Z1039) -> 42377.12 | D35: =SUM(B35-C35) -> 87138.63 | E35: 7.26 | F35: =SUM(D35*E35) -> 632626.46 | H35: 21494.435 | I35: =SUM(I34+F35-G35-H35) -> 5304561.6
A36: 45504 | F36: -311312.9 | I36: =SUM(I35+F36-G36-H36) -> 4993248.7 | J36: 应收海运运费
A37: 45510 | F37: 1287.5 | I37: =SUM(I36+F37-G37-H37) -> 4994536.2 | J37: 微信支付：240715000003 LOS代收运费（由公司支付人民币）
A38: 45525 | G38: 111607 | I38: =SUM(I37+F38-G38-H38) -> 4882929.2 | J38: 企业支付宝收到LOS回款
A39: 45527 | G39: 106430 | I39: =SUM(I38+F39-G39-H39) -> 4776499.2 | J39: 企业支付宝收到LOS回款，24,000,000.00/225.5=106430元
A40: 45528 | G40: 106195 | I40: =SUM(I39+F40-G40-H40) -> 4670304.2 | J40: 企业支付宝收到LOS回款
A41: 45529 | G41: 88692 | I41: =SUM(I40+F41-G41-H41) -> 4581612.2 | J41: 企业支付宝收到LOS回款
A42: 45530 | G42: 88613 | I42: =SUM(I41+F42-G42-H42) -> 4492999.2 | J42: 企业支付宝收到LOS回款
A43: 45535 | B43: =SUM('8月份'!L1062) -> 144288.29 | C43: =SUM('8月份'!Z1062) -> 53053.48 | D43: =SUM(B43-C43) -> 91234.81 | E43: 7.15 | F43: =SUM(D43*E43) -> 652328.89 | H43: 44344.209 | I43: =SUM(I42+F43-G43-H43) -> 5100983.9
A44: 45535 | F44: -350287.82 | I44: =SUM(I43+F44-G44-H44) -> 4750696 | J44: 应收海运运费
A45: 45565 | B45: =SUM('9月份'!L1066) -> 80071.31 | C45: =SUM('9月份'!Z1066) -> 29919.16 | D45: =SUM(B45-C45) -> 50152.15 | E45: 7.08 | F45: =SUM(D45*E45) -> 355077.22 | H45: 20592.54 | I45: =SUM(I44+F45-G45-H45) -> 5085180.7
A46: 45565 | F46: -229617.7 | I46: =SUM(I45+F46-G46-H46) -> 4855563 | J46: 应收海运运费
A47: 45587 | G47: 103306 | I47: =SUM(I46+F47-G47-H47) -> 4752257 | J47: 企业支付宝收到LOS回款
A48: 45588 | G48: 103008 | I48: =SUM(I47+F48-G48-H48) -> 4649249 | J48: 企业支付宝收到LOS回款
A49: 45590 | G49: 102754 | I49: =SUM(I48+F49-G49-H49) -> 4546495 | J49: 企业支付宝收到LOS回款
A50: 45592 | G50: 65990 | I50: =SUM(I49+F50-G50-H50) -> 4480505 | J50: 企业支付宝收到LOS回款
A51: 45592 | G51: 16382 | I51: =SUM(I50+F51-G51-H51) -> 4464123 | J51: 企业支付宝收到LOS回款
A52: 45596 | B52: =SUM('10月份'!L1018) -> 73147.63 | C52: =SUM('10月份'!Z1018) -> 51943.11 | D52: =SUM(B52-C52) -> 21204.52 | E52: 7.11 | F52: =SUM(D52*E52) -> 150764.14 | H52: 330936.07 | I52: =SUM(I51+F52-G52-H52) -> 4283951.1
A53: 45596 | F53: -525107.72 | I53: =SUM(I52+F53-G53-H53) -> 3758843.4 | J53: 应收海运运费
A54: 45626 | B54: =SUM('11月份'!L1136) -> 134923.21 | C54: =SUM('11月份'!Z1136) -> 38496.8 | D54: =SUM(B54-C54) -> 96426.41 | E54: 7.2 | F54: =SUM(D54*E54) -> 694270.15 | H54: 44453.37 | I54: =SUM(I53+F54-G54-H54) -> 4408660.1
A55: 45626 | F55: 9384.516 | I55: =SUM(I54+F55-G55-H55) -> 4418044.7 | J55: 应收海运运费
A56: 45632 | G56: 40000 | I56: =SUM(I55+F56-G56-H56) -> 4378044.7 | J56: 企业支付宝收到LOS回款
A57: 45632 | G57: 50000 | I57: =SUM(I56+F57-G57-H57) -> 4328044.7 | J57: 企业支付宝收到LOS回款
A58: 45632 | G58: 10000 | I58: =SUM(I57+F58-G58-H58) -> 4318044.7 | J58: 企业支付宝收到LOS回款
A59: 45633 | G59: 9409 | I59: =SUM(I58+F59-G59-H59) -> 4308635.7 | J59: 企业支付宝收到LOS回款
A60: 45636 | G60: 109409 | I60: =SUM(I59+F60-G60-H60) -> 4199226.7 | J60: 企业支付宝收到LOS回款
A61: 45657 | B61: =SUM('12月份'!L1010) -> 90803.27 | C61: =SUM('12月份'!Z1010) -> 33129.98 | D61: =SUM(B61-C61) -> 57673.29 | E61: 7.27 | F61: =SUM(D61*E61) -> 419284.82 | H61: 114197 | I61: =SUM(I60+F61-G61-H61) -> 4504314.5
A62: 45657 | F62: -820140.81 | I62: =SUM(I61+F62-G62-H62) -> 3684173.7 | J62: 应收海运运费
A63: 合计 | F63: =SUM(F3:F62) -> 3008554.1 | G63: =SUM(G3:G61) -> 3491914.9 | H63: =SUM(H4:H61) -> 862207.24 | I63: =SUM(I3+F63-G63-H63) -> 3684173.7
H65: 18-19年12月止 总欠金额 | I65: 1622665.1 | J65: 1622665.1
H66: 20年12月止 总欠金额 | I66: 494224.59 | J66: 1672197.9
H67: 21年12月止 总欠金额 | I67: 1177973.3
H68: 22年12月止 总欠金额 | I68: 410432.31 | J68: 410432.31
H69: 23年1-12月份欠公司 | I69: 1324446.4 | J69: 1326710.3
H70: 24年1-12月份欠公司 | I70: =SUM(I63-I3) -> -1345568 | J70: =SUM(I70) -> -1345568

Sheet 24年1-12月份利润表
A1: 24年1-12月份LOS（空运单）利润分成表
A2: 月份 | B2: 应 收 | F2: 总应收 （CHN收款+LOS收款） | G2: 起运港 成本合计 | H2: 目的港 成本合计 | I2: 总成本 （起运港+目的港） | J2: 利润
B3: CHN收到（RMB） | C3: LOS收(USD) | D3: 汇率 | E3: 美元结算成（CNY）
A4: 1 | B4: =SUM('1月份 '!H904) -> 2331593.2 | C4: =SUM('1月份 '!L904) -> 95253.51 | D4: 7.17 | E4: =SUM(C4*D4) -> 682967.67 | F4: =SUM(B4+E4) -> 3014560.9 | G4: =SUM('1月份 '!V904) -> 2066487.3 | H4: =SUM('1月份 '!AB904) -> 276852.34 | I4: =SUM(G4+H4) -> 2343339.6 | J4: =SUM(F4-I4) -> 671221.23
A5: 2 | B5: =SUM('2月份'!H569) -> 1261300.8 | C5: =SUM('2月份'!L569) -> 68020.04 | D5: =SUM('2月份'!J576) -> 7.19 | E5: =SUM(C5*D5) -> 489064.09 | F5: =SUM(B5+E5) -> 1750364.9 | G5: =SUM('2月份'!V569) -> 1195884.9 | H5: =SUM('2月份'!AB569) -> 228677.59 | I5: =SUM(G5+H5) -> 1424562.5 | J5: =SUM(F5-I5) -> 325802.41
A6: 3 | B6: =SUM('3月份'!H887) -> 1683224.3 | C6: =SUM('3月份'!L887) -> 124721.07 | D6: 7.19 | E6: =SUM(C6*D6) -> 896744.49 | F6: =SUM(B6+E6) -> 2579968.8 | G6: =SUM('3月份'!V887) -> 1838539.7 | H6: =SUM('3月份'!AB887) -> 259293.04 | I6: =SUM(G6+H6) -> 2097832.8 | J6: =SUM(F6-I6) -> 482136.03
A7: 4 | B7: =SUM('4月份'!H884) -> 2269988.9 | C7: =SUM('4月份'!L884) -> 66631.74 | D7: 7.23 | E7: =SUM(C7*D7) -> 481747.48 | F7: =SUM(B7+E7) -> 2751736.4 | G7: =SUM('4月份'!V884) -> 1944434.2 | H7: =SUM('4月份'!AB884) -> 455115.96 | I7: =SUM(G7+H7) -> 2399550.1 | J7: =SUM(F7-I7) -> 352186.26
A8: 5 | B8: =SUM('5月份'!H1159) -> 2145083.3 | C8: =SUM('5月份'!L1159) -> 116634.87 | D8: 7.22 | E8: =SUM(C8*D8) -> 842103.76 | F8: =SUM(B8+E8) -> 2987187 | G8: =SUM('5月份'!V1159) -> 2250146.4 | H8: =SUM('5月份'!AB1159) -> 291645.14 | I8: =SUM(G8+H8) -> 2541791.6 | J8: =SUM(F8-I8) -> 445395.44
A9: 6 | B9: =SUM('6月份'!H787) -> 2018709.7 | C9: =SUM('6月份'!L787) -> 89630.309 | D9: 7.24 | E9: =SUM(C9*D9) -> 648923.44 | F9: =SUM(B9+E9) -> 2667633.1 | G9: =SUM('6月份'!V787) -> 1663349.7 | H9: =SUM('6月份'!AB787) -> 493167.97 | I9: =SUM(G9+H9) -> 2156517.6 | J9: =SUM(F9-I9) -> 511115.45
A10: 7 | B10: =SUM('7月份'!H1039) -> 2206588.7 | C10: =SUM('7月份'!L1039) -> 129515.75 | D10: 7.26 | E10: =SUM(C10*D10) -> 940284.35 | F10: =SUM(B10+E10) -> 3146873 | G10: =SUM('7月份'!V1039) -> 2356737.3 | H10: =SUM('7月份'!AB1039) -> 305030.06 | I10: =SUM(G10+H10) -> 2661767.3 | J10: =SUM(F10-I10) -> 485105.69
A11: 8 | B11: =SUM('8月份'!H1062) -> 2202365 | C11: =SUM('8月份'!L1062) -> 144288.29 | D11: 7.15 | E11: =SUM(C11*D11) -> 1031661.3 | F11: =SUM(B11+E11) -> 3234026.2 | G11: =SUM('8月份'!V1062) -> 2290831.2 | H11: =SUM('8月份'!AB1062) -> 379332.38 | I11: =SUM(G11+H11) -> 2670163.6 | J11: =SUM(F11-I11) -> 563862.65
A12: 9 | B12: =SUM('9月份'!H1066) -> 1623346.2 | C12: =SUM('9月份'!L1066) -> 80071.31 | D12: 7.08 | E12: =SUM(C12*D12) -> 566904.87 | F12: =SUM(B12+E12) -> 2190251.1 | G12: =SUM('9月份'!V1066) -> 1570035.6 | H12: =SUM('9月份'!AB1066) -> 211827.65 | I12: =SUM(G12+H12) -> 1781863.2 | J12: =SUM(F12-I12) -> 408387.81
A13: 10 | B13: =SUM('10月份'!H1018) -> 1801137.7 | C13: =SUM('10月份'!L1018) -> 73147.63 | D13: 7.11 | E13: =SUM(C13*D13) -> 520079.65 | F13: =SUM(B13+E13) -> 2321217.4 | G13: =SUM('10月份'!V1018) -> 1564974.9 | H13: =SUM('10月份'!AB1018) -> 369315.51 | I13: =SUM(G13+H13) -> 1934290.4 | J13: =SUM(F13-I13) -> 386926.94
A14: 11 | B14: =SUM('11月份'!H1136) -> 2393347.8 | C14: =SUM('11月份'!L1136) -> 134923.21 | D14: 7.2 | E14: =SUM(C14*D14) -> 971447.11 | F14: =SUM(B14+E14) -> 3364794.9 | G14: =SUM('11月份'!V1136) -> 2761550.9 | H14: =SUM('11月份'!AB1136) -> 250652.45 | I14: =SUM(G14+H14) -> 3012203.3 | J14: =SUM(F14-I14) -> 352591.52
A15: 12 | B15: =SUM('12月份'!H1010) -> 2098453.8 | C15: =SUM('12月份'!L1010) -> 90803.27 | D15: 7.27 | E15: =SUM(C15*D15) -> 660139.77 | F15: =SUM(B15+E15) -> 2758593.6 | G15: =SUM('12月份'!V1010) -> 1980639.6 | H15: =SUM('12月份'!AB1010) -> 240854.95 | I15: =SUM(G15+H15) -> 2221494.5 | J15: =SUM(F15-I15) -> 537099.08
A16: 合计 | B16: =SUM(B4:B15) -> 24035139 | C16: =SUM(C4:C15) -> 1213641 | E16: =SUM(E4:E15) -> 8732068 | F16: =SUM(F4:F15) -> 32767207 | G16: =SUM(G4:G15) -> 23483612 | H16: =SUM(H4:H15) -> 3761765.1 | I16: =SUM(I4:I15) -> 27245377 | J16: =SUM(J4:J15) -> 5521830.5
